Workbook

Sheet Demanda
F2: Estimación anual de la demanda
F4: Población
F5: Población total Arg | H5: 46000000
F6: % Celíacos | H6: 0.01
F7: Subpoblación celíacos | H7: =H5*H6 -> 460000
F9: Consumo teórico anual por persona (según INDEC)
F10: Producto | H10: Consumo
F11: Panificados | H11: =1.2*12 -> 14.4 | I11: kg
F12: Galletitas saladas | H12: 5.04 | I12: kg
F13: Galletitas dulces | H13: 2.52 | I13: kg
F14: Total | H14: =SUM(H11:H13) -> 21.96 | I14: kg
F16: Consumo anual subpoblación celíaca
F17: Producto | H17: Consumo | J17: Factor conviviente | K17: Consumo
F18: Panificados | H18: =H11*$H$7 -> 6624000 | I18: kg | J18: 1.5 | K18: =J18*H18 -> 9936000 | L18: kg | M18: kg
F19: Galletitas saladas | H19: =H12*$H$7 -> 2318400 | I19: kg | J19: 1.5 | K19: =J19*H19 -> 3477600 | L19: kg | M19: kg
F20: Galletitas dulces | H20: =H13*$H$7 -> 1159200 | I20: kg | J20: 1.5 | K20: =J20*H20 -> 1738800 | L20: kg | M20: kg
F21: Total | H21: =SUM(H18:H20) -> 10101600 | I21: kg | K21: =SUM(K18:K20) -> 15152400 | L21: kg | M21: kg
F24: Ventas SMAMS 2025 [kg] | H24: 1462828.9
F25: %Mkt share de SMAMS | H25: =H24/K21 -> 0.096541071
F27: Ventas anuales nuestro proyecto [kg] | H27: =Produccion!E22 -> 383550
F28: %Mkt share de nuestro proyecto | H28: =H27/K21 -> 0.025312822

Sheet Produccion
D2: Produccion | H2: Personal | J2: Producción por turno y eficiencia | O2: Escala de producción
D3: Producto | E3: Linea | F3: Turnos | G3: Horario | H3: RH/turno | I3: RH | J3: Cajas/turno | K3: Cajas/h | L3: kg/caja | M3: kg/turno | N3: kg/h | O3: kg/dia | P3: kg/año | Q3: Tn/año | R3: $/kg | S3: FC ($M)
D4: Pepas | E4: A | F4: 2 | G4: M, T | H4: 9 | I4: =F4*H4 -> 18 | J4: 900 | K4: =J4/8 -> 112.5 | L4: 2.7 | M4: =J4*L4 -> 2430 | N4: =M4/8 -> 303.75 | O4: =M4*F4 -> 4860 | P4: =O4*24*12 -> 1399680 | Q4: =P4/1000 -> 1399.68 | R4: 10000 | S4: =P4*R4/1000000 -> 13996.8
D5: Polvorones | E5: A | F5: 1 | G5: N | H5: 6 | I5: =F5*H5 -> 6 | J5: 500 | K5: =J5/8 -> 62.5 | L5: 2.7 | M5: =J5*L5 -> 1350 | N5: =M5/8 -> 168.75 | O5: =M5*F5 -> 1350 | P5: =O5*24*12 -> 388800 | Q5: =P5/1000 -> 388.8 | R5: 10000 | S5: =P5*R5/1000000 -> 3888
D6: Budines | E6: B | F6: 1 | G6: M, T | H6: 8 | I6: =F6*H6 -> 8 | J6: 350 | K6: =J6/8 -> 43.75 | L6: 3 | M6: =J6*L6 -> 1050 | N6: =M6/8 -> 131.25 | O6: =M6*F6 -> 1050 | P6: =O6*24*12 -> 302400 | Q6: =P6/1000 -> 302.4 | R6: 15000 | S6: =P6*R6/1000000 -> 4536
D7: Total | F7: =AVERAGE(F4:F6) -> 1.3333333 | H7: =SUM(H4:H6) -> 23 | I7: =SUM(I4:I6) -> 32 | J7: =SUM(J4:J6) -> 1750 | K7: =SUM(K4:K6) -> 218.75 | L7: =AVERAGE(L4:L6) -> 2.8 | M7: =SUM(M4:M6) -> 4830 | N7: =SUM(N4:N6) -> 603.75 | O7: =SUM(O4:O6) -> 7260 | P7: =SUM(P4:P6) -> 2090880 | Q7: =SUM(Q4:Q6) -> 2090.88 | R7: =SUM(R4:R6) -> 35000 | S7: =SUM(S4:S6) -> 22420.8
D9: Linea A
D10: Linea B | H10: =16+18 -> 34
B13: Linea | C13: COD | D13: Producto | E13: kg/año | F13: Tn/año | G13: $/kg | H13: FC [$MM] | I13: kg/mes | J13: kg/dia | K13: Turnos | L13: kg/h | N13: Ventas smams | P13: Factor
B14: A | C14: A001 | D14: Chocolate con chips picante | E14: =N14*$P$14 -> 48000 | F14: =E14/1000 -> 48 | G14: 13700 | H14: =E14*G14/1000000 -> 657.6 | I14: =E14/12 -> 4000 | J14: =I14/20 -> 200 | K14: 2 | L14: =J14/(8*K14) -> 12.5 | N14: 80000 | P14: 0.6
B15: A | C15: A002 | D15: Galletitas simil chocolinas | E15: =N15*$P$14 -> 27750 | F15: =E15/1000 -> 27.75 | G15: 10500 | H15: =E15*G15/1000000 -> 291.375 | I15: =E15/12 -> 2312.5 | J15: =I15/20 -> 115.625 | K15: 2 | L15: =J15/(8*K15) -> 7.2265625 | N15: 46250
B16: A | C16: A003 | D16: Pepas chocolate y batata | E16: =N16*$P$14 -> 78000 | F16: =E16/1000 -> 78 | G16: 11000 | H16: =E16*G16/1000000 -> 858 | I16: =E16/12 -> 6500 | J16: =I16/20 -> 325 | K16: 2 | L16: =J16/(8*K16) -> 20.3125 | N16: 130000
B17: A | C17: A004 | D17: Bizcochos sabor queso | E17: =N17*$P$14 -> 31200 | F17: =E17/1000 -> 31.2 | G17: 7000 | H17: =E17*G17/1000000 -> 218.4 | I17: =E17/12 -> 2600 | J17: =I17/20 -> 130 | K17: 2 | L17: =J17/(8*K17) -> 8.125 | N17: 52000
B18: A | C18: A005 | D18: Polvorones | E18: =N18*$P$14 -> 52800 | F18: =E18/1000 -> 52.8 | G18: 10500 | H18: =E18*G18/1000000 -> 554.4 | I18: =E18/12 -> 4400 | J18: =I18/20 -> 220 | K18: 2 | L18: =J18/(8*K18) -> 13.75 | N18: 88000
B19: B | C19: B001 | D19: Pan de molde | E19: =N19*$P$14 -> 75000 | F19: =E19/1000 -> 75 | G19: 12700 | H19: =E19*G19/1000000 -> 952.5 | I19: =E19/12 -> 6250 | J19: =I19/20 -> 312.5 | K19: 2 | L19: =J19/(8*K19) -> 19.53125 | N19: 125000
B20: B | C20: B002 | D20: Budines | E20: =N20*$P$14 -> 70800 | F20: =E20/1000 -> 70.8 | G20: 12000 | H20: =E20*G20/1000000 -> 849.6 | I20: =E20/12 -> 5900 | J20: =I20/20 -> 295 | K20: 2 | L20: =J20/(8*K20) -> 18.4375 | N20: 118000
B21: B | C21: B003 | D21: Budines saludables | E21: =N21*$P$14 -> 18000 | F21: =E21/1000 -> 18 | G21: 12000 | H21: =E21*G21/1000000 -> 216 | I21: =E21/12 -> 1500 | J21: =I21/20 -> 75 | K21: 2 | L21: =J21/(8*K21) -> 4.6875 | N21: 30000
B22: Total | D22: Total | E22: =SUM(E14:E20) -> 383550 | F22: =SUM(F14:F20) -> 383.55 | G22: =AVERAGE(G14:G20) -> 11057.143 | H22: =SUM(H14:H20) -> 4381.875 | I22: =AVERAGE(I14:I20) -> 4566.0714 | J22: =AVERAGE(J14:J20) -> 228.30357 | K22: =AVERAGE(K14:K20) -> 2 | L22: =AVERAGE(L14:L20) -> 14.268973
B25: LINEA A | D25: Capacidad esperada (kg/h) | E25: =SUM(L14:L18) -> 61.914062 | I25: =100000*1400 -> 140000000
D26: Capacidad real (kg/h) | E26: =100 -> 100 | F26: Revisar capacidad de horno tunel
D27: Aprovechamiento | E27: =E25/E26 -> 0.61914062
B29: LINEA B | D29: Capacidad esperada (kg/h) | E29: =SUM(L19:L21) -> 42.65625
D30: Capacidad real (kg/h) | E30: 50 | F30: Revisar capacidad de horno rotativo | M30: =164000/12 -> 13666.667
D31: Aprovechamiento | E31: =E29/E30 -> 0.853125
B33: El aprovechamiento debe estar entre 60/90%. Esto se mejora bajando la capacidad de la maquina o aumentando la producción, sin agregar máquinas
D38: Producto | E38: Precio ($/kg)
D39: Galletitas de chocolate con chips picante | E39: 13700
D40: Galletitas estilo “Chocolinas” | E40: 10500
D41: Pepas de chocolate y batata | E41: 11000
D42: Bizcochos sabor queso | E42: 7000
D43: Polvorones | E43: 10500
D44: Budines saborizados | E44: 12000
D45: Pan de molde | E45: 12700

Sheet Plan de ventas
E2: [ARS MM]
B3: Producto | C3: Cantidad [Tn] | D3: Precio [$/Tn] | E3: Año 1 | F3: Año 2 | G3: Año 3 | H3: Año 4 | I3: Año 5 | J3: Año 6 | K3: Año 7 | L3: Año 8 | M3: Año 9 | N3: Año 10
B4: Chocolate con chips picante | C4: =Produccion!F14 -> 48 | D4: =Produccion!G14/1000 -> 13.7 | E4: =D4*C4 -> 657.6 | F4: =E4 -> 657.6 | G4: =F4 -> 657.6 | H4: =G4 -> 657.6 | I4: =H4 -> 657.6 | J4: =I4 -> 657.6 | K4: =J4 -> 657.6 | L4: =K4 -> 657.6 | M4: =L4 -> 657.6 | N4: =M4 -> 657.6
B5: Galletitas simil chocolinas | C5: =Produccion!F15 -> 27.75 | D5: =Produccion!G15/1000 -> 10.5 | E5: =D5*C5 -> 291.375 | F5: =E5 -> 291.375 | G5: =F5 -> 291.375 | H5: =G5 -> 291.375 | I5: =H5 -> 291.375 | J5: =I5 -> 291.375 | K5: =J5 -> 291.375 | L5: =K5 -> 291.375 | M5: =L5 -> 291.375 | N5: =M5 -> 291.375
B6: Pepas chocolate y batata | C6: =Produccion!F16 -> 78 | D6: =Produccion!G16/1000 -> 11 | E6: =D6*C6 -> 858 | F6: =E6 -> 858 | G6: =F6 -> 858 | H6: =G6 -> 858 | I6: =H6 -> 858 | J6: =I6 -> 858 | K6: =J6 -> 858 | L6: =K6 -> 858 | M6: =L6 -> 858 | N6: =M6 -> 858
B7: Bizcochos salados | C7: =Produccion!F17 -> 31.2 | D7: =Produccion!G17/1000 -> 7 | E7: =D7*C7 -> 218.4 | F7: =E7 -> 218.4 | G7: =F7 -> 218.4 | H7: =G7 -> 218.4 | I7: =H7 -> 218.4 | J7: =I7 -> 218.4 | K7: =J7 -> 218.4 | L7: =K7 -> 218.4 | M7: =L7 -> 218.4 | N7: =M7 -> 218.4
B8: Polvorones | C8: =Produccion!F18 -> 52.8 | D8: =Produccion!G18/1000 -> 10.5 | E8: =D8*C8 -> 554.4 | F8: =E8 -> 554.4 | G8: =F8 -> 554.4 | H8: =G8 -> 554.4 | I8: =H8 -> 554.4 | J8: =I8 -> 554.4 | K8: =J8 -> 554.4 | L8: =K8 -> 554.4 | M8: =L8 -> 554.4 | N8: =M8 -> 554.4
B9: Pan de molde | C9: =Produccion!F19 -> 75 | D9: =Produccion!G19/1000 -> 12.7 | E9: =D9*C9 -> 952.5 | F9: =E9 -> 952.5 | G9: =F9 -> 952.5 | H9: =G9 -> 952.5 | I9: =H9 -> 952.5 | J9: =I9 -> 952.5 | K9: =J9 -> 952.5 | L9: =K9 -> 952.5 | M9: =L9 -> 952.5 | N9: =M9 -> 952.5
B10: Budines | C10: =Produccion!F20 -> 70.8 | D10: =Produccion!G20/1000 -> 12 | E10: =D10*C10 -> 849.6 | F10: =E10 -> 849.6 | G10: =F10 -> 849.6 | H10: =G10 -> 849.6 | I10: =H10 -> 849.6 | J10: =I10 -> 849.6 | K10: =J10 -> 849.6 | L10: =K10 -> 849.6 | M10: =L10 -> 849.6 | N10: =M10 -> 849.6
B11: TOTAL | C11: =SUM(C4:C10) -> 383.55 | D11: =SUM(D4:D10) -> 77.4 | E11: =SUM(E4:E10) -> 4381.875 | F11: =E11 -> 4381.875 | G11: =F11 -> 4381.875 | H11: =G11 -> 4381.875 | I11: =H11 -> 4381.875 | J11: =I11 -> 4381.875 | K11: =J11 -> 4381.875 | L11: =K11 -> 4381.875 | M11: =L11 -> 4381.875 | N11: =M11 -> 4381.875
E13: =E11/365*30 -> 360.15411

Sheet Inversiones
B2: Activo fijo | Q2: Planta | T2: Activo trabajo
B3: Concepto | C3: ARS [MM] | D3: % | G3: Categoría | H3: Equipo | I3: Cantidad | J3: Precio USD | K3: Precio $ | L3: Total $ | N3: TC | O3: 1360 | Q3: Area | R3: m2 | T3: Concepto | U3: ARS MM | V3: Plazo | W3: AT
B4: Nave industrial | C4: =900000*O3/1000000 -> 1224 | D4: =C4/$C$9 -> 0.68804941 | F4: Rodados y equipos aux | G4: Uso general | H4: Autoelevador | I4: 1 | J4: 15000 | L4: =IF(J4="",I4*K4,I4*J4*$O$3) -> 20400000 | Q4: Producción y oficinas | R4: 680 | T4: Compras MP | U4: =Costos!C5 -> 944.77342 | V4: 30 | W4: =U4/365*V4 -> 77.65261
B5: Obras complementarias | C5: =R7*0.7*R9/1000000 -> 186.2 | D5: =C5/$C$9 -> 0.10466895 | H5: Zorra | I5: 2 | K5: 450000 | L5: =IF(J5="",I5*K5,I5*J5*$O$3) -> 900000 | Q5: Deposito producto terminado | R5: 450 | T5: Ventas PT | U5: ='Plan de ventas'!E11 -> 4381.875 | V5: 45 | W5: =U5/365*V5 -> 540.23116
B6: Máquinas operativas | C6: =L35/1000000 -> 336.792 | D6: =C6/$C$9 -> 0.18932152 | H6: Balanza micro pesado | I6: 1 | K6: 200000 | L6: =IF(J6="",I6*K6,I6*J6*$O$3) -> 200000 | Q6: Deposito mp | R6: 200
B7: Rodados y equipos auxiliares | C7: =L8/1000000 -> 22.2 | D7: =C7/$C$9 -> 0.012479328 | H7: Balanza macro pesado | I7: 1 | K7: 700000 | L7: =IF(J7="",I7*K7,I7*J7*$O$3) -> 700000 | Q7: Total | R7: =SUM(R4:R6) -> 1330 | W7: Inversion AT
B8: Muebles y útiles | C8: =L18/1000000 -> 9.75 | D8: =C8/$C$9 -> 0.0054807858 | G8: Total | L8: =SUM(L4:L7) -> 22200000 | W8: =W5-W4 -> 462.57855
B9: Total | C9: =SUM(C4:C8) -> 1778.942 | D9: =SUM(D4:D8) -> 1 | Q9: Costo construcción m2 | R9: =200000 -> 200000
F10: Muebles y utiles | H10: Impresora Injket | I10: 1 | K10: 200000 | L10: =IF(J10="",I10*K10,I10*J10*$O$3) -> 200000
B11: Activo trabajo | H11: Computadoras | I11: 8 | K11: 500000 | L11: =IF(J11="",I11*K11,I11*J11*$O$3) -> 4000000
B12: Concepto | C12: ARS MM | H12: Sillas | I12: 15 | K12: 150000 | L12: =IF(J12="",I12*K12,I12*J12*$O$3) -> 2250000
B13: Compras MP | C13: =#REF! -> #REF! | H13: Mesas | I13: 3 | K13: 200000 | L13: =IF(J13="",I13*K13,I13*J13*$O$3) -> 600000
B14: Ventas PT | C14: =#REF! -> #REF! | H14: Sanitario (inodoro + lavamano) | I14: 6 | K14: 450000 | L14: =IF(J14="",I14*K14,I14*J14*$O$3) -> 2700000
G18: Total | L18: =SUM(L10:L17) -> 9750000
F20: Maquinas | G20: Línea de Galletitas | H20: Amasadora Industrial | I20: 1 | J20: 13500 | L20: =IF(J20="",I20*K20,I20*J20*$O$3) -> 18360000
H21: Rotativa con dulcera | I21: 1 | J21: 15000 | L21: =IF(J21="",I21*K21,I21*J21*$O$3) -> 20400000
H22: Moldes formadores | I22: 4 | J22: 5000 | L22: =IF(J22="",I22*K22,I22*J22*$O$3) -> 27200000
H23: Horno de Túnel (Continuo) | I23: 1 | J23: 100000 | L23: =IF(J23="",I23*K23,I23*J23*$O$3) -> 136000000
H24: Cinta de Enfriamiento | I24: 1 | J24: 12000 | L24: =IF(J24="",I24*K24,I24*J24*$O$3) -> 16320000
H25: Envasadora | I25: 1 | J25: 4000 | L25: =IF(J25="",I25*K25,I25*J25*$O$3) -> 5440000
G26: Línea de panificados | H26: Batidora Industrial | I26: 1 | K26: 2500000 | L26: =IF(J26="",I26*K26,I26*J26*$O$3) -> 2500000
H27: Dosificadora Volumétrica de Pistones | I27: 1 | K27: 2000000 | L27: =IF(J27="",I27*K27,I27*J27*$O$3) -> 2000000
H28: Carros para horno | I28: 4 | K28: 510000 | L28: =IF(J28="",I28*K28,I28*J28*$O$3) -> 2040000
H29: Horno Rotativo | I29: 2 | K29: 15000000 | L29: =IF(J29="",I29*K29,I29*J29*$O$3) -> 30000000
H30: Fermentadora de pan | I30: 1 | K30: 1900000 | L30: =IF(J30="",I30*K30,I30*J30*$O$3) -> 1900000
H31: Cortadora de pan | I31: 1 | J31: 500 | L31: =IF(J31="",I31*K31,I31*J31*$O$3) -> 680000
H32: Carros de enfriamiento | I32: 4 | K32: 400000 | L32: =IF(J32="",I32*K32,I32*J32*$O$3) -> 1600000
H33: Detector de metales | I33: 1 | J33: 3200 | L33: =IF(J33="",I33*K33,I33*J33*$O$3) -> 4352000
H34: Envasadora | I34: 1 | J34: 50000 | L34: =IF(J34="",I34*K34,I34*J34*$O$3) -> 68000000
G35: Total | L35: =SUM(L20:L34) -> 336792000

Sheet Costos
B2: Resumen costos anuales | F2: Mano de obra | M2: Materia prima
B3: Concepto | C3: ARS [MM] | D3: % | F3: Sector | G3: Posición | H3: Tipo | I3: Cantidad | J3: Sueldo basico [ARS] | K3: Total anual [ARS] | M3: COD | N3: Producto | O3: Costo MP / Kg ($) | P3: Q anual (kg) | Q3: Costo anual ($) | S3: $/kg | T3: Costo/precio
B4: Mano de obra | C4: =$K$14/1000000 -> 1356.5203 | D4: =C4/$C$7 -> 0.41262191 | F4: Producción | G4: Operario | H4: Directo | I4: 37 | J4: 1072000 | K4: =I4*J4*12*1.24 -> 590200320 | M4: A001 | N4: Chocolate con chips picante | O4: 1775.67 | P4: =VLOOKUP(M4,Produccion!$C$14:$E$20,3,0) -> 48000 | Q4: =O4*P4 -> 85232160 | S4: =VLOOKUP(M4,Produccion!$C$14:$G$20,5,0) -> 13700 | T4: =O4/S4 -> 0.12961095
B5: Materia prima | C5: =Q12/1000000 -> 944.77342 | D5: =C5/$C$7 -> 0.28737809 | F5: Calidad | G5: Analistas | H5: Indirecto | I5: 3 | J5: 2200000 | K5: =I5*J5*12*1.24 -> 98208000 | M5: A002 | N5: Galletitas simil chocolinas | O5: 1498.67 | P5: =VLOOKUP(M5,Produccion!$C$14:$E$20,3,0) -> 27750 | Q5: =O5*P5 -> 41588092 | S5: =VLOOKUP(M5,Produccion!$C$14:$G$20,5,0) -> 10500 | T5: =O5/S5 -> 0.14273048
B6: Otros costos | C6: =SUM(C4:C5)/0.7*0.3 -> 986.26875 | D6: =C6/$C$7 -> 0.3 | F6: Admin y Finanzas | G6: Analistas | H6: Indirecto | I6: 4 | J6: 2200000 | K6: =I6*J6*12*1.24 -> 130944000 | M6: A003 | N6: Pepas chocolate y batata | O6: 2404.98 | P6: =VLOOKUP(M6,Produccion!$C$14:$E$20,3,0) -> 78000 | Q6: =O6*P6 -> 187588440 | S6: =VLOOKUP(M6,Produccion!$C$14:$G$20,5,0) -> 11000 | T6: =O6/S6 -> 0.21863455
B7: Total | C7: =SUM(C4:C6) -> 3287.5625 | D7: =SUM(D4:D6) -> 1 | F7: Producción | G7: Supervisores | H7: Directo | I7: 2 | J7: 2000000 | K7: =I7*J7*12*1.24 -> 59520000 | M7: A004 | N7: Bizcochos salados | O7: 974.85 | P7: =VLOOKUP(M7,Produccion!$C$14:$E$20,3,0) -> 31200 | Q7: =O7*P7 -> 30415320 | S7: =VLOOKUP(M7,Produccion!$C$14:$G$20,5,0) -> 7000 | T7: =O7/S7 -> 0.13926429
F8: Producción | G8: Jefes | H8: Directo | I8: 4 | J8: 2500000 | K8: =I8*J8*12*1.24 -> 148800000 | M8: A005 | N8: Polvorones | O8: 1958.97 | P8: =VLOOKUP(M8,Produccion!$C$14:$E$20,3,0) -> 52800 | Q8: =O8*P8 -> 103433616 | S8: =VLOOKUP(M8,Produccion!$C$14:$G$20,5,0) -> 10500 | T8: =O8/S8 -> 0.18656857
F9: Admin y Finanzas | G9: Gerente | H9: Indirecto | I9: 1 | J9: 3400000 | K9: =I9*J9*12*1.24 -> 50592000 | M9: B001 | N9: Pan de molde | O9: 3034.2 | P9: =VLOOKUP(M9,Produccion!$C$14:$E$20,3,0) -> 75000 | Q9: =O9*P9 -> 227565000 | S9: =VLOOKUP(M9,Produccion!$C$14:$G$20,5,0) -> 12700 | T9: =O9/S9 -> 0.23891339
F10: Calidad | G10: Gerente | H10: Indirecto | I10: 1 | J10: 3400000 | K10: =I10*J10*12*1.24 -> 50592000 | M10: B002 | N10: Budines | O10: 3798.74 | P10: =VLOOKUP(M10,Produccion!$C$14:$E$20,3,0) -> 70800 | Q10: =O10*P10 -> 268950792 | S10: =VLOOKUP(M10,Produccion!$C$14:$G$20,5,0) -> 12000 | T10: =O10/S10 -> 0.31656167
F11: Producción | G11: Gerente | H11: Directo | I11: 1 | J11: 3400000 | K11: =I11*J11*12*1.24 -> 50592000 | M11: B003 | N11: Budines | O11: 3798.74 | P11: =VLOOKUP(M11,Produccion!C21,E1000,3,0) -> #N/A | Q11: =O11*P11 -> #N/A | S11: =VLOOKUP(M11,Produccion!$C$14:$G$20,5,0) -> #N/A | T11: =O11/S11 -> #N/A
F12: Ventas | G12: Gerente | H12: Indirecto | I12: 1 | J12: 3400000 | K12: =I12*J12*12*1.24 -> 50592000 | M12: Total | Q12: =SUM(Q4:Q10) -> 9.4477342e+08
F13: Gerencia | G13: CEO | H13: Indirecto | I13: 1 | J13: 8500000 | K13: =I13*J13*12*1.24 -> 126480000
F14: Total | I14: =SUM(I4:I13) -> 55 | J14: =SUM(J4:J13) -> 32072000 | K14: =SUM(K4:K13) -> 1356520320
F17: Apertura mano de obra
F18: Concepto | G18: ARS [MM] | H18: %
F19: Mano de obra directa | G19: =SUMIF(H4:H13,"Directo",J4:J13) -> 8972000 | H19: =G19/$G$21 -> 0.27974557
F20: Mano de obra indirecta | G20: =SUMIF(H4:H13,"Indirecto",J4:J13) -> 23100000 | H20: =G20/$G$21 -> 0.72025443
F21: Total | G21: =SUM(G19:G20) -> 32072000 | H21: =SUM(H19:H20) -> 1

Sheet Flujo
D1: =IF(E2="x","y","") | E1: =IF(F2="x","y","") | F1: =IF(G2="x","y","") -> y | G1: =IF(H2="x","y","") | H1: =IF(I2="x","y","") | I1: =IF(J2="x","y","") | J1: =IF(K2="x","y","") | K1: =IF(L2="x","y","") | ... M1: =IF(N2="x","y","")
B2: Flujo de fondos [ARS MM] | D2: =IF(AND(D10>0,C10<0),"x","") | E2: =IF(AND(E10>0,D10<0),"x","") | F2: =IF(AND(F10>0,E10<0),"x","") | G2: =IF(AND(G10>0,F10<0),"x","") -> x | H2: =IF(AND(H10>0,G10<0),"x","") | I2: =IF(AND(I10>0,H10<0),"x","") | J2: =IF(AND(J10>0,I10<0),"x","") | K2: =IF(AND(K10>0,J10<0),"x","") | ... M2: =IF(AND(M10>0,L10<0),"x","")
B3: Concepto/Año | C3: 0 | D3: 1 | E3: 2 | F3: 3 | G3: 4 | H3: 5 | I3: 6 | J3: 7 | K3: 8 | L3: 9 | M3: 10 | N3: Total
B4: Ingresos | C4: 0 | D4: =Produccion!$H$22 -> 4381.875 | E4: =Produccion!$H$22 -> 4381.875 | F4: =Produccion!$H$22 -> 4381.875 | G4: =Produccion!$H$22 -> 4381.875 | H4: =Produccion!$H$22 -> 4381.875 | I4: =Produccion!$H$22 -> 4381.875 | J4: =Produccion!$H$22 -> 4381.875 | K4: =Produccion!$H$22 -> 4381.875 | ... M4: =Produccion!$H$22 -> 4381.875 | N4: =SUM(C4:M4) -> 43818.75
B5: Egresos | C5: =Inversiones!C9 -> 1778.942 | D5: =Costos!$C$7+Inversiones!W8 -> 3750.141 | E5: =Costos!$C$7 -> 3287.5625 | F5: =Costos!$C$7 -> 3287.5625 | G5: =Costos!$C$7 -> 3287.5625 | H5: =Costos!$C$7 -> 3287.5625 | I5: =Costos!$C$7 -> 3287.5625 | J5: =Costos!$C$7 -> 3287.5625 | K5: =Costos!$C$7 -> 3287.5625 | L5: =Costos!$C$7 -> 3287.5625 | M5: =Costos!$C$7-Inversiones!W8 -> 2824.9839 | N5: =SUM(C5:M5) -> 34654.567
B6: Utilidad | C6: =C4-C5 -> -1778.942 | D6: =D4-D5 -> 631.73396 | E6: =E4-E5 -> 1094.3125 | F6: =F4-F5 -> 1094.3125 | G6: =G4-G5 -> 1094.3125 | H6: =H4-H5 -> 1094.3125 | I6: =I4-I5 -> 1094.3125 | J6: =J4-J5 -> 1094.3125 | ... M6: =M4-M5 -> 1556.8911 | N6: =SUM(C6:M6) -> 9164.1831
B7: Honorarios directorio (5%) | C7: 0 | D7: =D6*5% -> 31.586698 | E7: =E6*5% -> 54.715626 | F7: =F6*5% -> 54.715626 | G7: =G6*5% -> 54.715626 | H7: =H6*5% -> 54.715626 | I7: =I6*5% -> 54.715626 | J7: =J6*5% -> 54.715626 | K7: =K6*5% -> 54.715626 | ... M7: =M6*5% -> 77.844553 | N7: =SUM(C7:M7) -> 547.15626
B8: IIGG (35%) | C8: 0 | D8: =D6*35% -> 221.10689 | E8: =E6*35% -> 383.00938 | F8: =F6*35% -> 383.00938 | G8: =G6*35% -> 383.00938 | H8: =H6*35% -> 383.00938 | I8: =I6*35% -> 383.00938 | J8: =J6*35% -> 383.00938 | K8: =K6*35% -> 383.00938 | ... M8: =M6*35% -> 544.91187 | N8: =SUM(C8:M8) -> 3830.0938
B9: Saldo | C9: =C6-C7-C8 -> -1778.942 | D9: =D6-D7-D8 -> 379.04038 | E9: =E6-E7-E8 -> 656.58751 | F9: =F6-F7-F8 -> 656.58751 | G9: =G6-G7-G8 -> 656.58751 | H9: =H6-H7-H8 -> 656.58751 | I9: =I6-I7-I8 -> 656.58751 | J9: =J6-J7-J8 -> 656.58751 | ... M9: =M6-M7-M8 -> 934.13464 | N9: =SUM(C9:M9) -> 4786.9331
B10: Saldo Acumulado | C10: =C9 -> -1778.942 | D10: =C10+D9 -> -1399.9016 | E10: =D10+E9 -> -743.31412 | F10: =E10+F9 -> -86.726608 | G10: =F10+G9 -> 569.8609 | H10: =G10+H9 -> 1226.4484 | I10: =H10+I9 -> 1883.0359 | J10: =I10+J9 -> 2539.6234 | K10: =J10+K9 -> 3196.2109 | ... N10: =M10+N9 -> 9573.8662
B12: Beneficio neto [ARS MM] | C12: =N6-N7-N8 -> 4786.9331
B13: Recupero inversión | C13: =HLOOKUP("x",$D$2:$M$3,2,0) & " años y " & ROUNDUP(-(HLOOKUP("y",$D$1:$M$10,10,0))*365/HLOOKUP("x",$D$2:$M$9,8,0),0) & " días" -> 4 años y 49 días | G13: =HLOOKUP("x",$D$2:$M$3,2,0)+(-(HLOOKUP("y",$D$1:$M$10,10,0))*365/HLOOKUP("x",$D$2:$M$9,8,0))/365 -> 4.1320869
B14: TIR [%] | C14: =IRR(C9:M9) -> 0.31067648
B15: VAN [ARS MM] | C15: {=NPV(F15,C9:M9)} -> 1168.3294 | E15: wacc | F15: 0.15
