Workbook

Sheet Demanda
F2: Estimación anual de la demanda
F4: Población
F5: Población total Arg | H5: 46000000
F6: % Celíacos | H6: 0.01
F7: Subpoblación celíacos | H7: =H5*H6 -> 460000
F9: Consumo teórico anual por persona (según INDEC)
F10: Producto | H10: Consumo
F11: Panificados | H11: =1.2*12 -> 14.4 | I11: kg
F12: Galletitas saladas | H12: 5.04 | I12: kg
F13: Galletitas dulces | H13: 2.52 | I13: kg
F14: Total | H14: =SUM(H11:H13) -> 21.96 | I14: kg
F16: Consumo anual subpoblación celíaca
F17: Producto | H17: Consumo | J17: Factor conviviente | K17: Consumo
F18: Panificados | H18: =H11*$C$36 -> 6624000 | I18: kg | J18: 1.5 | K18: =J18*H18 -> 9936000 | L18: kg | M18: kg
F19: Galletitas saladas | H19: =H12*$C$36 -> 2318400 | I19: kg | J19: 1.5 | K19: =J19*H19 -> 3477600 | L19: kg | M19: kg
F20: Galletitas dulces | H20: =H13*$C$36 -> 1159200 | I20: kg | J20: 1.5 | K20: =J20*H20 -> 1738800 | L20: kg | M20: kg
F21: Total | H21: =SUM(H18:H20) -> 10101600 | I21: kg | K21: =SUM(K18:K20) -> 15152400 | L21: kg | M21: kg
F24: Ventas SMAMS 2025 [kg] | H24: 1462828.9
F25: %Mkt share de SMAMS | H25: =H24/K21 -> 0.096541071
F27: Ventas anuales nuestro proyecto [kg] | H27: =Produccion!E21 -> 383550
F28: %Mkt share de nuestro proyecto | H28: =H27/K21 -> 0.025312822
B31: Ventas
B33: Mercado base
B34: Poblacion Arg | C34: 46000000
B35: Celiacos | C35: 0.01
B36: Total | C36: =C34*C35 -> 460000
B38: Mercado extra
B39: Factor conviviente | C39: 1.5
B40: Factor saludable | C40: 1.4
B41: Total | C41: =C36*(C39+C40) -> 1334000
B43: Proyeccion
B44: Participación | C44: 0.07
B45: Mercado objetivo | C45: =C41*C44 -> 93380
B46: Consumo kg/p mensual | C46: 2
B47: Consumo kg/p anual | C47: =C46*12 -> 24
B48: Demanda anual (kg) | C48: =C47*C45 -> 2241120
B50: Produccion anual (kg) | C50: =Produccion!P7 -> 2090880

Sheet Produccion
D2: Produccion | H2: Personal | J2: Producción por turno y eficiencia | O2: Escala de producción
D3: Producto | E3: Linea | F3: Turnos | G3: Horario | H3: RH/turno | I3: RH | J3: Cajas/turno | K3: Cajas/h | L3: kg/caja | M3: kg/turno | N3: kg/h | O3: kg/dia | P3: kg/año | Q3: Tn/año | R3: $/kg | S3: FC ($M)
D4: Pepas | E4: A | F4: 2 | G4: M, T | H4: 9 | I4: =F4*H4 -> 18 | J4: 900 | K4: =J4/8 -> 112.5 | L4: 2.7 | M4: =J4*L4 -> 2430 | N4: =M4/8 -> 303.75 | O4: =M4*F4 -> 4860 | P4: =O4*24*12 -> 1399680 | Q4: =P4/1000 -> 1399.68 | R4: 10000 | S4: =P4*R4/1000000 -> 13996.8
D5: Polvorones | E5: A | F5: 1 | G5: N | H5: 6 | I5: =F5*H5 -> 6 | J5: 500 | K5: =J5/8 -> 62.5 | L5: 2.7 | M5: =J5*L5 -> 1350 | N5: =M5/8 -> 168.75 | O5: =M5*F5 -> 1350 | P5: =O5*24*12 -> 388800 | Q5: =P5/1000 -> 388.8 | R5: 10000 | S5: =P5*R5/1000000 -> 3888
D6: Budines | E6: B | F6: 1 | G6: M, T | H6: 8 | I6: =F6*H6 -> 8 | J6: 350 | K6: =J6/8 -> 43.75 | L6: 3 | M6: =J6*L6 -> 1050 | N6: =M6/8 -> 131.25 | O6: =M6*F6 -> 1050 | P6: =O6*24*12 -> 302400 | Q6: =P6/1000 -> 302.4 | R6: 15000 | S6: =P6*R6/1000000 -> 4536
D7: Total | F7: =AVERAGE(F4:F6) -> 1.3333333 | H7: =SUM(H4:H6) -> 23 | I7: =SUM(I4:I6) -> 32 | J7: =SUM(J4:J6) -> 1750 | K7: =SUM(K4:K6) -> 218.75 | L7: =AVERAGE(L4:L6) -> 2.8 | M7: =SUM(M4:M6) -> 4830 | N7: =SUM(N4:N6) -> 603.75 | O7: =SUM(O4:O6) -> 7260 | P7: =SUM(P4:P6) -> 2090880 | Q7: =SUM(Q4:Q6) -> 2090.88 | R7: =SUM(R4:R6) -> 35000 | S7: =SUM(S4:S6) -> 22420.8
D9: Linea A
D10: Linea B | H10: =16+18 -> 34
B13: Linea | C13: COD | D13: Producto | E13: kg/año | F13: Tn/año | G13: $/kg | H13: FC [$MM] | I13: kg/mes | J13: kg/dia | K13: Turnos | L13: kg/h | N13: Ventas smams | P13: Factor
B14: A | C14: A1 | D14: Chocolate con chips picante | E14: =N14*$P$14 -> 48000 | F14: =E14/1000 -> 48 | G14: 13700 | H14: =E14*G14/1000000 -> 657.6 | I14: =E14/12 -> 4000 | J14: =I14/20 -> 200 | K14: 2 | L14: =J14/(8*K14) -> 12.5 | N14: 80000 | P14: 0.6
B15: A | C15: A2 | D15: Galletitas simil chocolinas | E15: =N15*$P$14 -> 27750 | F15: =E15/1000 -> 27.75 | G15: 10500 | H15: =E15*G15/1000000 -> 291.375 | I15: =E15/12 -> 2312.5 | J15: =I15/20 -> 115.625 | K15: 2 | L15: =J15/(8*K15) -> 7.2265625 | N15: 46250
B16: A | C16: A3 | D16: Pepas chocolate y batata | E16: =N16*$P$14 -> 78000 | F16: =E16/1000 -> 78 | G16: 11000 | H16: =E16*G16/1000000 -> 858 | I16: =E16/12 -> 6500 | J16: =I16/20 -> 325 | K16: 2 | L16: =J16/(8*K16) -> 20.3125 | N16: 130000
B17: A | C17: A4 | D17: Bizcochos salados | E17: =N17*$P$14 -> 31200 | F17: =E17/1000 -> 31.2 | G17: 7000 | H17: =E17*G17/1000000 -> 218.4 | I17: =E17/12 -> 2600 | J17: =I17/20 -> 130 | K17: 2 | L17: =J17/(8*K17) -> 8.125 | N17: 52000
B18: A | C18: A5 | D18: Polvorones | E18: =N18*$P$14 -> 52800 | F18: =E18/1000 -> 52.8 | G18: 10500 | H18: =E18*G18/1000000 -> 554.4 | I18: =E18/12 -> 4400 | J18: =I18/20 -> 220 | K18: 2 | L18: =J18/(8*K18) -> 13.75 | N18: 88000
B19: B | C19: B1 | D19: Pan de molde | E19: =N19*$P$14 -> 75000 | F19: =E19/1000 -> 75 | G19: 12700 | H19: =E19*G19/1000000 -> 952.5 | I19: =E19/12 -> 6250 | J19: =I19/20 -> 312.5 | K19: 2 | L19: =J19/(8*K19) -> 19.53125 | N19: 125000
B20: B | C20: B2 | D20: Budines | E20: =N20*$P$14 -> 70800 | F20: =E20/1000 -> 70.8 | G20: 12000 | H20: =E20*G20/1000000 -> 849.6 | I20: =E20/12 -> 5900 | J20: =I20/20 -> 295 | K20: 2 | L20: =J20/(8*K20) -> 18.4375 | N20: 118000
B21: Total | D21: Total | E21: =SUM(E14:E20) -> 383550 | F21: =SUM(F14:F20) -> 383.55 | G21: =AVERAGE(G14:G20) -> 11057.143 | H21: =SUM(H14:H20) -> 4381.875 | I21: =AVERAGE(I14:I20) -> 4566.0714 | J21: =AVERAGE(J14:J20) -> 228.30357 | K21: =AVERAGE(K14:K20) -> 2 | L21: =AVERAGE(L14:L20) -> 14.268973
B24: LINEA A | D24: Capacidad esperada (kg/h) | E24: =SUM(L14:L18) -> 61.914062 | I24: =100000*1400 -> 140000000
D25: Capacidad real (kg/h) | E25: =100 -> 100 | F25: Revisar capacidad de horno tunel
D26: Aprovechamiento | E26: =E24/E25 -> 0.61914062
B28: LINEA B | D28: Capacidad esperada (kg/h) | E28: =SUM(L19:L20) -> 37.96875
D29: Capacidad real (kg/h) | E29: 50 | F29: Revisar capacidad de horno rotativo
D30: Aprovechamiento | E30: =E28/E29 -> 0.759375
B32: El aprovechamiento debe estar entre 60/90%. Esto se mejora bajando la capacidad de la maquina o aumentando la producción, sin agregar máquinas
D37: Producto | E37: Precio ($/kg)
D38: Galletitas de chocolate con chips picante | E38: 13700
D39: Galletitas estilo “Chocolinas” | E39: 10500
D40: Pepas de chocolate y batata | E40: 11000
D41: Bizcochos salados | E41: 7000
D42: Polvorones | E42: 10500
D43: Budines saborizados | E43: 12000
D44: Pan de molde | E44: 12700

Sheet Plan de ventas
E2: [ARS MM]
B3: Producto | C3: Cantidad [Tn] | D3: Precio [$/Tn] | E3: Año 1 | F3: Año 2 | G3: Año 3 | H3: Año 4 | I3: Año 5 | J3: Año 6 | K3: Año 7 | L3: Año 8 | M3: Año 9 | N3: Año 10
B4: Chocolate con chips picante | C4: =Produccion!F14 -> 48 | D4: =Produccion!G14/1000 -> 13.7 | E4: =D4*C4 -> 657.6 | F4: =E4 -> 657.6 | G4: =F4 -> 657.6 | H4: =G4 -> 657.6 | I4: =H4 -> 657.6 | J4: =I4 -> 657.6 | K4: =J4 -> 657.6 | L4: =K4 -> 657.6 | M4: =L4 -> 657.6 | N4: =M4 -> 657.6
B5: Galletitas simil chocolinas | C5: =Produccion!F15 -> 27.75 | D5: =Produccion!G15/1000 -> 10.5 | E5: =D5*C5 -> 291.375 | F5: =E5 -> 291.375 | G5: =F5 -> 291.375 | H5: =G5 -> 291.375 | I5: =H5 -> 291.375 | J5: =I5 -> 291.375 | K5: =J5 -> 291.375 | L5: =K5 -> 291.375 | M5: =L5 -> 291.375 | N5: =M5 -> 291.375
B6: Pepas chocolate y batata | C6: =Produccion!F16 -> 78 | D6: =Produccion!G16/1000 -> 11 | E6: =D6*C6 -> 858 | F6: =E6 -> 858 | G6: =F6 -> 858 | H6: =G6 -> 858 | I6: =H6 -> 858 | J6: =I6 -> 858 | K6: =J6 -> 858 | L6: =K6 -> 858 | M6: =L6 -> 858 | N6: =M6 -> 858
B7: Bizcochos salados | C7: =Produccion!F17 -> 31.2 | D7: =Produccion!G17/1000 -> 7 | E7: =D7*C7 -> 218.4 | F7: =E7 -> 218.4 | G7: =F7 -> 218.4 | H7: =G7 -> 218.4 | I7: =H7 -> 218.4 | J7: =I7 -> 218.4 | K7: =J7 -> 218.4 | L7: =K7 -> 218.4 | M7: =L7 -> 218.4 | N7: =M7 -> 218.4
B8: Polvorones | C8: =Produccion!F18 -> 52.8 | D8: =Produccion!G18/1000 -> 10.5 | E8: =D8*C8 -> 554.4 | F8: =E8 -> 554.4 | G8: =F8 -> 554.4 | H8: =G8 -> 554.4 | I8: =H8 -> 554.4 | J8: =I8 -> 554.4 | K8: =J8 -> 554.4 | L8: =K8 -> 554.4 | M8: =L8 -> 554.4 | N8: =M8 -> 554.4
B9: Pan de molde | C9: =Produccion!F19 -> 75 | D9: =Produccion!G19/1000 -> 12.7 | E9: =D9*C9 -> 952.5 | F9: =E9 -> 952.5 | G9: =F9 -> 952.5 | H9: =G9 -> 952.5 | I9: =H9 -> 952.5 | J9: =I9 -> 952.5 | K9: =J9 -> 952.5 | L9: =K9 -> 952.5 | M9: =L9 -> 952.5 | N9: =M9 -> 952.5
B10: Budines | C10: =Produccion!F20 -> 70.8 | D10: =Produccion!G20/1000 -> 12 | E10: =D10*C10 -> 849.6 | F10: =E10 -> 849.6 | G10: =F10 -> 849.6 | H10: =G10 -> 849.6 | I10: =H10 -> 849.6 | J10: =I10 -> 849.6 | K10: =J10 -> 849.6 | L10: =K10 -> 849.6 | M10: =L10 -> 849.6 | N10: =M10 -> 849.6
B11: TOTAL | C11: =SUM(C4:C10) -> 383.55 | D11: =SUM(D4:D10) -> 77.4 | E11: =SUM(E4:E10) -> 4381.875 | F11: =E11 -> 4381.875 | G11: =F11 -> 4381.875 | H11: =G11 -> 4381.875 | I11: =H11 -> 4381.875 | J11: =I11 -> 4381.875 | K11: =J11 -> 4381.875 | L11: =K11 -> 4381.875 | M11: =L11 -> 4381.875 | N11: =M11 -> 4381.875

Sheet Inversiones
B2: Activo fijo | Q2: Planta
B3: Concepto | C3: ARS [MM] | D3: % | G3: Categoría | H3: Equipo | I3: Cantidad | J3: Precio USD | K3: Precio $ | L3: Total $ | N3: TC | O3: 1400 | Q3: Area | R3: m2
B4: Nave industrial | C4: =1000000*O3/1000000 -> 1400 | D4: =C4/$C$9 -> 0.71273297 | F4: Rodados y equipos aux | G4: Uso general | H4: Autoelevador | I4: 1 | J4: 15000 | L4: =IF(J4="",I4*K4,I4*J4*$O$3) -> 21000000 | Q4: Producción y oficinas | R4: 680
B5: Obras complementarias | C5: =R7*0.7*R9/1000000 -> 186.2 | D5: =C5/$C$9 -> 0.094793486 | H5: Zorra | I5: 2 | K5: 450000 | L5: =IF(J5="",I5*K5,I5*J5*$O$3) -> 900000 | Q5: Deposito producto terminado | R5: 450
B6: Máquinas operativas | C6: =L35/1000000 -> 345.52 | D6: =C6/$C$9 -> 0.1759025 | H6: Balanza micro pesado | I6: 1 | K6: 200000 | L6: =IF(J6="",I6*K6,I6*J6*$O$3) -> 200000 | Q6: Deposito mp | R6: 200
B7: Rodados y equipos auxiliares | C7: =L8/1000000 -> 22.8 | D7: =C7/$C$9 -> 0.011607366 | H7: Balanza macro pesado | I7: 1 | K7: 700000 | L7: =IF(J7="",I7*K7,I7*J7*$O$3) -> 700000 | Q7: Total | R7: =SUM(R4:R6) -> 1330
B8: Muebles y útiles | C8: =L18/1000000 -> 9.75 | D8: =C8/$C$9 -> 0.0049636761 | G8: Total | L8: =SUM(L4:L7) -> 22800000
B9: Total | C9: =SUM(C4:C8) -> 1964.27 | D9: =SUM(D4:D8) -> 1 | Q9: Costo construcción m2 | R9: =200000 -> 200000
F10: Muebles y utiles | H10: Impresora Injket | I10: 1 | K10: 200000 | L10: =IF(J10="",I10*K10,I10*J10*$O$3) -> 200000
H11: Computadoras | I11: 8 | K11: 500000 | L11: =IF(J11="",I11*K11,I11*J11*$O$3) -> 4000000
H12: Sillas | I12: 15 | K12: 150000 | L12: =IF(J12="",I12*K12,I12*J12*$O$3) -> 2250000
H13: Mesas | I13: 3 | K13: 200000 | L13: =IF(J13="",I13*K13,I13*J13*$O$3) -> 600000
H14: Sanitario (inodoro + lavamano) | I14: 6 | K14: 450000 | L14: =IF(J14="",I14*K14,I14*J14*$O$3) -> 2700000
G18: Total | L18: =SUM(L10:L17) -> 9750000
F20: Maquinas | G20: Línea de Galletitas | H20: Amasadora Industrial | I20: 1 | J20: 13500 | L20: =IF(J20="",I20*K20,I20*J20*$O$3) -> 18900000
H21: Rotativa con dulcera | I21: 1 | J21: 15000 | L21: =IF(J21="",I21*K21,I21*J21*$O$3) -> 21000000
H22: Moldes formadores | I22: 4 | J22: 5000 | L22: =IF(J22="",I22*K22,I22*J22*$O$3) -> 28000000
H23: Horno de Túnel (Continuo) | I23: 1 | J23: 100000 | L23: =IF(J23="",I23*K23,I23*J23*$O$3) -> 140000000
H24: Cinta de Enfriamiento | I24: 1 | J24: 12000 | L24: =IF(J24="",I24*K24,I24*J24*$O$3) -> 16800000
H25: Envasadora | I25: 1 | J25: 4000 | L25: =IF(J25="",I25*K25,I25*J25*$O$3) -> 5600000
G26: Línea de panificados | H26: Batidora Industrial | I26: 1 | K26: 2500000 | L26: =IF(J26="",I26*K26,I26*J26*$O$3) -> 2500000
H27: Dosificadora Volumétrica de Pistones | I27: 1 | K27: 2000000 | L27: =IF(J27="",I27*K27,I27*J27*$O$3) -> 2000000
H28: Carros para horno | I28: 4 | K28: 510000 | L28: =IF(J28="",I28*K28,I28*J28*$O$3) -> 2040000
H29: Horno Rotativo | I29: 2 | K29: 15000000 | L29: =IF(J29="",I29*K29,I29*J29*$O$3) -> 30000000
H30: Fermentadora de pan | I30: 1 | K30: 1900000 | L30: =IF(J30="",I30*K30,I30*J30*$O$3) -> 1900000
H31: Cortadora de pan | I31: 1 | J31: 500 | L31: =IF(J31="",I31*K31,I31*J31*$O$3) -> 700000
H32: Carros de enfriamiento | I32: 4 | K32: 400000 | L32: =IF(J32="",I32*K32,I32*J32*$O$3) -> 1600000
H33: Detector de metales | I33: 1 | J33: 3200 | L33: =IF(J33="",I33*K33,I33*J33*$O$3) -> 4480000
H34: Envasadora | I34: 1 | J34: 50000 | L34: =IF(J34="",I34*K34,I34*J34*$O$3) -> 70000000
G35: Total | L35: =SUM(L20:L34) -> 345520000

Sheet Costos
B2: Resumen costos anuales | F2: Mano de obra | L2: Materia prima
B3: Concepto | C3: ARS [MM] | D3: % | F3: Sector | G3: Posición | H3: Cantidad | I3: Sueldo basico [ARS] | J3: Total anual [ARS] | L3: COD | M3: Producto | N3: Costo MP / Kg ($) | O3: Q anual (kg) | P3: Costo anual ($) | R3: $/kg | S3: Costo/precio
B4: Mano de obra | C4: =$J$9/1000000 -> 1197.471 | D4: =C4/$C$7 -> 0.39128574 | F4: Producción | G4: Operario | H4: 32 | I4: 1072000 | J4: =H4*I4*12*1.24 -> 510443520 | L4: A1 | M4: Chocolate con chips picante | N4: 1775.67 | O4: =VLOOKUP(L4,Produccion!$C$14:$E$20,3,0) -> 48000 | P4: =N4*O4 -> 85232160 | R4: =VLOOKUP(L4,Produccion!$C$14:$G$20,5,0) -> 13700 | S4: =N4/R4 -> 0.12961095
B5: Materia prima | C5: =P11/1000000 -> 944.77342 | D5: =C5/$C$7 -> 0.30871426 | F5: Mantenimiento / Logística | G5: Empleado | H5: 6 | I5: 1395200 | J5: =H5*I5*12*1.24 -> 124563456 | L5: A2 | M5: Galletitas simil chocolinas | N5: 1498.67 | O5: =VLOOKUP(L5,Produccion!$C$14:$E$20,3,0) -> 27750 | P5: =N5*O5 -> 41588092 | R5: =VLOOKUP(L5,Produccion!$C$14:$G$20,5,0) -> 10500 | S5: =N5/R5 -> 0.14273048
B6: Otros costos | C6: =SUM(C4:C5)/0.7*0.3 -> 918.10474 | D6: =C6/$C$7 -> 0.3 | F6: Staff producción | G6: Empleado | H6: 6 | I6: 2500000 | J6: =H6*I6*12*1.24 -> 223200000 | L6: A3 | M6: Pepas chocolate y batata | N6: 2404.98 | O6: =VLOOKUP(L6,Produccion!$C$14:$E$20,3,0) -> 78000 | P6: =N6*O6 -> 187588440 | R6: =VLOOKUP(L6,Produccion!$C$14:$G$20,5,0) -> 11000 | S6: =N6/R6 -> 0.21863455
B7: Total | C7: =SUM(C4:C6) -> 3060.3491 | D7: =SUM(D4:D6) -> 1 | F7: Administrativos | G7: Empleado | H7: 4 | I7: 2200000 | J7: =H7*I7*12*1.24 -> 130944000 | L7: A4 | M7: Bizcochos salados | N7: 974.85 | O7: =VLOOKUP(L7,Produccion!$C$14:$E$20,3,0) -> 31200 | P7: =N7*O7 -> 30415320 | R7: =VLOOKUP(L7,Produccion!$C$14:$G$20,5,0) -> 7000 | S7: =N7/R7 -> 0.13926429
F8: Gerencia de Planta / Admin | G8: Gerente | H8: 2 | I8: 7000000 | J8: =H8*I8*12*1.24 -> 208320000 | L8: A5 | M8: Polvorones | N8: 1958.97 | O8: =VLOOKUP(L8,Produccion!$C$14:$E$20,3,0) -> 52800 | P8: =N8*O8 -> 103433616 | R8: =VLOOKUP(L8,Produccion!$C$14:$G$20,5,0) -> 10500 | S8: =N8/R8 -> 0.18656857
F9: Total | H9: =SUM(H4:H8) -> 50 | I9: =SUM(I4:I8) -> 14167200 | J9: =SUM(J4:J8) -> 1197470976 | L9: B1 | M9: Pan de molde | N9: 3034.2 | O9: =VLOOKUP(L9,Produccion!$C$14:$E$20,3,0) -> 75000 | P9: =N9*O9 -> 227565000 | R9: =VLOOKUP(L9,Produccion!$C$14:$G$20,5,0) -> 12700 | S9: =N9/R9 -> 0.23891339
L10: B2 | M10: Budines | N10: 3798.74 | O10: =VLOOKUP(L10,Produccion!$C$14:$E$20,3,0) -> 70800 | P10: =N10*O10 -> 268950792 | R10: =VLOOKUP(L10,Produccion!$C$14:$G$20,5,0) -> 12000 | S10: =N10/R10 -> 0.31656167
L11: Total | P11: =SUM(P4:P10) -> 9.4477342e+08

Sheet Flujo
D1: =IF(E2="x","y","") | E1: =IF(F2="x","y","") -> y | F1: =IF(G2="x","y","") | G1: =IF(H2="x","y","") | H1: =IF(I2="x","y","") | I1: =IF(J2="x","y","") | J1: =IF(K2="x","y","") | K1: =IF(L2="x","y","") | ... M1: =IF(N2="x","y","")
B2: Flujo de fondos [ARS MM] | D2: =IF(AND(D10>0,C10<0),"x","") | E2: =IF(AND(E10>0,D10<0),"x","") | F2: =IF(AND(F10>0,E10<0),"x","") -> x | G2: =IF(AND(G10>0,F10<0),"x","") | H2: =IF(AND(H10>0,G10<0),"x","") | I2: =IF(AND(I10>0,H10<0),"x","") | J2: =IF(AND(J10>0,I10<0),"x","") | K2: =IF(AND(K10>0,J10<0),"x","") | ... M2: =IF(AND(M10>0,L10<0),"x","")
B3: Concepto/Año | C3: 0 | D3: 1 | E3: 2 | F3: 3 | G3: 4 | H3: 5 | I3: 6 | J3: 7 | K3: 8 | L3: 9 | M3: 10 | N3: Total
B4: Ingresos | C4: 0 | D4: =Produccion!$H$21 -> 4381.875 | E4: =Produccion!$H$21 -> 4381.875 | F4: =Produccion!$H$21 -> 4381.875 | G4: =Produccion!$H$21 -> 4381.875 | H4: =Produccion!$H$21 -> 4381.875 | I4: =Produccion!$H$21 -> 4381.875 | J4: =Produccion!$H$21 -> 4381.875 | K4: =Produccion!$H$21 -> 4381.875 | ... M4: =Produccion!$H$21 -> 4381.875 | N4: =SUM(C4:M4) -> 43818.75
B5: Egresos | C5: =Inversiones!C9 -> 1964.27 | D5: =Costos!$C$7 -> 3060.3491 | E5: =Costos!$C$7 -> 3060.3491 | F5: =Costos!$C$7 -> 3060.3491 | G5: =Costos!$C$7 -> 3060.3491 | H5: =Costos!$C$7 -> 3060.3491 | I5: =Costos!$C$7 -> 3060.3491 | J5: =Costos!$C$7 -> 3060.3491 | K5: =Costos!$C$7 -> 3060.3491 | ... M5: =Costos!$C$7 -> 3060.3491 | N5: =SUM(C5:M5) -> 32567.761
B6: Utilidad | C6: =C4-C5 -> -1964.27 | D6: =D4-D5 -> 1321.5259 | E6: =E4-E5 -> 1321.5259 | F6: =F4-F5 -> 1321.5259 | G6: =G4-G5 -> 1321.5259 | H6: =H4-H5 -> 1321.5259 | I6: =I4-I5 -> 1321.5259 | J6: =J4-J5 -> 1321.5259 | ... M6: =M4-M5 -> 1321.5259 | N6: =SUM(C6:M6) -> 11250.989
B7: Honorarios directorio (5%) | C7: 0 | D7: =D6*5% -> 66.076293 | E7: =E6*5% -> 66.076293 | F7: =F6*5% -> 66.076293 | G7: =G6*5% -> 66.076293 | H7: =H6*5% -> 66.076293 | I7: =I6*5% -> 66.076293 | J7: =J6*5% -> 66.076293 | K7: =K6*5% -> 66.076293 | ... M7: =M6*5% -> 66.076293 | N7: =SUM(C7:M7) -> 660.76293
B8: IIGG (35%) | C8: 0 | D8: =D6*35% -> 462.53405 | E8: =E6*35% -> 462.53405 | F8: =F6*35% -> 462.53405 | G8: =G6*35% -> 462.53405 | H8: =H6*35% -> 462.53405 | I8: =I6*35% -> 462.53405 | J8: =J6*35% -> 462.53405 | K8: =K6*35% -> 462.53405 | ... M8: =M6*35% -> 462.53405 | N8: =SUM(C8:M8) -> 4625.3405
B9: Saldo | C9: =C6-C7-C8 -> -1964.27 | D9: =D6-D7-D8 -> 792.91552 | E9: =E6-E7-E8 -> 792.91552 | F9: =F6-F7-F8 -> 792.91552 | G9: =G6-G7-G8 -> 792.91552 | H9: =H6-H7-H8 -> 792.91552 | I9: =I6-I7-I8 -> 792.91552 | J9: =J6-J7-J8 -> 792.91552 | ... M9: =M6-M7-M8 -> 792.91552 | N9: =SUM(C9:M9) -> 5964.8852
B10: Saldo Acumulado | C10: =C9 -> -1964.27 | D10: =C10+D9 -> -1171.3545 | E10: =D10+E9 -> -378.43897 | F10: =E10+F9 -> 414.47655 | G10: =F10+G9 -> 1207.3921 | H10: =G10+H9 -> 2000.3076 | I10: =H10+I9 -> 2793.2231 | J10: =I10+J9 -> 3586.1386 | K10: =J10+K9 -> 4379.0541 | ... N10: =M10+N9 -> 11929.77
B12: Beneficio neto [ARS MM] | C12: =N6-N7-N8 -> 5964.8852
B13: Recupero inversión | C13: =HLOOKUP("x",$D$2:$M$3,2,0) & " años y " & ROUNDUP(-(HLOOKUP("y",$D$1:$M$10,10,0))*365/HLOOKUP("x",$D$2:$M$9,8,0),0) & " días" -> 3 años y 175 días | G13: =HLOOKUP("x",$D$2:$M$3,2,0)+(-(HLOOKUP("y",$D$1:$M$10,10,0))*365/HLOOKUP("x",$D$2:$M$9,8,0))/365 -> 3.4772753
B14: TIR [%] | C14: =IRR(C9:M9) -> 0.38851564
B15: VAN [ARS MM] | C15: {=NPV(F15,C9:M9)} -> 1752.3387 | E15: wacc | F15: 0.15
