Workbook

Sheet DATOS Iniciales y ACLARACIONES
A1: ESTA SOLAPA NO DEBE IMPRIMIRSE
A2: Como Referencia, se usa la siguiente configuración de Referencia:
B4: Las casillas en Amarillo son para Completar datos Numéricos
B5: Las casillas Grises son de Fórmulas.Si bien en reglas generales están correctas, puede llegar a ser modificadas
B6: Las casillas en Verde son Datos Cualitativos. | O6: =1.04^10-1 -> 0.48024428
B7: Las celdas cruzadas no deben completarse | Q7: Base | R7: 0.0527
B8: Los Rubros de Activos Fijos y Costos son generales y DEBEN ser modificados de manera de reflejar los del proyecto Propio | Q8: Crecimiento | R8: 0.005
B9: Demostrar los datos de Inversiones y Costos | Q9: Años | R9: 5
A11: Datos de Referencias: Se agregan los más comunes, se recomienda agregar más para usarlos con referencias | R11: =R7+R8*R9 -> 0.0777
A14: Fecha del Proyecto | B14: 46154
A15: IVA Gastos | B15: 0.21 | C15: General
B16: 0.105 | C16: Tasa Reducida (Maquinas y Alimentos)
B17: 0.27 | C17: Servicios
A18: IVA Ventas | B18: 0.21 | C18: Si se brindan algunos productos o servicios con tasas diferenciales, colocar el promedio ponderado o hacer tabla auxiliar
A19: Imp. A las Ganancias*1 | B19: 0.35 | C19: Tasa General
A20: Hon.al Directorio*2*3 | B20: 0.05 | C20: VARIABLE | D20: ajusto Mateo
A21: Tipos de Cambios | B21: 1400 | C21: $ por USD
C22: $ por Euro
A24: % Imprevistos | B24: 0.05 | C24: Sobre Inversiones
B25: 0.03 | C25: Sobre Costos
A27: Alicuota de Prorrateo de Gastos Indirectos
B28: Principal | C28: Alt1 | D28: Alt2
A29: Area de Producción | B29: 0.4 | C29: 0.95 | D29: 0.95
A30: Area Administrativa | B30: 0.4 | C30: 0.03 | D30: 0.03
A31: Area Comercial | B31: =IF((1-B30-B29)>0,(1-B30-B29), "ERROR") -> 0.2 | C31: =IF((1-C30-C29)>0,(1-C30-C29), "ERROR") -> 0.02 | D31: =IF((1-D30-D29)>0,(1-D30-D29), "ERROR") -> 0.02
A33: *1 En Argentina existen distintas escalas para Pequeñas y Medianas Empresas. Verificar estas escalas al momento de llenar esta información
A34: *2 Solo aplicable a Sociedades Anónimas. En caso de ser SRL o SAS, colocar valor 0 (Cero)
A35: *3 Colocar FIJO o VARIABLE en la Segunda Casilla. En el primer caso poner el valor Anual si es fijo, o el Porcentaje si es Variable
A37: Información de Dimensionamiento Físico
A39: Bienes de Cambio | C39: Año 0 | D39: Año 1 | E39: Año 2 | F39: Año 3 | G39: Año 4 | H39: Año 5 | I39: Año 6 | J39: Año 7 | K39: Año 8 | L39: Año 9 | M39: Año 10
A40: Stock MP | B40: Ueq PT al fin Ej.
A41: Stock MCySE | B41: Ueq PT al fin Ej.
A42: Stock PT | B42: Ueq PT al fin Ej.
A43: Créditos por Ventas | B43: días Prom Pond | D43: 180 | E43: 120 | F43: 90 | G43: 80 | H43: 70 | I43: 60 | J43: 50 | K43: 50 | L43: 100 | M43: 180
A44: Unidades Producción | B44: Totales Ueq | D44: 4139 | E44: 4730 | F44: 4926 | G44: 5136 | H44: 5381 | I44: 5635 | J44: 5905 | K44: 6184 | L44: 6475 | M44: 6780
A45: Ventas | B45: Totales Ueq | D45: 4139 | E45: 4730 | F45: 4926 | G45: 5136 | H45: 5381 | I45: 5635 | J45: 5905 | K45: 6184 | L45: 6475 | M45: 6780
A47: Min. en Caja y Bancos | B47: 0.02 | C47: Ventas Año 1
A55: COMO MODELIZAR
A56: VER COMO AFECTA EL IIGG en el CASHFLOW, VER SI HACER UN CUADRO DIFERENCIADO TIPO EL IVA

Sheet Inv AF
A2: Inversión en Activo Fijo | B2: Plazo Amort. | C2: IVA | D2: Año 0 | E2: Año 1 | F2: Año 2 | G2: Año 3 | H2: Año 4 | I2: Año 5 | J2: Año 6 | K2: Año 7 | L2: Año 8 | M2: Año 9 | N2: Año 10
A3: a) Bienes de Uso
A4: Terreno y Mejoras | B4: 0 | C4: 0 | D4: 1224000000
A5: Edificios y Obras Complementarias | B5: 30 | C5: ='DATOS Iniciales y ACLARACIONES'!B15 -> 0.21 | D5: 186000000
A6: Infraestructura en predio propio | B6: 30 | C6: ='DATOS Iniciales y ACLARACIONES'!B15 -> 0.21
A7: Instalaciones industriales | B7: 10 | C7: ='DATOS Iniciales y ACLARACIONES'!B16 -> 0.105
A8: Máquinas operativas Importadas | B8: 10 | C8: ='DATOS Iniciales y ACLARACIONES'!B16 -> 0.105 | D8: 337000000
A9: Gastos Conexos de Importación | B9: 10 | C9: ='DATOS Iniciales y ACLARACIONES'!B16 -> 0.105
A10: Maquinas Operativas Nacionales | B10: 10 | C10: ='DATOS Iniciales y ACLARACIONES'!B16 -> 0.105
A11: Transporte y montaje de la maquinaria: | B11: 10 | C11: ='DATOS Iniciales y ACLARACIONES'!$B$15 -> 0.21
A12: Repuestos Iniciales | B12: 3 | C12: ='DATOS Iniciales y ACLARACIONES'!$B$15 -> 0.21
A13: Rodados | B13: 5 | C13: ='DATOS Iniciales y ACLARACIONES'!$B$15 -> 0.21 | D13: 22000000
A14: Equipos Auxiliares de Fabricación | B14: 5 | C14: ='DATOS Iniciales y ACLARACIONES'!$B$15 -> 0.21
A15: Equipos Auxiliares de Logística | B15: 5 | C15: ='DATOS Iniciales y ACLARACIONES'!$B$15 -> 0.21
A16: Muebles y Herramental Operativo | B16: 5 | C16: ='DATOS Iniciales y ACLARACIONES'!$B$15 -> 0.21 | D16: 10000000
A17: Equipamiento e Instalac. Sistemas | B17: 5 | C17: ='DATOS Iniciales y ACLARACIONES'!$B$15 -> 0.21
A18: Muebles y Útiles Administrativos | B18: 5 | C18: ='DATOS Iniciales y ACLARACIONES'!$B$15 -> 0.21
A19: Otros 1 | B19: 5 | C19: ='DATOS Iniciales y ACLARACIONES'!$B$15 -> 0.21
A20: Otros 2 | B20: 5 | C20: ='DATOS Iniciales y ACLARACIONES'!$B$15 -> 0.21
A21: Otros3 | B21: 5 | C21: ='DATOS Iniciales y ACLARACIONES'!$B$15 -> 0.21
A22: Imprevistos | B22: 5 | C22: ='DATOS Iniciales y ACLARACIONES'!$B$15 -> 0.21 | D22: =SUM(D4:D21)*'DATOS Iniciales y ACLARACIONES'!$B$24 -> 88950000 | E22: =SUM(E4:E21)*'DATOS Iniciales y ACLARACIONES'!$B$24 -> 0 | F22: =SUM(F4:F21)*'DATOS Iniciales y ACLARACIONES'!$B$24 -> 0 | G22: =SUM(G4:G21)*'DATOS Iniciales y ACLARACIONES'!$B$24 -> 0 | H22: =SUM(H4:H21)*'DATOS Iniciales y ACLARACIONES'!$B$24 -> 0 | I22: =SUM(I4:I21)*'DATOS Iniciales y ACLARACIONES'!$B$24 -> 0 | J22: =SUM(J4:J21)*'DATOS Iniciales y ACLARACIONES'!$B$24 -> 0 | K22: =SUM(K4:K21)*'DATOS Iniciales y ACLARACIONES'!$B$24 -> 0 | ... N22: =SUM(N4:N21)*'DATOS Iniciales y ACLARACIONES'!$B$24 -> 0
A23: Total Bienes de uso: | D23: =SUM(D4:D22) -> 1867950000 | E23: =SUM(E4:E22) -> 0 | F23: =SUM(F4:F22) -> 0 | G23: =SUM(G4:G22) -> 0 | H23: =SUM(H4:H22) -> 0 | I23: =SUM(I4:I22) -> 0 | J23: =SUM(J4:J22) -> 0 | K23: =SUM(K4:K22) -> 0 | ... N23: =SUM(N4:N22) -> 0
A25: b) Gastos asimilables
A26: Investigaciones y estudios | B26: 5 | C26: ='DATOS Iniciales y ACLARACIONES'!$B$15 -> 0.21
A27: Constitución y Org.de la empresa | B27: 5 | C27: ='DATOS Iniciales y ACLARACIONES'!$B$15 -> 0.21
A28: Adm.e Ing. en Período de Instalación | B28: 5 | C28: ='DATOS Iniciales y ACLARACIONES'!$B$15 -> 0.21
A29: Gastos de puesta en marcha: | B29: 5 | C29: ='DATOS Iniciales y ACLARACIONES'!$B$15 -> 0.21
A30: Patentes y Licencias: | B30: 5 | C30: ='DATOS Iniciales y ACLARACIONES'!$B$15 -> 0.21
A31: Promocion y Publicidad Preoperativas | B31: 5 | C31: ='DATOS Iniciales y ACLARACIONES'!$B$15 -> 0.21
A32: Infraestructura en predio ajeno | B32: 5 | C32: ='DATOS Iniciales y ACLARACIONES'!$B$15 -> 0.21
A33: Intereses y Gastos Preoperativos | B33: 3 | C33: 0.21
A34: Imprevistos: | B34: 5 | C34: ='DATOS Iniciales y ACLARACIONES'!$B$15 -> 0.21 | D34: =SUM(D26:D32)*'DATOS Iniciales y ACLARACIONES'!$B$24 -> 0 | E34: =SUM(E26:E32)*'DATOS Iniciales y ACLARACIONES'!$B$24 -> 0 | F34: =SUM(F26:F32)*'DATOS Iniciales y ACLARACIONES'!$B$24 -> 0 | G34: =SUM(G26:G32)*'DATOS Iniciales y ACLARACIONES'!$B$24 -> 0 | H34: =SUM(H26:H32)*'DATOS Iniciales y ACLARACIONES'!$B$24 -> 0 | I34: =SUM(I26:I32)*'DATOS Iniciales y ACLARACIONES'!$B$24 -> 0 | J34: =SUM(J26:J32)*'DATOS Iniciales y ACLARACIONES'!$B$24 -> 0 | K34: =SUM(K26:K32)*'DATOS Iniciales y ACLARACIONES'!$B$24 -> 0 | ... N34: =SUM(N26:N32)*'DATOS Iniciales y ACLARACIONES'!$B$24 -> 0
A35: Total gastos asimilables | D35: =SUM(D26:D34) -> 0 | E35: =SUM(E26:E34) -> 0 | F35: =SUM(F26:F34) -> 0 | G35: =SUM(G26:G34) -> 0 | H35: =SUM(H26:H34) -> 0 | I35: =SUM(I26:I34) -> 0 | J35: =SUM(J26:J34) -> 0 | K35: =SUM(K26:K34) -> 0 | ... N35: =SUM(N26:N34) -> 0
A37: c) Total Inversión sin IVA | D37: =+D23+D35 -> 1867950000 | E37: =+E23+E35 -> 0 | F37: =+F23+F35 -> 0 | G37: =+G23+G35 -> 0 | H37: =+H23+H35 -> 0 | I37: =+I23+I35 -> 0 | J37: =+J23+J35 -> 0 | K37: =+K23+K35 -> 0 | ... N37: =+N23+N35 -> 0
A39: d) IVA | D39: =SUMPRODUCT($C$4:$C$22,D4:D22)+SUMPRODUCT($C$26:$C$34,D26:D34) -> 99844500 | E39: =SUMPRODUCT($C$4:$C$22,E4:E22)+SUMPRODUCT($C$26:$C$34,E26:E34) -> 0 | F39: =SUMPRODUCT($C$4:$C$22,F4:F22)+SUMPRODUCT($C$26:$C$34,F26:F34) -> 0 | G39: =SUMPRODUCT($C$4:$C$22,G4:G22)+SUMPRODUCT($C$26:$C$34,G26:G34) -> 0 | H39: =SUMPRODUCT($C$4:$C$22,H4:H22)+SUMPRODUCT($C$26:$C$34,H26:H34) -> 0 | I39: =SUMPRODUCT($C$4:$C$22,I4:I22)+SUMPRODUCT($C$26:$C$34,I26:I34) -> 0 | J39: =SUMPRODUCT($C$4:$C$22,J4:J22)+SUMPRODUCT($C$26:$C$34,J26:J34) -> 0 | K39: =SUMPRODUCT($C$4:$C$22,K4:K22)+SUMPRODUCT($C$26:$C$34,K26:K34) -> 0 | ... N39: =SUMPRODUCT($C$4:$C$22,N4:N22)+SUMPRODUCT($C$26:$C$34,N26:N34) -> 0
A41: e) TOTAL INV. ACTIVO FIJO | D41: =+D37+D39 -> 1967794500 | E41: =+E37+E39 -> 0 | F41: =+F37+F39 -> 0 | G41: =+G37+G39 -> 0 | H41: =+H37+H39 -> 0 | I41: =+I37+I39 -> 0 | J41: =+J37+J39 -> 0 | K41: =+K37+K39 -> 0 | ... N41: =+N37+N39 -> 0
D44: Inversión Inicial | E44: Alícuotas de amortización
A45: Rubro | D45: Año 0 y 1 | E45: Año 1 | F45: Año 2 | G45: Año 3 | H45: Año 4 | I45: Año 5 | J45: Año 6 | K45: Año 7 | L45: Año 8 | M45: Año 9 | N45: Año 10 | O45: V. Resid
A46: a) Bienes de Uso
A47: Terreno y Mejoras | B47: 0 | D47: =D4+E4 -> 1224000000 | E47: =(E4+D4)*$B47 -> 0 | F47: =SUM(D4:F4)*$B47 -> 0 | G47: =SUM(D4:G4)*$B47 -> 0 | H47: =SUM(D4:H4)*$B47 -> 0 | I47: =SUM($D4:I4)*$B47 -> 0 | J47: =SUM($D4:J4)*$B47 -> 0 | K47: =SUM($D4:K4)*$B47 -> 0 | L47: =SUM($D4:L4)*$B47 -> 0 | M47: =SUM($D4:M4)*$B47 -> 0 | N47: =SUM($D4:N4)*$B47 -> 0 | O47: =SUM(D4:N4)-SUM(E47:N47) -> 1224000000
A48: Edificios y Obras Complementarias | B48: =1/B5 -> 0.033333333 | D48: =D5+E5 -> 186000000 | E48: =(E5+D5)*$B48 -> 6200000 | F48: =SUM(D5:F5)*$B48 -> 6200000 | G48: =SUM(D5:G5)*$B48 -> 6200000 | H48: =SUM(D5:H5)*$B48 -> 6200000 | I48: =SUM($D5:I5)*$B48 -> 6200000 | J48: =SUM($D5:J5)*$B48 -> 6200000 | K48: =SUM($D5:K5)*$B48 -> 6200000 | L48: =SUM($D5:L5)*$B48 -> 6200000 | M48: =SUM($D5:M5)*$B48 -> 6200000 | N48: =SUM($D5:N5)*$B48 -> 6200000 | O48: =SUM(D5:N5)-SUM(E48:N48) -> 124000000
A49: Infraestructura en predio propio | B49: =1/B6 -> 0.033333333 | D49: =D6+E6 -> 0 | E49: =(E6+D6)*$B49 -> 0 | F49: =SUM(D6:F6)*$B49 -> 0 | G49: =SUM(D6:G6)*$B49 -> 0 | H49: =SUM(D6:H6)*$B49 -> 0 | I49: =SUM($D6:I6)*$B49 -> 0 | J49: =SUM($D6:J6)*$B49 -> 0 | K49: =SUM($D6:K6)*$B49 -> 0 | L49: =SUM($D6:L6)*$B49 -> 0 | M49: =SUM($D6:M6)*$B49 -> 0 | N49: =SUM($D6:N6)*$B49 -> 0 | O49: =SUM(D6:N6)-SUM(E49:N49) -> 0
A50: Instalaciones industriales | B50: =1/B7 -> 0.1 | D50: =D7+E7 -> 0 | E50: =(E7+D7)*$B50 -> 0 | F50: =SUM(D7:F7)*$B50 -> 0 | G50: =SUM(D7:G7)*$B50 -> 0 | H50: =SUM(D7:H7)*$B50 -> 0 | I50: =SUM($D7:I7)*$B50 -> 0 | J50: =SUM($D7:J7)*$B50 -> 0 | K50: =SUM($D7:K7)*$B50 -> 0 | L50: =SUM($D7:L7)*$B50 -> 0 | M50: =SUM($D7:M7)*$B50 -> 0 | N50: =SUM($D7:N7)*$B50 -> 0 | O50: =SUM(D7:N7)-SUM(E50:N50) -> 0
A51: Máquinas operativas Importadas | B51: =1/B8 -> 0.1 | D51: =D8+E8 -> 337000000 | E51: =(E8+D8)*$B51 -> 33700000 | F51: =SUM(D8:F8)*$B51 -> 33700000 | G51: =SUM(D8:G8)*$B51 -> 33700000 | H51: =SUM(D8:H8)*$B51 -> 33700000 | I51: =SUM($D8:I8)*$B51 -> 33700000 | J51: =SUM($D8:J8)*$B51 -> 33700000 | K51: =SUM($D8:K8)*$B51 -> 33700000 | L51: =SUM($D8:L8)*$B51 -> 33700000 | M51: =SUM($D8:M8)*$B51 -> 33700000 | N51: =SUM($D8:N8)*$B51 -> 33700000 | O51: =SUM(D8:N8)-SUM(E51:N51) -> 0
A52: Gastos Conexos de Importación | B52: =1/B9 -> 0.1 | D52: =D9+E9 -> 0 | E52: =(E9+D9)*$B52 -> 0 | F52: =SUM(D9:F9)*$B52 -> 0 | G52: =SUM(D9:G9)*$B52 -> 0 | H52: =SUM(D9:H9)*$B52 -> 0 | I52: =SUM($D9:I9)*$B52 -> 0 | J52: =SUM($D9:J9)*$B52 -> 0 | K52: =SUM($D9:K9)*$B52 -> 0 | L52: =SUM($D9:L9)*$B52 -> 0 | M52: =SUM($D9:M9)*$B52 -> 0 | N52: =SUM($D9:N9)*$B52 -> 0 | O52: =SUM(D9:N9)-SUM(E52:N52) -> 0
A53: Maquinas Operativas Nacionales | B53: =1/B10 -> 0.1 | D53: =D10+E10 -> 0 | E53: =(E10+D10)*$B53 -> 0 | F53: =SUM(D10:F10)*$B53 -> 0 | G53: =SUM(D10:G10)*$B53 -> 0 | H53: =SUM(D10:H10)*$B53 -> 0 | I53: =SUM($D10:I10)*$B53 -> 0 | J53: =SUM($D10:J10)*$B53 -> 0 | K53: =SUM($D10:K10)*$B53 -> 0 | L53: =SUM($D10:L10)*$B53 -> 0 | M53: =SUM($D10:M10)*$B53 -> 0 | N53: =SUM($D10:N10)*$B53 -> 0 | O53: =SUM(D10:N10)-SUM(E53:N53) -> 0
A54: Transporte y montaje de la maquinaria: | B54: =1/B11 -> 0.1 | D54: =D11+E11 -> 0 | E54: =(E11+D11)*$B54 -> 0 | F54: =SUM(D11:F11)*$B54 -> 0 | G54: =SUM(D11:G11)*$B54 -> 0 | H54: =SUM(D11:H11)*$B54 -> 0 | I54: =SUM($D11:I11)*$B54 -> 0 | J54: =SUM($D11:J11)*$B54 -> 0 | K54: =SUM($D11:K11)*$B54 -> 0 | L54: =SUM($D11:L11)*$B54 -> 0 | M54: =SUM($D11:M11)*$B54 -> 0 | N54: =SUM($D11:N11)*$B54 -> 0 | O54: =SUM(D11:N11)-SUM(E54:N54) -> 0
A55: Repuestos Iniciales | B55: =1/B12 -> 0.33333333 | D55: =D12+E12 -> 0 | E55: =(E12+D12)*$B55 -> 0 | F55: =SUM(D12:F12)*$B55 -> 0 | G55: =SUM(D12:G12)*$B55 -> 0 | H55: =SUM(F12:H12)*$B55 -> 0 | I55: =SUM(G12:I12)*$B55 -> 0 | J55: =SUM(H12:J12)*$B55 -> 0 | K55: =SUM(I12:K12)*$B55 -> 0 | L55: =SUM(J12:L12)*$B55 -> 0 | M55: =SUM(K12:M12)*$B55 -> 0 | N55: =SUM(L12:N12)*$B55 -> 0 | O55: =SUM(D12:N12)-SUM(E55:N55) -> 0
A56: Rodados | B56: =1/B13 -> 0.2 | D56: =D13+E13 -> 22000000 | E56: =(E13+D13)*$B56 -> 4400000 | F56: =SUM(D13:F13)*$B56 -> 4400000 | G56: =SUM(D13:G13)*$B56 -> 4400000 | H56: =SUM(D13:H13)*$B56 -> 4400000 | I56: =SUM($D13:I13)*$B56 -> 4400000 | J56: =SUM(F13:J13)*$B56 -> 0 | K56: =SUM(G13:K13)*$B56 -> 0 | L56: =SUM(H13:L13)*$B56 -> 0 | M56: =SUM(I13:M13)*$B56 -> 0 | N56: =SUM(J13:N13)*$B56 -> 0 | O56: =SUM(D13:N13)-SUM(E56:N56) -> 0
A57: Equipos Auxiliares de Fabricación | B57: =1/B14 -> 0.2 | D57: =D14+E14 -> 0 | E57: =(E14+D14)*$B57 -> 0 | F57: =SUM(D14:F14)*$B57 -> 0 | G57: =SUM(D14:G14)*$B57 -> 0 | H57: =SUM(D14:H14)*$B57 -> 0 | I57: =SUM($D14:I14)*$B57 -> 0 | J57: =SUM(F14:J14)*$B57 -> 0 | K57: =SUM(G14:K14)*$B57 -> 0 | L57: =SUM(H14:L14)*$B57 -> 0 | M57: =SUM(I14:M14)*$B57 -> 0 | N57: =SUM(J14:N14)*$B57 -> 0 | O57: =SUM(D14:N14)-SUM(E57:N57) -> 0
A58: Equipos Auxiliares de Logística | B58: =1/B15 -> 0.2 | D58: =D15+E15 -> 0 | E58: =(E15+D15)*$B58 -> 0 | F58: =SUM(D15:F15)*$B58 -> 0 | G58: =SUM(D15:G15)*$B58 -> 0 | H58: =SUM(D15:H15)*$B58 -> 0 | I58: =SUM($D15:I15)*$B58 -> 0 | J58: =SUM(F15:J15)*$B58 -> 0 | K58: =SUM(G15:K15)*$B58 -> 0 | L58: =SUM(H15:L15)*$B58 -> 0 | M58: =SUM(I15:M15)*$B58 -> 0 | N58: =SUM(J15:N15)*$B58 -> 0 | O58: =SUM(D15:N15)-SUM(E58:N58) -> 0
A59: Muebles y Herramental Operativo | B59: =1/B16 -> 0.2 | D59: =D16+E16 -> 10000000 | E59: =(E16+D16)*$B59 -> 2000000 | F59: =SUM(D16:F16)*$B59 -> 2000000 | G59: =SUM(D16:G16)*$B59 -> 2000000 | H59: =SUM(D16:H16)*$B59 -> 2000000 | I59: =SUM($D16:I16)*$B59 -> 2000000 | J59: =SUM(F16:J16)*$B59 -> 0 | K59: =SUM(G16:K16)*$B59 -> 0 | L59: =SUM(H16:L16)*$B59 -> 0 | M59: =SUM(I16:M16)*$B59 -> 0 | N59: =SUM(J16:N16)*$B59 -> 0 | O59: =SUM(D16:N16)-SUM(E59:N59) -> 0
A60: Equipamiento e Instalac. Sistemas | B60: =1/B17 -> 0.2 | D60: =D17+E17 -> 0 | E60: =(E17+D17)*$B60 -> 0 | F60: =SUM(D17:F17)*$B60 -> 0 | G60: =SUM(D17:G17)*$B60 -> 0 | H60: =SUM(D17:H17)*$B60 -> 0 | I60: =SUM($D17:I17)*$B60 -> 0 | J60: =SUM(F17:J17)*$B60 -> 0 | K60: =SUM(G17:K17)*$B60 -> 0 | L60: =SUM(H17:L17)*$B60 -> 0 | M60: =SUM(I17:M17)*$B60 -> 0 | N60: =SUM(J17:N17)*$B60 -> 0 | O60: =SUM(D17:N17)-SUM(E60:N60) -> 0
A61: Muebles y Útiles Administrativos | B61: =1/B18 -> 0.2 | D61: =D18+E18 -> 0 | E61: =(E18+D18)*$B61 -> 0 | F61: =SUM(D18:F18)*$B61 -> 0 | G61: =SUM(D18:G18)*$B61 -> 0 | H61: =SUM(D18:H18)*$B61 -> 0 | I61: =SUM($D18:I18)*$B61 -> 0 | J61: =SUM(F18:J18)*$B61 -> 0 | K61: =SUM(G18:K18)*$B61 -> 0 | L61: =SUM(H18:L18)*$B61 -> 0 | M61: =SUM(I18:M18)*$B61 -> 0 | N61: =SUM(J18:N18)*$B61 -> 0 | O61: =SUM(D18:N18)-SUM(E61:N61) -> 0
A62: Otros 1 | B62: =1/B19 -> 0.2 | D62: =D19+E19 -> 0 | E62: =(E19+D19)*$B62 -> 0 | F62: =SUM(D19:F19)*$B62 -> 0 | G62: =SUM(D19:G19)*$B62 -> 0 | H62: =SUM(D19:H19)*$B62 -> 0 | I62: =SUM($D19:I19)*$B62 -> 0 | J62: =SUM(F19:J19)*$B62 -> 0 | K62: =SUM(G19:K19)*$B62 -> 0 | L62: =SUM(H19:L19)*$B62 -> 0 | M62: =SUM(I19:M19)*$B62 -> 0 | N62: =SUM(J19:N19)*$B62 -> 0 | O62: =SUM(D19:N19)-SUM(E62:N62) -> 0
A63: Otros 2 | B63: =1/B20 -> 0.2 | D63: =D20+E20 -> 0 | E63: =(E20+D20)*$B63 -> 0 | F63: =SUM(D20:F20)*$B63 -> 0 | G63: =SUM(D20:G20)*$B63 -> 0 | H63: =SUM(D20:H20)*$B63 -> 0 | I63: =SUM($D20:I20)*$B63 -> 0 | J63: =SUM(F20:J20)*$B63 -> 0 | K63: =SUM(G20:K20)*$B63 -> 0 | L63: =SUM(H20:L20)*$B63 -> 0 | M63: =SUM(I20:M20)*$B63 -> 0 | N63: =SUM(J20:N20)*$B63 -> 0 | O63: =SUM(D20:N20)-SUM(E63:N63) -> 0
A64: Otros3 | B64: =1/B21 -> 0.2 | D64: =D21+E21 -> 0 | E64: =(E21+D21)*$B64 -> 0 | F64: =SUM(D21:F21)*$B64 -> 0 | G64: =SUM(D21:G21)*$B64 -> 0 | H64: =SUM(D21:H21)*$B64 -> 0 | I64: =SUM($D21:I21)*$B64 -> 0 | J64: =SUM(F21:J21)*$B64 -> 0 | K64: =SUM(G21:K21)*$B64 -> 0 | L64: =SUM(H21:L21)*$B64 -> 0 | M64: =SUM(I21:M21)*$B64 -> 0 | N64: =SUM(J21:N21)*$B64 -> 0 | O64: =SUM(D21:N21)-SUM(E64:N64) -> 0
A65: Imprevistos | B65: =1/B22 -> 0.2 | D65: =D22+E22 -> 88950000 | E65: =(E22+D22)*$B65 -> 17790000 | F65: =SUM(D22:F22)*$B65 -> 17790000 | G65: =SUM(D22:G22)*$B65 -> 17790000 | H65: =SUM(D22:H22)*$B65 -> 17790000 | I65: =SUM($D22:I22)*$B65 -> 17790000 | J65: =SUM(F22:J22)*$B65 -> 0 | K65: =SUM(G22:K22)*$B65 -> 0 | L65: =SUM(H22:L22)*$B65 -> 0 | M65: =SUM(I22:M22)*$B65 -> 0 | N65: =SUM(J22:N22)*$B65 -> 0 | O65: =SUM(D22:N22)-SUM(E65:N65) -> 0
A66: Amortiz. Por Bienes de Uso | E66: =SUM(E47:E65) -> 64090000 | F66: =SUM(F47:F65) -> 64090000 | G66: =SUM(G47:G65) -> 64090000 | H66: =SUM(H47:H65) -> 64090000 | I66: =SUM(I47:I65) -> 64090000 | J66: =SUM(J47:J65) -> 39900000 | K66: =SUM(K47:K65) -> 39900000 | L66: =SUM(L47:L65) -> 39900000 | ... O66: =SUM(O47:O65) -> 1348000000
A68: b) Gastos asimilables
A69: Investigaciones y estudios | B69: =1/B26 -> 0.2 | D69: =D26+E26 -> 0 | E69: =(E26+D26)*$B69 -> 0 | F69: =SUM(D26:F26)*$B69 -> 0 | G69: =SUM(D26:G26)*$B69 -> 0 | H69: =SUM(D26:H26)*$B69 -> 0 | I69: =SUM($D26:I26)*$B69 -> 0 | J69: =SUM(F26:J26)*$B69 -> 0 | K69: =SUM(G26:K26)*$B69 -> 0 | L69: =SUM(H26:L26)*$B69 -> 0 | M69: =SUM(I26:M26)*$B69 -> 0 | N69: =SUM(J26:N26)*$B69 -> 0 | O69: =SUM(D26:N26)-SUM(E69:N69) -> 0
A70: Constitución y Org.de la empresa | B70: =1/B27 -> 0.2 | D70: =D27+E27 -> 0 | E70: =(E27+D27)*$B70 -> 0 | F70: =SUM(D27:F27)*$B70 -> 0 | G70: =SUM(D27:G27)*$B70 -> 0 | H70: =SUM(D27:H27)*$B70 -> 0 | I70: =SUM($D27:I27)*$B70 -> 0 | J70: =SUM(F27:J27)*$B70 -> 0 | K70: =SUM(G27:K27)*$B70 -> 0 | L70: =SUM(H27:L27)*$B70 -> 0 | M70: =SUM(I27:M27)*$B70 -> 0 | N70: =SUM(J27:N27)*$B70 -> 0 | O70: =SUM(D27:N27)-SUM(E70:N70) -> 0
A71: Adm.e Ing. en Período de Instalación | B71: =1/B28 -> 0.2 | D71: =D28+E28 -> 0 | E71: =(E28+D28)*$B71 -> 0 | F71: =SUM(D28:F28)*$B71 -> 0 | G71: =SUM(D28:G28)*$B71 -> 0 | H71: =SUM(D28:H28)*$B71 -> 0 | I71: =SUM($D28:I28)*$B71 -> 0 | J71: =SUM(F28:J28)*$B71 -> 0 | K71: =SUM(G28:K28)*$B71 -> 0 | L71: =SUM(H28:L28)*$B71 -> 0 | M71: =SUM(I28:M28)*$B71 -> 0 | N71: =SUM(J28:N28)*$B71 -> 0 | O71: =SUM(D28:N28)-SUM(E71:N71) -> 0
A72: Gastos de puesta en marcha | B72: =1/B29 -> 0.2 | D72: =D29+E29 -> 0 | E72: =(E29+D29)*$B72 -> 0 | F72: =SUM(D29:F29)*$B72 -> 0 | G72: =SUM(D29:G29)*$B72 -> 0 | H72: =SUM(D29:H29)*$B72 -> 0 | I72: =SUM($D29:I29)*$B72 -> 0 | J72: =SUM(F29:J29)*$B72 -> 0 | K72: =SUM(G29:K29)*$B72 -> 0 | L72: =SUM(H29:L29)*$B72 -> 0 | M72: =SUM(I29:M29)*$B72 -> 0 | N72: =SUM(J29:N29)*$B72 -> 0 | O72: =SUM(D29:N29)-SUM(E72:N72) -> 0
A73: Patentes y Licencias | B73: =1/B30 -> 0.2 | D73: =D30+E30 -> 0 | E73: =(E30+D30)*$B73 -> 0 | F73: =SUM(D30:F30)*$B73 -> 0 | G73: =SUM(D30:G30)*$B73 -> 0 | H73: =SUM(D30:H30)*$B73 -> 0 | I73: =SUM($D30:I30)*$B73 -> 0 | J73: =SUM(F30:J30)*$B73 -> 0 | K73: =SUM(G30:K30)*$B73 -> 0 | L73: =SUM(H30:L30)*$B73 -> 0 | M73: =SUM(I30:M30)*$B73 -> 0 | N73: =SUM(J30:N30)*$B73 -> 0 | O73: =SUM(D30:N30)-SUM(E73:N73) -> 0
A74: Promocion y Publicidad Preoperativas | B74: =1/B31 -> 0.2 | D74: =D31+E31 -> 0 | E74: =(E31+D31)*$B74 -> 0 | F74: =SUM(D31:F31)*$B74 -> 0 | G74: =SUM(D31:G31)*$B74 -> 0 | H74: =SUM(D31:H31)*$B74 -> 0 | I74: =SUM($D31:I31)*$B74 -> 0 | J74: =SUM(F31:J31)*$B74 -> 0 | K74: =SUM(G31:K31)*$B74 -> 0 | L74: =SUM(H31:L31)*$B74 -> 0 | M74: =SUM(I31:M31)*$B74 -> 0 | N74: =SUM(J31:N31)*$B74 -> 0 | O74: =SUM(D31:N31)-SUM(E74:N74) -> 0
A75: Infraestructura en predio ajeno | B75: =1/B32 -> 0.2 | D75: =D32+E32 -> 0 | E75: =(E32+D32)*$B75 -> 0 | F75: =SUM(D32:F32)*$B75 -> 0 | G75: =SUM(D32:G32)*$B75 -> 0 | H75: =SUM(D32:H32)*$B75 -> 0 | I75: =SUM($D32:I32)*$B75 -> 0 | J75: =SUM(F32:J32)*$B75 -> 0 | K75: =SUM(G32:K32)*$B75 -> 0 | L75: =SUM(H32:L32)*$B75 -> 0 | M75: =SUM(I32:M32)*$B75 -> 0 | N75: =SUM(J32:N32)*$B75 -> 0 | O75: =SUM(D32:N32)-SUM(E75:N75) -> 0
A76: Intereses y Gastos Preoperativos | B76: =1/B33 -> 0.33333333 | D76: =D33+E33 -> 0 | E76: =(E33+D33)*$B76 -> 0 | F76: =SUM(D33:F33)*$B76 -> 0 | G76: =SUM(D33:G33)*$B76 -> 0 | H76: =SUM(F33:H33)*$B76 -> 0 | I76: =SUM($G33:I33)*$B76 -> 0 | J76: =SUM($H33:J33)*$B76 -> 0 | K76: =SUM($I33:K33)*$B76 -> 0 | L76: =SUM($J33:L33)*$B76 -> 0 | M76: =SUM($K33:M33)*$B76 -> 0 | N76: =SUM($L33:N33)*$B76 -> 0 | O76: =SUM(D33:N33)-SUM(E76:N76) -> 0
A77: Imprevistos: | B77: =1/B34 -> 0.2 | D77: =D34+E34 -> 0 | E77: =(E34+D34)*$B77 -> 0 | F77: =SUM(D34:F34)*$B77 -> 0 | G77: =SUM(D34:G34)*$B77 -> 0 | H77: =SUM(D34:H34)*$B77 -> 0 | I77: =SUM($D34:I34)*$B77 -> 0 | J77: =SUM(F34:J34)*$B77 -> 0 | K77: =SUM(G34:K34)*$B77 -> 0 | L77: =SUM(H34:L34)*$B77 -> 0 | M77: =SUM(I34:M34)*$B77 -> 0 | N77: =SUM(J34:N34)*$B77 -> 0 | O77: =SUM(D34:N34)-SUM(E77:N77) -> 0
A78: Amortiz. Por Gastos Asimilables | E78: =SUM(E69:E77) -> 0 | F78: =SUM(F69:F77) -> 0 | G78: =SUM(G69:G77) -> 0 | H78: =SUM(H69:H77) -> 0 | I78: =SUM(I69:I77) -> 0 | J78: =SUM(J69:J77) -> 0 | K78: =SUM(K69:K77) -> 0 | L78: =SUM(L69:L77) -> 0 | ... O78: =SUM(O69:O77) -> 0
A80: Total Amortización Anual | E80: =E78+E66 -> 64090000 | F80: =F78+F66 -> 64090000 | G80: =G78+G66 -> 64090000 | H80: =H78+H66 -> 64090000 | I80: =I78+I66 -> 64090000 | J80: =J78+J66 -> 39900000 | K80: =K78+K66 -> 39900000 | L80: =L78+L66 -> 39900000 | ... O80: =O78+O66 -> 1348000000
A81: Alicuota de Amortiz. Producción | B81: ='DATOS Iniciales y ACLARACIONES'!B29 -> 0.4 | E81: =(E$80-E$84)*$B81 -> 25636000 | F81: =(F$80-F$84)*$B81 -> 25636000 | G81: =(G$80-G$84)*$B81 -> 25636000 | H81: =(H$80-H$84)*$B81 -> 25636000 | I81: =(I$80-I$84)*$B81 -> 25636000 | J81: =(J$80-J$84)*$B81 -> 15960000 | K81: =(K$80-K$84)*$B81 -> 15960000 | L81: =(L$80-L$84)*$B81 -> 15960000 | ... N81: =(N$80-N$84)*$B81 -> 15960000
A82: Alicuota de Amortiz. Comercializ. | B82: ='DATOS Iniciales y ACLARACIONES'!B30 -> 0.4 | E82: =(E$80-E$84)*$B82 -> 25636000 | F82: =(F$80-F$84)*$B82 -> 25636000 | G82: =(G$80-G$84)*$B82 -> 25636000 | H82: =(H$80-H$84)*$B82 -> 25636000 | I82: =(I$80-I$84)*$B82 -> 25636000 | J82: =(J$80-J$84)*$B82 -> 15960000 | K82: =(K$80-K$84)*$B82 -> 15960000 | L82: =(L$80-L$84)*$B82 -> 15960000 | ... N82: =(N$80-N$84)*$B82 -> 15960000
A83: Alicuota de Amortiz. Administrac. | B83: ='DATOS Iniciales y ACLARACIONES'!B31 -> 0.2 | E83: =(E$80-E$84)*$B83 -> 12818000 | F83: =(F$80-F$84)*$B83 -> 12818000 | G83: =(G$80-G$84)*$B83 -> 12818000 | H83: =(H$80-H$84)*$B83 -> 12818000 | I83: =(I$80-I$84)*$B83 -> 12818000 | J83: =(J$80-J$84)*$B83 -> 7980000 | K83: =(K$80-K$84)*$B83 -> 7980000 | L83: =(L$80-L$84)*$B83 -> 7980000 | ... N83: =(N$80-N$84)*$B83 -> 7980000
A84: Alicuota de Amortiz. Financiera | E84: =E76 -> 0 | F84: =F76 -> 0 | G84: =G76 -> 0 | H84: =H76 -> 0 | I84: =I76 -> 0 | J84: =J76 -> 0 | K84: =K76 -> 0 | L84: =L76 -> 0 | ... N84: =N76 -> 0
A85: En este cuadro se ha utilizado se ha usado el criterio principal para el Prorrateo de Amortización. En caso de utilizarse otros Criterios, reveer las fórmulas de las últimas 3 filas
A86: Las Alicuotas de Amortización del año 4 en adelante se han calculado considerando que los rubros (y en particular el plazo de Amortización) son los originales. En caso de cambiarlos, verificar las fórmulas

Sheet InvAT
A1: INVERSIONES EN ACTIVO DE TRABAJO
A2: Rubros | B2: Año 0 | C2: Año 1 | D2: Año 2 | E2: Año 3 | F2: Año 4 | G2: Año 5 | H2: Año 6 | I2: Año 7 | J2: Año 8 | K2: Año 9 | L2: Año 10
A3: 1. Activo de Trabajo: (valor contable)
A4: a) Disponibilidad Mínima en Caja y Bancos: | B4: ='CTV y CResult'!$B$13*'DATOS Iniciales y ACLARACIONES'!$B$47 -> 79464000 | C4: =B4 -> 79464000 | D4: =C4 -> 79464000 | E4: =D4 -> 79464000 | F4: =E4 -> 79464000 | G4: =F4 -> 79464000 | H4: =G4 -> 79464000 | I4: =H4 -> 79464000 | J4: =I4 -> 79464000 | ... L4: =K4 -> 79464000
A5: b) Crédito por Ventas | B5: 0 | C5: ='CTV y CResult'!B13*'DATOS Iniciales y ACLARACIONES'!D43/365 -> 1959386301 | D5: ='CTV y CResult'!C13*'DATOS Iniciales y ACLARACIONES'!E43/365 -> 1492668493 | E5: ='CTV y CResult'!D13*'DATOS Iniciales y ACLARACIONES'!F43/365 -> 1166104110 | F5: ='CTV y CResult'!E13*'DATOS Iniciales y ACLARACIONES'!G43/365 -> 1081183562 | G5: ='CTV y CResult'!F13*'DATOS Iniciales y ACLARACIONES'!H43/365 -> 9.9114247e+08 | H5: ='CTV y CResult'!G13*'DATOS Iniciales y ACLARACIONES'!I43/365 -> 8.8959452e+08 | I5: ='CTV y CResult'!H13*'DATOS Iniciales y ACLARACIONES'!J43/365 -> 7.7671233e+08 | J5: ='CTV y CResult'!I13*'DATOS Iniciales y ACLARACIONES'!K43/365 -> 8.1353425e+08 | ... L5: ='CTV y CResult'!K13*'DATOS Iniciales y ACLARACIONES'!M43/365 -> 3211446575
A7: c) Bienes de cambio: | B7: =SUM(B8:B11) -> 0 | C7: =SUM(C8:C11) -> 0 | D7: =SUM(D8:D11) -> 0 | E7: =SUM(E8:E11) -> 0 | F7: =SUM(F8:F11) -> 0 | G7: =SUM(G8:G11) -> 0 | H7: =SUM(H8:H11) -> 0 | I7: =SUM(I8:I11) -> 0 | ... L7: =SUM(L8:L11) -> 0
A8: Stock de materias prima:
A9: Stock de materiales:
A10: Mercadería en curso y semielaborada | B10: 0 | C10: =CostoPROD!B40 -> 0 | D10: =CostoPROD!C40 -> 0 | E10: =CostoPROD!D40 -> 0 | F10: =CostoPROD!E40 -> 0 | G10: =CostoPROD!F40 -> 0 | H10: =CostoPROD!G40 -> 0 | I10: =CostoPROD!H40 -> 0 | J10: =CostoPROD!I40 -> 0 | ... L10: =CostoPROD!K40 -> 0
A11: Stock de elaborados | B11: 0 | C11: ='CTV y CResult'!B25 -> 0 | D11: ='CTV y CResult'!C25 -> 0 | E11: ='CTV y CResult'!D25 -> 0 | F11: ='CTV y CResult'!E25 -> 0 | G11: ='CTV y CResult'!F25 -> 0 | H11: ='CTV y CResult'!G25 -> 0 | I11: ='CTV y CResult'!H25 -> 0 | J11: ='CTV y CResult'!I25 -> 0 | ... L11: ='CTV y CResult'!K25 -> 0
A13: d) Total Activo de Trabajo, sin IVA: | B13: =SUM(B4:B7) -> 79464000 | C13: =SUM(C4:C7) -> 2038850301 | D13: =SUM(D4:D7) -> 1572132493 | E13: =SUM(E4:E7) -> 1245568110 | F13: =SUM(F4:F7) -> 1160647562 | G13: =SUM(G4:G7) -> 1070606466 | H13: =SUM(H4:H7) -> 9.6905852e+08 | I13: =SUM(I4:I7) -> 8.5617633e+08 | ... L13: =SUM(L4:L7) -> 3290910575
A14: 2. Menos:
A15: Amortizaciones en Mercadería en proceso | B15: 0 | C15: =CostoPROD!B28 -> 0 | D15: =CostoPROD!C28 -> 0 | E15: =CostoPROD!D28 -> 0 | F15: =CostoPROD!E28 -> 0 | G15: =CostoPROD!F28 -> 0 | H15: =CostoPROD!G28 -> 0 | I15: =CostoPROD!H28 -> 0 | J15: =CostoPROD!I28 -> 0 | ... L15: =CostoPROD!K28 -> 0
A16: Amortizaciones en Stock de elaborado | B16: 0 | C16: =(CostoPROD!B6-C15)/CostoPROD!B49*InvAT!C11 -> 0 | D16: =(CostoPROD!C6-D15)/CostoPROD!C49*InvAT!D11 -> 0 | E16: =(CostoPROD!D6-E15)/CostoPROD!D49*InvAT!E11 -> 0 | F16: =(CostoPROD!E6-F15)/CostoPROD!E49*InvAT!F11 -> 0 | G16: =(CostoPROD!F6-G15)/CostoPROD!F49*InvAT!G11 -> 0 | H16: =(CostoPROD!G6-H15)/CostoPROD!G49*InvAT!H11 -> 0 | I16: =(CostoPROD!H6-I15)/CostoPROD!H49*InvAT!I11 -> 0 | J16: =(CostoPROD!I6-J15)/CostoPROD!I49*InvAT!J11 -> 0 | ... L16: =(CostoPROD!K6-L15)/CostoPROD!K49*InvAT!L11 -> 0
A17: Utilidades en Crédito por ventas | B17: 0 | C17: ='CTV y CResult'!B41*InvAT!C5 -> 1.9969549e+08 | D17: ='CTV y CResult'!C41*InvAT!D5 -> 233109505 | E17: ='CTV y CResult'!D41*InvAT!E5 -> 1.9916323e+08 | F17: ='CTV y CResult'!E41*InvAT!F5 -> 2.003438e+08 | G17: ='CTV y CResult'!F41*InvAT!G5 -> 1.9885095e+08 | H17: ='CTV y CResult'!G41*InvAT!H5 -> 1.938792e+08 | I17: ='CTV y CResult'!H41*InvAT!I5 -> 1.8003989e+08 | J17: ='CTV y CResult'!I41*InvAT!J5 -> 1.9926448e+08 | ... L17: ='CTV y CResult'!K41*InvAT!L5 -> 864960880
A18: Amortizaciones en Crédito por ventas | B18: 0 | C18: =('Inv AF'!E80-InvAT!C15-InvAT!C16)/'CTV y CResult'!B13*C5 -> 31606027 | D18: =('Inv AF'!F80-InvAT!D15-InvAT!D16)/'CTV y CResult'!C13*D5 -> 21070685 | E18: =('Inv AF'!G80-InvAT!E15-InvAT!E16)/'CTV y CResult'!D13*E5 -> 15803014 | F18: =('Inv AF'!H80-InvAT!F15-InvAT!F16)/'CTV y CResult'!E13*F5 -> 14047123 | G18: =('Inv AF'!I80-InvAT!G15-InvAT!G16)/'CTV y CResult'!F13*G5 -> 12291233 | H18: =('Inv AF'!J80-InvAT!H15-InvAT!H16)/'CTV y CResult'!G13*H5 -> 6558904.1 | I18: =('Inv AF'!K80-InvAT!I15-InvAT!I16)/'CTV y CResult'!H13*I5 -> 5465753.4 | J18: =('Inv AF'!L80-InvAT!J15-InvAT!J16)/'CTV y CResult'!I13*J5 -> 5465753.4 | ... L18: =('Inv AF'!N80-InvAT!L15-InvAT!L16)/'CTV y CResult'!K13*L5 -> 19676712
A20: 3. Inversiones en Activo de Trabajo, sin IVA | B20: =+B13-B15-B16-B17-B18 -> 79464000 | C20: =+C13-C15-C16-C17-C18 -> 1807548784 | D20: =+D13-D15-D16-D17-D18 -> 1317952303 | E20: =+E13-E15-E16-E17-E18 -> 1030601870 | F20: =+F13-F15-F16-F17-F18 -> 9.4625663e+08 | G20: =+G13-G15-G16-G17-G18 -> 859464287 | H20: =+H13-H15-H16-H17-H18 -> 7.6862041e+08 | I20: =+I13-I15-I16-I17-I18 -> 6.7067069e+08 | ... L20: =+L13-L15-L16-L17-L18 -> 2406272983
A22: 4. Incrementos de Activo de Trabajo | B22: =+B13 -> 79464000 | C22: =+C13-B13 -> 1959386301 | D22: =+D13-C13 -> -4.6671781e+08 | E22: =+E13-D13 -> -3.2656438e+08 | F22: =+F13-E13 -> -84920548 | G22: =+G13-F13 -> -90041096 | H22: =+H13-G13 -> -1.0154795e+08 | I22: =+I13-H13 -> -1.1288219e+08 | J22: =+J13-I13 -> 36821918 | ... L22: =+L13-K13 -> 1507857534
A23: Incrementos de Inversión en Activo de Trabajo | B23: =+B20 -> 79464000 | C23: =+C20-B20 -> 1728084784 | D23: =+D20-C20 -> -4.8959648e+08 | E23: =+E20-D20 -> -287350433 | F23: =+F20-E20 -> -84345236 | G23: =+G20-F20 -> -86792347 | H23: =+H20-G20 -> -90843872 | I23: =+I20-H20 -> -97949730 | J23: =+J20-I20 -> 17597333 | ... L23: =+L20-K20 -> 1072631491
A25: 5. Incrementos IVA sobre Inversiones
A26: Crédito por Ventas
A27: Bienes de cambio:
A28: Stock de materia prima | B28: =+B8*'DATOS Iniciales y ACLARACIONES'!$B$15 -> 0 | C28: =(+C8-B8)*'DATOS Iniciales y ACLARACIONES'!$B$15 -> 0 | D28: =(+D8-C8)*'DATOS Iniciales y ACLARACIONES'!$B$15 -> 0 | E28: =(+E8-D8)*'DATOS Iniciales y ACLARACIONES'!$B$15 -> 0 | F28: =(+F8-E8)*'DATOS Iniciales y ACLARACIONES'!$B$15 -> 0 | G28: =(+G8-F8)*'DATOS Iniciales y ACLARACIONES'!$B$15 -> 0 | H28: =(+H8-G8)*'DATOS Iniciales y ACLARACIONES'!$B$15 -> 0 | I28: =(+I8-H8)*'DATOS Iniciales y ACLARACIONES'!$B$15 -> 0 | J28: =(+J8-I8)*'DATOS Iniciales y ACLARACIONES'!$B$15 -> 0 | ... L28: =(+L8-K8)*'DATOS Iniciales y ACLARACIONES'!$B$15 -> 0
A29: Stock de materiales | B29: =+B9*'DATOS Iniciales y ACLARACIONES'!B15 -> 0 | C29: =(+C9-B9)*'DATOS Iniciales y ACLARACIONES'!$B$15 -> 0 | D29: =(+D9-C9)*'DATOS Iniciales y ACLARACIONES'!$B$15 -> 0 | E29: =(+E9-D9)*'DATOS Iniciales y ACLARACIONES'!$B$15 -> 0 | F29: =(+F9-E9)*'DATOS Iniciales y ACLARACIONES'!$B$15 -> 0 | G29: =(+G9-F9)*'DATOS Iniciales y ACLARACIONES'!$B$15 -> 0 | H29: =(+H9-G9)*'DATOS Iniciales y ACLARACIONES'!$B$15 -> 0 | I29: =(+I9-H9)*'DATOS Iniciales y ACLARACIONES'!$B$15 -> 0 | J29: =(+J9-I9)*'DATOS Iniciales y ACLARACIONES'!$B$15 -> 0 | ... L29: =(+L9-K9)*'DATOS Iniciales y ACLARACIONES'!$B$15 -> 0
A30: Mercadería en proceso | B30: 0 | C30: =IVA!D5/'CTV y CResult'!B22*C10 -> 0 | D30: =IVA!E5/'CTV y CResult'!C22*D10-(IVA!D5/'CTV y CResult'!B22*C10) -> 0 | E30: =IVA!F5/'CTV y CResult'!D22*E10-(IVA!E5/'CTV y CResult'!C22*D10) -> 0 | F30: =IVA!G5/'CTV y CResult'!E22*F10-(IVA!F5/'CTV y CResult'!D22*E10) -> 0 | G30: =IVA!H5/'CTV y CResult'!F22*G10-(IVA!G5/'CTV y CResult'!E22*F10) -> 0 | H30: =IVA!I5/'CTV y CResult'!G22*H10-(IVA!H5/'CTV y CResult'!F22*G10) -> 0 | I30: =IVA!J5/'CTV y CResult'!H22*I10-(IVA!I5/'CTV y CResult'!G22*H10) -> 0 | J30: =IVA!K5/'CTV y CResult'!I22*J10-(IVA!J5/'CTV y CResult'!H22*I10) -> 0 | K30: =IVA!L5/'CTV y CResult'!J22*K10-(IVA!K5/'CTV y CResult'!I22*J10) -> 0 | L30: =IVA!M5/'CTV y CResult'!K22*L10-(IVA!L5/'CTV y CResult'!J22*K10) -> 0
A31: Stock de elaborados | B31: 0 | C31: =IVA!D5/'CTV y CResult'!B22*C11 -> 0 | D31: =IVA!E5/'CTV y CResult'!C22*D11-(IVA!D5/'CTV y CResult'!B22*C11) -> 0 | E31: =IVA!F5/'CTV y CResult'!D22*E11-(IVA!E5/'CTV y CResult'!C22*D11) -> 0 | F31: =IVA!G5/'CTV y CResult'!E22*F11-(IVA!F5/'CTV y CResult'!D22*E11) -> 0 | G31: =IVA!H5/'CTV y CResult'!F22*G11-(IVA!G5/'CTV y CResult'!E22*F11) -> 0 | H31: =IVA!I5/'CTV y CResult'!G22*H11-(IVA!H5/'CTV y CResult'!F22*G11) -> 0 | I31: =IVA!J5/'CTV y CResult'!H22*I11-(IVA!I5/'CTV y CResult'!G22*H11) -> 0 | J31: =IVA!K5/'CTV y CResult'!I22*J11-(IVA!J5/'CTV y CResult'!H22*I11) -> 0 | K31: =IVA!L5/'CTV y CResult'!J22*K11-(IVA!K5/'CTV y CResult'!I22*J11) -> 0 | L31: =IVA!M5/'CTV y CResult'!K22*L11-(IVA!L5/'CTV y CResult'!J22*K11) -> 0
A32: Total incrementos IVA sobre inversiones | B32: =SUM(B26:B31) -> 0 | C32: =SUM(C26:C31) -> 0 | D32: =SUM(D26:D31) -> 0 | E32: =SUM(E26:E31) -> 0 | F32: =SUM(F26:F31) -> 0 | G32: =SUM(G26:G31) -> 0 | H32: =SUM(H26:H31) -> 0 | I32: =SUM(I26:I31) -> 0 | ... L32: =SUM(L26:L31) -> 0
A34: 6. Incrementos Inversiones en Activo de Trabajo | B34: =+B23+B32 -> 79464000 | C34: =+C23+C32 -> 1728084784 | D34: =+D23+D32 -> -4.8959648e+08 | E34: =+E23+E32 -> -287350433 | F34: =+F23+F32 -> -84345236 | G34: =+G23+G32 -> -86792347 | H34: =+H23+H32 -> -90843872 | I34: =+I23+I32 -> -97949730 | ... L34: =+L23+L32 -> 1072631491

Sheet CostoPROD
A1: COSTO TOTAL DE PRODUCCION
B2: Gastos en el Area de Producción
A3: Rubros | B3: Año 1 | C3: Año 2 | D3: Año 3 | E3: Año 4 | F3: Año 5 | G3: Año 6 | H3: Año 7 | I3: Año 8 | J3: Año 9 | K3: Año 10 | L3: Tipo de Gasto
A4: Materia prima | B4: 1004000000 | C4: 1004000000 | D4: 1004000000 | E4: 1004000000 | F4: 1004000000 | G4: 1004000000 | H4: 1004000000 | I4: 1004000000 | J4: 1004000000 | K4: 1004000000 | L4: FIJO
A5: Mano de obra directa | B5: 850000000 | C5: =B5 -> 850000000 | D5: =C5 -> 850000000 | E5: =D5 -> 850000000 | F5: =E5 -> 850000000 | G5: =F5 -> 850000000 | H5: =G5 -> 850000000 | I5: =H5 -> 850000000 | J5: =I5 -> 850000000 | K5: =J5 -> 850000000 | L5: FIJO
A6: Amortizaciones | B6: ='Inv AF'!E81 -> 25636000 | C6: ='Inv AF'!F81 -> 25636000 | D6: ='Inv AF'!G81 -> 25636000 | E6: ='Inv AF'!H81 -> 25636000 | F6: ='Inv AF'!I81 -> 25636000 | G6: ='Inv AF'!J81 -> 15960000 | H6: ='Inv AF'!K81 -> 15960000 | I6: ='Inv AF'!L81 -> 15960000 | ... K6: ='Inv AF'!N81 -> 15960000 | L6: FIJO
A7: Personal indirecto | L7: VARIABLE
A8: Materiales | L8: FIJO
A9: Energía eléctrica | L9: FIJO
A10: Telefono, Gas, Agua | L10: FIJO
A11: Tasas e impuestos | L11: FIJO
A12: Seguros | L12: FIJO
A13: Procesos y Servicios Tercerizados | L13: FIJO
A14: Regalias Patentes y Licencias | L14: FIJO
A15: Tratamiento de residuos | L15: FIJO
A16: Gastos Logísticos | B16: 34 | D16: 123 | G16: 3123 | L16: FIJO
A17: Imprevistos | B17: =SUM(B3:B12)*'DATOS Iniciales y ACLARACIONES'!$B$25 -> 56389080 | C17: =SUM(C3:C12)*'DATOS Iniciales y ACLARACIONES'!$B$25 -> 56389080 | D17: =SUM(D3:D12)*'DATOS Iniciales y ACLARACIONES'!$B$25 -> 56389080 | E17: =SUM(E3:E12)*'DATOS Iniciales y ACLARACIONES'!$B$25 -> 56389080 | F17: =SUM(F3:F12)*'DATOS Iniciales y ACLARACIONES'!$B$25 -> 56389080 | G17: =SUM(G3:G12)*'DATOS Iniciales y ACLARACIONES'!$B$25 -> 56098800 | H17: =SUM(H3:H12)*'DATOS Iniciales y ACLARACIONES'!$B$25 -> 56098800 | I17: =SUM(I3:I12)*'DATOS Iniciales y ACLARACIONES'!$B$25 -> 56098800 | ... K17: =SUM(K3:K12)*'DATOS Iniciales y ACLARACIONES'!$B$25 -> 56098800 | L17: FIJO
A18: Gastos Total de Producción | B18: =SUM(B4:B17) -> 1936025114 | C18: =SUM(C4:C17) -> 1936025080 | D18: =SUM(D4:D17) -> 1936025203 | E18: =SUM(E4:E17) -> 1936025080 | F18: =SUM(F4:F17) -> 1936025080 | G18: =SUM(G4:G17) -> 1926061923 | H18: =SUM(H4:H17) -> 1926058800 | I18: =SUM(I4:I17) -> 1926058800 | ... K18: =SUM(K4:K17) -> 1926058800
A20: Gasto Variable | B20: =SUMIF($L$4:$L$17,"VARIABLE",B4:B17) -> 0 | C20: =SUMIF($L$4:$L$17,"VARIABLE",C4:C17) -> 0 | D20: =SUMIF($L$4:$L$17,"VARIABLE",D4:D17) -> 0 | E20: =SUMIF($L$4:$L$17,"VARIABLE",E4:E17) -> 0 | F20: =SUMIF($L$4:$L$17,"VARIABLE",F4:F17) -> 0 | G20: =SUMIF($L$4:$L$17,"VARIABLE",G4:G17) -> 0 | H20: =SUMIF($L$4:$L$17,"VARIABLE",H4:H17) -> 0 | I20: =SUMIF($L$4:$L$17,"VARIABLE",I4:I17) -> 0 | ... K20: =SUMIF($L$4:$L$17,"VARIABLE",K4:K17) -> 0
A21: Gasto Constante | B21: =SUMIF($L$4:$L$17,"FIJO",B4:B17) -> 1936025114 | C21: =SUMIF($L$4:$L$17,"FIJO",C4:C17) -> 1936025080 | D21: =SUMIF($L$4:$L$17,"FIJO",D4:D17) -> 1936025203 | E21: =SUMIF($L$4:$L$17,"FIJO",E4:E17) -> 1936025080 | F21: =SUMIF($L$4:$L$17,"FIJO",F4:F17) -> 1936025080 | G21: =SUMIF($L$4:$L$17,"FIJO",G4:G17) -> 1926061923 | H21: =SUMIF($L$4:$L$17,"FIJO",H4:H17) -> 1926058800 | I21: =SUMIF($L$4:$L$17,"FIJO",I4:I17) -> 1926058800 | ... K21: =SUMIF($L$4:$L$17,"FIJO",K4:K17) -> 1926058800
B23: Gastos a activar
B24: Mercadería en Curso y Semielaborada*1
A25: Rubros | B25: Año 1 | C25: Año 2 | D25: Año 3 | E25: Año 4 | F25: Año 5 | G25: Año 6 | H25: Año 7 | I25: Año 8 | J25: Año 9 | K25: Año 10
A26: Materia prima | B26: =B4/'DATOS Iniciales y ACLARACIONES'!D$44*'DATOS Iniciales y ACLARACIONES'!D$41/2 -> 0 | C26: =C4/'DATOS Iniciales y ACLARACIONES'!E$44*'DATOS Iniciales y ACLARACIONES'!E$41/2 -> 0 | D26: =D4/'DATOS Iniciales y ACLARACIONES'!F$44*'DATOS Iniciales y ACLARACIONES'!F$41/2 -> 0 | E26: =E4/'DATOS Iniciales y ACLARACIONES'!G$44*'DATOS Iniciales y ACLARACIONES'!G$41/2 -> 0 | F26: =F4/'DATOS Iniciales y ACLARACIONES'!H$44*'DATOS Iniciales y ACLARACIONES'!H$41/2 -> 0 | G26: =G4/'DATOS Iniciales y ACLARACIONES'!I$44*'DATOS Iniciales y ACLARACIONES'!I$41/2 -> 0 | H26: =H4/'DATOS Iniciales y ACLARACIONES'!J$44*'DATOS Iniciales y ACLARACIONES'!J$41/2 -> 0 | I26: =I4/'DATOS Iniciales y ACLARACIONES'!K$44*'DATOS Iniciales y ACLARACIONES'!K$41/2 -> 0 | ... K26: =K4/'DATOS Iniciales y ACLARACIONES'!M$44*'DATOS Iniciales y ACLARACIONES'!M$41/2 -> 0
A27: Mano de obra directa | B27: =B5/'DATOS Iniciales y ACLARACIONES'!D$44*'DATOS Iniciales y ACLARACIONES'!D$41/2 -> 0 | C27: =C5/'DATOS Iniciales y ACLARACIONES'!E$44*'DATOS Iniciales y ACLARACIONES'!E$41/2 -> 0 | D27: =D5/'DATOS Iniciales y ACLARACIONES'!F$44*'DATOS Iniciales y ACLARACIONES'!F$41/2 -> 0 | E27: =E5/'DATOS Iniciales y ACLARACIONES'!G$44*'DATOS Iniciales y ACLARACIONES'!G$41/2 -> 0 | F27: =F5/'DATOS Iniciales y ACLARACIONES'!H$44*'DATOS Iniciales y ACLARACIONES'!H$41/2 -> 0 | G27: =G5/'DATOS Iniciales y ACLARACIONES'!I$44*'DATOS Iniciales y ACLARACIONES'!I$41/2 -> 0 | H27: =H5/'DATOS Iniciales y ACLARACIONES'!J$44*'DATOS Iniciales y ACLARACIONES'!J$41/2 -> 0 | I27: =I5/'DATOS Iniciales y ACLARACIONES'!K$44*'DATOS Iniciales y ACLARACIONES'!K$41/2 -> 0 | ... K27: =K5/'DATOS Iniciales y ACLARACIONES'!M$44*'DATOS Iniciales y ACLARACIONES'!M$41/2 -> 0
A28: Amortizaciones | B28: =B6/'DATOS Iniciales y ACLARACIONES'!D$44*'DATOS Iniciales y ACLARACIONES'!D$41/2 -> 0 | C28: =C6/'DATOS Iniciales y ACLARACIONES'!E$44*'DATOS Iniciales y ACLARACIONES'!E$41/2 -> 0 | D28: =D6/'DATOS Iniciales y ACLARACIONES'!F$44*'DATOS Iniciales y ACLARACIONES'!F$41/2 -> 0 | E28: =E6/'DATOS Iniciales y ACLARACIONES'!G$44*'DATOS Iniciales y ACLARACIONES'!G$41/2 -> 0 | F28: =F6/'DATOS Iniciales y ACLARACIONES'!H$44*'DATOS Iniciales y ACLARACIONES'!H$41/2 -> 0 | G28: =G6/'DATOS Iniciales y ACLARACIONES'!I$44*'DATOS Iniciales y ACLARACIONES'!I$41/2 -> 0 | H28: =H6/'DATOS Iniciales y ACLARACIONES'!J$44*'DATOS Iniciales y ACLARACIONES'!J$41/2 -> 0 | I28: =I6/'DATOS Iniciales y ACLARACIONES'!K$44*'DATOS Iniciales y ACLARACIONES'!K$41/2 -> 0 | ... K28: =K6/'DATOS Iniciales y ACLARACIONES'!M$44*'DATOS Iniciales y ACLARACIONES'!M$41/2 -> 0
A29: Personal indirecto | B29: =B7/'DATOS Iniciales y ACLARACIONES'!D$44*'DATOS Iniciales y ACLARACIONES'!D$41/2 -> 0 | C29: =C7/'DATOS Iniciales y ACLARACIONES'!E$44*'DATOS Iniciales y ACLARACIONES'!E$41/2 -> 0 | D29: =D7/'DATOS Iniciales y ACLARACIONES'!F$44*'DATOS Iniciales y ACLARACIONES'!F$41/2 -> 0 | E29: =E7/'DATOS Iniciales y ACLARACIONES'!G$44*'DATOS Iniciales y ACLARACIONES'!G$41/2 -> 0 | F29: =F7/'DATOS Iniciales y ACLARACIONES'!H$44*'DATOS Iniciales y ACLARACIONES'!H$41/2 -> 0 | G29: =G7/'DATOS Iniciales y ACLARACIONES'!I$44*'DATOS Iniciales y ACLARACIONES'!I$41/2 -> 0 | H29: =H7/'DATOS Iniciales y ACLARACIONES'!J$44*'DATOS Iniciales y ACLARACIONES'!J$41/2 -> 0 | I29: =I7/'DATOS Iniciales y ACLARACIONES'!K$44*'DATOS Iniciales y ACLARACIONES'!K$41/2 -> 0 | ... K29: =K7/'DATOS Iniciales y ACLARACIONES'!M$44*'DATOS Iniciales y ACLARACIONES'!M$41/2 -> 0
A30: Materiales | B30: =B8/'DATOS Iniciales y ACLARACIONES'!D$44*'DATOS Iniciales y ACLARACIONES'!D$41/2 -> 0 | C30: =C8/'DATOS Iniciales y ACLARACIONES'!E$44*'DATOS Iniciales y ACLARACIONES'!E$41/2 -> 0 | D30: =D8/'DATOS Iniciales y ACLARACIONES'!F$44*'DATOS Iniciales y ACLARACIONES'!F$41/2 -> 0 | E30: =E8/'DATOS Iniciales y ACLARACIONES'!G$44*'DATOS Iniciales y ACLARACIONES'!G$41/2 -> 0 | F30: =F8/'DATOS Iniciales y ACLARACIONES'!H$44*'DATOS Iniciales y ACLARACIONES'!H$41/2 -> 0 | G30: =G8/'DATOS Iniciales y ACLARACIONES'!I$44*'DATOS Iniciales y ACLARACIONES'!I$41/2 -> 0 | H30: =H8/'DATOS Iniciales y ACLARACIONES'!J$44*'DATOS Iniciales y ACLARACIONES'!J$41/2 -> 0 | I30: =I8/'DATOS Iniciales y ACLARACIONES'!K$44*'DATOS Iniciales y ACLARACIONES'!K$41/2 -> 0 | ... K30: =K8/'DATOS Iniciales y ACLARACIONES'!M$44*'DATOS Iniciales y ACLARACIONES'!M$41/2 -> 0
A31: Energía eléctrica | B31: =B9/'DATOS Iniciales y ACLARACIONES'!D$44*'DATOS Iniciales y ACLARACIONES'!D$41/2 -> 0 | C31: =C9/'DATOS Iniciales y ACLARACIONES'!E$44*'DATOS Iniciales y ACLARACIONES'!E$41/2 -> 0 | D31: =D9/'DATOS Iniciales y ACLARACIONES'!F$44*'DATOS Iniciales y ACLARACIONES'!F$41/2 -> 0 | E31: =E9/'DATOS Iniciales y ACLARACIONES'!G$44*'DATOS Iniciales y ACLARACIONES'!G$41/2 -> 0 | F31: =F9/'DATOS Iniciales y ACLARACIONES'!H$44*'DATOS Iniciales y ACLARACIONES'!H$41/2 -> 0 | G31: =G9/'DATOS Iniciales y ACLARACIONES'!I$44*'DATOS Iniciales y ACLARACIONES'!I$41/2 -> 0 | H31: =H9/'DATOS Iniciales y ACLARACIONES'!J$44*'DATOS Iniciales y ACLARACIONES'!J$41/2 -> 0 | I31: =I9/'DATOS Iniciales y ACLARACIONES'!K$44*'DATOS Iniciales y ACLARACIONES'!K$41/2 -> 0 | ... K31: =K9/'DATOS Iniciales y ACLARACIONES'!M$44*'DATOS Iniciales y ACLARACIONES'!M$41/2 -> 0
A32: Combustibles | B32: =B10/'DATOS Iniciales y ACLARACIONES'!D$44*'DATOS Iniciales y ACLARACIONES'!D$41/2 -> 0 | C32: =C10/'DATOS Iniciales y ACLARACIONES'!E$44*'DATOS Iniciales y ACLARACIONES'!E$41/2 -> 0 | D32: =D10/'DATOS Iniciales y ACLARACIONES'!F$44*'DATOS Iniciales y ACLARACIONES'!F$41/2 -> 0 | E32: =E10/'DATOS Iniciales y ACLARACIONES'!G$44*'DATOS Iniciales y ACLARACIONES'!G$41/2 -> 0 | F32: =F10/'DATOS Iniciales y ACLARACIONES'!H$44*'DATOS Iniciales y ACLARACIONES'!H$41/2 -> 0 | G32: =G10/'DATOS Iniciales y ACLARACIONES'!I$44*'DATOS Iniciales y ACLARACIONES'!I$41/2 -> 0 | H32: =H10/'DATOS Iniciales y ACLARACIONES'!J$44*'DATOS Iniciales y ACLARACIONES'!J$41/2 -> 0 | I32: =I10/'DATOS Iniciales y ACLARACIONES'!K$44*'DATOS Iniciales y ACLARACIONES'!K$41/2 -> 0 | ... K32: =K10/'DATOS Iniciales y ACLARACIONES'!M$44*'DATOS Iniciales y ACLARACIONES'!M$41/2 -> 0
A33: Tasas e impuestos | B33: =B11/'DATOS Iniciales y ACLARACIONES'!D$44*'DATOS Iniciales y ACLARACIONES'!D$41/2 -> 0 | C33: =C11/'DATOS Iniciales y ACLARACIONES'!E$44*'DATOS Iniciales y ACLARACIONES'!E$41/2 -> 0 | D33: =D11/'DATOS Iniciales y ACLARACIONES'!F$44*'DATOS Iniciales y ACLARACIONES'!F$41/2 -> 0 | E33: =E11/'DATOS Iniciales y ACLARACIONES'!G$44*'DATOS Iniciales y ACLARACIONES'!G$41/2 -> 0 | F33: =F11/'DATOS Iniciales y ACLARACIONES'!H$44*'DATOS Iniciales y ACLARACIONES'!H$41/2 -> 0 | G33: =G11/'DATOS Iniciales y ACLARACIONES'!I$44*'DATOS Iniciales y ACLARACIONES'!I$41/2 -> 0 | H33: =H11/'DATOS Iniciales y ACLARACIONES'!J$44*'DATOS Iniciales y ACLARACIONES'!J$41/2 -> 0 | I33: =I11/'DATOS Iniciales y ACLARACIONES'!K$44*'DATOS Iniciales y ACLARACIONES'!K$41/2 -> 0 | ... K33: =K11/'DATOS Iniciales y ACLARACIONES'!M$44*'DATOS Iniciales y ACLARACIONES'!M$41/2 -> 0
A34: Seguros | B34: =B12/'DATOS Iniciales y ACLARACIONES'!D$44*'DATOS Iniciales y ACLARACIONES'!D$41/2 -> 0 | C34: =C12/'DATOS Iniciales y ACLARACIONES'!E$44*'DATOS Iniciales y ACLARACIONES'!E$41/2 -> 0 | D34: =D12/'DATOS Iniciales y ACLARACIONES'!F$44*'DATOS Iniciales y ACLARACIONES'!F$41/2 -> 0 | E34: =E12/'DATOS Iniciales y ACLARACIONES'!G$44*'DATOS Iniciales y ACLARACIONES'!G$41/2 -> 0 | F34: =F12/'DATOS Iniciales y ACLARACIONES'!H$44*'DATOS Iniciales y ACLARACIONES'!H$41/2 -> 0 | G34: =G12/'DATOS Iniciales y ACLARACIONES'!I$44*'DATOS Iniciales y ACLARACIONES'!I$41/2 -> 0 | H34: =H12/'DATOS Iniciales y ACLARACIONES'!J$44*'DATOS Iniciales y ACLARACIONES'!J$41/2 -> 0 | I34: =I12/'DATOS Iniciales y ACLARACIONES'!K$44*'DATOS Iniciales y ACLARACIONES'!K$41/2 -> 0 | ... K34: =K12/'DATOS Iniciales y ACLARACIONES'!M$44*'DATOS Iniciales y ACLARACIONES'!M$41/2 -> 0
A35: Procesos y Servicios Tercerizados | B35: =B13/'DATOS Iniciales y ACLARACIONES'!D$44*'DATOS Iniciales y ACLARACIONES'!D$41/2 -> 0 | C35: =C13/'DATOS Iniciales y ACLARACIONES'!E$44*'DATOS Iniciales y ACLARACIONES'!E$41/2 -> 0 | D35: =D13/'DATOS Iniciales y ACLARACIONES'!F$44*'DATOS Iniciales y ACLARACIONES'!F$41/2 -> 0 | E35: =E13/'DATOS Iniciales y ACLARACIONES'!G$44*'DATOS Iniciales y ACLARACIONES'!G$41/2 -> 0 | F35: =F13/'DATOS Iniciales y ACLARACIONES'!H$44*'DATOS Iniciales y ACLARACIONES'!H$41/2 -> 0 | G35: =G13/'DATOS Iniciales y ACLARACIONES'!I$44*'DATOS Iniciales y ACLARACIONES'!I$41/2 -> 0 | H35: =H13/'DATOS Iniciales y ACLARACIONES'!J$44*'DATOS Iniciales y ACLARACIONES'!J$41/2 -> 0 | I35: =I13/'DATOS Iniciales y ACLARACIONES'!K$44*'DATOS Iniciales y ACLARACIONES'!K$41/2 -> 0 | ... K35: =K13/'DATOS Iniciales y ACLARACIONES'!M$44*'DATOS Iniciales y ACLARACIONES'!M$41/2 -> 0
A36: Regalias Patentes y Licencias | B36: =B14/'DATOS Iniciales y ACLARACIONES'!D$44*'DATOS Iniciales y ACLARACIONES'!D$41/2 -> 0 | C36: =C14/'DATOS Iniciales y ACLARACIONES'!E$44*'DATOS Iniciales y ACLARACIONES'!E$41/2 -> 0 | D36: =D14/'DATOS Iniciales y ACLARACIONES'!F$44*'DATOS Iniciales y ACLARACIONES'!F$41/2 -> 0 | E36: =E14/'DATOS Iniciales y ACLARACIONES'!G$44*'DATOS Iniciales y ACLARACIONES'!G$41/2 -> 0 | F36: =F14/'DATOS Iniciales y ACLARACIONES'!H$44*'DATOS Iniciales y ACLARACIONES'!H$41/2 -> 0 | G36: =G14/'DATOS Iniciales y ACLARACIONES'!I$44*'DATOS Iniciales y ACLARACIONES'!I$41/2 -> 0 | H36: =H14/'DATOS Iniciales y ACLARACIONES'!J$44*'DATOS Iniciales y ACLARACIONES'!J$41/2 -> 0 | I36: =I14/'DATOS Iniciales y ACLARACIONES'!K$44*'DATOS Iniciales y ACLARACIONES'!K$41/2 -> 0 | ... K36: =K14/'DATOS Iniciales y ACLARACIONES'!M$44*'DATOS Iniciales y ACLARACIONES'!M$41/2 -> 0
A37: Tratamiento de residuos | B37: =B15/'DATOS Iniciales y ACLARACIONES'!D$44*'DATOS Iniciales y ACLARACIONES'!D$41/2 -> 0 | C37: =C15/'DATOS Iniciales y ACLARACIONES'!E$44*'DATOS Iniciales y ACLARACIONES'!E$41/2 -> 0 | D37: =D15/'DATOS Iniciales y ACLARACIONES'!F$44*'DATOS Iniciales y ACLARACIONES'!F$41/2 -> 0 | E37: =E15/'DATOS Iniciales y ACLARACIONES'!G$44*'DATOS Iniciales y ACLARACIONES'!G$41/2 -> 0 | F37: =F15/'DATOS Iniciales y ACLARACIONES'!H$44*'DATOS Iniciales y ACLARACIONES'!H$41/2 -> 0 | G37: =G15/'DATOS Iniciales y ACLARACIONES'!I$44*'DATOS Iniciales y ACLARACIONES'!I$41/2 -> 0 | H37: =H15/'DATOS Iniciales y ACLARACIONES'!J$44*'DATOS Iniciales y ACLARACIONES'!J$41/2 -> 0 | I37: =I15/'DATOS Iniciales y ACLARACIONES'!K$44*'DATOS Iniciales y ACLARACIONES'!K$41/2 -> 0 | ... K37: =K15/'DATOS Iniciales y ACLARACIONES'!M$44*'DATOS Iniciales y ACLARACIONES'!M$41/2 -> 0
... A39: Imprevistos | B39: =B17/'DATOS Iniciales y ACLARACIONES'!D$44*'DATOS Iniciales y ACLARACIONES'!D$41/2 -> 0 | C39: =C17/'DATOS Iniciales y ACLARACIONES'!E$44*'DATOS Iniciales y ACLARACIONES'!E$41/2 -> 0 | D39: =D17/'DATOS Iniciales y ACLARACIONES'!F$44*'DATOS Iniciales y ACLARACIONES'!F$41/2 -> 0 | E39: =E17/'DATOS Iniciales y ACLARACIONES'!G$44*'DATOS Iniciales y ACLARACIONES'!G$41/2 -> 0 | F39: =F17/'DATOS Iniciales y ACLARACIONES'!H$44*'DATOS Iniciales y ACLARACIONES'!H$41/2 -> 0 | G39: =G17/'DATOS Iniciales y ACLARACIONES'!I$44*'DATOS Iniciales y ACLARACIONES'!I$41/2 -> 0 | H39: =H17/'DATOS Iniciales y ACLARACIONES'!J$44*'DATOS Iniciales y ACLARACIONES'!J$41/2 -> 0 | I39: =I17/'DATOS Iniciales y ACLARACIONES'!K$44*'DATOS Iniciales y ACLARACIONES'!K$41/2 -> 0 | ... K39: =K17/'DATOS Iniciales y ACLARACIONES'!M$44*'DATOS Iniciales y ACLARACIONES'!M$41/2 -> 0
A40: Total gastos a activar MCySE | B40: =SUM(B26:B39) -> 0 | C40: =SUM(C26:C39) -> 0 | D40: =SUM(D26:D39) -> 0 | E40: =SUM(E26:E39) -> 0 | F40: =SUM(F26:F39) -> 0 | G40: =SUM(G26:G39) -> 0 | H40: =SUM(H26:H39) -> 0 | I40: =SUM(I26:I39) -> 0 | ... K40: =SUM(K26:K39) -> 0
A41: Total de Gasto a Activar Gasto P. Marcha | B41: 4500
B43: Costo en el Area de Producción
B44: Año 1 | C44: Año 2 | D44: Año 3 | E44: Año 4 | F44: Año 5 | G44: Año 6 | H44: Año 7 | I44: Año 8 | J44: Año 9 | K44: Año 10
A45: Gastos Total de Producción | B45: =+B18 -> 1936025114 | C45: =+C18 -> 1936025080 | D45: =+D18 -> 1936025203 | E45: =+E18 -> 1936025080 | F45: =+F18 -> 1936025080 | G45: =+G18 -> 1926061923 | H45: =+H18 -> 1926058800 | I45: =+I18 -> 1926058800 | ... K45: =+K18 -> 1926058800
A46: Menos:
A47: Gasto de puesta en marcha | B47: =B41 -> 4500
A48: Variación Mercadería en proceso | B48: =B40 -> 0 | C48: =C40-B40 -> 0 | D48: =D40-C40 -> 0 | E48: =E40-D40 -> 0 | F48: =F40-E40 -> 0 | G48: =G40-F40 -> 0 | H48: =H40-G40 -> 0 | I48: =I40-H40 -> 0 | J48: =J40-I40 -> 0 | K48: =K40-J40 -> 0
A49: Costo de producción anual | B49: =+B45-B47-B48 -> 1936020614 | C49: =+C45-C47-C48 -> 1936025080 | D49: =+D45-D47-D48 -> 1936025203 | E49: =+E45-E47-E48 -> 1936025080 | F49: =+F45-F47-F48 -> 1936025080 | G49: =+G45-G47-G48 -> 1926061923 | H49: =+H45-H47-H48 -> 1926058800 | I49: =+I45-I47-I48 -> 1926058800 | ... K49: =+K45-K47-K48 -> 1926058800
A50: Costo de prod. Unitario Promedio
A52: *1 El gasto de Mercadería en Curso y Semielaborado se calcula asumiendo costos similares para la totalidad de las unidades producidas. En caso de esto no resultar razonable, deberá calcularse especificamente el valor en MCy SE para cada producto

Sheet CostoAdmComFin
B2: Gastos en el Area de Administración
A3: Rubros | B3: Año 1 | C3: Año 2 | D3: Año 3 | E3: Año 4 | F3: Año 5 | G3: Año 6 | H3: Año 7 | I3: Año 8 | J3: Año 9 | K3: Año 10 | L3: Tipo de Gasto
A4: Personal | B4: 507000000 | C4: 507000000 | D4: 507000000 | E4: 507000000 | F4: 507000000 | G4: 507000000 | H4: 507000000 | I4: 507000000 | J4: 507000000 | K4: 507000000 | L4: VARIABLE
A5: Amortizaciones de A. Fijo | B5: ='Inv AF'!E83 -> 12818000 | C5: ='Inv AF'!F83 -> 12818000 | D5: ='Inv AF'!G83 -> 12818000 | E5: ='Inv AF'!H83 -> 12818000 | F5: ='Inv AF'!I83 -> 12818000 | G5: ='Inv AF'!J83 -> 7980000 | H5: ='Inv AF'!K83 -> 7980000 | I5: ='Inv AF'!L83 -> 7980000 | ... K5: ='Inv AF'!N83 -> 7980000 | L5: FIJO
A6: Materiales | L6: FIJO
A7: Electricidad | L7: FIJO
A8: Combustible | L8: FIJO
A9: Sistema y Tecnologías de la Información | L9: FIJO
A10: Servicios Tercerizados
A11: Tasas e impuestos | L11: FIJO
A12: Seguros | L12: FIJO
A13: Imprevistos | B13: =SUM(B4:B12)*'DATOS Iniciales y ACLARACIONES'!$B$25 -> 15594540 | C13: =SUM(C4:C12)*'DATOS Iniciales y ACLARACIONES'!$B$25 -> 15594540 | D13: =SUM(D4:D12)*'DATOS Iniciales y ACLARACIONES'!$B$25 -> 15594540 | E13: =SUM(E4:E12)*'DATOS Iniciales y ACLARACIONES'!$B$25 -> 15594540 | F13: =SUM(F4:F12)*'DATOS Iniciales y ACLARACIONES'!$B$25 -> 15594540 | G13: =SUM(G4:G12)*'DATOS Iniciales y ACLARACIONES'!$B$25 -> 15449400 | H13: =SUM(H4:H12)*'DATOS Iniciales y ACLARACIONES'!$B$25 -> 15449400 | I13: =SUM(I4:I12)*'DATOS Iniciales y ACLARACIONES'!$B$25 -> 15449400 | ... K13: =SUM(K4:K12)*'DATOS Iniciales y ACLARACIONES'!$B$25 -> 15449400 | L13: VARIABLE
A15: Costo total de Admistración | B15: =SUM(B4:B13) -> 535412540 | C15: =SUM(C4:C13) -> 535412540 | D15: =SUM(D4:D13) -> 535412540 | E15: =SUM(E4:E13) -> 535412540 | F15: =SUM(F4:F13) -> 535412540 | G15: =SUM(G4:G13) -> 530429400 | H15: =SUM(H4:H13) -> 530429400 | I15: =SUM(I4:I13) -> 530429400 | ... K15: =SUM(K4:K13) -> 530429400
A17: % Costo Variable | B17: =SUMIF($L$4:$L$13,"VARIABLE",B4:B13) -> 522594540 | C17: =SUMIF($L$4:$L$13,"VARIABLE",C4:C13) -> 522594540 | D17: =SUMIF($L$4:$L$13,"VARIABLE",D4:D13) -> 522594540 | E17: =SUMIF($L$4:$L$13,"VARIABLE",E4:E13) -> 522594540 | F17: =SUMIF($L$4:$L$13,"VARIABLE",F4:F13) -> 522594540 | G17: =SUMIF($L$4:$L$13,"VARIABLE",G4:G13) -> 522449400 | H17: =SUMIF($L$4:$L$13,"VARIABLE",H4:H13) -> 522449400 | I17: =SUMIF($L$4:$L$13,"VARIABLE",I4:I13) -> 522449400 | ... K17: =SUMIF($L$4:$L$13,"VARIABLE",K4:K13) -> 522449400
A18: % Costo Constante | B18: =B15-B17 -> 12818000 | C18: =C15-C17 -> 12818000 | D18: =D15-D17 -> 12818000 | E18: =E15-E17 -> 12818000 | F18: =F15-F17 -> 12818000 | G18: =G15-G17 -> 7980000 | H18: =H15-H17 -> 7980000 | I18: =I15-I17 -> 7980000 | ... K18: =K15-K17 -> 7980000
B21: Gastos en el Area de Comercialización
A22: Rubros | B22: Año 1 | C22: Año 2 | D22: Año 3 | E22: Año 4 | F22: Año 5 | G22: Año 6 | H22: Año 7 | I22: Año 8 | J22: Año 9 | K22: Año 10 | L22: Tipo de Gasto
A23: Personal (Fijo) | B23: =(2*13*1.25*3000000)+(4*13*1.25*1200000) -> 175500000 | C23: =(2*13*1.25*3000000)+(4*13*1.25*1200000) -> 175500000 | D23: =(2*13*1.25*3000000)+(4*13*1.25*1200000) -> 175500000 | E23: =(2*13*1.25*3000000)+(4*13*1.25*1200000) -> 175500000 | F23: =(2*13*1.25*3000000)+(4*13*1.25*1200000) -> 175500000 | G23: =(2*13*1.25*3000000)+(4*13*1.25*1200000) -> 175500000 | H23: =(2*13*1.25*3000000)+(4*13*1.25*1200000) -> 175500000 | I23: =(2*13*1.25*3000000)+(4*13*1.25*1200000) -> 175500000 | ... K23: =(2*13*1.25*3000000)+(4*13*1.25*1200000) -> 175500000 | L23: FIJO
A24: Amortizaciones de A. Fijo | B24: ='Inv AF'!E82 -> 25636000 | C24: ='Inv AF'!F82 -> 25636000 | D24: ='Inv AF'!G82 -> 25636000 | E24: ='Inv AF'!H82 -> 25636000 | F24: ='Inv AF'!I82 -> 25636000 | G24: ='Inv AF'!J82 -> 15960000 | H24: ='Inv AF'!K82 -> 15960000 | I24: ='Inv AF'!L82 -> 15960000 | ... K24: ='Inv AF'!N82 -> 15960000 | L24: FIJO
A25: Comisiones por Ventas | B25: ='CTV y CResult'!B13*0.15 -> 595980000 | C25: ='CTV y CResult'!C13*0.15 -> 681030000 | D25: ='CTV y CResult'!D13*0.15 -> 709380000 | E25: ='CTV y CResult'!E13*0.15 -> 739935000 | F25: ='CTV y CResult'!F13*0.15 -> 775215000 | G25: ='CTV y CResult'!G13*0.15 -> 811755000 | H25: ='CTV y CResult'!H13*0.15 -> 850500000 | I25: ='CTV y CResult'!I13*0.15 -> 890820000 | ... K25: ='CTV y CResult'!K13*0.15 -> 976815000 | L25: VARIABLE
A26: Promoción y Publicidad | B26: =9600000+3*1300000 + 7920000 + 2820000 -> 24240000 | C26: =800000+7920000 + 2820000 -> 11540000 | D26: =800000+7920000 + 2820000 -> 11540000 | E26: =800000+7920000 + 2820000 -> 11540000 | F26: =800000+7920000 + 2820000 -> 11540000 | G26: =800000+7920000 + 2820000 -> 11540000 | H26: =800000+7920000 + 2820000 -> 11540000 | I26: =800000+7920000 + 2820000 -> 11540000 | J26: =800000+7920000 + 2820000 -> 11540000 | K26: =800000+7920000 + 2820000 -> 11540000 | L26: FIJO
A27: Servicio Técnico y Postventa | L27: FIJO
A28: Tasas e impuestos | L28: FIJO
A29: Logística y Combustibles | L29: FIJO
A30: Energía Eléctrica | L30: FIJO
A31: Seguros | L31: FIJO
A32: Servicios Tercerizados | L32: FIJO
A33: Imprevistos | B33: =SUM(B23:B32)*'DATOS Iniciales y ACLARACIONES'!$B$25 -> 24640680 | C33: =SUM(C23:C32)*'DATOS Iniciales y ACLARACIONES'!$B$25 -> 26811180 | D33: =SUM(D23:D32)*'DATOS Iniciales y ACLARACIONES'!$B$25 -> 27661680 | E33: =SUM(E23:E32)*'DATOS Iniciales y ACLARACIONES'!$B$25 -> 28578330 | F33: =SUM(F23:F32)*'DATOS Iniciales y ACLARACIONES'!$B$25 -> 29636730 | G33: =SUM(G23:G32)*'DATOS Iniciales y ACLARACIONES'!$B$25 -> 30442650 | H33: =SUM(H23:H32)*'DATOS Iniciales y ACLARACIONES'!$B$25 -> 31605000 | I33: =SUM(I23:I32)*'DATOS Iniciales y ACLARACIONES'!$B$25 -> 32814600 | ... K33: =SUM(K23:K32)*'DATOS Iniciales y ACLARACIONES'!$B$25 -> 35394450 | L33: FIJO
A35: Costo total de Comercialización | B35: =SUM(B23:B33) -> 845996680 | C35: =SUM(C23:C33) -> 920517180 | D35: =SUM(D23:D33) -> 949717680 | E35: =SUM(E23:E33) -> 981189330 | F35: =SUM(F23:F33) -> 1017527730 | G35: =SUM(G23:G33) -> 1045197650 | H35: =SUM(H23:H33) -> 1085105000 | I35: =SUM(I23:I33) -> 1126634600 | ... K35: =SUM(K23:K33) -> 1215209450
A37: % Costo Variable | B37: =SUMIF($L$23:$L$33,"VARIABLE",B23:B33) -> 595980000 | C37: =SUMIF($L$23:$L$33,"VARIABLE",C23:C33) -> 681030000 | D37: =SUMIF($L$23:$L$33,"VARIABLE",D23:D33) -> 709380000 | E37: =SUMIF($L$23:$L$33,"VARIABLE",E23:E33) -> 739935000 | F37: =SUMIF($L$23:$L$33,"VARIABLE",F23:F33) -> 775215000 | G37: =SUMIF($L$23:$L$33,"VARIABLE",G23:G33) -> 811755000 | H37: =SUMIF($L$23:$L$33,"VARIABLE",H23:H33) -> 850500000 | I37: =SUMIF($L$23:$L$33,"VARIABLE",I23:I33) -> 890820000 | ... K37: =SUMIF($L$23:$L$33,"VARIABLE",K23:K33) -> 976815000
A38: % Costo Constante | B38: =B35-B37 -> 250016680 | C38: =C35-C37 -> 239487180 | D38: =D35-D37 -> 240337680 | E38: =E35-E37 -> 241254330 | F38: =F35-F37 -> 242312730 | G38: =G35-G37 -> 233442650 | H38: =H35-H37 -> 234605000 | I38: =I35-I37 -> 235814600 | ... K38: =K35-K37 -> 238394450
B40: Gastos en el Area de Financiera
A41: Rubros | B41: Año 1 | C41: Año 2 | D41: Año 3 | E41: Año 4 | F41: Año 5 | G41: Año 6 | H41: Año 7 | I41: Año 8 | J41: Año 9 | K41: Año 10
A42: Intereses Devengados año a año
A43: Alicuotas de Amortización de IGPO | B43: ='Inv AF'!E84 -> 0 | C43: ='Inv AF'!F84 -> 0 | D43: ='Inv AF'!G84 -> 0 | E43: ='Inv AF'!H84 -> 0 | F43: ='Inv AF'!I84 -> 0 | G43: ='Inv AF'!J84 -> 0 | H43: ='Inv AF'!K84 -> 0 | I43: ='Inv AF'!L84 -> 0 | ... K43: ='Inv AF'!N84 -> 0
A44: Gastos Bancarios Año a Año
A45: Gastos de la Oficina Financiera
A46: Costo total Financiero | B46: =SUM(B42:B45) -> 0 | C46: =SUM(C42:C45) -> 0 | D46: =SUM(D42:D45) -> 0 | E46: =SUM(E42:E45) -> 0 | F46: =SUM(F42:F45) -> 0 | G46: =SUM(G42:G45) -> 0 | H46: =SUM(H42:H45) -> 0 | I46: =SUM(I42:I45) -> 0 | ... K46: =SUM(K42:K45) -> 0
A48: % Costo Constante | B48: 1 | C48: 1 | D48: 1 | E48: 1 | F48: 1 | G48: 1 | H48: 1 | I48: 1 | J48: 1 | K48: 1

Sheet CTV y CResult
B1: =B4*1000 -> 1892000000 | C1: =C4*1000 -> 2162000000 | D1: =D4*1000 -> 2252000000 | E1: =E4*1000 -> 2349000000 | F1: =F4*1000 -> 2461000000 | G1: =G4*1000 -> 2577000000 | H1: =H4*1000 -> 2700000000 | I1: =I4*1000 -> 2828000000 | ... K1: =K4*1000 -> 3101000000
A2: COSTO TOTAL de lo VENDIDO
B3: Año 1 | C3: Año 2 | D3: Año 3 | E3: Año 4 | F3: Año 5 | G3: Año 6 | H3: Año 7 | I3: Año 8 | J3: Año 9 | K3: Año 10
A4: Venta anual, en Unidades Producto 1 | B4: 1892000 | C4: 2162000 | D4: 2252000 | E4: 2349000 | F4: 2461000 | G4: 2577000 | H4: 2700000 | I4: 2828000 | J4: 2961000 | K4: 3101000
A5: Precio de venta Producto 1 | B5: 2100 | C5: 2100 | D5: 2100 | E5: 2100 | F5: 2100 | G5: 2100 | H5: 2100 | I5: 2100 | J5: 2100 | K5: 2100
A6: Venta anual, en Unidades Producto 2
A7: Precio de venta Producto 2
A8: Venta anual, en Unidades Producto 3
A9: Precio de venta Producto 3
A10: Venta anual, en Unidades Producto 4
A11: Precio de venta Producto 4
A12: Otros Ingresos Ordinarios (en $)
A13: VENTAS ANUALES | B13: =+B4*B5+B6*B7+B8*B9+B10*B11+B12 -> 3973200000 | C13: =+C4*C5+C6*C7+C8*C9+C10*C11+C12 -> 4540200000 | D13: =+D4*D5+D6*D7+D8*D9+D10*D11+D12 -> 4729200000 | E13: =+E4*E5+E6*E7+E8*E9+E10*E11+E12 -> 4932900000 | F13: =+F4*F5+F6*F7+F8*F9+F10*F11+F12 -> 5168100000 | G13: =+G4*G5+G6*G7+G8*G9+G10*G11+G12 -> 5411700000 | H13: =+H4*H5+H6*H7+H8*H9+H10*H11+H12 -> 5670000000 | I13: =+I4*I5+I6*I7+I8*I9+I10*I11+I12 -> 5938800000 | ... K13: =+K4*K5+K6*K7+K8*K9+K10*K11+K12 -> 6512100000
A15: Consumo de materia prima | B15: =CostoPROD!B4 -> 1004000000 | C15: =CostoPROD!C4 -> 1004000000 | D15: =CostoPROD!D4 -> 1004000000 | E15: =CostoPROD!E4 -> 1004000000 | F15: =CostoPROD!F4 -> 1004000000 | G15: =CostoPROD!G4 -> 1004000000 | H15: =CostoPROD!H4 -> 1004000000 | I15: =CostoPROD!I4 -> 1004000000 | ... K15: =CostoPROD!K4 -> 1004000000
A16: Mano de obra directa | B16: =CostoPROD!B5 -> 850000000 | C16: =CostoPROD!C5 -> 850000000 | D16: =CostoPROD!D5 -> 850000000 | E16: =CostoPROD!E5 -> 850000000 | F16: =CostoPROD!F5 -> 850000000 | G16: =CostoPROD!G5 -> 850000000 | H16: =CostoPROD!H5 -> 850000000 | I16: =CostoPROD!I5 -> 850000000 | ... K16: =CostoPROD!K5 -> 850000000
A17: Gastos de fabricación | B17: =CostoPROD!B18-CostoPROD!B4-CostoPROD!B5 -> 82025114 | C17: =CostoPROD!C18-CostoPROD!C4-CostoPROD!C5 -> 82025080 | D17: =CostoPROD!D18-CostoPROD!D4-CostoPROD!D5 -> 82025203 | E17: =CostoPROD!E18-CostoPROD!E4-CostoPROD!E5 -> 82025080 | F17: =CostoPROD!F18-CostoPROD!F4-CostoPROD!F5 -> 82025080 | G17: =CostoPROD!G18-CostoPROD!G4-CostoPROD!G5 -> 72061923 | H17: =CostoPROD!H18-CostoPROD!H4-CostoPROD!H5 -> 72058800 | I17: =CostoPROD!I18-CostoPROD!I4-CostoPROD!I5 -> 72058800 | ... K17: =CostoPROD!K18-CostoPROD!K4-CostoPROD!K5 -> 72058800
A18: Gastos de Producción | B18: =SUM(B15:B17) -> 1936025114 | C18: =SUM(C15:C17) -> 1936025080 | D18: =SUM(D15:D17) -> 1936025203 | E18: =SUM(E15:E17) -> 1936025080 | F18: =SUM(F15:F17) -> 1936025080 | G18: =SUM(G15:G17) -> 1926061923 | H18: =SUM(H15:H17) -> 1926058800 | I18: =SUM(I15:I17) -> 1926058800 | ... K18: =SUM(K15:K17) -> 1926058800
A20: (-) Puesta en marcha | B20: =CostoPROD!B41 -> 4500 | C20: =CostoPROD!C41 | D20: =CostoPROD!D41 | E20: =CostoPROD!E41 | F20: =CostoPROD!F41 | G20: =CostoPROD!G41 | H20: =CostoPROD!H41 | I20: =CostoPROD!I41 | ... K20: =CostoPROD!K41
A21: (-) Variación Mercadería en proceso | B21: =CostoPROD!B48 -> 0 | C21: =CostoPROD!C48 -> 0 | D21: =CostoPROD!D48 -> 0 | E21: =CostoPROD!E48 -> 0 | F21: =CostoPROD!F48 -> 0 | G21: =CostoPROD!G48 -> 0 | H21: =CostoPROD!H48 -> 0 | I21: =CostoPROD!I48 -> 0 | ... K21: =CostoPROD!K48 -> 0
A22: COSTO DE PRODUCCION ANUAL | B22: =+B18-B20-B21 -> 1936020614 | C22: =+C18-C20-C21 -> 1936025080 | D22: =+D18-D20-D21 -> 1936025203 | E22: =+E18-E20-E21 -> 1936025080 | F22: =+F18-F20-F21 -> 1936025080 | G22: =+G18-G20-G21 -> 1926061923 | H22: =+H18-H20-H21 -> 1926058800 | I22: =+I18-I20-I21 -> 1926058800 | ... K22: =+K18-K20-K21 -> 1926058800
A23: Producción anual en Unidades Equivalentes | B23: =+B4+B6+B8+B10 -> 1892000 | C23: =+C4+C6+C8+C10 -> 2162000 | D23: =+D4+D6+D8+D10 -> 2252000 | E23: =+E4+E6+E8+E10 -> 2349000 | F23: =+F4+F6+F8+F10 -> 2461000 | G23: =+G4+G6+G8+G10 -> 2577000 | H23: =+H4+H6+H8+H10 -> 2700000 | I23: =+I4+I6+I8+I10 -> 2828000 | ... K23: =+K4+K6+K8+K10 -> 3101000
A24: Costo de producción unitario Promedio Equiv | B24: =B22/B23 -> 1023.2667 | C24: =C22/C23 -> 895.47876 | D24: =D22/D23 -> 859.69148 | E24: =E22/E23 -> 824.19118 | F24: =F22/F23 -> 786.68228 | G24: =G22/G23 -> 747.4047 | H24: =H22/H23 -> 713.35511 | I24: =I22/I23 -> 681.06747 | ... K24: =K22/K23 -> 621.10893
A25: Stock de Elaborados Valorizado | B25: =B24*'DATOS Iniciales y ACLARACIONES'!D42 -> 0 | C25: =C24*'DATOS Iniciales y ACLARACIONES'!E42 -> 0 | D25: =D24*'DATOS Iniciales y ACLARACIONES'!F42 -> 0 | E25: =E24*'DATOS Iniciales y ACLARACIONES'!G42 -> 0 | F25: =F24*'DATOS Iniciales y ACLARACIONES'!H42 -> 0 | G25: =G24*'DATOS Iniciales y ACLARACIONES'!I42 -> 0 | H25: =H24*'DATOS Iniciales y ACLARACIONES'!J42 -> 0 | I25: =I24*'DATOS Iniciales y ACLARACIONES'!K42 -> 0 | ... K25: =K24*'DATOS Iniciales y ACLARACIONES'!M42 -> 0
A27: (-) Variación de Stock de Elaborado | B27: =B25 -> 0 | C27: =C25-B25 -> 0 | D27: =D25-C25 -> 0 | E27: =E25-D25 -> 0 | F27: =F25-E25 -> 0 | G27: =G25-F25 -> 0 | H27: =H25-G25 -> 0 | I27: =I25-H25 -> 0 | J27: =J25-I25 -> 0 | K27: =K25-J25 -> 0
A28: COSTO DE PRODUCCION DE LO VENDIDO | B28: =+B22-B27 -> 1936020614 | C28: =+C22-C27 -> 1936025080 | D28: =+D22-D27 -> 1936025203 | E28: =+E22-E27 -> 1936025080 | F28: =+F22-F27 -> 1936025080 | G28: =+G22-G27 -> 1926061923 | H28: =+H22-H27 -> 1926058800 | I28: =+I22-I27 -> 1926058800 | ... K28: =+K22-K27 -> 1926058800
A29: GASTO DE ADMINISTRACION | B29: =CostoAdmComFin!B15 -> 535412540 | C29: =CostoAdmComFin!C15 -> 535412540 | D29: =CostoAdmComFin!D15 -> 535412540 | E29: =CostoAdmComFin!E15 -> 535412540 | F29: =CostoAdmComFin!F15 -> 535412540 | G29: =CostoAdmComFin!G15 -> 530429400 | H29: =CostoAdmComFin!H15 -> 530429400 | I29: =CostoAdmComFin!I15 -> 530429400 | ... K29: =CostoAdmComFin!K15 -> 530429400
A30: GASTO DE COMERCIALIZACION | B30: =CostoAdmComFin!B35 -> 845996680 | C30: =CostoAdmComFin!C35 -> 920517180 | D30: =CostoAdmComFin!D35 -> 949717680 | E30: =CostoAdmComFin!E35 -> 981189330 | F30: =CostoAdmComFin!F35 -> 1017527730 | G30: =CostoAdmComFin!G35 -> 1045197650 | H30: =CostoAdmComFin!H35 -> 1085105000 | I30: =CostoAdmComFin!I35 -> 1126634600 | ... K30: =CostoAdmComFin!K35 -> 1215209450
A31: GASTO DE FINANCIACION | B31: =CostoAdmComFin!B46 -> 0 | C31: =CostoAdmComFin!C46 -> 0 | D31: =CostoAdmComFin!D46 -> 0 | E31: =CostoAdmComFin!E46 -> 0 | F31: =CostoAdmComFin!F46 -> 0 | G31: =CostoAdmComFin!G46 -> 0 | H31: =CostoAdmComFin!H46 -> 0 | I31: =CostoAdmComFin!I46 -> 0 | ... K31: =CostoAdmComFin!K46 -> 0
A32: COSTO ANUAL DE LO VENDIDO | B32: =+B28+B29+B30 -> 3317429834 | C32: =+C28+C29+C30 -> 3391954800 | D32: =+D28+D29+D30 -> 3421155423 | E32: =+E28+E29+E30 -> 3452626950 | F32: =+F28+F29+F30 -> 3488965350 | G32: =+G28+G29+G30 -> 3501688973 | H32: =+H28+H29+H30 -> 3541593200 | I32: =+I28+I29+I30 -> 3583122800 | ... K32: =+K28+K29+K30 -> 3671697650
A34: Costo total unitario promedio | B34: =B32/(B10+B4+B6+B8) -> 1753.3984 | C34: =C32/(C10+C4+C6+C8) -> 1568.8968 | D34: =D32/(D10+D4+D6+D8) -> 1519.1632 | E34: =E32/(E10+E4+E6+E8) -> 1469.8284 | F34: =F32/(F10+F4+F6+F8) -> 1417.7023 | G34: =G32/(G10+G4+G6+G8) -> 1358.8238 | H34: =H32/(H10+H4+H6+H8) -> 1311.7012 | I34: =I32/(I10+I4+I6+I8) -> 1267.0165 | ... K34: =K32/(K10+K4+K6+K8) -> 1184.0366
A36: UTILIDAD (a/H. D. e Impuesto) | B36: =+B13-B32 -> 655770166 | C36: =+C13-C32 -> 1148245200 | D36: =+D13-D32 -> 1308044577 | E36: =+E13-E32 -> 1480273050 | F36: =+F13-F32 -> 1679134650 | G36: =+G13-G32 -> 1910011027 | H36: =+H13-H32 -> 2128406800 | I36: =+I13-I32 -> 2355677200 | ... K36: =+K13-K32 -> 2840402350
A37: Honorarios al Directorio | B37: =IF('DATOS Iniciales y ACLARACIONES'!$C$20="FIJO",'DATOS Iniciales y ACLARACIONES'!$B$20,'DATOS Iniciales y ACLARACIONES'!$B$20*'CTV y CResult'!B36) -> 32788508 | C37: =IF('DATOS Iniciales y ACLARACIONES'!$C$20="FIJO",'DATOS Iniciales y ACLARACIONES'!$B$20,'DATOS Iniciales y ACLARACIONES'!$B$20*'CTV y CResult'!C36) -> 57412260 | D37: =IF('DATOS Iniciales y ACLARACIONES'!$C$20="FIJO",'DATOS Iniciales y ACLARACIONES'!$B$20,'DATOS Iniciales y ACLARACIONES'!$B$20*'CTV y CResult'!D36) -> 65402229 | E37: =IF('DATOS Iniciales y ACLARACIONES'!$C$20="FIJO",'DATOS Iniciales y ACLARACIONES'!$B$20,'DATOS Iniciales y ACLARACIONES'!$B$20*'CTV y CResult'!E36) -> 74013652 | F37: =IF('DATOS Iniciales y ACLARACIONES'!$C$20="FIJO",'DATOS Iniciales y ACLARACIONES'!$B$20,'DATOS Iniciales y ACLARACIONES'!$B$20*'CTV y CResult'!F36) -> 83956732 | G37: =IF('DATOS Iniciales y ACLARACIONES'!$C$20="FIJO",'DATOS Iniciales y ACLARACIONES'!$B$20,'DATOS Iniciales y ACLARACIONES'!$B$20*'CTV y CResult'!G36) -> 95500551 | H37: =IF('DATOS Iniciales y ACLARACIONES'!$C$20="FIJO",'DATOS Iniciales y ACLARACIONES'!$B$20,'DATOS Iniciales y ACLARACIONES'!$B$20*'CTV y CResult'!H36) -> 106420340 | I37: =IF('DATOS Iniciales y ACLARACIONES'!$C$20="FIJO",'DATOS Iniciales y ACLARACIONES'!$B$20,'DATOS Iniciales y ACLARACIONES'!$B$20*'CTV y CResult'!I36) -> 117783860 | ... K37: =IF('DATOS Iniciales y ACLARACIONES'!$C$20="FIJO",'DATOS Iniciales y ACLARACIONES'!$B$20,'DATOS Iniciales y ACLARACIONES'!$B$20*'CTV y CResult'!K36) -> 1.4202012e+08
A38: Impuesto a la ganancia | B38: =(B36-B37)*'DATOS Iniciales y ACLARACIONES'!$B$19 -> 2.1804358e+08 | C38: =(C36-C37)*'DATOS Iniciales y ACLARACIONES'!$B$19 -> 381791529 | D38: =(D36-D37)*'DATOS Iniciales y ACLARACIONES'!$B$19 -> 4.3492482e+08 | E38: =(E36-E37)*'DATOS Iniciales y ACLARACIONES'!$B$19 -> 4.9219079e+08 | F38: =(F36-F37)*'DATOS Iniciales y ACLARACIONES'!$B$19 -> 5.5831227e+08 | G38: =(G36-G37)*'DATOS Iniciales y ACLARACIONES'!$B$19 -> 6.3507867e+08 | H38: =(H36-H37)*'DATOS Iniciales y ACLARACIONES'!$B$19 -> 707695261 | I38: =(I36-I37)*'DATOS Iniciales y ACLARACIONES'!$B$19 -> 783262669 | ... K38: =(K36-K37)*'DATOS Iniciales y ACLARACIONES'!$B$19 -> 9.4443378e+08
A40: UTILIDAD (d/H.D. e Impuesto) | B40: =B36-B37-B38 -> 4.0493808e+08 | C40: =C36-C37-C38 -> 709041411 | D40: =D36-D37-D38 -> 8.0771753e+08 | E40: =E36-E37-E38 -> 9.1406861e+08 | F40: =F36-F37-F38 -> 1036865646 | G40: =G36-G37-G38 -> 1179431809 | H40: =H36-H37-H38 -> 1314291199 | I40: =I36-I37-I38 -> 1454630671 | ... K40: =K36-K37-K38 -> 1753948451
A41: % sobre VENTAS | B41: =+B40/B13 -> 0.10191737 | C41: =+C40/C13 -> 0.15616964 | D41: =+D40/D13 -> 0.17079369 | E41: =+E40/E13 -> 0.18530045 | F41: =+F40/F13 -> 0.20062802 | G41: =+G40/G13 -> 0.21794109 | H41: =+H40/H13 -> 0.23179739 | I41: =+I40/I13 -> 0.2449368 | ... K41: =+K40/K13 -> 0.26933684
A43: FONDOS AUTOGENERADOS | B43: =+B44+B45 -> 4.6902808e+08 | C43: =+C44+C45 -> 773131411 | D43: =+D44+D45 -> 8.7180753e+08 | E43: =+E44+E45 -> 9.7815861e+08 | F43: =+F44+F45 -> 1100955646 | G43: =+G44+G45 -> 1219331809 | H43: =+H44+H45 -> 1354191199 | I43: =+I44+I45 -> 1494530671 | ... K43: =+K44+K45 -> 1793848451
A44: Utilidad Económica (d/H.D. e Impuesto) | B44: =+B40 -> 4.0493808e+08 | C44: =+C40 -> 709041411 | D44: =+D40 -> 8.0771753e+08 | E44: =+E40 -> 9.1406861e+08 | F44: =+F40 -> 1036865646 | G44: =+G40 -> 1179431809 | H44: =+H40 -> 1314291199 | I44: =+I40 -> 1454630671 | ... K44: =+K40 -> 1753948451
A45: Amortización anual | B45: =+'Inv AF'!E80 -> 64090000 | C45: =+'Inv AF'!F80 -> 64090000 | D45: =+'Inv AF'!G80 -> 64090000 | E45: =+'Inv AF'!H80 -> 64090000 | F45: =+'Inv AF'!I80 -> 64090000 | G45: =+'Inv AF'!J80 -> 39900000 | H45: =+'Inv AF'!K80 -> 39900000 | I45: =+'Inv AF'!L80 -> 39900000 | ... K45: =+'Inv AF'!N80 -> 39900000
A47: Costo Variable | B47: =CostoPROD!B20+CostoAdmComFin!B17+CostoAdmComFin!B37 -> 1118574540 | C47: =CostoPROD!C20+CostoAdmComFin!C17+CostoAdmComFin!C37 -> 1203624540 | D47: =CostoPROD!D20+CostoAdmComFin!D17+CostoAdmComFin!D37 -> 1231974540 | E47: =CostoPROD!E20+CostoAdmComFin!E17+CostoAdmComFin!E37 -> 1262529540 | F47: =CostoPROD!F20+CostoAdmComFin!F17+CostoAdmComFin!F37 -> 1297809540 | G47: =CostoPROD!G20+CostoAdmComFin!G17+CostoAdmComFin!G37 -> 1334204400 | H47: =CostoPROD!H20+CostoAdmComFin!H17+CostoAdmComFin!H37 -> 1372949400 | I47: =CostoPROD!I20+CostoAdmComFin!I17+CostoAdmComFin!I37 -> 1413269400 | ... K47: =CostoPROD!K20+CostoAdmComFin!K17+CostoAdmComFin!K37 -> 1499264400
A48: Costo Constante | B48: =CostoPROD!B21+CostoAdmComFin!B18+CostoAdmComFin!B38+CostoAdmComFin!B48 -> 2198859795 | C48: =CostoPROD!C21+CostoAdmComFin!C18+CostoAdmComFin!C38+CostoAdmComFin!C48 -> 2188330261 | D48: =CostoPROD!D21+CostoAdmComFin!D18+CostoAdmComFin!D38+CostoAdmComFin!D48 -> 2189180884 | E48: =CostoPROD!E21+CostoAdmComFin!E18+CostoAdmComFin!E38+CostoAdmComFin!E48 -> 2190097411 | F48: =CostoPROD!F21+CostoAdmComFin!F18+CostoAdmComFin!F38+CostoAdmComFin!F48 -> 2191155811 | G48: =CostoPROD!G21+CostoAdmComFin!G18+CostoAdmComFin!G38+CostoAdmComFin!G48 -> 2167484574 | H48: =CostoPROD!H21+CostoAdmComFin!H18+CostoAdmComFin!H38+CostoAdmComFin!H48 -> 2168643801 | I48: =CostoPROD!I21+CostoAdmComFin!I18+CostoAdmComFin!I38+CostoAdmComFin!I48 -> 2169853401 | ... K48: =CostoPROD!K21+CostoAdmComFin!K18+CostoAdmComFin!K38+CostoAdmComFin!K48 -> 2172433251
A49: UTILIDAD MARGINAL | B49: =+B13-B47 -> 2854625460 | C49: =+C13-C47 -> 3336575460 | D49: =+D13-D47 -> 3497225460 | E49: =+E13-E47 -> 3670370460 | F49: =+F13-F47 -> 3870290460 | G49: =+G13-G47 -> 4077495600 | H49: =+H13-H47 -> 4297050600 | I49: =+I13-I47 -> 4525530600 | ... K49: =+K13-K47 -> 5012835600
A50: PUNTO DE EQUILIBRIO | B50: =B48/B49 -> 0.77027961 | C50: =C48/C49 -> 0.65586116 | D50: =D48/D49 -> 0.62597648 | E50: =E48/E49 -> 0.59669656 | F50: =F48/F49 -> 0.56614764 | G50: =G48/G49 -> 0.53157251 | H50: =H48/H49 -> 0.50468193 | I50: =I48/I49 -> 0.47946939 | ... K50: =K48/K49 -> 0.43337413
A52: CUADRO DE RESULTADOS PROFORMA
A53: Rubros | B53: Año 1 | C53: Año 2 | D53: Año 3 | E53: Año 4 | F53: Año 5 | G53: Año 6 | H53: Año 7 | I53: Año 8 | J53: Año 9 | K53: Año 10 | L53: Totales
A54: Ventas netas (Ingresos Ordinarios) | B54: =B13 -> 3973200000 | C54: =C13 -> 4540200000 | D54: =D13 -> 4729200000 | E54: =E13 -> 4932900000 | F54: =F13 -> 5168100000 | G54: =G13 -> 5411700000 | H54: =H13 -> 5670000000 | I54: =I13 -> 5938800000 | ... K54: =K13 -> 6512100000 | L54: =SUM(B54:K54) -> 53094300000
A55: (-) Costo de producción de lo Vendido | B55: =B28 -> 1936020614 | C55: =C28 -> 1936025080 | D55: =D28 -> 1936025203 | E55: =E28 -> 1936025080 | F55: =F28 -> 1936025080 | G55: =G28 -> 1926061923 | H55: =H28 -> 1926058800 | I55: =I28 -> 1926058800 | ... K55: =K28 -> 1926058800 | L55: =SUM(B55:K55) -> 19310418180
A56: Resultado operativo | B56: =B54-B55 -> 2037179386 | C56: =C54-C55 -> 2604174920 | D56: =D54-D55 -> 2793174797 | E56: =E54-E55 -> 2996874920 | F56: =F54-F55 -> 3232074920 | G56: =G54-G55 -> 3485638077 | H56: =H54-H55 -> 3743941200 | I56: =I54-I55 -> 4012741200 | ... K56: =K54-K55 -> 4586041200 | L56: =SUM(B56:K56) -> 33783881820
A58: (-) Gastos de Administración | B58: =B29 -> 535412540 | C58: =C29 -> 535412540 | D58: =D29 -> 535412540 | E58: =E29 -> 535412540 | F58: =F29 -> 535412540 | G58: =G29 -> 530429400 | H58: =H29 -> 530429400 | I58: =I29 -> 530429400 | ... K58: =K29 -> 530429400 | L58: =SUM(B58:K58) -> 5329209700
A59: (-) Gastos de Comercialización | B59: =B30 -> 845996680 | C59: =C30 -> 920517180 | D59: =D30 -> 949717680 | E59: =E30 -> 981189330 | F59: =F30 -> 1017527730 | G59: =G30 -> 1045197650 | H59: =H30 -> 1085105000 | I59: =I30 -> 1126634600 | ... K59: =K30 -> 1215209450 | L59: =SUM(B59:K59) -> 10356881750
A60: (-) Gastos Financieros | B60: =B31 -> 0 | C60: =C31 -> 0 | D60: =D31 -> 0 | E60: =E31 -> 0 | F60: =F31 -> 0 | G60: =G31 -> 0 | H60: =H31 -> 0 | I60: =I31 -> 0 | ... K60: =K31 -> 0 | L60: =SUM(B60:K60) -> 0
A61: RESULTADO (a/Hon. e Imp.) | B61: =B56-B58-B59-B60 -> 655770166 | C61: =C56-C58-C59-C60 -> 1148245200 | D61: =D56-D58-D59-D60 -> 1308044577 | E61: =E56-E58-E59-E60 -> 1480273050 | F61: =F56-F58-F59-F60 -> 1679134650 | G61: =G56-G58-G59-G60 -> 1910011027 | H61: =H56-H58-H59-H60 -> 2128406800 | I61: =I56-I58-I59-I60 -> 2355677200 | ... L61: =L56-L58-L59-L60 -> 18097790370
A62: Menos: Honorarios al Direct. | B62: =B37 -> 32788508 | C62: =C37 -> 57412260 | D62: =D37 -> 65402229 | E62: =E37 -> 74013652 | F62: =F37 -> 83956732 | G62: =G37 -> 95500551 | H62: =H37 -> 106420340 | I62: =I37 -> 117783860 | ... K62: =K37 -> 1.4202012e+08 | L62: =SUM(B62:K62) -> 9.0488952e+08
A63: Menos: Impuesto a la Ganancia | B63: =B38 -> 2.1804358e+08 | C63: =C38 -> 381791529 | D63: =D38 -> 4.3492482e+08 | E63: =E38 -> 4.9219079e+08 | F63: =F38 -> 5.5831227e+08 | G63: =G38 -> 6.3507867e+08 | H63: =H38 -> 707695261 | I63: =I38 -> 783262669 | ... K63: =K38 -> 9.4443378e+08 | L63: =SUM(B63:K63) -> 6017515298
A64: RESULTADO (d/Hon. e Imp.) | B64: =B61-B62-B63 -> 4.0493808e+08 | C64: =C61-C62-C63 -> 709041411 | D64: =D61-D62-D63 -> 8.0771753e+08 | E64: =E61-E62-E63 -> 9.1406861e+08 | F64: =F61-F62-F63 -> 1036865646 | G64: =G61-G62-G63 -> 1179431809 | H64: =H61-H62-H63 -> 1314291199 | I64: =I61-I62-I63 -> 1454630671 | ... K64: =K61-K62-K63 -> 1753948451 | L64: =SUM(B64:K64) -> 11175385553

Sheet IVA
A1: IVA plan de Explotación, Cancelación del Credito Fiscal y pago al Fisco por IVA
C2: TOTALES PARA LAS TRES AREAS
A3: Rubros | C3: Año 0 | D3: Año 1 | E3: Año 2 | F3: Año 3 | G3: Año 4 | H3: Año 5 | I3: Año 6 | J3: Año 7 | K3: Año 8 | L3: Año 9 | M3: Año 10
A4: a) IVA pagado Costo Total de lo Vendido*1 | B4: Tasa
A5: Total Pagado en Producción | D5: =SUM(D6:D9) -> 2.2268171e+08 | E5: =SUM(E6:E9) -> 2.2268171e+08 | F5: =SUM(F6:F9) -> 2.2268173e+08 | G5: =SUM(G6:G9) -> 2.2268171e+08 | H5: =SUM(H6:H9) -> 2.2268171e+08 | I5: =SUM(I6:I9) -> 2.226214e+08 | J5: =SUM(J6:J9) -> 222620748 | K5: =SUM(K6:K9) -> 222620748 | ... M5: =SUM(M6:M9) -> 222620748
A6: Materia Prima con tarifa Normal | B6: ='DATOS Iniciales y ACLARACIONES'!B15 -> 0.21 | D6: =(CostoPROD!B4)*$B$6 -> 210840000 | E6: =(CostoPROD!C4)*$B$6 -> 210840000 | F6: =(CostoPROD!D4)*$B$6 -> 210840000 | G6: =(CostoPROD!E4)*$B$6 -> 210840000 | H6: =(CostoPROD!F4)*$B$6 -> 210840000 | I6: =(CostoPROD!G4)*$B$6 -> 210840000 | J6: =(CostoPROD!H4)*$B$6 -> 210840000 | K6: =(CostoPROD!I4)*$B$6 -> 210840000 | ... M6: =(CostoPROD!K4)*$B$6 -> 210840000
A7: Materia Prima con tarifa Reducida | B7: ='DATOS Iniciales y ACLARACIONES'!B16 -> 0.105
A8: Servicios | B8: ='DATOS Iniciales y ACLARACIONES'!B17 -> 0.27 | D8: =(CostoPROD!B9+CostoPROD!B10)*IVA!$B$8 -> 0 | E8: =(CostoPROD!C9+CostoPROD!C10)*IVA!$B$8 -> 0 | F8: =(CostoPROD!D9+CostoPROD!D10)*IVA!$B$8 -> 0 | G8: =(CostoPROD!E9+CostoPROD!E10)*IVA!$B$8 -> 0 | H8: =(CostoPROD!F9+CostoPROD!F10)*IVA!$B$8 -> 0 | I8: =(CostoPROD!G9+CostoPROD!G10)*IVA!$B$8 -> 0 | J8: =(CostoPROD!H9+CostoPROD!H10)*IVA!$B$8 -> 0 | K8: =(CostoPROD!I9+CostoPROD!I10)*IVA!$B$8 -> 0 | ... M8: =(CostoPROD!K9+CostoPROD!K10)*IVA!$B$8 -> 0
A9: Otros Gastos tarifa normal | B9: ='DATOS Iniciales y ACLARACIONES'!B15 -> 0.21 | D9: =(CostoPROD!B8+CostoPROD!B12+CostoPROD!B13+CostoPROD!B14+CostoPROD!B15+CostoPROD!B16+CostoPROD!B17)*$B$9 -> 11841714 | E9: =(CostoPROD!C8+CostoPROD!C12+CostoPROD!C13+CostoPROD!C14+CostoPROD!C15+CostoPROD!C16+CostoPROD!C17)*$B$9 -> 11841707 | F9: =(CostoPROD!D8+CostoPROD!D12+CostoPROD!D13+CostoPROD!D14+CostoPROD!D15+CostoPROD!D16+CostoPROD!D17)*$B$9 -> 11841733 | G9: =(CostoPROD!E8+CostoPROD!E12+CostoPROD!E13+CostoPROD!E14+CostoPROD!E15+CostoPROD!E16+CostoPROD!E17)*$B$9 -> 11841707 | H9: =(CostoPROD!F8+CostoPROD!F12+CostoPROD!F13+CostoPROD!F14+CostoPROD!F15+CostoPROD!F16+CostoPROD!F17)*$B$9 -> 11841707 | I9: =(CostoPROD!G8+CostoPROD!G12+CostoPROD!G13+CostoPROD!G14+CostoPROD!G15+CostoPROD!G16+CostoPROD!G17)*$B$9 -> 11781404 | J9: =(CostoPROD!H8+CostoPROD!H12+CostoPROD!H13+CostoPROD!H14+CostoPROD!H15+CostoPROD!H16+CostoPROD!H17)*$B$9 -> 11780748 | K9: =(CostoPROD!I8+CostoPROD!I12+CostoPROD!I13+CostoPROD!I14+CostoPROD!I15+CostoPROD!I16+CostoPROD!I17)*$B$9 -> 11780748 | ... M9: =(CostoPROD!K8+CostoPROD!K12+CostoPROD!K13+CostoPROD!K14+CostoPROD!K15+CostoPROD!K16+CostoPROD!K17)*$B$9 -> 11780748
A10: Total Pagado por Administración | D10: =SUM(D11:D12) -> 0 | E10: =SUM(E11:E12) -> 0 | F10: =SUM(F11:F12) -> 0 | G10: =SUM(G11:G12) -> 0 | H10: =SUM(H11:H12) -> 0 | I10: =SUM(I11:I12) -> 0 | J10: =SUM(J11:J12) -> 0 | K10: =SUM(K11:K12) -> 0 | ... M10: =SUM(M11:M12) -> 0
A11: Servicios | B11: ='DATOS Iniciales y ACLARACIONES'!B17 -> 0.27 | D11: =$B$11*(CostoAdmComFin!B7) -> 0 | E11: =$B$11*(CostoAdmComFin!C7) -> 0 | F11: =$B$11*(CostoAdmComFin!D7) -> 0 | G11: =$B$11*(CostoAdmComFin!E7) -> 0 | H11: =$B$11*(CostoAdmComFin!F7) -> 0 | I11: =$B$11*(CostoAdmComFin!G7) -> 0 | J11: =$B$11*(CostoAdmComFin!H7) -> 0 | K11: =$B$11*(CostoAdmComFin!I7) -> 0 | ... M11: =$B$11*(CostoAdmComFin!K7) -> 0
A12: otros Gastos | B12: ='DATOS Iniciales y ACLARACIONES'!B15 -> 0.21 | D12: =$B$11*(CostoAdmComFin!B6+CostoAdmComFin!B8+CostoAdmComFin!B9+CostoAdmComFin!B10+CostoAdmComFin!B12) -> 0 | E12: =$B$11*(CostoAdmComFin!C6+CostoAdmComFin!C8+CostoAdmComFin!C9+CostoAdmComFin!C10+CostoAdmComFin!C12) -> 0 | F12: =$B$11*(CostoAdmComFin!D6+CostoAdmComFin!D8+CostoAdmComFin!D9+CostoAdmComFin!D10+CostoAdmComFin!D12) -> 0 | G12: =$B$11*(CostoAdmComFin!E6+CostoAdmComFin!E8+CostoAdmComFin!E9+CostoAdmComFin!E10+CostoAdmComFin!E12) -> 0 | H12: =$B$11*(CostoAdmComFin!F6+CostoAdmComFin!F8+CostoAdmComFin!F9+CostoAdmComFin!F10+CostoAdmComFin!F12) -> 0 | I12: =$B$11*(CostoAdmComFin!G6+CostoAdmComFin!G8+CostoAdmComFin!G9+CostoAdmComFin!G10+CostoAdmComFin!G12) -> 0 | J12: =$B$11*(CostoAdmComFin!H6+CostoAdmComFin!H8+CostoAdmComFin!H9+CostoAdmComFin!H10+CostoAdmComFin!H12) -> 0 | K12: =$B$11*(CostoAdmComFin!I6+CostoAdmComFin!I8+CostoAdmComFin!I9+CostoAdmComFin!I10+CostoAdmComFin!I12) -> 0 | ... M12: =$B$11*(CostoAdmComFin!K6+CostoAdmComFin!K8+CostoAdmComFin!K9+CostoAdmComFin!K10+CostoAdmComFin!K12) -> 0
A13: Total pagado por Comercialización | D13: =SUM(D14:D15) -> 5090400 | E13: =SUM(E14:E15) -> 2423400 | F13: =SUM(F14:F15) -> 2423400 | G13: =SUM(G14:G15) -> 2423400 | H13: =SUM(H14:H15) -> 2423400 | I13: =SUM(I14:I15) -> 2423400 | J13: =SUM(J14:J15) -> 2423400 | K13: =SUM(K14:K15) -> 2423400 | ... M13: =SUM(M14:M15) -> 2423400
A14: Servicios | B14: ='DATOS Iniciales y ACLARACIONES'!B17 -> 0.27 | D14: =$B$14*(CostoAdmComFin!B30) -> 0 | E14: =$B$14*(CostoAdmComFin!C30) -> 0 | F14: =$B$14*(CostoAdmComFin!D30) -> 0 | G14: =$B$14*(CostoAdmComFin!E30) -> 0 | H14: =$B$14*(CostoAdmComFin!F30) -> 0 | I14: =$B$14*(CostoAdmComFin!G30) -> 0 | J14: =$B$14*(CostoAdmComFin!H30) -> 0 | K14: =$B$14*(CostoAdmComFin!I30) -> 0 | ... M14: =$B$14*(CostoAdmComFin!K30) -> 0
A15: Otros Gastos | B15: ='DATOS Iniciales y ACLARACIONES'!B15 -> 0.21 | D15: =$B$15*(CostoAdmComFin!B26+CostoAdmComFin!B27+CostoAdmComFin!B29+CostoAdmComFin!B31+CostoAdmComFin!B32) -> 5090400 | E15: =$B$15*(CostoAdmComFin!C26+CostoAdmComFin!C27+CostoAdmComFin!C29+CostoAdmComFin!C31+CostoAdmComFin!C32) -> 2423400 | F15: =$B$15*(CostoAdmComFin!D26+CostoAdmComFin!D27+CostoAdmComFin!D29+CostoAdmComFin!D31+CostoAdmComFin!D32) -> 2423400 | G15: =$B$15*(CostoAdmComFin!E26+CostoAdmComFin!E27+CostoAdmComFin!E29+CostoAdmComFin!E31+CostoAdmComFin!E32) -> 2423400 | H15: =$B$15*(CostoAdmComFin!F26+CostoAdmComFin!F27+CostoAdmComFin!F29+CostoAdmComFin!F31+CostoAdmComFin!F32) -> 2423400 | I15: =$B$15*(CostoAdmComFin!G26+CostoAdmComFin!G27+CostoAdmComFin!G29+CostoAdmComFin!G31+CostoAdmComFin!G32) -> 2423400 | J15: =$B$15*(CostoAdmComFin!H26+CostoAdmComFin!H27+CostoAdmComFin!H29+CostoAdmComFin!H31+CostoAdmComFin!H32) -> 2423400 | K15: =$B$15*(CostoAdmComFin!I26+CostoAdmComFin!I27+CostoAdmComFin!I29+CostoAdmComFin!I31+CostoAdmComFin!I32) -> 2423400 | ... M15: =$B$15*(CostoAdmComFin!K26+CostoAdmComFin!K27+CostoAdmComFin!K29+CostoAdmComFin!K31+CostoAdmComFin!K32) -> 2423400
A16: Total pagado por Financiación | B16: ='DATOS Iniciales y ACLARACIONES'!B15 -> 0.21 | D16: =$B$16*(CostoAdmComFin!B42+CostoAdmComFin!B44+CostoAdmComFin!B45) -> 0 | E16: =$B$16*(CostoAdmComFin!C42+CostoAdmComFin!C44+CostoAdmComFin!C45) -> 0 | F16: =$B$16*(CostoAdmComFin!D42+CostoAdmComFin!D44+CostoAdmComFin!D45) -> 0 | G16: =$B$16*(CostoAdmComFin!E42+CostoAdmComFin!E44+CostoAdmComFin!E45) -> 0 | H16: =$B$16*(CostoAdmComFin!F42+CostoAdmComFin!F44+CostoAdmComFin!F45) -> 0 | I16: =$B$16*(CostoAdmComFin!G42+CostoAdmComFin!G44+CostoAdmComFin!G45) -> 0 | J16: =$B$16*(CostoAdmComFin!H42+CostoAdmComFin!H44+CostoAdmComFin!H45) -> 0 | K16: =$B$16*(CostoAdmComFin!I42+CostoAdmComFin!I44+CostoAdmComFin!I45) -> 0 | ... M16: =$B$16*(CostoAdmComFin!K42+CostoAdmComFin!K44+CostoAdmComFin!K45) -> 0
A17: IVA abonado en Costo Total de lo Vendido: | D17: =SUM(D5:D16) -> 4.5554423e+08 | E17: =SUM(E5:E16) -> 4.5021021e+08 | F17: =SUM(F5:F16) -> 4.5021027e+08 | G17: =SUM(G5:G16) -> 4.5021021e+08 | H17: =SUM(H5:H16) -> 4.5021021e+08 | I17: =SUM(I5:I16) -> 4.5008961e+08 | J17: =SUM(J5:J16) -> 450088296 | K17: =SUM(K5:K16) -> 450088296 | ... M17: =SUM(M5:M16) -> 450088296
A19: IVA total abonado por insumos | C19: =C17 | D19: =D17 -> 4.5554423e+08 | E19: =E17 -> 4.5021021e+08 | F19: =F17 -> 4.5021027e+08 | G19: =G17 -> 4.5021021e+08 | H19: =H17 -> 4.5021021e+08 | I19: =I17 -> 4.5008961e+08 | J19: =J17 -> 450088296 | ... M19: =M17 -> 450088296
A20: IVA total cobrado por ventas | B20: ='DATOS Iniciales y ACLARACIONES'!B18 -> 0.21 | C20: 0 | D20: ='CTV y CResult'!B13*IVA!$B$20 -> 834372000 | E20: ='CTV y CResult'!C13*IVA!$B$20 -> 953442000 | F20: ='CTV y CResult'!D13*IVA!$B$20 -> 993132000 | G20: ='CTV y CResult'!E13*IVA!$B$20 -> 1035909000 | H20: ='CTV y CResult'!F13*IVA!$B$20 -> 1085301000 | I20: ='CTV y CResult'!G13*IVA!$B$20 -> 1136457000 | J20: ='CTV y CResult'!H13*IVA!$B$20 -> 1190700000 | K20: ='CTV y CResult'!I13*IVA!$B$20 -> 1247148000 | ... M20: ='CTV y CResult'!K13*IVA!$B$20 -> 1367541000
A21: b) IVA diferencia | C21: =C20-C19 -> 0 | D21: =D20-D19 -> 3.7882777e+08 | E21: =E20-E19 -> 5.0323179e+08 | F21: =F20-F19 -> 5.4292173e+08 | G21: =G20-G19 -> 5.8569879e+08 | H21: =H20-H19 -> 6.3509079e+08 | I21: =I20-I19 -> 6.8636739e+08 | J21: =J20-J19 -> 740611704 | ... M21: =M20-M19 -> 917452704
A23: c) Crédito Fiscal Anterior | D23: =C25 -> 99844500 | E23: =IF(D25<0,0,D25) -> 0 | F23: =IF(E25<0,0,E25) -> 0 | G23: =IF(F25<0,0,F25) -> 0 | H23: =IF(G25<0,0,G25) -> 0 | I23: =IF(H25<0,0,H25) -> 0 | J23: =IF(I25<0,0,I25) -> 0 | K23: =IF(J25<0,0,J25) -> 0 | L23: =IF(K25<0,0,K25) -> 0 | M23: =IF(L25<0,0,L25) -> 0
A24: d) Crédito Fiscal del Año | C24: ='Inv AF'!D39+InvAT!B32 -> 99844500 | D24: ='Inv AF'!E39+InvAT!C32 -> 0 | E24: ='Inv AF'!F39+InvAT!D32 -> 0 | F24: ='Inv AF'!G39+InvAT!E32 -> 0 | G24: ='Inv AF'!H39+InvAT!F32 -> 0 | H24: ='Inv AF'!I39+InvAT!G32 -> 0 | I24: ='Inv AF'!J39+InvAT!H32 -> 0 | J24: ='Inv AF'!K39+InvAT!I32 -> 0 | ... M24: ='Inv AF'!N39+InvAT!L32 -> 0
A25: e) Crédito Fiscal Final Año | C25: =C24 -> 99844500 | D25: =IF(D23+D24-D21<0,0,D23+D24-D21) -> 0 | E25: =IF(E23+E24<E21,0,+E23+E24-E21) -> 0 | F25: =IF(F23+F24<F21,0,+F23+F24-F21) -> 0 | G25: =IF(G23+G24<G21,0,+G23+G24-G21) -> 0 | H25: =IF(H23+H24<H21,0,+H23+H24-H21) -> 0 | I25: =IF(I23+I24<I21,0,+I23+I24-I21) -> 0 | J25: =IF(J23+J24<J21,0,+J23+J24-J21) -> 0 | K25: =IF(K23+K24<K21,0,+K23+K24-K21) -> 0 | L25: =IF(L23+L24<L21,0,+L23+L24-L21) -> 0 | M25: =IF(M23+M24<M21,0,+M23+M24-M21) -> 0
A26: f) Recupero Credito Fiscal | D26: =IF(D25>0,D21,D23+D24) -> 99844500 | E26: =IF(E25>0,E21,E23+E24) -> 0 | F26: =IF(F25>0,F21,F23+F24) -> 0 | G26: =IF(G25>0,G21,G23+G24) -> 0 | H26: =IF(H25>0,H21,H23+H24) -> 0 | I26: =IF(I25>0,I21,I23+I24) -> 0 | J26: =IF(J25>0,J21,J23+J24) -> 0 | K26: =IF(K25>0,K21,K23+K24) -> 0 | ... M26: =IF(M25>0,M21,M23+M24) -> 0
A28: Pago al Fisco por IVA | D28: =IF(D25>0,0,-D25) -> 0 | E28: =IF(E25=0,E21-E26,0) -> 5.0323179e+08 | F28: =IF(F25=0,F21-F26,0) -> 5.4292173e+08 | G28: =IF(G25=0,G21-G26,0) -> 5.8569879e+08 | H28: =IF(H25=0,H21-H26,0) -> 6.3509079e+08 | I28: =IF(I25=0,I21-I26,0) -> 6.8636739e+08 | J28: =IF(J25=0,J21-J26,0) -> 740611704 | K28: =IF(K25=0,K21-K26,0) -> 797059704 | L28: =IF(L25=0,L21-L26,0) -> 855712704 | M28: =IF(M25=0,M21-M26,0) -> 917452704
A30: *1 En caso de modificarse los rubros de Costos, deberán adecuarse las formulas de estas casillas

Sheet Resumen Cred
A2: CUADRO RESUMEN DE CREDITOS*1
A3: día/mes/año | B3: deuda fin Ejercicio | D3: amortización | E3: deuda | F3: interés | H3: gasto
B4: No renovable | C4: Renovable | D4: anual | E4: prom. anual | F4: anual | G4: kd | H4: bancario
A5: 31/12/-1
A6: gastos preoperativos: | F6: =SUM(F5) -> 0 | H6: =SUM(H5) -> 0
A7: 37256
A8: 37621
A9: 37986
A10: 38352
A11: 38717
A12: 39082
A13: 39447
A14: 39813
A15: 40178
A16: 40543
A17: Totales: | D17: =SUM(D7:D16) -> 0 | F17: =SUM(F6:F16) -> 0 | H17: =H6 -> 0
A19: *1 Elaborar créditos y traer valores al final de cada ejercicio a este cuadro

Sheet 2 Estructura
A1: SEGUNDA ESTRUCTURA FINANCIERA
A2: Rubros | C2: Año 0 | D2: Año 1 | E2: Totales
A3: a) Inversión y calendario de Activo Fijo Incrementos
A5: Bienes de uso | C5: ='Inv AF'!D23 -> 1867950000 | D5: ='Inv AF'!E23 -> 0 | E5: =D5+C5 -> 1867950000
A6: Cargos diferidos: | C6: ='Inv AF'!D35 -> 0 | D6: ='Inv AF'!E35 -> 0 | E6: =D6+C6 -> 0
A7: Totales de activo fijo, sin IVA | C7: =C6+C5 -> 1867950000 | D7: =D6+D5 -> 0 | E7: =D7+C7 -> 1867950000
A8: IVA | C8: ='Inv AF'!D39 -> 99844500 | D8: ='Inv AF'!E39 -> 0 | E8: =D8+C8 -> 99844500
A9: Totales de activo fijo, con IVA | C9: =C8+C7 -> 1967794500 | D9: =D8+D7 -> 0 | E9: =+E8+E7 -> 1967794500
A10: b) Inversión y calendario de activo de trabajo: incrementos
A11: Disponibilidad mínima | C11: =InvAT!B4 -> 79464000 | D11: =InvAT!C4-InvAT!B4 -> 0 | E11: =D11+C11 -> 79464000
A12: Crédito por ventas (valor contable) | C12: =InvAT!B5 -> 0 | D12: =InvAT!C5-InvAT!B5 -> 1959386301 | E12: =D12+C12 -> 1959386301
A13: Bienes de cambio (valor contable) | C13: =InvAT!B7 -> 0 | D13: =InvAT!C7-InvAT!B7 -> 0 | E13: =D13+C13 -> 0
A14: Totales activo de trabajo, sin IVA | C14: =SUM(C11:C13) -> 79464000 | D14: =SUM(D11:D13) -> 1959386301 | E14: =D14+C14 -> 2038850301
A15: Menos:
A16: Amortizaciones en inventarios | C16: =InvAT!B15+InvAT!B16 -> 0 | D16: =InvAT!C15+InvAT!C16-InvAT!B15-InvAT!B16 -> 0 | E16: =D16+C16 -> 0
A17: Amortizaciones en crédito | C17: =InvAT!B18 -> 0 | D17: =InvAT!C18-InvAT!B18 -> 31606027 | E17: =D17+C17 -> 31606027
A18: Utilidades en crédito | C18: =InvAT!B17 -> 0 | D18: =InvAT!C17-InvAT!B17 -> 1.9969549e+08 | E18: =D18+C18 -> 1.9969549e+08
A19: Inversión activo de trabajo, s/IVA | C19: =C14-C16-C17-C18 -> 79464000 | D19: =D14-D16-D17-D18 -> 1728084784 | E19: =E14-E17-E18-E16 -> 1807548784
A20: IVA | C20: =InvAT!B32 -> 0 | D20: =InvAT!C32 -> 0 | E20: =SUM(C20:D20) -> 0
A21: Totales activo de trabajo (v. contable), c/IVA | C21: =C14+C20 -> 79464000 | D21: =D14+D20 -> 1959386301 | E21: =D21+C21 -> 2038850301
A22: Inversión activo de trabajo, con IVA | C22: =C19+C20 -> 79464000 | D22: =D19+D20 -> 1728084784 | E22: =D22+C22 -> 1807548784
A23: c) Inversión y calendario totales: incrementos
A24: Activo fijo, con IVA | C24: =C9 -> 1967794500 | D24: =D9 -> 0 | E24: =D24+C24 -> 1967794500
A25: Inversión activo de trabajo, c/IVA | C25: =InvAT!B34 -> 79464000 | D25: =InvAT!C34 -> 1728084784 | E25: =D25+C25 -> 1807548784
A26: Inversiones Totales, con IVA | C26: =C25+C24 -> 2047258500 | D26: =D25+D24 -> 1728084784 | E26: =D26+C26 -> 3775343284
A27: d) Financiación global (segunda y definitiva): | B27: %
A28: Crédito renovable | B28: =E28/E$31 -> 0 | C28: 0 | D28: ='Resumen Cred'!C7 | E28: =+D28+C28 -> 0
A29: Crédito no renovable | B29: =E29/E$31 -> 0 | C29: ='Resumen Cred'!B5 | D29: 0 | E29: =+D29+C29 -> 0
A30: Capital propio | B30: =E30/E$31 -> 1 | C30: =C26-C29 -> 2047258500 | D30: =D26-D29 -> 1728084784 | E30: =+D30+C30 -> 3775343284
A31: Totales | B31: =E31/E$31 -> 1 | C31: =C30+C28+C29 -> 2047258500 | D31: =D30+D28+D29 -> 1728084784 | E31: =+D31+C31 -> 3775343284

Sheet CFyU
A2: CUADRO DE FUENTES Y USOS
B3: Año 0 | C3: Año 1 | D3: Año 2 | E3: Año 3 | F3: Año 4 | G3: Año 5 | H3: Año 6 | I3: Año 7 | J3: Año 8 | K3: Año 9 | L3: Año 10 | M3: Totales
A4: FUENTES: Totales | B4: =SUM(B5:B11) -> 2047258500 | C4: =SUM(C5:C11) -> 5801129284 | D4: =SUM(D5:D11) -> 4877771060 | E4: =SUM(E5:E11) -> 6306620279 | F4: =SUM(F5:F11) -> 7708692189 | G4: =SUM(G5:G11) -> 9006971345 | H4: =SUM(H5:H11) -> 10441568087 | I4: =SUM(I5:I11) -> 12020747842 | ... M4: =SUM(M5:M11) -> 56969487784
A5: Saldo ejercicio anterior | B5: 0 | C5: =B27 -> 0 | D5: =C27 -> 3.3757106e+08 | E5: =D27 -> 1577420279 | F5: =E27 -> 2775792189 | G5: =F27 -> 3838871345 | H5: =G27 -> 5029868087 | I5: =H27 -> 6350747842 | J5: =I27 -> 7817821233 | ... L5: =K27 -> 10025827345 | M5: 0
A6: Aporte de capital propio | B6: ='2 Estructura'!C30 -> 2047258500 | C6: ='2 Estructura'!D30 -> 1728084784 | D6: 0 | E6: 0 | F6: 0 | G6: 0 | I6: 0 | J6: 0 | K6: 0 | L6: 0 | M6: =SUM(B6:L6) -> 3775343284
A7: Créditos renovables | B7: ='Resumen Cred'!C6 | C7: ='Resumen Cred'!C7-'Resumen Cred'!C6 -> 0 | D7: ='Resumen Cred'!C8-'Resumen Cred'!C7 -> 0 | E7: ='Resumen Cred'!C9-'Resumen Cred'!C8 -> 0 | F7: ='Resumen Cred'!C10-'Resumen Cred'!C9 -> 0 | G7: ='Resumen Cred'!C11-'Resumen Cred'!C10 -> 0 | H7: ='Resumen Cred'!C12-'Resumen Cred'!C11 -> 0 | I7: ='Resumen Cred'!C13-'Resumen Cred'!C12 -> 0 | J7: ='Resumen Cred'!C14-'Resumen Cred'!C13 -> 0 | K7: ='Resumen Cred'!C15-'Resumen Cred'!C14 -> 0 | L7: ='Resumen Cred'!C16-'Resumen Cred'!C15 -> 0 | M7: =SUM(B7:L7) -> 0
A8: Créditos no renovables | B8: ='2 Estructura'!C29 | C8: ='2 Estructura'!D29 -> 0 | D8: 0 | E8: 0 | F8: 0 | G8: 0 | H8: 0 | I8: 0 | J8: 0 | K8: 0 | L8: 0 | M8: =SUM(B8:L8) -> 0
A9: Ventas del ejercicio | B9: 0 | C9: ='CTV y CResult'!B54 -> 3973200000 | D9: ='CTV y CResult'!C54 -> 4540200000 | E9: ='CTV y CResult'!D54 -> 4729200000 | F9: ='CTV y CResult'!E54 -> 4932900000 | G9: ='CTV y CResult'!F54 -> 5168100000 | H9: ='CTV y CResult'!G54 -> 5411700000 | I9: ='CTV y CResult'!H54 -> 5670000000 | J9: ='CTV y CResult'!I54 -> 5938800000 | ... L9: ='CTV y CResult'!K54 -> 6512100000 | M9: =SUM(B9:L9) -> 53094300000
A10: Recupero Crédito Fiscal | B10: =IVA!C26 | C10: =IVA!D26 -> 99844500 | D10: =IVA!E26 -> 0 | E10: =IVA!F26 -> 0 | F10: =IVA!G26 -> 0 | G10: =IVA!H26 -> 0 | H10: =IVA!I26 -> 0 | I10: =IVA!J26 -> 0 | ... L10: =IVA!M26 -> 0 | M10: =SUM(B10:L10) -> 99844500
A11: Otros ingresos | B11: 0 | C11: 0 | D11: 0 | E11: 0 | F11: 0 | G11: 0 | H11: 0 | I11: 0 | J11: 0 | K11: 0 | L11: 0 | M11: =SUM(B11:L11) -> 0
A13: USOS: Totales | B13: =SUM(B14:B22) -> 2047258500 | C13: =SUM(C14:C22) -> 5527648224 | D13: =SUM(D14:D22) -> 3364440781 | E13: =SUM(E14:E22) -> 3594918090 | F13: =SUM(F14:F22) -> 3933910844 | G13: =SUM(G14:G22) -> 4041193258 | H13: =SUM(H14:H22) -> 4130720246 | I13: =SUM(I14:I22) -> 4242826609 | ... L13: =SUM(L14:L22) -> 6266009083 | M13: =SUM(B13:L13) -> 47177619522
A14: Activo Fijo | B14: ='Inv AF'!D37 -> 1867950000 | C14: ='Inv AF'!E37 -> 0 | D14: ='Inv AF'!F37 -> 0 | E14: ='Inv AF'!G37 -> 0 | F14: ='Inv AF'!H37 -> 0 | G14: ='Inv AF'!I37 -> 0 | H14: ='Inv AF'!J37 -> 0 | I14: ='Inv AF'!K37 -> 0 | ... L14: ='Inv AF'!N37 -> 0 | M14: =SUM(B14:L14) -> 1867950000
A15: Activo de Trabajo | B15: =InvAT!B22 -> 79464000 | C15: =InvAT!C22 -> 1959386301 | D15: =InvAT!D22 -> -4.6671781e+08 | E15: =InvAT!E22 -> -3.2656438e+08 | F15: =InvAT!F22 -> -84920548 | G15: =InvAT!G22 -> -90041096 | H15: =InvAT!H22 -> -1.0154795e+08 | I15: =InvAT!I22 -> -1.1288219e+08 | ... L15: =InvAT!L22 -> 1507857534 | M15: =SUM(B15:L15) -> 3290910575
A16: Costo de lo Vendido | B16: 0 | C16: ='CTV y CResult'!B55+'CTV y CResult'!B58+'CTV y CResult'!B59+'CTV y CResult'!B60 -> 3317429834 | D16: ='CTV y CResult'!C55+'CTV y CResult'!C58+'CTV y CResult'!C59+'CTV y CResult'!C60 -> 3391954800 | E16: ='CTV y CResult'!D55+'CTV y CResult'!D58+'CTV y CResult'!D59+'CTV y CResult'!D60 -> 3421155423 | F16: ='CTV y CResult'!E55+'CTV y CResult'!E58+'CTV y CResult'!E59+'CTV y CResult'!E60 -> 3452626950 | G16: ='CTV y CResult'!F55+'CTV y CResult'!F58+'CTV y CResult'!F59+'CTV y CResult'!F60 -> 3488965350 | H16: ='CTV y CResult'!G55+'CTV y CResult'!G58+'CTV y CResult'!G59+'CTV y CResult'!G60 -> 3501688973 | I16: ='CTV y CResult'!H55+'CTV y CResult'!H58+'CTV y CResult'!H59+'CTV y CResult'!H60 -> 3541593200 | J16: ='CTV y CResult'!I55+'CTV y CResult'!I58+'CTV y CResult'!I59+'CTV y CResult'!I60 -> 3583122800 | ... L16: ='CTV y CResult'!K55+'CTV y CResult'!K58+'CTV y CResult'!K59+'CTV y CResult'!K60 -> 3671697650 | M16: =SUM(B16:L16) -> 34996509630
A17: Impuesto a la Ganancia | B17: 0 | C17: ='CTV y CResult'!B63 -> 2.1804358e+08 | D17: ='CTV y CResult'!C63 -> 381791529 | E17: ='CTV y CResult'!D63 -> 4.3492482e+08 | F17: ='CTV y CResult'!E63 -> 4.9219079e+08 | G17: ='CTV y CResult'!F63 -> 5.5831227e+08 | H17: ='CTV y CResult'!G63 -> 6.3507867e+08 | I17: ='CTV y CResult'!H63 -> 707695261 | J17: ='CTV y CResult'!I63 -> 783262669 | ... L17: ='CTV y CResult'!K63 -> 9.4443378e+08 | M17: =SUM(B17:L17) -> 6017515298
A18: Cancelación de deudas | B18: 0 | C18: ='Resumen Cred'!D7 | D18: ='Resumen Cred'!D8 | E18: ='Resumen Cred'!D9 | F18: ='Resumen Cred'!D10 | G18: ='Resumen Cred'!D11 | H18: ='Resumen Cred'!D12 | I18: ='Resumen Cred'!D13 | J18: ='Resumen Cred'!D14 | K18: ='Resumen Cred'!D15 | L18: ='Resumen Cred'!D16 | M18: =SUM(B18:L18) -> 0
A19: Honorarios del Directorio | B19: 0 | C19: ='CTV y CResult'!B62 -> 32788508 | D19: ='CTV y CResult'!C62 -> 57412260 | E19: ='CTV y CResult'!D62 -> 65402229 | F19: ='CTV y CResult'!E62 -> 74013652 | G19: ='CTV y CResult'!F62 -> 83956732 | H19: ='CTV y CResult'!G62 -> 95500551 | I19: ='CTV y CResult'!H62 -> 106420340 | J19: ='CTV y CResult'!I62 -> 117783860 | ... L19: ='CTV y CResult'!K62 -> 1.4202012e+08 | M19: =SUM(B19:L19) -> 9.0488952e+08
A20: Dividendos en efectivo | B20: 0 | C20: 0 | D20: 0 | E20: 0 | F20: 0 | G20: 0 | H20: 0 | I20: 0 | J20: 0 | K20: 0 | L20: 0 | M20: =SUM(B20:L20) -> 0
A21: IVA inversión | B21: =IVA!C24 -> 99844500 | C21: =IVA!D24 -> 0 | D21: =IVA!E24 -> 0 | E21: =IVA!F24 -> 0 | F21: =IVA!G24 -> 0 | G21: =IVA!H24 -> 0 | H21: =IVA!I24 -> 0 | I21: =IVA!J24 -> 0 | ... L21: =IVA!M24 -> 0 | M21: =SUM(B21:L21) -> 99844500
A22: Otros egresos | B22: 0 | C22: 0 | D22: 0 | E22: 0 | F22: 0 | G22: 0 | H22: 0 | I22: 0 | J22: 0 | K22: 0 | L22: 0 | M22: =SUM(B22:L22) -> 0
A24: FUENTES - USOS | B24: =B4-B13 -> 0 | C24: =C4-C13 -> 2.7348106e+08 | D24: =D4-D13 -> 1513330279 | E24: =E4-E13 -> 2711702189 | F24: =F4-F13 -> 3774781345 | G24: =G4-G13 -> 4965778087 | H24: =H4-H13 -> 6310847842 | I24: =I4-I13 -> 7777921233 | ... M24: =M4-M13 -> 9791868262
A25: (+) Amortizaciones del ejercicio | B25: 0 | C25: ='Inv AF'!E80 -> 64090000 | D25: ='Inv AF'!F80 -> 64090000 | E25: ='Inv AF'!G80 -> 64090000 | F25: ='Inv AF'!H80 -> 64090000 | G25: ='Inv AF'!I80 -> 64090000 | H25: ='Inv AF'!J80 -> 39900000 | I25: ='Inv AF'!K80 -> 39900000 | J25: ='Inv AF'!L80 -> 39900000 | ... L25: ='Inv AF'!N80 -> 39900000 | M25: =SUM(B25:L25) -> 519950000
A27: Saldo al Ej. siguiente (acumulado) | B27: =B24+B25 -> 0 | C27: =C25+C24 -> 3.3757106e+08 | D27: =D25+D24 -> 1577420279 | E27: =E25+E24 -> 2775792189 | F27: =F25+F24 -> 3838871345 | G27: =G25+G24 -> 5029868087 | H27: =H25+H24 -> 6350747842 | I27: =I25+I24 -> 7817821233 | J27: =J25+J24 -> 9275529986 | ... M27: =M25+M24 -> 10311818262
A28: Saldo Propio del Ejercicio | B28: =B27-B5 -> 0 | C28: =C27-C5 -> 3.3757106e+08 | D28: =D27-D5 -> 1239849219 | E28: =E27-E5 -> 1198371910 | F28: =F27-F5 -> 1063079156 | G28: =G27-G5 -> 1190996742 | H28: =H27-H5 -> 1320879754 | I28: =I27-I5 -> 1467073391 | ... L28: =L27-L5 -> 2.8599092e+08 | M28: =SUM(B28:L28) -> 10311818262

Sheet Balance
A3: BALANCES PROFORMAS
B4: Año 0 | C4: Año 1 | D4: Año 2 | E4: Año 3 | F4: Año 4 | G4: Año 5 | H4: Año 6 | I4: Año 7 | J4: Año 8 | K4: Año 9 | L4: Año 10
A5: ACTIVO CORRIENTE: Total | B5: =SUM(B7:B11) -> 179308500 | C5: =SUM(C7:C11) -> 2376421361 | D5: =SUM(D7:D11) -> 3149552772 | E5: =SUM(E7:E11) -> 4021360298 | F5: =SUM(F7:F11) -> 4999518907 | G5: =SUM(G7:G11) -> 6100474553 | H5: =SUM(H7:H11) -> 7319806362 | I5: =SUM(I7:I11) -> 8673997561 | ... L5: =SUM(L7:L11) -> 13602728837
A6: Caja y Bancos:
A7: - mínimo | B7: =InvAT!B4 -> 79464000 | C7: =InvAT!C4 -> 79464000 | D7: =InvAT!D4 -> 79464000 | E7: =InvAT!E4 -> 79464000 | F7: =InvAT!F4 -> 79464000 | G7: =InvAT!G4 -> 79464000 | H7: =InvAT!H4 -> 79464000 | I7: =InvAT!I4 -> 79464000 | ... L7: =InvAT!L4 -> 79464000
A8: - saldo acumulado de Fuentes y Usos | B8: =CFyU!B5 -> 0 | C8: =CFyU!C27 -> 3.3757106e+08 | D8: =CFyU!D27 -> 1577420279 | E8: =CFyU!E27 -> 2775792189 | F8: =CFyU!F27 -> 3838871345 | G8: =CFyU!G27 -> 5029868087 | H8: =CFyU!H27 -> 6350747842 | I8: =CFyU!I27 -> 7817821233 | J8: =CFyU!J27 -> 9275529986 | ... L8: =CFyU!L27 -> 10311818262
A9: Crédito por ventas | B9: =InvAT!B5 -> 0 | C9: =InvAT!C5 -> 1959386301 | D9: =InvAT!D5 -> 1492668493 | E9: =InvAT!E5 -> 1166104110 | F9: =InvAT!F5 -> 1081183562 | G9: =InvAT!G5 -> 9.9114247e+08 | H9: =InvAT!H5 -> 8.8959452e+08 | I9: =InvAT!I5 -> 7.7671233e+08 | ... L9: =InvAT!L5 -> 3211446575
A10: Bienes de cambio | B10: =InvAT!B7 -> 0 | C10: =InvAT!C7 -> 0 | D10: =InvAT!D7 -> 0 | E10: =InvAT!E7 -> 0 | F10: =InvAT!F7 -> 0 | G10: =InvAT!G7 -> 0 | H10: =InvAT!H7 -> 0 | I10: =InvAT!I7 -> 0 | ... L10: =InvAT!L7 -> 0
A11: Crédito Fiscal | B11: =IF(IVA!C25>IVA!D21,IVA!D21,IVA!C25) -> 99844500 | C11: =IF(IVA!D25>IVA!E21,IVA!E21,IVA!D25) -> 0 | D11: =IF(IVA!E25>IVA!F21,IVA!F21,IVA!E25) -> 0 | E11: =IF(IVA!F25>IVA!G21,IVA!G21,IVA!F25) -> 0 | F11: =IF(IVA!G25>IVA!H21,IVA!H21,IVA!G25) -> 0 | G11: =IF(IVA!H25>IVA!I21,IVA!I21,IVA!H25) -> 0 | H11: =IF(IVA!I25>IVA!J21,IVA!J21,IVA!I25) -> 0 | I11: =IF(IVA!J25>IVA!K21,IVA!K21,IVA!J25) -> 0 | ... L11: =IF(IVA!M25>IVA!N21,IVA!N21,IVA!M25) -> 0
A12: ACTIVO NO CORRIENTE: Total | B12: =B17+B22+B23 -> 1867950000 | C12: =C17+C22+C23 -> 1803860000 | D12: =D17+D22+D23 -> 1739770000 | E12: =E17+E22+E23 -> 1675680000 | F12: =F17+F22+F23 -> 1611590000 | G12: =G17+G22+G23 -> 1547500000 | H12: =H17+H22+H23 -> 1507600000 | I12: =I17+I22+I23 -> 1467700000 | ... L12: =L17+L22+L23 -> 1348000000
A13: Cargos Diferidos:
A14: - valor inicial | B14: 0 | C14: =B17 -> 0 | D14: =C17 -> 0 | E14: =D17 -> 0 | F14: =E17 -> 0 | G14: =F17 -> 0 | H14: =G17 -> 0 | I14: =H17 -> 0 | J14: =I17 -> 0 | ... L14: =K17 -> 0
A15: más inversiones del ejercicio | B15: ='Inv AF'!D35 -> 0 | C15: ='Inv AF'!E35 -> 0 | D15: ='Inv AF'!F35 -> 0 | E15: ='Inv AF'!G35 -> 0 | F15: ='Inv AF'!H35 -> 0 | G15: ='Inv AF'!I35 -> 0 | H15: ='Inv AF'!J35 -> 0 | I15: ='Inv AF'!K35 -> 0 | ... L15: ='Inv AF'!N35 -> 0
A16: menos amortizaciones del ejerc. | B16: 0 | C16: ='Inv AF'!E78 -> 0 | D16: ='Inv AF'!F78 -> 0 | E16: ='Inv AF'!G78 -> 0 | F16: ='Inv AF'!H78 -> 0 | G16: ='Inv AF'!I78 -> 0 | H16: ='Inv AF'!J78 -> 0 | I16: ='Inv AF'!K78 -> 0 | J16: ='Inv AF'!L78 -> 0 | ... L16: ='Inv AF'!N78 -> 0
A17: - valor final del ejercicio | B17: =B14+B15-B16 -> 0 | C17: =C14+C15-C16 -> 0 | D17: =D14+D15-D16 -> 0 | E17: =E14+E15-E16 -> 0 | F17: =F14+F15-F16 -> 0 | G17: =G14+G15-G16 -> 0 | H17: =H14+H15-H16 -> 0 | I17: =I14+I15-I16 -> 0 | ... L17: =L14+L15-L16 -> 0
A18: Bienes de Uso
A19: - valor inicial | B19: 0 | C19: =B22 -> 1867950000 | D19: =C22 -> 1803860000 | E19: =D22 -> 1739770000 | F19: =E22 -> 1675680000 | G19: =F22 -> 1611590000 | H19: =G22 -> 1547500000 | I19: =H22 -> 1507600000 | J19: =I22 -> 1467700000 | ... L19: =K22 -> 1387900000
A20: más inversiones del ejercicio | B20: ='Inv AF'!D23 -> 1867950000 | C20: ='Inv AF'!E23 -> 0 | D20: ='Inv AF'!F23 -> 0 | E20: ='Inv AF'!G23 -> 0 | F20: ='Inv AF'!H23 -> 0 | G20: ='Inv AF'!I23 -> 0 | H20: ='Inv AF'!J23 -> 0 | I20: ='Inv AF'!K23 -> 0 | ... L20: ='Inv AF'!N23 -> 0
A21: menos amortizaciones del ejerc | B21: 0 | C21: ='Inv AF'!E66 -> 64090000 | D21: ='Inv AF'!F66 -> 64090000 | E21: ='Inv AF'!G66 -> 64090000 | F21: ='Inv AF'!H66 -> 64090000 | G21: ='Inv AF'!I66 -> 64090000 | H21: ='Inv AF'!J66 -> 39900000 | I21: ='Inv AF'!K66 -> 39900000 | J21: ='Inv AF'!L66 -> 39900000 | ... L21: ='Inv AF'!N66 -> 39900000
A22: - valor final del ejercicio | B22: =B19+B20-B21 -> 1867950000 | C22: =C19+C20-C21 -> 1803860000 | D22: =D19+D20-D21 -> 1739770000 | E22: =E19+E20-E21 -> 1675680000 | F22: =F19+F20-F21 -> 1611590000 | G22: =G19+G20-G21 -> 1547500000 | H22: =H19+H20-H21 -> 1507600000 | I22: =I19+I20-I21 -> 1467700000 | ... L22: =L19+L20-L21 -> 1348000000
A23: Crédito Fiscal | B23: =IVA!C25-Balance!B11 -> 0 | C23: =IVA!D25-Balance!C11 -> 0 | D23: =IVA!E25-Balance!D11 -> 0 | E23: =IVA!F25-Balance!E11 -> 0 | F23: =IVA!G25-Balance!F11 -> 0 | G23: =IVA!H25-Balance!G11 -> 0 | H23: =IVA!I25-Balance!H11 -> 0 | I23: =IVA!J25-Balance!I11 -> 0 | ... L23: =IVA!M25-Balance!L11 -> 0
A24: ACTIVO TOTAL: | B24: =B12+B5 -> 2047258500 | C24: =C12+C5 -> 4180281361 | D24: =D12+D5 -> 4889322772 | E24: =E12+E5 -> 5697040298 | F24: =F12+F5 -> 6611108907 | G24: =G12+G5 -> 7647974553 | H24: =H12+H5 -> 8827406362 | I24: =I12+I5 -> 10141697561 | ... L24: =L12+L5 -> 14950728837
A25: PASIVO CORRIENTE: Total | B25: =B26+B27 -> 0 | C25: =C26+C27 -> 0 | D25: =D26+D27 -> 0 | E25: =E26+E27 -> 0 | F25: =F26+F27 -> 0 | G25: =G26+G27 -> 0 | H25: =H26+H27 -> 0 | I25: =I26+I27 -> 0 | ... L25: =L26+L27 -> 0
A26: Deudas comerciales | B26: 0 | C26: ='Resumen Cred'!C7 | D26: ='Resumen Cred'!C8 | E26: ='Resumen Cred'!C9 | F26: ='Resumen Cred'!C10 | G26: ='Resumen Cred'!C11 | H26: ='Resumen Cred'!C12 | I26: ='Resumen Cred'!C13 | J26: ='Resumen Cred'!C14 | K26: ='Resumen Cred'!C15 | L26: ='Resumen Cred'!C16
A27: Deudas bancarias | B27: ='Resumen Cred'!D7 | C27: ='Resumen Cred'!D8 | D27: ='Resumen Cred'!D9 | E27: ='Resumen Cred'!D10 | F27: ='Resumen Cred'!D11 | G27: ='Resumen Cred'!D12 | H27: ='Resumen Cred'!D13 | I27: ='Resumen Cred'!D14 | J27: ='Resumen Cred'!D15 | K27: ='Resumen Cred'!D16 | L27: 0
A28: PASIVO NO CORRIENTE: Total | B28: =+B29 -> 0 | C28: =+C29 -> 0 | D28: =+D29 -> 0 | E28: =+E29 -> 0 | F28: =+F29 -> 0 | G28: =+G29 -> 0 | H28: =+H29 -> 0 | I28: =+I29 -> 0 | ... L28: =+L29 -> 0
A29: Deudas bancarias | B29: ='Resumen Cred'!B5-B27 -> 0 | C29: ='Resumen Cred'!B7-C27 -> 0 | D29: ='Resumen Cred'!B8-D27 -> 0 | E29: ='Resumen Cred'!B9-E27 -> 0 | F29: ='Resumen Cred'!B10-F27 -> 0 | G29: ='Resumen Cred'!B11-G27 -> 0 | H29: ='Resumen Cred'!B12-H27 -> 0 | I29: ='Resumen Cred'!IB13-I27 -> 0 | J29: ='Resumen Cred'!B14-J27 -> 0 | K29: ='Resumen Cred'!B15-K27 -> 0 | L29: ='Resumen Cred'!B16-L27 -> 0
A30: PASIVO TOTAL: | B30: =+B29+B25 -> 0 | C30: =+C29+C25 -> 0 | D30: =+D29+D25 -> 0 | E30: =+E29+E25 -> 0 | F30: =+F29+F25 -> 0 | G30: =+G29+G25 -> 0 | H30: =+H29+H25 -> 0 | I30: =+I29+I25 -> 0 | ... L30: =+L29+L25 -> 0
A31: PATRIMONIO NETO: | B31: =B32+B33+B34 -> 2047258500 | C31: =C32+C33+C34 -> 4180281361 | D31: =D32+D33+D34 -> 4889322772 | E31: =E32+E33+E34 -> 5697040298 | F31: =F32+F33+F34 -> 6611108907 | G31: =G32+G33+G34 -> 7647974553 | H31: =H32+H33+H34 -> 8827406362 | I31: =I32+I33+I34 -> 10141697561 | ... L31: =L32+L33+L34 -> 14950728837
A32: Capital societario | B32: =CFyU!B6 -> 2047258500 | C32: =CFyU!C6+Balance!B32 -> 3775343284 | D32: =CFyU!D6+Balance!C32 -> 3775343284 | E32: =CFyU!E6+Balance!D32 -> 3775343284 | F32: =CFyU!F6+Balance!E32 -> 3775343284 | G32: =CFyU!G6+Balance!F32 -> 3775343284 | H32: =CFyU!H6+Balance!G32 -> 3775343284 | I32: =CFyU!I6+Balance!H32 -> 3775343284 | J32: =CFyU!J6+Balance!I32 -> 3775343284 | ... L32: =CFyU!L6+Balance!K32 -> 3775343284
A33: Utilidad del ejercicio | B33: 0 | C33: ='CTV y CResult'!B64 -> 4.0493808e+08 | D33: ='CTV y CResult'!C64 -> 709041411 | E33: ='CTV y CResult'!D64 -> 8.0771753e+08 | F33: ='CTV y CResult'!E64 -> 9.1406861e+08 | G33: ='CTV y CResult'!F64 -> 1036865646 | H33: ='CTV y CResult'!G64 -> 1179431809 | I33: ='CTV y CResult'!H64 -> 1314291199 | J33: ='CTV y CResult'!I64 -> 1454630671 | ... L33: ='CTV y CResult'!K64 -> 1753948451
A34: Utilidad acumulada | B34: 0 | C34: 0 | D34: =C34+C33 -> 4.0493808e+08 | E34: =D34+D33 -> 1113979489 | F34: =E34+E33 -> 1921697015 | G34: =F34+F33 -> 2835765623 | H34: =G34+G33 -> 3872631270 | I34: =H34+H33 -> 5052063079 | J34: =I34+I33 -> 6366354278 | K34: =J34+J33 -> 7820984949 | L34: =K34+K33 -> 9421437102
A35: PASIVO + PATRIMONIO NETO | B35: =B31+B30 -> 2047258500 | C35: =C31+C30 -> 4180281361 | D35: =D31+D30 -> 4889322772 | E35: =E31+E30 -> 5697040298 | F35: =F31+F30 -> 6611108907 | G35: =G31+G30 -> 7647974553 | H35: =H31+H30 -> 8827406362 | I35: =I31+I30 -> 10141697561 | ... L35: =L31+L30 -> 14950728837
B36: =B35-B24 -> 0 | C36: =C35-C24 -> 4.7683716e-07 | D36: =D35-D24 -> 0 | E36: =E35-E24 -> 0 | F36: =F35-F24 -> 1.9073486e-06 | G36: =G35-G24 -> 9.5367432e-07 | H36: =H35-H24 -> 0 | I36: =I35-I24 -> 1.9073486e-06 | ... L36: =L35-L24 -> 1.9073486e-06
C37: =C36-B36 -> 4.7683716e-07 | D37: =D36-C36 -> -4.7683716e-07 | E37: =E36-D36 -> 0 | F37: =F36-E36 -> 1.9073486e-06 | G37: =G36-F36 -> -9.5367432e-07 | H37: =H36-G36 -> -9.5367432e-07 | I37: =I36-H36 -> 1.9073486e-06 | J37: =J36-I36 -> 0 | ... L37: =L36-K36 -> 0

Sheet DF- Form
A1: Formulación del Proyecto a Nivel Financiero
A2: Año | B2: Activo Fijo | C2: Activo de Trabajo | D2: Credito Fiscal | E2: Honorarios al Directorio | F2: Impuesto a las Ganancias | G2: Total Egresos | H2: Utilidad Antes HD e IG | I2: Intereses Pagados | J2: Amortizaciones | K2: Cobro Credito Fiscal | L2: Total Ingresos | M2: Saldo Anual | N2: Saldo Acumulado
A3: 0 | B3: =CFyU!B14 -> 1867950000 | C3: =CFyU!B15 -> 79464000 | D3: =CFyU!B21 -> 99844500 | E3: =CFyU!B19 -> 0 | F3: =CFyU!B17 -> 0 | G3: =SUM(B3:F3) -> 2047258500 | H3: 0 | I3: ='Resumen Cred'!F5+'Resumen Cred'!H5 -> 0 | J3: =CFyU!B25 -> 0 | K3: =CFyU!B10 | L3: =SUM(H3:K3) -> 0 | M3: =L3-G3 -> -2047258500 | N3: =M3 -> -2047258500
A4: 1 | B4: =CFyU!C14 -> 0 | C4: =CFyU!C15 -> 1959386301 | D4: =CFyU!C21 -> 0 | E4: =CFyU!C19 -> 32788508 | F4: =CFyU!C17 -> 2.1804358e+08 | G4: =SUM(B4:F4) -> 2210218390 | H4: ='CTV y CResult'!B61 -> 655770166 | I4: ='Resumen Cred'!F7+'Resumen Cred'!H7 -> 0 | J4: =CFyU!C25 -> 64090000 | K4: =CFyU!C10 -> 99844500 | L4: =SUM(H4:K4) -> 819704666 | M4: =L4-G4 -> -1390513724 | N4: =N3+M4 -> -3437772224
A5: 2 | B5: =CFyU!D14 -> 0 | C5: =CFyU!D15 -> -4.6671781e+08 | D5: =CFyU!D21 -> 0 | E5: =CFyU!D19 -> 57412260 | F5: =CFyU!D17 -> 381791529 | G5: =SUM(B5:F5) -> -27514019 | H5: ='CTV y CResult'!C61 -> 1148245200 | I5: ='Resumen Cred'!F8+'Resumen Cred'!H8 -> 0 | J5: =CFyU!D25 -> 64090000 | K5: =CFyU!D10 -> 0 | L5: =SUM(H5:K5) -> 1212335200 | M5: =L5-G5 -> 1239849219 | N5: =N4+M5 -> -2197923005
A6: 3 | B6: =CFyU!E14 -> 0 | C6: =CFyU!E15 -> -3.2656438e+08 | D6: =CFyU!E21 -> 0 | E6: =CFyU!E19 -> 65402229 | F6: =CFyU!E17 -> 4.3492482e+08 | G6: =SUM(B6:F6) -> 1.7376267e+08 | H6: ='CTV y CResult'!D61 -> 1308044577 | I6: ='Resumen Cred'!F9+'Resumen Cred'!H9 -> 0 | J6: =CFyU!E25 -> 64090000 | K6: =CFyU!E10 -> 0 | L6: =SUM(H6:K6) -> 1372134577 | M6: =L6-G6 -> 1198371910 | N6: =N5+M6 -> -9.9955109e+08
A7: 4 | B7: =CFyU!F14 -> 0 | C7: =CFyU!F15 -> -84920548 | D7: =CFyU!F21 -> 0 | E7: =CFyU!F19 -> 74013652 | F7: =CFyU!F17 -> 4.9219079e+08 | G7: =SUM(B7:F7) -> 4.8128389e+08 | H7: ='CTV y CResult'!E61 -> 1480273050 | I7: ='Resumen Cred'!F10+'Resumen Cred'!H10 -> 0 | J7: =CFyU!F25 -> 64090000 | K7: =CFyU!F10 -> 0 | L7: =SUM(H7:K7) -> 1544363050 | M7: =L7-G7 -> 1063079156 | N7: =N6+M7 -> 63528062
A8: 5 | B8: =CFyU!G14 -> 0 | C8: =CFyU!G15 -> -90041096 | D8: =CFyU!G21 -> 0 | E8: =CFyU!G19 -> 83956732 | F8: =CFyU!G17 -> 5.5831227e+08 | G8: =SUM(B8:F8) -> 5.5222791e+08 | H8: ='CTV y CResult'!F61 -> 1679134650 | I8: ='Resumen Cred'!F11+'Resumen Cred'!H11 -> 0 | J8: =CFyU!G25 -> 64090000 | K8: =CFyU!G10 -> 0 | L8: =SUM(H8:K8) -> 1743224650 | M8: =L8-G8 -> 1190996742 | N8: =N7+M8 -> 1254524804
A9: 6 | B9: =CFyU!H14 -> 0 | C9: =CFyU!H15 -> -1.0154795e+08 | D9: =CFyU!H21 -> 0 | E9: =CFyU!H19 -> 95500551 | F9: =CFyU!H17 -> 6.3507867e+08 | G9: =SUM(B9:F9) -> 6.2903127e+08 | H9: ='CTV y CResult'!G61 -> 1910011027 | I9: ='Resumen Cred'!F12+'Resumen Cred'!H12 -> 0 | J9: =CFyU!H25 -> 39900000 | K9: =CFyU!H10 -> 0 | L9: =SUM(H9:K9) -> 1949911027 | M9: =L9-G9 -> 1320879754 | N9: =N8+M9 -> 2575404558
A10: 7 | B10: =CFyU!I14 -> 0 | C10: =CFyU!I15 -> -1.1288219e+08 | D10: =CFyU!I21 -> 0 | E10: =CFyU!I19 -> 106420340 | F10: =CFyU!I17 -> 707695261 | G10: =SUM(B10:F10) -> 7.0123341e+08 | H10: ='CTV y CResult'!H61 -> 2128406800 | I10: ='Resumen Cred'!F13+'Resumen Cred'!H13 -> 0 | J10: =CFyU!I25 -> 39900000 | K10: =CFyU!I10 -> 0 | L10: =SUM(H10:K10) -> 2168306800 | M10: =L10-G10 -> 1467073391 | N10: =N9+M10 -> 4042477949
A11: 8 | B11: =CFyU!J14 -> 0 | C11: =CFyU!J15 -> 36821918 | D11: =CFyU!J21 -> 0 | E11: =CFyU!J19 -> 117783860 | F11: =CFyU!J17 -> 783262669 | G11: =SUM(B11:F11) -> 9.3786845e+08 | H11: ='CTV y CResult'!I61 -> 2355677200 | I11: ='Resumen Cred'!F14+'Resumen Cred'!H14 -> 0 | J11: =CFyU!J25 -> 39900000 | K11: =CFyU!J10 -> 0 | L11: =SUM(H11:K11) -> 2395577200 | M11: =L11-G11 -> 1457708753 | N11: =N10+M11 -> 5500186702
A12: 9 | B12: =CFyU!K14 -> 0 | C12: =CFyU!K15 -> 8.9005479e+08 | D12: =CFyU!K21 -> 0 | E12: =CFyU!K19 -> 1.2959127e+08 | F12: =CFyU!K17 -> 8.6178193e+08 | G12: =SUM(B12:F12) -> 1881427991 | H12: ='CTV y CResult'!J61 -> 2591825350 | I12: ='Resumen Cred'!F15+'Resumen Cred'!H15 -> 0 | J12: =CFyU!K25 -> 39900000 | K12: =CFyU!K10 -> 0 | L12: =SUM(H12:K12) -> 2631725350 | M12: =L12-G12 -> 7.5029736e+08 | N12: =N11+M12 -> 6250484061
A13: 10 | B13: =CFyU!L14-'Inv AF'!O80 -> -1348000000 | C13: =-InvAT!L13+InvAT!L22 -> -1783053041 | D13: =CFyU!L21 -> 0 | E13: =CFyU!L19 -> 1.4202012e+08 | F13: =CFyU!L17 -> 9.4443378e+08 | G13: =SUM(B13:F13) -> -2044599142 | H13: ='CTV y CResult'!K61 -> 2840402350 | I13: ='Resumen Cred'!F16+'Resumen Cred'!H16 -> 0 | J13: =CFyU!L25 -> 39900000 | K13: =CFyU!L10 -> 0 | L13: =SUM(H13:K13) -> 2880302350 | M13: =L13-G13 -> 4924901492 | N13: =N12+M13 -> 11175385553
A15: Suma. | B15: =SUM(B3:B13) -> 519950000 | C15: =SUM(C3:C13) -> 0 | D15: =SUM(D3:D13) -> 99844500 | E15: =SUM(E3:E13) -> 9.0488952e+08 | F15: =SUM(F3:F13) -> 6017515298 | G15: =SUM(G3:G13) -> 7542199317 | H15: =SUM(H3:H13) -> 18097790370 | I15: =SUM(I3:I13) -> 0 | ... L15: =SUM(L3:L13) -> 18717584870 | M15: =L15-G15 -> 11175385553 | N15: =N13 -> 11175385553
C17: Beneficio Neto | D17: =N15 -> 11175385553
C18: Periodo de Recupero de la Inversión | E18: en años
C19: TIR modificada | D19: =IRR(M3:M13) -> 0.29718654
A24: Formulación para el Inversor
A25: Año | B25: Aporte de Capital | C25: Total Egresos | D25: Dividendos en efectivo | E25: Saldo propio de Fuentes y Usos | F25: Total Ingresos | G25: Saldo Anual | H25: Saldo Acumulado
A26: 0 | B26: =CFyU!B6 -> 2047258500 | C26: =B26 -> 2047258500 | D26: 0 | E26: =CFyU!B28 -> 0 | F26: =SUM(D26:E26) -> 0 | G26: =F26-C26 -> -2047258500 | H26: =G26 -> -2047258500
A27: 1 | B27: =CFyU!C6 -> 1728084784 | C27: =B27 -> 1728084784 | D27: =CFyU!C20 -> 0 | E27: =CFyU!C28 -> 3.3757106e+08 | F27: =SUM(D27:E27) -> 3.3757106e+08 | G27: =F27-C27 -> -1390513724 | H27: =H26+G27 -> -3437772224
A28: 2 | B28: =CFyU!D6 -> 0 | C28: =B28 -> 0 | D28: =CFyU!D20 -> 0 | E28: =CFyU!D28 -> 1239849219 | F28: =SUM(D28:E28) -> 1239849219 | G28: =F28-C28 -> 1239849219 | H28: =H27+G28 -> -2197923005
A29: 3 | B29: =CFyU!E6 -> 0 | C29: =B29 -> 0 | D29: =CFyU!E20 -> 0 | E29: =CFyU!E28 -> 1198371910 | F29: =SUM(D29:E29) -> 1198371910 | G29: =F29-C29 -> 1198371910 | H29: =H28+G29 -> -9.9955109e+08
A30: 4 | B30: =CFyU!F6 -> 0 | C30: =B30 -> 0 | D30: =CFyU!F20 -> 0 | E30: =CFyU!F28 -> 1063079156 | F30: =SUM(D30:E30) -> 1063079156 | G30: =F30-C30 -> 1063079156 | H30: =H29+G30 -> 63528062
A31: 5 | B31: =CFyU!G6 -> 0 | C31: =B31 -> 0 | D31: =CFyU!G20 -> 0 | E31: =CFyU!G28 -> 1190996742 | F31: =SUM(D31:E31) -> 1190996742 | G31: =F31-C31 -> 1190996742 | H31: =H30+G31 -> 1254524804
A32: 6 | B32: =CFyU!H6 | C32: =B32 | D32: =CFyU!H20 -> 0 | E32: =CFyU!H28 -> 1320879754 | F32: =SUM(D32:E32) -> 1320879754 | G32: =F32-C32 -> 1320879754 | H32: =H31+G32 -> 2575404558
A33: 7 | B33: =CFyU!I6 -> 0 | C33: =B33 -> 0 | D33: =CFyU!I20 -> 0 | E33: =CFyU!I28 -> 1467073391 | F33: =SUM(D33:E33) -> 1467073391 | G33: =F33-C33 -> 1467073391 | H33: =H32+G33 -> 4042477949
A34: 8 | B34: =CFyU!J6 -> 0 | C34: =B34 -> 0 | D34: =CFyU!J20 -> 0 | E34: =CFyU!J28 -> 1457708753 | F34: =SUM(D34:E34) -> 1457708753 | G34: =F34-C34 -> 1457708753 | H34: =H33+G34 -> 5500186702
A35: 9 | B35: =CFyU!K6 -> 0 | C35: =B35 -> 0 | D35: =CFyU!K20 -> 0 | E35: =CFyU!K28 -> 7.5029736e+08 | F35: =SUM(D35:E35) -> 7.5029736e+08 | G35: =F35-C35 -> 7.5029736e+08 | H35: =H34+G35 -> 6250484061
A36: 10 | B36: =-'Inv AF'!O80-CFyU!M15+CFyU!M7 -> -4638910575 | C36: =B36 -> -4638910575 | D36: =CFyU!L20 -> 0 | E36: =CFyU!L28 -> 2.8599092e+08 | F36: =SUM(D36:E36) -> 2.8599092e+08 | G36: =F36-C36 -> 4924901492 | H36: =H35+G36 -> 11175385553
A38: Suma. | B38: =SUM(B26:B36) -> -8.6356729e+08 | C38: =SUM(C26:C36) -> -8.6356729e+08 | D38: =SUM(D26:D36) -> 0 | E38: =SUM(E26:E36) -> 10311818262 | F38: =SUM(F26:F36) -> 10311818262 | G38: =F38-C38 -> 11175385553 | H38: =H36 -> 11175385553
C41: Beneficio Neto | D41: =H38 -> 11175385553 | E41: para el inversor
C42: Periodo de Recupero de la Inversión | E42: en años para el inversor
C43: TIR | D43: =IRR(G26:G36) -> 0.29718654
