Workbook

Sheet Análisis
B2: INVERSIÓN EN ACTIVO FIJO | C2: SAN NICOLÁS | D2: ALBERTI | E2: SAN LUIS
B3: Costo terreno [USD/m2] | C3: 166 | D3: 40 | E3: 1.81
B4: Superficie terreno [m2] | C4: 5000 | D4: 5000 | E4: 5000
B5: Inversión en terreno [USD] | C5: =C3*C4 -> 830000 | D5: =D3*D4 -> 200000 | E5: =E3*E4 -> 9050
B6: Inversión nave industrial [USD] | C6: 2062500 | D6: 2062500 | E6: 2062500
B7: Inversión equipos [USD] | C7: 687500 | D7: 687500 | E7: 687500
B8: TOTAL ACTIVO FIJO [USD] | C8: =C5+C6+C7 -> 3580000 | D8: =D5+D6+D7 -> 2950000 | E8: =E5+E6+E7 -> 2759050
B10: AMORTIZACIONES | C10: SAN NICOLÁS | D10: ALBERTI | E10: SAN LUIS
B11: Vida útil terreno [años] | C11: 10 | D11: 10 | E11: 10
B12: Vida útil nave industrial [años] | C12: 10 | D12: 10 | E12: 10
B13: Vida útil equipos [años] | C13: 5 | D13: 5 | E13: 5
B14: Amortiz. anual terreno [USD/año] | C14: =C5/C11 -> 83000 | D14: =D5/D11 -> 20000 | E14: =E5/E11 -> 905
B15: Amortiz. anual nave industrial [USD/año] | C15: =C6/C12 -> 206250 | D15: =D6/D12 -> 206250 | E15: =E6/E12 -> 206250
B16: Amortiz. anual equipos [USD/año] | C16: =C7/C13 -> 137500 | D16: =D7/D13 -> 137500 | E16: =E7/E13 -> 137500
B17: TOTAL AMORTIZACIÓN ANUAL [USD/año] | C17: =C14+C15+C16 -> 426750 | D17: =D14+D15+D16 -> 363750 | E17: =E14+E15+E16 -> 344655
B19: PRECIO DE VENTA | C19: SAN NICOLÁS | D19: ALBERTI | E19: SAN LUIS | F19: Precio corregido
B20: Costo de producción por cuchara [USD] | C20: 840000 | D20: 840000 | E20: 840000
B21: Margen bruto [%] | C21: 0.2 | D21: 0.2 | E21: 0.2
B22: Costo transporte MP por cuchara [USD] | C22: =C31 -> 25812 | D22: =D31 -> 56280 | E22: =E31 -> 65088
B23: Costo transporte PT prom. pond. por cuchara [USD] | C23: =(E35*I49+E36*I50+E37*I51)/I52 -> 8492.4444 | D23: =(H35*P49+H36*P50+H37*P51)/P52 -> 9795.4074 | E23: =(K35*W49+K36*W50+K37*W51)/W52 -> 19093.333
B24: Costo total por cuchara [USD] | C24: =C20+C22+C23 -> 874304.44 | D24: =D20+D22+D23 -> 906075.41 | E24: =E20+E22+E23 -> 924181.33
B25: PRECIO DE VENTA [USD/cuchara] | C25: =C24/(1-C21) -> 1092880.6 | D25: =D24/(1-D21) -> 1132594.3 | E25: =E24/(1-E21) -> 1155226.7 | F25: =AVERAGE(C25:E25) -> 1126900.5 | G25: Como hay un único precio de mercado y 3 alternativas debido a los costos de cada localización, se toma un único precio promedio
B27: TRANSPORTE DE MATERIA PRIMA | C27: SAN NICOLÁS | D27: ALBERTI | E27: SAN LUIS
B28: Costo MP [USD/km] | C28: 18 | D28: 14 | E28: 12
B29: Distancia al proveedor (AMBA) [km] | C29: 239 | D29: 670 | E29: 904
B30: Semirremolques por cuchara | C30: 6 | D30: 6 | E30: 6
B31: Costo transporte MP por cuchara [USD] | C31: =C28*C29*C30 -> 25812 | D31: =D28*D29*D30 -> 56280 | E31: =E28*E29*E30 -> 65088
B33: TRANSPORTE DE PRODUCTO TERMINADO | C33: SAN NICOLÁS | F33: ALBERTI | I33: SAN LUIS | L33: Distancias corregidas
B34: Cliente | C34: Costo/km [USD] | D34: Dist. [km] | E34: Costo/cuchara [USD] | F34: Costo/km [USD] | G34: Dist. [km] | H34: Costo/cuchara [USD] | I34: Costo/km [USD] | J34: Dist. [km] | K34: Costo/cuchara [USD]
B35: Metcon (San Nicolás) | C35: 22 | D35: 10 | E35: =C35*D35 -> 220 | F35: 22 | G35: 362 | H35: =F35*G35 -> 7964 | I35: 24 | J35: 733 | K35: =I35*J35 -> 17592
B36: Zapla (Jujuy) | C36: 14 | D36: 254 | E36: =C36*D36 -> 3556 | F36: 12 | G36: 508 | H36: =F36*G36 -> 6096 | I36: 24 | J36: 727 | K36: =I36*J36 -> 17448
B37: Acerbrag (Bragado) | C37: 18 | D37: 1288 | E37: =C37*D37 -> 23184 | F37: 16 | G37: 906 | H37: =F37*G37 -> 14496 | I37: 18 | J37: 1232 | K37: =I37*J37 -> 22176
B40: CRÉDITO FISCAL | C40: SAN NICOLÁS | D40: ALBERTI | E40: SAN LUIS | F40: Análisis de crédito fiscal corregido. Se puede ver en fila la fila 79 esta reducción para San Luis
B41: Crédito fiscal [USD] (3% × AF) | C41: 0 | D41: 0 | E41: =E8*0.03 -> 82771.5 | F41: Crédito fiscal 10 años. Se descuenta de los impuestos a pagar cada año.
B44: ACTIVO DE TRABAJO | C44: SAN NICOLÁS | D44: ALBERTI | E44: SAN LUIS | F44: Justificación de activo de trabajo añadida
B45: Inversión activo de trabajo [USD] | C45: =ROUND((C20*D52+C31*D52+E35*D49+E36*D50+E37*D51)/12,0) -> 72169 | D45: =ROUND((C20*K52+D31*K52+H35*K49+H36*K50+H37*K51)/12,0) -> 75354 | E45: =ROUND((C20*R52+E31*R52+K35*R49+K36*R50+K37*R51)/12,0) -> 76890 | F45: 1 mes de costos operativos variables del Año 1 (producción + transporte MP + transporte PT). Criterio: período mínimo de capital inmovilizado antes del primer cobro.
B47: VENTAS [unidades] - Equipo 523 | C47: SAN NICOLÁS | J47: ALBERTI | Q47: SAN LUIS
B48: Cliente | D48: Año 1 | E48: Año 2 | F48: Año 3 | G48: Año 4 | H48: Año 5 | I48: TOTAL | K48: Año 1 | L48: Año 2 | M48: Año 3 | N48: Año 4 | O48: Año 5 | P48: TOTAL | R48: Año 1 | S48: Año 2 | T48: Año 3 | U48: Año 4 | V48: Año 5 | W48: TOTAL
B49: Metcon | C49: 0 | D49: 1 | E49: 3 | F49: 3 | G49: 3 | H49: 3 | I49: =SUM(D49:H49) -> 13 | J49: 0 | K49: 1 | L49: 3 | M49: 3 | N49: 3 | O49: 3 | P49: =SUM(K49:O49) -> 13 | Q49: 0 | R49: 1 | S49: 3 | T49: 3 | U49: 3 | V49: 3 | W49: =SUM(R49:V49) -> 13
B50: Zapla | C50: 0 | D50: 0 | E50: 0 | F50: 0 | G50: 0 | H50: 5 | I50: =SUM(D50:H50) -> 5 | J50: 0 | K50: 0 | L50: 0 | M50: 0 | N50: 0 | O50: 5 | P50: =SUM(K50:O50) -> 5 | Q50: 0 | R50: 0 | S50: 0 | T50: 0 | U50: 0 | V50: 5 | W50: =SUM(R50:V50) -> 5
B51: Acerbrag | C51: 0 | D51: 0 | E51: 5 | F51: 2 | G51: 1 | H51: 1 | I51: =SUM(D51:H51) -> 9 | J51: 0 | K51: 0 | L51: 5 | M51: 2 | N51: 1 | O51: 1 | P51: =SUM(K51:O51) -> 9 | Q51: 0 | R51: 0 | S51: 5 | T51: 2 | U51: 1 | V51: 1 | W51: =SUM(R51:V51) -> 9
B52: TOTAL | C52: 0 | D52: =D49+D50+D51 -> 1 | E52: =E49+E50+E51 -> 8 | F52: =F49+F50+F51 -> 5 | G52: =G49+G50+G51 -> 4 | H52: =H49+H50+H51 -> 9 | I52: =I49+I50+I51 -> 27 | J52: 0 | K52: =K49+K50+K51 -> 1 | L52: =L49+L50+L51 -> 8 | M52: =M49+M50+M51 -> 5 | N52: =N49+N50+N51 -> 4 | O52: =O49+O50+O51 -> 9 | P52: =P49+P50+P51 -> 27 | Q52: 0 | R52: =R49+R50+R51 -> 1 | S52: =S49+S50+S51 -> 8 | T52: =T49+T50+T51 -> 5 | U52: =U49+U50+U51 -> 4 | V52: =V49+V50+V51 -> 9 | W52: =W49+W50+W51 -> 27
B54: 9. FLUJO DE FONDOS | C54: SAN NICOLÁS | J54: ALBERTI | Q54: SAN LUIS
C55: Año 0 | D55: Año 1 | E55: Año 2 | F55: Año 3 | G55: Año 4 | H55: Año 5 | I55: TOTAL | J55: Año 0 | K55: Año 1 | L55: Año 2 | M55: Año 3 | N55: Año 4 | O55: Año 5 | P55: TOTAL | Q55: Año 0 | R55: Año 1 | S55: Año 2 | T55: Año 3 | U55: Año 4 | V55: Año 5 | W55: TOTAL
B56: EGRESOS
B57: Inversión Activo Fijo [USD] | C57: =C8 -> 3580000 | D57: 0 | E57: 0 | F57: 0 | G57: 0 | H57: 0 | I57: =C8 -> 3580000 | J57: =D8 -> 2950000 | K57: 0 | L57: 0 | M57: 0 | N57: 0 | O57: 0 | P57: =D8 -> 2950000 | Q57: =E8 -> 2759050 | R57: 0 | S57: 0 | T57: 0 | U57: 0 | V57: 0 | W57: =E8 -> 2759050
B58: Inversión Activo de Trabajo [USD] | C58: =C45 -> 72169 | D58: 0 | E58: 0 | F58: 0 | G58: 0 | H58: 0 | I58: =C45 -> 72169 | J58: =D45 -> 75354 | K58: 0 | L58: 0 | M58: 0 | N58: 0 | O58: 0 | P58: =D45 -> 75354 | Q58: =E45 -> 76890 | R58: 0 | S58: 0 | T58: 0 | U58: 0 | V58: 0 | W58: =E45 -> 76890
B59: (-) Crédito Fiscal [USD] | C59: 0 | D59: 0 | E59: 0 | F59: 0 | G59: 0 | H59: 0 | I59: 0 | J59: 0 | K59: 0 | L59: 0 | M59: 0 | N59: 0 | O59: 0 | P59: 0 | Q59: =-$E$38 -> 0 | R59: =-$E$38 -> 0 | S59: =-$E$38 -> 0 | T59: =-$E$38 -> 0 | U59: =-$E$38 -> 0 | V59: =-$E$38 -> 0 | W59: =-E41 -> -82771.5
B60: TOTAL EGRESOS [USD] | C60: =C57+C58+C59 -> 3652169 | D60: =D57+D58+D59 -> 0 | E60: =E57+E58+E59 -> 0 | F60: =F57+F58+F59 -> 0 | G60: =G57+G58+G59 -> 0 | H60: =H57+H58+H59 -> 0 | I60: =I57+I58+I59+I79 -> 4823754.8 | J60: =J57+J58+J59 -> 3025354 | K60: =K57+K58+K59 -> 0 | L60: =L57+L58+L59 -> 0 | M60: =M57+M58+M59 -> 0 | N60: =N57+N58+N59 -> 0 | O60: =O57+O58+O59 -> 0 | P60: =P57+P58+P59+P79 -> 4061235.8 | Q60: =Q57+Q58+Q59 -> 2835940 | R60: =R57+R58+R59 -> 0 | S60: =S57+S58+S59 -> 0 | T60: =T57+T58+T59 -> 0 | U60: =U57+U58+U59 -> 0 | V60: =V57+V58+V59 -> 0 | W60: =W57+W58+W59+W79 -> 3394726.7
B61: INGRESOS
B62: Ingresos Metcon [USD] | C62: 0 | D62: =$F$25*D49 -> 1126900.5 | E62: =$F$25*E49 -> 3380701.5 | F62: =$F$25*F49 -> 3380701.5 | G62: =$F$25*G49 -> 3380701.5 | H62: =$F$25*H49 -> 3380701.5 | I62: =SUM(D62:H62) -> 14649706 | J62: 0 | K62: =$F$25*K49 -> 1126900.5 | L62: =$F$25*L49 -> 3380701.5 | M62: =$F$25*M49 -> 3380701.5 | N62: =$F$25*N49 -> 3380701.5 | O62: =$F$25*O49 -> 3380701.5 | P62: =SUM(K62:O62) -> 14649706 | Q62: 0 | R62: =$F$25*R49 -> 1126900.5 | S62: =$F$25*S49 -> 3380701.5 | T62: =$F$25*T49 -> 3380701.5 | U62: =$F$25*U49 -> 3380701.5 | V62: =$F$25*V49 -> 3380701.5 | W62: =SUM(R62:V62) -> 14649706
B63: Ingresos Zapla [USD] | C63: 0 | D63: =$F$25*D50 -> 0 | E63: =$F$25*E50 -> 0 | F63: =$F$25*F50 -> 0 | G63: =$F$25*G50 -> 0 | H63: =$F$25*H50 -> 5634502.5 | I63: =SUM(D63:H63) -> 5634502.5 | J63: 0 | K63: =$F$25*K50 -> 0 | L63: =$F$25*L50 -> 0 | M63: =$F$25*M50 -> 0 | N63: =$F$25*N50 -> 0 | O63: =$F$25*O50 -> 5634502.5 | P63: =SUM(K63:O63) -> 5634502.5 | Q63: 0 | R63: =$F$25*R50 -> 0 | S63: =$F$25*S50 -> 0 | T63: =$F$25*T50 -> 0 | U63: =$F$25*U50 -> 0 | V63: =$F$25*V50 -> 5634502.5 | W63: =SUM(R63:V63) -> 5634502.5
B64: Ingresos Acerbrag [USD] | C64: 0 | D64: =$F$25*D51 -> 0 | E64: =$F$25*E51 -> 5634502.5 | F64: =$F$25*F51 -> 2253801 | G64: =$F$25*G51 -> 1126900.5 | H64: =$F$25*H51 -> 1126900.5 | I64: =SUM(D64:H64) -> 10142104 | J64: 0 | K64: =$F$25*K51 -> 0 | L64: =$F$25*L51 -> 5634502.5 | M64: =$F$25*M51 -> 2253801 | N64: =$F$25*N51 -> 1126900.5 | O64: =$F$25*O51 -> 1126900.5 | P64: =SUM(K64:O64) -> 10142104 | Q64: 0 | R64: =$F$25*R51 -> 0 | S64: =$F$25*S51 -> 5634502.5 | T64: =$F$25*T51 -> 2253801 | U64: =$F$25*U51 -> 1126900.5 | V64: =$F$25*V51 -> 1126900.5 | W64: =SUM(R64:V64) -> 10142104
B65: Valor residual activo fijo [USD] | C65: 0 | D65: 0 | E65: 0 | F65: 0 | G65: 0 | H65: =C5*(1-5/C11)+C6*(1-5/C12)+C7*(1-5/C13) -> 1446250 | I65: =H65 -> 1446250 | J65: 0 | K65: 0 | L65: 0 | M65: 0 | N65: 0 | O65: =D5*(1-5/D11)+D6*(1-5/D12)+D7*(1-5/D13) -> 1131250 | P65: =O65 -> 1131250 | Q65: 0 | R65: 0 | S65: 0 | T65: 0 | U65: 0 | V65: =E5*(1-5/E11)+E6*(1-5/E12)+E7*(1-5/E13) -> 1035775 | W65: =V65 -> 1035775
B66: Recupero activo de trabajo [USD] | C66: 0 | D66: 0 | E66: 0 | F66: 0 | G66: 0 | H66: =C45 -> 72169 | I66: =H66 -> 72169 | J66: 0 | K66: 0 | L66: 0 | M66: 0 | N66: 0 | O66: =D45 -> 75354 | P66: =O66 -> 75354 | Q66: 0 | R66: 0 | S66: 0 | T66: 0 | U66: 0 | V66: =E45 -> 76890 | W66: =V66 -> 76890
B67: TOTAL INGRESOS [USD] | C67: =C62+C63+C64+C65+C66 -> 0 | D67: =D62+D63+D64+D65+D66 -> 1126900.5 | E67: =E62+E63+E64+E65+E66 -> 9015204 | F67: =F62+F63+F64+F65+F66 -> 5634502.5 | G67: =G62+G63+G64+G65+G66 -> 4507602 | H67: =H62+H63+H64+H65+H66 -> 11660523 | I67: =I62+I63+I64+I65+I66 -> 31944732 | J67: =J62+J63+J64+J65+J66 -> 0 | ... W67: =W62+W63+W64+W65+W66 -> 31538978
B68: COSTOS OPERATIVOS
B69: Costo de producción [USD] | C69: 0 | D69: =C20*D52 -> 840000 | E69: =C20*E52 -> 6720000 | F69: =C20*F52 -> 4200000 | G69: =C20*G52 -> 3360000 | H69: =C20*H52 -> 7560000 | I69: =SUM(D69:H69) -> 22680000 | J69: 0 | K69: =C20*K52 -> 840000 | L69: =C20*L52 -> 6720000 | M69: =C20*M52 -> 4200000 | N69: =C20*N52 -> 3360000 | O69: =C20*O52 -> 7560000 | P69: =SUM(K69:O69) -> 22680000 | Q69: 0 | R69: =C20*R52 -> 840000 | S69: =C20*S52 -> 6720000 | T69: =C20*T52 -> 4200000 | U69: =C20*U52 -> 3360000 | V69: =C20*V52 -> 7560000 | W69: =SUM(R69:V69) -> 22680000
B70: Costo transporte materia prima [USD] | C70: 0 | D70: =C31*D52 -> 25812 | E70: =C31*E52 -> 206496 | F70: =C31*F52 -> 129060 | G70: =C31*G52 -> 103248 | H70: =C31*H52 -> 232308 | I70: =SUM(D70:H70) -> 696924 | J70: 0 | K70: =D31*K52 -> 56280 | L70: =D31*L52 -> 450240 | M70: =D31*M52 -> 281400 | N70: =D31*N52 -> 225120 | O70: =D31*O52 -> 506520 | P70: =SUM(K70:O70) -> 1519560 | Q70: 0 | R70: =E31*R52 -> 65088 | S70: =E31*S52 -> 520704 | T70: =E31*T52 -> 325440 | U70: =E31*U52 -> 260352 | V70: =E31*V52 -> 585792 | W70: =SUM(R70:V70) -> 1757376
B71: Costo transporte PT – Metcon [USD] | C71: 0 | D71: =E35*D49 -> 220 | E71: =E35*E49 -> 660 | F71: =E35*F49 -> 660 | G71: =E35*G49 -> 660 | H71: =E35*H49 -> 660 | I71: =SUM(D71:H71) -> 2860 | J71: 0 | K71: =H35*K49 -> 7964 | L71: =H35*L49 -> 23892 | M71: =H35*M49 -> 23892 | N71: =H35*N49 -> 23892 | O71: =H35*O49 -> 23892 | P71: =SUM(K71:O71) -> 103532 | Q71: 0 | R71: =K35*R49 -> 17592 | S71: =K35*S49 -> 52776 | T71: =K35*T49 -> 52776 | U71: =K35*U49 -> 52776 | V71: =K35*V49 -> 52776 | W71: =SUM(R71:V71) -> 228696
B72: Costo transporte PT – Zapla [USD] | C72: 0 | D72: =E36*D50 -> 0 | E72: =E36*E50 -> 0 | F72: =E36*F50 -> 0 | G72: =E36*G50 -> 0 | H72: =E36*H50 -> 17780 | I72: =SUM(D72:H72) -> 17780 | J72: 0 | K72: =H36*K50 -> 0 | L72: =H36*L50 -> 0 | M72: =H36*M50 -> 0 | N72: =H36*N50 -> 0 | O72: =H36*O50 -> 30480 | P72: =SUM(K72:O72) -> 30480 | Q72: 0 | R72: =K36*R50 -> 0 | S72: =K36*S50 -> 0 | T72: =K36*T50 -> 0 | U72: =K36*U50 -> 0 | V72: =K36*V50 -> 87240 | W72: =SUM(R72:V72) -> 87240
B73: Costo transporte PT – Acerbrag [USD] | C73: 0 | D73: =E37*D51 -> 0 | E73: =E37*E51 -> 115920 | F73: =E37*F51 -> 46368 | G73: =E37*G51 -> 23184 | H73: =E37*H51 -> 23184 | I73: =SUM(D73:H73) -> 208656 | J73: 0 | K73: =H37*K51 -> 0 | L73: =H37*L51 -> 72480 | M73: =H37*M51 -> 28992 | N73: =H37*N51 -> 14496 | O73: =H37*O51 -> 14496 | P73: =SUM(K73:O73) -> 130464 | Q73: 0 | R73: =K37*R51 -> 0 | S73: =K37*S51 -> 110880 | T73: =K37*T51 -> 44352 | U73: =K37*U51 -> 22176 | V73: =K37*V51 -> 22176 | W73: =SUM(R73:V73) -> 199584
B74: Total costo transporte PT [USD] | C74: =C71+C72+C73 -> 0 | D74: =D71+D72+D73 -> 220 | E74: =E71+E72+E73 -> 116580 | F74: =F71+F72+F73 -> 47028 | G74: =G71+G72+G73 -> 23844 | H74: =H71+H72+H73 -> 41624 | I74: =I71+I72+I73 -> 229296 | J74: =J71+J72+J73 -> 0 | ... W74: =W71+W72+W73 -> 515520
B75: Amortizaciones [USD/año] | C75: 0 | D75: =C17 -> 426750 | E75: =C17 -> 426750 | F75: =C17 -> 426750 | G75: =C17 -> 426750 | H75: =C17 -> 426750 | I75: =SUM(D75:H75) -> 2133750 | J75: 0 | K75: =D17 -> 363750 | L75: =D17 -> 363750 | M75: =D17 -> 363750 | N75: =D17 -> 363750 | O75: =D17 -> 363750 | P75: =SUM(K75:O75) -> 1818750 | Q75: 0 | R75: =E17 -> 344655 | S75: =E17 -> 344655 | T75: =E17 -> 344655 | U75: =E17 -> 344655 | V75: =E17 -> 344655 | W75: =SUM(R75:V75) -> 1723275
B76: TOTAL COSTOS OPERATIVOS [USD] | C76: =C69+C70+C74+C75 -> 0 | D76: =D69+D70+D74+D75 -> 1292782 | E76: =E69+E70+E74+E75 -> 7469826 | F76: =F69+F70+F74+F75 -> 4802838 | G76: =G69+G70+G74+G75 -> 3913842 | H76: =H69+H70+H74+H75 -> 8260682 | I76: =I69+I70+I74+I75 -> 25739970 | J76: =J69+J70+J74+J75 -> 0 | ... W76: =W69+W70+W74+W75 -> 26676171
B77: RESULTADO ECONÓMICO
B78: Utilidad antes de impuestos [USD] | C78: =(C62+C63+C64)-C76 -> 0 | D78: =(D62+D63+D64)-D76 -> -165881.51 | E78: =(E62+E63+E64)-E76 -> 1545378 | F78: =(F62+F63+F64)-F76 -> 831664.47 | G78: =(G62+G63+G64)-G76 -> 593759.98 | H78: =(H62+H63+H64)-H76 -> 1881422.4 | I78: =(I62+I63+I64)-I76 -> 4686343.3 | J78: =(J62+J63+J64)-J76 -> 0 | ... W78: =(W62+W63+W64)-W76 -> 3750142.3
B79: Impuestos [USD] | C79: 0 | D79: =IF(D78>0,D78*0.25,0) -> 0 | E79: =IF(E78>0,E78*0.25,0) -> 386344.49 | F79: =IF(F78>0,F78*0.25,0) -> 207916.12 | G79: =IF(G78>0,G78*0.25,0) -> 148439.99 | H79: =IF(H78>0,H78*0.25,0) -> 470355.61 | I79: =IF(I78>0,I78*0.25,0) -> 1171585.8 | J79: 0 | K79: =IF(K78>0,K78*0.25,0) -> 0 | L79: =IF(L78>0,L78*0.25,0) -> 346210.49 | M79: =IF(M78>0,M78*0.25,0) -> 184117.12 | N79: =IF(N78>0,N78*0.25,0) -> 130085.99 | O79: =IF(O78>0,O78*0.25,0) -> 410741.61 | P79: =IF(P78>0,P78*0.25,0) -> 1035881.8 | Q79: 0 | R79: =MAX(0,IF(R78>0,R78*0.25-$E$41,0)) -> 0 | S79: =MAX(0,IF(S78>0,S78*0.25-$E$41,0)) -> 233775.74 | T79: =MAX(0,IF(T78>0,T78*0.25-$E$41,0)) -> 84048.367 | U79: =MAX(0,IF(U78>0,U78*0.25-$E$41,0)) -> 34139.244 | V79: =MAX(0,IF(V78>0,V78*0.25-$E$41,0)) -> 289594.86 | W79: =SUM(R79:V79) -> 641558.21
B80: GANANCIA NETA [USD] | C80: =C78-C79 -> 0 | D80: =D78-D79 -> -165881.51 | E80: =E78-E79 -> 1159033.5 | F80: =F78-F79 -> 623748.35 | G80: =G78-G79 -> 445319.98 | H80: =H78-H79 -> 1411066.8 | I80: =I78-I79 -> 3514757.5 | J80: =J78-J79 -> 0 | ... W80: =W78-W79 -> 3108584.1
B82: Formulación del proyecto - San Nicolás
B83: Año | C83: Activo Fijo | D83: Activo de Trabajo | E83: Impuestos | F83: Total Egresos | G83: Utilidad Antes de Impuestos | H83: Amortizaciones | I83: Total Ingresos | J83: Saldo Anual | K83: Saldo Acumulado
B84: Año 0 | C84: =C57 -> 3580000 | D84: =C58 -> 72169 | E84: =C79 -> 0 | F84: =SUM(C84:E84) -> 3652169 | G84: =C78 -> 0 | H84: =C75 -> 0 | I84: =SUM(G84:H84) -> 0 | J84: =I84-F84 -> -3652169 | K84: =J84 -> -3652169
B85: Año 1 | C85: =D57 -> 0 | D85: =D58 -> 0 | E85: =D79 -> 0 | F85: =SUM(C85:E85) -> 0 | G85: =D78 -> -165881.51 | H85: =D75 -> 426750 | I85: =SUM(G85:H85) -> 260868.49 | J85: =I85-F85 -> 260868.49 | K85: =K84+J85 -> -3391300.5
B86: Año 2 | C86: =E57 -> 0 | D86: =E58 -> 0 | E86: =E79 -> 386344.49 | F86: =SUM(C86:E86) -> 386344.49 | G86: =E78 -> 1545378 | H86: =E75 -> 426750 | I86: =SUM(G86:H86) -> 1972128 | J86: =I86-F86 -> 1585783.5 | K86: =K85+J86 -> -1805517
B87: Año 3 | C87: =F57 -> 0 | D87: =F58 -> 0 | E87: =F79 -> 207916.12 | F87: =SUM(C87:E87) -> 207916.12 | G87: =F78 -> 831664.47 | H87: =F75 -> 426750 | I87: =SUM(G87:H87) -> 1258414.5 | J87: =I87-F87 -> 1050498.4 | K87: =K86+J87 -> -755018.69
B88: Año 4 | C88: =G57 -> 0 | D88: =G58 -> 0 | E88: =G79 -> 148439.99 | F88: =SUM(C88:E88) -> 148439.99 | G88: =G78 -> 593759.98 | H88: =G75 -> 426750 | I88: =SUM(G88:H88) -> 1020510 | J88: =I88-F88 -> 872069.98 | K88: =K87+J88 -> 117051.29
B89: Año 5 | C89: =-H65 -> -1446250 | D89: =-H66 -> -72169 | E89: =H79 -> 470355.61 | F89: =SUM(C89:E89) -> -1048063.4 | G89: =H78 -> 1881422.4 | H89: =H75 -> 426750 | I89: =SUM(G89:H89) -> 2308172.4 | J89: =I89-F89 -> 3356235.8 | K89: =K88+J89 -> 3473287.1
B90: TOTAL | C90: =SUM(C84:C89) -> 2133750 | D90: =SUM(D84:D89) -> 0 | E90: =SUM(E84:E89) -> 1213056.2 | F90: =SUM(F84:F89) -> 3346806.2 | G90: =SUM(G84:G89) -> 4686343.3 | H90: =SUM(H84:H89) -> 2133750 | I90: =SUM(I84:I89) -> 6820093.3 | J90: =SUM(J84:J89) -> 3473287.1 | K90: =K89 -> 3473287.1
B92: Formulación del proyecto - Alberti
B93: Año | C93: Activo Fijo | D93: Activo de Trabajo | E93: Impuestos | F93: Total Egresos | G93: Utilidad Antes de Impuestos | H93: Amortizaciones | I93: Total Ingresos | J93: Saldo Anual | K93: Saldo Acumulado
B94: Año 0 | C94: =J57 -> 2950000 | D94: =J58 -> 75354 | E94: =J79 -> 0 | F94: =SUM(C94:E94) -> 3025354 | G94: =J78 -> 0 | H94: =J75 -> 0 | I94: =SUM(G94:H94) -> 0 | J94: =I94-F94 -> -3025354 | K94: =J94 -> -3025354
B95: Año 1 | C95: =K57 -> 0 | D95: =K58 -> 0 | E95: =K79 -> 0 | F95: =SUM(C95:E95) -> 0 | G95: =K78 -> -141093.51 | H95: =K75 -> 363750 | I95: =SUM(G95:H95) -> 222656.49 | J95: =I95-F95 -> 222656.49 | K95: =K94+J95 -> -2802697.5
B96: Año 2 | C96: =L57 -> 0 | D96: =L58 -> 0 | E96: =L79 -> 346210.49 | F96: =SUM(C96:E96) -> 346210.49 | G96: =L78 -> 1384842 | H96: =L75 -> 363750 | I96: =SUM(G96:H96) -> 1748592 | J96: =I96-F96 -> 1402381.5 | K96: =K95+J96 -> -1400316
B97: Año 3 | C97: =M57 -> 0 | D97: =M58 -> 0 | E97: =M79 -> 184117.12 | F97: =SUM(C97:E97) -> 184117.12 | G97: =M78 -> 736468.47 | H97: =M75 -> 363750 | I97: =SUM(G97:H97) -> 1100218.5 | J97: =I97-F97 -> 916101.35 | K97: =K96+J97 -> -484214.69
B98: Año 4 | C98: =N57 -> 0 | D98: =N58 -> 0 | E98: =N79 -> 130085.99 | F98: =SUM(C98:E98) -> 130085.99 | G98: =N78 -> 520343.98 | H98: =N75 -> 363750 | I98: =SUM(G98:H98) -> 884093.98 | J98: =I98-F98 -> 754007.98 | K98: =K97+J98 -> 269793.29
B99: Año 5 | C99: =-O65 -> -1131250 | D99: =-O66 -> -75354 | E99: =O79 -> 410741.61 | F99: =SUM(C99:E99) -> -795862.39 | G99: =O78 -> 1642966.4 | H99: =O75 -> 363750 | I99: =SUM(G99:H99) -> 2006716.4 | J99: =I99-F99 -> 2802578.8 | K99: =K98+J99 -> 3072372.1
B100: TOTAL | C100: =SUM(C94:C99) -> 1818750 | D100: =SUM(D94:D99) -> 0 | E100: =SUM(E94:E99) -> 1071155.2 | F100: =SUM(F94:F99) -> 2889905.2 | G100: =SUM(G94:G99) -> 4143527.3 | H100: =SUM(H94:H99) -> 1818750 | I100: =SUM(I94:I99) -> 5962277.3 | J100: =SUM(J94:J99) -> 3072372.1 | K100: =K99 -> 3072372.1
B102: Formulación del proyecto - San Luis
B103: Año | C103: Activo Fijo | D103: Activo de Trabajo | E103: Impuestos | F103: Total Egresos | G103: Utilidad Antes de Impuestos | H103: Amortizaciones | I103: Total Ingresos | J103: Saldo Anual | K103: Saldo Acumulado
B104: Año 0 | C104: =Q57 -> 2759050 | D104: =Q58 -> 76890 | E104: =Q79 -> 0 | F104: =SUM(C104:E104) -> 2835940 | G104: =Q78 -> 0 | H104: =Q75 -> 0 | I104: =SUM(G104:H104) -> 0 | J104: =I104-F104 -> -2835940 | K104: =J104 -> -2835940
B105: Año 1 | C105: =R57 -> 0 | D105: =R58 -> 0 | E105: =R79 -> 0 | F105: =SUM(C105:E105) -> 0 | G105: =R78 -> -140434.51 | H105: =R75 -> 344655 | I105: =SUM(G105:H105) -> 204220.49 | J105: =I105-F105 -> 204220.49 | K105: =K104+J105 -> -2631719.5
B106: Año 2 | C106: =S57 -> 0 | D106: =S58 -> 0 | E106: =S79 -> 233775.74 | F106: =SUM(C106:E106) -> 233775.74 | G106: =S78 -> 1266189 | H106: =S75 -> 344655 | I106: =SUM(G106:H106) -> 1610844 | J106: =I106-F106 -> 1377068.2 | K106: =K105+J106 -> -1254651.3
B107: Año 3 | C107: =T57 -> 0 | D107: =T58 -> 0 | E107: =T79 -> 84048.367 | F107: =SUM(C107:E107) -> 84048.367 | G107: =T78 -> 667279.47 | H107: =T75 -> 344655 | I107: =SUM(G107:H107) -> 1011934.5 | J107: =I107-F107 -> 927886.1 | K107: =K106+J107 -> -326765.19
B108: Año 4 | C108: =U57 -> 0 | D108: =U58 -> 0 | E108: =U79 -> 34139.244 | F108: =SUM(C108:E108) -> 34139.244 | G108: =U78 -> 467642.98 | H108: =U75 -> 344655 | I108: =SUM(G108:H108) -> 812297.98 | J108: =I108-F108 -> 778158.73 | K108: =K107+J108 -> 451393.54
B109: Año 5 | C109: =-V65 -> -1035775 | D109: =-V66 -> -76890 | E109: =V79 -> 289594.86 | F109: =SUM(C109:E109) -> -823070.14 | G109: =V78 -> 1489465.4 | H109: =V75 -> 344655 | I109: =SUM(G109:H109) -> 1834120.4 | J109: =I109-F109 -> 2657190.6 | K109: =K108+J109 -> 3108584.1
B110: TOTAL | C110: =SUM(C104:C109) -> 1723275 | D110: =SUM(D104:D109) -> 0 | E110: =SUM(E104:E109) -> 641558.21 | F110: =SUM(F104:F109) -> 2364833.2 | G110: =SUM(G104:G109) -> 3750142.3 | H110: =SUM(H104:H109) -> 1723275 | I110: =SUM(I104:I109) -> 5473417.3 | J110: =SUM(J104:J109) -> 3108584.1 | K110: =K109 -> 3108584.1
B112: RESUMEN DE INDICADORES | C112: SAN NICOLÁS | D112: ALBERTI | E112: SAN LUIS
B113: VAN ( 9%) [USD] | C113: =NPV(9%,J84:J89) -> 1405668.8 | D113: =NPV(9%,J94:J99) -> 1304876.1 | E113: =NPV(9%,J104:J109) -> 1380941.4
B114: TIR [%] | C114: =IRR(J84:J89) -> 0.20417893 | D114: =IRR(J94:J99) -> 0.21774213 | E114: =IRR(J104:J109) -> 0.23294437
B115: Beneficio neto [USD] | C115: =K89 -> 3473287.1 | D115: =K100 -> 3072372.1 | E115: =K110 -> 3108584.1

Sheet Ponderación
A1: Modelo de ponderación
A2: Lj = Σ Pi × Vfi /Vfi normalizado: mejor valor del factor = 1.00. Costos: menor = mejor (Vfi = MIN/valor). Beneficios: mayor = mejor (Vfi = valor/MAX).
A3: Factor | B3: Ponderación | C3: SAN NICOLÁS | D3: ALBERTI | E3: SAN LUIS
A4: FACTORES CUANTITATIVOS
A5: VAN ( 9%) [USD] | B5: 0.15 | C5: =Análisis!C113 -> 1405668.8 | D5: =Análisis!D113 -> 1304876.1 | E5: =Análisis!E113 -> 1380941.4
A6: Costo transp. MP [USD] | B6: 0.3 | C6: =Análisis!I70 -> 696924 | D6: =Análisis!P70 -> 1519560 | E6: =Análisis!W70 -> 1757376
A7: Costo transp. PT [USD] | B7: 0.25 | C7: =Análisis!I74 -> 229296 | D7: =Análisis!P74 -> 264476 | E7: =Análisis!W74 -> 515520
A8: Beneficio neto [USD] | B8: 0.1 | C8: =Análisis!C115 -> 3473287.1 | D8: =Análisis!D115 -> 3072372.1 | E8: =Análisis!E115 -> 3108584.1
A9: Impuestos [USD] | B9: 0.1 | C9: =Análisis!E90 -> 1213056.2 | D9: =Análisis!E100 -> 1071155.2 | E9: =Análisis!E110 -> 641558.21
A10: FACTORES CUALITATIVOS
A11: Disponibilidad de MO calificada | B11: 0.05 | C11: 8 | D11: 5 | E11: 4 | F11: Justificación en documento word adjunto
A12: Gestión ambiental in situ | B12: 0.05 | C12: 4 | D12: 9 | E12: 7 | F12: Justificación en documento word adjunto
A14: PUNTAJES NORMALIZADOS (Vfi)
A15: Factor | B15: Ponderación (Pi) | C15: SAN NICOLÁS | D15: ALBERTI | E15: SAN LUIS | F15: Dirección
A16: VAN (tasa 9%) [USD] | B16: =B5 -> 0.15 | C16: =IF(MAX(C5,D5,E5)=0,0,C5/MAX(C5,D5,E5)) -> 1 | D16: =IF(MAX(C5,D5,E5)=0,0,D5/MAX(C5,D5,E5)) -> 0.9282956 | E16: =IF(MAX(C5,D5,E5)=0,0,E5/MAX(C5,D5,E5)) -> 0.98240885 | F16: mayor = mejor
A17: Costo transp. MP [USD] | B17: =B6 -> 0.3 | C17: =IF(C6=0,0,MIN(C6,D6,E6)/C6) -> 1 | D17: =IF(D6=0,0,MIN(C6,D6,E6)/D6) -> 0.45863539 | E17: =IF(E6=0,0,MIN(C6,D6,E6)/E6) -> 0.3965708 | F17: menor = mejor
A18: Costo transp. PT [USD] | B18: =B7 -> 0.25 | C18: =IF(C7=0,0,MIN(C7,D7,E7)/C7) -> 1 | D18: =IF(D7=0,0,MIN(C7,D7,E7)/D7) -> 0.86698226 | E18: =IF(E7=0,0,MIN(C7,D7,E7)/E7) -> 0.44478585 | F18: menor = mejor
A19: Beneficio neto [USD] | B19: =B8 -> 0.1 | C19: =IF(MAX(C8,D8,E8)=0,0,C8/MAX(C8,D8,E8)) -> 1 | D19: =IF(MAX(C8,D8,E8)=0,0,D8/MAX(C8,D8,E8)) -> 0.88457188 | E19: =IF(MAX(C8,D8,E8)=0,0,E8/MAX(C8,D8,E8)) -> 0.89499774 | F19: mayor = mejor
A20: Impuestos [USD] | B20: =B9 -> 0.1 | C20: =IF(C9=0,0,MIN(C9,D9,E9)/C9) -> 0.52887756 | D20: =IF(D9=0,0,MIN(C9,D9,E9)/D9) -> 0.59894047 | E20: =IF(E9=0,0,MIN(C9,D9,E9)/E9) -> 1 | F20: menor = mejor
A21: Disponibilidad de MO calificada | B21: =B11 -> 0.05 | C21: =IF(MAX(C11,D11,E11)=0,0,C11/MAX(C11,D11,E11)) -> 1 | D21: =IF(MAX(C11,D11,E11)=0,0,D11/MAX(C11,D11,E11)) -> 0.625 | E21: =IF(MAX(C11,D11,E11)=0,0,E11/MAX(C11,D11,E11)) -> 0.5 | F21: mayor = mejor
A22: Gestión ambiental in situ | B22: =B12 -> 0.05 | C22: =IF(MAX(C12,D12,E12)=0,0,C12/MAX(C12,D12,E12)) -> 0.44444444 | D22: =IF(MAX(C12,D12,E12)=0,0,D12/MAX(C12,D12,E12)) -> 1 | E22: =IF(MAX(C12,D12,E12)=0,0,E12/MAX(C12,D12,E12)) -> 0.77777778 | F22: mayor = mejor
A24: RESULTADO
A25: Localización | B25: Puntaje | C25: Ranking
A26: SAN NICOLÁS | B26: =SUMPRODUCT(B16:B22,C16:C22) -> 0.92510998 | C26: 1°
A27: ALBERTI | B27: =SUMPRODUCT(B16:B22,D16:D22) -> 0.72318176 | C27: 2°
A28: SAN LUIS | B28: =SUMPRODUCT(B16:B22,E16:E22) -> 0.63091769 | C28: 3°
A30: LOCALIZACIÓN ÓPTIMA: SAN NICOLÁS
