Workbook

Sheet DE
A1: ACTIVO FIJO (BS DE USO + CS DIFERIDOS)
B2: SIN IVA | C2: IVA | D2: CON IVA | E2: Año
A3: Compra Bs de Uso | B3: 50000 | C3: =B3*0.21 -> 10500 | D3: =B3+C3 -> 60500 | E3: 0
A4: Gs investig y estudios | B4: 6000 | C4: =B4*0.21 -> 1260 | D4: =B4+C4 -> 7260 | E4: 0
A5: Gs instalación | B5: 15000 | C5: =B5*0.21 -> 3150 | D5: =B5+C5 -> 18150 | E5: 0
A6: Gs puesta en marcha | B6: 2000 | C6: =B6*0.21 -> 420 | D6: =B6+C6 -> 2420 | E6: 1
A7: Totales | B7: =SUM(B3:B6) -> 73000 | C7: =SUM(C3:C6) -> 15330 | D7: =SUM(D3:D6) -> 88330
A8: VR BIENES DE USO | B8: 50000
A11: VALOR CONTABLE AT
B12: SIN IVA | C12: Año
A13: Caja y Bancos | B13: 700 | C13: 0
A14: Compra MP para PM | B14: 2000 | C14: 0
A15: Créditos por Ventas | B15: 2500 | C15: 1
A16: Form. Stock MP, MCySE, PT | B16: 3750 | C16: 1
A17: Totales | B17: =SUM(B13:B16) -> 8950
A19: INVERSIÓN AT
B20: SIN IVA | C20: IVA | D20: CON IVA | E20: Año
A21: Caja y Bancos | B21: 700 | D21: =B21+C21 -> 700 | E21: 0
A22: Compra MP para PM | B22: 2000 | C22: =B22*0.21 -> 420 | D22: =B22+C22 -> 2420 | E22: 0
A23: Créditos por Ventas | B23: =B15*0.8 -> 2000 | D23: =B23+C23 -> 2000 | E23: 1
A24: Form. Stock MP, MCySE, PT | B24: =B16*0.8 -> 3000 | C24: =B24*0.21 -> 630 | D24: =SUM(B24+C24) -> 3630 | E24: 1
A25: Totales | B25: =SUM(B21:B24) -> 7700 | C25: =SUM(C21:C24) -> 1050 | D25: =SUM(D21:D24) -> 8750
B27: Cantidad | D27: Pvu | F27: IVA DF
A28: Año 1 | B28: 300 | C28: unidades | D28: 250 | E28: $/u | F28: =B28*D28*0.21 -> 15750
A29: Año 2 a n | B29: 500 | C29: unidades | D29: 250 | E29: $/u | F29: =B29*D29*0.21 -> 26250
B31: Año 1 | C31: Año 2 a n
A32: Gastos prod, admin y comerc | B32: 20000 | C32: 25000
A33: Gastos variables de lo vendido | B33: 10000 | C33: 15000
A34: IVA costos | B34: =(B32+B33)*0.15 -> 4500 | C34: =(C32+C33)*0.15 -> 6000
A36: HD | C36: no son variables con la utilidad
A37: IIGG | B37: 0.35
A38: kc | B38: 0.3

Sheet CREDITOS
A1: CREDITO NO RENOVABLE
A2: i | B2: =20% -> 0.2
A3: 30% INVERSIÓN DE LARGO PLAZO | D3: =DE!B7*0.3 -> 21900
A5: Fecha | B5: Deuda | C5: Amort. Anual | D5: Int. Anuales
A6: 31/12/-2 | B6: =D3 -> 21900 | C6: 0 | D6: =B6*B2 -> 4380
A7: 31/12/-1 | B7: =B6 -> 21900 | C7: 0 | D7: =B7*B2 -> 4380
A8: Gastos preop. | B8: =SUM(D6:D7) -> 8760
A9: 36892 | B9: =B7 -> 21900 | C9: 0 | D9: 0
A10: 37255 | B10: =B9-C10 -> 14600 | C10: =$B$7/3 -> 7300 | D10: =B9*$B$2 -> 4380
A11: 37620 | B11: =B10-C11 -> 7300 | C11: =$B$7/3 -> 7300 | D11: =B10*$B$2 -> 2920
A12: 37985 | B12: 0 | C12: =$B$7/3 -> 7300 | D12: =B11*$B$2 -> 1460
A15: CREDITO RENOVABLE
A16: i | B16: 0.1
A17: 50% INVERSION DE CORTO PLAZO | C17: =DE!B25*0.5 -> 3850
A19: Fecha | B19: Deuda | C19: Amort. Anual | D19: Int. Anuales
A20: 36892 | B20: =C17 -> 3850 | C20: 0 | D20: 0
A21: 37255 | B21: =B20 -> 3850 | C21: 0 | D21: =B21*$B$16 -> 385
A22: 37620 | B22: =B20 -> 3850 | C22: 0 | D22: =B22*$B$16 -> 385
A23: 37985 | B23: =B20 -> 3850 | C23: 0 | D23: =B23*$B$16 -> 385
A25: CREDITOS TOTALES
A26: i | B26: =20% -> 0.2
A27: 30% INVERSIÓN DE LARGO PLAZO | D27: =DE!B34*0.3 -> 1350
A29: Fecha | B29: Deuda | C29: Amort. Anual | D29: Int. Anuales | E29: kd
A30: 31/12/-2 | B30: =B6 -> 21900 | C30: 0 | D30: =D6 -> 4380
A31: 31/12/-1 | B31: =B7 -> 21900 | C31: 0 | D31: =D7 -> 4380
A32: Gastos preop. | B32: =B8 -> 8760
A33: 36892 | B33: =B9+B20 -> 25750 | C33: 0 | D33: 0
A34: 37255 | B34: =B10+B21 -> 18450 | C34: =C10+C21 -> 7300 | D34: =D10+D21 -> 4765 | E34: =D34/B33 -> 0.18504854
A35: 37620 | B35: =B11+B22 -> 11150 | C35: =C11+C22 -> 7300 | D35: =D11+D22 -> 3305 | E35: =D35/B34 -> 0.17913279
A36: 37985 | B36: =B12+B23 -> 3850 | C36: =$B$7/3 -> 7300 | D36: =D12+D23 -> 1845 | E36: =D36/B35 -> 0.16547085
B38: Año 1 | C38: Año 2 | D38: Año 3
A39: Gasto Financiero | B39: =B32/2+D34 -> 9145 | C39: =B32/2+D35 -> 7685 | D39: =D36 -> 1845

Sheet 1era estructura Financiera
A1: PRIMERA ESTRUCTURA FINANCIERA
B2: Total | C2: Credito Renovable | D2: Credito No Renovable | E2: Aporte Cap. Propio
A3: Activo Fijo, sin IVA | B3: =DE!B7 -> 73000 | C3: 0 | D3: =CREDITOS!D3 -> 21900 | E3: =+B3-D3 -> 51100
A4: IVA Inversion | B4: =B3*0.21 -> 15330 | C4: 0 | D4: 0 | E4: =+B4 -> 15330
A6: Activo de trabajo | B6: =DE!B17 -> 8950 | D6: 0
A7: Inversión Activo Trabajo s/ IVA | B7: =DE!B25 -> 7700 | C7: =CREDITOS!C17 -> 3850 | D7: 0 | E7: =+B7-C7 -> 3850
A8: IVA Inversion | B8: =DE!C25 -> 1050 | C8: 0 | D8: 0 | E8: =+B8 -> 1050
A10: Inversiones s/ IVA | B10: =+B3+B7 -> 80700 | C10: =+SUM(C3:C9) -> 3850 | D10: =+SUM(D3:D9) -> 21900 | E10: =+B10-C10-D10 -> 54950
A11: IVA Inversion | B11: =+B4+B8 -> 16380 | C11: 0 | D11: 0 | E11: =+B11 -> 16380
A12: Inversion Total | B12: =+B10+B11 -> 97080 | C12: =+C10 -> 3850 | D12: =+D10 -> 21900 | E12: =SUM(E10:E11) -> 71330

Sheet CRes
A1: CUADRO DE RESULT. PROFORMA
A2: Año | B2: Ventas | C2: CTV | D2: U a/ HD e IIGG | E2: HD | F2: IIGG | G2: U d/HD e IIGG
A3: 1 | B3: =DE!B28*DE!D28 -> 75000 | C3: =DE!B32+DE!B33+CREDITOS!B39 -> 39145 | D3: =B3-C3 -> 35855 | E3: 2000 | F3: =(D3-E3)*DE!$B$37 -> 11849.25 | G3: =D3-E3-F3 -> 22005.75
A4: 2 | B4: =DE!B29*DE!D29 -> 125000 | C4: =DE!C32+DE!C33+CREDITOS!C39 -> 47685 | D4: =B4-C4 -> 77315 | E4: 2000 | F4: =(D4-E4)*DE!$B$37 -> 26360.25 | G4: =D4-E4-F4 -> 48954.75
A5: 3 | B5: =B4 -> 125000 | C5: =DE!C32+DE!C33+CREDITOS!D39 -> 41845 | D5: =B5-C5 -> 83155 | E5: 2000 | F5: =(D5-E5)*DE!$B$37 -> 28404.25 | G5: =D5-E5-F5 -> 52750.75
A7: BN inversor | B7: =SUM(G3:G5) -> 123711.25

Sheet Calendario Inv
A1: CALENDARIO DE INVERSIONES (incrementos)
B2: Año 0 | C2: Año 1 | D2: Totales
A3: a) Activo Fijo (incrementos) | B3: =DE!B3+DE!B4+DE!B5+CREDITOS!B32 -> 79760 | C3: =DE!B6 -> 2000 | D3: =+C3+B3 -> 81760
A4: IVA Inversión | B4: =DE!C7-DE!C6+0.21*CREDITOS!B32 -> 16749.6 | C4: =DE!C6 -> 420 | D4: =+C4+B4 -> 17169.6
A5: Inversion total a) | B5: =+B4+B3 -> 96509.6 | C5: =+C3+C4 -> 2420 | D5: =+C5+B5 -> 98929.6
A7: AT (incrementos) | B7: =DE!B13+DE!B14 -> 2700 | C7: =DE!B15+DE!B16 -> 6250 | D7: =+C7+B7 -> 8950
A8: Inv. AT (incrementos) | B8: =DE!B21+DE!B22 -> 2700 | C8: =DE!B23+DE!B24+500 -> 5500 | D8: =+C8+B8 -> 8200
A9: IVA Inversion | B9: =DE!C21+DE!C22 -> 420 | C9: =DE!C23+DE!C24 -> 630 | D9: =+C9+B9 -> 1050
A10: Inversión Total AT | B10: =B8+B9 -> 3120 | C10: =+C8+C9 -> 6130 | D10: =+D9+D8 -> 9250
A12: Total s/ IVA | B12: =+B8+B3 -> 82460 | C12: =+C8+C3 -> 7500 | D12: =+D8+D3 -> 89960
A13: IVA Inversion | B13: =+B9+B4 -> 17169.6 | C13: =+C9+C4 -> 1050 | D13: =+D9+D4 -> 18219.6
A14: Inversion Total | B14: =+B13+B12 -> 99629.6 | C14: =+C13+C12 -> 8550 | D14: =+D13+D12 -> 108179.6

Sheet 2da Est. 
A1: 2° ESTRUCTURA FINANCIERA
B2: Año 0 | D2: Año 1 | F2: Totales
B3: AF | C3: Inv. AT | D3: AF | E3: Inv. AT | F3: AF | G3: Inv. AT | H3: Total | I3: %
A4: Inversion total | B4: ='Calendario Inv'!B5 -> 96509.6 | C4: ='Calendario Inv'!B10 -> 3120 | D4: ='Calendario Inv'!C5 -> 2420 | E4: ='Calendario Inv'!C10 -> 6130 | F4: =+B4+D4 -> 98929.6 | G4: =+C4+E4 -> 9250 | H4: =+G4+F4 -> 108179.6 | I4: =+I5+I6+I7 -> 1
A5: Crédito No Renovable | B5: ='1era estructura Financiera'!D3 -> 21900 | C5: 0 | D5: 0 | E5: 0 | F5: =+B5+D5 -> 21900 | G5: =+C5+E5 -> 0 | H5: =+G5+F5 -> 21900 | I5: =+H5/H4 -> 0.20244113
A6: Crédito Renovable | B6: 0 | C6: 0 | E6: ='1era estructura Financiera'!C7 -> 3850 | F6: =+B6+D6 -> 0 | G6: =+C6+E6 -> 3850 | H6: =+G6+F6 -> 3850 | I6: =+H6/H4 -> 0.035588965
A7: Aporte de Capital | B7: =+B4-B5 -> 74609.6 | C7: =+C4 -> 3120 | D7: =+D4 -> 2420 | E7: =+E4-E6 -> 2280 | F7: =+B7+D7 -> 77029.6 | G7: =+C7+E7 -> 5400 | H7: =+G7+F7 -> 82429.6 | I7: =+H7/H4 -> 0.76196991

Sheet RECUPERO IVA
A1: IVA diferencia
A2: IVA Plan Explotación | B2: Año 1 | C2: Año 2 | D2: Año 3
A3: IVA Percibido (ventas) | B3: =DE!F28 -> 15750 | C3: =DE!F29 -> 26250 | D3: =DE!F29 -> 26250
A4: IVA pagado (s/costos, sin intereses) | B4: =DE!B34 -> 4500 | C4: =DE!C34 -> 6000 | D4: =DE!C34 -> 6000
A5: IVA pagado (sobre intereses) | B5: =CREDITOS!D34*0.21 -> 1000.65 | C5: =CREDITOS!D35*0.21 -> 694.05 | D5: =CREDITOS!D36*0.21 -> 387.45
A6: IVA diferencia | B6: =+B3-B4-B5 -> 10249.35 | C6: =+C3-C4-C5 -> 19555.95 | D6: =+D3-D4-D5 -> 19862.55
A8: Cobro del Crédito Fiscal
B9: Crédito Fiscal | C9: IVA diferencia | D9: Recupero IVA
A10: Año 0 | B10: ='Calendario Inv'!B13 -> 17169.6 | C10: 0 | D10: 0
A11: Año 1 | B11: ='Calendario Inv'!D13 -> 18219.6 | C11: =B6 -> 10249.35 | D11: =C11 -> 10249.35
A12: Año 2 | B12: =B11-D11 -> 7970.25 | C12: =+C6 -> 19555.95 | D12: =B12 -> 7970.25 | E12: IVA DF al fisco | F12: =C12-D12 -> 11585.7
A13: Año 3 | B13: 0 | C13: =+D6 -> 19862.55 | D13: 0 | E13: IVA DF al fisco | F13: =C13 -> 19862.55

Sheet CFyU
B1: Año 0 | C1: Año 1 | D1: Año 2 | E1: Año 3 | F1: TOTALES
A2: FUENTES: Totales | B2: =SUM(B3:B9) -> 99629.6 | C2: =SUM(C3:C9) -> 93799.35 | D2: =SUM(D3:D9) -> 181555.35 | E2: =SUM(E3:E9) -> 247590.1 | F2: =SUM(F3:F9) -> 451399.2
A3: Saldo ej. Anterior (Ac) | B3: 0 | C3: =B25 -> 0 | D3: =C25 -> 48585.1 | E3: =D25 -> 122590.1 | F3: 0
A4: Aporte de Cap. Propio | B4: ='2da Est. '!B7+'2da Est. '!C7 -> 77729.6 | C4: ='2da Est. '!D7+'2da Est. '!E7 -> 4700 | D4: 0 | E4: 0 | F4: =SUM(B4:E4) -> 82429.6
A5: Créditos Renovables | B5: 0 | C5: =CREDITOS!C17 -> 3850 | D5: 0 | E5: 0 | F5: =SUM(B5:E5) -> 3850
A6: Créditos No Renovables | B6: =CREDITOS!D3 -> 21900 | C6: 0 | D6: 0 | E6: 0 | F6: =SUM(B6:E6) -> 21900
A7: Ventas del ej. | B7: 0 | C7: =CRes!B3 -> 75000 | D7: =CRes!B4 -> 125000 | E7: =CRes!B5 -> 125000 | F7: =SUM(B7:E7) -> 325000
A8: Recupero Crédito Fiscal | B8: 0 | C8: ='RECUPERO IVA'!D11 -> 10249.35 | D8: ='RECUPERO IVA'!D12 -> 7970.25 | E8: 0 | F8: =SUM(B8:E8) -> 18219.6
A9: Otros ingresos | B9: 0 | C9: 0 | D9: 0 | E9: 0 | F9: 0
A11: USOS: Totales | B11: =SUM(B12:B19) -> 99629.6 | C11: =SUM(C12:C19) -> 69594.25 | D11: =SUM(D12:D19) -> 83345.25 | E11: =SUM(E12:E19) -> 79549.25 | F11: =SUM(B11:E11) -> 332118.35
A12: Activo Fijo | B12: ='Calendario Inv'!B3 -> 79760 | C12: ='Calendario Inv'!C3 -> 2000 | D12: 0 | E12: 0 | F12: =SUM(B12:E12) -> 81760
A13: Activo Trabajo | B13: ='Calendario Inv'!B7 -> 2700 | C13: ='Calendario Inv'!C7 -> 6250 | D13: 0 | E13: 0 | F13: =SUM(B13:E13) -> 8950
A14: Costo de lo vendido | B14: 0 | C14: =CRes!C3 -> 39145 | D14: =CRes!C4 -> 47685 | E14: =CRes!C5 -> 41845 | F14: =SUM(B14:E14) -> 128675
A15: IIGG | B15: 0 | C15: =CRes!F3 -> 11849.25 | D15: =CRes!F4 -> 26360.25 | E15: =CRes!F5 -> 28404.25 | F15: =SUM(B15:E15) -> 66613.75
A16: Cancelación de deudas | B16: 0 | C16: =CREDITOS!C10 -> 7300 | D16: =C16 -> 7300 | E16: =C16 -> 7300 | F16: =SUM(B16:E16) -> 21900
A17: HD | B17: 0 | C17: =CRes!E3 -> 2000 | D17: =CRes!E4 -> 2000 | E17: =CRes!E5 -> 2000 | F17: =SUM(B17:E17) -> 6000
A18: Dividendos Efectivo | B18: 0 | C18: 0 | D18: 0 | E18: 0 | F18: =SUM(B18:E18) -> 0
A19: IVA Inversion | B19: ='Calendario Inv'!B13 -> 17169.6 | C19: ='Calendario Inv'!C13 -> 1050 | D19: 0 | E19: 0 | F19: =SUM(B19:E19) -> 18219.6
A20: Otros egresos
A22: FUENTES - USOS | B22: =+B2-B11 -> 0 | C22: =+C2-C11 -> 24205.1 | D22: =+D2-D11 -> 98210.1 | E22: =+E2-E11 -> 168040.85 | F22: =F2-F11 -> 119280.85
A23: Amortizaciones del Ejercicio | B23: 0 | C23: =B35 -> 24380 | D23: =B36 -> 24380 | E23: =B37 -> 20000 | F23: =SUM(B23:E23) -> 68760
A25: Saldo al ej. Siguiente (Ac) | B25: =+B22+B23 -> 0 | C25: =+C22+C23 -> 48585.1 | D25: =+D22+D23 -> 122590.1 | E25: =+E22+E23 -> 188040.85 | F25: =F22+F23 -> 188040.85
A26: Saldo propio del ejercicio | B26: =+B25 -> 0 | C26: =C25-B25 -> 48585.1 | D26: =D25-C25 -> 74005 | E26: =E25-D25 -> 65450.75 | F26: =F25 -> 188040.85
A28: Amortizaciones ejercicio
A30: =SUM(DE!B3:B6) -> 73000 | B30: VO | E30: VERIFICACIONES
A31: 13000 | B31: VR | E31: BN inv | F31: =E25+A31+F13-F4-F5 -> 123711.25
E32: Bn inv | F32: =CRes!B7 -> 123711.25
A33: Amort int y gastos preop | B33: =CREDITOS!B32/2 -> 4380 | C33: se amortizan en 2 años | E33: BN mod | F33: =F32+SUM(CREDITOS!B39:D39) -> 142386.25
E34: BN puro | F34: =F31+SUM(CREDITOS!B39:D39)*(1-DE!B37) -> 135850
A35: Amort año 1 | B35: =(A30-A31)/3+B33 -> 24380
A36: Amort año 2 | B36: =B35 -> 24380 | E36: AHORRO IMPOSITIVO | F36: =SUM(CREDITOS!B39:D39)*DE!B37 -> 6536.25
A37: Amort año 3 | B37: =(A30-A31)/3 -> 20000
