Workbook

Sheet Carátula
K1: UNIVERSIDAD TECNOLÓGICA NACIONAL FACULTAD REGIONAL BUENOS AIRES
A2: DEPARTAMENTO DE INGENIERÍA INDUSTRIAL
A3: ASIGNATURA | L3: CÓDIGO | S3: CICLO LECTIVO
A4: EVALUACIÓN DE PROYECTOS | L4: 32590 | S4: 2024
A5: ESTUDIANTES | B5: NOMBRE Y APELLIDO | E5: Lucio Cahe | T5: LEGAJO 150.459-9 | W5: 1504599
B6: NOMBRE Y APELLIDO | E6: Santiago Greco | T6: LEGAJO 177.980-1 | W6: 1779801
B7: NOMBRE Y APELLIDO | E7: Joan Manonelles | T7: LEGAJO 173.276-6 | W7: 1732766
B8: NOMBRE Y APELLIDO | E8: Penélope Mattia | T8: LEGAJO 175.443-9 | W8: 1754439
B9: NOMBRE Y APELLIDO | E9: Ignacio Morón | T9: LEGAJO 162.519-6 | W9: 1625196
O10: DIVISIÓN | R10: AÑO | U10: EQUIPO
O11: I–4053 | R11: 4to | U11: 10
A12: DOCENTES | B12: Docentes Adjuntos: | I12: Ing. Juan José Cosentino
B13: Jefe de Trabajos Prácticos | I13: Ing. Lucas Martín Costantino
B14: Ayudantes: | I14: Ing. Matías A. Carpinacci Sireix Ing. Miguel A. Beltrán Ing. Nicolás Elías Sabaryn
A15: Parte 5: Dimensionamiento Económico
A16: TEMA: Harina de soja con huerta hidropónica
A18: OBSERVACIONES
A19: FIRMA DEL ESTUDIANTE | G19: FIRMA DEL JTP / ATP | P19: NOTA
A20: ENTREGA | C20: Fecha ENTREGA | H20: Fecha VISADO | N20: FECHAS DESTACADAS
A21: 1ra | C21: 8 | D21: 10 | F21: 24 | N21: FECHA DE INICIO
A22: 2da | C22: 29 | D22: 10 | F22: 24
A23: 3ra | N23: FECHA DE FINALIZACIÓN
A24: 4ta

Sheet Ejercicio 1
A1: EJERCICIO 1
A2: SECCIONES | C2: DESPERDICIOS (litros)
C3: Recuperables | D3: No recuperables
A4: 1 | B4: Descascarado | C4: 0 | D4: 115 | E4: 2% del peso
A5: 2 | B5: Molido grueso | C5: 0 | D5: 0
A6: 3 | B6: Extrusión | C6: 0 | D6: 0
A7: 4 | B7: Prensado | C7: 0 | D7: 750 | E7: Sale aceite
A8: 5 | B8: Secado / Enfriado | C8: 0 | D8: 0
A9: 6 | B9: Molienda | C9: 0 | D9: 0
A10: 7 | B10: Empaquetado | C10: 0 | D10: 0
B13: Volumen total ingresado = | C13: =C22 -> 5865
B14: Consumo real MP = | C14: =C13 -> 5865
B15: % Desperdicio operativo = | C15: =(D29+E29)/F28 -> 0.173
B16: % Desperdicio real = | C16: =(E29)/F28 -> 0.173
A19: SECCIONES | C19: ALIMENTACION (Anual) | D19: DESPERDICIOS (Toneladas) | F19: PRODUCCIONES SECCIONALES (Tn/ Anual) | G19: PRODUCCIONES SECCIONALES (Kg/Anual)
D20: Recuperables | E20: No recuperables
A21: 1 | B21: Separador | C21: 5865 | D21: 0 | E21: 0 | F21: 5865 | G21: =F21*1000 -> 5865000
A22: 2 | B22: Descascarado | C22: =F22*1.02 -> 5865 | D22: 0 | E22: =0.02*F22 -> 115 | F22: =C23 -> 5750 | G22: =F22*1000 -> 5750000 | H22: 2% del peso
A23: 3 | B23: Molido grueso | C23: =F23 -> 5750 | D23: 0 | E23: 0 | F23: =C24 -> 5750 | G23: =F23*1000 -> 5750000
A24: 4 | B24: Extrusión | C24: =D24+E24+F24 -> 5750 | D24: 0 | E24: 0 | F24: =C25 -> 5750 | G24: =F24*1000 -> 5750000
A25: 5 | B25: Prensado | C25: =D25+E25+F25 -> 5750 | D25: 0 | E25: =0.15*F25 -> 750 | F25: =C26 -> 5000 | G25: =F25*1000 -> 5000000
A26: 6 | B26: Secado / Enfriado | C26: =F26 -> 5000 | D26: 0 | E26: 0 | F26: =C27 -> 5000 | G26: =F26*1000 -> 5000000
A27: 7 | B27: Molienda | C27: =F27+D27+E27 -> 5000 | D27: 0 | E27: 0 | F27: =C28 -> 5000 | G27: =F27*1000 -> 5000000
A28: 8 | B28: Empaquetado | C28: =F28+D28+E28 -> 5000 | D28: 0 | E28: 0 | F28: =I28 -> 5000 | G28: =F28*1000 -> 5000000 | I28: =InfoInicial!B17 -> 5000 | J28: Toneladas anuales
A29: Totales | C29: =C22 -> 5865 | D29: =SUM(D22:D28) -> 0 | E29: =SUM(E22:E28) -> 865 | F29: =F28 -> 5000 | G29: =F29*1000 -> 5000000

Sheet Ejercicio 2 
A1: EJERCICIO 2
A2: Dias totales del año = | B2: 365
A3: Feriados del año = | B3: 10
A4: Vacaciones = | B4: 15
A5: Dias totales laborales = | B5: 340 | C5: 7 | D5: A la semana
A7: Equipos rotativos = | B7: 1
A8: Horas de cada turno = | B8: 8
A9: Turnos diarios = | B9: 2
A11: HORAS ACTIVAS/AÑO | B11: =B5*B8*B9 -> 5440 | C11: Horas
A12: HORAS/AÑO POR EQUIPO DE OPERARIOS | B12: =B11/B7 -> 5440 | C12: Horas

Sheet Ejercicio 3
A1: EJERCICIO 3
A2: SECCIONES OPERATIVAS | C2: CAPACIDAD TEORICA / MAQUINA X HORA | E2: HORAS ACTIVA / AÑO | F2: CAPACIDAD TEORICA / MAQUINA X AÑO | G2: RENDIMIENTO OPERATIVO | H2: CAPACIDAD REAL / MAQUINA X AÑO
A3: 1 | B3: Separador | C3: 8000 | D3: Kg/h | E3: ='Ejercicio 2 '!$B$11 -> 5440 | F3: =C3*E3 -> 43520000 | G3: 0.95 | H3: =F3*G3 -> 41344000
A4: 2 | B4: Descascarado | C4: =(150*1000)/24 -> 6250 | D4: Kg/h | E4: ='Ejercicio 2 '!$B$11 -> 5440 | F4: =C4*E4 -> 34000000 | G4: 0.95 | H4: =F4*G4 -> 32300000
A5: 3 | B5: Molido grueso | C5: 1000 | D5: Kg/h | E5: ='Ejercicio 2 '!$B$11 -> 5440 | F5: =C5*E5 -> 5440000 | G5: 0.95 | H5: =F5*G5 -> 5168000
A6: 4 | B6: Extrusión | C6: 1000 | D6: Kg/h | E6: ='Ejercicio 2 '!$B$11 -> 5440 | F6: =C6*E6 -> 5440000 | G6: 0.95 | H6: =F6*G6 -> 5168000
A7: 5 | B7: Prensado | C7: =(70*1000)/24 -> 2916.6667 | D7: Kg/h | E7: ='Ejercicio 2 '!$B$11 -> 5440 | F7: =C7*E7 -> 15866667 | G7: 0.95 | H7: =F7*G7 -> 15073333
A8: 6 | B8: Secado / Enfriado | C8: =10*1000 -> 10000 | D8: Kg/h | E8: ='Ejercicio 2 '!$B$11 -> 5440 | F8: =C8*E8 -> 54400000 | G8: 0.95 | H8: =F8*G8 -> 51680000
A9: 7 | B9: Molienda | C9: =4*1000 -> 4000 | D9: Kg/h | E9: ='Ejercicio 2 '!$B$11 -> 5440 | F9: =C9*E9 -> 21760000 | G9: 0.95 | H9: =F9*G9 -> 20672000
A10: 8 | B10: Empaquetado | C10: =(4*60)*50 -> 12000 | D10: Kg/h | E10: ='Ejercicio 2 '!$B$11 -> 5440 | F10: =C10*E10 -> 65280000 | G10: 0.95 | H10: =F10*G10 -> 62016000

Sheet Ejercicio 4 y 5
A1: EJERCICIO 4 Y 5
A2: SECCIONES OPERATIVAS | C2: PROGRAMA ANUAL DE PRODUCCION | D2: CAPACIDAD REAL/MAQXAÑO | E2: CANTIDAD MAQS NECESARIAS | F2: CAPACIDAD REAL/SECCION X AÑO | G2: APROVECHAMIENTO SECCIONAL (%)
A4: 1 | B4: Separador | C4: ='Ejercicio 1'!G21 -> 5865000 | D4: ='Ejercicio 3'!H3 -> 41344000 | E4: =ROUNDUP(C4/D4,0) -> 1 | F4: =D4*E4 -> 41344000 | G4: =(C4/F4) -> 0.14185855
A5: 2 | B5: Descascarado | C5: ='Ejercicio 1'!G22 -> 5750000 | D5: ='Ejercicio 3'!H4 -> 32300000 | E5: =ROUNDUP(C5/D5,0) -> 1 | F5: =D5*E5 -> 32300000 | G5: =(C5/F5) -> 0.17801858
A6: 3 | B6: Molido grueso | C6: ='Ejercicio 1'!G23 -> 5750000 | D6: ='Ejercicio 3'!H5 -> 5168000 | E6: =ROUNDUP(C6/D6,0) -> 2 | F6: =D6*E6 -> 10336000 | G6: =(C6/F6) -> 0.55630805
A7: 4 | B7: Extrusión | C7: ='Ejercicio 1'!G24 -> 5750000 | D7: ='Ejercicio 3'!H6 -> 5168000 | E7: =ROUNDUP(C7/D7,0) -> 2 | F7: =D7*E7 -> 10336000 | G7: =(C7/F7) -> 0.55630805
A8: 5 | B8: Prensado | C8: ='Ejercicio 1'!G25 -> 5000000 | D8: ='Ejercicio 3'!H7 -> 15073333 | E8: 2 | F8: =D8*E8 -> 30146667 | G8: =(C8/F8) -> 0.16585582 | H8: Si bien, en términos de capacidades, sólo resulta necesaria una prensa en la sección operativa, es recomendable el agregado de una adicional, minimizando el costo perdido por paradas de máquinas debido a desperfectos y obteniendo un mayor porcentaje de extracción
A9: 6 | B9: Secado / Enfriado | C9: ='Ejercicio 1'!G26 -> 5000000 | D9: ='Ejercicio 3'!H8 -> 51680000 | E9: =ROUNDUP(C9/D9,0) -> 1 | F9: =D9*E9 -> 51680000 | G9: =(C9/F9) -> 0.096749226
A10: 7 | B10: Molienda | C10: ='Ejercicio 1'!G27 -> 5000000 | D10: ='Ejercicio 3'!H9 -> 20672000 | E10: =ROUNDUP(C10/D10,0) -> 1 | F10: =D10*E10 -> 20672000 | G10: =(C10/F10) -> 0.24187307
A11: 8 | B11: Empaquetado | C11: ='Ejercicio 1'!G28 -> 5000000 | D11: ='Ejercicio 3'!H10 -> 62016000 | E11: =ROUNDUP(C11/D11,0) -> 1 | F11: =D11*E11 -> 62016000 | G11: =(C11/F11) -> 0.080624355

Sheet Ejercicio 6
A1: EJERCICIO 6 | H1: 345 | I1: días laborales
A2: Venta volúmen [Tn]
A3: Anual | C3: Mensual | H3: =(H1*12)/365 -> 11.342466 | I3: meses laborales
A4: =InfoInicial!B17 -> 5000 | C4: =A4/H4 -> 434.78261 | H4: 11.5
A6: Mes | B6: Ritmo de producción al inicio | C6: Ritmo de producción al final | D6: Producción Prom. | E6: Producción Mensual Prom. | F6: Producción Propuesta
A7: 1 | B7: 0 | C7: 0.04 | D7: 0.02 | E7: =$C$4 -> 434.78261 | F7: =D7*E7 -> 8.6956522
A8: 2 | B8: 0.04 | C8: 0.16 | D8: 0.1 | E8: =E7 -> 434.78261 | F8: =D8*E8 -> 43.478261
A9: 3 | B9: 0.16 | C9: 1 | D9: 0.58 | E9: =E8 -> 434.78261 | F9: =D9*E9 -> 252.17391
E10: TOTAL = | F10: =SUM(F7:F9) -> 304.34783 | H10: Resto del año
B11: Año 1 | C11: Año 2 a 10 | H11: =B12-F10 -> 3695.6522
A12: Producción | B12: =F10+(11.5-3)*C4 -> 4000 | C12: =A4 -> 5000 | E12: RESTO DEL AÑO | F12: 3696

Sheet Ejercicio 7 y 8
A1: EJERCICIO 7 | G1: EJERCICIO 8
A2: Venta [Tn] | H2: Año 1 | I2: Año 2 a 10
A3: Anual | C3: Cuatrimestral | G3: Producción | H3: ='Ejercicio 6'!B12 -> 4000 | I3: ='Ejercicio 6'!C12 -> 5000
A4: =InfoInicial!B17 -> 5000 | C4: =A4/4 -> 1250
G5: Ventas del año 1 = | H5: =H3-C7 -> 3375
A6: Volumen de produccion cuatrimestral = | C6: =C4 -> 1250 | D6: Tn | G6: Ventas del año 2 a 10 = | H6: =I3 -> 5000
A7: Stock promedio elaborados = | C7: =C6/2 -> 625 | D7: Tn
A10: Se opera sin la formación de un stock de seguridad

Sheet Ejercicio 9
A1: EJERCICIO 9
A2: Punto A
A3: Ciclo de elaboracion = | B3: 7 | C3: días
A4: Ciclos anuales = | B4: =ROUND(340/B3,0) -> 49 | C4: ciclos
A6: Periodo de puesta en marcha (3 meses) = | B6: ='Ejercicio 6'!F10*1.173 -> 357 | C6: con 17,3% de desperdicio
A7: Resto del año = | B7: ='Ejercicio 6'!H11*1.173 -> 4335 | C7: con 17,3% de desperdicio
A8: total materia prima para la producción | B8: =B7+B6 -> 4692
A9: Produccion año 1 = | B9: ='Ejercicio 6'!B12 -> 4000
A10: Desperdicio no recuperable = | B10: =B8-B9 -> 692
A12: Punto B
A13: Cantidad de ciclos productivos = | B13: =B4 -> 49 | C13: ciclos
A14: Vol. Anual / días año * longitud proceso = | B14: ='Ejercicio 1'!C22/340*'Ejercicio 2 '!C5 -> 120.75 | C14: Tn
A16: Desglose por ciclo productivo (en régimen)
A17: Producto elaborado = | B17: MP / Coef desperdicio operativo = | D17: =B14/1.173 -> 102.94118 | F17: Coef Desp Operativo (Ej1) = 17.3%
A18: Desperdicio no recuperable = | B18: MP * % Desperdicio real = | D18: =D17*1.173 -> 120.75 | F18: Desperdicio Real (Ej1) = 17.3%
A19: Desperdicio recuperable = | B19: MP * % Recuperable = | D19: 0 | F19: Recuperable (Ej1) = 0%
C20: TOTAL = | D20: =SUM(D17:D19) -> 223.69118
A22: Punto C
A23: Consumo total MP año 1 = MP Produccion + MP Mercaderia en curso y SE = | C23: =D20+B6+B7 -> 4915.6912 | D23: Tn
A25: Punto D
A26: Consumo MP años 2 a 10 = | B26: ='Ejercicio 1'!C22*1.1 -> 6451.5 | C26: Tn

Sheet Ejercicio 10
A1: EJERCICIO 10
A2: Al final del mes | B2: Stock | C2: Compras | E2: Total de compras anuales= | F2: ='Ejercicio 9'!B26 -> 6451.5 | G2: Tn | I2: =340/365 -> 0.93150685
A3: Enero | B3: - | C3: - | E3: 12 Compras por año= | F3: =F2/I3 -> 577.15625 | G3: Tn | I3: =12*I2 -> 11.178082
A4: Febrero | B4: - | C4: - | E4: Consumo mensual= | F4: =F3 -> 577.15625 | G4: Tn
A5: Marzo | B5: =F3*3 -> 1731.4688 | C5: =B5 -> 1731.4688
A6: Abril | B6: - | C6: =B6 -> -
A7: Mayo | B7: - | C7: =B7 -> - | E7: El período de tiempo entre siembra y cosecha son 3 meses
A8: Junio | B8: =B5 -> 1731.4688 | C8: =B8 -> 1731.4688
A9: Julio | B9: - | C9: =B9 -> -
A10: Agosto | B10: - | C10: =B10 -> -
A11: Septiembre | B11: =B8 -> 1731.4688 | C11: =B11 -> 1731.4688
A12: Octubre | B12: - | C12: =B12 -> -
A13: Noviembre | B13: - | C13: =B13 -> -
A14: Diciembre | B14: =B11 -> 1731.4688 | C14: =B14 -> 1731.4688

Sheet Ejercicio 11
A1: EJERCICIO 11
B2: U. de medida | C2: Período Instalación | D2: Año 1 | E2: Año 2 a 10
A3: Ventas | B3: t. PT | C3: 0 | D3: ='Ejercicio 7 y 8'!H5 -> 3375 | E3: ='Ejercicio 7 y 8'!H6 -> 5000
A4: Stock Promedio de elaborados | B4: t. PT | C4: 0 | D4: ='Ejercicio 7 y 8'!C7 -> 625 | E4: ='Ejercicio 7 y 8'!C7 -> 625
A5: Producción | B5: t. MP | C5: 0 | D5: ='Ejercicio 6'!B12 -> 4000 | E5: ='Ejercicio 6'!C12 -> 5000
A6: Desperdicio No Recuperables | B6: t. MP | C6: 0 | D6: ='Ejercicio 9'!B10 -> 692 | E6: ='Ejercicio 9'!D18 -> 120.75
A7: En Curso y Semielaborados | B7: t. MP | C7: 0 | D7: ='Ejercicio 9'!D20 -> 223.69118 | E7: ='Ejercicio 9'!D20 -> 223.69118
A8: Consumo de MP | B8: t. MP | C8: 0 | D8: ='Ejercicio 9'!C23 -> 4915.6912 | E8: ='Ejercicio 9'!B26 -> 6451.5
A9: Stock de MP | B9: t. MP | C9: ='Ejercicio 10'!F4*3 -> 1731.4688 | D9: =AVERAGE('Ejercicio 10'!B3:B14) -> 1731.4688 | E9: =D9 -> 1731.4688
A10: Compra de MP | B10: t. MP | C10: =C9 -> 1731.4688 | D10: =D8 -> 4915.6912 | E10: =E8 -> 6451.5

Sheet InfoInicial
A2: Tasa porcentual de IVA | B2: 0.21
A3: Tasa porcentual de Impuesto a las Ganancias | B3: 0.35
A4: Honorarios al Directorio | B4: 0 | C4: Variable sobre Utilidad economica antes de HD e IG
A6: Tiempo de Amortización Activos Fijos: | B6: Se considera una depreciación lineal y un valor residual nulo
A7: edificios y obras complementarias | B7: 30 | C7: años
A8: instalaciones industriales | B8: 10 | C8: años
A9: máquinas, equipos y accesorios | B9: 10 | C9: años
A10: rodados y equipos auxiliares | B10: 5 | C10: años
A11: muebles y útiles | B11: 5 | C11: años
A12: repuestos iniciales | B12: 3 | C12: años
A13: Otros Activos y Cargos Diferidos | B13: 5 | C13: años | G13: Imprevistos sin Especificar | I13: 0.02
A15: Nombre del Producto | B15: Harina de Soja
A17: Ventas Anuales Promedio | B17: 5000 | C17: en Unidades | D17: -> Toneladas
A18: Precio Promedio | B18: 450 | C18: en $ | H18: https://www.bolsadecereales.com/fob
A20: Cantidad de personal total
A21: en Producción | B21: 8 | C21: personas
A22: en Comercialización | B22: 1 | C22: personas
A23: en Administración | B23: 3 | C23: personas
A25: Tamaño de la planta en metros cuadrados | B25: 2500 | C25: m2
A26: Periodo de Instalación | B26: 9 | C26: en meses
A27: Período de Puesta en Marcha | B27: 3 | C27: en meses
A30: Tasa de Cambio | B30: 1300 | C30: $ por cada | D30: 1 | E30: U$S
A33: Tasa de Credito Bancario | B33: 0.5 | C33: anual
A34: Rubro a financiar | B34: Activo Fijo
A35: % sobre el total del Rubro | B35: 0.3
A37: Dias de Financiación de Proveedores | B37: 30
A38: % sobre Compras | B38: 0.5
A39: Tasa de financiación | B39: 0.12 | C39: anual

Sheet Materia Prima
C4: Granos | F4: Bolsas de Polipropileno
B5: Tonelada | C5: ='Ejercicio 10'!F2 -> 6451.5 | F5: Año 1 | G5: =1000*3375 -> 3375000 | H5: kg | I5: =G5/50 -> 67500 | J5: Bolsas | K5: =I5*H8 -> 40486500
B6: Precio x u | C6: 90000 | F6: Año 2 a 10 | G6: =1000*5000 -> 5000000 | H6: kg | I6: =G6/50 -> 100000 | J6: Bolsas | K6: =I6*H8 -> 59980000
B7: Total | C7: =C5*C6 -> 5.80635e+08
G8: Precio unitario | H8: =29990/50 -> 599.8 | I8: https://articulo.mercadolibre.com.ar/MLA-1297825597-bolsa-de-rafia-blanca-56x97-x50unidades-50-55kg-_JM#polycard_client=search-nordic&position=21&search_layout=stack&type=item&tracking_id=21379e5e-2703-47be-a018-e752532858f4
B10: Año 1 | C10: =C7*0.75 -> 4.3547625e+08
B11: Año 2 a 10 | C11: =C7 -> 5.80635e+08
B14: Stock Materia Prima año 0 | D14: ='Ejercicio 11'!C9*C6 -> 1.5583219e+08
B18: 90000 | D18: =6451.5*1000 -> 6451500
B19: =D19*B18/D18 -> 0.55800977 | D19: 40

Sheet Materiales área producción
A1: Referencias
A2: Mantenimiento | B2: 0.01
A3: Repuestos | B3: 0.016
A4: Producción | B4: 0.015
A5: Personal | B5: 0.03
A8: PRODUCCIÓN | B8: Año | C8: 1 | D8: 2 | E8: 3 | F8: 4 | G8: 5 | H8: 6 | I8: 7 | J8: 8 | K8: 9 | L8: 10
B9: Mantenimiento | C9: =$B$2*('DE-Inv AF y Am'!$B$20+'DE-Inv AF y Am'!$D$20) -> 28400068 | D9: =$B$2*('DE-Inv AF y Am'!$B$20+'DE-Inv AF y Am'!$D$20) -> 28400068 | E9: =$B$2*('DE-Inv AF y Am'!$B$20+'DE-Inv AF y Am'!$D$20) -> 28400068 | F9: =$B$2*('DE-Inv AF y Am'!$B$20+'DE-Inv AF y Am'!$D$20) -> 28400068 | G9: =$B$2*('DE-Inv AF y Am'!$B$20+'DE-Inv AF y Am'!$D$20) -> 28400068 | H9: =$B$2*('DE-Inv AF y Am'!$B$20+'DE-Inv AF y Am'!$D$20) -> 28400068 | I9: =$B$2*('DE-Inv AF y Am'!$B$20+'DE-Inv AF y Am'!$D$20) -> 28400068 | J9: =$B$2*('DE-Inv AF y Am'!$B$20+'DE-Inv AF y Am'!$D$20) -> 28400068 | ... L9: =$B$2*('DE-Inv AF y Am'!$B$20+'DE-Inv AF y Am'!$D$20) -> 28400068
B10: Repuestos | C10: =$B$3*('DE-Inv AF y Am'!$B$12+'DE-Inv AF y Am'!$D$11) -> 884000 | D10: =$B$3*('DE-Inv AF y Am'!$B$12+'DE-Inv AF y Am'!$D$11) -> 884000 | E10: =$B$3*('DE-Inv AF y Am'!$B$12+'DE-Inv AF y Am'!$D$11) -> 884000 | F10: =$B$3*('DE-Inv AF y Am'!$B$12+'DE-Inv AF y Am'!$D$11) -> 884000 | G10: =$B$3*('DE-Inv AF y Am'!$B$12+'DE-Inv AF y Am'!$D$11) -> 884000 | H10: =$B$3*('DE-Inv AF y Am'!$B$12+'DE-Inv AF y Am'!$D$11) -> 884000 | I10: =$B$3*('DE-Inv AF y Am'!$B$12+'DE-Inv AF y Am'!$D$11) -> 884000 | J10: =$B$3*('DE-Inv AF y Am'!$B$12+'DE-Inv AF y Am'!$D$11) -> 884000 | ... L10: =$B$3*('DE-Inv AF y Am'!$B$12+'DE-Inv AF y Am'!$D$11) -> 884000
B11: Producción | C11: =$B$4*'DE-Costos'!B4 -> 7139441.3 | D11: =$B$4*'DE-Costos'!C4 -> 9609225 | E11: =$B$4*'DE-Costos'!D4 -> 9609225 | F11: =$B$4*'DE-Costos'!E4 -> 9609225 | G11: =$B$4*'DE-Costos'!F4 -> 9609225 | H11: =$B$4*'DE-Costos'!G4 -> 9609225 | I11: =$B$4*'DE-Costos'!H4 -> 9609225 | J11: =$B$4*'DE-Costos'!I4 -> 9609225 | ... L11: =$B$4*'DE-Costos'!K4 -> 9609225
B12: Personal | C12: =$B$5*('DE-Costos'!B5+'DE-Costos'!B8) -> 1606466.2 | D12: =$B$5*('DE-Costos'!C5+'DE-Costos'!C8) -> 1606466.2 | E12: =$B$5*('DE-Costos'!D5+'DE-Costos'!D8) -> 1606466.2 | F12: =$B$5*('DE-Costos'!E5+'DE-Costos'!E8) -> 1606466.2 | G12: =$B$5*('DE-Costos'!F5+'DE-Costos'!F8) -> 1606466.2 | H12: =$B$5*('DE-Costos'!G5+'DE-Costos'!G8) -> 1606466.2 | I12: =$B$5*('DE-Costos'!H5+'DE-Costos'!H8) -> 1606466.2 | J12: =$B$5*('DE-Costos'!I5+'DE-Costos'!I8) -> 1606466.2 | ... L12: =$B$5*('DE-Costos'!K5+'DE-Costos'!K8) -> 1606466.2
B13: TOTAL | C13: =SUM(C9:C12) -> 38029975 | D13: =SUM(D9:D12) -> 40499759 | E13: =SUM(E9:E12) -> 40499759 | F13: =SUM(F9:F12) -> 40499759 | G13: =SUM(G9:G12) -> 40499759 | H13: =SUM(H9:H12) -> 40499759 | I13: =SUM(I9:I12) -> 40499759 | J13: =SUM(J9:J12) -> 40499759 | ... L13: =SUM(L9:L12) -> 40499759

Sheet Gastos Merc en curso y SE
A1: Produccion año 1 | B1: ='Ejercicio 11'!D5 -> 4000 | C1: Tn | D1: Dividimos el valor de gastos del area de fabricacion por la cantidad fabricada en año 1 y año 2 a 10. Luego lo mutliplicamos por la cantidad de semielaborados (Ejercicio 11)
A2: Produccion año 2 a 10 | B2: ='Ejercicio 11'!E5 -> 5000 | C2: Tn
B6: Año 1 | C6: Año 2 a 10
A7: Materia prima | B7: =('DE-Costos'!B4/'Gastos Merc en curso y SE'!$B$1)*'Ejercicio 11'!$D$7 -> 26617167 | C7: =('DE-Costos'!C4/'Gastos Merc en curso y SE'!$B$2)*'Ejercicio 11'!$E$7 -> 28659985
A8: Mano de obra directa | B8: =('DE-Costos'!B5/'Gastos Merc en curso y SE'!$B$1)*'Ejercicio 11'!$D$7 -> 1655879.4 | C8: =('DE-Costos'!C5/'Gastos Merc en curso y SE'!$B$2)*'Ejercicio 11'!$E$7 -> 1324703.5
A9: Amortizaciones | B9: =('DE-Costos'!B7/'Gastos Merc en curso y SE'!$B$1)*'Ejercicio 11'!$D$7 -> 8979537.7 | C9: =('DE-Costos'!C7/'Gastos Merc en curso y SE'!$B$2)*'Ejercicio 11'!$E$7 -> 7183630.2
A10: Personal indirecto | B10: =('DE-Costos'!B8/'Gastos Merc en curso y SE'!$B$1)*'Ejercicio 11'!$D$7 -> 1338723.3 | C10: =('DE-Costos'!C8/'Gastos Merc en curso y SE'!$B$2)*'Ejercicio 11'!$E$7 -> 1070978.7
A11: Materiales | B11: =('DE-Costos'!B9/'Gastos Merc en curso y SE'!$B$1)*'Ejercicio 11'!$D$7 -> 2126742.5 | C11: =('DE-Costos'!C9/'Gastos Merc en curso y SE'!$B$2)*'Ejercicio 11'!$E$7 -> 1811887.7
A12: Energía eléctrica | B12: =('DE-Costos'!B10/'Gastos Merc en curso y SE'!$B$1)*'Ejercicio 11'!$D$7 -> 6577691.2 | C12: =('DE-Costos'!C10/'Gastos Merc en curso y SE'!$B$2)*'Ejercicio 11'!$E$7 -> 5539108.3
A13: Combustibles | B13: =('DE-Costos'!B11/'Gastos Merc en curso y SE'!$B$1)*'Ejercicio 11'!$D$7 -> 0 | C13: =('DE-Costos'!C11/'Gastos Merc en curso y SE'!$B$2)*'Ejercicio 11'!$E$7 -> 0
A14: Tasas e impuestos | B14: =('DE-Costos'!B12/'Gastos Merc en curso y SE'!$B$1)*'Ejercicio 11'!$D$7 -> 1752001.1 | C14: =('DE-Costos'!C12/'Gastos Merc en curso y SE'!$B$2)*'Ejercicio 11'!$E$7 -> 1401600.8
A15: Seguros | B15: =('DE-Costos'!B13/'Gastos Merc en curso y SE'!$B$1)*'Ejercicio 11'!$D$7 -> 6622045.3 | C15: =('DE-Costos'!C13/'Gastos Merc en curso y SE'!$B$2)*'Ejercicio 11'!$E$7 -> 5115346.8
A16: Imprevistos | B16: =('DE-Costos'!B14/'Gastos Merc en curso y SE'!$B$1)*'Ejercicio 11'!$D$7 -> 1113395.7 | C16: =('DE-Costos'!C14/'Gastos Merc en curso y SE'!$B$2)*'Ejercicio 11'!$E$7 -> 1042144.8

Sheet Seguros
A1: Bienes de uso | B1: Valor original | C1: Año 1 | E1: Años 2 a 10
C2: Coeficiente | D2: Prima | E2: Coeficiente | F2: Prima
A3: Edificio | B3: ='DE-Inv AF y Am'!B7 -> 1.9338843e+09 | C3: 0.01 | D3: =B3*C3 -> 19338843 | E3: 0.008 | F3: =B3*E3 -> 15471074
A4: Instalaciones | B4: ='DE-Inv AF y Am'!B8 -> 0 | C4: 0.015 | D4: =B4*C4 -> 0 | E4: 0.01 | F4: =B4*E4 -> 0
A5: Máquinas | B5: ='DE-Inv AF y Am'!B12 -> 55250000 | C5: 0.015 | D5: =B5*C5 -> 828750 | E5: 0.008 | F5: =B5*E5 -> 442000
A6: Rodados y equipos | B6: ='DE-Inv AF y Am'!B16 -> 713037970 | C6: 0.11 | D6: =B6*C6 -> 78434177 | E6: 0.11 | F6: =B6*E6 -> 78434177
A7: Muebles y útiles | B7: ='DE-Inv AF y Am'!B17 -> 51585600 | C7: 0.015 | D7: =B7*C7 -> 773784 | E7: 0.015 | F7: =B7*E7 -> 773784
B8: Totales | D8: =SUM(D3:D7) -> 99375554 | F8: =SUM(F3:F7) -> 95121035
C10: Año 1 | E10: Año 2 al 10
B11: Bienes de cambio | C11: Coeficiente | D11: Prima | E11: Coeficiente | F11: Prima
B12: Stock de materia prima | C12: 0.02 | D12: =C12*'DE-Costos'!$B$4 -> 9519255 | E12: 0.02 | F12: =E12*'DE-Costos'!$C$4 -> 12812300
B13: Stock de materiales | C13: 0.01 | D13: =C13*'DE-Costos'!$B$4 -> 4759627.5 | E13: 0.01
B14: Mercadería en proceso | C14: 0.01 | D14: =C14*'DE-Costos'!$B$4 -> 4759627.5 | E14: 0.01 | F14: =E14*'DE-Costos'!$C$4 -> 6406150
B15: Totales | D15: =SUM(D12:D14) -> 19038510 | F15: =SUM(F12:F14) -> 19218450
B18: Resumen: | C18: Prima | D18: Año 1 | E18: Año 2 a 10
C19: Bienes de uso | D19: =D8 -> 99375554 | E19: =F8 -> 95121035
C20: Bienes de cambio | D20: =D15 -> 19038510 | E20: =F15 -> 19218450
C21: Total | D21: =SUM(D19:D20) -> 1.1841406e+08 | E21: =SUM(E19:E20) -> 1.1433949e+08

Sheet Tasas e Impuestos
A1: Tasa municipal | B1: 0.008 | E1: Distribución por Área
A2: Impuesto inmobiliario | B2: 0.01 | E2: Producción | F2: Administración | G2: Comercialización
E3: 0.9 | F3: 0.05 | G3: 0.05
A7: Edificio y obras complementarias: | B7: ='DE-Inv AF y Am'!B43 -> 1.9338843e+09
A9: - | B9: Producción | C9: Administración | D9: Comercialización
A10: Tasa municipal | B10: =B1*$E$3*$B$7 -> 13923967 | C10: =B1*$F$3*$B$7 -> 773553.72 | D10: =B1*$G$3*$B$7 -> 773553.72
A11: Impuesto inmobiliario | B11: =B2*$E$3*$B$7 -> 17404959 | C11: =B2*$F$3*$B$7 -> 966942.15 | D11: =B2*$G$3*$B$7 -> 966942.15
A12: total anual año 1 a 10 | B12: =SUM(B10:B11) -> 31328926 | C12: =SUM(C10:C11) -> 1740495.9 | D12: =SUM(D10:D11) -> 1740495.9

Sheet DE-Inv AF y Am
J2: CALCULOS AUXILIARES | Q2: Muebles Y Utiles | R2: Precio x Un. | S2: Cantidad | T2: Total | V2: Instalaciones industriales | W2: Total
A3: Inversión Inicial en Activo Fijo | B3: Gasto interno (en $) | D3: Gasto Externo (en U$S) | Q3: Escritorios | R3: 86000 | S3: 12 | T3: =R3*S3 -> 1032000 | V3: Circuitos Iluminación | W3: 9000000
B4: Año 0 | C4: Año 1 | D4: Año 0 | E4: Año 1 | J4: https://inmueble.mercadolibre.com.ar/MLA-1411251467-2500-m2-pacheco-sobre-4200-m2-de-terreno-ubicado-a-300-mts-de-au-panamericana-_JM#position=10&search_layout=grid&type=item&tracking_id=0bfa1e80-f939-4613-b9c2-5152c3262cbb | K4: Terreno | L4: 1800000 | M4: USD | Q4: Sillas de oficina | R4: 114000 | S4: 20 | T4: =R4*S4 -> 2280000 | V4: Desague | W4: 3700000
Q5: Notebooks/PC | R5: 1180000 | S5: 12 | T5: =R5*S5 -> 14160000 | V5: Bombas | W5: 600000
A6: a) Bienes de Uso | Q6: Impresora | R6: 445000 | S6: 1 | T6: =R6*S6 -> 445000 | V6: Tanque de agua | W6: 900000
A7: Terreno y sus mejoras: | B7: =(L4*InfoInicial!B30)/1.21 -> 1.9338843e+09 | Q7: Telefonos | R7: 540000 | S7: 12 | T7: =R7*S7 -> 6480000 | V7: Sanitarias | W7: 1600000
A8: Edificio y obras complementarias: | B8: 0 | J8: Rodados y Eq. Aux | K8: Precio x Un. | L8: Cantidad | M8: Total | Q8: Set de utiles | R8: 15000 | S8: 12 | T8: =R8*S8 -> 180000 | V8: Deteccion de incendio | W8: 1200000
A9: Instalaciones industriales: | B9: =W11 -> 27800000 | J9: Autoelevador | K9: 22000000 | L9: 1 | M9: =K9*L9 -> 22000000 | Q9: Mesas Comedor | R9: 400000 | S9: 4 | T9: =R9*S9 -> 1600000 | V9: Sistema Tuberías | W9: 800000
A10: Máquinas operativas: | J10: Zorra hidraulica | K10: 500000 | L10: 2 | M10: =K10*L10 -> 1000000 | Q10: Sillas Comedor | R10: 420000 | S10: 25 | T10: =R10*S10 -> 10500000 | V10: Fuerza motriz | W10: 10000000
A11: importadas, valor FOB, con repuestos: | B11: 0 | J11: Cinta Transportadora | K11: 1200000 | L11: 1 | M11: =K11*L11 -> 1200000 | Q11: Tachos de basura | R11: 93000 | S11: 7 | T11: =R11*S11 -> 651000 | W11: =SUM(W3:W10) -> 27800000
A12: nacionales, precio en fábrica del proveedor: | B12: =SUM($M$27:$M$34) -> 55250000 | J12: Medidor digital de humedad para granos de soja | K12: 175000 | L12: 1 | M12: =K12*L12 -> 175000 | Q12: Proyectores | R12: 190000 | S12: 5 | T12: =R12*S12 -> 950000
J13: Medidor digital de humedad para harinas de soja | K13: 425000 | L13: 1 | M13: =K13*L13 -> 425000
A14: Gastos conexos a la importación de maquinaria: | B14: 0 | J14: Termómetro infrarojo | K14: 42500 | L14: 1 | M14: =K14*L14 -> 42500 | Q14: Mingitorios | R14: 700000 | S14: 3 | T14: =R14*S14 -> 2100000
A15: Transporte y montaje de la maquinaria: | B15: =B12*0.05 -> 2762500 | J15: Medidor de PH | K15: 68274 | L15: 1 | M15: =K15*L15 -> 68274 | Q15: Inodoro | R15: 80000 | S15: 5 | T15: =R15*S15 -> 400000
A16: Rodados y equipos auxiliares: | B16: =M19 -> 713037970 | J16: Pallets de madera normalizados | K16: =M47 -> 2600 | L16: =N45 -> 358 | M16: =K16*L16 -> 930800 | Q16: Lavamanos | R16: 160000 | S16: 3 | T16: =R16*S16 -> 480000
A17: Muebles y útiles: | B17: =T30 -> 51585600 | J17: Tubos PVC | K17: =L57 -> 1688 | L17: =N53 -> 291667 | M17: =K17*L17 -> 492333896 | Q17: Dispenser de agua | R17: 150000 | S17: 4 | T17: =R17*S17 -> 600000
A18: Infraestructura en predio propio: | J18: Bomba de agua | K18: =L61 -> 22270 | L18: =P53 -> 8750 | M18: =K18*L18 -> 194862500 | Q18: Aire Acondicionado | R18: 560000 | S18: 3 | T18: =R18*S18 -> 1680000
A19: Imprevistos: | B19: =SUM(B7:B18)*InfoInicial!I13 -> 55686407 | L19: Total | M19: =SUM(M9:M18) -> 713037970 | Q19: Matafuegos | R19: 69000 | S19: 3 | T19: =R19*S19 -> 207000
A20: Total Bienes de uso: | B20: =SUM(B7:B19) -> 2.8400068e+09 | Q20: Horno Eléctrico | R20: 150000 | S20: 3 | T20: =R20*S20 -> 450000
Q21: Heladera c/freezer | R21: 580000 | S21: 3 | T21: =R21*S21 -> 1740000
A22: b) Gastos asimilables o cargos diferidos: | Q22: Lavavajillas | R22: 770000 | S22: 2 | T22: =R22*S22 -> 1540000
A23: Investigaciones y estudios: | B23: 300000 | Q23: Cafetera | R23: 260000 | S23: 1 | T23: =R23*S23 -> 260000
A24: Constitución y organización de la empresa: | B24: 623000 | Q24: Microondas | R24: 200000 | S24: 1 | T24: =R24*S24 -> 200000
A25: Gastos de Administración e Ingeniería | B25: 18050000 | Q25: Mesa de Trabajo | R25: 180000 | S25: 3 | T25: =R25*S25 -> 540000
A26: durante el período de instalación: | B26: 0 | J26: Máquinas Operativas | K26: Precio x Un. | L26: Cantidad | M26: Total | N26: Nacional | Q26: Detector de humo | R26: 16000 | S26: 4 | T26: =R26*S26 -> 64000
A27: Gastos de puesta en marcha: | B27: 0 | C27: 9152278.7 | J27: Separadora | K27: 5850000 | L27: 1 | M27: =K27*L27 -> 5850000 | N27: x | Q27: Estanterias | R27: 160000 | S27: 10 | T27: =R27*S27 -> 1600000
A28: Patentes y Licencias: | B28: 150000 | J28: Descascaradora | K28: 9750000 | L28: 1 | M28: =K28*L28 -> 9750000 | N28: x | Q28: Locker | R28: 422200 | S28: 3 | T28: =R28*S28 -> 1266600 | U28: (Locker de 8 puertas la unidad)
A29: Infraestructura en predio ajeno: | J29: Molino Grueso | K29: 3000000 | L29: 2 | M29: =K29*L29 -> 6000000 | N29: x | Q29: Ventiladores | R29: 45000 | S29: 4 | T29: =R29*S29 -> 180000
A30: Imprevistos: | B30: =SUM(B23:B29)*InfoInicial!I13 -> 382460 | C30: =SUM(C23:C29)*InfoInicial!I13 -> 183045.57 | J30: Extrusora | K30: 4750000 | L30: 2 | M30: =K30*L30 -> 9500000 | N30: x | S30: Total | T30: =SUM(T3:T29) -> 51585600
A31: Total gastos asimilables o cargos diferidos: | B31: =SUM(B23:B30) -> 19505460 | C31: =SUM(C23:C30) -> 9335324.3 | J31: Prensa | K31: 8500000 | L31: 1 | M31: =K31*L31 -> 8500000 | N31: x
J32: Secadora de Granos | K32: 7400000 | L32: 1 | M32: =K32*L32 -> 7400000 | N32: x
A33: c) Total Inversiones iniciales Activo Fijo, sin IVA | B33: =B20+B31 -> 2.8595122e+09 | C33: =C20+C31 -> 9335324.3 | J33: Molienda | K33: 3250000 | L33: 1 | M33: =K33*L33 -> 3250000 | N33: x
J34: Empaquetadora | K34: 5000000 | L34: 1 | M34: =K34*L34 -> 5000000 | N34: x
A35: d) IVA: | B35: =B33*0.21 -> 6.0049757e+08 | C35: =C33*0.21 -> 1960418.1
A37: e) TOTAL INVERSIONES INICIALES ACTIVO FIJO | B37: =B33+B35 -> 3.4600098e+09 | C37: =C33+C35 -> 11295742 | J37: http://pa.bibdigital.ucc.edu.ar/3437/1/TM_Bruera%20%282%29.pdf | K37: Planta de Acopio y Secado de granos, referencia
J38: https://www.moralesyasociados.com.ar/costo-de-constituir-una-srl-o-una-sa/#:~:text=Tanto%20en%20CABA%20como%20en,disponga%20la%20compa%C3%B1ia%20de%20seguros). | K38: Estudio de Abogados
J39: https://www.uoyepweb.org.ar/escala-salarial/ | K39: Escala Salarial
A40: Rubro | B40: Inversión | C40: Coeficiente | D40: Alícuotas de amortización | G40: Valor residual
B41: original | D41: Años 1/3 | E41: Años 4/5 | F41: Años 6/10
A42: Bienes de Uso
A43: Terreno y sus mejoras: | B43: =B7 -> 1.9338843e+09 | G43: =B43-D43 -> 1.9338843e+09
A44: Edificio y obras complementarias: | B44: 0 | C44: =1/InfoInicial!B7 -> 0.033333333 | D44: 0 | E44: 0 | F44: 0 | G44: 0 | L44: Pallets (3500kg)
A45: Instalaciones industriales: | B45: =B9 -> 27800000 | C45: =1/InfoInicial!B8 -> 0.1 | D45: =$B45*$C45 -> 2780000 | E45: =$B45*$C45 -> 2780000 | F45: =$B45*$C45 -> 2780000 | G45: =B45-D45*10 -> 0 | K45: Lote cuatrimestral en régimen | L45: =(1000*5000)/4 -> 1250000 | M45: kg | N45: 358 | O45: Pallets | P45: =N45*M47 -> 930800 | Q45: Es una única compra en el año 1
A46: Máquinas operativas: (*) | B46: =B12+B15 -> 58012500 | C46: =1/InfoInicial!B9 -> 0.1 | D46: =$B46*$C46 -> 5801250 | E46: =$B46*$C46 -> 5801250 | F46: =$B46*$C46 -> 5801250 | G46: =B46-D46*10 -> 0
A47: Rodados y equipos auxiliares: (**) | B47: =B16 -> 713037970 | C47: =1/InfoInicial!B10 -> 0.2 | D47: =$B47*$C47 -> 142607594 | E47: =$B47*$C47 -> 142607594 | F47: 0 | G47: =B47-D47*5 -> 0 | L47: Precio unitario | M47: 2600 | N47: https://articulo.mercadolibre.com.ar/MLA-1142588105-pallet-madera-normalizados-_JM?searchVariation=174645647545#searchVariation%3D174645647545%26position%3D4%26search_layout%3Dgrid%26type%3Ditem%26tracking_id%3D4291ee21-22bf-4939-9bf7-413ede7b6573#polycard_client=search-nordic&searchVariation=174645647545&position=4&search_layout=grid&type=item&tracking_id=4291ee21-22bf-4939-9bf7-413ede7b6573
A48: Muebles y útiles: (***) | B48: =B17 -> 51585600 | C48: =1/InfoInicial!B11 -> 0.2 | D48: =$B48*$C48 -> 10317120 | E48: =$B48*$C48 -> 10317120 | F48: 0 | G48: =B48-D48*5 -> 0
A49: Imprevistos | B49: =B19+D19 -> 55686407 | C49: =1/InfoInicial!B13 -> 0.2 | D49: =$B49*$C49 -> 11137281 | E49: =$B49*$C49 -> 11137281 | F49: 0 | G49: =B49-D49*5 -> 0
A50: Repuestos (****) | B50: 0 | C50: =1/InfoInicial!B12 -> 0.33333333 | D50: =$B50*$C50 -> 0 | E50: =$B50*$C50 -> 0 | F50: =$B50*$C50 -> 0 | G50: 0
A51: Subtotal | B51: =SUM(B43:B50) -> 2.8400068e+09 | D51: =SUM(D44:D50) -> 1.7264325e+08 | E51: =SUM(E44:E50) -> 1.7264325e+08 | F51: =SUM(F44:F50) -> 8581250 | G51: =B51-3*D51-2*E51-5*F51 -> 1.9338843e+09 | N51: Sistema Hidropónico
L52: Cantidad Plantas | M52: Toneladas | N52: Tubos | P52: Bombas | R52: Total
A53: Cargos Diferidos | B53: =B31+C31 -> 28840784 | C53: =1/InfoInicial!B13 -> 0.2 | D53: =$B53*$C53 -> 5768156.9 | E53: =$B53*$C53 -> 5768156.9 | F53: 0 | G53: =B53-D53*5 -> 0 | L53: 8750000 | M53: 1250 | N53: 291667 | O53: =N53*L57 -> 492333896 | P53: 8750 | Q53: =P53*L61 -> 194862500 | R53: =O53+Q53 -> 687196396
A55: Totales, s/IVA | B55: =B51+B53 -> 2.8688476e+09 | D55: =D51+D53 -> 1.784114e+08 | E55: =E51+E53 -> 1.784114e+08 | F55: =F51+F53 -> 8581250 | G55: =G51 -> 1.9338843e+09
L56: Tubo (Un) | M56: https://www.mercadolibre.com.ar/tubo-de-pvc-cano-rigido-semipesado-20mm-34-genrod-x37-tiras/p/MLA29106841#polycard_client=search-nordic&searchVariation=MLA29106841&position=2&search_layout=grid&type=product&tracking_id=822af6ef-2040-
L57: 1688
L58: =30 -> 30 | M58: Plantas por tubo
L60: Bomba (Un) | M60: https://articulo.mercadolibre.com.ar/MLA-1470630360-bomba-rs-932-15-mts-de-manguera-12-pulgada-hidroponia-_JM#polycard_client=search-nordic&position=2&search_layout=stack&type=item&tracking_id=cb55a88d-eba8-458c-a8cf-aad896fb2873
L61: =22270 -> 22270
L62: 1000 | M62: Por planta

Sheet DE-Costos
A1: COSTO TOTAL DE PRODUCCION
B2: Gastos en el Area de Producción | O2: CALCULOS AUXILIARES
A3: Rubros | B3: Año 1 | C3: Año 2 | D3: Año 3 | E3: Año 4 | F3: Año 5 | G3: Año 6 | H3: Año 7 | I3: Año 8 | J3: Año 9 | K3: Año 10
A4: Materia prima | B4: ='Materia Prima'!C10+'Materia Prima'!K5 -> 4.7596275e+08 | C4: ='Materia Prima'!$C$11+'Materia Prima'!$K$6 -> 6.40615e+08 | D4: ='Materia Prima'!$C$11+'Materia Prima'!$K$6 -> 6.40615e+08 | E4: ='Materia Prima'!$C$11+'Materia Prima'!$K$6 -> 6.40615e+08 | F4: ='Materia Prima'!$C$11+'Materia Prima'!$K$6 -> 6.40615e+08 | G4: ='Materia Prima'!$C$11+'Materia Prima'!$K$6 -> 6.40615e+08 | H4: ='Materia Prima'!$C$11+'Materia Prima'!$K$6 -> 6.40615e+08 | I4: ='Materia Prima'!$C$11+'Materia Prima'!$K$6 -> 6.40615e+08 | J4: ='Materia Prima'!$C$11+'Materia Prima'!$K$6 -> 6.40615e+08 | K4: ='Materia Prima'!$C$11+'Materia Prima'!$K$6 -> 6.40615e+08 | P4: https://www.boletinoficial.gob.ar/detalleAviso/primera/308813/20240607#:~:text=ART%C3%8DCULO%205.,asciende%20a%2095%2C624%20%24%2FkWh. | Q4: Tomando de referencia que el valor de KWH es de 95,624$/kwh
A5: Mano de obra directa | B5: =$W$34 -> 29610097 | C5: =$W$34 -> 29610097 | D5: =$W$34 -> 29610097 | E5: =$W$34 -> 29610097 | F5: =$W$34 -> 29610097 | G5: =$W$34 -> 29610097 | H5: =$W$34 -> 29610097 | I5: =$W$34 -> 29610097 | ... K5: =$W$34 -> 29610097 | P5: Maquinaria | Q5: Cant | R5: Consumo Unitario (KWh) | S5: Hs Activas al Año | T5: Consumo Anual (KW) | U5: Costo KWH
A6: Gastos de fabricación: | P6: Separadora de Granos | Q6: 1 | R6: 3.5 | S6: 5440 | T6: =Q6*R6*S6 -> 19040 | U6: =T6*95.624 -> 1820681
A7: Amortizaciones | B7: ='DE-Inv AF y Am'!$D$55*0.9 -> 1.6057026e+08 | C7: ='DE-Inv AF y Am'!$D$55*0.9 -> 1.6057026e+08 | D7: ='DE-Inv AF y Am'!$D$55*0.9 -> 1.6057026e+08 | E7: ='DE-Inv AF y Am'!$D$55*0.9 -> 1.6057026e+08 | F7: ='DE-Inv AF y Am'!$D$55*0.9 -> 1.6057026e+08 | G7: ='DE-Inv AF y Am'!$D$55*0.9 -> 1.6057026e+08 | H7: ='DE-Inv AF y Am'!$D$55*0.9 -> 1.6057026e+08 | I7: ='DE-Inv AF y Am'!$D$55*0.9 -> 1.6057026e+08 | ... K7: ='DE-Inv AF y Am'!$D$55*0.9 -> 1.6057026e+08 | P7: Descascadora | Q7: 1 | R7: 15 | S7: 5440 | T7: =Q7*R7*S7 -> 81600 | U7: =T7*95.624 -> 7802918.4
A8: Personal indirecto | B8: =$W$33 -> 23938778 | C8: =$W$33 -> 23938778 | D8: =$W$33 -> 23938778 | E8: =$W$33 -> 23938778 | F8: =$W$33 -> 23938778 | G8: =$W$33 -> 23938778 | H8: =$W$33 -> 23938778 | I8: =$W$33 -> 23938778 | ... K8: =$W$33 -> 23938778 | P8: Molino Grueso | Q8: 2 | R8: 0.55 | S8: 5440 | T8: =Q8*R8*S8 -> 5984 | U8: =T8*95.624 -> 572214.02
A9: Materiales | B9: ='Materiales área producción'!C13 -> 38029975 | C9: ='Materiales área producción'!D13 -> 40499759 | D9: ='Materiales área producción'!E13 -> 40499759 | E9: ='Materiales área producción'!F13 -> 40499759 | F9: ='Materiales área producción'!G13 -> 40499759 | G9: ='Materiales área producción'!H13 -> 40499759 | H9: ='Materiales área producción'!I13 -> 40499759 | I9: ='Materiales área producción'!J13 -> 40499759 | ... K9: ='Materiales área producción'!L13 -> 40499759 | P9: Extrusora | Q9: 2 | R9: 92.5 | S9: 5440 | T9: =Q9*R9*S9 -> 1006400 | U9: =T9*95.624 -> 96235994
A10: Energía eléctrica | B10: =0.95*U13 -> 1.1762093e+08 | C10: =$U$13 -> 1.2381151e+08 | D10: =$U$13 -> 1.2381151e+08 | E10: =$U$13 -> 1.2381151e+08 | F10: =$U$13 -> 1.2381151e+08 | G10: =$U$13 -> 1.2381151e+08 | H10: =$U$13 -> 1.2381151e+08 | I10: =$U$13 -> 1.2381151e+08 | J10: =$U$13 -> 1.2381151e+08 | K10: =$U$13 -> 1.2381151e+08 | P10: Prensadora | Q10: 1 | R10: 30 | S10: 5440 | T10: =Q10*R10*S10 -> 163200 | U10: =T10*95.624 -> 15605837
A11: Combustibles | B11: 0 | C11: 0 | D11: 0 | E11: 0 | F11: 0 | G11: 0 | H11: 0 | I11: 0 | J11: 0 | K11: 0 | P11: Molienda | Q11: 1 | R11: 1.21 | S11: 5440 | T11: =Q11*R11*S11 -> 6582.4 | U11: =T11*95.624 -> 629435.42
A12: Tasas e impuestos | B12: ='Tasas e Impuestos'!$B$12 -> 31328926 | C12: ='Tasas e Impuestos'!$B$12 -> 31328926 | D12: ='Tasas e Impuestos'!$B$12 -> 31328926 | E12: ='Tasas e Impuestos'!$B$12 -> 31328926 | F12: ='Tasas e Impuestos'!$B$12 -> 31328926 | G12: ='Tasas e Impuestos'!$B$12 -> 31328926 | H12: ='Tasas e Impuestos'!$B$12 -> 31328926 | I12: ='Tasas e Impuestos'!$B$12 -> 31328926 | ... K12: ='Tasas e Impuestos'!$B$12 -> 31328926 | P12: Empaquetadora | Q12: 1 | R12: 2.2 | S12: 5440 | T12: =Q12*R12*S12 -> 11968 | U12: =T12*95.624 -> 1144428
A13: Seguros | B13: =Seguros!$D$21 -> 1.1841406e+08 | C13: =Seguros!$E$21 -> 1.1433949e+08 | D13: =Seguros!$E$21 -> 1.1433949e+08 | E13: =Seguros!$E$21 -> 1.1433949e+08 | F13: =Seguros!$E$21 -> 1.1433949e+08 | G13: =Seguros!$E$21 -> 1.1433949e+08 | H13: =Seguros!$E$21 -> 1.1433949e+08 | I13: =Seguros!$E$21 -> 1.1433949e+08 | J13: =Seguros!$E$21 -> 1.1433949e+08 | K13: =Seguros!$E$21 -> 1.1433949e+08 | U13: =SUM(U6:U12) -> 1.2381151e+08
A14: Imprevistos | B14: =SUM(B4:B13)*InfoInicial!$I$13 -> 19909516 | C14: =SUM(C4:C13)*InfoInicial!$I$13 -> 23294276 | D14: =SUM(D4:D13)*InfoInicial!$I$13 -> 23294276 | E14: =SUM(E4:E13)*InfoInicial!$I$13 -> 23294276 | F14: =SUM(F4:F13)*InfoInicial!$I$13 -> 23294276 | G14: =SUM(G4:G13)*InfoInicial!$I$13 -> 23294276 | H14: =SUM(H4:H13)*InfoInicial!$I$13 -> 23294276 | I14: =SUM(I4:I13)*InfoInicial!$I$13 -> 23294276 | ... K14: =SUM(K4:K13)*InfoInicial!$I$13 -> 23294276
A15: Gastos Total de Producción | B15: =SUM(B4:B14) -> 1.0153853e+09 | C15: =SUM(C4:C14) -> 1.1880081e+09 | D15: =SUM(D4:D14) -> 1.1880081e+09 | E15: =SUM(E4:E14) -> 1.1880081e+09 | F15: =SUM(F4:F14) -> 1.1880081e+09 | G15: =SUM(G4:G14) -> 1.1880081e+09 | H15: =SUM(H4:H14) -> 1.1880081e+09 | I15: =SUM(I4:I14) -> 1.1880081e+09 | ... K15: =SUM(K4:K14) -> 1.1880081e+09
P16: Equipo | Q16: Cantidad | R16: Consumo Unitario (KWh) | S16: Hs Activas al Año | T16: Consumo Anual (KW) | U16: Costo KWH
A17: % Gasto Variable | B17: =1-B18 -> 0.53536606 | C17: =1-C18 -> 0.59824917 | D17: =1-D18 -> 0.59824917 | E17: =1-E18 -> 0.59824917 | F17: =1-F18 -> 0.59824917 | G17: =1-G18 -> 0.59824917 | H17: =1-H18 -> 0.59824917 | I17: =1-I18 -> 0.59824917 | ... K17: =1-K18 -> 0.59824917 | P17: Ventiladores | Q17: 4 | R17: 0.06 | S17: 1188 | T17: =Q17*R17*S17 -> 285.12 | U17: =T17*95.624 -> 27264.315
A18: % Gasto Constante | B18: =(B7+B8+B10+B11+B12+B13+B14)/B15 -> 0.46463394 | C18: =(C7+C8+C10+C11+C12+C13+C14)/C15 -> 0.40175083 | D18: =(D7+D8+D10+D11+D12+D13+D14)/D15 -> 0.40175083 | E18: =(E7+E8+E10+E11+E12+E13+E14)/E15 -> 0.40175083 | F18: =(F7+F8+F10+F11+F12+F13+F14)/F15 -> 0.40175083 | G18: =(G7+G8+G10+G11+G12+G13+G14)/G15 -> 0.40175083 | H18: =(H7+H8+H10+H11+H12+H13+H14)/H15 -> 0.40175083 | I18: =(I7+I8+I10+I11+I12+I13+I14)/I15 -> 0.40175083 | ... K18: =(K7+K8+K10+K11+K12+K13+K14)/K15 -> 0.40175083 | P18: Computadoras | Q18: 12 | R18: 0.02 | S18: 5440 | T18: =Q18*R18*S18 -> 1305.6 | U18: =T18*95.624 -> 124846.69
P19: Aire Acondicionado | Q19: 3 | R19: 1.013 | S19: 4200 | T19: =Q19*R19*S19 -> 12763.8 | U19: =T19*95.624 -> 1220525.6
B20: Gastos a activar | P20: Impresora | Q20: 1 | R20: 0.6 | S20: 1560 | T20: =Q20*R20*S20 -> 936 | U20: =T20*95.624 -> 89504.064
B21: Mercadería en Curso y Semielaborada | L21: Puesta en marcha | P21: Microondas | Q21: 1 | R21: 0.64 | S21: 600 | T21: =Q21*R21*S21 -> 384 | U21: =T21*95.624 -> 36719.616
A22: Rubros | B22: Año 1 | C22: Año 2 | D22: Año 3 | E22: Año 4 | F22: Año 5 | G22: Año 6 | H22: Año 7 | I22: Año 8 | J22: Año 9 | K22: Año 10 | L22: Año 1 | P22: Luminarias | Q22: 20 | R22: 0.1 | S22: 5440 | T22: =Q22*R22*S22 -> 10880 | U22: =T22*95.624 -> 1040389.1
A23: Materia prima | B23: ='Gastos Merc en curso y SE'!B7 -> 26617167 | C23: ='Gastos Merc en curso y SE'!$C$7 -> 28659985 | D23: ='Gastos Merc en curso y SE'!$C$7 -> 28659985 | E23: ='Gastos Merc en curso y SE'!$C$7 -> 28659985 | F23: ='Gastos Merc en curso y SE'!$C$7 -> 28659985 | G23: ='Gastos Merc en curso y SE'!$C$7 -> 28659985 | H23: ='Gastos Merc en curso y SE'!$C$7 -> 28659985 | I23: ='Gastos Merc en curso y SE'!$C$7 -> 28659985 | J23: ='Gastos Merc en curso y SE'!$C$7 -> 28659985 | K23: ='Gastos Merc en curso y SE'!$C$7 -> 28659985 | L23: =(B23/11.5)*3 -> 6943608.8 | P23: Lavavajilla | Q23: 1 | R23: 0.0285 | S23: 8640 | T23: =Q23*R23*S23 -> 246.24 | U23: =T23*95.624 -> 23546.454
A24: Mano de obra directa | B24: ='Gastos Merc en curso y SE'!B8 -> 1655879.4 | C24: ='Gastos Merc en curso y SE'!$C$8 -> 1324703.5 | D24: ='Gastos Merc en curso y SE'!$C$8 -> 1324703.5 | E24: ='Gastos Merc en curso y SE'!$C$8 -> 1324703.5 | F24: ='Gastos Merc en curso y SE'!$C$8 -> 1324703.5 | G24: ='Gastos Merc en curso y SE'!$C$8 -> 1324703.5 | H24: ='Gastos Merc en curso y SE'!$C$8 -> 1324703.5 | I24: ='Gastos Merc en curso y SE'!$C$8 -> 1324703.5 | J24: ='Gastos Merc en curso y SE'!$C$8 -> 1324703.5 | K24: ='Gastos Merc en curso y SE'!$C$8 -> 1324703.5 | L24: =(B24/11.5)*3 -> 431968.53 | P24: Heladera | Q24: 1 | R24: 0.09 | S24: 8640 | T24: =Q24*R24*S24 -> 777.6 | U24: =T24*95.624 -> 74357.222
A25: Gastos de fabricación: | L25: =(B25/11.5)*3 -> 0 | P25: Cafetera | Q25: 1 | R25: 0.9 | S25: 1440 | T25: =Q25*R25*S25 -> 1296 | U25: =T25*95.624 -> 123928.7
A26: Amortizaciones | B26: ='Gastos Merc en curso y SE'!B9 -> 8979537.7 | C26: ='Gastos Merc en curso y SE'!$C$9 -> 7183630.2 | D26: ='Gastos Merc en curso y SE'!$C$9 -> 7183630.2 | E26: ='Gastos Merc en curso y SE'!$C$9 -> 7183630.2 | F26: ='Gastos Merc en curso y SE'!$C$9 -> 7183630.2 | G26: ='Gastos Merc en curso y SE'!$C$9 -> 7183630.2 | H26: ='Gastos Merc en curso y SE'!$C$9 -> 7183630.2 | I26: ='Gastos Merc en curso y SE'!$C$9 -> 7183630.2 | J26: ='Gastos Merc en curso y SE'!$C$9 -> 7183630.2 | K26: ='Gastos Merc en curso y SE'!$C$9 -> 7183630.2 | L26: 0 | P26: Horno Eléctrico | Q26: 1 | R26: 0.75 | S26: 1080 | T26: =Q26*R26*S26 -> 810 | U26: =T26*95.624 -> 77455.44
A27: Personal indirecto | B27: ='Gastos Merc en curso y SE'!B10 -> 1338723.3 | C27: ='Gastos Merc en curso y SE'!$C$10 -> 1070978.7 | D27: ='Gastos Merc en curso y SE'!$C$10 -> 1070978.7 | E27: ='Gastos Merc en curso y SE'!$C$10 -> 1070978.7 | F27: ='Gastos Merc en curso y SE'!$C$10 -> 1070978.7 | G27: ='Gastos Merc en curso y SE'!$C$10 -> 1070978.7 | H27: ='Gastos Merc en curso y SE'!$C$10 -> 1070978.7 | I27: ='Gastos Merc en curso y SE'!$C$10 -> 1070978.7 | J27: ='Gastos Merc en curso y SE'!$C$10 -> 1070978.7 | K27: ='Gastos Merc en curso y SE'!$C$10 -> 1070978.7 | L27: 0 | P27: Proyector | Q27: 2 | R27: 0.568 | S27: 420 | T27: =Q27*R27*S27 -> 477.12 | U27: =T27*95.624 -> 45624.123
A28: Materiales | B28: ='Gastos Merc en curso y SE'!B11 -> 2126742.5 | C28: ='Gastos Merc en curso y SE'!$C$11 -> 1811887.7 | D28: ='Gastos Merc en curso y SE'!$C$11 -> 1811887.7 | E28: ='Gastos Merc en curso y SE'!$C$11 -> 1811887.7 | F28: ='Gastos Merc en curso y SE'!$C$11 -> 1811887.7 | G28: ='Gastos Merc en curso y SE'!$C$11 -> 1811887.7 | H28: ='Gastos Merc en curso y SE'!$C$11 -> 1811887.7 | I28: ='Gastos Merc en curso y SE'!$C$11 -> 1811887.7 | J28: ='Gastos Merc en curso y SE'!$C$11 -> 1811887.7 | K28: ='Gastos Merc en curso y SE'!$C$11 -> 1811887.7 | L28: =(B28/11.5)*3 -> 554802.38 | U28: =SUM(U17:U27) -> 2884161.4
A29: Energía eléctrica | B29: ='Gastos Merc en curso y SE'!B12 -> 6577691.2 | C29: ='Gastos Merc en curso y SE'!$C$12 -> 5539108.3 | D29: ='Gastos Merc en curso y SE'!$C$12 -> 5539108.3 | E29: ='Gastos Merc en curso y SE'!$C$12 -> 5539108.3 | F29: ='Gastos Merc en curso y SE'!$C$12 -> 5539108.3 | G29: ='Gastos Merc en curso y SE'!$C$12 -> 5539108.3 | H29: ='Gastos Merc en curso y SE'!$C$12 -> 5539108.3 | I29: ='Gastos Merc en curso y SE'!$C$12 -> 5539108.3 | J29: ='Gastos Merc en curso y SE'!$C$12 -> 5539108.3 | K29: ='Gastos Merc en curso y SE'!$C$12 -> 5539108.3 | L29: =(B29/11.5)*3 -> 1715919.4
A30: Combustibles | B30: ='Gastos Merc en curso y SE'!B13 -> 0 | C30: ='Gastos Merc en curso y SE'!C13 -> 0 | L30: =(B30/11.5)*3 -> 0
A31: Tasas e impuestos | B31: ='Gastos Merc en curso y SE'!B14 -> 1752001.1 | C31: ='Gastos Merc en curso y SE'!$C$14 -> 1401600.8 | D31: ='Gastos Merc en curso y SE'!$C$14 -> 1401600.8 | E31: ='Gastos Merc en curso y SE'!$C$14 -> 1401600.8 | F31: ='Gastos Merc en curso y SE'!$C$14 -> 1401600.8 | G31: ='Gastos Merc en curso y SE'!$C$14 -> 1401600.8 | H31: ='Gastos Merc en curso y SE'!$C$14 -> 1401600.8 | I31: ='Gastos Merc en curso y SE'!$C$14 -> 1401600.8 | J31: ='Gastos Merc en curso y SE'!$C$14 -> 1401600.8 | K31: ='Gastos Merc en curso y SE'!$C$14 -> 1401600.8 | L31: 0 | P31: https://www.argentina.gob.ar/transporte/cnrt/transparencia/escalas-salariales | Q31: https://www.ignacioonline.com.ar/categorias-empleados-de-comercio-de-comercio-cct-130-75/ | R31: Escalas Salariales
A32: Seguros | B32: ='Gastos Merc en curso y SE'!B15 -> 6622045.3 | C32: ='Gastos Merc en curso y SE'!$C$15 -> 5115346.8 | D32: ='Gastos Merc en curso y SE'!$C$15 -> 5115346.8 | E32: ='Gastos Merc en curso y SE'!$C$15 -> 5115346.8 | F32: ='Gastos Merc en curso y SE'!$C$15 -> 5115346.8 | G32: ='Gastos Merc en curso y SE'!$C$15 -> 5115346.8 | H32: ='Gastos Merc en curso y SE'!$C$15 -> 5115346.8 | I32: ='Gastos Merc en curso y SE'!$C$15 -> 5115346.8 | J32: ='Gastos Merc en curso y SE'!$C$15 -> 5115346.8 | K32: ='Gastos Merc en curso y SE'!$C$15 -> 5115346.8 | L32: 0 | P32: Puesto | Q32: Salario Bruto x Mes | R32: Salario Bruto x Año | S32: Cantidad | T32: Sub total | U32: Cargas Sociales | V32: Aguinaldo Anual | W32: Total
A33: Imprevistos | B33: ='Gastos Merc en curso y SE'!B16 -> 1113395.7 | C33: ='Gastos Merc en curso y SE'!$C$16 -> 1042144.8 | D33: ='Gastos Merc en curso y SE'!$C$16 -> 1042144.8 | E33: ='Gastos Merc en curso y SE'!$C$16 -> 1042144.8 | F33: ='Gastos Merc en curso y SE'!$C$16 -> 1042144.8 | G33: ='Gastos Merc en curso y SE'!$C$16 -> 1042144.8 | H33: ='Gastos Merc en curso y SE'!$C$16 -> 1042144.8 | I33: ='Gastos Merc en curso y SE'!$C$16 -> 1042144.8 | J33: ='Gastos Merc en curso y SE'!$C$16 -> 1042144.8 | K33: ='Gastos Merc en curso y SE'!$C$16 -> 1042144.8 | L33: =(B33/11.5)*3 -> 290451.06 | P33: Jefe de calidad | Q33: 1185088 | R33: =Q33*12 -> 14221056 | S33: 1 | T33: =R33*S33 -> 14221056 | U33: =R33*0.6 -> 8532633.6 | V33: =Q33 -> 1185088 | W33: =T33+U33+V33 -> 23938778
A34: Total gastos a activar | B34: =SUM(B23:B33) -> 56783183 | C34: =SUM(C23:C33) -> 53149385 | D34: =SUM(D23:D33) -> 53149385 | E34: =SUM(E23:E33) -> 53149385 | F34: =SUM(F23:F33) -> 53149385 | G34: =SUM(G23:G33) -> 53149385 | H34: =SUM(H23:H33) -> 53149385 | I34: =SUM(I23:I33) -> 53149385 | ... K34: =SUM(K23:K33) -> 53149385 | L34: =SUM($L$23:$L$33) -> 9936750.2 | P34: Operario | Q34: 284166 | R34: =Q34*12 -> 3409992 | S34: 8 | T34: =R34*S34 -> 27279936 | U34: =R34*0.6 -> 2045995.2 | V34: =Q34 -> 284166 | W34: =T34+U34+V34 -> 29610097
L35: 9152278.7 | P35: Gerente de administracion | Q35: 1452453 | R35: =Q35*12 -> 17429436 | S35: 1 | T35: =R35*S35 -> 17429436 | U35: =R35*0.6 -> 10457662 | V35: =Q35 -> 1452453 | W35: =T35+U35+V35 -> 29339551
B36: Costo en el Area de Producción | P36: Encargado administrativo | Q36: 855278 | R36: =Q36*12 -> 10263336 | S36: 1 | T36: =R36*S36 -> 10263336 | U36: =R36*0.6 -> 6158001.6 | V36: =Q36 -> 855278 | W36: =T36+U36+V36 -> 17276616
B37: Año 1 | C37: Año 2 | D37: Año 3 | E37: Año 4 | F37: Año 5 | G37: Año 6 | H37: Año 7 | I37: Año 8 | J37: Año 9 | K37: Año 10 | P37: Encargado RRHH | Q37: 744500 | R37: =Q37*12 -> 8934000 | S37: 1 | T37: =R37*S37 -> 8934000 | U37: =R37*0.6 -> 5360400 | V37: =Q37 -> 744500 | W37: =T37+U37+V37 -> 15038900
A38: Gastos Total de Producción | B38: =+B15 -> 1.0153853e+09 | C38: =+C15 -> 1.1880081e+09 | D38: =+D15 -> 1.1880081e+09 | E38: =+E15 -> 1.1880081e+09 | F38: =+F15 -> 1.1880081e+09 | G38: =+G15 -> 1.1880081e+09 | H38: =+H15 -> 1.1880081e+09 | I38: =+I15 -> 1.1880081e+09 | ... K38: =+K15 -> 1.1880081e+09 | P38: Encargado de ventas | Q38: 855278 | R38: =Q38*12 -> 10263336 | S38: 1 | T38: =R38*S38 -> 10263336 | U38: =R38*0.6 -> 6158001.6 | V38: =Q38 -> 855278 | W38: =T38+U38+V38 -> 17276616
A39: Menos:
A40: Gasto de puesta en marcha (-) | B40: =L34 -> 9936750.2 | C40: 0 | E40: 0 | F40: 0 | G40: 0 | H40: 0 | I40: 0 | J40: 0 | K40: 0
A41: Mercadería al principio (+) | B41: =B34 -> 56783183 | C41: =C34 -> 53149385 | D41: =D34 -> 53149385 | E41: =E34 -> 53149385 | F41: =F34 -> 53149385 | G41: =G34 -> 53149385 | H41: =H34 -> 53149385 | I41: =I34 -> 53149385 | ... K41: =K34 -> 53149385
A42: Mercadería al final (-) | B42: 0 | C42: =B34 -> 56783183 | D42: =C34 -> 53149385 | E42: =D34 -> 53149385 | F42: =E34 -> 53149385 | G42: =F34 -> 53149385 | H42: =G34 -> 53149385 | I42: =H34 -> 53149385 | J42: =I34 -> 53149385 | K42: =J34 -> 53149385
A43: Variación Mercadería en proceso | B43: =B41-B42 -> 56783183 | C43: =C41-C42 -> -3633797.6 | D43: =D41-D42 -> 0 | E43: =E41-E42 -> 0 | F43: =F41-F42 -> 0 | G43: =G41-G42 -> 0 | H43: =H41-H42 -> 0 | I43: =I41-I42 -> 0 | ... K43: =K41-K42 -> 0
A44: Costo de producción anual | B44: =B38-B40-B43 -> 9.4866537e+08 | C44: =C38-C40-C43 -> 1.1916419e+09 | D44: =D38-D40-D43 -> 1.1880081e+09 | E44: =E38-E40-E43 -> 1.1880081e+09 | F44: =F38-F40-F43 -> 1.1880081e+09 | G44: =G38-G40-G43 -> 1.1880081e+09 | H44: =H38-H40-H43 -> 1.1880081e+09 | I44: =I38-I40-I43 -> 1.1880081e+09 | ... K44: =K38-K40-K43 -> 1.1880081e+09
A45: Costo de prod. Unitario Promedio ($/Tn) | B45: =B44/'Ejercicio 11'!$D$5 -> 237166.34 | C45: =C44/'Ejercicio 11'!$E$5 -> 238328.38 | D45: =D44/'Ejercicio 11'!$E$5 -> 237601.62 | E45: =E44/'Ejercicio 11'!$E$5 -> 237601.62 | F45: =F44/'Ejercicio 11'!$E$5 -> 237601.62 | G45: =G44/'Ejercicio 11'!$E$5 -> 237601.62 | H45: =H44/'Ejercicio 11'!$E$5 -> 237601.62 | I45: =I44/'Ejercicio 11'!$E$5 -> 237601.62 | J45: =J44/'Ejercicio 11'!$E$5 -> 237601.62 | K45: =K44/'Ejercicio 11'!$E$5 -> 237601.62
A47: % Costo Variable | B47: =(B4+B5+B7+B8+B9+B40)/B44 -> 0.77798625 | C47: =(C4+C5+C7+C8+C9+C40)/C44 -> 0.75126085 | D47: =(D4+D5+D7+D8+D9+D40)/D44 -> 0.75355875 | E47: =(E4+E5+E7+E8+E9+E40)/E44 -> 0.75355875 | F47: =(F4+F5+F7+F8+F9+F40)/F44 -> 0.75355875 | G47: =(G4+G5+G7+G8+G9+G40)/G44 -> 0.75355875 | H47: =(H4+H5+H7+H8+H9+H40)/H44 -> 0.75355875 | I47: =(I4+I5+I7+I8+I9+I40)/I44 -> 0.75355875 | ... K47: =(K4+K5+K7+K8+K9+K40)/K44 -> 0.75355875
A48: % Costo Constante | B48: =(B10+B13+B12+B14)/B44 -> 0.30281851 | C48: =(C10+C13+C12+C14)/C44 -> 0.24568975 | D48: =(D10+D13+D12+D14)/D44 -> 0.24644125 | E48: =(E10+E13+E12+E14)/E44 -> 0.24644125 | F48: =(F10+F13+F12+F14)/F44 -> 0.24644125 | G48: =(G10+G13+G12+G14)/G44 -> 0.24644125 | H48: =(H10+H13+H12+H14)/H44 -> 0.24644125 | I48: =(I10+I13+I12+I14)/I44 -> 0.24644125 | ... K48: =(K10+K13+K12+K14)/K44 -> 0.24644125
B51: Gastos en el Area de Administración
A52: Rubros | B52: Año 1 | C52: Año 2 | D52: Año 3 | E52: Año 4 | F52: Año 5 | G52: Año 6 | H52: Año 7 | I52: Año 8 | J52: Año 9 | K52: Año 10
A53: Personal | B53: =SUM($W$35:$W$37) -> 61655066 | C53: =SUM($W$35:$W$37) -> 61655066 | D53: =SUM($W$35:$W$37) -> 61655066 | E53: =SUM($W$35:$W$37) -> 61655066 | F53: =SUM($W$35:$W$37) -> 61655066 | G53: =SUM($W$35:$W$37) -> 61655066 | H53: =SUM($W$35:$W$37) -> 61655066 | I53: =SUM($W$35:$W$37) -> 61655066 | ... K53: =SUM($W$35:$W$37) -> 61655066
A54: Amortizaciones de A. Fijo | B54: ='DE-Inv AF y Am'!$D$55*0.05 -> 8920570.1 | C54: ='DE-Inv AF y Am'!$D$55*0.05 -> 8920570.1 | D54: ='DE-Inv AF y Am'!$D$55*0.05 -> 8920570.1 | E54: ='DE-Inv AF y Am'!$D$55*0.05 -> 8920570.1 | F54: ='DE-Inv AF y Am'!$D$55*0.05 -> 8920570.1 | G54: ='DE-Inv AF y Am'!$D$55*0.05 -> 8920570.1 | H54: ='DE-Inv AF y Am'!$D$55*0.05 -> 8920570.1 | I54: ='DE-Inv AF y Am'!$D$55*0.05 -> 8920570.1 | ... K54: ='DE-Inv AF y Am'!$D$55*0.05 -> 8920570.1
A55: Materiales | B55: ='DE-Inv AF y Am'!$B$49*0.5 -> 27843204 | C55: ='DE-Inv AF y Am'!$B$49*0.5 -> 27843204 | D55: ='DE-Inv AF y Am'!$B$49*0.5 -> 27843204 | E55: ='DE-Inv AF y Am'!$B$49*0.5 -> 27843204 | F55: ='DE-Inv AF y Am'!$B$49*0.5 -> 27843204 | G55: ='DE-Inv AF y Am'!$B$49*0.5 -> 27843204 | H55: ='DE-Inv AF y Am'!$B$49*0.5 -> 27843204 | I55: ='DE-Inv AF y Am'!$B$49*0.5 -> 27843204 | ... K55: ='DE-Inv AF y Am'!$B$49*0.5 -> 27843204
A56: Electricidad | B56: =$U$28/2 -> 1442080.7 | C56: =$U$28/2 -> 1442080.7 | D56: =$U$28/2 -> 1442080.7 | E56: =$U$28/2 -> 1442080.7 | F56: =$U$28/2 -> 1442080.7 | G56: =$U$28/2 -> 1442080.7 | H56: =$U$28/2 -> 1442080.7 | I56: =$U$28/2 -> 1442080.7 | ... K56: =$U$28/2 -> 1442080.7
A57: Combustible | B57: 0 | C57: 0 | D57: 0 | E57: 0 | F57: 0 | G57: 0 | H57: 0 | I57: 0 | J57: 0 | K57: 0
A58: Varios | B58: 0 | C58: 0 | D58: 0 | E58: 0 | F58: 0 | G58: 0 | H58: 0 | I58: 0 | J58: 0 | K58: 0
A59: Tasas e impuestos | B59: ='Tasas e Impuestos'!$C$12 -> 1740495.9 | C59: ='Tasas e Impuestos'!$C$12 -> 1740495.9 | D59: ='Tasas e Impuestos'!$C$12 -> 1740495.9 | E59: ='Tasas e Impuestos'!$C$12 -> 1740495.9 | F59: ='Tasas e Impuestos'!$C$12 -> 1740495.9 | G59: ='Tasas e Impuestos'!$C$12 -> 1740495.9 | H59: ='Tasas e Impuestos'!$C$12 -> 1740495.9 | I59: ='Tasas e Impuestos'!$C$12 -> 1740495.9 | ... K59: ='Tasas e Impuestos'!$C$12 -> 1740495.9
A60: Seguros | B60: 0 | C60: 0 | D60: 0 | E60: 0 | F60: 0 | G60: 0 | H60: 0 | I60: 0 | J60: 0 | K60: 0
A61: Total acumulado: | B61: =SUM(B53:B60) -> 1.0160142e+08 | C61: =SUM(C53:C60) -> 1.0160142e+08 | D61: =SUM(D53:D60) -> 1.0160142e+08 | E61: =SUM(E53:E60) -> 1.0160142e+08 | F61: =SUM(F53:F60) -> 1.0160142e+08 | G61: =SUM(G53:G60) -> 1.0160142e+08 | H61: =SUM(H53:H60) -> 1.0160142e+08 | I61: =SUM(I53:I60) -> 1.0160142e+08 | ... K61: =SUM(K53:K60) -> 1.0160142e+08
A62: Imprevistos aprox. 2%: | B62: =B61*0.02 -> 2032028.3 | C62: =C61*0.02 -> 2032028.3 | D62: =D61*0.02 -> 2032028.3 | E62: =E61*0.02 -> 2032028.3 | F62: =F61*0.02 -> 2032028.3 | G62: =G61*0.02 -> 2032028.3 | H62: =H61*0.02 -> 2032028.3 | I62: =I61*0.02 -> 2032028.3 | ... K62: =K61*0.02 -> 2032028.3
A64: Costo total de Admistración | B64: =B61+B62 -> 1.0363344e+08 | C64: =C61+C62 -> 1.0363344e+08 | D64: =D61+D62 -> 1.0363344e+08 | E64: =E61+E62 -> 1.0363344e+08 | F64: =F61+F62 -> 1.0363344e+08 | G64: =G61+G62 -> 1.0363344e+08 | H64: =H61+H62 -> 1.0363344e+08 | I64: =I61+I62 -> 1.0363344e+08 | ... K64: =K61+K62 -> 1.0363344e+08
A66: % Costo Variable | B66: =1-B67 -> 0.86360412 | C66: =1-C67 -> 0.86360412 | D66: =1-D67 -> 0.86360412 | E66: =1-E67 -> 0.86360412 | F66: =1-F67 -> 0.86360412 | G66: =1-G67 -> 0.86360412 | H66: =1-H67 -> 0.86360412 | I66: =1-I67 -> 0.86360412 | ... K66: =1-K67 -> 0.86360412
A67: % Costo Constante | B67: =(B56+B57+B58+B59+B60+B62+B54)/B64 -> 0.13639588 | C67: =(C56+C57+C58+C59+C60+C62+C54)/C64 -> 0.13639588 | D67: =(D56+D57+D58+D59+D60+D62+D54)/D64 -> 0.13639588 | E67: =(E56+E57+E58+E59+E60+E62+E54)/E64 -> 0.13639588 | F67: =(F56+F57+F58+F59+F60+F62+F54)/F64 -> 0.13639588 | G67: =(G56+G57+G58+G59+G60+G62+G54)/G64 -> 0.13639588 | H67: =(H56+H57+H58+H59+H60+H62+H54)/H64 -> 0.13639588 | I67: =(I56+I57+I58+I59+I60+I62+I54)/I64 -> 0.13639588 | ... K67: =(K56+K57+K58+K59+K60+K62+K54)/K64 -> 0.13639588
B70: Gastos en el Area de Comercialización
A71: Rubros | B71: Año 1 | C71: Año 2 | D71: Año 3 | E71: Año 4 | F71: Año 5 | G71: Año 6 | H71: Año 7 | I71: Año 8 | J71: Año 9 | K71: Año 10
A72: Personal | B72: =$W$38 -> 17276616 | C72: =$W$38 -> 17276616 | D72: =$W$38 -> 17276616 | E72: =$W$38 -> 17276616 | F72: =$W$38 -> 17276616 | G72: =$W$38 -> 17276616 | H72: =$W$38 -> 17276616 | I72: =$W$38 -> 17276616 | ... K72: =$W$38 -> 17276616
A73: Amortizaciones de A. Fijo | B73: ='DE-Inv AF y Am'!$D$55*0.05 -> 8920570.1 | C73: ='DE-Inv AF y Am'!$D$55*0.05 -> 8920570.1 | D73: ='DE-Inv AF y Am'!$D$55*0.05 -> 8920570.1 | E73: ='DE-Inv AF y Am'!$D$55*0.05 -> 8920570.1 | F73: ='DE-Inv AF y Am'!$D$55*0.05 -> 8920570.1 | G73: ='DE-Inv AF y Am'!$D$55*0.05 -> 8920570.1 | H73: ='DE-Inv AF y Am'!$D$55*0.05 -> 8920570.1 | I73: ='DE-Inv AF y Am'!$D$55*0.05 -> 8920570.1 | ... K73: ='DE-Inv AF y Am'!$D$55*0.05 -> 8920570.1
A74: Materiales | B74: ='DE-Inv AF y Am'!$B$49*0.5 -> 27843204 | C74: ='DE-Inv AF y Am'!$B$49*0.5 -> 27843204 | D74: ='DE-Inv AF y Am'!$B$49*0.5 -> 27843204 | E74: ='DE-Inv AF y Am'!$B$49*0.5 -> 27843204 | F74: ='DE-Inv AF y Am'!$B$49*0.5 -> 27843204 | G74: ='DE-Inv AF y Am'!$B$49*0.5 -> 27843204 | H74: ='DE-Inv AF y Am'!$B$49*0.5 -> 27843204 | I74: ='DE-Inv AF y Am'!$B$49*0.5 -> 27843204 | ... K74: ='DE-Inv AF y Am'!$B$49*0.5 -> 27843204
A75: Energía Eléctrica | B75: =$U$28/2 -> 1442080.7 | C75: =$U$28/2 -> 1442080.7 | D75: =$U$28/2 -> 1442080.7 | E75: =$U$28/2 -> 1442080.7 | F75: =$U$28/2 -> 1442080.7 | G75: =$U$28/2 -> 1442080.7 | H75: =$U$28/2 -> 1442080.7 | I75: =$U$28/2 -> 1442080.7 | ... K75: =$U$28/2 -> 1442080.7
A76: Combustible | B76: 0 | C76: 0 | D76: 0 | E76: 0 | F76: 0 | G76: 0 | H76: 0 | I76: 0 | J76: 0 | K76: 0
A77: Varios | B77: 0 | C77: 0 | D77: 0 | E77: 0 | F77: 0 | G77: 0 | H77: 0 | I77: 0 | J77: 0 | K77: 0
A78: Tasas e impuestos | B78: ='Tasas e Impuestos'!$D$12 -> 1740495.9 | C78: ='Tasas e Impuestos'!$D$12 -> 1740495.9 | D78: ='Tasas e Impuestos'!$D$12 -> 1740495.9 | E78: ='Tasas e Impuestos'!$D$12 -> 1740495.9 | F78: ='Tasas e Impuestos'!$D$12 -> 1740495.9 | G78: ='Tasas e Impuestos'!$D$12 -> 1740495.9 | H78: ='Tasas e Impuestos'!$D$12 -> 1740495.9 | I78: ='Tasas e Impuestos'!$D$12 -> 1740495.9 | ... K78: ='Tasas e Impuestos'!$D$12 -> 1740495.9
A79: Seguros | B79: 0 | C79: 0 | D79: 0 | E79: 0 | F79: 0 | G79: 0 | H79: 0 | I79: 0 | J79: 0 | K79: 0
A80: Total acumulado: | B80: =SUM(B72:B79) -> 57222966 | C80: =SUM(C72:C79) -> 57222966 | D80: =SUM(D72:D79) -> 57222966 | E80: =SUM(E72:E79) -> 57222966 | F80: =SUM(F72:F79) -> 57222966 | G80: =SUM(G72:G79) -> 57222966 | H80: =SUM(H72:H79) -> 57222966 | I80: =SUM(I72:I79) -> 57222966 | ... K80: =SUM(K72:K79) -> 57222966
A81: Imprevistos aprox. 2%: | B81: =B80*0.02 -> 1144459.3 | C81: =C80*0.02 -> 1144459.3 | D81: =D80*0.02 -> 1144459.3 | E81: =E80*0.02 -> 1144459.3 | F81: =F80*0.02 -> 1144459.3 | G81: =G80*0.02 -> 1144459.3 | H81: =H80*0.02 -> 1144459.3 | I81: =I80*0.02 -> 1144459.3 | ... K81: =K80*0.02 -> 1144459.3
A83: Costo total de Comercialización | B83: =B80+B81 -> 58367425 | C83: =C80+C81 -> 58367425 | D83: =D80+D81 -> 58367425 | E83: =E80+E81 -> 58367425 | F83: =F80+F81 -> 58367425 | G83: =G80+G81 -> 58367425 | H83: =H80+H81 -> 58367425 | I83: =I80+I81 -> 58367425 | ... K83: =K80+K81 -> 58367425
A85: % Costo Variable | B85: =(B72+B74)/B83 -> 0.77303083 | C85: =(C72+C74)/C83 -> 0.77303083 | D85: =(D72+D74)/D83 -> 0.77303083 | E85: =(E72+E74)/E83 -> 0.77303083 | F85: =(F72+F74)/F83 -> 0.77303083 | G85: =(G72+G74)/G83 -> 0.77303083 | H85: =(H72+H74)/H83 -> 0.77303083 | I85: =(I72+I74)/I83 -> 0.77303083 | ... K85: =(K72+K74)/K83 -> 0.77303083
A86: % Costo Constante | B86: =1-B85 -> 0.22696917 | C86: =1-C85 -> 0.22696917 | D86: =1-D85 -> 0.22696917 | E86: =1-E85 -> 0.22696917 | F86: =1-F85 -> 0.22696917 | G86: =1-G85 -> 0.22696917 | H86: =1-H85 -> 0.22696917 | I86: =1-I85 -> 0.22696917 | ... K86: =1-K85 -> 0.22696917
A89: COSTO TOTAL Y RESULTADO A NIVEL ECONOMICO
B90: Año 1 | C90: Año 2 | D90: Año 3 | E90: Año 4 | F90: Año 5 | G90: Año 6 | H90: Año 7 | I90: Año 8 | J90: Año 9 | K90: Año 10
A91: Venta anual, en toneladas Producto 1 | B91: ='Ejercicio 11'!D3 -> 3375 | C91: ='Ejercicio 11'!$E$3 -> 5000 | D91: ='Ejercicio 11'!$E$3 -> 5000 | E91: ='Ejercicio 11'!$E$3 -> 5000 | F91: ='Ejercicio 11'!$E$3 -> 5000 | G91: ='Ejercicio 11'!$E$3 -> 5000 | H91: ='Ejercicio 11'!$E$3 -> 5000 | I91: ='Ejercicio 11'!$E$3 -> 5000 | J91: ='Ejercicio 11'!$E$3 -> 5000 | K91: ='Ejercicio 11'!$E$3 -> 5000
A92: Precio de venta Producto 1 | B92: =InfoInicial!$B$18*InfoInicial!$B$30 -> 585000 | C92: =InfoInicial!$B$18*InfoInicial!$B$30 -> 585000 | D92: =InfoInicial!$B$18*InfoInicial!$B$30 -> 585000 | E92: =InfoInicial!$B$18*InfoInicial!$B$30 -> 585000 | F92: =InfoInicial!$B$18*InfoInicial!$B$30 -> 585000 | G92: =InfoInicial!$B$18*InfoInicial!$B$30 -> 585000 | H92: =InfoInicial!$B$18*InfoInicial!$B$30 -> 585000 | I92: =InfoInicial!$B$18*InfoInicial!$B$30 -> 585000 | ... K92: =InfoInicial!$B$18*InfoInicial!$B$30 -> 585000
A94: VENTAS ANUALES | B94: =B91*InfoInicial!$B$18*InfoInicial!$B$30 -> 1974375000 | C94: =C91*InfoInicial!$B$18*InfoInicial!$B$30 -> 2925000000 | D94: =D91*InfoInicial!$B$18*InfoInicial!$B$30 -> 2925000000 | E94: =E91*InfoInicial!$B$18*InfoInicial!$B$30 -> 2925000000 | F94: =F91*InfoInicial!$B$18*InfoInicial!$B$30 -> 2925000000 | G94: =G91*InfoInicial!$B$18*InfoInicial!$B$30 -> 2925000000 | H94: =H91*InfoInicial!$B$18*InfoInicial!$B$30 -> 2925000000 | I94: =I91*InfoInicial!$B$18*InfoInicial!$B$30 -> 2925000000 | ... K94: =K91*InfoInicial!$B$18*InfoInicial!$B$30 -> 2925000000
A96: Consumo de materia prima | B96: =B4 -> 4.7596275e+08 | C96: =C4 -> 6.40615e+08 | D96: =D4 -> 6.40615e+08 | E96: =E4 -> 6.40615e+08 | F96: =F4 -> 6.40615e+08 | G96: =G4 -> 6.40615e+08 | H96: =H4 -> 6.40615e+08 | I96: =I4 -> 6.40615e+08 | ... K96: =K4 -> 6.40615e+08
A97: Mano de obra directa | B97: =B5 -> 29610097 | C97: =C5 -> 29610097 | D97: =D5 -> 29610097 | E97: =E5 -> 29610097 | F97: =F5 -> 29610097 | G97: =G5 -> 29610097 | H97: =H5 -> 29610097 | I97: =I5 -> 29610097 | ... K97: =K5 -> 29610097
A98: Gastos de fabricación | B98: =SUM(B7:B14) -> 5.0981245e+08 | C98: =SUM(C7:C14) -> 5.1778299e+08 | D98: =SUM(D7:D14) -> 5.1778299e+08 | E98: =SUM(E7:E14) -> 5.1778299e+08 | F98: =SUM(F7:F14) -> 5.1778299e+08 | G98: =SUM(G7:G14) -> 5.1778299e+08 | H98: =SUM(H7:H14) -> 5.1778299e+08 | I98: =SUM(I7:I14) -> 5.1778299e+08 | ... K98: =SUM(K7:K14) -> 5.1778299e+08
A100: Gastos de Producción | B100: =B15 -> 1.0153853e+09 | C100: =C15 -> 1.1880081e+09 | D100: =D15 -> 1.1880081e+09 | E100: =E15 -> 1.1880081e+09 | F100: =F15 -> 1.1880081e+09 | G100: =G15 -> 1.1880081e+09 | H100: =H15 -> 1.1880081e+09 | I100: =I15 -> 1.1880081e+09 | ... K100: =K15 -> 1.1880081e+09
A102: Menos:
A103: Puesta en marcha | B103: =B40 -> 9936750.2 | C103: 0 | D103: 0 | E103: 0 | F103: 0 | G103: 0 | H103: 0 | I103: 0 | J103: 0 | K103: 0
A104: Variación Mercadería en proceso | B104: =B43 -> 56783183 | C104: =C43 -> -3633797.6 | D104: =D43 -> 0 | E104: =E43 -> 0 | F104: =F43 -> 0 | G104: =G43 -> 0 | H104: =H43 -> 0 | I104: =I43 -> 0 | ... K104: =K43 -> 0
A106: COSTO DE PRODUCCION ANUAL | B106: =B44 -> 9.4866537e+08 | C106: =C44 -> 1.1916419e+09 | D106: =D44 -> 1.1880081e+09 | E106: =E44 -> 1.1880081e+09 | F106: =F44 -> 1.1880081e+09 | G106: =G44 -> 1.1880081e+09 | H106: =H44 -> 1.1880081e+09 | I106: =I44 -> 1.1880081e+09 | ... K106: =K44 -> 1.1880081e+09
A107: Producción anual en Unidades (Tn) | B107: ='Ejercicio 11'!$D$5 -> 4000 | C107: ='Ejercicio 11'!$E$5 -> 5000 | D107: ='Ejercicio 11'!$E$5 -> 5000 | E107: ='Ejercicio 11'!$E$5 -> 5000 | F107: ='Ejercicio 11'!$E$5 -> 5000 | G107: ='Ejercicio 11'!$E$5 -> 5000 | H107: ='Ejercicio 11'!$E$5 -> 5000 | I107: ='Ejercicio 11'!$E$5 -> 5000 | J107: ='Ejercicio 11'!$E$5 -> 5000 | K107: ='Ejercicio 11'!$E$5 -> 5000
A108: Costo de producción unitario Promedio | B108: =B106/'Ejercicio 11'!$D$5 -> 237166.34 | C108: =C106/'Ejercicio 11'!$E$5 -> 238328.38 | D108: =D106/'Ejercicio 11'!$E$5 -> 237601.62 | E108: =E106/'Ejercicio 11'!$E$5 -> 237601.62 | F108: =F106/'Ejercicio 11'!$E$5 -> 237601.62 | G108: =G106/'Ejercicio 11'!$E$5 -> 237601.62 | H108: =H106/'Ejercicio 11'!$E$5 -> 237601.62 | I108: =I106/'Ejercicio 11'!$E$5 -> 237601.62 | J108: =J106/'Ejercicio 11'!$E$5 -> 237601.62 | K108: =K106/'Ejercicio 11'!$E$5 -> 237601.62
A110: Menos:
A111: Variación de Stock de Elaborado | B111: =B108*'Ejercicio 11'!D4 -> 1.4822896e+08 | C111: =(C108*'Ejercicio 11'!E4)-B111 -> 726272.55 | D111: =D108*'Ejercicio 11'!E4-C108*'Ejercicio 11'!E4 -> -454224.69 | E111: =E108*'Ejercicio 11'!E4-D108*'Ejercicio 11'!E4 -> 0 | F111: =F108*'Ejercicio 11'!F4-E108*'Ejercicio 11'!F4 -> 0 | G111: =G108*'Ejercicio 11'!G4-F108*'Ejercicio 11'!G4 -> 0 | H111: =H108*'Ejercicio 11'!H4-G108*'Ejercicio 11'!H4 -> 0 | I111: =I108*'Ejercicio 11'!I4-H108*'Ejercicio 11'!I4 -> 0 | J111: =J108*'Ejercicio 11'!J4-I108*'Ejercicio 11'!J4 -> 0 | K111: =K108*'Ejercicio 11'!K4-J108*'Ejercicio 11'!K4 -> 0
A113: COSTO DE PRODUCCION DE LO VENDIDO | B113: =B106-B111 -> 8.004364e+08 | C113: =C106-C111 -> 1.1909156e+09 | D113: =D106-D111 -> 1.1884623e+09 | E113: =E106-E111 -> 1.1880081e+09 | F113: =F106-F111 -> 1.1880081e+09 | G113: =G106-G111 -> 1.1880081e+09 | H113: =H106-H111 -> 1.1880081e+09 | I113: =I106-I111 -> 1.1880081e+09 | ... K113: =K106-K111 -> 1.1880081e+09
A115: GASTO DE ADMINISTRACION | B115: =B64 -> 1.0363344e+08 | C115: =C64 -> 1.0363344e+08 | D115: =D64 -> 1.0363344e+08 | E115: =E64 -> 1.0363344e+08 | F115: =F64 -> 1.0363344e+08 | G115: =G64 -> 1.0363344e+08 | H115: =H64 -> 1.0363344e+08 | I115: =I64 -> 1.0363344e+08 | ... K115: =K64 -> 1.0363344e+08
A116: GASTO DE COMERCIALIZACION | B116: =B83 -> 58367425 | C116: =C83 -> 58367425 | D116: =D83 -> 58367425 | E116: =E83 -> 58367425 | F116: =F83 -> 58367425 | G116: =G83 -> 58367425 | H116: =H83 -> 58367425 | I116: =I83 -> 58367425 | ... K116: =K83 -> 58367425
A118: COSTO ANUAL DE LO VENDIDO | B118: =B113+B115+B116 -> 9.6243727e+08 | C118: =C113+C115+C116 -> 1.3529165e+09 | D118: =D113+D115+D116 -> 1.3504632e+09 | E118: =E113+E115+E116 -> 1.350009e+09 | F118: =F113+F115+F116 -> 1.350009e+09 | G118: =G113+G115+G116 -> 1.350009e+09 | H118: =H113+H115+H116 -> 1.350009e+09 | I118: =I113+I115+I116 -> 1.350009e+09 | ... K118: =K113+K115+K116 -> 1.350009e+09
A120: Costo total unitario promedio | B120: =B118/B107 -> 240609.32 | C120: =C118/C107 -> 270583.3 | D120: =D118/D107 -> 270092.64 | E120: =E118/E107 -> 270001.79 | F120: =F118/F107 -> 270001.79 | G120: =G118/G107 -> 270001.79 | H120: =H118/H107 -> 270001.79 | I120: =I118/I107 -> 270001.79 | ... K120: =K118/K107 -> 270001.79
A122: UTILIDAD ECONOMICA (a/H. D. e Impuesto) | B122: =B94-B118 -> 1.0119377e+09 | C122: =C94-C118 -> 1.5720835e+09 | D122: =D94-D118 -> 1.5745368e+09 | E122: =E94-E118 -> 1.574991e+09 | F122: =F94-F118 -> 1.574991e+09 | G122: =G94-G118 -> 1.574991e+09 | H122: =H94-H118 -> 1.574991e+09 | I122: =I94-I118 -> 1.574991e+09 | ... K122: =K94-K118 -> 1.574991e+09
...

Sheet DE-InvAT
A1: INVERSIONES EN ACTIVO DE TRABAJO
A2: Rubros | B2: Año 0 | C2: Año 1 | D2: Año 2 | E2: Año 3 | F2: Año 4 | G2: Año 5 | H2: Año 6 | I2: Año 7 | J2: Año 8 | K2: Año 9 | L2: Año 10
A3: 1. Activo de Trabajo: (valor contable) | B3: =B4+B5 -> 39487500 | C3: =C4+C5 -> 2.207774e+08 | D3: =D4+D5 -> 2.9891096e+08 | E3: =E4+E5 -> 2.9891096e+08 | F3: =F4+F5 -> 2.9891096e+08 | G3: =G4+G5 -> 2.9891096e+08 | H3: =H4+H5 -> 2.9891096e+08 | I3: =I4+I5 -> 2.9891096e+08 | ... L3: =L4+L5 -> 2.9891096e+08
A4: a) Disponibilidad Mínima en Caja y Bancos: | B4: ='DE-Costos'!B94*0.02 -> 39487500 | C4: ='DE-Costos'!$C$94*0.02 -> 58500000 | D4: ='DE-Costos'!$C$94*0.02 -> 58500000 | E4: ='DE-Costos'!$C$94*0.02 -> 58500000 | F4: ='DE-Costos'!$C$94*0.02 -> 58500000 | G4: ='DE-Costos'!$C$94*0.02 -> 58500000 | H4: ='DE-Costos'!$C$94*0.02 -> 58500000 | I4: ='DE-Costos'!$C$94*0.02 -> 58500000 | J4: ='DE-Costos'!$C$94*0.02 -> 58500000 | ... L4: ='DE-Costos'!$C$94*0.02 -> 58500000
A5: b) Crédito por Ventas | B5: 0 | C5: ='DE-Costos'!B94*(30/365) -> 1.622774e+08 | D5: ='DE-Costos'!C94*(30/365) -> 2.4041096e+08 | E5: ='DE-Costos'!D94*(30/365) -> 2.4041096e+08 | F5: ='DE-Costos'!E94*(30/365) -> 2.4041096e+08 | G5: ='DE-Costos'!F94*(30/365) -> 2.4041096e+08 | H5: ='DE-Costos'!G94*(30/365) -> 2.4041096e+08 | I5: ='DE-Costos'!H94*(30/365) -> 2.4041096e+08 | J5: ='DE-Costos'!I94*(30/365) -> 2.4041096e+08 | ... L5: ='DE-Costos'!K94*(30/365) -> 2.4041096e+08 | M5: El plazo promedio de financiación a clientes es de 30 días
A7: c) Bienes de cambio: | B7: =SUM(B8:B11) -> 1.9773552e+08 | C7: =SUM(C8:C11) -> 6.9635951e+08 | D7: =SUM(D8:D11) -> 8.4108052e+08 | E7: =SUM(E8:E11) -> 8.406263e+08 | F7: =SUM(F8:F11) -> 8.406263e+08 | G7: =SUM(G8:G11) -> 8.406263e+08 | H7: =SUM(H8:H11) -> 8.406263e+08 | I7: =SUM(I8:I11) -> 8.406263e+08 | ... L7: =SUM(L8:L11) -> 8.406263e+08
A8: Stock de materias prima: | B8: ='Materia Prima'!D14 -> 1.5583219e+08 | C8: ='Materia Prima'!C10 -> 4.3547625e+08 | D8: ='Materia Prima'!$C$11 -> 5.80635e+08 | E8: ='Materia Prima'!$C$11 -> 5.80635e+08 | F8: ='Materia Prima'!$C$11 -> 5.80635e+08 | G8: ='Materia Prima'!$C$11 -> 5.80635e+08 | H8: ='Materia Prima'!$C$11 -> 5.80635e+08 | I8: ='Materia Prima'!$C$11 -> 5.80635e+08 | J8: ='Materia Prima'!$C$11 -> 5.80635e+08 | K8: ='Materia Prima'!$C$11 -> 5.80635e+08 | L8: ='Materia Prima'!$C$11 -> 5.80635e+08
A9: Stock de materiales: | B9: =9/12*C9 -> 41903337 | C9: ='DE-Costos'!B9+'DE-Costos'!B54+'DE-Costos'!B73 -> 55871115 | D9: ='DE-Costos'!C9+'DE-Costos'!C54+'DE-Costos'!C73 -> 58340899 | E9: ='DE-Costos'!D9+'DE-Costos'!D54+'DE-Costos'!D73 -> 58340899 | F9: ='DE-Costos'!E9+'DE-Costos'!E54+'DE-Costos'!E73 -> 58340899 | G9: ='DE-Costos'!F9+'DE-Costos'!F54+'DE-Costos'!F73 -> 58340899 | H9: ='DE-Costos'!G9+'DE-Costos'!G54+'DE-Costos'!G73 -> 58340899 | I9: ='DE-Costos'!H9+'DE-Costos'!H54+'DE-Costos'!H73 -> 58340899 | J9: ='DE-Costos'!I9+'DE-Costos'!I54+'DE-Costos'!I73 -> 58340899 | ... L9: ='DE-Costos'!K9+'DE-Costos'!K54+'DE-Costos'!K73 -> 58340899
A10: Mercadería en curso y semielaborada | B10: 0 | C10: ='DE-Costos'!B34 -> 56783183 | D10: ='DE-Costos'!C34 -> 53149385 | E10: ='DE-Costos'!D34 -> 53149385 | F10: ='DE-Costos'!E34 -> 53149385 | G10: ='DE-Costos'!F34 -> 53149385 | H10: ='DE-Costos'!G34 -> 53149385 | I10: ='DE-Costos'!H34 -> 53149385 | J10: ='DE-Costos'!I34 -> 53149385 | ... L10: ='DE-Costos'!K34 -> 53149385
A11: Stock de elaborados | B11: 0 | C11: =B11+'DE-Costos'!B111 -> 1.4822896e+08 | D11: =C11+'DE-Costos'!C111 -> 1.4895524e+08 | E11: =D11+'DE-Costos'!D111 -> 1.4850101e+08 | F11: =E11+'DE-Costos'!E111 -> 1.4850101e+08 | G11: =F11+'DE-Costos'!F111 -> 1.4850101e+08 | H11: =G11+'DE-Costos'!G111 -> 1.4850101e+08 | I11: =H11+'DE-Costos'!H111 -> 1.4850101e+08 | J11: =I11+'DE-Costos'!I111 -> 1.4850101e+08 | ... L11: =K11+'DE-Costos'!K111 -> 1.4850101e+08
A13: d) Total Activo de Trabajo, sin IVA: | B13: =B3+B7 -> 2.3722302e+08 | C13: =C3+C7 -> 9.1713691e+08 | D13: =D3+D7 -> 1.1399915e+09 | E13: =E3+E7 -> 1.1395373e+09 | F13: =F3+F7 -> 1.1395373e+09 | G13: =G3+G7 -> 1.1395373e+09 | H13: =H3+H7 -> 1.1395373e+09 | I13: =I3+I7 -> 1.1395373e+09 | ... L13: =L3+L7 -> 1.1395373e+09
A14: 2. Menos:
A15: Amortizaciones en Mercadería en proceso | B15: 0 | C15: ='DE-Costos'!B26 -> 8979537.7 | D15: ='DE-Costos'!C26 -> 7183630.2 | E15: ='DE-Costos'!D26 -> 7183630.2 | F15: ='DE-Costos'!E26 -> 7183630.2 | G15: ='DE-Costos'!F26 -> 7183630.2 | H15: ='DE-Costos'!G26 -> 7183630.2 | I15: ='DE-Costos'!H26 -> 7183630.2 | J15: ='DE-Costos'!I26 -> 7183630.2 | ... L15: ='DE-Costos'!K26 -> 7183630.2
A16: Amortizaciones en Stock de elaborado | B16: 0 | C16: =('DE-Costos'!B7-'DE-Costos'!B26)/'Ejercicio 11'!$D$5*'Ejercicio 11'!$D4 -> 23686051 | D16: =('DE-Costos'!C7-'DE-Costos'!C26)/'Ejercicio 11'!$E$5*'Ejercicio 11'!$E$4 -> 19173329 | E16: =('DE-Costos'!D7-'DE-Costos'!D26)/'Ejercicio 11'!$E$5*'Ejercicio 11'!$E$4 -> 19173329 | F16: =('DE-Costos'!E7-'DE-Costos'!E26)/'Ejercicio 11'!$E$5*'Ejercicio 11'!$E$4 -> 19173329 | G16: =('DE-Costos'!F7-'DE-Costos'!F26)/'Ejercicio 11'!$E$5*'Ejercicio 11'!$E$4 -> 19173329 | H16: =('DE-Costos'!G7-'DE-Costos'!G26)/'Ejercicio 11'!$E$5*'Ejercicio 11'!$E$4 -> 19173329 | I16: =('DE-Costos'!H7-'DE-Costos'!H26)/'Ejercicio 11'!$E$5*'Ejercicio 11'!$E$4 -> 19173329 | J16: =('DE-Costos'!I7-'DE-Costos'!I26)/'Ejercicio 11'!$E$5*'Ejercicio 11'!$E$4 -> 19173329 | K16: =('DE-Costos'!J7-'DE-Costos'!J26)/'Ejercicio 11'!$E$5*'Ejercicio 11'!$E$4 -> 19173329 | L16: =('DE-Costos'!K7-'DE-Costos'!K26)/'Ejercicio 11'!$E$5*'Ejercicio 11'!$E$4 -> 19173329
A17: Utilidades en Crédito por ventas | B17: 0 | C17: =C5*'DE-Costos'!B127 -> 54062427 | D17: =D5*'DE-Costos'!C127 -> 83988023 | E17: =E5*'DE-Costos'!D127 -> 84119090 | F17: =F5*'DE-Costos'!E127 -> 84143357 | G17: =G5*'DE-Costos'!F127 -> 84143357 | H17: =H5*'DE-Costos'!G127 -> 84143357 | I17: =I5*'DE-Costos'!H127 -> 84143357 | J17: =J5*'DE-Costos'!I127 -> 84143357 | ... L17: =L5*'DE-Costos'!K127 -> 84143357
A18: Amortizaciones en Crédito por ventas | B18: 0 | C18: =('DE-Inv AF y Am'!D55-C15-C16)/365/30 -> 13310.12 | D18: =C18 -> 13310.12 | E18: =D18 -> 13310.12 | F18: =('DE-Inv AF y Am'!E55-D15-D16)/365/30 -> 13886.251 | G18: =F18 -> 13886.251 | H18: =('DE-Inv AF y Am'!F55-E15-E16)/365/30 -> -1623.3524 | I18: =H18 -> -1623.3524 | J18: =I18 -> -1623.3524 | K18: =J18 -> -1623.3524 | L18: =K18 -> -1623.3524
A20: 3. Inversiones en Activo de Trabajo, sin IVA | B20: =B13-SUM(B15:B18) -> 2.3722302e+08 | C20: =C13-SUM(C15:C18) -> 8.3039558e+08 | D20: =D13-SUM(D15:D18) -> 1.0296332e+09 | E20: =E13-SUM(E15:E18) -> 1.0290479e+09 | F20: =F13-SUM(F15:F18) -> 1.0290231e+09 | G20: =G13-SUM(G15:G18) -> 1.0290231e+09 | H20: =H13-SUM(H15:H18) -> 1.0290386e+09 | I20: =I13-SUM(I15:I18) -> 1.0290386e+09 | ... L20: =L13-SUM(L15:L18) -> 1.0290386e+09 | M20: ='DE-Cal Inv.'!N16 -> 1.0290386e+09
A22: 4. Incrementos de Activo de Trabajo | B22: =B13 -> 2.3722302e+08 | C22: =C13-B13 -> 6.7991389e+08 | D22: =D13-C13 -> 2.2285457e+08 | E22: =E13-D13 -> -454224.69 | F22: =F13-E13 -> 0 | G22: =G13-F13 -> 0 | H22: =H13-G13 -> 0 | I22: =I13-H13 -> 0 | J22: =J13-I13 -> 0 | ... L22: =L13-K13 -> 0
A23: Incrementos de Inversión en Activo de Trabajo | B23: =B20 -> 2.3722302e+08 | C23: =C20-B20 -> 5.9317256e+08 | D23: =D20-C20 -> 1.992376e+08 | E23: =E20-D20 -> -585291.42 | F23: =F20-E20 -> -24842.929 | G23: =G20-F20 -> 0 | H23: =H20-G20 -> 15509.603 | I23: =I20-H20 -> 0 | J23: =J20-I20 -> 0 | ... L23: =L20-K20 -> 0
A25: 5. Incrementos IVA sobre Inversiones
A26: Crédito por Ventas | B26: =B5*0.21 -> 0 | C26: =C5*0.21 -> 34078253 | D26: =D5*0.21 -> 50486301 | E26: =E5*0.21 -> 50486301 | F26: =F5*0.21 -> 50486301 | G26: =G5*0.21 -> 50486301 | H26: =H5*0.21 -> 50486301 | I26: =I5*0.21 -> 50486301 | ... L26: =L5*0.21 -> 50486301
A27: Bienes de cambio:
A28: Stock de materia prima | B28: =B8*0.21 -> 32724759 | C28: =C8*0.21 -> 91450013 | D28: =D8*0.21 -> 1.2193335e+08 | E28: =E8*0.21 -> 1.2193335e+08 | F28: =F8*0.21 -> 1.2193335e+08 | G28: =G8*0.21 -> 1.2193335e+08 | H28: =H8*0.21 -> 1.2193335e+08 | I28: =I8*0.21 -> 1.2193335e+08 | ... L28: =L8*0.21 -> 1.2193335e+08
A29: Stock de materiales | B29: =B9*0.21 -> 8799700.7 | C29: =C9*0.21 -> 11732934 | D29: =D9*0.21 -> 12251589 | E29: =E9*0.21 -> 12251589 | F29: =F9*0.21 -> 12251589 | G29: =G9*0.21 -> 12251589 | H29: =H9*0.21 -> 12251589 | I29: =I9*0.21 -> 12251589 | ... L29: =L9*0.21 -> 12251589
A30: Mercadería en proceso | B30: =B10*0.21 -> 0 | C30: =C10*0.21 -> 11924468 | D30: =D10*0.21 -> 11161371 | E30: =E10*0.21 -> 11161371 | F30: =F10*0.21 -> 11161371 | G30: =G10*0.21 -> 11161371 | H30: =H10*0.21 -> 11161371 | I30: =I10*0.21 -> 11161371 | ... L30: =L10*0.21 -> 11161371
A31: Stock de elaborados | B31: =B11*0.21 -> 0 | C31: =C11*0.21 -> 31128082 | D31: =D11*0.21 -> 31280600 | E31: =E11*0.21 -> 31185212 | F31: =F11*0.21 -> 31185212 | G31: =G11*0.21 -> 31185212 | H31: =H11*0.21 -> 31185212 | I31: =I11*0.21 -> 31185212 | ... L31: =L11*0.21 -> 31185212
A32: Total incrementos IVA sobre inversiones | B32: =SUM(B26:B31) -> 41524460 | C32: =SUM(C26:C31) -> 1.8031375e+08 | D32: =SUM(D26:D31) -> 2.2711321e+08 | E32: =SUM(E26:E31) -> 2.2701782e+08 | F32: =SUM(F26:F31) -> 2.2701782e+08 | G32: =SUM(G26:G31) -> 2.2701782e+08 | H32: =SUM(H26:H31) -> 2.2701782e+08 | I32: =SUM(I26:I31) -> 2.2701782e+08 | ... L32: =SUM(L26:L31) -> 2.2701782e+08
A34: 6. Incrementos Inversiones en Activo de Trabajo | B34: =B23+B32 -> 2.7874748e+08 | C34: =C23+C32 -> 7.7348631e+08 | D34: =D23+D32 -> 4.2635081e+08 | E34: =E23+E32 -> 2.2643253e+08 | F34: =F23+F32 -> 2.2699298e+08 | G34: =G23+G32 -> 2.2701782e+08 | H34: =H23+H32 -> 2.2703333e+08 | I34: =I23+I32 -> 2.2701782e+08 | ... L34: =L23+L32 -> 2.2701782e+08

Sheet DE-Cal Inv.
A1: Calendario de Inversiones
A2: Rubros | B2: Año 0: Preinversion | C2: Año 0: Instalación | D2: Año 1 | E2: Año 2 | F2: Año 3 | G2: Año 4 | H2: Año 5 | I2: Año 6 | J2: Año 7 | K2: Año 8 | L2: Año 9 | M2: Año 10 | N2: Totales
A3: Inversiones en Activo Fijo
A4: Bienes de uso | B4: 0 | C4: ='DE-Inv AF y Am'!B20 -> 2.8400068e+09 | D4: 0 | E4: 0 | F4: 0 | G4: 0 | H4: 0 | I4: 0 | J4: 0 | K4: 0 | L4: 0 | M4: 0 | N4: =SUM(B4:M4) -> 2.8400068e+09
A5: Asimilables | B5: ='DE-Inv AF y Am'!B31 -> 19505460 | D5: ='DE-Inv AF y Am'!C31 -> 9335324.3 | E5: 0 | F5: 0 | G5: 0 | H5: 0 | I5: 0 | J5: 0 | K5: 0 | L5: 0 | M5: 0 | N5: =SUM(B5:M5) -> 28840784
A6: Subtotal Activo Fijo | B6: =SUM(B4:B5) -> 19505460 | C6: =SUM(C4:C5) -> 2.8400068e+09 | D6: =SUM(D4:D5) -> 9335324.3 | E6: =SUM(E4:E5) -> 0 | F6: =SUM(F4:F5) -> 0 | G6: =SUM(G4:G5) -> 0 | H6: =SUM(H4:H5) -> 0 | I6: =SUM(I4:I5) -> 0 | ... M6: =SUM(M4:M5) -> 0 | N6: =SUM(B6:M6) -> 2.8688476e+09
A8: Inversiones en A. de Trabajo
A9: Disp. mínimas C y B | B9: 0 | C9: ='DE-InvAT'!B4 -> 39487500 | D9: ='DE-InvAT'!C4-'DE-InvAT'!B4 -> 19012500 | E9: ='DE-InvAT'!D4-'DE-InvAT'!C4 -> 0 | F9: ='DE-InvAT'!E4-'DE-InvAT'!D4 -> 0 | G9: ='DE-InvAT'!F4-'DE-InvAT'!E4 -> 0 | H9: ='DE-InvAT'!G4-'DE-InvAT'!F4 -> 0 | I9: ='DE-InvAT'!H4-'DE-InvAT'!G4 -> 0 | J9: ='DE-InvAT'!I4-'DE-InvAT'!H4 -> 0 | K9: ='DE-InvAT'!J4-'DE-InvAT'!I4 -> 0 | ... M9: ='DE-InvAT'!L4-'DE-InvAT'!K4 -> 0 | N9: =SUM(B9:M9) -> 58500000
A10: Crédito por ventas | B10: 0 | C10: ='DE-InvAT'!B5-'DE-InvAT'!B17-'DE-InvAT'!B18 -> 0 | D10: ='DE-InvAT'!C5-'DE-InvAT'!B5-'DE-InvAT'!C17-'DE-InvAT'!C18-C10 -> 1.0820166e+08 | E10: =('DE-InvAT'!D5-'DE-InvAT'!D17-'DE-InvAT'!D18)-('DE-InvAT'!C5-'DE-InvAT'!C17-'DE-InvAT'!C18) -> 48207965 | F10: =('DE-InvAT'!E5-'DE-InvAT'!E17-'DE-InvAT'!E18)-('DE-InvAT'!D5-'DE-InvAT'!D17-'DE-InvAT'!D18) -> -131066.73 | G10: =('DE-InvAT'!F5-'DE-InvAT'!F17-'DE-InvAT'!F18)-('DE-InvAT'!E5-'DE-InvAT'!E17-'DE-InvAT'!E18) -> -24842.929 | H10: =('DE-InvAT'!G5-'DE-InvAT'!G17-'DE-InvAT'!G18)-('DE-InvAT'!F5-'DE-InvAT'!F17-'DE-InvAT'!F18) -> 0 | I10: =('DE-InvAT'!H5-'DE-InvAT'!H17-'DE-InvAT'!H18)-('DE-InvAT'!G5-'DE-InvAT'!G17-'DE-InvAT'!G18) -> 15509.603 | J10: =('DE-InvAT'!I5-'DE-InvAT'!I17-'DE-InvAT'!I18)-('DE-InvAT'!H5-'DE-InvAT'!H17-'DE-InvAT'!H18) -> 0 | K10: =('DE-InvAT'!J5-'DE-InvAT'!J17-'DE-InvAT'!J18)-('DE-InvAT'!I5-'DE-InvAT'!I17-'DE-InvAT'!I18) -> 0 | L10: =('DE-InvAT'!K5-'DE-InvAT'!K17-'DE-InvAT'!K18)-('DE-InvAT'!J5-'DE-InvAT'!J17-'DE-InvAT'!J18) -> 0 | M10: =('DE-InvAT'!L5-'DE-InvAT'!L17-'DE-InvAT'!L18)-('DE-InvAT'!K5-'DE-InvAT'!K17-'DE-InvAT'!K18) -> 0 | N10: =SUM(B10:M10) -> 1.5626923e+08
A11: Bienes de cambio: | B11: 0
A12: Stock de Materia Prima | B12: 0 | C12: ='DE-InvAT'!B8 -> 1.5583219e+08 | D12: ='DE-InvAT'!C8-'DE-InvAT'!B8 -> 2.7964406e+08 | E12: ='DE-InvAT'!D8-'DE-InvAT'!C8 -> 145158750 | F12: ='DE-InvAT'!E8-'DE-InvAT'!D8 -> 0 | G12: ='DE-InvAT'!F8-'DE-InvAT'!E8 -> 0 | H12: ='DE-InvAT'!G8-'DE-InvAT'!F8 -> 0 | I12: ='DE-InvAT'!H8-'DE-InvAT'!G8 -> 0 | J12: ='DE-InvAT'!I8-'DE-InvAT'!H8 -> 0 | K12: ='DE-InvAT'!J8-'DE-InvAT'!I8 -> 0 | ... M12: ='DE-InvAT'!L8-'DE-InvAT'!K8 -> 0 | N12: =SUM(B12:M12) -> 5.80635e+08
A13: Stock de Materiales | B13: 0 | C13: ='DE-InvAT'!B9 -> 41903337 | D13: ='DE-InvAT'!C9-'DE-InvAT'!B9 -> 13967779 | E13: ='DE-InvAT'!D9-'DE-InvAT'!C9 -> 2469783.8 | F13: ='DE-InvAT'!E9-'DE-InvAT'!D9 -> 0 | G13: ='DE-InvAT'!F9-'DE-InvAT'!E9 -> 0 | H13: ='DE-InvAT'!G9-'DE-InvAT'!F9 -> 0 | I13: ='DE-InvAT'!H9-'DE-InvAT'!G9 -> 0 | J13: ='DE-InvAT'!I9-'DE-InvAT'!H9 -> 0 | K13: ='DE-InvAT'!J9-'DE-InvAT'!I9 -> 0 | ... M13: ='DE-InvAT'!L9-'DE-InvAT'!K9 -> 0 | N13: =SUM(B13:M13) -> 58340899
A14: Mercadería en proceso | B14: 0 | C14: 0 | D14: =('DE-InvAT'!C10-'DE-InvAT'!C15)-('DE-InvAT'!B10-'DE-InvAT'!B15) -> 47803645 | E14: =('DE-InvAT'!D10-'DE-InvAT'!D15)-('DE-InvAT'!C10-'DE-InvAT'!C15) -> -1837890 | F14: =('DE-InvAT'!E10-'DE-InvAT'!E15)-('DE-InvAT'!D10-'DE-InvAT'!D15) -> 0 | G14: =('DE-InvAT'!F10-'DE-InvAT'!F15)-('DE-InvAT'!E10-'DE-InvAT'!E15) -> 0 | H14: =('DE-InvAT'!G10-'DE-InvAT'!G15)-('DE-InvAT'!F10-'DE-InvAT'!F15) -> 0 | I14: =('DE-InvAT'!H10-'DE-InvAT'!H15)-('DE-InvAT'!G10-'DE-InvAT'!G15) -> 0 | J14: =('DE-InvAT'!I10-'DE-InvAT'!I15)-('DE-InvAT'!H10-'DE-InvAT'!H15) -> 0 | K14: =('DE-InvAT'!J10-'DE-InvAT'!J15)-('DE-InvAT'!I10-'DE-InvAT'!I15) -> 0 | ... M14: =('DE-InvAT'!L10-'DE-InvAT'!L15)-('DE-InvAT'!K10-'DE-InvAT'!K15) -> 0 | N14: =SUM(B14:M14) -> 45965755
A15: Stock de Elaborados | B15: 0 | C15: ='DE-InvAT'!B11 -> 0 | D15: =('DE-InvAT'!C11-'DE-InvAT'!C16)-('DE-InvAT'!B11-'DE-InvAT'!B16) -> 1.2454291e+08 | E15: =('DE-InvAT'!D11-'DE-InvAT'!D16)-('DE-InvAT'!C11-'DE-InvAT'!C16) -> 5238994.2 | F15: =('DE-InvAT'!E11-'DE-InvAT'!E16)-('DE-InvAT'!D11-'DE-InvAT'!D16) -> -454224.69 | G15: =('DE-InvAT'!F11-'DE-InvAT'!F16)-('DE-InvAT'!E11-'DE-InvAT'!E16) -> 0 | H15: =('DE-InvAT'!G11-'DE-InvAT'!G16)-('DE-InvAT'!F11-'DE-InvAT'!F16) -> 0 | I15: =('DE-InvAT'!H11-'DE-InvAT'!H16)-('DE-InvAT'!G11-'DE-InvAT'!G16) -> 0 | J15: =('DE-InvAT'!I11-'DE-InvAT'!I16)-('DE-InvAT'!H11-'DE-InvAT'!H16) -> 0 | K15: =('DE-InvAT'!J11-'DE-InvAT'!J16)-('DE-InvAT'!I11-'DE-InvAT'!I16) -> 0 | ... M15: =('DE-InvAT'!L11-'DE-InvAT'!L16)-('DE-InvAT'!K11-'DE-InvAT'!K16) -> 0 | N15: =SUM(B15:M15) -> 1.2932768e+08
A16: Subtotal Activo Trabajo | B16: 0 | C16: =SUM(C9:C15) -> 2.3722302e+08 | D16: =SUM(D9:D15) -> 5.9317256e+08 | E16: =SUM(E9:E15) -> 1.992376e+08 | F16: =SUM(F9:F15) -> -585291.42 | G16: =SUM(G9:G15) -> -24842.929 | H16: =SUM(H9:H15) -> 0 | I16: =SUM(I9:I15) -> 15509.603 | J16: =SUM(J9:J15) -> 0 | ... M16: =SUM(M9:M15) -> 0 | N16: =SUM(B16:M16) -> 1.0290386e+09
A18: IVA:
A19: por inversión A. Fijo | B19: =0.21*B6 -> 4096146.6 | C19: =0.21*C6 -> 5.9640142e+08 | D19: =0.21*D6 -> 1960418.1 | E19: =0.21*E6 -> 0 | F19: =0.21*F6 -> 0 | G19: =0.21*G6 -> 0 | H19: =0.21*H6 -> 0 | I19: =0.21*I6 -> 0 | ... M19: =0.21*M6 -> 0 | N19: =SUM(B19:M19) -> 6.0245799e+08
A20: por inversión A. T. | B20: =0.21*B16 -> 0 | C20: =0.21*C16 -> 49816835 | D20: =0.21*D16 -> 1.2456624e+08 | E20: =0.21*E16 -> 41839897 | F20: =0.21*F16 -> -122911.2 | G20: =0.21*G16 -> -5217.0152 | H20: =0.21*H16 -> 0 | I20: =0.21*I16 -> 3257.0166 | ... M20: =0.21*M16 -> 0 | N20: =SUM(B20:M20) -> 2.160981e+08
A21: Subtotal IVA Inversión | B21: =SUM(B19:B20) -> 4096146.6 | C21: =SUM(C19:C20) -> 6.4621826e+08 | D21: =SUM(D19:D20) -> 1.2652666e+08 | E21: =SUM(E19:E20) -> 41839897 | F21: =SUM(F19:F20) -> -122911.2 | G21: =SUM(G19:G20) -> -5217.0152 | H21: =SUM(H19:H20) -> 0 | I21: =SUM(I19:I20) -> 3257.0166 | ... M21: =SUM(M19:M20) -> 0 | N21: =SUM(B21:M21) -> 8.1855609e+08
N22: =SUM(B22:M22) -> 0
A23: Inversiones Totales | B23: =B6+B16+B21 -> 23601607 | C23: =C6+C16+C21 -> 3.7234481e+09 | D23: =D6+D16+D21 -> 7.2903454e+08 | E23: =E6+E16+E21 -> 2.410775e+08 | F23: =F6+F16+F21 -> -708202.62 | G23: =G6+G16+G21 -> -30059.944 | H23: =H6+H16+H21 -> 0 | I23: =I6+I16+I21 -> 18766.62 | ... M23: =M6+M16+M21 -> 0 | N23: =SUM(B23:M23) -> 4.7164422e+09

Sheet DE-IVA 
A1: IVA plan de Explotación, Cancelación del Credito Fiscal y pago al Fisco por IVA
B2: TOTALES PARA LAS TRES AREAS
A3: Rubros | B3: Año 0 | C3: Año 1 | D3: Año 2 | E3: Año 3 | F3: Año 4 | G3: Año 5 | H3: Año 6 | I3: Año 7 | J3: Año 8 | K3: Año 9 | L3: Año 10
A4: Rubros que abonan IVA
A5: Materia Prima | C5: =('DE-Costos'!B4+'DE-Costos'!B23)*0.21 -> 1.0554178e+08 | D5: =('DE-Costos'!C4+'DE-Costos'!C23)*0.21 -> 1.4054775e+08 | E5: =('DE-Costos'!D4+'DE-Costos'!D23)*0.21 -> 1.4054775e+08 | F5: =('DE-Costos'!E4+'DE-Costos'!E23)*0.21 -> 1.4054775e+08 | G5: =('DE-Costos'!F4+'DE-Costos'!F23)*0.21 -> 1.4054775e+08 | H5: =('DE-Costos'!G4+'DE-Costos'!G23)*0.21 -> 1.4054775e+08 | I5: =('DE-Costos'!H4+'DE-Costos'!H23)*0.21 -> 1.4054775e+08 | J5: =('DE-Costos'!I4+'DE-Costos'!I23)*0.21 -> 1.4054775e+08 | ... L5: =('DE-Costos'!K4+'DE-Costos'!K23)*0.21 -> 1.4054775e+08
A6: Materiales | C6: =('DE-Costos'!B74+'DE-Costos'!B55+'DE-Costos'!B9)*0.21 -> 19680440 | D6: =('DE-Costos'!C74+'DE-Costos'!C55+'DE-Costos'!C9)*0.21 -> 20199095 | E6: =('DE-Costos'!D74+'DE-Costos'!D55+'DE-Costos'!D9)*0.21 -> 20199095 | F6: =('DE-Costos'!E74+'DE-Costos'!E55+'DE-Costos'!E9)*0.21 -> 20199095 | G6: =('DE-Costos'!F74+'DE-Costos'!F55+'DE-Costos'!F9)*0.21 -> 20199095 | H6: =('DE-Costos'!G74+'DE-Costos'!G55+'DE-Costos'!G9)*0.21 -> 20199095 | I6: =('DE-Costos'!H74+'DE-Costos'!H55+'DE-Costos'!H9)*0.21 -> 20199095 | J6: =('DE-Costos'!I74+'DE-Costos'!I55+'DE-Costos'!I9)*0.21 -> 20199095 | ... L6: =('DE-Costos'!K74+'DE-Costos'!K55+'DE-Costos'!K9)*0.21 -> 20199095
A7: Energía eléctrica | C7: =('DE-Costos'!B10+'DE-Costos'!B56+'DE-Costos'!B75)*0.21 -> 25306070 | D7: =('DE-Costos'!C10+'DE-Costos'!C56+'DE-Costos'!C75)*0.21 -> 26606090 | E7: =('DE-Costos'!D10+'DE-Costos'!D56+'DE-Costos'!D75)*0.21 -> 26606090 | F7: =('DE-Costos'!E10+'DE-Costos'!E56+'DE-Costos'!E75)*0.21 -> 26606090 | G7: =('DE-Costos'!F10+'DE-Costos'!F56+'DE-Costos'!F75)*0.21 -> 26606090 | H7: =('DE-Costos'!G10+'DE-Costos'!G56+'DE-Costos'!G75)*0.21 -> 26606090 | I7: =('DE-Costos'!H10+'DE-Costos'!H56+'DE-Costos'!H75)*0.21 -> 26606090 | J7: =('DE-Costos'!I10+'DE-Costos'!I56+'DE-Costos'!I75)*0.21 -> 26606090 | ... L7: =('DE-Costos'!K10+'DE-Costos'!K56+'DE-Costos'!K75)*0.21 -> 26606090
A8: Combustibles | C8: =('DE-Costos'!B11+'DE-Costos'!B30+'DE-Costos'!B57)*0.21 -> 0 | D8: =('DE-Costos'!C11+'DE-Costos'!C30+'DE-Costos'!C57)*0.21 -> 0 | E8: =('DE-Costos'!D11+'DE-Costos'!D30+'DE-Costos'!D57)*0.21 -> 0 | F8: =('DE-Costos'!E11+'DE-Costos'!E30+'DE-Costos'!E57)*0.21 -> 0 | G8: =('DE-Costos'!F11+'DE-Costos'!F30+'DE-Costos'!F57)*0.21 -> 0 | H8: =('DE-Costos'!G11+'DE-Costos'!G30+'DE-Costos'!G57)*0.21 -> 0 | I8: =('DE-Costos'!H11+'DE-Costos'!H30+'DE-Costos'!H57)*0.21 -> 0 | J8: =('DE-Costos'!I11+'DE-Costos'!I30+'DE-Costos'!I57)*0.21 -> 0 | ... L8: =('DE-Costos'!K11+'DE-Costos'!K30+'DE-Costos'!K57)*0.21 -> 0
A9: Seguros | C9: =('DE-Costos'!B13+'DE-Costos'!B60+'DE-Costos'!B79)*0.21 -> 24866953 | D9: =('DE-Costos'!C13+'DE-Costos'!C60+'DE-Costos'!C79)*0.21 -> 24011292 | E9: =('DE-Costos'!D13+'DE-Costos'!D60+'DE-Costos'!D79)*0.21 -> 24011292 | F9: =('DE-Costos'!E13+'DE-Costos'!E60+'DE-Costos'!E79)*0.21 -> 24011292 | G9: =('DE-Costos'!F13+'DE-Costos'!F60+'DE-Costos'!F79)*0.21 -> 24011292 | H9: =('DE-Costos'!G13+'DE-Costos'!G60+'DE-Costos'!G79)*0.21 -> 24011292 | I9: =('DE-Costos'!H13+'DE-Costos'!H60+'DE-Costos'!H79)*0.21 -> 24011292 | J9: =('DE-Costos'!I13+'DE-Costos'!I60+'DE-Costos'!I79)*0.21 -> 24011292 | ... L9: =('DE-Costos'!K13+'DE-Costos'!K60+'DE-Costos'!K79)*0.21 -> 24011292
A10: Varios | C10: 0 | D10: 0 | E10: 0 | F10: 0 | G10: 0 | H10: 0 | I10: 0 | J10: 0 | K10: 0 | L10: 0
A11: Subtotal | C11: =SUM(C5:C10) -> 1.7539525e+08 | D11: =SUM(D5:D10) -> 2.1136422e+08 | E11: =SUM(E5:E10) -> 2.1136422e+08 | F11: =SUM(F5:F10) -> 2.1136422e+08 | G11: =SUM(G5:G10) -> 2.1136422e+08 | H11: =SUM(H5:H10) -> 2.1136422e+08 | I11: =SUM(I5:I10) -> 2.1136422e+08 | J11: =SUM(J5:J10) -> 2.1136422e+08 | ... L11: =SUM(L5:L10) -> 2.1136422e+08
A12: Menos: Puesta en marcha | C12: ='DE-Costos'!L34-'DE-Costos'!L24 -> 9504781.6
A13: (s/mano de obra directa)
A14: Merc. en proceso | C14: ='DE-InvAT'!C30 -> 11924468 | D14: ='DE-InvAT'!D30 -> 11161371 | E14: ='DE-InvAT'!E30 -> 11161371 | F14: ='DE-InvAT'!F30 -> 11161371 | G14: ='DE-InvAT'!G30 -> 11161371 | H14: ='DE-InvAT'!H30 -> 11161371 | I14: ='DE-InvAT'!I30 -> 11161371 | J14: ='DE-InvAT'!J30 -> 11161371 | ... L14: ='DE-InvAT'!L30 -> 11161371
A15: Stock elaborados | C15: ='DE-InvAT'!C31 -> 31128082 | D15: ='DE-InvAT'!D31 -> 31280600 | E15: ='DE-InvAT'!E31 -> 31185212 | F15: ='DE-InvAT'!F31 -> 31185212 | G15: ='DE-InvAT'!G31 -> 31185212 | H15: ='DE-InvAT'!H31 -> 31185212 | I15: ='DE-InvAT'!I31 -> 31185212 | J15: ='DE-InvAT'!J31 -> 31185212 | ... L15: ='DE-InvAT'!L31 -> 31185212
A16: Total Area Producción | C16: =C11-C12-C14-C15 -> 1.2283791e+08 | D16: =D11-D12-D14-D15 -> 1.6892225e+08 | E16: =E11-E12-E14-E15 -> 1.6901764e+08 | F16: =F11-F12-F14-F15 -> 1.6901764e+08 | G16: =G11-G12-G14-G15 -> 1.6901764e+08 | H16: =H11-H12-H14-H15 -> 1.6901764e+08 | I16: =I11-I12-I14-I15 -> 1.6901764e+08 | J16: =J11-J12-J14-J15 -> 1.6901764e+08 | ... L16: =L11-L12-L14-L15 -> 1.6901764e+08
A17: Total Area Administración | C17: =('DE-Costos'!B55+'DE-Costos'!B56+'DE-Costos'!B60)*InfoInicial!$B$2 -> 6149909.7 | D17: =('DE-Costos'!C55+'DE-Costos'!C56+'DE-Costos'!C60)*InfoInicial!$B$2 -> 6149909.7 | E17: =('DE-Costos'!D55+'DE-Costos'!D56+'DE-Costos'!D60)*InfoInicial!$B$2 -> 6149909.7 | F17: =('DE-Costos'!E55+'DE-Costos'!E56+'DE-Costos'!E60)*InfoInicial!$B$2 -> 6149909.7 | G17: =('DE-Costos'!F55+'DE-Costos'!F56+'DE-Costos'!F60)*InfoInicial!$B$2 -> 6149909.7 | H17: =('DE-Costos'!G55+'DE-Costos'!G56+'DE-Costos'!G60)*InfoInicial!$B$2 -> 6149909.7 | I17: =('DE-Costos'!H55+'DE-Costos'!H56+'DE-Costos'!H60)*InfoInicial!$B$2 -> 6149909.7 | J17: =('DE-Costos'!I55+'DE-Costos'!I56+'DE-Costos'!I60)*InfoInicial!$B$2 -> 6149909.7 | ... L17: =('DE-Costos'!K55+'DE-Costos'!K56+'DE-Costos'!K60)*InfoInicial!$B$2 -> 6149909.7
A18: Total Area Comercialización | C18: =('DE-Costos'!B74+'DE-Costos'!B75+'DE-Costos'!B79)*InfoInicial!$B$2 -> 6149909.7 | D18: =('DE-Costos'!C74+'DE-Costos'!C75+'DE-Costos'!C79)*InfoInicial!$B$2 -> 6149909.7 | E18: =('DE-Costos'!D74+'DE-Costos'!D75+'DE-Costos'!D79)*InfoInicial!$B$2 -> 6149909.7 | F18: =('DE-Costos'!E74+'DE-Costos'!E75+'DE-Costos'!E79)*InfoInicial!$B$2 -> 6149909.7 | G18: =('DE-Costos'!F74+'DE-Costos'!F75+'DE-Costos'!F79)*InfoInicial!$B$2 -> 6149909.7 | H18: =('DE-Costos'!G74+'DE-Costos'!G75+'DE-Costos'!G79)*InfoInicial!$B$2 -> 6149909.7 | I18: =('DE-Costos'!H74+'DE-Costos'!H75+'DE-Costos'!H79)*InfoInicial!$B$2 -> 6149909.7 | J18: =('DE-Costos'!I74+'DE-Costos'!I75+'DE-Costos'!I79)*InfoInicial!$B$2 -> 6149909.7 | ... L18: =('DE-Costos'!K74+'DE-Costos'!K75+'DE-Costos'!K79)*InfoInicial!$B$2 -> 6149909.7
A20: IVA total abonado por insumos | B20: 0 | C20: =C16+C17+C18 -> 1.3513773e+08 | D20: =D16+D17+D18 -> 1.8122207e+08 | E20: =E16+E17+E18 -> 1.8131746e+08 | F20: =F16+F17+F18 -> 1.8131746e+08 | G20: =G16+G17+G18 -> 1.8131746e+08 | H20: =H16+H17+H18 -> 1.8131746e+08 | I20: =I16+I17+I18 -> 1.8131746e+08 | J20: =J16+J17+J18 -> 1.8131746e+08 | ... L20: =L16+L17+L18 -> 1.8131746e+08
A21: IVA total cobrado por ventas | B21: 0 | C21: ='DE-Costos'!B94*InfoInicial!$B$2 -> 414618750 | D21: ='DE-Costos'!C94*InfoInicial!$B$2 -> 614250000 | E21: ='DE-Costos'!D94*InfoInicial!$B$2 -> 614250000 | F21: ='DE-Costos'!E94*InfoInicial!$B$2 -> 614250000 | G21: ='DE-Costos'!F94*InfoInicial!$B$2 -> 614250000 | H21: ='DE-Costos'!G94*InfoInicial!$B$2 -> 614250000 | I21: ='DE-Costos'!H94*InfoInicial!$B$2 -> 614250000 | J21: ='DE-Costos'!I94*InfoInicial!$B$2 -> 614250000 | ... L21: ='DE-Costos'!K94*InfoInicial!$B$2 -> 614250000
A22: a) IVA diferencia | B22: 0 | C22: =C21-C20 -> 2.7948102e+08 | D22: =D21-D20 -> 4.3302793e+08 | E22: =E21-E20 -> 4.3293254e+08 | F22: =F21-F20 -> 4.3293254e+08 | G22: =G21-G20 -> 4.3293254e+08 | H22: =H21-H20 -> 4.3293254e+08 | I22: =I21-I20 -> 4.3293254e+08 | J22: =J21-J20 -> 4.3293254e+08 | ... L22: =L21-L20 -> 4.3293254e+08
A24: b) Crédito Fiscal Anterior | B24: 0 | C24: =B26 -> 6.503144e+08 | D24: =C26 -> 4.9736004e+08 | E24: =D26 -> 0 | F24: =E26 -> 0 | G24: =F26 -> 0 | H24: =G26 -> 0 | I24: =H26 -> 0 | J24: =I26 -> 0 | ... L24: =K26 -> 0
A25: c) Crédito Fiscal del Año | B25: ='DE-Cal Inv.'!B21+'DE-Cal Inv.'!C21 -> 6.503144e+08 | C25: ='DE-Cal Inv.'!D21 -> 1.2652666e+08 | D25: ='DE-Cal Inv.'!E21 -> 41839897 | E25: 0 | F25: 0 | G25: 0 | H25: 0 | I25: 0 | J25: 0 | K25: 0 | L25: 0
A26: d) Crédito Fiscal Final Año | B26: =B25+B24-B22 -> 6.503144e+08 | C26: =C25+C24-C22 -> 4.9736004e+08 | D26: 0 | E26: 0 | F26: 0 | G26: 0 | H26: 0 | I26: 0 | J26: 0 | K26: 0 | L26: 0
A27: e) Recuepro de Credito Fiscal | B27: 0 | C27: =C24+C25-C26 -> 2.7948102e+08 | D27: =D24+D25-D26 -> 5.3919994e+08 | E27: =E24+E25-E26 -> 0 | F27: =F24+F25-F26 -> 0 | G27: =G24+G25-G26 -> 0 | H27: =H24+H25-H26 -> 0 | I27: =I24+I25-I26 -> 0 | J27: =J24+J25-J26 -> 0 | K27: =K24+K25-K26 -> 0 | L27: 0
A29: Pago al Fisco por IVA | C29: =C22-C27 -> 0 | D29: =D22-D27 -> -1.0617201e+08 | E29: =E22-E27 -> 4.3293254e+08 | F29: =F22-F27 -> 4.3293254e+08 | G29: =G22-G27 -> 4.3293254e+08 | H29: =H22-H27 -> 4.3293254e+08 | I29: =I22-I27 -> 4.3293254e+08 | J29: =J22-J27 -> 4.3293254e+08 | ... L29: =L22-L27 -> 4.3293254e+08

Sheet DE-Form
A1: Formulación del Proyecto a Nivel Económico
A2: Año | B2: Inversión en Activo Fijo | C2: Inversión en Activo de Trabajo | D2: Credito Fiscal | E2: Honorarios al Directorio | F2: Impuesto a las Ganancias | G2: Total Egresos | H2: Utilidad Economica Antes HD e IG | I2: Amortizaciones | J2: Cobro Credito Fiscal | K2: Total Ingresos | L2: Saldo Anual | M2: Saldo Acumulado
A3: 0 | B3: ='DE-Cal Inv.'!B6+'DE-Cal Inv.'!C6 -> 2.8595122e+09 | C3: ='DE-Cal Inv.'!C16 -> 2.3722302e+08 | D3: ='DE-IVA '!B25 -> 6.503144e+08 | E3: 0 | F3: 0 | G3: =(SUM(B3:F3)) -> 3.7470497e+09 | H3: 0 | I3: 0 | J3: 0 | K3: =SUM(H3:J3) -> 0 | L3: =K3-G3 -> -3.7470497e+09 | M3: =L3 -> -3.7470497e+09
A4: 1 | B4: ='DE-Cal Inv.'!D6 -> 9335324.3 | C4: ='DE-Cal Inv.'!D16 -> 5.9317256e+08 | D4: ='DE-IVA '!C25 -> 1.2652666e+08 | E4: ='DE-Costos'!B123 -> 0 | F4: ='DE-Costos'!B124 -> 3.541782e+08 | G4: =(SUM(B4:F4)) -> 1.0832127e+09 | H4: ='DE-Costos'!B122 -> 1.0119377e+09 | I4: ='DE-Costos'!B131 -> 1.784114e+08 | J4: ='DE-IVA '!C27 -> 2.7948102e+08 | K4: =SUM(H4:J4) -> 1.4698301e+09 | L4: =K4-G4 -> 3.866174e+08 | M4: =M3+L4 -> -3.3604323e+09
A5: 2 | C5: ='DE-Cal Inv.'!E16 -> 1.992376e+08 | D5: ='DE-IVA '!D25 -> 41839897 | E5: ='DE-Costos'!C123 -> 0 | F5: ='DE-Costos'!C124 -> 5.5022923e+08 | G5: =(SUM(B5:F5)) -> 7.9130673e+08 | H5: ='DE-Costos'!C122 -> 1.5720835e+09 | I5: ='DE-Costos'!C131 -> 1.784114e+08 | J5: ='DE-IVA '!D27 -> 5.3919994e+08 | K5: =SUM(H5:J5) -> 2.2896949e+09 | L5: =K5-G5 -> 1.4983881e+09 | M5: =M4+L5 -> -1.8620441e+09
A6: 3 | C6: ='DE-Cal Inv.'!F16 -> -585291.42 | D6: ='DE-IVA '!E25 -> 0 | E6: ='DE-Costos'!D123 -> 0 | F6: ='DE-Costos'!D124 -> 5.5108789e+08 | G6: =(SUM(B6:F6)) -> 5.5050259e+08 | H6: ='DE-Costos'!D122 -> 1.5745368e+09 | I6: ='DE-Costos'!D131 -> 1.784114e+08 | J6: ='DE-IVA '!E27 -> 0 | K6: =SUM(H6:J6) -> 1.7529482e+09 | L6: =K6-G6 -> 1.2024456e+09 | M6: =M5+L6 -> -6.5959851e+08
A7: 4 | C7: ='DE-Cal Inv.'!G16 -> -24842.929 | D7: ='DE-IVA '!F25 -> 0 | E7: ='DE-Costos'!E123 -> 0 | F7: ='DE-Costos'!E124 -> 5.5124686e+08 | G7: =(SUM(B7:F7)) -> 5.5122202e+08 | H7: ='DE-Costos'!E122 -> 1.574991e+09 | I7: ='DE-Costos'!E131 -> 1.784114e+08 | J7: ='DE-IVA '!F27 -> 0 | K7: =SUM(H7:J7) -> 1.7534024e+09 | L7: =K7-G7 -> 1.2021804e+09 | M7: =M6+L7 -> 5.4258191e+08
A8: 5 | C8: ='DE-Cal Inv.'!H16 -> 0 | D8: ='DE-IVA '!G25 -> 0 | E8: ='DE-Costos'!F123 -> 0 | F8: ='DE-Costos'!F124 -> 5.5124686e+08 | G8: =(SUM(B8:F8)) -> 5.5124686e+08 | H8: ='DE-Costos'!F122 -> 1.574991e+09 | I8: ='DE-Costos'!F131 -> 1.784114e+08 | J8: ='DE-IVA '!G27 -> 0 | K8: =SUM(H8:J8) -> 1.7534024e+09 | L8: =K8-G8 -> 1.2021556e+09 | M8: =M7+L8 -> 1.7447375e+09
A9: 6 | C9: ='DE-Cal Inv.'!I16 -> 15509.603 | D9: ='DE-IVA '!H25 -> 0 | E9: ='DE-Costos'!G123 -> 0 | F9: ='DE-Costos'!G124 -> 5.5124686e+08 | G9: =(SUM(B9:F9)) -> 5.5126237e+08 | H9: ='DE-Costos'!G122 -> 1.574991e+09 | I9: ='DE-Costos'!G131 -> 8581250 | J9: ='DE-IVA '!H27 -> 0 | K9: =SUM(H9:J9) -> 1.5835723e+09 | L9: =K9-G9 -> 1.0323099e+09 | M9: =M8+L9 -> 2.7770474e+09
A10: 7 | C10: ='DE-Cal Inv.'!J16 -> 0 | D10: ='DE-IVA '!I25 -> 0 | E10: ='DE-Costos'!H123 -> 0 | F10: ='DE-Costos'!H124 -> 5.5124686e+08 | G10: =(SUM(B10:F10)) -> 5.5124686e+08 | H10: ='DE-Costos'!H122 -> 1.574991e+09 | I10: ='DE-Costos'!H131 -> 8581250 | J10: ='DE-IVA '!I27 -> 0 | K10: =SUM(H10:J10) -> 1.5835723e+09 | L10: =K10-G10 -> 1.0323254e+09 | M10: =M9+L10 -> 3.8093728e+09
A11: 8 | C11: ='DE-Cal Inv.'!G14 -> 0 | D11: ='DE-IVA '!J25 -> 0 | E11: ='DE-Costos'!I123 -> 0 | F11: ='DE-Costos'!I124 -> 5.5124686e+08 | G11: =(SUM(B11:F11)) -> 5.5124686e+08 | H11: ='DE-Costos'!I122 -> 1.574991e+09 | I11: ='DE-Costos'!I131 -> 8581250 | J11: ='DE-IVA '!J27 -> 0 | K11: =SUM(H11:J11) -> 1.5835723e+09 | L11: =K11-G11 -> 1.0323254e+09 | M11: =M10+L11 -> 4.8416983e+09
A12: 9 | C12: ='DE-Cal Inv.'!H14 -> 0 | D12: ='DE-IVA '!K25 -> 0 | E12: ='DE-Costos'!J123 -> 0 | F12: ='DE-Costos'!J124 -> 5.5124686e+08 | G12: =(SUM(B12:F12)) -> 5.5124686e+08 | H12: ='DE-Costos'!J122 -> 1.574991e+09 | I12: ='DE-Costos'!J131 -> 8581250 | J12: ='DE-IVA '!K27 -> 0 | K12: =SUM(H12:J12) -> 1.5835723e+09 | L12: =K12-G12 -> 1.0323254e+09 | M12: =M11+L12 -> 5.8740237e+09
A13: 10 | B13: =-'DE-Inv AF y Am'!G55 -> -1.9338843e+09 | C13: =-'DE-Cal Inv.'!N16 -> -1.0290386e+09 | D13: ='DE-IVA '!L25 -> 0 | E13: ='DE-Costos'!K123 -> 0 | F13: ='DE-Costos'!K124 -> 5.5124686e+08 | G13: =(SUM(B13:F13)) -> -2.411676e+09 | H13: ='DE-Costos'!K122 -> 1.574991e+09 | I13: ='DE-Costos'!K131 -> 8581250 | J13: ='DE-IVA '!L27 -> 0 | K13: =SUM(H13:J13) -> 1.5835723e+09 | L13: =K13-G13 -> 3.9952483e+09 | M13: =M12+L13 -> 9.869272e+09
A15: Suma. | B15: =SUM(B3:B13) -> 9.3496326e+08 | C15: =SUM(C3:C13) -> 0 | D15: =SUM(D3:D13) -> 8.1868096e+08 | E15: =SUM(E3:E13) -> 0 | F15: =SUM(F3:F13) -> 5.3142234e+09 | G15: =SUM(G3:G13) -> 7.0678676e+09 | H15: =SUM(H3:H13) -> 1.5183495e+10 | I15: =SUM(I3:I13) -> 9.3496326e+08 | ... L15: =SUM(L3:L13) -> 9.869272e+09
C17: Beneficio Neto | D17: =L15 -> 9.869272e+09
C18: Periodo de Recupero de la Inversión | D18: 3 | E18: años y | F18: =ROUNDUP(((-M6)/L7)*365,0) -> 201 | G18: días
C19: TIR | D19: =IRR(L3:L13) -> 0.2682887
C22: Beneficio Neto | D22: =H15-E15-F15 -> 9.869272e+09

Sheet DF-2 Estructura
A1: SEGUNDA ESTRUCTURA FINANCIERA
A2: Rubros | B2: Año 0 | C2: Año 1 | D2: Totales
A3: a) Inversión y calendario de activo fijo: incrementos
A5: Bienes de uso | B5: ='DE-Inv AF y Am'!B20 -> 2.8400068e+09 | C5: 0 | D5: =SUM(B5:C5) -> 2.8400068e+09
A6: Cargos diferidos: | B6: ='DE-Inv AF y Am'!B31+'DF-Cred'!M6 -> 5.7462746e+08 | C6: ='DE-Inv AF y Am'!C31 -> 9335324.3 | D6: =SUM(B6:C6) -> 5.8396279e+08
A7: Totales de activo fijo, sin IVA | B7: =SUM(B5:B6) -> 3.4146342e+09 | C7: =SUM(C5:C6) -> 9335324.3 | D7: =SUM(B7:C7) -> 3.4239696e+09
A8: IVA | B8: =0.21*B7 -> 7.1707319e+08 | C8: =0.21*C7 -> 1960418.1 | D8: =SUM(B8:C8) -> 7.1903361e+08
A9: Totales de activo fijo, con IVA | B9: =B7+B8 -> 4.1317074e+09 | C9: =C7+C8 -> 11295742 | D9: =SUM(B9:C9) -> 4.1430032e+09
A10: b) Inversión y calendario de activo de trabajo: incrementos
A11: Disponibilidad mínima | B11: ='DE-InvAT'!B4 -> 39487500 | C11: ='DE-InvAT'!C4 -> 58500000 | D11: =B11+C11 -> 97987500
A12: Crédito por ventas (valor contable) | B12: ='DE-InvAT'!B5 -> 0 | C12: ='DE-InvAT'!C5 -> 1.622774e+08 | D12: =B12+C12 -> 1.622774e+08
A13: Bienes de cambio (valor contable) | B13: ='DE-InvAT'!B7 -> 1.9773552e+08 | C13: ='DE-InvAT'!C7 -> 6.9635951e+08 | D13: =B13+C13 -> 8.9409504e+08
A14: Totales activo de trabajo, sin IVA | B14: =SUM(B11:B13) -> 2.3722302e+08 | C14: =SUM(C11:C13) -> 9.1713691e+08 | D14: =B14+C14 -> 1.1543599e+09
A15: Menos:
A16: Amortizaciones en inventarios | B16: ='DE-InvAT'!B15+'DE-InvAT'!B16 -> 0 | C16: ='DE-InvAT'!C15+'DE-InvAT'!C16 -> 32665588 | D16: =B16+C16 -> 32665588
A17: Amortizaciones en crédito | B17: ='DE-InvAT'!B16+'DE-InvAT'!B17 -> 0 | C17: ='DE-InvAT'!C18 -> 13310.12 | D17: =B17+C17 -> 13310.12
A18: Utilidades en crédito | B18: ='DE-InvAT'!B17+'DE-InvAT'!B18 -> 0 | C18: ='DE-InvAT'!C17 -> 54062427 | D18: =B18+C18 -> 54062427
A19: Inversión activo de trabajo, s/IVA | B19: =B14-SUM(B16:B18) -> 2.3722302e+08 | C19: =C14-SUM(C16:C18) -> 8.3039558e+08 | D19: =B19+C19 -> 1.0676186e+09
A20: IVA | B20: =0.21*B19 -> 49816835 | C20: =0.21*C19 -> 1.7438307e+08 | D20: =B20+C20 -> 2.2419991e+08
A21: Totales activo de trabajo (v. contable), c/IVA | B21: =B20+B14 -> 2.8703986e+08 | C21: =C20+C14 -> 1.09152e+09 | D21: =B21+C21 -> 1.3785598e+09
A22: Inversión activo de trabajo, con IVA | B22: =B20+B19 -> 2.8703986e+08 | C22: =C20+C19 -> 1.0047787e+09 | D22: =B22+C22 -> 1.2918185e+09
A23: c) Inversión y calendario totales: incrementos
A24: Activo fijo, con IVA | B24: =B9 -> 4.1317074e+09 | C24: =C9 -> 11295742 | D24: =B24+C24 -> 4.1430032e+09
A25: Inversión activo de trabajo, c/IVA | B25: =B22 -> 2.8703986e+08 | C25: =C22 -> 1.0047787e+09 | D25: =B25+C25 -> 1.2918185e+09
A26: Inversiones Totales, con IVA | B26: =SUM(B24:B25) -> 4.4187473e+09 | C26: =SUM(C24:C25) -> 1.0160744e+09 | D26: =B26+C26 -> 5.4348217e+09
A27: d) Financiación global (segunda y definitiva): | E27: Porcentaje
A28: Crédito renovable | B28: 0 | C28: ='DF-Cred'!D5 -> 4.1519779e+08 | D28: =B28+C28 -> 4.1519779e+08 | E28: =D28/$D$31 -> 0.076395844
A29: Crédito no renovable | B29: ='DF-Cred'!D4 -> 8.6065427e+08 | C29: 0 | D29: =B29+C29 -> 8.6065427e+08 | E29: =D29/$D$31 -> 0.15835925
A30: Capital propio | B30: =B26-(B28+B29) -> 3.558093e+09 | C30: =C26-(C28+C29) -> 6.0087661e+08 | D30: =B30+C30 -> 4.1589696e+09 | E30: =D30/$D$31 -> 0.76524491
A31: Totales | B31: =SUM(B28:B30) -> 4.4187473e+09 | C31: =SUM(C28:C30) -> 1.0160744e+09 | D31: =B31+C31 -> 5.4348217e+09 | E31: =SUM(E28:E30) -> 1
A33: PUNTO DE EQUILIBRIO ECONOMICO FINANCIERO
A34: Rubros | B34: Año 1 | C34: Año 2 | D34: Año 3 | E34: Año 4 | F34: Año 5 | G34: Año 6 | H34: Año 7 | I34: Año 8 | J34: Año 9 | K34: Año 10
A35: Costo Variable Sector de Producción | B35: ='DE-Costos'!B134 -> 5.4360282e+08 | C35: ='DE-Costos'!C134 -> 7.1072486e+08 | D35: ='DE-Costos'!D134 -> 7.1072486e+08 | E35: ='DE-Costos'!E134 -> 7.1072486e+08 | F35: ='DE-Costos'!F134 -> 7.1072486e+08 | G35: ='DE-Costos'!G134 -> 7.1072486e+08 | H35: ='DE-Costos'!H134 -> 7.1072486e+08 | I35: ='DE-Costos'!I134 -> 7.1072486e+08 | ... K35: ='DE-Costos'!K134 -> 7.1072486e+08
A36: Costo Constante Sector de Producción | B36: ='DE-Costos'!B135 -> 4.7178248e+08 | C36: ='DE-Costos'!C135 -> 4.7728323e+08 | D36: ='DE-Costos'!D135 -> 4.7728323e+08 | E36: ='DE-Costos'!E135 -> 4.7728323e+08 | F36: ='DE-Costos'!F135 -> 4.7728323e+08 | G36: ='DE-Costos'!G135 -> 4.7728323e+08 | H36: ='DE-Costos'!H135 -> 4.7728323e+08 | I36: ='DE-Costos'!I135 -> 4.7728323e+08 | ... K36: ='DE-Costos'!K135 -> 4.7728323e+08
A37: Costo Variable Sector de Administración | B37: ='DE-Costos'!B136 -> 89498270 | C37: ='DE-Costos'!C136 -> 89498270 | D37: ='DE-Costos'!D136 -> 89498270 | E37: ='DE-Costos'!E136 -> 89498270 | F37: ='DE-Costos'!F136 -> 89498270 | G37: ='DE-Costos'!G136 -> 89498270 | H37: ='DE-Costos'!H136 -> 89498270 | I37: ='DE-Costos'!I136 -> 89498270 | ... K37: ='DE-Costos'!K136 -> 89498270
A38: Costo Constante Sector de Administración | B38: ='DE-Costos'!B137 -> 14135175 | C38: ='DE-Costos'!C137 -> 14135175 | D38: ='DE-Costos'!D137 -> 14135175 | E38: ='DE-Costos'!E137 -> 14135175 | F38: ='DE-Costos'!F137 -> 14135175 | G38: ='DE-Costos'!G137 -> 14135175 | H38: ='DE-Costos'!H137 -> 14135175 | I38: ='DE-Costos'!I137 -> 14135175 | ... K38: ='DE-Costos'!K137 -> 14135175
A39: Costo Variable Sector de Comercialización | B39: ='DE-Costos'!B138 -> 45119819 | C39: ='DE-Costos'!C138 -> 45119819 | D39: ='DE-Costos'!D138 -> 45119819 | E39: ='DE-Costos'!E138 -> 45119819 | F39: ='DE-Costos'!F138 -> 45119819 | G39: ='DE-Costos'!G138 -> 45119819 | H39: ='DE-Costos'!H138 -> 45119819 | I39: ='DE-Costos'!I138 -> 45119819 | ... K39: ='DE-Costos'!K138 -> 45119819
A40: Costo Constante Sector de Comercialización | B40: ='DE-Costos'!B139 -> 13247606 | C40: ='DE-Costos'!C139 -> 13247606 | D40: ='DE-Costos'!D139 -> 13247606 | E40: ='DE-Costos'!E139 -> 13247606 | F40: ='DE-Costos'!F139 -> 13247606 | G40: ='DE-Costos'!G139 -> 13247606 | H40: ='DE-Costos'!H139 -> 13247606 | I40: ='DE-Costos'!I139 -> 13247606 | ... K40: ='DE-Costos'!K139 -> 13247606
A41: Gasto Financiero | B41: ='DF-CRes'!B9 -> 6.2933094e+08 | C41: ='DF-CRes'!C9 -> 4.8588856e+08 | D41: ='DF-CRes'!D9 -> 3.4244619e+08 | E41: ='DF-CRes'!E9 -> 49823735 | F41: ='DF-CRes'!F9 -> 49823735 | G41: ='DF-CRes'!G9 -> 49823735 | H41: ='DF-CRes'!H9 -> 49823735 | I41: ='DF-CRes'!I9 -> 49823735 | ... K41: ='DF-CRes'!K9 -> 49823735
A42: Costos variables Totales | B42: =B35+B37+B39 -> 6.7822091e+08 | C42: =C35+C37+C39 -> 8.4534295e+08 | D42: =D35+D37+D39 -> 8.4534295e+08 | E42: =E35+E37+E39 -> 8.4534295e+08 | F42: =F35+F37+F39 -> 8.4534295e+08 | G42: =G35+G37+G39 -> 8.4534295e+08 | H42: =H35+H37+H39 -> 8.4534295e+08 | I42: =I35+I37+I39 -> 8.4534295e+08 | ... K42: =K35+K37+K39 -> 8.4534295e+08
A43: Costos contantes Totales | B43: =B36+B38+B40+B41 -> 1.1284962e+09 | C43: =C36+C38+C40+C41 -> 9.9055458e+08 | D43: =D36+D38+D40+D41 -> 8.471122e+08 | E43: =E36+E38+E40+E41 -> 5.5448975e+08 | F43: =F36+F38+F40+F41 -> 5.5448975e+08 | G43: =G36+G38+G40+G41 -> 5.5448975e+08 | H43: =H36+H38+H40+H41 -> 5.5448975e+08 | I43: =I36+I38+I40+I41 -> 5.5448975e+08 | ... K43: =K36+K38+K40+K41 -> 5.5448975e+08
A44: UTILIDAD MARGINAL | B44: =B48-B42 -> 1.2961541e+09 | C44: =C48-C42 -> 2.0796571e+09 | D44: =D48-D42 -> 2.0796571e+09 | E44: =E48-E42 -> 2.0796571e+09 | F44: =F48-F42 -> 2.0796571e+09 | G44: =G48-G42 -> 2.0796571e+09 | H44: =H48-H42 -> 2.0796571e+09 | I44: =I48-I42 -> 2.0796571e+09 | ... K44: =K48-K42 -> 2.0796571e+09
A45: PUNTO DE EQUILIBRIO | B45: =(B36+B38+B40+B41)/B44 -> 0.87064972 | C45: =(C36+C38+C40+C41)/C44 -> 0.4763067 | D45: =(D36+D38+D40+D41)/D44 -> 0.40733264 | E45: =(E36+E38+E40+E41)/E44 -> 0.26662557 | F45: =(F36+F38+F40+F41)/F44 -> 0.26662557 | G45: =(G36+G38+G40+G41)/G44 -> 0.26662557 | H45: =(H36+H38+H40+H41)/H44 -> 0.26662557 | I45: =(I36+I38+I40+I41)/I44 -> 0.26662557 | ... K45: =(K36+K38+K40+K41)/K44 -> 0.26662557
A48: Ventas Anuales = | B48: ='DE-Costos'!B94 -> 1974375000 | C48: ='DE-Costos'!C94 -> 2925000000 | D48: ='DE-Costos'!D94 -> 2925000000 | E48: ='DE-Costos'!E94 -> 2925000000 | F48: ='DE-Costos'!F94 -> 2925000000 | G48: ='DE-Costos'!G94 -> 2925000000 | H48: ='DE-Costos'!H94 -> 2925000000 | I48: ='DE-Costos'!I94 -> 2925000000 | ... K48: ='DE-Costos'!K94 -> 2925000000
A50: HACER DIAGRAMA DE PUNTO DE EQUILIBRIO PARA EL AÑO 1 Y PARA EL AÑO 10
B53: Año 1 | G53: Año 10
B54: Volumen de ventas año 1 (Tn) | C54: 3375 | D54: =C54*B45 -> 2938.4428 | G54: Volumen de ventas año 1 (Tn) | H54: 5000 | I54: =H54*H58 -> 1333.1279
B55: Precio de venta unitario | C55: =InfoInicial!$B$18*InfoInicial!$B$30 -> 585000 | G55: Precio de venta unitario | H55: =InfoInicial!$B$18*InfoInicial!$B$30 -> 585000
B56: Costos fijos | C56: =B38+B36+B40+B41 -> 1.1284962e+09 | G56: Costos fijos | H56: =K36+K38+K40+K41 -> 5.5448975e+08
B57: Costo variable unitario | C57: =(B37+B39+B35)/C54 -> 200954.34 | G57: Costo variable unitario | H57: =(K35+K37+K39)/H54 -> 169068.59
B58: Punto de Equilibrio | C58: =B45 -> 0.87064972 | G58: Punto de Equilibrio | H58: =K45 -> 0.26662557
G60: Año 10
B61: Año 1 | G61: Q | H61: % C.I. | I61: Ventas | J61: Costo Total
B62: Q | C62: % C.I. | D62: Ventas | E62: Costo Total | G62: 0 | H62: =G62/$H$54 -> 0 | I62: =G62*$H$55 -> 0 | J62: =$H$56+$H$57*G62 -> 5.5448975e+08
B63: 0 | C63: =B63/$C$54 -> 0 | D63: =B63*$C$55 -> 0 | E63: =$C$56+$C$57*B63 -> 1.1284962e+09 | G63: 250 | H63: =G63/$H$54 -> 0.05 | I63: =G63*$H$55 -> 146250000 | J63: =$H$56+$H$57*G63 -> 5.967569e+08
B64: 225 | C64: =B64/$C$54 -> 0.066666667 | D64: =B64*$C$55 -> 131625000 | E64: =$C$56+$C$57*B64 -> 1.1737109e+09 | G64: 500 | H64: =G64/$H$54 -> 0.1 | I64: =G64*$H$55 -> 292500000 | J64: =$H$56+$H$57*G64 -> 6.3902404e+08
B65: 450 | C65: =B65/$C$54 -> 0.13333333 | D65: =B65*$C$55 -> 263250000 | E65: =$C$56+$C$57*B65 -> 1.2189257e+09 | G65: 750 | H65: =G65/$H$54 -> 0.15 | I65: =G65*$H$55 -> 438750000 | J65: =$H$56+$H$57*G65 -> 6.8129119e+08
B66: 675 | C66: =B66/$C$54 -> 0.2 | D66: =B66*$C$55 -> 394875000 | E66: =$C$56+$C$57*B66 -> 1.2641404e+09 | G66: 1000 | H66: =G66/$H$54 -> 0.2 | I66: =G66*$H$55 -> 585000000 | J66: =$H$56+$H$57*G66 -> 7.2355834e+08
B67: 900 | C67: =B67/$C$54 -> 0.26666667 | D67: =B67*$C$55 -> 526500000 | E67: =$C$56+$C$57*B67 -> 1.3093551e+09 | G67: 1250 | H67: =G67/$H$54 -> 0.25 | I67: =G67*$H$55 -> 731250000 | J67: =$H$56+$H$57*G67 -> 7.6582549e+08
B68: 1125 | C68: =B68/$C$54 -> 0.33333333 | D68: =B68*$C$55 -> 658125000 | E68: =$C$56+$C$57*B68 -> 1.3545698e+09 | G68: 1500 | H68: =G68/$H$54 -> 0.3 | I68: =G68*$H$55 -> 877500000 | J68: =$H$56+$H$57*G68 -> 8.0809263e+08
B69: 1350 | C69: =B69/$C$54 -> 0.4 | D69: =B69*$C$55 -> 789750000 | E69: =$C$56+$C$57*B69 -> 1.3997846e+09 | G69: 1750 | H69: =G69/$H$54 -> 0.35 | I69: =G69*$H$55 -> 1023750000 | J69: =$H$56+$H$57*G69 -> 8.5035978e+08
B70: 1575 | C70: =B70/$C$54 -> 0.46666667 | D70: =B70*$C$55 -> 921375000 | E70: =$C$56+$C$57*B70 -> 1.4449993e+09 | G70: 2000 | H70: =G70/$H$54 -> 0.4 | I70: =G70*$H$55 -> 1170000000 | J70: =$H$56+$H$57*G70 -> 8.9262693e+08
B71: 1800 | C71: =B71/$C$54 -> 0.53333333 | D71: =B71*$C$55 -> 1053000000 | E71: =$C$56+$C$57*B71 -> 1.490214e+09 | G71: 2250 | H71: =G71/$H$54 -> 0.45 | I71: =G71*$H$55 -> 1316250000 | J71: =$H$56+$H$57*G71 -> 9.3489408e+08
B72: 2025 | C72: =B72/$C$54 -> 0.6 | D72: =B72*$C$55 -> 1184625000 | E72: =$C$56+$C$57*B72 -> 1.5354287e+09 | G72: 2500 | H72: =G72/$H$54 -> 0.5 | I72: =G72*$H$55 -> 1462500000 | J72: =$H$56+$H$57*G72 -> 9.7716122e+08
B73: 2250 | C73: =B73/$C$54 -> 0.66666667 | D73: =B73*$C$55 -> 1316250000 | E73: =$C$56+$C$57*B73 -> 1.5806435e+09 | G73: 2750 | H73: =G73/$H$54 -> 0.55 | I73: =G73*$H$55 -> 1608750000 | J73: =$H$56+$H$57*G73 -> 1.0194284e+09
B74: 2475 | C74: =B74/$C$54 -> 0.73333333 | D74: =B74*$C$55 -> 1447875000 | E74: =$C$56+$C$57*B74 -> 1.6258582e+09 | G74: 3000 | H74: =G74/$H$54 -> 0.6 | I74: =G74*$H$55 -> 1755000000 | J74: =$H$56+$H$57*G74 -> 1.0616955e+09
... B78: 3375 | C78: =B78/$C$54 -> 1 | D78: =B78*$C$55 -> 1974375000 | E78: =$C$56+$C$57*B78 -> 1.8067171e+09 | G78: 4000 | H78: =G78/$H$54 -> 0.8 | I78: =G78*$H$55 -> 2340000000 | J78: =$H$56+$H$57*G78 -> 1.2307641e+09
G79: 4250 | H79: =G79/$H$54 -> 0.85 | I79: =G79*$H$55 -> 2486250000 | J79: =$H$56+$H$57*G79 -> 1.2730313e+09
G80: 4500 | H80: =G80/$H$54 -> 0.9 | I80: =G80*$H$55 -> 2632500000 | J80: =$H$56+$H$57*G80 -> 1.3152984e+09
G81: 4750 | H81: =G81/$H$54 -> 0.95 | I81: =G81*$H$55 -> 2778750000 | J81: =$H$56+$H$57*G81 -> 1.3575655e+09
G82: 5000 | H82: =G82/$H$54 -> 1 | I82: =G82*$H$55 -> 2925000000 | J82: =$H$56+$H$57*G82 -> 1.3998327e+09

Sheet DF-Cred
A1: PRIMERA ESTRUCTURA FINANCIERA
A2: Rubros | B2: Total Inversión | D2: Créditos | F2: Capital Propio
A3: Inversión | B3: monto | C3: % | D3: monto | E3: % | F3: monto | G3: %
A4: Activo Fijo | B4: ='DE-Cal Inv.'!B6+'DE-Cal Inv.'!C6+'DE-Cal Inv.'!D6 -> 2.8688476e+09 | C4: =B4/$B$7 -> 0.64092797 | D4: =B4*InfoInicial!B35 -> 8.6065427e+08 | E4: =D4/$B$7 -> 0.19227839 | F4: =B4-D4 -> 2.0081933e+09 | G4: =F4/$B$7 -> 0.44864958 | K4: Comisiones y gastos bancarios: | L4: 0.02 | M4: A. Fijo
A5: Activo de Trabajo | B5: ='DE-Cal Inv.'!C16+'DE-Cal Inv.'!D16 -> 8.3039558e+08 | C5: =B5/$B$7 -> 0.18551831 | D5: =B5*InfoInicial!B38 -> 4.1519779e+08 | E5: =D5/$B$7 -> 0.092759156 | F5: =B5-D5 -> 4.1519779e+08 | G5: =F5/$B$7 -> 0.092759156
A6: IVA | B6: ='DE-Cal Inv.'!B21+'DE-Cal Inv.'!C21+'DE-Cal Inv.'!D21 -> 7.7684106e+08 | C6: =B6/$B$7 -> 0.17355372 | D6: 0 | E6: =D6/$B$7 -> 0 | F6: =B6-D6 -> 7.7684106e+08 | G6: =F6/$B$7 -> 0.17355372 | K6: Interreses y gastos bancarios preoperativos | M6: =I16+D16 -> 5.55122e+08
A7: Totales | B7: =SUM(B4:B6) -> 4.4760842e+09 | C7: =B7/$B$7 -> 1 | D7: =SUM(D4:D6) -> 1.2758521e+09 | E7: =D7/$B$7 -> 0.28503755 | F7: =SUM(F4:F6) -> 3.2002321e+09 | G7: =SUM(G4:G6) -> 0.71496245 | H7: =E7+G7 -> 1
A9: CUADRO RESUMEN DE CREDITOS
A10: día/mes/año | B10: deuda | C10: amortización | D10: interés | E10: amortización | F10: deuda | G10: interés | I10: gasto | K10: Crédito No Renovable | L10: deuda | M10: amortización | N10: interés | O10: amortización | P10: interés | Q10: gasto | R10: Cuota Semestral
C11: semestral | D11: semestral | E11: anual | F11: prom. anual | G11: anual | H11: kd | I11: bancario | K11: Activo FIjo | M11: semestral | N11: semestral | O11: anual | P11: anual | Q11: bancario
A12: 45657 | B12: =L13 -> 7.1721189e+08 | C12: =M13 -> 1.4344238e+08 | D12: =N13 -> 2.1516357e+08 | E12: =O13 -> 0 | I12: =Q13 -> 17213085 | L12: =D4 -> 8.6065427e+08
A13: 45838 | B13: =L14 -> 5.7376951e+08 | C13: =M14 -> 1.4344238e+08 | D13: =N14 -> 1.7930297e+08 | E13: =O14 -> 2.8688476e+08 | F13: =(B12) -> 7.1721189e+08 | G13: =P14 -> 3.9446654e+08 | H13: =G13/F13 -> 0.55 | J13: -1 | K13: 45657 | L13: =L12-M13 -> 7.1721189e+08 | M13: =$L$12/6 -> 1.4344238e+08 | N13: =(InfoInicial!$B$33/2)*L12 -> 2.1516357e+08 | Q13: =L12*L4 -> 17213085 | R13: =M13+N13 -> 3.5860594e+08
A14: 46022 | B14: =L15 -> 4.3032713e+08 | C14: =M15 -> 1.4344238e+08 | D14: =N15 -> 1.4344238e+08 | E14: =O15 -> 0 | J14: -1 | K14: 45838 | L14: =L13-M14 -> 5.7376951e+08 | M14: =$L$12/6 -> 1.4344238e+08 | N14: =(InfoInicial!$B$33/2)*L13 -> 1.7930297e+08 | O14: =M14+M13 -> 2.8688476e+08 | P14: =N14+N13 -> 3.9446654e+08 | R14: =M14+N14 -> 3.2274535e+08
J15: 1 | K15: 46022 | L15: =L14-M15 -> 4.3032713e+08 | M15: =$L$12/6 -> 1.4344238e+08 | N15: =(InfoInicial!$B$33/2)*L14 -> 1.4344238e+08 | R15: =M15+N15 -> 2.8688476e+08
A16: gastos preoperativos: | D16: =SUM(D12:D14) -> 5.3790892e+08 | I16: =I12 -> 17213085 | J16: 1 | K16: 46203 | L16: =L15-M16 -> 2.8688476e+08 | M16: =$L$12/6 -> 1.4344238e+08 | N16: =(InfoInicial!$B$33/2)*L15 -> 1.0758178e+08 | O16: =M16+M15 -> 2.8688476e+08 | P16: =N16+N15 -> 2.5102416e+08 | R16: =M16+N16 -> 2.5102416e+08
A17: 46203 | B17: =L16+L25 -> 7.0208255e+08 | C17: =M16 -> 1.4344238e+08 | D17: =N16+N25 -> 1.3249365e+08 | E17: =O16 -> 2.8688476e+08 | F17: =AVERAGE(B14,B17) -> 5.6620484e+08 | G17: =M16+M15+N25 -> 3.1179662e+08 | H17: =G17/F17 -> 0.55067813 | J17: 2 | K17: 46387 | L17: =L16-$M$17 -> 1.4344238e+08 | M17: =$L$12/6 -> 1.4344238e+08 | N17: =(InfoInicial!$B$33/2)*L16 -> 71721189 | R17: =M17+N17 -> 2.1516357e+08
A18: 46387 | B18: =L17+L26 -> 5.5864017e+08 | C18: =M17 -> 1.4344238e+08 | D18: =N17+N26 -> 96633057 | J18: 2 | K18: 46568 | L18: =L17-$M$17 -> 0 | M18: =$L$12/6 -> 1.4344238e+08 | N18: =(InfoInicial!$B$33/2)*L17 -> 35860594 | O18: =M17+M18 -> 2.8688476e+08 | P18: =N17+N18 -> 1.0758178e+08 | R18: =M18+N18 -> 1.7930297e+08
A19: 46568 | B19: =L18+L27 -> 4.1519779e+08 | C19: =M18 -> 1.4344238e+08 | D19: =N18+N27 -> 60772462 | E19: =O18 -> 2.8688476e+08 | F19: =AVERAGE(B18,B19) -> 4.8691898e+08 | G19: =N18+N17+N27+N26 -> 1.5740552e+08 | H19: =G19/F19 -> 0.3232684
A20: 46752 | B20: =L28 -> 4.1519779e+08 | D20: =N28 -> 24911868
A21: 46934 | B21: =L29 -> 4.1519779e+08 | D21: =N29 -> 24911868 | F21: =AVERAGE(B20,B21) -> 4.1519779e+08 | G21: =N29+N28 -> 49823735 | H21: =G21/F21 -> 0.12
A22: 47118 | B22: =L30 -> 4.1519779e+08 | D22: =N30 -> 24911868 | K22: Crédito Renovable | L22: deuda | M22: amortización | N22: interés | O22: amortización | P22: interés | Q22: Cuota Semestral
A23: 47299 | B23: =L31 -> 4.1519779e+08 | D23: =N31 -> 24911868 | F23: =AVERAGE(B22,B23) -> 4.1519779e+08 | G23: =N30+N31 -> 49823735 | H23: =G23/F23 -> 0.12 | K23: Activo de Trabajo | M23: semestral | N23: semestral | O23: anual | P23: anual
A24: 47483 | B24: =L32 -> 4.1519779e+08 | D24: =N32 -> 24911868 | L24: =D5 -> 4.1519779e+08
A25: 47664 | B25: =L33 -> 4.1519779e+08 | D25: =N33 -> 24911868 | F25: =AVERAGE(B24,B25) -> 4.1519779e+08 | G25: =N31+N32 -> 49823735 | H25: =G25/F25 -> 0.12 | J25: 1 | K25: 46203 | L25: =L24 -> 4.1519779e+08 | M25: - | N25: =L24*(InfoInicial!$B$39/2) -> 24911868 | O25: - | Q25: =N25 -> 24911868
A26: 47848 | B26: =L34 -> 4.1519779e+08 | D26: =N34 -> 24911868 | J26: 1 | K26: 46387 | L26: =L25 -> 4.1519779e+08 | M26: - | N26: =L25*(InfoInicial!$B$39/2) -> 24911868 | O26: - | P26: =N25+N26 -> 49823735 | Q26: =N26 -> 24911868
A27: 48029 | B27: =L35 -> 4.1519779e+08 | D27: =N35 -> 24911868 | F27: =AVERAGE(B26,B27) -> 4.1519779e+08 | G27: =N34+N33 -> 49823735 | H27: =G27/F27 -> 0.12 | J27: 2 | K27: 46568 | L27: =L26 -> 4.1519779e+08 | M27: - | N27: =L26*(InfoInicial!$B$39/2) -> 24911868 | O27: - | Q27: =N27 -> 24911868
A28: 48213 | B28: =L36 -> 4.1519779e+08 | D28: =N36 -> 24911868 | J28: 2 | K28: 46752 | L28: =L27 -> 4.1519779e+08 | M28: - | N28: =L27*(InfoInicial!$B$39/2) -> 24911868 | O28: - | P28: =N27+N28 -> 49823735 | Q28: =N28 -> 24911868
A29: 48395 | B29: =L37 -> 4.1519779e+08 | D29: =N37 -> 24911868 | F29: =AVERAGE(B28,B29) -> 4.1519779e+08 | G29: =N36+N35 -> 49823735 | H29: =G29/F29 -> 0.12 | J29: 3 | K29: 46934 | L29: =L28 -> 4.1519779e+08 | M29: - | N29: =L28*(InfoInicial!$B$39/2) -> 24911868 | O29: - | Q29: =N29 -> 24911868
A30: 48579 | B30: =L38 -> 4.1519779e+08 | D30: =N38 -> 24911868 | J30: 3 | K30: 47118 | L30: =L29 -> 4.1519779e+08 | M30: - | N30: =L29*(InfoInicial!$B$39/2) -> 24911868 | O30: - | P30: =N29+N30 -> 49823735 | Q30: =N30 -> 24911868
A31: 48760 | B31: =L39 -> 4.1519779e+08 | D31: =N39 -> 24911868 | F31: =AVERAGE(B30,B31) -> 4.1519779e+08 | G31: =N37+N38 -> 49823735 | H31: =G31/F31 -> 0.12 | J31: 4 | K31: 47299 | L31: =L30 -> 4.1519779e+08 | M31: - | N31: =L30*(InfoInicial!$B$39/2) -> 24911868 | O31: - | Q31: =N31 -> 24911868
A32: 48944 | B32: =L40 -> 4.1519779e+08 | D32: =N40 -> 24911868 | J32: 4 | K32: 47483 | L32: =L31 -> 4.1519779e+08 | M32: - | N32: =L31*(InfoInicial!$B$39/2) -> 24911868 | O32: - | P32: =N31+N32 -> 49823735 | Q32: =N32 -> 24911868
A33: 49125 | B33: =L41 -> 4.1519779e+08 | D33: =N41 -> 24911868 | F33: =AVERAGE(B32,B33) -> 4.1519779e+08 | G33: =N39+N40 -> 49823735 | H33: =G33/F33 -> 0.12 | J33: 5 | K33: 47664 | L33: =L32 -> 4.1519779e+08 | M33: - | N33: =L32*(InfoInicial!$B$39/2) -> 24911868 | O33: - | Q33: =N33 -> 24911868
A34: 49309 | B34: =L42 -> 4.1519779e+08 | D34: =N42 -> 24911868 | J34: 5 | K34: 47848 | L34: =L33 -> 4.1519779e+08 | M34: - | N34: =L33*(InfoInicial!$B$39/2) -> 24911868 | O34: - | P34: =N33+N34 -> 49823735 | Q34: =N34 -> 24911868
A35: 49490 | B35: =L43 -> 4.1519779e+08 | D35: =N43 -> 24911868 | F35: =AVERAGE(B34,B35) -> 4.1519779e+08 | G35: =N41+N42 -> 49823735 | H35: =G35/F35 -> 0.12 | J35: 6 | K35: 48029 | L35: =L34 -> 4.1519779e+08 | M35: - | N35: =L34*(InfoInicial!$B$39/2) -> 24911868 | O35: - | Q35: =N35 -> 24911868
A36: 49674 | B36: =L44 -> 4.1519779e+08 | D36: =N44 -> 24911868 | J36: 6 | K36: 48213 | L36: =L35 -> 4.1519779e+08 | M36: - | N36: =L35*(InfoInicial!$B$39/2) -> 24911868 | O36: - | P36: =N35+N36 -> 49823735 | Q36: =N36 -> 24911868
A37: Totales: | B37: =SUM(B17:B36,B12:B14) -> 1.0455592e+10 | C37: =SUM(C17:C36,C12:C14) -> 8.6065427e+08 | D37: =SUM(D17:D36,D12:D14) -> 1.2513098e+09 | E37: =E13+E17+E19 -> 8.6065427e+08 | J37: 7 | K37: 48395 | L37: =L36 -> 4.1519779e+08 | M37: - | N37: =L36*(InfoInicial!$B$39/2) -> 24911868 | O37: - | Q37: =N37 -> 24911868
J38: 7 | K38: 48579 | L38: =L37 -> 4.1519779e+08 | M38: - | N38: =L37*(InfoInicial!$B$39/2) -> 24911868 | O38: - | P38: =N37+N38 -> 49823735 | Q38: =N38 -> 24911868
J39: 8 | K39: 48760 | L39: =L38 -> 4.1519779e+08 | M39: - | N39: =L38*(InfoInicial!$B$39/2) -> 24911868 | O39: - | Q39: =N39 -> 24911868
J40: 8 | K40: 48944 | L40: =L39 -> 4.1519779e+08 | M40: - | N40: =L39*(InfoInicial!$B$39/2) -> 24911868 | O40: - | P40: =N39+N40 -> 49823735 | Q40: =N40 -> 24911868
J41: 9 | K41: 49125 | L41: =L40 -> 4.1519779e+08 | M41: - | N41: =L40*(InfoInicial!$B$39/2) -> 24911868 | O41: - | Q41: =N41 -> 24911868
J42: 9 | K42: 49309 | L42: =L41 -> 4.1519779e+08 | M42: - | N42: =L41*(InfoInicial!$B$39/2) -> 24911868 | O42: - | P42: =N41+N42 -> 49823735 | Q42: =N42 -> 24911868
J43: 10 | K43: 49490 | L43: =L42 -> 4.1519779e+08 | M43: - | N43: =L42*(InfoInicial!$B$39/2) -> 24911868 | O43: - | Q43: =N43 -> 24911868
J44: 10 | K44: 49674 | L44: =L43 -> 4.1519779e+08 | N44: =L43*(InfoInicial!$B$39/2) -> 24911868 | O44: - | P44: =N43+N44 -> 49823735 | Q44: =N44 -> 24911868

Sheet DF-CRes
A1: CUADRO DE RESULTADOS PROFORMA
A2: Rubros | B2: Año 1 | C2: Año 2 | D2: Año 3 | E2: Año 4 | F2: Año 5 | G2: Año 6 | H2: Año 7 | I2: Año 8 | J2: Año 9 | K2: Año 10 | L2: Totales
A3: Ventas netas | B3: ='DE-Costos'!B94 -> 1974375000 | C3: ='DE-Costos'!C94 -> 2925000000 | D3: ='DE-Costos'!D94 -> 2925000000 | E3: ='DE-Costos'!E94 -> 2925000000 | F3: ='DE-Costos'!F94 -> 2925000000 | G3: ='DE-Costos'!G94 -> 2925000000 | H3: ='DE-Costos'!H94 -> 2925000000 | I3: ='DE-Costos'!I94 -> 2925000000 | ... K3: ='DE-Costos'!K94 -> 2925000000 | L3: =SUM(B3:K3) -> 28299375000
A4: (-) Costo de producción de lo Vendido | B4: ='DE-Costos'!B118 -> 9.6243727e+08 | C4: ='DE-Costos'!C118 -> 1.3529165e+09 | D4: ='DE-Costos'!D118 -> 1.3504632e+09 | E4: ='DE-Costos'!E118 -> 1.350009e+09 | F4: ='DE-Costos'!F118 -> 1.350009e+09 | G4: ='DE-Costos'!G118 -> 1.350009e+09 | H4: ='DE-Costos'!H118 -> 1.350009e+09 | I4: ='DE-Costos'!I118 -> 1.350009e+09 | ... K4: ='DE-Costos'!K118 -> 1.350009e+09 | L4: =SUM(B4:K4) -> 1.311588e+10
A5: Resultado operativo | B5: =B3-B4 -> 1.0119377e+09 | C5: =C3-C4 -> 1.5720835e+09 | D5: =D3-D4 -> 1.5745368e+09 | E5: =E3-E4 -> 1.574991e+09 | F5: =F3-F4 -> 1.574991e+09 | G5: =G3-G4 -> 1.574991e+09 | H5: =H3-H4 -> 1.574991e+09 | I5: =I3-I4 -> 1.574991e+09 | ... K5: =K3-K4 -> 1.574991e+09 | L5: =SUM(B5:K5) -> 1.5183495e+10
A6: Menos: | L6: =SUM(B6:K6) -> 0
A7: Gastos de Administración | B7: ='DE-Costos'!B115 -> 1.0363344e+08 | C7: ='DE-Costos'!C115 -> 1.0363344e+08 | D7: ='DE-Costos'!D115 -> 1.0363344e+08 | E7: ='DE-Costos'!E115 -> 1.0363344e+08 | F7: ='DE-Costos'!F115 -> 1.0363344e+08 | G7: ='DE-Costos'!G115 -> 1.0363344e+08 | H7: ='DE-Costos'!H115 -> 1.0363344e+08 | I7: ='DE-Costos'!I115 -> 1.0363344e+08 | ... K7: ='DE-Costos'!K115 -> 1.0363344e+08 | L7: =SUM(B7:K7) -> 1.0363344e+09
A8: Gastos de Comercialización | B8: ='DE-Costos'!B116 -> 58367425 | C8: ='DE-Costos'!C116 -> 58367425 | D8: ='DE-Costos'!D116 -> 58367425 | E8: ='DE-Costos'!E116 -> 58367425 | F8: ='DE-Costos'!F116 -> 58367425 | G8: ='DE-Costos'!G116 -> 58367425 | H8: ='DE-Costos'!H116 -> 58367425 | I8: ='DE-Costos'!I116 -> 58367425 | ... K8: ='DE-Costos'!K116 -> 58367425 | L8: =SUM(B8:K8) -> 5.8367425e+08
A9: Gastos Financieros | B9: =H21 -> 6.2933094e+08 | C9: =H22 -> 4.8588856e+08 | D9: =H23 -> 3.4244619e+08 | E9: =H24 -> 49823735 | F9: =H25 -> 49823735 | G9: =H26 -> 49823735 | H9: =H27 -> 49823735 | I9: =H28 -> 49823735 | J9: =H29 -> 49823735 | K9: =H30 -> 49823735 | L9: =SUM(B9:K9) -> 1.8064318e+09
A10: RESULTADO (a/Hon. e Imp.) | B10: =B5-(B7+B8+B9) -> 2.2060592e+08 | C10: =C5-(C7+C8+C9) -> 9.2419408e+08 | D10: =D5-(D7+D8+D9) -> 1.0700898e+09 | E10: =E5-(E7+E8+E9) -> 1.3631664e+09 | F10: =F5-(F7+F8+F9) -> 1.3631664e+09 | G10: =G5-(G7+G8+G9) -> 1.3631664e+09 | H10: =H5-(H7+H8+H9) -> 1.3631664e+09 | I10: =I5-(I7+I8+I9) -> 1.3631664e+09 | ... K10: =K5-(K7+K8+K9) -> 1.3631664e+09 | L10: =SUM(B10:K10) -> 1.1757055e+10
A11: Menos: Honorarios al Direct. | B11: ='DE-Form'!E4 -> 0 | C11: ='DE-Form'!E5 -> 0 | D11: ='DE-Form'!E6 -> 0 | E11: ='DE-Form'!E7 -> 0 | F11: ='DE-Form'!E8 -> 0 | G11: ='DE-Form'!E9 -> 0 | H11: ='DE-Form'!E10 -> 0 | I11: ='DE-Form'!E11 -> 0 | J11: ='DE-Form'!E12 -> 0 | K11: ='DE-Form'!E13 -> 0 | L11: =SUM(B11:K11) -> 0
A12: Menos: Impuesto a la Ganancia | B12: =(B10-B11)*InfoInicial!$B$3 -> 77212070 | C12: =(C10-C11)*InfoInicial!$B$3 -> 3.2346793e+08 | D12: =(D10-D11)*InfoInicial!$B$3 -> 3.7453142e+08 | E12: =(E10-E11)*InfoInicial!$B$3 -> 4.7710825e+08 | F12: =(F10-F11)*InfoInicial!$B$3 -> 4.7710825e+08 | G12: =(G10-G11)*InfoInicial!$B$3 -> 4.7710825e+08 | H12: =(H10-H11)*InfoInicial!$B$3 -> 4.7710825e+08 | I12: =(I10-I11)*InfoInicial!$B$3 -> 4.7710825e+08 | ... L12: =(L10-L11)*InfoInicial!$B$3 -> 4.1149692e+09
A13: RESULTADO (d/Hon. e Imp.) | B13: =B10-B12 -> 1.4339384e+08 | C13: =C10-C12 -> 6.0072615e+08 | D13: =D10-D12 -> 6.9555834e+08 | E13: =E10-E12 -> 8.8605818e+08 | F13: =F10-F12 -> 8.8605818e+08 | G13: =G10-G12 -> 8.8605818e+08 | H13: =H10-H12 -> 8.8605818e+08 | I13: =I10-I12 -> 8.8605818e+08 | ... K13: =K10-K12 -> 8.8605818e+08 | L13: =SUM(B13:K13) -> 7.6420856e+09 | M13: = BN Inversor
A19: Año | B19: Am Int. y g op. | D19: Intereses Créd NO Renov | F19: Intereses Créd Renov | H19: TOTAL GASTO FINANCIERO
A21: 1 | B21: =('DF-Cred'!$M$6)/3 -> 1.8504067e+08 | D21: ='DF-Cred'!P14 -> 3.9446654e+08 | F21: ='DF-Cred'!P26 -> 49823735 | H21: =B21+D21+F21 -> 6.2933094e+08
A22: 2 | B22: =('DF-Cred'!$M$6)/3 -> 1.8504067e+08 | D22: ='DF-Cred'!P16 -> 2.5102416e+08 | F22: ='DF-Cred'!P28 -> 49823735 | H22: =B22+D22+F22 -> 4.8588856e+08
A23: 3 | B23: =('DF-Cred'!$M$6)/3 -> 1.8504067e+08 | D23: ='DF-Cred'!P18 -> 1.0758178e+08 | F23: ='DF-Cred'!P30 -> 49823735 | H23: =B23+D23+F23 -> 3.4244619e+08
A24: 4 | F24: ='DF-Cred'!P32 -> 49823735 | H24: =B24+D24+F24 -> 49823735
A25: 5 | F25: ='DF-Cred'!P34 -> 49823735 | H25: =B25+D25+F25 -> 49823735
A26: 6 | F26: ='DF-Cred'!P36 -> 49823735 | H26: =B26+D26+F26 -> 49823735
A27: 7 | F27: ='DF-Cred'!P38 -> 49823735 | H27: =B27+D27+F27 -> 49823735
A28: 8 | F28: ='DF-Cred'!P40 -> 49823735 | H28: =B28+D28+F28 -> 49823735
A29: 9 | F29: ='DF-Cred'!P42 -> 49823735 | H29: =B29+D29+F29 -> 49823735
A30: 10 | F30: ='DF-Cred'!P44 -> 49823735 | H30: =B30+D30+F30 -> 49823735
A31: Total | B31: =SUM(B21:C30) -> 5.55122e+08 | D31: =SUM(D21:E30) -> 7.5307248e+08 | F31: =SUM(F21:G30) -> 4.9823735e+08 | H31: =SUM(H21:I30) -> 1.8064318e+09
E35: =B31+F31 -> 1.0533594e+09

Sheet DF-IVA
A1: IVA plan de Explotación, Cancelación del Credito Fiscal y pago al Fisco por IVA
B2: TOTALES PARA LAS TRES AREAS
A3: Rubros | B3: Año 0 | C3: Año 1 | D3: Año 2 | E3: Año 3 | F3: Año 4 | G3: Año 5 | H3: Año 6 | I3: Año 7 | J3: Año 8 | K3: Año 9 | L3: Año 10
A4: a) IVA pagado en el Costo Total de lo Vendido:
A5: Total pagado en el Area de Producción | B5: 0 | C5: ='DE-IVA '!C16 -> 1.2283791e+08 | D5: ='DE-IVA '!D16 -> 1.6892225e+08 | E5: ='DE-IVA '!E16 -> 1.6901764e+08 | F5: ='DE-IVA '!F16 -> 1.6901764e+08 | G5: ='DE-IVA '!G16 -> 1.6901764e+08 | H5: ='DE-IVA '!H16 -> 1.6901764e+08 | I5: ='DE-IVA '!I16 -> 1.6901764e+08 | J5: ='DE-IVA '!J16 -> 1.6901764e+08 | ... L5: ='DE-IVA '!L16 -> 1.6901764e+08
A6: Total pagado en el Area Administrativa | B6: 0 | C6: ='DE-IVA '!C17 -> 6149909.7 | D6: ='DE-IVA '!D17 -> 6149909.7 | E6: ='DE-IVA '!E17 -> 6149909.7 | F6: ='DE-IVA '!F17 -> 6149909.7 | G6: ='DE-IVA '!G17 -> 6149909.7 | H6: ='DE-IVA '!H17 -> 6149909.7 | I6: ='DE-IVA '!I17 -> 6149909.7 | J6: ='DE-IVA '!J17 -> 6149909.7 | ... L6: ='DE-IVA '!L17 -> 6149909.7
A7: Total pagado en el Area Comercial | B7: 0 | C7: ='DE-IVA '!C18 -> 6149909.7 | D7: ='DE-IVA '!D18 -> 6149909.7 | E7: ='DE-IVA '!E18 -> 6149909.7 | F7: ='DE-IVA '!F18 -> 6149909.7 | G7: ='DE-IVA '!G18 -> 6149909.7 | H7: ='DE-IVA '!H18 -> 6149909.7 | I7: ='DE-IVA '!I18 -> 6149909.7 | J7: ='DE-IVA '!J18 -> 6149909.7 | ... L7: ='DE-IVA '!L18 -> 6149909.7
A8: Total pagado por Financiación | B8: 0 | C8: =0.21*('DF-CRes'!D21+'DF-CRes'!F21) -> 93300958 | D8: =0.21*('DF-CRes'!D22+'DF-CRes'!F22) -> 63178058 | E8: =0.21*('DF-CRes'!D23+'DF-CRes'!F23) -> 33055159 | F8: =0.21*('DF-CRes'!D24+'DF-CRes'!F24) -> 10462984 | G8: =0.21*('DF-CRes'!D25+'DF-CRes'!F25) -> 10462984 | H8: =0.21*('DF-CRes'!D26+'DF-CRes'!F26) -> 10462984 | I8: =0.21*('DF-CRes'!D27+'DF-CRes'!F27) -> 10462984 | J8: =0.21*('DF-CRes'!D28+'DF-CRes'!F28) -> 10462984 | K8: =0.21*('DF-CRes'!D29+'DF-CRes'!F29) -> 10462984 | L8: =0.21*('DF-CRes'!D30+'DF-CRes'!F30) -> 10462984
A9: IVA abonado en Costo Total de lo Vendido: | B9: =SUM(B5:B8) -> 0 | C9: =SUM(C5:C8) -> 2.2843869e+08 | D9: =SUM(D5:D8) -> 2.4440013e+08 | E9: =SUM(E5:E8) -> 2.1437262e+08 | F9: =SUM(F5:F8) -> 1.9178044e+08 | G9: =SUM(G5:G8) -> 1.9178044e+08 | H9: =SUM(H5:H8) -> 1.9178044e+08 | I9: =SUM(I5:I8) -> 1.9178044e+08 | ... L9: =SUM(L5:L8) -> 1.9178044e+08
A11: IVA total abonado por insumos | B11: ='DE-IVA '!B20 -> 0 | C11: ='DE-IVA '!C20 -> 1.3513773e+08 | D11: ='DE-IVA '!D20 -> 1.8122207e+08 | E11: ='DE-IVA '!E20 -> 1.8131746e+08 | F11: ='DE-IVA '!F20 -> 1.8131746e+08 | G11: ='DE-IVA '!G20 -> 1.8131746e+08 | H11: ='DE-IVA '!H20 -> 1.8131746e+08 | I11: ='DE-IVA '!I20 -> 1.8131746e+08 | ... L11: ='DE-IVA '!L20 -> 1.8131746e+08
A12: IVA total cobrado por ventas | B12: ='DE-IVA '!B21 -> 0 | C12: ='DE-IVA '!C21 -> 414618750 | D12: ='DE-IVA '!D21 -> 614250000 | E12: ='DE-IVA '!E21 -> 614250000 | F12: ='DE-IVA '!F21 -> 614250000 | G12: ='DE-IVA '!G21 -> 614250000 | H12: ='DE-IVA '!H21 -> 614250000 | I12: ='DE-IVA '!I21 -> 614250000 | ... L12: ='DE-IVA '!L21 -> 614250000
A13: b) IVA diferencia | B13: =B12-B11 -> 0 | C13: =C12-C11 -> 2.7948102e+08 | D13: =D12-D11 -> 4.3302793e+08 | E13: =E12-E11 -> 4.3293254e+08 | F13: =F12-F11 -> 4.3293254e+08 | G13: =G12-G11 -> 4.3293254e+08 | H13: =H12-H11 -> 4.3293254e+08 | I13: =I12-I11 -> 4.3293254e+08 | ... L13: =L12-L11 -> 4.3293254e+08
A15: c) Crédito Fiscal Anterior (incrementado) | B15: 0 | C15: =B16 -> 7.6689002e+08 | D15: =C17 -> 6.637525e+08 | E15: =D17 -> 2.7256447e+08 | F15: ='DE-IVA '!F24 -> 0 | G15: ='DE-IVA '!G24 -> 0 | H15: ='DE-IVA '!H24 -> 0 | I15: ='DE-IVA '!I24 -> 0 | J15: ='DE-IVA '!J24 -> 0 | K15: ='DE-IVA '!K24 -> 0 | L15: ='DE-IVA '!L24 -> 0
A16: d) Crédito Fiscal del Año (incrementado) | B16: ='DF-2 Estructura'!B8+'DF-2 Estructura'!B20 -> 7.6689002e+08 | C16: ='DF-2 Estructura'!C8+'DF-2 Estructura'!C20 -> 1.7634349e+08 | D16: ='DE-IVA '!D25 -> 41839897 | E16: ='DE-IVA '!E25 -> 0 | F16: ='DE-IVA '!F25 -> 0 | G16: ='DE-IVA '!G25 -> 0 | H16: ='DE-IVA '!H25 -> 0 | I16: ='DE-IVA '!I25 -> 0 | J16: ='DE-IVA '!J25 -> 0 | K16: ='DE-IVA '!K25 -> 0 | L16: ='DE-IVA '!L25 -> 0
A17: e) Crédito Fiscal Final Año | B17: =B16 -> 7.6689002e+08 | C17: =C16+C15-C13 -> 6.637525e+08 | D17: =D16+D15-D13 -> 2.7256447e+08
A18: f) Recupero Credito Fiscal | C18: =C15+C16-C17 -> 2.7948102e+08 | D18: =D15+D16-D17 -> 4.3302793e+08 | E18: =E15 -> 2.7256447e+08 | F18: =F15 -> 0 | G18: =G15 -> 0 | H18: =H15 -> 0 | I18: =I15 -> 0 | J18: =J15 -> 0 | K18: =K15 -> 0 | L18: =L15 -> 0
A20: Pago al Fisco por IVA | E20: =E13-E18 -> 1.6036807e+08

Sheet DF- CFyU
A3: CUADRO DE FUENTES Y USOS
B4: Año 0 | C4: Año 1 | D4: Año 2 | E4: Año 3 | F4: Año 4 | G4: Año 5 | H4: Año 6 | I4: Año 7 | J4: Año 8 | K4: Año 9 | L4: Año 10 | M4: Totales
A5: FUENTES: Totales | B5: =SUM(B6:B12) -> 4.4187473e+09 | C5: =SUM(C6:C12) -> 3.2699304e+09 | D5: =SUM(D6:D12) -> 4.0946931e+09 | E5: =SUM(E6:E12) -> 4.8034736e+09 | F5: =SUM(F6:F12) -> 5.5761845e+09 | G5: =SUM(G6:G12) -> 6.6406789e+09 | H5: =SUM(H6:H12) -> 7.7051485e+09 | I5: =SUM(I6:I12) -> 8.5997724e+09 | ... L5: =SUM(L6:L12) -> 1.1283691e+10 | M5: =SUM(B5:L5) -> 7.6275783e+10
A6: Saldo ejercicio anterior | B6: 0 | C6: =B28 -> 0 | D6: =C28 -> 7.366652e+08 | E6: =D28 -> 1.6059091e+09 | F6: =E28 -> 2.6511845e+09 | G6: =F28 -> 3.7156789e+09 | H6: =G28 -> 4.7801485e+09 | I6: =H28 -> 5.6747724e+09 | J6: =I28 -> 6.5694119e+09 | ... L6: =K28 -> 8.3586907e+09 | M6: =SUM(B6:L6) -> 4.1556513e+10
A7: Aporte de capital propio | B7: ='DF-2 Estructura'!B30 -> 3.558093e+09 | C7: ='DF-2 Estructura'!C30 -> 6.0087661e+08 | D7: 0 | E7: 0 | F7: 0 | G7: 0 | H7: 0 | I7: 0 | J7: 0 | K7: 0 | L7: 0 | M7: =SUM(B7:L7) -> 4.1589696e+09
A8: Créditos renovables | B8: ='DF-2 Estructura'!B28 -> 0 | C8: ='DF-2 Estructura'!C28 -> 4.1519779e+08 | D8: 0 | E8: 0 | F8: 0 | G8: 0 | H8: 0 | I8: 0 | J8: 0 | K8: 0 | L8: 0 | M8: =SUM(B8:L8) -> 4.1519779e+08
A9: Créditos no renovables | B9: ='DF-2 Estructura'!B29 -> 8.6065427e+08 | C9: ='DF-2 Estructura'!C29 -> 0 | D9: 0 | E9: 0 | F9: 0 | G9: 0 | H9: 0 | I9: 0 | J9: 0 | K9: 0 | L9: 0 | M9: =SUM(B9:L9) -> 8.6065427e+08
A10: Ventas del ejercicio | B10: 0 | C10: ='DF-CRes'!B3 -> 1974375000 | D10: ='DF-CRes'!C3 -> 2925000000 | E10: ='DF-CRes'!D3 -> 2925000000 | F10: ='DF-CRes'!E3 -> 2925000000 | G10: ='DF-CRes'!F3 -> 2925000000 | H10: ='DF-CRes'!G3 -> 2925000000 | I10: ='DF-CRes'!H3 -> 2925000000 | J10: ='DF-CRes'!I3 -> 2925000000 | ... L10: ='DF-CRes'!K3 -> 2925000000 | M10: =SUM(B10:L10) -> 28299375000
A11: Recupero Crédito Fiscal | B11: 0 | C11: ='DF-IVA'!C18 -> 2.7948102e+08 | D11: ='DF-IVA'!D18 -> 4.3302793e+08 | E11: ='DF-IVA'!E18 -> 2.7256447e+08 | F11: ='DF-IVA'!F18 -> 0 | G11: ='DF-IVA'!G18 -> 0 | H11: ='DF-IVA'!H18 -> 0 | I11: ='DF-IVA'!I18 -> 0 | J11: ='DF-IVA'!J18 -> 0 | ... L11: ='DF-IVA'!L18 -> 0 | M11: =SUM(B11:L11) -> 9.8507341e+08
A12: Otros ingresos | B12: 0 | C12: 0 | D12: 0 | E12: 0 | F12: 0 | G12: 0 | H12: 0 | I12: 0 | J12: 0 | K12: 0 | L12: 0 | M12: =SUM(B12:L12) -> 0
A14: USOS: Totales | B14: =SUM(B15:B23) -> 4.4187473e+09 | C14: =SUM(C15:C23) -> 2.8967173e+09 | D14: =SUM(D15:D23) -> 2.8522361e+09 | E14: =SUM(E15:E23) -> 2.5157411e+09 | F14: =SUM(F15:F23) -> 2.038917e+09 | G14: =SUM(G15:G23) -> 2.0389418e+09 | H14: =SUM(H15:H23) -> 2.0389573e+09 | I14: =SUM(I15:I23) -> 2.0389418e+09 | ... L14: =SUM(L15:L23) -> 2.0389418e+09 | M14: =SUM(B14:L14) -> 2.6956025e+10
A15: Activo Fijo | B15: ='DF-2 Estructura'!B7 -> 3.4146342e+09 | C15: ='DF-2 Estructura'!C7 -> 9335324.3 | D15: 0 | E15: 0 | F15: 0 | G15: 0 | H15: 0 | I15: 0 | J15: 0 | K15: 0 | L15: 0 | M15: =SUM(B15:L15) -> 3.4239696e+09
A16: Activo de Trabajo | B16: ='DE-InvAT'!B23 -> 2.3722302e+08 | C16: ='DE-InvAT'!C23 -> 5.9317256e+08 | D16: ='DE-InvAT'!D23 -> 1.992376e+08 | E16: ='DE-InvAT'!E23 -> -585291.42 | F16: ='DE-InvAT'!F23 -> -24842.929 | G16: ='DE-InvAT'!G23 -> 0 | H16: ='DE-InvAT'!H23 -> 15509.603 | I16: ='DE-InvAT'!I23 -> 0 | ... L16: ='DE-InvAT'!L23 -> 0 | M16: =SUM(B16:L16) -> 1.0290386e+09
A17: Costo de lo Vendido | B17: 0 | C17: ='DF-CRes'!B4+'DF-CRes'!B7+'DF-CRes'!B8+'DF-CRes'!B9 -> 1.7537691e+09 | D17: ='DF-CRes'!C4+'DF-CRes'!C7+'DF-CRes'!C8+'DF-CRes'!C9 -> 2.0008059e+09 | E17: ='DF-CRes'!D4+'DF-CRes'!D7+'DF-CRes'!D8+'DF-CRes'!D9 -> 1.8549102e+09 | F17: ='DF-CRes'!E4+'DF-CRes'!E7+'DF-CRes'!E8+'DF-CRes'!E9 -> 1.5618336e+09 | G17: ='DF-CRes'!F4+'DF-CRes'!F7+'DF-CRes'!F8+'DF-CRes'!F9 -> 1.5618336e+09 | H17: ='DF-CRes'!G4+'DF-CRes'!G7+'DF-CRes'!G8+'DF-CRes'!G9 -> 1.5618336e+09 | I17: ='DF-CRes'!H4+'DF-CRes'!H7+'DF-CRes'!H8+'DF-CRes'!H9 -> 1.5618336e+09 | J17: ='DF-CRes'!I4+'DF-CRes'!I7+'DF-CRes'!I8+'DF-CRes'!I9 -> 1.5618336e+09 | ... L17: ='DF-CRes'!K4+'DF-CRes'!K7+'DF-CRes'!K8+'DF-CRes'!K9 -> 1.5618336e+09 | M17: =SUM(B17:L17) -> 1.654232e+10
A18: Impuesto a la Ganancia | B18: 0 | C18: ='DF-CRes'!B12 -> 77212070 | D18: ='DF-CRes'!C12 -> 3.2346793e+08 | E18: ='DF-CRes'!D12 -> 3.7453142e+08 | F18: ='DF-CRes'!E12 -> 4.7710825e+08 | G18: ='DF-CRes'!F12 -> 4.7710825e+08 | H18: ='DF-CRes'!G12 -> 4.7710825e+08 | I18: ='DF-CRes'!H12 -> 4.7710825e+08 | J18: ='DF-CRes'!I12 -> 4.7710825e+08 | ... L18: ='DF-CRes'!K12 -> 4.7710825e+08 | M18: =SUM(B18:L18) -> 4.1149692e+09
A19: Cancelación de deudas | C19: ='DF-Cred'!O14 -> 2.8688476e+08 | D19: ='DF-Cred'!O16 -> 2.8688476e+08 | E19: ='DF-Cred'!O18 -> 2.8688476e+08 | M19: =SUM(B19:L19) -> 8.6065427e+08
A20: Honorarios del Directorio | B20: 0 | C20: 0 | D20: 0 | E20: 0 | F20: 0 | G20: 0 | H20: 0 | I20: 0 | J20: 0 | K20: 0 | L20: 0 | M20: =SUM(B20:L20) -> 0
A21: Dividendos en efectivo | B21: 0 | C21: 0 | D21: 0 | E21: 0 | F21: 0 | G21: 0 | H21: 0 | I21: 0 | J21: 0 | K21: 0 | L21: 0 | M21: =SUM(B21:L21) -> 0
A22: IVA inversión | B22: ='DF-IVA'!B16 -> 7.6689002e+08 | C22: ='DF-IVA'!C16 -> 1.7634349e+08 | D22: ='DF-IVA'!D16 -> 41839897 | E22: ='DF-IVA'!E16 -> 0 | F22: ='DF-IVA'!F16 -> 0 | G22: ='DF-IVA'!G16 -> 0 | H22: ='DF-IVA'!H16 -> 0 | I22: ='DF-IVA'!I16 -> 0 | ... L22: ='DF-IVA'!L16 -> 0 | M22: =SUM(B22:L22) -> 9.8507341e+08
A23: Otros egresos | B23: 0 | C23: 0 | D23: 0 | E23: 0 | F23: 0 | G23: 0 | H23: 0 | I23: 0 | J23: 0 | K23: 0 | L23: 0 | M23: =SUM(B23:L23) -> 0
A25: FUENTES - USOS | B25: =B5-B14 -> 0 | C25: =C5-C14 -> 3.7321313e+08 | D25: =D5-D14 -> 1.242457e+09 | E25: =E5-E14 -> 2.2877324e+09 | F25: =F5-F14 -> 3.5372675e+09 | G25: =G5-G14 -> 4.6017371e+09 | H25: =H5-H14 -> 5.6661912e+09 | I25: =I5-I14 -> 6.5608306e+09 | ... L25: =L5-L14 -> 9.2447489e+09 | M25: =SUM(B25:L25) -> 4.9319758e+10
A26: Más: Amortizaciones del ejercicio | B26: 0 | C26: ='DE-Inv AF y Am'!D55+'DF-CRes'!B21 -> 3.6345207e+08 | D26: ='DE-Inv AF y Am'!D55+'DF-CRes'!B22 -> 3.6345207e+08 | E26: ='DE-Inv AF y Am'!D55+'DF-CRes'!B23 -> 3.6345207e+08 | F26: ='DE-Inv AF y Am'!E55+'DF-CRes'!B24 -> 1.784114e+08 | G26: ='DE-Inv AF y Am'!E55+'DF-CRes'!B25 -> 1.784114e+08 | H26: ='DE-Inv AF y Am'!F55+'DF-CRes'!B26 -> 8581250 | I26: ='DE-Inv AF y Am'!F55 -> 8581250 | J26: ='DE-Inv AF y Am'!F55 -> 8581250 | K26: ='DE-Inv AF y Am'!F55 -> 8581250 | L26: ='DE-Inv AF y Am'!F55 -> 8581250 | M26: =SUM(B26:L26) -> 1.4900853e+09
M27: =SUM(B27:L27) -> 0
A28: Saldo al ejercicio siguiente (acumulado) | B28: =B25+B26 -> 0 | C28: =C25+C26 -> 7.366652e+08 | D28: =D25+D26 -> 1.6059091e+09 | E28: =E25+E26 -> 2.6511845e+09 | F28: =F25+F26 -> 3.7156789e+09 | G28: =G25+G26 -> 4.7801485e+09 | H28: =H25+H26 -> 5.6747724e+09 | I28: =I25+I26 -> 6.5694119e+09 | ... L28: =L25+L26 -> 9.2533302e+09 | M28: =SUM(B28:L28) -> 5.0809843e+10
A29: Saldo Propio del Ejercicio | B29: =B28 -> 0 | C29: =C28-B28 -> 7.366652e+08 | D29: =D28-C28 -> 8.6924389e+08 | E29: =E28-D28 -> 1.0452754e+09 | F29: =F28-E28 -> 1.0644944e+09 | G29: =G28-F28 -> 1.0644696e+09 | H29: =H28-G28 -> 8.9462392e+08 | I29: =I28-H28 -> 8.9463943e+08 | J29: =J28-I28 -> 8.9463943e+08 | ... L29: =L28-K28 -> 8.9463943e+08 | M29: =SUM(B29:L29) -> 9.2533302e+09
B34: Valor Residual AF = | C34: =M15-M26 -> 1.9338843e+09
B35: BN Inversor = | C35: =M29-M7+M16+C34-M8 -> 7.6420856e+09

Sheet DF-Balance
B1: Mal BN inversor implícito
A3: BALANCES PROFORMAS
B4: Año 0 | C4: Año 1 | D4: Año 2 | E4: Año 3 | F4: Año 4 | G4: Año 5 | H4: Año 6 | I4: Año 7 | J4: Año 8 | K4: Año 9 | L4: Año 10
A5: ACTIVO CORRIENTE: Total | B5: =SUM(B7:B11) -> 2.3722302e+08 | C5: =SUM(C7:C11) -> 1.9332831e+09 | D5: =SUM(D7:D11) -> 3.1789285e+09 | E5: =SUM(E7:E11) -> 4.0632862e+09 | F5: =SUM(F7:F11) -> 4.8552162e+09 | G5: =SUM(G7:G11) -> 5.9196858e+09 | H5: =SUM(H7:H11) -> 6.8143097e+09 | I5: =SUM(I7:I11) -> 7.7089491e+09 | ... L5: =SUM(L7:L11) -> 1.0392867e+10
A6: Caja y Bancos:
A7: - mínimo | B7: ='DE-InvAT'!B4 -> 39487500 | C7: ='DE-InvAT'!C4 -> 58500000 | D7: ='DE-InvAT'!D4 -> 58500000 | E7: ='DE-InvAT'!E4 -> 58500000 | F7: ='DE-InvAT'!F4 -> 58500000 | G7: ='DE-InvAT'!G4 -> 58500000 | H7: ='DE-InvAT'!H4 -> 58500000 | I7: ='DE-InvAT'!I4 -> 58500000 | ... L7: ='DE-InvAT'!L4 -> 58500000
A8: - saldo acumulado de Fuentes y Usos | B8: ='DF- CFyU'!B28 -> 0 | C8: ='DF- CFyU'!C28 -> 7.366652e+08 | D8: ='DF- CFyU'!D28 -> 1.6059091e+09 | E8: ='DF- CFyU'!E28 -> 2.6511845e+09 | F8: ='DF- CFyU'!F28 -> 3.7156789e+09 | G8: ='DF- CFyU'!G28 -> 4.7801485e+09 | H8: ='DF- CFyU'!H28 -> 5.6747724e+09 | I8: ='DF- CFyU'!I28 -> 6.5694119e+09 | ... L8: ='DF- CFyU'!L28 -> 9.2533302e+09
A9: Crédito por ventas | B9: - | C9: ='DE-InvAT'!C5 -> 1.622774e+08 | D9: ='DE-InvAT'!D5 -> 2.4041096e+08 | E9: ='DE-InvAT'!E5 -> 2.4041096e+08 | F9: ='DE-InvAT'!F5 -> 2.4041096e+08 | G9: ='DE-InvAT'!G5 -> 2.4041096e+08 | H9: ='DE-InvAT'!H5 -> 2.4041096e+08 | I9: ='DE-InvAT'!I5 -> 2.4041096e+08 | J9: ='DE-InvAT'!J5 -> 2.4041096e+08 | ... L9: ='DE-InvAT'!L5 -> 2.4041096e+08
A10: Bienes de cambio | B10: ='DE-InvAT'!B7 -> 1.9773552e+08 | C10: ='DE-InvAT'!C7 -> 6.9635951e+08 | D10: ='DE-InvAT'!D7 -> 8.4108052e+08 | E10: ='DE-InvAT'!E7 -> 8.406263e+08 | F10: ='DE-InvAT'!F7 -> 8.406263e+08 | G10: ='DE-InvAT'!G7 -> 8.406263e+08 | H10: ='DE-InvAT'!H7 -> 8.406263e+08 | I10: ='DE-InvAT'!I7 -> 8.406263e+08 | ... L10: ='DE-InvAT'!L7 -> 8.406263e+08
A11: Crédito Fiscal | B11: - | C11: ='DF-IVA'!C18 -> 2.7948102e+08 | D11: ='DF-IVA'!D18 -> 4.3302793e+08 | E11: ='DF-IVA'!E18 -> 2.7256447e+08 | F11: ='DF-IVA'!F18 -> 0 | G11: ='DF-IVA'!G18 -> 0 | H11: ='DF-IVA'!H18 -> 0 | I11: ='DF-IVA'!I18 -> 0 | J11: ='DF-IVA'!J18 -> 0 | ... L11: ='DF-IVA'!L18 -> 0
A12: ACTIVO NO CORRIENTE: Total | B12: =B17+B22+B23 -> 3.9020432e+09 | C12: =C17+C22+C23 -> 3.2912421e+09 | D12: =D17+D22+D23 -> 2.6970654e+09 | E12: =E17+E22+E23 -> 2.3336134e+09 | F12: =F17+F22+F23 -> 2.1552019e+09 | G12: =G17+G22+G23 -> 1.9767905e+09 | H12: =H17+H22+H23 -> 1.9682093e+09 | I12: =I17+I22+I23 -> 1.959628e+09 | ... L12: =L17+L22+L23 -> 1.9338843e+09
A13: Cargos Diferidos:
A14: - valor inicial | B14: ='DF-2 Estructura'!B6 -> 5.7462746e+08 | C14: =B17 -> 5.7462746e+08 | D14: =C17 -> 3.9315396e+08 | E14: =D17 -> 2.0234514e+08 | F14: =E17 -> 11536314 | G14: =F17 -> 5768156.9 | H14: =G17 -> -2.2351742e-08 | I14: =H17 -> -2.2351742e-08 | J14: =I17 -> -2.2351742e-08 | ... L14: =K17 -> -2.2351742e-08
A15: más inversiones del ejercicio | B15: - | C15: ='DF-2 Estructura'!C6 -> 9335324.3
A16: menos amortizaciones del ejerc. | B16: - | C16: ='DE-Inv AF y Am'!D53+'DF-CRes'!B21 -> 1.9080882e+08 | D16: ='DE-Inv AF y Am'!D53+'DF-CRes'!B22 -> 1.9080882e+08 | E16: ='DE-Inv AF y Am'!D53+'DF-CRes'!B23 -> 1.9080882e+08 | F16: ='DE-Inv AF y Am'!E53+'DF-CRes'!B24 -> 5768156.9 | G16: ='DE-Inv AF y Am'!E53+'DF-CRes'!B25 -> 5768156.9 | H16: ='DE-Inv AF y Am'!F53+'DF-CRes'!B26 -> 0 | I16: ='DE-Inv AF y Am'!F53 -> 0 | J16: ='DE-Inv AF y Am'!F53 -> 0 | K16: ='DE-Inv AF y Am'!F53 -> 0 | L16: ='DE-Inv AF y Am'!F53 -> 0
A17: - valor final del ejercicio | B17: =B14 -> 5.7462746e+08 | C17: =C14+C15-C16 -> 3.9315396e+08 | D17: =D14+D15-D16 -> 2.0234514e+08 | E17: =E14+E15-E16 -> 11536314 | F17: =F14+F15-F16 -> 5768156.9 | G17: =G14+G15-G16 -> -2.2351742e-08 | H17: =H14+H15-H16 -> -2.2351742e-08 | I17: =I14+I15-I16 -> -2.2351742e-08 | J17: =J14+J15-J16 -> -2.2351742e-08 | ... L17: =L14+L15-L16 -> -2.2351742e-08
A18: Bienes de Uso
A19: - valor inicial | B19: ='DF-2 Estructura'!B5 -> 2.8400068e+09 | C19: =B22 -> 2.8400068e+09 | D19: =C22 -> 2.6673635e+09 | E19: =D22 -> 2.4947203e+09 | F19: =E22 -> 2.322077e+09 | G19: =F22 -> 2.1494338e+09 | H19: =G22 -> 1.9767905e+09 | I19: =H22 -> 1.9682093e+09 | J19: =I22 -> 1.959628e+09 | ... L19: =K22 -> 1.9424655e+09
A20: más inversiones del ejercicio
A21: menos amortizaciones del ejerc | B21: - | C21: ='DE-Inv AF y Am'!$D$51 -> 1.7264325e+08 | D21: ='DE-Inv AF y Am'!$D$51 -> 1.7264325e+08 | E21: ='DE-Inv AF y Am'!$D$51 -> 1.7264325e+08 | F21: ='DE-Inv AF y Am'!$E$51 -> 1.7264325e+08 | G21: ='DE-Inv AF y Am'!$E$51 -> 1.7264325e+08 | H21: ='DE-Inv AF y Am'!$F$51 -> 8581250 | I21: ='DE-Inv AF y Am'!$F$51 -> 8581250 | J21: ='DE-Inv AF y Am'!$F$51 -> 8581250 | K21: ='DE-Inv AF y Am'!$F$51 -> 8581250 | L21: ='DE-Inv AF y Am'!$F$51 -> 8581250
A22: - valor final del ejercicio | B22: =B19 -> 2.8400068e+09 | C22: =C19+C20-C21 -> 2.6673635e+09 | D22: =D19+D20-D21 -> 2.4947203e+09 | E22: =E19+E20-E21 -> 2.322077e+09 | F22: =F19+F20-F21 -> 2.1494338e+09 | G22: =G19+G20-G21 -> 1.9767905e+09 | H22: =H19+H20-H21 -> 1.9682093e+09 | I22: =I19+I20-I21 -> 1.959628e+09 | J22: =J19+J20-J21 -> 1.9510468e+09 | ... L22: =L19+L20-L21 -> 1.9338843e+09 | M22: = Valor Residual AF
A23: Crédito Fiscal | B23: ='DF-IVA'!C17-'DF-IVA'!C16 -> 4.8740901e+08 | C23: ='DF-IVA'!D17-'DF-IVA'!D16 -> 2.3072457e+08
A24: ACTIVO TOTAL: | B24: =B5+B12 -> 4.1392663e+09 | C24: =C5+C12 -> 5.2245252e+09 | D24: =D5+D12 -> 5.8759939e+09 | E24: =E5+E12 -> 6.3968996e+09 | F24: =F5+F12 -> 7.0104181e+09 | G24: =G5+G12 -> 7.8964763e+09 | H24: =H5+H12 -> 8.782519e+09 | I24: =I5+I12 -> 9.6685772e+09 | ... L24: =L5+L12 -> 1.2326752e+10
A25: PASIVO CORRIENTE: Total | B25: =B26+B27 -> 2.8688476e+08 | C25: =C26+C27 -> 7.0208255e+08 | D25: =D26+D27 -> 7.0208255e+08 | E25: =E26+E27 -> 4.1519779e+08 | F25: =F26+F27 -> 4.1519779e+08 | G25: =G26+G27 -> 4.1519779e+08 | H25: =H26+H27 -> 4.1519779e+08 | I25: =I26+I27 -> 4.1519779e+08 | ... L25: =L26+L27 -> 4.1519779e+08
A26: Deudas comerciales | C26: ='DF-Cred'!D5 -> 4.1519779e+08 | D26: =C26 -> 4.1519779e+08 | E26: =D26 -> 4.1519779e+08 | F26: =E26 -> 4.1519779e+08 | G26: =F26 -> 4.1519779e+08 | H26: =G26 -> 4.1519779e+08 | I26: =H26 -> 4.1519779e+08 | J26: =I26 -> 4.1519779e+08 | K26: =J26 -> 4.1519779e+08 | L26: =K26 -> 4.1519779e+08
A27: Deudas bancarias | B27: ='DF-Cred'!$E$19 -> 2.8688476e+08 | C27: ='DF-Cred'!$E$19 -> 2.8688476e+08 | D27: ='DF-Cred'!$E$19 -> 2.8688476e+08
A28: PASIVO NO CORRIENTE: Total
A29: Deudas bancarias | B29: ='DF-Cred'!E37-B27 -> 5.7376951e+08 | C29: =B29-C27 -> 2.8688476e+08 | D29: =C29-D27 -> 0 | E29: =D29-E27 -> 0 | F29: =E29-F27 -> 0 | G29: =F29-G27 -> 0 | H29: =G29-H27 -> 0 | I29: =H29-I27 -> 0 | J29: =I29-J27 -> 0 | ... L29: =K29-L27 -> 0
A30: PASIVO TOTAL: | B30: =B28+B25 -> 2.8688476e+08 | C30: =C28+C25 -> 7.0208255e+08 | D30: =D28+D25 -> 7.0208255e+08 | E30: =E28+E25 -> 4.1519779e+08 | F30: =F28+F25 -> 4.1519779e+08 | G30: =G28+G25 -> 4.1519779e+08 | H30: =H28+H25 -> 4.1519779e+08 | I30: =I28+I25 -> 4.1519779e+08 | ... L30: =L28+L25 -> 4.1519779e+08
A31: PATRIMONIO NETO: | B31: =B24-B30 -> 3.8523815e+09 | C31: =C24-C30 -> 4.5224426e+09 | D31: =D24-D30 -> 5.1739114e+09 | E31: =E24-E30 -> 5.9817018e+09 | F31: =F24-F30 -> 6.5952204e+09 | G31: =G24-G30 -> 7.4812785e+09 | H31: =H24-H30 -> 8.3673212e+09 | I31: =I24-I30 -> 9.2533794e+09 | ... L31: =L24-L30 -> 1.1911554e+10
A32: Capital societario | B32: ='DF-2 Estructura'!B30 -> 3.558093e+09 | C32: ='DF-2 Estructura'!$D$30 -> 4.1589696e+09 | D32: ='DF-2 Estructura'!$D$30 -> 4.1589696e+09 | E32: ='DF-2 Estructura'!$D$30 -> 4.1589696e+09 | F32: ='DF-2 Estructura'!$D$30 -> 4.1589696e+09 | G32: ='DF-2 Estructura'!$D$30 -> 4.1589696e+09 | H32: ='DF-2 Estructura'!$D$30 -> 4.1589696e+09 | I32: ='DF-2 Estructura'!$D$30 -> 4.1589696e+09 | J32: ='DF-2 Estructura'!$D$30 -> 4.1589696e+09 | ... L32: ='DF-2 Estructura'!$D$30 -> 4.1589696e+09
A33: Utilidad del ejercicio | C33: ='DF-CRes'!B13 -> 1.4339384e+08 | D33: ='DF-CRes'!C13 -> 6.0072615e+08 | E33: ='DF-CRes'!D13 -> 6.9555834e+08 | F33: ='DF-CRes'!E13 -> 8.8605818e+08 | G33: ='DF-CRes'!F13 -> 8.8605818e+08 | H33: ='DF-CRes'!G13 -> 8.8605818e+08 | I33: ='DF-CRes'!H13 -> 8.8605818e+08 | J33: ='DF-CRes'!I13 -> 8.8605818e+08 | ... L33: ='DF-CRes'!K13 -> 8.8605818e+08
A34: Utilidad acumulada | D34: =C33+C34 -> 1.4339384e+08 | E34: =D33+D34 -> 7.4412e+08 | F34: =E33+E34 -> 1.4396783e+09 | G34: =F33+F34 -> 2.3257365e+09 | H34: =G33+G34 -> 3.2117947e+09 | I34: =H33+H34 -> 4.0978529e+09 | J34: =I33+I34 -> 4.9839111e+09 | K34: =J33+J34 -> 5.8699693e+09 | L34: =K33+K34 -> 6.7560274e+09
A35: PASIVO + PATRIMONIO NETO | B35: =B31+B30 -> 4.1392663e+09 | C35: =C31+C30 -> 5.2245252e+09 | D35: =D31+D30 -> 5.8759939e+09 | E35: =E31+E30 -> 6.3968996e+09 | F35: =F31+F30 -> 7.0104181e+09 | G35: =G31+G30 -> 7.8964763e+09 | H35: =H31+H30 -> 8.782519e+09 | I35: =I31+I30 -> 9.6685772e+09 | ... L35: =L31+L30 -> 1.2326752e+10
C38: BN Inversor = | D38: =L34+L33 -> 7.6420856e+09

Sheet DF- Form
A1: Formulación del Proyecto a Nivel Financiero
A2: Año | B2: Activo Fijo | C2: Activo de Trabajo | D2: Credito Fiscal | E2: Honorarios al Directorio | F2: Impuesto a las Ganancias | G2: Total Egresos | H2: Utilidad Antes HD e IG | I2: Intereses Pagados | J2: Amortizaciones | K2: Cobro Credito Fiscal | L2: Total Ingresos | M2: Saldo Anual | N2: Saldo Acumulado
A3: 0 | B3: ='DF-2 Estructura'!B7 -> 3.4146342e+09 | C3: ='DF- CFyU'!B16 -> 2.3722302e+08 | D3: ='DF- CFyU'!B22 -> 7.6689002e+08 | E3: 0 | F3: ='DF- CFyU'!B18 -> 0 | G3: =SUM(B3:F3) -> 4.4187473e+09 | I3: ='DF-Cred'!G13 -> 3.9446654e+08 | J3: ='DF- CFyU'!B26 -> 0 | L3: =SUM(H3:K3) -> 3.9446654e+08 | M3: =L3-G3 -> -4.0242807e+09 | N3: =M3 -> -4.0242807e+09
A4: 1 | B4: ='DF-2 Estructura'!C7 -> 9335324.3 | C4: ='DF- CFyU'!C16 -> 5.9317256e+08 | D4: ='DF- CFyU'!C22 -> 1.7634349e+08 | E4: 0 | F4: ='DF- CFyU'!C18 -> 77212070 | G4: =SUM(B4:F4) -> 8.5606345e+08 | H4: ='DF-CRes'!B10 -> 2.2060592e+08 | I4: ='DF-Cred'!G17 -> 3.1179662e+08 | J4: ='DF- CFyU'!C26 -> 3.6345207e+08 | K4: ='DF-IVA'!C18 -> 2.7948102e+08 | L4: =SUM(H4:K4) -> 1.1753356e+09 | M4: =L4-G4 -> 3.1927218e+08 | N4: =M4+N3 -> -3.7050086e+09
A5: 2 | C5: ='DF- CFyU'!D16 -> 1.992376e+08 | D5: ='DF- CFyU'!D22 -> 41839897 | E5: 0 | F5: ='DF- CFyU'!D18 -> 3.2346793e+08 | G5: =SUM(B5:F5) -> 5.6454543e+08 | H5: ='DF-CRes'!C10 -> 9.2419408e+08 | I5: ='DF-Cred'!G19 -> 1.5740552e+08 | J5: ='DF- CFyU'!D26 -> 3.6345207e+08 | K5: ='DF-IVA'!D18 -> 4.3302793e+08 | L5: =SUM(H5:K5) -> 1.8780796e+09 | M5: =L5-G5 -> 1.3135342e+09 | N5: =M5+N4 -> -2.3914744e+09
A6: 3 | C6: ='DF- CFyU'!E16 -> -585291.42 | E6: 0 | F6: ='DF- CFyU'!E18 -> 3.7453142e+08 | G6: =SUM(B6:F6) -> 3.7394612e+08 | H6: ='DF-CRes'!D10 -> 1.0700898e+09 | I6: ='DF-Cred'!G21 -> 49823735 | J6: ='DF- CFyU'!E26 -> 3.6345207e+08 | K6: ='DF-IVA'!E18 -> 2.7256447e+08 | L6: =SUM(H6:K6) -> 1.75593e+09 | M6: =L6-G6 -> 1.3819839e+09 | N6: =M6+N5 -> -1.0094905e+09
A7: 4 | C7: ='DF- CFyU'!F16 -> -24842.929 | E7: 0 | F7: ='DF- CFyU'!F18 -> 4.7710825e+08 | G7: =SUM(B7:F7) -> 4.7708341e+08 | H7: ='DF-CRes'!E10 -> 1.3631664e+09 | I7: ='DF-Cred'!G23 -> 49823735 | J7: ='DF- CFyU'!F26 -> 1.784114e+08 | K7: ='DF-IVA'!F18 -> 0 | L7: =SUM(H7:K7) -> 1.5914016e+09 | M7: =L7-G7 -> 1.1143182e+09 | N7: =M7+N6 -> 1.0482767e+08
A8: 5 | C8: ='DF- CFyU'!G16 -> 0 | E8: 0 | F8: ='DF- CFyU'!G18 -> 4.7710825e+08 | G8: =SUM(B8:F8) -> 4.7710825e+08 | H8: ='DF-CRes'!F10 -> 1.3631664e+09 | I8: ='DF-Cred'!G25 -> 49823735 | J8: ='DF- CFyU'!G26 -> 1.784114e+08 | L8: =SUM(H8:K8) -> 1.5914016e+09 | M8: =L8-G8 -> 1.1142933e+09 | N8: =M8+N7 -> 1.219121e+09
A9: 6 | C9: ='DF- CFyU'!H16 -> 15509.603 | E9: 0 | F9: ='DF- CFyU'!H18 -> 4.7710825e+08 | G9: =SUM(B9:F9) -> 4.7712376e+08 | H9: ='DF-CRes'!G10 -> 1.3631664e+09 | I9: ='DF-Cred'!G27 -> 49823735 | J9: ='DF- CFyU'!H26 -> 8581250 | L9: =SUM(H9:K9) -> 1.4215714e+09 | M9: =L9-G9 -> 9.4444766e+08 | N9: =M9+N8 -> 2.1635686e+09
A10: 7 | C10: ='DF- CFyU'!I16 -> 0 | E10: 0 | F10: ='DF- CFyU'!I18 -> 4.7710825e+08 | G10: =SUM(B10:F10) -> 4.7710825e+08 | H10: ='DF-CRes'!H10 -> 1.3631664e+09 | I10: ='DF-Cred'!G29 -> 49823735 | J10: ='DF- CFyU'!I26 -> 8581250 | L10: =SUM(H10:K10) -> 1.4215714e+09 | M10: =L10-G10 -> 9.4446317e+08 | N10: =M10+N9 -> 3.1080318e+09
A11: 8 | C11: ='DF- CFyU'!J16 -> 0 | E11: 0 | F11: ='DF- CFyU'!J18 -> 4.7710825e+08 | G11: =SUM(B11:F11) -> 4.7710825e+08 | H11: ='DF-CRes'!I10 -> 1.3631664e+09 | I11: ='DF-Cred'!G31 -> 49823735 | J11: ='DF- CFyU'!J26 -> 8581250 | L11: =SUM(H11:K11) -> 1.4215714e+09 | M11: =L11-G11 -> 9.4446317e+08 | N11: =M11+N10 -> 4.052495e+09
A12: 9 | C12: ='DF- CFyU'!K16 -> 0 | E12: 0 | F12: ='DF- CFyU'!K18 -> 4.7710825e+08 | G12: =SUM(B12:F12) -> 4.7710825e+08 | H12: ='DF-CRes'!J10 -> 1.3631664e+09 | I12: ='DF-Cred'!G33 -> 49823735 | J12: ='DF- CFyU'!K26 -> 8581250 | L12: =SUM(H12:K12) -> 1.4215714e+09 | M12: =L12-G12 -> 9.4446317e+08 | N12: =M12+N11 -> 4.9969582e+09
A13: 10 | B13: =-'DF- CFyU'!C34 -> -1.9338843e+09 | C13: ='DF- CFyU'!L16-'DF- CFyU'!M16 -> -1.0290386e+09 | E13: 0 | F13: ='DF- CFyU'!L18 -> 4.7710825e+08 | G13: =SUM(B13:F13) -> -2.4858146e+09 | H13: ='DF-CRes'!K10 -> 1.3631664e+09 | I13: ='DF-Cred'!G35 -> 49823735 | J13: ='DF- CFyU'!L26 -> 8581250 | L13: =SUM(H13:K13) -> 1.4215714e+09 | M13: =L13-G13 -> 3.907386e+09 | N13: =M13+N12 -> 8.9043442e+09
M14: =L14-G14 -> 0
A15: Suma. | B15: =SUM(B3:B13) -> 1.4900853e+09 | C15: =SUM(C3:C13) -> 0 | D15: =SUM(D3:D13) -> 9.8507341e+08 | E15: =SUM(E3:E13) -> 0 | F15: =SUM(F3:F13) -> 4.1149692e+09 | G15: =SUM(G3:G13) -> 6.5901279e+09 | H15: =SUM(H3:H13) -> 1.1757055e+10 | I15: =SUM(I3:I13) -> 1.2622586e+09 | ... M15: =SUM(M3:M13) -> 8.9043442e+09
C17: Beneficio Neto | D17: =N13 -> 8.9043442e+09
C18: Periodo de Recupero de la Inversión | D18: 4 | E18: años y | F18: =ROUNDUP((-N6/M7)*365,0) -> 331 | H18: BN mod = Ut a/ IHG y HD + Int pag - (HD + IG) | J18: ='DF-CRes'!L10+'DF-Cred'!D37-'DF-CRes'!L12 -> 8.8933955e+09
C19: TIR modificada | D19: =IRR(M3:M13) -> 0.23281088 | H19: BN Inversor | I19: =J18-'DF-Cred'!D37 -> 7.6420856e+09 | J19: = BN mod - Int Pagados
A24: Formulación para el Inversor
A25: Año | B25: Aporte de Capital | C25: Total Egresos | D25: Dividendos en efectivo | E25: Saldo propio de Fuentes y Usos | F25: Total Ingresos | G25: Saldo Anual | H25: Saldo Acumulado
A26: 0 | B26: ='DF-2 Estructura'!B30 -> 3.558093e+09 | C26: =B26 -> 3.558093e+09 | D26: 0 | E26: ='DF- CFyU'!B29 -> 0 | F26: =D26+E26 -> 0 | G26: =F26-C26 -> -3.558093e+09 | H26: =G26 -> -3.558093e+09
A27: 1 | B27: ='DF-2 Estructura'!C30 -> 6.0087661e+08 | C27: =B27 -> 6.0087661e+08 | D27: 0 | E27: ='DF- CFyU'!C29 -> 7.366652e+08 | F27: =D27+E27 -> 7.366652e+08 | G27: =F27-C27 -> 1.3578859e+08 | H27: =G27+H26 -> -3.4223044e+09
A28: 2 | C28: =B28 -> 0 | D28: 0 | E28: ='DF- CFyU'!D29 -> 8.6924389e+08 | F28: =D28+E28 -> 8.6924389e+08 | G28: =F28-C28 -> 8.6924389e+08 | H28: =G28+H27 -> -2.5530605e+09
A29: 3 | C29: =B29 -> 0 | D29: 0 | E29: ='DF- CFyU'!E29 -> 1.0452754e+09 | F29: =D29+E29 -> 1.0452754e+09 | G29: =F29-C29 -> 1.0452754e+09 | H29: =G29+H28 -> -1.5077851e+09
A30: 4 | C30: =B30 -> 0 | D30: 0 | E30: ='DF- CFyU'!F29 -> 1.0644944e+09 | F30: =D30+E30 -> 1.0644944e+09 | G30: =F30-C30 -> 1.0644944e+09 | H30: =G30+H29 -> -4.4329069e+08
A31: 5 | C31: =B31 -> 0 | D31: 0 | E31: ='DF- CFyU'!G29 -> 1.0644696e+09 | F31: =D31+E31 -> 1.0644696e+09 | G31: =F31-C31 -> 1.0644696e+09 | H31: =G31+H30 -> 6.211789e+08
A32: 6 | C32: =B32 -> 0 | D32: 0 | E32: ='DF- CFyU'!H29 -> 8.9462392e+08 | F32: =D32+E32 -> 8.9462392e+08 | G32: =F32-C32 -> 8.9462392e+08 | H32: =G32+H31 -> 1.5158028e+09
A33: 7 | C33: =B33 -> 0 | D33: 0 | E33: ='DF- CFyU'!I29 -> 8.9463943e+08 | F33: =D33+E33 -> 8.9463943e+08 | G33: =F33-C33 -> 8.9463943e+08 | H33: =G33+H32 -> 2.4104423e+09
A34: 8 | C34: =B34 -> 0 | D34: 0 | E34: ='DF- CFyU'!J29 -> 8.9463943e+08 | F34: =D34+E34 -> 8.9463943e+08 | G34: =F34-C34 -> 8.9463943e+08 | H34: =G34+H33 -> 3.3050817e+09
A35: 9 | C35: =B35 -> 0 | D35: 0 | E35: ='DF- CFyU'!K29 -> 8.9463943e+08 | F35: =D35+E35 -> 8.9463943e+08 | G35: =F35-C35 -> 8.9463943e+08 | H35: =G35+H34 -> 4.1997211e+09
A36: 10 | B36: =-(-B13-C13-'DF- CFyU'!M8) -> -2.5477251e+09 | C36: =B36 -> -2.5477251e+09 | D36: 0 | E36: ='DF- CFyU'!L29 -> 8.9463943e+08 | F36: =D36+E36 -> 8.9463943e+08 | G36: =F36-C36 -> 3.4423645e+09 | H36: =G36+H35 -> 7.6420856e+09 | I36: = BN inv
D37: 0
A38: Suma. | B38: =SUM(B26:B36) -> 1.6112446e+09 | C38: =SUM(C26:C36) -> 1.6112446e+09 | D38: =SUM(D26:D36) -> 0 | E38: =SUM(E26:E36) -> 9.2533302e+09 | F38: =SUM(F26:F36) -> 9.2533302e+09 | G38: =SUM(G26:G36) -> 7.6420856e+09
C41: Beneficio Neto | D41: =H36 -> 7.6420856e+09 | E41: para el inversor
C42: Periodo de Recupero de la Inversión | D42: 5 | E42: años y | F42: =ROUNDUP((-H30/G31)*365,0) -> 153
C43: TOR | D43: =IRR(G26:G36) -> 0.21214909
A45: VR AF = | B45: ='DF- CFyU'!C34 -> 1.9338843e+09
A46: AL = | B46: =-C13 -> 1.0290386e+09
A47: C Renov = | B47: ='DF- CFyU'!M8 -> 4.1519779e+08
A48: VR aporte K propio | B48: = VR AF + AL -C Renov | D48: Apalancamiento = | E48: =D43/D19 -> 0.91125074 | F48: < 1 --> No es conveniente financiarse
A49: Aporte de K (10) = | B49: =B45+B46-B47 -> 2.5477251e+09

Sheet Sensibilidad
H2: VAN mod = 0
F3: Unidades vendidas (un) | G3: =InfoInicial!B17 -> 5000 | H3: 12003 | I3: =(H3*1/G3)-1 -> 1.4006 | J3: Info inicial
F4: Precio unitario ($) | G4: =InfoInicial!B18 -> 450 | H4: 834 | I4: =(H4*1/G4)-1 -> 0.85333333 | J4: Info inicial
F7: Wacc | G7: = Kd | H7: Deuda (0 y 1) | I7: + | J7: Kcapm | K7: Capital
H8: Inv. (0 y 1) | K8: Inv. (0 y 1)
B12: Kd = | C12: ='DF-Cred'!H17 -> 0.55067813 | D12: Año 1 (Mayor riesgo) | G12: AT (0 y 1) = | H12: ='DF-Balance'!B24+'DF-Balance'!C24 -> 9.3637915e+09
B13: Kc = | C13: 0.6 | G13: PT (0 y 1) = | H13: ='DF-Balance'!B30+'DF-Balance'!C30 -> 9.889673e+08
B14: WACC = | C14: =C12*(H13/H12)+C13*(H14/H12) -> 0.59479082 | G14: PN (0 y 1) = | H14: ='DF-Balance'!B31+'DF-Balance'!C31 -> 8.3748242e+09

Sheet WACC
B4: Wacc | C4: = Kd | D4: Deuda (0 y 1) | E4: + | F4: Kcapm | G4: Capital
D5: Inv. (0 y 1) | G5: Inv. (0 y 1)
