Workbook

Sheet DE
A1: ACTIVO FIJO (BS DE USO + CS DIFERIDOS)
B2: SIN IVA | C2: IVA | D2: CON IVA | E2: Año
A3: Compra Bs de Uso | B3: 150000 | C3: =B3*0.21 -> 31500 | D3: =B3+C3 -> 181500 | E3: 0
A4: Gs investig y estudios | B4: 18000 | C4: =B4*0.21 -> 3780 | D4: =B4+C4 -> 21780 | E4: 0
A5: Gs instalación | B5: 45000 | C5: =B5*0.21 -> 9450 | D5: =B5+C5 -> 54450 | E5: 0
A6: Gs puesta en marcha | B6: 6000 | C6: =B6*0.21 -> 1260 | D6: =B6+C6 -> 7260 | E6: 1
A7: Totales | B7: =SUM(B3:B6) -> 219000 | C7: =SUM(C3:C6) -> 45990 | D7: =SUM(D3:D6) -> 264990
A8: VR BIENES DE USO | B8: 50000
A11: VALOR CONTABLE AT
B12: SIN IVA | C12: Año
A13: Caja y Bancos | B13: 2100 | C13: 0
A14: Compra MP para PM | B14: 6000 | C14: 0
A15: Créditos por Ventas | B15: 7500 | C15: 1
A16: Form. Stock MP, MCySE, PT | B16: 12000 | C16: 1
A17: Totales | B17: =SUM(B13:B16) -> 27600
A19: INVERSIÓN AT
B20: SIN IVA | C20: IVA | D20: CON IVA | E20: Año
A21: Caja y Bancos | B21: =B13 -> 2100 | D21: =B21+C21 -> 2100 | E21: 0
A22: Compra MP para PM | B22: =B14 -> 6000 | C22: =B22*0.21 -> 1260 | D22: =B22+C22 -> 7260 | E22: 0
A23: Créditos por Ventas | B23: =B15*0.8 -> 6000 | D23: =B23+C23 -> 6000 | E23: 1
A24: Form. Stock MP, MCySE, PT | B24: =B16*0.8 -> 9600 | C24: =B24*0.21 -> 2016 | D24: =SUM(B24+C24) -> 11616 | E24: 1
A25: Totales | B25: =SUM(B21:B24) -> 23700 | C25: =SUM(C21:C24) -> 3276 | D25: =SUM(D21:D24) -> 26976
B27: Cantidad | D27: Pvu | F27: IVA DF
A28: Año 1 | B28: 300 | C28: unidades | D28: - | E28: $/u | F28: 225000
A29: Año 2 a n | B29: 500 | C29: unidades | D29: - | E29: $/u | F29: 375000
B31: Año 1 | C31: Año 2 a n
A32: CTV DE | B32: 90000 | C32: 120000
A34: HD | C34: no son variables con la utilidad
A35: IIGG | B35: 0.35
A36: kc | B36: 0.6

Sheet CREDITOS
A1: CREDITO NO RENOVABLE
A2: i | B2: =20% -> 0.2
A3: 40% INVERSIÓN DE LARGO PLAZO | D3: =DE!B7*0.4 -> 87600
A5: Fecha | B5: Deuda | C5: Amort. Anual | D5: Int. Anuales
A6: 31/12/-1 | B6: =D3 -> 87600 | C6: 0 | D6: 52560
A7: Gastos preop. | B7: =SUM(D6:D6) -> 52560
A8: 36892 | B8: =B6 -> 87600 | C8: 0
A9: 37255 | B9: =B8-C9 -> 58400 | C9: =B8/3 -> 29200
A10: 37620 | B10: =B9-C10 -> 29200 | C10: =C9 -> 29200
A11: 37985 | B11: 0 | C11: =C9 -> 29200
A14: CREDITO RENOVABLE
A15: i
A16: 50% INVERSION DE CORTO PLAZO | C16: =DE!B25*0.5 -> 11850
A18: Fecha | B18: Deuda | C18: Amort. Anual | D18: Int. Anuales
A19: 36892 | B19: =C16 -> 11850 | C19: 0
A20: 37255 | B20: =B19 -> 11850 | C20: 0
A21: 37620 | B21: =B19 -> 11850 | C21: 0
A22: 37985 | B22: =B19 -> 11850 | C22: 0
A24: CREDITOS TOTALES
A26: Fecha | B26: Deuda | C26: Amort. Anual | D26: Int. Anuales | E26: kd
A27: 31/12/-1 | B27: =B6 -> 87600 | C27: 0 | D27: =D6 -> 52560
A28: Gastos preop. | B28: =B7 -> 52560
A29: 36892 | B29: =B8+B19 -> 99450 | C29: 0 | D29: 0
A30: 37255 | B30: =B9+B20 -> 70250 | C30: =C9+C20 -> 29200 | D30: =27500 -> 27500 | E30: =D30/B29 -> 0.27652086
A31: 37620 | B31: =B10+B21 -> 41050 | C31: =C10+C21 -> 29200 | D31: 18700 | E31: =D31/B30 -> 0.26619217
A32: 37985 | B32: =B11+B22 -> 11850 | C32: =C11 -> 29200 | D32: 10000 | E32: =D32/B31 -> 0.24360536
B34: Año 1 | C34: Año 2 | D34: Año 3
A35: Gasto Financiero | B35: =B28/3+D30 -> 45020 | C35: =B28/3+D31 -> 36220 | D35: =D32+B28/3 -> 27520

Sheet 1era estructura Financiera
A1: PRIMERA ESTRUCTURA FINANCIERA
B2: Total | C2: Credito Renovable | D2: Credito No Renovable | E2: Aporte Cap. Propio
A3: Activo Fijo, sin IVA | B3: =DE!B7 -> 219000 | C3: 0 | D3: =CREDITOS!D3 -> 87600 | E3: =+B3-D3 -> 131400
A4: IVA Inversion | B4: =B3*0.21 -> 45990 | C4: 0 | D4: 0 | E4: =+B4 -> 45990
A6: Activo de trabajo | B6: =DE!B17 -> 27600 | D6: 0
A7: Inversión Activo Trabajo s/ IVA | B7: =DE!B25 -> 23700 | C7: =CREDITOS!C16 -> 11850 | D7: 0 | E7: =+B7-C7 -> 11850
A8: IVA Inversion | B8: =DE!C25 -> 3276 | C8: 0 | D8: 0 | E8: =+B8 -> 3276
A10: Inversiones s/ IVA | B10: =+B3+B7 -> 242700 | C10: =+SUM(C3:C9) -> 11850 | D10: =+SUM(D3:D9) -> 87600 | E10: =+B10-C10-D10 -> 143250
A11: IVA Inversion | B11: =+B4+B8 -> 49266 | C11: 0 | D11: 0 | E11: =+B11 -> 49266
A12: Inversion Total | B12: =+B10+B11 -> 291966 | C12: =+C10 -> 11850 | D12: =+D10 -> 87600 | E12: =SUM(E10:E11) -> 192516

Sheet CRes
A1: CUADRO DE RESULT. PROFORMA
A2: Año | B2: Ventas | C2: CTV | D2: U a/ HD e IIGG | E2: HD | F2: IIGG | G2: U d/HD e IIGG
A3: 1 | B3: =DE!F28 -> 225000 | C3: =DE!B32+CREDITOS!B35 -> 135020 | D3: =B3-C3 -> 89980 | E3: 10000 | F3: =(D3-E3)*DE!$B$35 -> 27993 | G3: =D3-E3-F3 -> 51987
A4: 2 | B4: =DE!F29 -> 375000 | C4: =DE!C32+CREDITOS!C35 -> 156220 | D4: =B4-C4 -> 218780 | E4: 10000 | F4: =(D4-E4)*DE!$B$35 -> 73073 | G4: =D4-E4-F4 -> 135707
A5: 3 | B5: =B4 -> 375000 | C5: =DE!C32+CREDITOS!D35 -> 147520 | D5: =B5-C5 -> 227480 | E5: 10000 | F5: =(D5-E5)*DE!$B$35 -> 76118 | G5: =D5-E5-F5 -> 141362
A7: BN inversor | B7: =SUM(G3:G5) -> 329056

Sheet Calendario Inv
A1: CALENDARIO DE INVERSIONES (incrementos)
B2: Año 0 | C2: Año 1 | D2: Totales
A3: a) Activo Fijo (incrementos) | B3: =DE!B3+DE!B4+DE!B5+CREDITOS!B28 -> 265560 | C3: =DE!B6 -> 6000 | D3: =+C3+B3 -> 271560
A4: IVA Inversión | B4: =DE!C7-DE!C6+0.21*CREDITOS!B28 -> 55767.6 | C4: =DE!C6 -> 1260 | D4: =+C4+B4 -> 57027.6
A5: Inversion total a) | B5: =+B4+B3 -> 321327.6 | C5: =+C3+C4 -> 7260 | D5: =+C5+B5 -> 328587.6
A7: AT (incrementos) | B7: =DE!B13+DE!B14 -> 8100 | C7: =DE!B15+DE!B16 -> 19500 | D7: =+C7+B7 -> 27600
A8: Inv. AT (incrementos) | B8: =DE!B21+DE!B22 -> 8100 | C8: =DE!B23+DE!B24+2400 -> 18000 | D8: =+C8+B8 -> 26100
A9: IVA Inversion | B9: =DE!C21+DE!C22 -> 1260 | C9: =DE!C23+DE!C24 -> 2016 | D9: =+C9+B9 -> 3276
A10: Inversión Total AT | B10: =B8+B9 -> 9360 | C10: =+C8+C9 -> 20016 | D10: =+D9+D8 -> 29376
A12: Total s/ IVA | B12: =+B8+B3 -> 273660 | C12: =+C8+C3 -> 24000 | D12: =+D8+D3 -> 297660
A13: IVA Inversion | B13: =+B9+B4 -> 57027.6 | C13: =+C9+C4 -> 3276 | D13: =+D9+D4 -> 60303.6
A14: Inversion Total | B14: =+B13+B12 -> 330687.6 | C14: =+C13+C12 -> 27276 | D14: =+D13+D12 -> 357963.6

Sheet 2da Est. 
A1: 2° ESTRUCTURA FINANCIERA
B2: Año 0 | D2: Año 1 | F2: Totales
B3: AF | C3: Inv. AT | D3: AF | E3: Inv. AT | F3: AF | G3: Inv. AT | H3: Total | I3: %
A4: Inversion total | B4: ='Calendario Inv'!B5 -> 321327.6 | C4: ='Calendario Inv'!B10 -> 9360 | D4: ='Calendario Inv'!C5 -> 7260 | E4: ='Calendario Inv'!C10 -> 20016 | F4: =+B4+D4 -> 328587.6 | G4: =+C4+E4 -> 29376 | H4: =+G4+F4 -> 357963.6 | I4: =+I5+I6+I7 -> 1
A5: Crédito No Renovable | B5: ='1era estructura Financiera'!D3 -> 87600 | C5: 0 | D5: 0 | E5: 0 | F5: =+B5+D5 -> 87600 | G5: =+C5+E5 -> 0 | H5: =+G5+F5 -> 87600 | I5: =+H5/H4 -> 0.24471762
A6: Crédito Renovable | B6: 0 | C6: 0 | E6: ='1era estructura Financiera'!C7 -> 11850 | F6: =+B6+D6 -> 0 | G6: =+C6+E6 -> 11850 | H6: =+G6+F6 -> 11850 | I6: =+H6/H4 -> 0.033103925
A7: Aporte de Capital | B7: =+B4-B5 -> 233727.6 | C7: =+C4 -> 9360 | D7: =+D4 -> 7260 | E7: =+E4-E6 -> 8166 | F7: =+B7+D7 -> 240987.6 | G7: =+C7+E7 -> 17526 | H7: =+G7+F7 -> 258513.6 | I7: =+H7/H4 -> 0.72217846

Sheet RECUPERO IVA
A1: IVA diferencia
A2: IVA Plan Explotación | B2: Año 1 | C2: Año 2 | D2: Año 3
A3: IVA diferencia | B3: 28000 | C3: 57000 | D3: 59000
A5: Cobro del Crédito Fiscal
B6: Crédito Fiscal | C6: IVA diferencia | D6: Recupero IVA
A7: Año 0 | B7: ='Calendario Inv'!B13 -> 57027.6 | C7: 0 | D7: 0
A8: Año 1 | B8: ='Calendario Inv'!D13 -> 60303.6 | C8: =B3 -> 28000 | D8: =C8 -> 28000
A9: Año 2 | B9: =B8-D8 -> 32303.6 | C9: =+C3 -> 57000 | D9: =B9 -> 32303.6 | E9: IVA DF al fisco | F9: =C9-D9 -> 24696.4
A10: Año 3 | B10: 0 | C10: =+D3 -> 59000 | D10: 0 | E10: IVA DF al fisco | F10: =C10 -> 59000

Sheet CFyU
B1: Año 0 | C1: Año 1 | D1: Año 2 | E1: Año 3 | F1: TOTALES
A2: FUENTES: Totales | B2: =SUM(B3:B9) -> 330687.6 | C2: =SUM(C3:C9) -> 280276 | D2: =SUM(D3:D9) -> 534110.6 | E2: =SUM(E3:E9) -> 718137.6 | F2: =SUM(F3:F9) -> 1393267.2
A3: Saldo ej. Anterior (Ac) | B3: 0 | C3: =B25 -> 0 | D3: =C25 -> 126807 | E3: =D25 -> 343137.6 | F3: 0
A4: Aporte de Cap. Propio | B4: ='2da Est. '!B7+'2da Est. '!C7 -> 243087.6 | C4: ='2da Est. '!D7+'2da Est. '!E7 -> 15426 | D4: 0 | E4: 0 | F4: =SUM(B4:E4) -> 258513.6
A5: Créditos Renovables | B5: 0 | C5: =CREDITOS!C16 -> 11850 | D5: 0 | E5: 0 | F5: =SUM(B5:E5) -> 11850
A6: Créditos No Renovables | B6: =CREDITOS!D3 -> 87600 | C6: 0 | D6: 0 | E6: 0 | F6: =SUM(B6:E6) -> 87600
A7: Ventas del ej. | B7: 0 | C7: =CRes!B3 -> 225000 | D7: =CRes!B4 -> 375000 | E7: =CRes!B5 -> 375000 | F7: =SUM(B7:E7) -> 975000
A8: Recupero Crédito Fiscal | B8: 0 | C8: ='RECUPERO IVA'!D8 -> 28000 | D8: ='RECUPERO IVA'!D9 -> 32303.6 | E8: 0 | F8: =SUM(B8:E8) -> 60303.6
A9: Otros ingresos | B9: 0 | C9: 0 | D9: 0 | E9: 0 | F9: 0
A11: USOS: Totales | B11: =SUM(B12:B19) -> 330687.6 | C11: =SUM(C12:C19) -> 230989 | D11: =SUM(D12:D19) -> 268493 | E11: =SUM(E12:E19) -> 262838 | F11: =SUM(B11:E11) -> 1093007.6
A12: Activo Fijo | B12: ='Calendario Inv'!B3 -> 265560 | C12: ='Calendario Inv'!C3 -> 6000 | D12: 0 | E12: 0 | F12: =SUM(B12:E12) -> 271560
A13: Activo Trabajo | B13: ='Calendario Inv'!B7 -> 8100 | C13: ='Calendario Inv'!C7 -> 19500 | D13: 0 | E13: 0 | F13: =SUM(B13:E13) -> 27600
A14: Costo de lo vendido | B14: 0 | C14: =CRes!C3 -> 135020 | D14: =CRes!C4 -> 156220 | E14: =CRes!C5 -> 147520 | F14: =SUM(B14:E14) -> 438760
A15: IIGG | B15: 0 | C15: =CRes!F3 -> 27993 | D15: =CRes!F4 -> 73073 | E15: =CRes!F5 -> 76118 | F15: =SUM(B15:E15) -> 177184
A16: Cancelación de deudas | B16: 0 | C16: =CREDITOS!C9 -> 29200 | D16: =C16 -> 29200 | E16: =C16 -> 29200 | F16: =SUM(B16:E16) -> 87600
A17: HD | B17: 0 | C17: =CRes!E3 -> 10000 | D17: =CRes!E4 -> 10000 | E17: =CRes!E5 -> 10000 | F17: =SUM(B17:E17) -> 30000
A18: Dividendos Efectivo | B18: 0 | C18: 0 | D18: 0 | E18: 0 | F18: =SUM(B18:E18) -> 0
A19: IVA Inversion | B19: ='Calendario Inv'!B13 -> 57027.6 | C19: ='Calendario Inv'!C13 -> 3276 | D19: 0 | E19: 0 | F19: =SUM(B19:E19) -> 60303.6
A20: Otros egresos
A22: FUENTES - USOS | B22: =+B2-B11 -> 0 | C22: =+C2-C11 -> 49287 | D22: =+D2-D11 -> 265617.6 | E22: =+E2-E11 -> 455299.6 | F22: =F2-F11 -> 300259.6
A23: Amortizaciones del Ejercicio | B23: 0 | C23: =B36 -> 77520 | D23: =B37 -> 77520 | E23: =B38 -> 77520 | F23: =SUM(B23:E23) -> 232560
A25: Saldo al ej. Siguiente (Ac) | B25: =+B22+B23 -> 0 | C25: =+C22+C23 -> 126807 | D25: =+D22+D23 -> 343137.6 | E25: =+E22+E23 -> 532819.6 | F25: =F22+F23 -> 532819.6
A26: Saldo propio del ejercicio | B26: =+B25 -> 0 | C26: =C25-B25 -> 126807 | D26: =D25-C25 -> 216330.6 | E26: =E25-D25 -> 189682 | F26: =F25 -> 532819.6
A28: Amortizaciones ejercicio
A30: =SUM(DE!B3:B6) -> 219000 | B30: VO | E30: VERIFICACIONES
A31: 39000 | B31: VR | E31: BN inv | F31: =E25+A31+F13-F4-F5 -> 329056
E32: Bn inv | F32: =CRes!B7 -> 329056
E33: Bn inv | F33: ='Balance proforma'!H34+'Balance proforma'!H35 -> 329056
A34: Amort int y gastos preop | B34: =CREDITOS!B28/3 -> 17520 | C34: se amortizan en 3 años | E34: BN mod | F34: =F32+SUM(CREDITOS!B35:D35) -> 437816
E35: BN puro | F35: =F31+SUM(CREDITOS!B35:D35)*(1-DE!B35) -> 399750
A36: Amort año 1 | B36: =(A30-A31)/3+B34 -> 77520
A37: Amort año 2 | B37: =B36 -> 77520 | E37: AHORRO IMPOSITIVO | F37: =SUM(CREDITOS!B35:D35)*DE!B35 -> 38066
A38: Amort año 3 | B38: =(A30-A31)/3+B34 -> 77520

Sheet Balance proforma
E1: Año 0 | F1: Año 1 | G1: Año 2 | H1: Año 3
A2: ACTIVO CORRIENTE: Total | E2: =E3+E6+E7+E8 -> 9360 | F2: =F3+F6+F7+F8 -> 156161.9 | G2: =G3+G6+G7+G8 -> 370737.6 | H2: =H3+H6+H7+H8 -> 560419.6
A3: Caja y Bancos | E3: =SUM(E4:E5) -> 2100 | F3: =SUM(F4:F5) -> 128907 | G3: =SUM(G4:G5) -> 345237.6 | H3: =SUM(H4:H5) -> 534919.6
A4: Mínimo | E4: 2100 | F4: 2100 | G4: 2100 | H4: 2100
A5: Saldo Ac. FyU | E5: =CFyU!B25 -> 0 | F5: =CFyU!C25 -> 126807 | G5: =CFyU!D25 -> 343137.6 | H5: =CFyU!E25 -> 532819.6
A6: Créditos x Ventas (valor contable) | E6: 0 | F6: =DE!B15 -> 7500 | G6: =F6 -> 7500 | H6: =F6 -> 7500
A7: Bs. de Cambio | E7: =DE!B22 -> 6000 | F7: =E7+DE!B16 -> 18000 | G7: =F7 -> 18000 | H7: =F7 -> 18000
A8: Crédito fiscal | E8: ='Calendario Inv'!B9 -> 1260 | F8: ='Calendario Inv'!D9/'Calendario Inv'!D13*'RECUPERO IVA'!B9 -> 1754.8968 | G8: ='Calendario Inv'!D9/'Calendario Inv'!D13*'RECUPERO IVA'!B10 -> 0 | H8: 0
A10: ACTIVO NO CORRIENTE: Total | E10: =E15+E20+E21 -> 321327.6 | F10: =F15+F20+F21 -> 224588.7 | G10: =G15+G20+G21 -> 116520 | H10: =H15+H20+H21 -> 39000
A11: Cargos diferidos:
A12: Valor inicial del ejercicio | E12: =DE!B4+DE!B5+CREDITOS!B28 -> 115560 | F12: =E15 -> 115560 | G12: =F15 -> 81040 | H12: =G15 -> 40520
A13: más inversiones del ejercicio | E13: 0 | F13: =DE!B6 -> 6000 | G13: 0 | H13: 0
A14: menos amortizaciones del ejercicio | E14: 0 | F14: =(F12+F13)/3 -> 40520 | G14: =F14 -> 40520 | H14: =F14 -> 40520
A15: valor final del ejercicio | E15: =E12+E13-E14 -> 115560 | F15: =F12+F13-F14 -> 81040 | G15: =G12+G13-G14 -> 40520 | H15: =H12+H13-H14 -> 0
A16: Bienes de uso:
A17: Valor inicial del ejercicio | E17: =DE!B3 -> 150000 | F17: =E20 -> 150000 | G17: =F20 -> 113000 | H17: =G20 -> 76000
A18: más inversiones del ejercicio | E18: 0 | F18: 0 | G18: 0 | H18: 0 | K18: VO bs uso | L18: =E17 -> 150000
A19: menos amortizaciones del ejercicio | E19: 0 | F19: =L21 -> 37000 | G19: =L21 -> 37000 | H19: =L21 -> 37000 | K19: VR | L19: 39000
A20: valor final del ejercicio | E20: =E17+E18-E19 -> 150000 | F20: =F17+F18-F19 -> 113000 | G20: =G17+G18-G19 -> 76000 | H20: =H17+H18-H19 -> 39000
A21: Crédito fiscal | E21: ='Calendario Inv'!B4 -> 55767.6 | F21: ='Calendario Inv'!D4/'Calendario Inv'!D13*'RECUPERO IVA'!B9 -> 30548.703 | G21: 0 | H21: 0 | K21: Amort | L21: =(L18-L19)/3 -> 37000
A23: ACTIVO TOTAL | E23: =E2+E10 -> 330687.6 | F23: =F2+F10 -> 380750.6 | G23: =G2+G10 -> 487257.6 | H23: =H2+H10 -> 599419.6
A25: PASIVO CORRIENTE: total | E25: =SUM(E26:E27) -> 0 | F25: =F26 -> 11850 | G25: =G26 -> 11850 | H25: =H26 -> 11850
A26: Deudas comerciales | E26: 0 | F26: =CREDITOS!C16 -> 11850 | G26: =F26 -> 11850 | H26: =F26 -> 11850
A28: PASIVO NO CORRIENTE: total | E28: =E29 -> 87600 | F28: =F29 -> 58400 | G28: =G29 -> 29200 | H28: =H29 -> 0
A29: Deudas bancarias | E29: =CREDITOS!B8 -> 87600 | F29: =CREDITOS!B9 -> 58400 | G29: =CREDITOS!B10 -> 29200 | H29: 0
A30: PASIVO TOTAL | E30: =E25+E28 -> 87600 | F30: =F25+F28 -> 70250 | G30: =G25+G28 -> 41050 | H30: =H25+H28 -> 11850
A32: PATRIMONIO NETO: total | E32: =SUM(E33:E35) -> 243087.6 | F32: =SUM(F33:F35) -> 310500.6 | G32: =SUM(G33:G35) -> 446207.6 | H32: =SUM(H33:H35) -> 587569.6
A33: Capital societario | E33: =CFyU!B4 -> 243087.6 | F33: =CFyU!F4 -> 258513.6 | G33: =CFyU!F4 -> 258513.6 | H33: =CFyU!F4 -> 258513.6
A34: Utilidad del ejercicio | E34: 0 | F34: =CRes!G3 -> 51987 | G34: =CRes!G4 -> 135707 | H34: =CRes!G5 -> 141362
A35: Utilidad acumulada | E35: 0 | F35: =SUM(E34:E35) -> 0 | G35: =SUM(F34:F35) -> 51987 | H35: =SUM(G34:G35) -> 187694
A37: PASIVO + PN | E37: =E30+E32 -> 330687.6 | F37: =F30+F32 -> 380750.6 | G37: =G30+G32 -> 487257.6 | H37: =H30+H32 -> 599419.6
A38: CHECK | E38: =E23-E37 -> 0 | F38: =F23-F37 -> 0 | G38: =G23-G37 -> 0 | H38: =H23-H37 -> 0
