Workbook

Sheet DE
A1: ACTIVO FIJO (BS DE USO + CS DIFERIDOS)
B2: SIN IVA | C2: IVA | D2: CON IVA | E2: Año
A3: Compra Bs de Uso | B3: 220000 | C3: =B3*0.21 -> 46200 | D3: =B3+C3 -> 266200 | E3: 0
A4: Gs investig y estudios | B4: =40000 -> 40000 | C4: =B4*0.21 -> 8400 | D4: =B4+C4 -> 48400 | E4: 0
A5: Gs instalación | B5: 80000 | C5: =B5*0.21 -> 16800 | D5: =B5+C5 -> 96800 | E5: 0
A6: Gs puesta en marcha | B6: 10000 | C6: =B6*0.21 -> 2100 | D6: =B6+C6 -> 12100 | E6: 1
A7: Totales | B7: =SUM(B3:B6) -> 350000 | C7: =SUM(C3:C6) -> 73500 | D7: =SUM(D3:D6) -> 423500
A8: VR BIENES DE USO | B8: 50000
A11: VALOR CONTABLE AT
B12: SIN IVA | C12: Año
A13: Caja y Bancos | B13: 2000 | C13: 0
A14: Compra MP para PM | B14: =8000 -> 8000 | C14: 0
A15: Créditos por Ventas | B15: 10000 | C15: 1
A16: Form. Stock MP, MCySE, PT | B16: =15000 -> 15000 | C16: 1
A17: Totales | B17: =SUM(B13:B16) -> 35000
A19: INVERSIÓN AT
B20: SIN IVA | C20: IVA | D20: CON IVA | E20: Año
A21: Caja y Bancos | B21: 2000 | D21: =B21+C21 -> 2000 | E21: 0
A22: Compra MP para PM | B22: =8000 -> 8000 | C22: =B22*0.21 -> 1680 | D22: =B22+C22 -> 9680 | E22: 0
A23: Créditos por Ventas | B23: =B15*0.7 -> 7000 | D23: =B23+C23 -> 7000 | E23: 1
A24: Form. Stock MP, MCySE, PT | B24: =B16*0.7 -> 10500 | C24: =B24*0.21 -> 2205 | D24: =SUM(B24+C24) -> 12705 | E24: 1
A25: Totales | B25: =SUM(B21:B24) -> 27500 | C25: =SUM(C21:C24) -> 3885 | D25: =SUM(D21:D24) -> 31385
B27: Cantidad | D27: Pvu | F27: IVA DF
A28: Año 1 | B28: 300 | C28: unidades | D28: 1000 | E28: $/u | F28: =B28*D28*0.21 -> 63000
A29: Año 2 a n | B29: 500 | C29: unidades | D29: 1000 | E29: $/u | F29: =B29*D29*0.21 -> 105000
B31: Año 1 | C31: Año 2 a n
A32: Gastos prod, admin y comerc | B32: =80000 -> 80000 | C32: =100000 -> 100000
A33: Gastos variables de lo vendido | B33: 40000 | C33: 60000
A34: IVA costos | B34: =(B32+B33)*0.15 -> 18000 | C34: =(C32+C33)*0.15 -> 24000
A36: HD | B36: 0.1
A37: IIGG | B37: 0.35
A38: kc | B38: 0.3

Sheet CREDITOS
A1: CREDITO NO RENOVABLE
A2: i | B2: =20% -> 0.2
A3: 30% INVERSIÓN DE LARGO PLAZO | D3: =DE!B7*0.3 -> 105000
A5: Fecha | B5: Deuda | C5: Amort. Anual | D5: Int. Anuales
A6: 1/1/-1 | B6: 105000 | C6: 0 | D6: 0
A7: 31/12/-1 | B7: 105000 | C7: 0 | D7: 21000
A8: Gastos preop. | B8: =D7 -> 21000
A9: 36892 | B9: 105000 | C9: 0 | D9: 0
A10: 37255 | B10: 70000 | C10: =$B$7/3 -> 35000 | D10: =B9*$B$2 -> 21000
A11: 37620 | B11: 35000 | C11: =$B$7/3 -> 35000 | D11: =B10*$B$2 -> 14000
A12: 37985 | B12: 0 | C12: =$B$7/3 -> 35000 | D12: =B11*$B$2 -> 7000
A15: CREDITO RENOVABLE
A16: i | B16: 0.1
A17: 50% INVERSION DE CORTO PLAZO | C17: =DE!B25*0.5 -> 13750
A19: Fecha | B19: Deuda | C19: Amort. Anual | D19: Int. Anuales
A20: 36892 | B20: =C17 -> 13750 | C20: 0 | D20: 0
A21: 37255 | B21: =B20 -> 13750 | C21: 0 | D21: =B21*$B$16 -> 1375
A22: 37620 | B22: =B20 -> 13750 | C22: 0 | D22: =B22*$B$16 -> 1375
A23: 37985 | B23: =B20 -> 13750 | C23: 0 | D23: =B23*$B$16 -> 1375
A25: CREDITOS TOTALES
A26: i | B26: =20% -> 0.2
A27: 30% INVERSIÓN DE LARGO PLAZO | D27: =DE!B34*0.3 -> 5400
A29: Fecha | B29: Deuda | C29: Amort. Anual | D29: Int. Anuales | E29: kd
A30: 1/1/-1 | B30: =B6 -> 105000 | C30: 0 | D30: 0
A31: 31/12/-1 | B31: =B7 -> 105000 | C31: 0 | D31: =D7 -> 21000
A32: Gastos preop. | B32: =B8 -> 21000
A33: 36892 | B33: =B9+B20 -> 118750 | C33: 0 | D33: 0
A34: 37255 | B34: =B10+B21 -> 83750 | C34: =C10+C21 -> 35000 | D34: =D10+D21 -> 22375 | E34: =D34/B33 -> 0.18842105
A35: 37620 | B35: =B11+B22 -> 48750 | C35: =C11+C22 -> 35000 | D35: =D11+D22 -> 15375 | E35: =D35/B34 -> 0.18358209
A36: 37985 | B36: =B12+B23 -> 13750 | C36: =$B$7/3 -> 35000 | D36: =D12+D23 -> 8375 | E36: =D36/B35 -> 0.17179487
B38: Año 1 | C38: Año 2 | D38: Año 3
A39: Gasto Financiero | B39: =B32/2+D34 -> 32875 | C39: =B32/2+D35 -> 25875 | D39: =D36 -> 8375

Sheet 1era estructura Financiera
A1: PRIMERA ESTRUCTURA FINANCIERA
B2: Total | C2: Credito Renovable | D2: Credito No Renovable | E2: Aporte Cap. Propio
A3: Activo Fijo, sin IVA | B3: =DE!B7 -> 350000 | C3: 0 | D3: =CREDITOS!D3 -> 105000 | E3: =+B3-D3 -> 245000
A4: IVA Inversion | B4: =B3*0.21 -> 73500 | C4: 0 | D4: 0 | E4: =+B4 -> 73500
A6: Activo de trabajo | B6: =DE!B17 -> 35000 | D6: 0
A7: Inversión Activo Trabajo s/ IVA | B7: =DE!B25 -> 27500 | C7: =CREDITOS!C17 -> 13750 | D7: 0 | E7: =+B7-C7 -> 13750
A8: IVA Inversion | B8: =DE!C25 -> 3885 | C8: 0 | D8: 0 | E8: =+B8 -> 3885
A10: Inversiones s/ IVA | B10: =+B3+B7 -> 377500 | C10: =+SUM(C3:C9) -> 13750 | D10: =+SUM(D3:D9) -> 105000 | E10: =+B10-C10-D10 -> 258750
A11: IVA Inversion | B11: =+B4+B8 -> 77385 | C11: 0 | D11: 0 | E11: =+B11 -> 77385
A12: Inversion Total | B12: =+B10+B11 -> 454885 | C12: =+C10 -> 13750 | D12: =+D10 -> 105000 | E12: =SUM(E10:E11) -> 336135
A15: Costo total de lo vendido

Sheet CRes
A1: CUADRO DE RESULT. PROFORMA
A2: Año | B2: Ventas | C2: CTV | D2: U a/ HD e IIGG | E2: HD | F2: IIGG | G2: U d/HD e IIGG
A3: 1 | B3: =DE!B28*DE!D28 -> 300000 | C3: =DE!B32+DE!B33+CREDITOS!B39 -> 152875 | D3: =B3-C3 -> 147125 | E3: =D3*DE!$B$36 -> 14712.5 | F3: =(D3-E3)*DE!$B$37 -> 46344.375 | G3: =D3-E3-F3 -> 86068.125
A4: 2 | B4: =DE!B29*DE!D29 -> 500000 | C4: =DE!C32+DE!C33+CREDITOS!C39 -> 185875 | D4: =B4-C4 -> 314125 | E4: =D4*DE!$B$36 -> 31412.5 | F4: =(D4-E4)*DE!$B$37 -> 98949.375 | G4: =D4-E4-F4 -> 183763.12
A5: 3 | B5: =B4 -> 500000 | C5: =DE!C32+DE!C33+CREDITOS!D39 -> 168375 | D5: =B5-C5 -> 331625 | E5: =D5*DE!$B$36 -> 33162.5 | F5: =(D5-E5)*DE!$B$37 -> 104461.88 | G5: =D5-E5-F5 -> 194000.62
A7: BN inversor | B7: =SUM(G3:G5) -> 463831.88

Sheet Calendario Inv
A1: CALENDARIO DE INVERSIONES (incrementos)
B2: Año 0 | C2: Año 1 | D2: Totales
A3: a) Activo Fijo (incrementos) | B3: =DE!B3+DE!B4+DE!B5+CREDITOS!B32 -> 361000 | C3: =DE!B6 -> 10000 | D3: =+C3+B3 -> 371000
A4: IVA Inversión | B4: =DE!C7-DE!C6+0.21*CREDITOS!B32 -> 75810 | C4: =DE!C6 -> 2100 | D4: =+C4+B4 -> 77910
A5: Inversion total a) | B5: =+B4+B3 -> 436810 | C5: =+C3+C4 -> 12100 | D5: =+C5+B5 -> 448910
A7: AT (incrementos) | B7: =DE!B13+DE!B14 -> 10000 | C7: =DE!B15+DE!B16 -> 25000 | D7: =+C7+B7 -> 35000
A8: Inv. AT (incrementos) | B8: =DE!B21+DE!B22 -> 10000 | C8: =DE!B23+DE!B24 -> 17500 | D8: =+C8+B8 -> 27500
A9: IVA Inversion | B9: =DE!C21+DE!C22 -> 1680 | C9: =DE!C23+DE!C24 -> 2205 | D9: =+C9+B9 -> 3885
A10: Inversión Total AT | B10: =B8+B9 -> 11680 | C10: =+C8+C9 -> 19705 | D10: =+D9+D8 -> 31385
A12: Total s/ IVA | B12: =+B8+B3 -> 371000 | C12: =+C8+C3 -> 27500 | D12: =+D8+D3 -> 398500
A13: IVA Inversion | B13: =+B9+B4 -> 77490 | C13: =+C9+C4 -> 4305 | D13: =+D9+D4 -> 81795
A14: Inversion Total | B14: =+B13+B12 -> 448490 | C14: =+C13+C12 -> 31805 | D14: =+D13+D12 -> 480295

Sheet 2da Est. 
A1: 2° ESTRUCTURA FINANCIERA
B2: Año 0 | D2: Año 1 | F2: Totales
B3: AF | C3: Inv. AT | D3: AF | E3: Inv. AT | F3: AF | G3: Inv. AT | H3: Total | I3: %
A4: Inversion total | B4: ='Calendario Inv'!B5 -> 436810 | C4: ='Calendario Inv'!B10 -> 11680 | D4: ='Calendario Inv'!C5 -> 12100 | E4: ='Calendario Inv'!C10 -> 19705 | F4: =+B4+D4 -> 448910 | G4: =+C4+E4 -> 31385 | H4: =+G4+F4 -> 480295 | I4: =+I5+I6+I7 -> 1
A5: Crédito No Renovable | B5: ='1era estructura Financiera'!D3 -> 105000 | C5: 0 | D5: 0 | E5: 0 | F5: =+B5+D5 -> 105000 | G5: =+C5+E5 -> 0 | H5: =+G5+F5 -> 105000 | I5: =+H5/H4 -> 0.21861564
A6: Crédito Renovable | B6: 0 | C6: 0 | E6: ='1era estructura Financiera'!C7 -> 13750 | F6: =+B6+D6 -> 0 | G6: =+C6+E6 -> 13750 | H6: =+G6+F6 -> 13750 | I6: =+H6/H4 -> 0.028628239
A7: Aporte de Capital | B7: =+B4-B5 -> 331810 | C7: =+C4 -> 11680 | D7: =+D4 -> 12100 | E7: =+E4-E6 -> 5955 | F7: =+B7+D7 -> 343910 | G7: =+C7+E7 -> 17635 | H7: =+G7+F7 -> 361545 | I7: =+H7/H4 -> 0.75275612

Sheet RECUPERO IVA
A1: IVA diferencia
A2: IVA Plan Explotación | B2: Año 1 | C2: Año 2 | D2: Año 3
A3: IVA Percibido (ventas) | B3: =DE!F28 -> 63000 | C3: =DE!F29 -> 105000 | D3: =DE!F29 -> 105000
A4: IVA pagado (s/costos, sin intereses) | B4: =DE!B34 -> 18000 | C4: =DE!C34 -> 24000 | D4: =DE!C34 -> 24000
A5: IVA pagado (sobre intereses) | B5: =CREDITOS!D34*0.21 -> 4698.75 | C5: =CREDITOS!D35*0.21 -> 3228.75 | D5: =CREDITOS!D36*0.21 -> 1758.75
A6: IVA diferencia | B6: =+B3-B4-B5 -> 40301.25 | C6: =+C3-C4-C5 -> 77771.25 | D6: =+D3-D4-D5 -> 79241.25
A8: Cobro del Crédito Fiscal
B9: Crédito Fiscal | C9: IVA diferencia | D9: Recupero IVA
A10: Año 0 | B10: ='Calendario Inv'!B13 -> 77490 | C10: 0 | D10: 0
A11: Año 1 | B11: ='Calendario Inv'!D13 -> 81795 | C11: =B6 -> 40301.25 | D11: =C11 -> 40301.25
A12: Año 2 | B12: =B11-D11 -> 41493.75 | C12: =+C6 -> 77771.25 | D12: =B12 -> 41493.75 | E12: IVA DF al fisco | F12: =C12-D12 -> 36277.5
A13: Año 3 | B13: 0 | C13: =+D6 -> 79241.25 | D13: 0 | E13: IVA DF al fisco | F13: =C13 -> 79241.25

Sheet CFyU
B1: Año 0 | C1: Año 1 | D1: Año 2 | E1: Año 3 | F1: TOTALES
A2: FUENTES: Totales | B2: =SUM(B3:B9) -> 448490 | C2: =SUM(C3:C9) -> 372106.25 | D2: =SUM(D3:D9) -> 735863.12 | E2: =SUM(E3:E9) -> 995126.25 | F2: =SUM(F3:F9) -> 1862090
A3: Saldo ej. Anterior (Ac) | B3: 0 | C3: =B25 -> 0 | D3: =C25 -> 194369.38 | E3: =D25 -> 495126.25 | F3: 0
A4: Aporte de Cap. Propio | B4: ='2da Est. '!B7+'2da Est. '!C7 -> 343490 | C4: ='2da Est. '!D7+'2da Est. '!E7 -> 18055 | D4: 0 | E4: 0 | F4: =SUM(B4:E4) -> 361545
A5: Créditos Renovables | B5: 0 | C5: =CREDITOS!C17 -> 13750 | D5: 0 | E5: 0 | F5: =SUM(B5:E5) -> 13750
A6: Créditos No Renovables | B6: =CREDITOS!D3 -> 105000 | C6: 0 | D6: 0 | E6: 0 | F6: =SUM(B6:E6) -> 105000
A7: Ventas del ej. | B7: 0 | C7: =CRes!B3 -> 300000 | D7: =CRes!B4 -> 500000 | E7: =CRes!B5 -> 500000 | F7: =SUM(B7:E7) -> 1300000
A8: Recupero Crédito Fiscal | B8: 0 | C8: ='RECUPERO IVA'!D11 -> 40301.25 | D8: ='RECUPERO IVA'!D12 -> 41493.75 | E8: 0 | F8: =SUM(B8:E8) -> 81795
A9: Otros ingresos | B9: 0 | C9: 0 | D9: 0 | E9: 0 | F9: 0
A11: USOS: Totales | B11: =SUM(B12:B19) -> 448490 | C11: =SUM(C12:C19) -> 288236.88 | D11: =SUM(D12:D19) -> 351236.88 | E11: =SUM(E12:E19) -> 340999.38 | F11: =SUM(B11:E11) -> 1428963.1
A12: Activo Fijo | B12: ='Calendario Inv'!B3 -> 361000 | C12: ='Calendario Inv'!C3 -> 10000 | D12: 0 | E12: 0 | F12: =SUM(B12:E12) -> 371000
A13: Activo Trabajo | B13: ='Calendario Inv'!B7 -> 10000 | C13: ='Calendario Inv'!C7 -> 25000 | D13: 0 | E13: 0 | F13: =SUM(B13:E13) -> 35000
A14: Costo de lo vendido | B14: 0 | C14: =CRes!C3 -> 152875 | D14: =CRes!C4 -> 185875 | E14: =CRes!C5 -> 168375 | F14: =SUM(B14:E14) -> 507125
A15: IIGG | B15: 0 | C15: =CRes!F3 -> 46344.375 | D15: =CRes!F4 -> 98949.375 | E15: =CRes!F5 -> 104461.88 | F15: =SUM(B15:E15) -> 249755.62
A16: Cancelación de deudas | B16: 0 | C16: =CREDITOS!C10 -> 35000 | D16: =C16 -> 35000 | E16: =C16 -> 35000 | F16: =SUM(B16:E16) -> 105000
A17: HD | B17: 0 | C17: =CRes!E3 -> 14712.5 | D17: =CRes!E4 -> 31412.5 | E17: =CRes!E5 -> 33162.5 | F17: =SUM(B17:E17) -> 79287.5
A18: Dividendos Efectivo | B18: 0 | C18: 0 | D18: 0 | E18: 0 | F18: =SUM(B18:E18) -> 0
A19: IVA Inversion | B19: ='Calendario Inv'!B13 -> 77490 | C19: ='Calendario Inv'!C13 -> 4305 | D19: 0 | E19: 0 | F19: =SUM(B19:E19) -> 81795
A20: Otros egresos
A22: FUENTES - USOS | B22: =+B2-B11 -> 0 | C22: =+C2-C11 -> 83869.375 | D22: =+D2-D11 -> 384626.25 | E22: =+E2-E11 -> 654126.88 | F22: =F2-F11 -> 433126.88
A23: Amortizaciones del Ejercicio | B23: 0 | C23: =B35 -> 110500 | D23: =B36 -> 110500 | E23: =B37 -> 100000 | F23: =SUM(B23:E23) -> 321000
A25: Saldo al ej. Siguiente (Ac) | B25: =+B22+B23 -> 0 | C25: =+C22+C23 -> 194369.38 | D25: =+D22+D23 -> 495126.25 | E25: =+E22+E23 -> 754126.88 | F25: =F22+F23 -> 754126.88
A26: Saldo propio del ejercicio | B26: =+B25 -> 0 | C26: =C25-B25 -> 194369.38 | D26: =D25-C25 -> 300756.88 | E26: =E25-D25 -> 259000.62 | F26: =F25 -> 754126.88
A28: Amortizaciones ejercicio
A30: =SUM(DE!B3:B6) -> 350000 | B30: VO | E30: VERIFICACIONES
A31: 50000 | B31: VR | E31: BN inv | F31: =E25+A31+F13-F4-F5 -> 463831.88
E32: Bn inv | F32: =CRes!B7 -> 463831.88
A33: Amort int y gastos preop | B33: =CREDITOS!B32/2 -> 10500 | C33: se amortizan en 2 años | E33: BN mod | F33: =F32+SUM(CREDITOS!B39:D39) -> 530956.88
E34: BN puro | F34: =F31+SUM(CREDITOS!B39:D39)*(1-DE!B37)*(1-DE!B36) -> 503100
A35: Amort año 1 | B35: =(A30-A31)/3+B33 -> 110500
A36: Amort año 2 | B36: =B35 -> 110500
A37: Amort año 3 | B37: =(A30-A31)/3 -> 100000
