Workbook

Sheet Demanda
B2: Estimación anual de la demanda
B4: Población | D4: Cuantifiación
B5: Población total Arg | D5: 46000000
B6: % Celíacos | D6: 0.01
B7: Subpoblación celíacos | D7: =D6*D5 -> 460000
B8: Factor conviviente - demanda periférica | D8: =1.5 -> 1.5
B9: Mercado potencial | D9: =D8*D7 -> 690000
B10: % Habitantes grandes aglomerados | D10: 0.453
B11: Mercado objetivo - Aglomerados | D11: =D10*D9 -> 312570
B13: Consumo teórico anual por persona (según INDEC)
B14: Producto | D14: Consumo
B15: Panificados | D15: =1.2*12 -> 14.4 | E15: kg
B16: Galletitas saladas | D16: 5.04 | E16: kg
B17: Galletitas dulces | D17: 2.52 | E17: kg
B18: Total | D18: =SUM(D15:D17) -> 21.96 | E18: kg
B20: Consumo anual mercado objetivo | K20: Consumo anual mercado objetivo
B21: Producto | D21: Consumo | F21: Ventas anuales | H21: % Mkt Share | K21: Producto | M21: Consumo | O21: Ventas anuales | Q21: % Mkt Share
B22: Panificados | D22: =D15*$D$11 -> 4501008 | E22: kg | F22: =SUM(Produccion!E22:E24) -> 190000 | G22: kg | H22: =F22/D22*100 -> 4.2212767 | I22: % | K22: Panificados | M22: =D22/1000 -> 4501.008 | N22: Tn | O22: =F22/1000 -> 190 | P22: Tn | Q22: =O22/M22*100 -> 4.2212767 | R22: %
B23: Galletitas saladas | D23: =D16*$D$11 -> 1575352.8 | E23: kg | F23: =SUM(Produccion!E18) -> 7800 | G23: kg | H23: =F23/D23*100 -> 0.49512719 | I23: % | K23: Galletitas saladas | M23: =D23/1000 -> 1575.3528 | N23: Tn | O23: =F23/1000 -> 7.8 | P23: Tn | Q23: =O23/M23*100 -> 0.49512719 | R23: %
B24: Galletitas dulces | D24: =D17*$D$11 -> 787676.4 | E24: kg | F24: =Produccion!E14+Produccion!E15+Produccion!E17+Produccion!E20 -> 137300 | G24: kg | H24: =F24/D24*100 -> 17.431016 | I24: % | K24: Galletitas dulces | M24: =D24/1000 -> 787.6764 | N24: Tn | O24: =F24/1000 -> 137.3 | P24: Tn | Q24: =O24/M24*100 -> 17.431016 | R24: %
B25: Total | D25: =SUM(D22:D24) -> 6864037.2 | E25: kg | F25: =SUM(F22:F24) -> 335100 | G25: kg | H25: =F25/D25*100 -> 4.8819665 | I25: % | K25: Total | M25: =SUM(M22:M24) -> 6864.0372 | N25: Tn | O25: =SUM(O22:O24) -> 335.1 | P25: Tn | Q25: =O25/M25*100 -> 4.8819665 | R25: %
B28: Ventas SMAMS 2025 [kg] | D28: 1462828.9
B29: %Mkt share de SMAMS | D29: =D28/D25 -> 0.21311495
B31: Ventas anuales nuestro proyecto [kg] | D31: =Produccion!E25 -> 403000
B32: %Mkt share de nuestro proyecto | D32: =D31/D25 -> 0.058711803

Sheet Plan de ventas
B2: PRECIOS
H3: Supermercados | L3: Distribuidores
B4: COD | C4: Producto | E4: Peso [gr] | F4: Linea | G4: Costo MP/kg | H4: $/kg | I4: $/u | J4: $/u sugerido | K4: Margen | L4: $/kg | M4: $/u | N4: $/u sugerido | O4: Margen
B5: A03 | C5: Galletitas símil chocolinas | E5: 150 | F5: Clasicas | G5: 1499 | H5: 8127 | I5: 1220 | J5: 2067 | K5: 4.42 | L5: 9346 | M5: 1410 | N5: 2764 | O5: 5.23
B6: A06 | C6: Bizcochos sabor queso | E6: 150 | F6: Clasicas | G6: 975 | H6: 7989 | I6: 1200 | J6: 2033 | K6: 7.19 | L6: 9187 | M6: 1380 | N6: 2705 | O6: 8.42
B7: A08 | C7: Polvorones | E7: 150 | F7: Clasicas | G7: 1959 | H7: 7989 | I7: 1200 | J7: 2033 | K7: 3.08 | L7: 9187 | M7: 1380 | N7: 2705 | O7: 3.69
B8: B03 | C8: Budines free | E8: 180 | F8: Free | G8: 3799 | H8: 11296 | I8: 2040 | J8: 3456 | K8: 1.97 | L8: 12990 | M8: 2340 | N8: 4587 | O8: 2.42
B9: A02 | C9: Galletitas símil chocolinas free | E9: 150 | F9: Free | G9: 1723 | H9: 9102 | I9: 1370 | J9: 2321 | K9: 4.28 | L9: 10467 | M9: 1580 | N9: 3097 | O9: 5.08
B10: A07 | C10: Polvorones free | E10: 150 | F10: Free | G10: 2253 | H10: 8948 | I10: 1350 | J10: 2287 | K10: 2.97 | L10: 10290 | M10: 1550 | N10: 3038 | O10: 3.57
B11: A05 | C11: Bizcochos sabor queso free | E11: 150 | F11: Free | G11: 975 | H11: 7989 | I11: 1200 | J11: 2033 | K11: 7.19 | L11: 9187 | M11: 1380 | N11: 2705 | O11: 8.42
B12: A01 | C12: Chocolate con chips picante | E12: 150 | F12: Gourmet | G12: 1776 | H12: 9590 | I12: 1440 | J12: 2439 | K12: 4.4 | L12: 11028 | M12: 1660 | N12: 3254 | O12: 5.21
B13: A04 | C13: Pepas chocolate y batata | E13: 150 | F13: Gourmet | G13: 2405 | H13: 7935 | I13: 1200 | J13: 2033 | K13: 2.3 | L13: 9125 | M13: 1370 | N13: 2685 | O13: 2.79
B14: B01 | C14: Pan de molde | E14: 400 | F14: Panificados | G14: 3034 | H14: 9000 | I14: 3600 | J14: 6098 | K14: 1.97 | L14: 10350 | M14: 4140 | N14: 8115 | O14: 2.41
B15: B02 | C15: Budines | E15: 180 | F15: Panificados | G15: 3799 | H15: 11296 | I15: 2040 | J15: 3456 | K15: 1.97 | L15: 12990 | M15: 2340 | N15: 4587 | O15: 2.42
E17: Ventas # con 5,27% de mercado
B18: COD | C18: Producto | D18: Peso | E18: Cantidad [u] | F18: $ super | G18: % distr
B19: A01 | C19: Chocolate con chips picante 150gr. | D19: 150 | E19: =ROUNDUP(Produccion!E14*1000/D19,0) -> 400000 | F19: =VLOOKUP(B19,$B$4:$I$15,8,0) -> 1440 | G19: =VLOOKUP(B19,$B$4:$M$15,12,0) -> 1660
B20: A02 | C20: Galletitas símil chocolinas free 150gr. | D20: 150 | E20: =ROUNDUP(Produccion!E15*1000/D20,0) -> 52000 | F20: =VLOOKUP(B20,$B$4:$I$15,8,0) -> 1370 | G20: =VLOOKUP(B20,$B$4:$M$15,12,0) -> 1580
B21: A03 | C21: Galletitas símil chocolinas 150gr. | D21: 150 | E21: =ROUNDUP(Produccion!E16*1000/D21,0) -> 121334 | F21: =VLOOKUP(B21,$B$4:$I$15,8,0) -> 1220 | G21: =VLOOKUP(B21,$B$4:$M$15,12,0) -> 1410
B22: A04 | C22: Pepas chocolate y batata 150gr. | D22: 150 | E22: =ROUNDUP(Produccion!E17*1000/D22,0) -> 373334 | F22: =VLOOKUP(B22,$B$4:$I$15,8,0) -> 1200 | G22: =VLOOKUP(B22,$B$4:$M$15,12,0) -> 1370
B23: A05 | C23: Bizcochos sabor queso free 150gr. | D23: 150 | E23: =ROUNDUP(Produccion!E18*1000/D23,0) -> 52000 | F23: =VLOOKUP(B23,$B$4:$I$15,8,0) -> 1200 | G23: =VLOOKUP(B23,$B$4:$M$15,12,0) -> 1380
B24: A06 | C24: Bizcochos sabor queso 150gr. | D24: 150 | E24: =ROUNDUP(Produccion!E19*1000/D24,0) -> 121334 | F24: =VLOOKUP(B24,$B$4:$I$15,8,0) -> 1200 | G24: =VLOOKUP(B24,$B$4:$M$15,12,0) -> 1380
B25: A07 | C25: Polvorones free 150gr. | D25: 150 | E25: =ROUNDUP(Produccion!E20*1000/D25,0) -> 90000 | F25: =VLOOKUP(B25,$B$4:$I$15,8,0) -> 1350 | G25: =VLOOKUP(B25,$B$4:$M$15,12,0) -> 1550
B26: A08 | C26: Polvorones 150gr. | D26: 150 | E26: =ROUNDUP(Produccion!E21*1000/D26,0) -> 210000 | F26: =VLOOKUP(B26,$B$4:$I$15,8,0) -> 1200 | G26: =VLOOKUP(B26,$B$4:$M$15,12,0) -> 1380
B27: B01 | C27: Pan de molde 400gr. | D27: 400 | E27: =ROUNDUP(Produccion!E22*1000/D27,0) -> 175000 | F27: =VLOOKUP(B27,$B$4:$I$15,8,0) -> 3600 | G27: =VLOOKUP(B27,$B$4:$M$15,12,0) -> 4140
B28: B02 | C28: Budines vainilla/cítricos 180gr. | D28: 180 | E28: =ROUNDUP(Produccion!E23*1000/D28,0) -> 466667 | F28: =VLOOKUP(B28,$B$4:$I$15,8,0) -> 2040 | G28: =VLOOKUP(B28,$B$4:$M$15,12,0) -> 2340
B29: B03 | C29: Budines chocolate 180gr. | D29: 180 | E29: =ROUNDUP(Produccion!E24*1000/D29,0) -> 200000 | F29: =VLOOKUP(B29,$B$4:$I$15,8,0) -> 2040 | G29: =VLOOKUP(B29,$B$4:$M$15,12,0) -> 2340
C30: TOTAL | E30: =SUM(E19:E29) -> 2261669 | F30: =SUM(F19:F29) -> 17860 | G30: =SUM(G19:G29) -> 20530
F32: [Miles de unidades] | G32: [Miles de unidades] | H32: [Miles de unidades] | I32: [Miles de unidades] | J32: [Miles de unidades] | K32: [Miles de unidades] | L32: [Miles de unidades] | M32: [Miles de unidades] | N32: [Miles de unidades] | O32: [Miles de unidades] | S32: [kg] | T32: [kg] | U32: [kg] | V32: [kg] | W32: [kg] | X32: [kg] | Y32: [kg] | Z32: [kg] | AA32: [kg] | AB32: [kg]
B33: COD | C33: Producto | D33: Peso | E33: Linea | F33: Año 1 | G33: Año 2 | H33: Año 3 | I33: Año 4 | J33: Año 5 | K33: Año 6 | L33: Año 7 | M33: Año 8 | N33: Año 9 | O33: Año 10
B34: A01 | C34: Chocolate con chips picante 150gr. | D34: 150 | E34: Gourmet | F34: =ROUNDUP((E19/4*0.5)+E19/4*3,0)/1000 -> 350 | G34: =E19/1000 -> 400 | H34: =G34*1.04*1.02 -> 424.32 | I34: =H34*1.04*1.02 -> 450.11866 | J34: =I34*1.04*1.02 -> 477.48587 | K34: =J34*1.04*1.03 -> 511.48286 | L34: =K34*1.04*1.03 -> 547.90044 | M34: =L34*1.04*1.03 -> 586.91096 | N34: =M34*1.04*1.03 -> 628.69902 | O34: =N34*1.04*1.03 -> 673.46239
B35: A02 | C35: Galletitas símil chocolinas free 150gr. | D35: 150 | E35: Free | F35: =ROUNDUP((E20/4*0.5)+E20/4*3,0)/1000 -> 45.5 | G35: =E20/1000 -> 52 | H35: =G35*1.04*1.02 -> 55.1616 | I35: =H35*1.04*1.02 -> 58.515425 | J35: =I35*1.04*1.02 -> 62.073163 | K35: =J35*1.04*1.03 -> 66.492772 | L35: =K35*1.04*1.03 -> 71.227058 | M35: =L35*1.04*1.03 -> 76.298424 | N35: =M35*1.04*1.03 -> 81.730872 | O35: =N35*1.04*1.03 -> 87.55011
B36: A03 | C36: Galletitas símil chocolinas 150gr. | D36: 150 | E36: Clásicas | F36: =ROUNDUP((E21/4*0.5)+E21/4*3,0)/1000 -> 106.168 | G36: =E21/1000 -> 121.334 | H36: =G36*1.04*1.02 -> 128.71111 | I36: =H36*1.04*1.02 -> 136.53674 | J36: =I36*1.04*1.02 -> 144.83818 | K36: =J36*1.04*1.03 -> 155.15065 | L36: =K36*1.04*1.03 -> 166.19738 | M36: =L36*1.04*1.03 -> 178.03063 | N36: =M36*1.04*1.03 -> 190.70642 | O36: =N36*1.04*1.03 -> 204.28471
B37: A04 | C37: Pepas chocolate y batata 150gr. | D37: 150 | E37: Gourmet | F37: =ROUNDUP((E22/4*0.5)+E22/4*3,0)/1000 -> 326.668 | G37: =E22/1000 -> 373.334 | H37: =G37*1.04*1.02 -> 396.03271 | I37: =H37*1.04*1.02 -> 420.1115 | J37: =I37*1.04*1.02 -> 445.65427 | K37: =J37*1.04*1.03 -> 477.38486 | L37: =K37*1.04*1.03 -> 511.37466 | M37: =L37*1.04*1.03 -> 547.78454 | N37: =M37*1.04*1.03 -> 586.7868 | O37: =N37*1.04*1.03 -> 628.56602
B38: A05 | C38: Bizcochos sabor queso free 150gr. | D38: 150 | E38: Free | F38: =ROUNDUP((E23/4*0.5)+E23/4*3,0)/1000 -> 45.5 | G38: =E23/1000 -> 52 | H38: =G38*1.04*1.02 -> 55.1616 | I38: =H38*1.04*1.02 -> 58.515425 | J38: =I38*1.04*1.02 -> 62.073163 | K38: =J38*1.04*1.03 -> 66.492772 | L38: =K38*1.04*1.03 -> 71.227058 | M38: =L38*1.04*1.03 -> 76.298424 | N38: =M38*1.04*1.03 -> 81.730872 | O38: =N38*1.04*1.03 -> 87.55011
B39: A06 | C39: Bizcochos sabor queso 150gr. | D39: 150 | E39: Clásicas | F39: =ROUNDUP((E24/4*0.5)+E24/4*3,0)/1000 -> 106.168 | G39: =E24/1000 -> 121.334 | H39: =G39*1.04*1.02 -> 128.71111 | I39: =H39*1.04*1.02 -> 136.53674 | J39: =I39*1.04*1.02 -> 144.83818 | K39: =J39*1.04*1.03 -> 155.15065 | L39: =K39*1.04*1.03 -> 166.19738 | M39: =L39*1.04*1.03 -> 178.03063 | N39: =M39*1.04*1.03 -> 190.70642 | O39: =N39*1.04*1.03 -> 204.28471
B40: A07 | C40: Polvorones free 150gr. | D40: 150 | E40: Free | F40: =ROUNDUP((E25/4*0.5)+E25/4*3,0)/1000 -> 78.75 | G40: =E25/1000 -> 90 | H40: =G40*1.04*1.02 -> 95.472 | I40: =H40*1.04*1.02 -> 101.2767 | J40: =I40*1.04*1.02 -> 107.43432 | K40: =J40*1.04*1.03 -> 115.08364 | L40: =K40*1.04*1.03 -> 123.2776 | M40: =L40*1.04*1.03 -> 132.05497 | N40: =M40*1.04*1.03 -> 141.45728 | O40: =N40*1.04*1.03 -> 151.52904
B41: A08 | C41: Polvorones 150gr. | D41: 150 | E41: Clásicas | F41: =ROUNDUP((E26/4*0.5)+E26/4*3,0)/1000 -> 183.75 | G41: =E26/1000 -> 210 | H41: =G41*1.04*1.02 -> 222.768 | I41: =H41*1.04*1.02 -> 236.31229 | J41: =I41*1.04*1.02 -> 250.68008 | K41: =J41*1.04*1.03 -> 268.5285 | L41: =K41*1.04*1.03 -> 287.64773 | M41: =L41*1.04*1.03 -> 308.12825 | N41: =M41*1.04*1.03 -> 330.06698 | O41: =N41*1.04*1.03 -> 353.56775
B42: B01 | C42: Pan de molde 400gr. | D42: 400 | E42: Panificados | F42: =ROUNDUP((E27/4*0.5)+E27/4*3,0)/1000 -> 153.125 | G42: =E27/1000 -> 175 | H42: =G42*1.04*1.02 -> 185.64 | I42: =H42*1.04*1.02 -> 196.92691 | J42: =I42*1.04*1.02 -> 208.90007 | K42: =J42*1.04*1.03 -> 223.77375 | L42: =K42*1.04*1.03 -> 239.70644 | M42: =L42*1.04*1.03 -> 256.77354 | N42: =M42*1.04*1.03 -> 275.05582 | O42: =N42*1.04*1.03 -> 294.63979
B43: B02 | C43: Budines vainilla/cítricos 180gr. | D43: 180 | E43: Panificados | F43: =ROUNDUP((E28/4*0.5)+E28/4*3,0)/1000 -> 408.334 | G43: =E28/1000 -> 466.667 | H43: =G43*1.04*1.02 -> 495.04035 | I43: =H43*1.04*1.02 -> 525.13881 | J43: =I43*1.04*1.02 -> 557.06725 | K43: =J43*1.04*1.03 -> 596.73043 | L43: =K43*1.04*1.03 -> 639.21764 | M43: =L43*1.04*1.03 -> 684.72994 | N43: =M43*1.04*1.03 -> 733.48271 | O43: =N43*1.04*1.03 -> 785.70668
B44: B03 | C44: Budines chocolate 180gr. | D44: 180 | E44: Free | F44: =ROUNDUP((E29/4*0.5)+E29/4*3,0)/1000 -> 175 | G44: =E29/1000 -> 200 | H44: =G44*1.04*1.02 -> 212.16 | I44: =H44*1.04*1.02 -> 225.05933 | J44: =I44*1.04*1.02 -> 238.74294 | K44: =J44*1.04*1.03 -> 255.74143 | L44: =K44*1.04*1.03 -> 273.95022 | M44: =L44*1.04*1.03 -> 293.45548 | N44: =M44*1.04*1.03 -> 314.34951 | O44: =N44*1.04*1.03 -> 336.73119
C45: TOTAL | F45: =SUM(F34:F44) -> 1978.963 | G45: =SUM(G34:G44) -> 2261.669 | H45: =SUM(H34:H44) -> 2399.1785 | I45: =SUM(I34:I44) -> 2545.0485 | J45: =SUM(J34:J44) -> 2699.7875 | K45: =SUM(K34:K44) -> 2892.0123 | L45: =SUM(L34:L44) -> 3097.9236 | M45: =SUM(M34:M44) -> 3318.4958 | ... O45: =SUM(O34:O44) -> 3807.8725
F47: [Tn] | G47: [Tn] | H47: [Tn] | I47: [Tn] | J47: [Tn] | K47: [Tn] | L47: [Tn] | M47: [Tn] | N47: [Tn] | O47: [Tn]
B48: COD | C48: Producto | D48: Peso | E48: Linea | F48: Año 1 | G48: Año 2 | H48: Año 3 | I48: Año 4 | J48: Año 5 | K48: Año 6 | L48: Año 7 | M48: Año 8 | N48: Año 9 | O48: Año 10 | P48: Ponderacion
B49: A01 | C49: Chocolate con chips picante 150gr. | D49: 150 | E49: Gourmet | F49: =F34*1000*$D34/1000000 -> 52.5 | G49: =G34*1000*$D34/1000000 -> 60 | H49: =H34*1000*$D34/1000000 -> 63.648 | I49: =I34*1000*$D34/1000000 -> 67.517798 | J49: =J34*1000*$D34/1000000 -> 71.622881 | K49: =K34*1000*$D34/1000000 -> 76.72243 | L49: =L34*1000*$D34/1000000 -> 82.185067 | M49: =M34*1000*$D34/1000000 -> 88.036643 | ... O49: =O34*1000*$D34/1000000 -> 101.01936 | P49: =O49/SUM($O$49:$O$56) -> 0.28168974
B50: A02 | C50: Galletitas símil chocolinas free 150gr. | D50: 150 | E50: Free | F50: =F35*1000*$D35/1000000 -> 6.825 | G50: =G35*1000*$D35/1000000 -> 7.8 | H50: =H35*1000*$D35/1000000 -> 8.27424 | I50: =I35*1000*$D35/1000000 -> 8.7773138 | J50: =J35*1000*$D35/1000000 -> 9.3109745 | K50: =K35*1000*$D35/1000000 -> 9.9739159 | L50: =L35*1000*$D35/1000000 -> 10.684059 | M50: =M35*1000*$D35/1000000 -> 11.444764 | ... O50: =O35*1000*$D35/1000000 -> 13.132517 | P50: =O50/SUM($O$49:$O$56) -> 0.036619667
B51: A03 | C51: Galletitas símil chocolinas 150gr. | D51: 150 | E51: Clásicas | F51: =F36*1000*$D36/1000000 -> 15.9252 | G51: =G36*1000*$D36/1000000 -> 18.2001 | H51: =H36*1000*$D36/1000000 -> 19.306666 | I51: =I36*1000*$D36/1000000 -> 20.480511 | J51: =J36*1000*$D36/1000000 -> 21.725726 | K51: =K36*1000*$D36/1000000 -> 23.272598 | L51: =L36*1000*$D36/1000000 -> 24.929607 | M51: =M36*1000*$D36/1000000 -> 26.704595 | ... O51: =O36*1000*$D36/1000000 -> 30.642707 | P51: =O51/SUM($O$49:$O$56) -> 0.085446359
B52: A04 | C52: Pepas chocolate y batata 150gr. | D52: 150 | E52: Gourmet | F52: =F37*1000*$D37/1000000 -> 49.0002 | G52: =G37*1000*$D37/1000000 -> 56.0001 | H52: =H37*1000*$D37/1000000 -> 59.404906 | I52: =I37*1000*$D37/1000000 -> 63.016724 | J52: =J37*1000*$D37/1000000 -> 66.848141 | K52: =K37*1000*$D37/1000000 -> 71.607729 | L52: =L37*1000*$D37/1000000 -> 76.706199 | M52: =M37*1000*$D37/1000000 -> 82.167681 | ... O52: =O37*1000*$D37/1000000 -> 94.284902 | P52: =O52/SUM($O$49:$O$56) -> 0.2629109
B53: A05 | C53: Bizcochos sabor queso free 150gr. | D53: 150 | E53: Free | F53: =F38*1000*$D38/1000000 -> 6.825 | G53: =G38*1000*$D38/1000000 -> 7.8 | H53: =H38*1000*$D38/1000000 -> 8.27424 | I53: =I38*1000*$D38/1000000 -> 8.7773138 | J53: =J38*1000*$D38/1000000 -> 9.3109745 | K53: =K38*1000*$D38/1000000 -> 9.9739159 | L53: =L38*1000*$D38/1000000 -> 10.684059 | M53: =M38*1000*$D38/1000000 -> 11.444764 | ... O53: =O38*1000*$D38/1000000 -> 13.132517 | P53: =O53/SUM($O$49:$O$56) -> 0.036619667
B54: A06 | C54: Bizcochos sabor queso 150gr. | D54: 150 | E54: Clásicas | F54: =F39*1000*$D39/1000000 -> 15.9252 | G54: =G39*1000*$D39/1000000 -> 18.2001 | H54: =H39*1000*$D39/1000000 -> 19.306666 | I54: =I39*1000*$D39/1000000 -> 20.480511 | J54: =J39*1000*$D39/1000000 -> 21.725726 | K54: =K39*1000*$D39/1000000 -> 23.272598 | L54: =L39*1000*$D39/1000000 -> 24.929607 | M54: =M39*1000*$D39/1000000 -> 26.704595 | ... O54: =O39*1000*$D39/1000000 -> 30.642707 | P54: =O54/SUM($O$49:$O$56) -> 0.085446359
B55: A07 | C55: Polvorones free 150gr. | D55: 150 | E55: Free | F55: =F40*1000*$D40/1000000 -> 11.8125 | G55: =G40*1000*$D40/1000000 -> 13.5 | H55: =H40*1000*$D40/1000000 -> 14.3208 | I55: =I40*1000*$D40/1000000 -> 15.191505 | J55: =J40*1000*$D40/1000000 -> 16.115148 | K55: =K40*1000*$D40/1000000 -> 17.262547 | L55: =L40*1000*$D40/1000000 -> 18.49164 | M55: =M40*1000*$D40/1000000 -> 19.808245 | ... O55: =O40*1000*$D40/1000000 -> 22.729356 | P55: =O55/SUM($O$49:$O$56) -> 0.063380192
B56: A08 | C56: Polvorones 150gr. | D56: 150 | E56: Clásicas | F56: =F41*1000*$D41/1000000 -> 27.5625 | G56: =G41*1000*$D41/1000000 -> 31.5 | H56: =H41*1000*$D41/1000000 -> 33.4152 | I56: =I41*1000*$D41/1000000 -> 35.446844 | J56: =J41*1000*$D41/1000000 -> 37.602012 | K56: =K41*1000*$D41/1000000 -> 40.279276 | L56: =L41*1000*$D41/1000000 -> 43.14716 | M56: =M41*1000*$D41/1000000 -> 46.219238 | ... O56: =O41*1000*$D41/1000000 -> 53.035163 | P56: =O56/SUM($O$49:$O$56) -> 0.14788712 | Q56: =SUM(P49:P56) -> 1
B57: B01 | C57: Pan de molde 400gr. | D57: 400 | E57: Panificados | F57: =F42*1000*$D42/1000000 -> 61.25 | G57: =G42*1000*$D42/1000000 -> 70 | H57: =H42*1000*$D42/1000000 -> 74.256 | I57: =I42*1000*$D42/1000000 -> 78.770765 | J57: =J42*1000*$D42/1000000 -> 83.560027 | K57: =K42*1000*$D42/1000000 -> 89.509501 | L57: =L42*1000*$D42/1000000 -> 95.882578 | M57: =M42*1000*$D42/1000000 -> 102.70942 | ... O57: =O42*1000*$D42/1000000 -> 117.85592 | P57: =O57/SUM($O$57:$O$59) -> 0.36842094
B58: B02 | C58: Budines vainilla/cítricos 180gr. | D58: 180 | E58: Panificados | F58: =F43*1000*$D43/1000000 -> 73.50012 | G58: =G43*1000*$D43/1000000 -> 84.00006 | H58: =H43*1000*$D43/1000000 -> 89.107264 | I58: =I43*1000*$D43/1000000 -> 94.524985 | J58: =J43*1000*$D43/1000000 -> 100.2721 | K58: =K43*1000*$D43/1000000 -> 107.41148 | L58: =L43*1000*$D43/1000000 -> 115.05918 | M58: =M43*1000*$D43/1000000 -> 123.25139 | ... O58: =O43*1000*$D43/1000000 -> 141.4272 | P58: =O58/SUM($O$57:$O$59) -> 0.44210544
B59: B03 | C59: Budines chocolate 180gr. | D59: 180 | E59: Free | F59: =F44*1000*$D44/1000000 -> 31.5 | G59: =G44*1000*$D44/1000000 -> 36 | H59: =H44*1000*$D44/1000000 -> 38.1888 | I59: =I44*1000*$D44/1000000 -> 40.510679 | J59: =J44*1000*$D44/1000000 -> 42.973728 | K59: =K44*1000*$D44/1000000 -> 46.033458 | L59: =L44*1000*$D44/1000000 -> 49.31104 | M59: =M44*1000*$D44/1000000 -> 52.821986 | ... O59: =O44*1000*$D44/1000000 -> 60.611615 | P59: =O59/SUM($O$57:$O$59) -> 0.18947362 | Q59: =SUM(P57:P59) -> 1
C60: TOTAL | F60: =SUM(F49:F59) -> 352.62572 | G60: =SUM(G49:G59) -> 403.00036 | H60: =SUM(H49:H59) -> 427.50278 | I60: =SUM(I49:I59) -> 453.49495 | J60: =SUM(J49:J59) -> 481.06744 | K60: =SUM(K49:K59) -> 515.31945 | L60: =SUM(L49:L59) -> 552.01019 | M60: =SUM(M49:M59) -> 591.31332 | ... P60: =SUM(P49:P59) -> 2
F63: [ARS MM] | G63: [ARS MM] | H63: [ARS MM] | I63: [ARS MM] | J63: [ARS MM] | K63: [ARS MM] | L63: [ARS MM] | M63: [ARS MM] | N63: [ARS MM] | O63: [ARS MM]
B64: COD | C64: Producto | D64: Peso | E64: Linea | F64: Año 1 | G64: Año 2 | H64: Año 3 | I64: Año 4 | J64: Año 5 | K64: Año 6 | L64: Año 7 | M64: Año 8 | N64: Año 9 | O64: Año 10
B65: A01 | C65: Chocolate con chips picante 150gr. | D65: 150 | E65: Gourmet | F65: =(((F34*1000)/2)*($F19+$G19))/1000000 -> 542.5 | G65: =(((G34*1000)/2)*($F19+$G19))/1000000 -> 620 | H65: =(((H34*1000)/2)*($F19+$G19))/1000000 -> 657.696 | I65: =(((I34*1000)/2)*($F19+$G19))/1000000 -> 697.68392 | J65: =(((J34*1000)/2)*($F19+$G19))/1000000 -> 740.1031 | K65: =(((K34*1000)/2)*($F19+$G19))/1000000 -> 792.79844 | L65: =(((L34*1000)/2)*($F19+$G19))/1000000 -> 849.24569 | M65: =(((M34*1000)/2)*($F19+$G19))/1000000 -> 909.71198 | ... O65: =(((O34*1000)/2)*($F19+$G19))/1000000 -> 1043.8667
B66: A02 | C66: Galletitas símil chocolinas free 150gr. | D66: 150 | E66: Free | F66: =(((F35*1000)/2)*(F20+G20))/1000000 -> 67.1125 | G66: =(((G35*1000)/2)*($F20+$G20))/1000000 -> 76.7 | H66: =(((H35*1000)/2)*($F20+$G20))/1000000 -> 81.36336 | I66: =(((I35*1000)/2)*($F20+$G20))/1000000 -> 86.310252 | J66: =(((J35*1000)/2)*($F20+$G20))/1000000 -> 91.557916 | K66: =(((K35*1000)/2)*($F20+$G20))/1000000 -> 98.076839 | L66: =(((L35*1000)/2)*($F20+$G20))/1000000 -> 105.05991 | M66: =(((M35*1000)/2)*($F20+$G20))/1000000 -> 112.54018 | N66: =(((N35*1000)/2)*($F20+$G20))/1000000 -> 120.55304 | O66: =(((O35*1000)/2)*($F20+$G20))/1000000 -> 129.13641 | R66: Grupo | S66: Año 1 | T66: Año 2 | U66: Año 3 | V66: Año 4 | W66: Año 5 | X66: Año 6 | Y66: Año 7 | Z66: Año 8 | AA66: Año 9 | AB66: Año 10
B67: A03 | C67: Galletitas símil chocolinas 150gr. | D67: 150 | E67: Clásicas | F67: =(((F36*1000)/2)*(F21+G21))/1000000 -> 139.61092 | G67: =(((G36*1000)/2)*($F21+$G21))/1000000 -> 159.55421 | H67: =(((H36*1000)/2)*($F21+$G21))/1000000 -> 169.25511 | I67: =(((I36*1000)/2)*($F21+$G21))/1000000 -> 179.54582 | J67: =(((J36*1000)/2)*($F21+$G21))/1000000 -> 190.4622 | K67: =(((K36*1000)/2)*($F21+$G21))/1000000 -> 204.02311 | L67: =(((L36*1000)/2)*($F21+$G21))/1000000 -> 218.54956 | M67: =(((M36*1000)/2)*($F21+$G21))/1000000 -> 234.11028 | N67: =(((N36*1000)/2)*($F21+$G21))/1000000 -> 250.77894 | O67: =(((O36*1000)/2)*($F21+$G21))/1000000 -> 268.6344 | R67: Gourmet | S67: =SUMIFS(F$49:F$59,$E$49:$E$59,$R67) -> 101.5002 | T67: =SUMIFS(G$49:G$59,$E$49:$E$59,$R67) -> 116.0001 | U67: =SUMIFS(H$49:H$59,$E$49:$E$59,$R67) -> 123.05291 | V67: =SUMIFS(I$49:I$59,$E$49:$E$59,$R67) -> 130.53452 | W67: =SUMIFS(J$49:J$59,$E$49:$E$59,$R67) -> 138.47102 | X67: =SUMIFS(K$49:K$59,$E$49:$E$59,$R67) -> 148.33016 | Y67: =SUMIFS(L$49:L$59,$E$49:$E$59,$R67) -> 158.89127 | Z67: =SUMIFS(M$49:M$59,$E$49:$E$59,$R67) -> 170.20432 | ... AB67: =SUMIFS(O$49:O$59,$E$49:$E$59,$R67) -> 195.30426
B68: A04 | C68: Pepas chocolate y batata 150gr. | D68: 150 | E68: Gourmet | F68: =(((F37*1000)/2)*(F22+G22))/1000000 -> 419.76838 | G68: =(((G37*1000)/2)*($F22+$G22))/1000000 -> 479.73419 | H68: =(((H37*1000)/2)*($F22+$G22))/1000000 -> 508.90203 | I68: =(((I37*1000)/2)*($F22+$G22))/1000000 -> 539.84327 | J68: =(((J37*1000)/2)*($F22+$G22))/1000000 -> 572.66574 | K68: =(((K37*1000)/2)*($F22+$G22))/1000000 -> 613.43954 | L68: =(((L37*1000)/2)*($F22+$G22))/1000000 -> 657.11644 | M68: =(((M37*1000)/2)*($F22+$G22))/1000000 -> 703.90313 | N68: =(((N37*1000)/2)*($F22+$G22))/1000000 -> 754.02103 | O68: =(((O37*1000)/2)*($F22+$G22))/1000000 -> 807.70733 | R68: Free | S68: =SUMIFS(F$49:F$59,$E$49:$E$59,$R68) -> 56.9625 | T68: =SUMIFS(G$49:G$59,$E$49:$E$59,$R68) -> 65.1 | U68: =SUMIFS(H$49:H$59,$E$49:$E$59,$R68) -> 69.05808 | V68: =SUMIFS(I$49:I$59,$E$49:$E$59,$R68) -> 73.256811 | W68: =SUMIFS(J$49:J$59,$E$49:$E$59,$R68) -> 77.710825 | X68: =SUMIFS(K$49:K$59,$E$49:$E$59,$R68) -> 83.243836 | Y68: =SUMIFS(L$49:L$59,$E$49:$E$59,$R68) -> 89.170797 | Z68: =SUMIFS(M$49:M$59,$E$49:$E$59,$R68) -> 95.519758 | ... AB68: =SUMIFS(O$49:O$59,$E$49:$E$59,$R68) -> 109.606
B69: A05 | C69: Bizcochos sabor queso free 150gr. | D69: 150 | E69: Free | F69: =(((F38*1000)/2)*(F23+G23))/1000000 -> 58.695 | G69: =(((G38*1000)/2)*($F23+$G23))/1000000 -> 67.08 | H69: =(((H38*1000)/2)*($F23+$G23))/1000000 -> 71.158464 | I69: =(((I38*1000)/2)*($F23+$G23))/1000000 -> 75.484899 | J69: =(((J38*1000)/2)*($F23+$G23))/1000000 -> 80.07438 | K69: =(((K38*1000)/2)*($F23+$G23))/1000000 -> 85.775676 | L69: =(((L38*1000)/2)*($F23+$G23))/1000000 -> 91.882904 | M69: =(((M38*1000)/2)*($F23+$G23))/1000000 -> 98.424967 | N69: =(((N38*1000)/2)*($F23+$G23))/1000000 -> 105.43282 | O69: =(((O38*1000)/2)*($F23+$G23))/1000000 -> 112.93964 | R69: Clásicas | S69: =SUMIFS(F$49:F$59,$E$49:$E$59,$R69) -> 59.4129 | T69: =SUMIFS(G$49:G$59,$E$49:$E$59,$R69) -> 67.9002 | U69: =SUMIFS(H$49:H$59,$E$49:$E$59,$R69) -> 72.028532 | V69: =SUMIFS(I$49:I$59,$E$49:$E$59,$R69) -> 76.407867 | W69: =SUMIFS(J$49:J$59,$E$49:$E$59,$R69) -> 81.053465 | X69: =SUMIFS(K$49:K$59,$E$49:$E$59,$R69) -> 86.824472 | Y69: =SUMIFS(L$49:L$59,$E$49:$E$59,$R69) -> 93.006374 | Z69: =SUMIFS(M$49:M$59,$E$49:$E$59,$R69) -> 99.628428 | ... AB69: =SUMIFS(O$49:O$59,$E$49:$E$59,$R69) -> 114.32058
B70: A06 | C70: Bizcochos sabor queso 150gr. | D70: 150 | E70: Clásicas | F70: =(((F39*1000)/2)*(F24+G24))/1000000 -> 136.95672 | G70: =(((G39*1000)/2)*($F24+$G24))/1000000 -> 156.52086 | H70: =(((H39*1000)/2)*($F24+$G24))/1000000 -> 166.03733 | I70: =(((I39*1000)/2)*($F24+$G24))/1000000 -> 176.1324 | J70: =(((J39*1000)/2)*($F24+$G24))/1000000 -> 186.84125 | K70: =(((K39*1000)/2)*($F24+$G24))/1000000 -> 200.14434 | L70: =(((L39*1000)/2)*($F24+$G24))/1000000 -> 214.39462 | M70: =(((M39*1000)/2)*($F24+$G24))/1000000 -> 229.65952 | N70: =(((N39*1000)/2)*($F24+$G24))/1000000 -> 246.01128 | O70: =(((O39*1000)/2)*($F24+$G24))/1000000 -> 263.52728 | R70: Panificados | S70: =SUMIFS(F$49:F$59,$E$49:$E$59,$R70) -> 134.75012 | T70: =SUMIFS(G$49:G$59,$E$49:$E$59,$R70) -> 154.00006 | U70: =SUMIFS(H$49:H$59,$E$49:$E$59,$R70) -> 163.36326 | V70: =SUMIFS(I$49:I$59,$E$49:$E$59,$R70) -> 173.29575 | W70: =SUMIFS(J$49:J$59,$E$49:$E$59,$R70) -> 183.83213 | X70: =SUMIFS(K$49:K$59,$E$49:$E$59,$R70) -> 196.92098 | Y70: =SUMIFS(L$49:L$59,$E$49:$E$59,$R70) -> 210.94175 | Z70: =SUMIFS(M$49:M$59,$E$49:$E$59,$R70) -> 225.96081 | ... AB70: =SUMIFS(O$49:O$59,$E$49:$E$59,$R70) -> 259.28312
B71: A07 | C71: Polvorones free 150gr. | D71: 150 | E71: Free | F71: =(((F40*1000)/2)*(F25+G25))/1000000 -> 114.1875 | G71: =(((G40*1000)/2)*($F25+$G25))/1000000 -> 130.5 | H71: =(((H40*1000)/2)*($F25+$G25))/1000000 -> 138.4344 | I71: =(((I40*1000)/2)*($F25+$G25))/1000000 -> 146.85121 | J71: =(((J40*1000)/2)*($F25+$G25))/1000000 -> 155.77977 | K71: =(((K40*1000)/2)*($F25+$G25))/1000000 -> 166.87128 | L71: =(((L40*1000)/2)*($F25+$G25))/1000000 -> 178.75252 | M71: =(((M40*1000)/2)*($F25+$G25))/1000000 -> 191.4797 | N71: =(((N40*1000)/2)*($F25+$G25))/1000000 -> 205.11305 | O71: =(((O40*1000)/2)*($F25+$G25))/1000000 -> 219.7171
B72: A08 | C72: Polvorones 150gr. | D72: 150 | E72: Clásicas | F72: =(((F41*1000)/2)*(F26+G26))/1000000 -> 237.0375 | G72: =(((G41*1000)/2)*($F26+$G26))/1000000 -> 270.9 | H72: =(((H41*1000)/2)*($F26+$G26))/1000000 -> 287.37072 | I72: =(((I41*1000)/2)*($F26+$G26))/1000000 -> 304.84286 | J72: =(((J41*1000)/2)*($F26+$G26))/1000000 -> 323.37731 | K72: =(((K41*1000)/2)*($F26+$G26))/1000000 -> 346.40177 | L72: =(((L41*1000)/2)*($F26+$G26))/1000000 -> 371.06558 | M72: =(((M41*1000)/2)*($F26+$G26))/1000000 -> 397.48544 | N72: =(((N41*1000)/2)*($F26+$G26))/1000000 -> 425.78641 | O72: =(((O41*1000)/2)*($F26+$G26))/1000000 -> 456.1024 | R72: Grupo | S72: Año 1 | T72: Año 2 | U72: Año 3 | V72: Año 4 | W72: Año 5 | X72: Año 6 | Y72: Año 7 | Z72: Año 8 | AA72: Año 9 | AB72: Año 10
B73: B01 | C73: Pan de molde 400gr. | D73: 400 | E73: Panificados | F73: =(((F42*1000)/2)*(F27+G27))/1000000 -> 592.59375 | G73: =(((G42*1000)/2)*($F27+$G27))/1000000 -> 677.25 | H73: =(((H42*1000)/2)*($F27+$G27))/1000000 -> 718.4268 | I73: =(((I42*1000)/2)*($F27+$G27))/1000000 -> 762.10715 | J73: =(((J42*1000)/2)*($F27+$G27))/1000000 -> 808.44326 | K73: =(((K42*1000)/2)*($F27+$G27))/1000000 -> 866.00442 | L73: =(((L42*1000)/2)*($F27+$G27))/1000000 -> 927.66394 | M73: =(((M42*1000)/2)*($F27+$G27))/1000000 -> 993.71361 | N73: =(((N42*1000)/2)*($F27+$G27))/1000000 -> 1064.466 | O73: =(((O42*1000)/2)*($F27+$G27))/1000000 -> 1140.256 | R73: Gourmet | S73: =SUMIFS(F$49:F$59,$E$49:$E$59,$R73) -> 101.5002 | T73: =SUMIFS(G$49:G$59,$E$49:$E$59,$R73) -> 116.0001 | U73: =SUMIFS(H$49:H$59,$E$49:$E$59,$R73) -> 123.05291 | V73: =SUMIFS(I$49:I$59,$E$49:$E$59,$R73) -> 130.53452 | W73: =SUMIFS(J$49:J$59,$E$49:$E$59,$R73) -> 138.47102 | X73: =SUMIFS(K$49:K$59,$E$49:$E$59,$R73) -> 148.33016 | Y73: =SUMIFS(L$49:L$59,$E$49:$E$59,$R73) -> 158.89127 | Z73: =SUMIFS(M$49:M$59,$E$49:$E$59,$R73) -> 170.20432 | ... AB73: =SUMIFS(O$49:O$59,$E$49:$E$59,$R73) -> 195.30426
B74: B02 | C74: Budines vainilla/cítricos 180gr. | D74: 180 | E74: Panificados | F74: =(((F43*1000)/2)*(F28+G28))/1000000 -> 894.25146 | G74: =(((G43*1000)/2)*($F28+$G28))/1000000 -> 1022.0007 | H74: =(((H43*1000)/2)*($F28+$G28))/1000000 -> 1084.1384 | I74: =(((I43*1000)/2)*($F28+$G28))/1000000 -> 1150.054 | J74: =(((J43*1000)/2)*($F28+$G28))/1000000 -> 1219.9773 | K74: =(((K43*1000)/2)*($F28+$G28))/1000000 -> 1306.8397 | L74: =(((L43*1000)/2)*($F28+$G28))/1000000 -> 1399.8866 | M74: =(((M43*1000)/2)*($F28+$G28))/1000000 -> 1499.5586 | N74: =(((N43*1000)/2)*($F28+$G28))/1000000 -> 1606.3271 | O74: =(((O43*1000)/2)*($F28+$G28))/1000000 -> 1720.6976 | R74: Free | S74: =SUMIFS(F$49:F$59,$E$49:$E$59,$R74) -> 56.9625 | T74: =SUMIFS(G$49:G$59,$E$49:$E$59,$R74) -> 65.1 | U74: =SUMIFS(H$49:H$59,$E$49:$E$59,$R74) -> 69.05808 | V74: =SUMIFS(I$49:I$59,$E$49:$E$59,$R74) -> 73.256811 | W74: =SUMIFS(J$49:J$59,$E$49:$E$59,$R74) -> 77.710825 | X74: =SUMIFS(K$49:K$59,$E$49:$E$59,$R74) -> 83.243836 | Y74: =SUMIFS(L$49:L$59,$E$49:$E$59,$R74) -> 89.170797 | Z74: =SUMIFS(M$49:M$59,$E$49:$E$59,$R74) -> 95.519758 | ... AB74: =SUMIFS(O$49:O$59,$E$49:$E$59,$R74) -> 109.606
B75: B03 | C75: Budines chocolate 180gr. | D75: 180 | E75: Free | F75: =(((F44*1000)/2)*(F29+G29))/1000000 -> 383.25 | G75: =(((G44*1000)/2)*($F29+$G29))/1000000 -> 438 | H75: =(((H44*1000)/2)*($F29+$G29))/1000000 -> 464.6304 | I75: =(((I44*1000)/2)*($F29+$G29))/1000000 -> 492.87993 | J75: =(((J44*1000)/2)*($F29+$G29))/1000000 -> 522.84703 | K75: =(((K44*1000)/2)*($F29+$G29))/1000000 -> 560.07374 | L75: =(((L44*1000)/2)*($F29+$G29))/1000000 -> 599.95099 | M75: =(((M44*1000)/2)*($F29+$G29))/1000000 -> 642.6675 | N75: =(((N44*1000)/2)*($F29+$G29))/1000000 -> 688.42542 | O75: =(((O44*1000)/2)*($F29+$G29))/1000000 -> 737.44131 | R75: Clásicas | S75: =SUMIFS(F$49:F$59,$E$49:$E$59,$R75) -> 59.4129 | T75: =SUMIFS(G$49:G$59,$E$49:$E$59,$R75) -> 67.9002 | U75: =SUMIFS(H$49:H$59,$E$49:$E$59,$R75) -> 72.028532 | V75: =SUMIFS(I$49:I$59,$E$49:$E$59,$R75) -> 76.407867 | W75: =SUMIFS(J$49:J$59,$E$49:$E$59,$R75) -> 81.053465 | X75: =SUMIFS(K$49:K$59,$E$49:$E$59,$R75) -> 86.824472 | Y75: =SUMIFS(L$49:L$59,$E$49:$E$59,$R75) -> 93.006374 | Z75: =SUMIFS(M$49:M$59,$E$49:$E$59,$R75) -> 99.628428 | ... AB75: =SUMIFS(O$49:O$59,$E$49:$E$59,$R75) -> 114.32058
C76: TOTAL | F76: =SUM(F65:F75) -> 3585.9637 | G76: =SUM(G65:G75) -> 4098.24 | H76: =SUM(H65:H75) -> 4347.413 | I76: =SUM(I65:I75) -> 4611.7357 | J76: =SUM(J65:J75) -> 4892.1292 | K76: =SUM(K65:K75) -> 5240.4488 | L76: =SUM(L65:L75) -> 5613.5688 | M76: =SUM(M65:M75) -> 6013.2549 | ... O76: =SUM(O65:O75) -> 6900.0262 | R76: Panificados | S76: =SUMIFS(F$49:F$59,$E$49:$E$59,$R76) -> 134.75012 | T76: =SUMIFS(G$49:G$59,$E$49:$E$59,$R76) -> 154.00006 | U76: =SUMIFS(H$49:H$59,$E$49:$E$59,$R76) -> 163.36326 | V76: =SUMIFS(I$49:I$59,$E$49:$E$59,$R76) -> 173.29575 | W76: =SUMIFS(J$49:J$59,$E$49:$E$59,$R76) -> 183.83213 | X76: =SUMIFS(K$49:K$59,$E$49:$E$59,$R76) -> 196.92098 | Y76: =SUMIFS(L$49:L$59,$E$49:$E$59,$R76) -> 210.94175 | Z76: =SUMIFS(M$49:M$59,$E$49:$E$59,$R76) -> 225.96081 | ... AB76: =SUMIFS(O$49:O$59,$E$49:$E$59,$R76) -> 259.28312
Q84: Producto | R84: Unidades | S84: $
Q85: Budines 180gr. | R85: =SUMIFS($O$49:$O$59,$C$49:$C$59,Q85) -> 0 | S85: =SUMIFS($O$65:$O$75,$C$65:$C$75,Q85) -> 0
Q86: Pan de molde 400gr. | R86: =SUMIFS($O$49:$O$59,$C$49:$C$59,Q86) -> 117.85592 | S86: =SUMIFS($O$65:$O$75,$C$65:$C$75,Q86) -> 1140.256
Q87: Chocolate con chips picante 150gr. | R87: =SUMIFS($O$49:$O$59,$C$49:$C$59,Q87) -> 101.01936 | S87: =SUMIFS($O$65:$O$75,$C$65:$C$75,Q87) -> 1043.8667
Q88: Pepas chocolate y batata 150gr. | R88: =SUMIFS($O$49:$O$59,$C$49:$C$59,Q88) -> 94.284902 | S88: =SUMIFS($O$65:$O$75,$C$65:$C$75,Q88) -> 807.70733
Q89: Budines free 180gr. | R89: =SUMIFS($O$49:$O$59,$C$49:$C$59,Q89) -> 0 | S89: =SUMIFS($O$65:$O$75,$C$65:$C$75,Q89) -> 0
Q90: Polvorones 150gr. | R90: =SUMIFS($O$49:$O$59,$C$49:$C$59,Q90) -> 53.035163 | S90: =SUMIFS($O$65:$O$75,$C$65:$C$75,Q90) -> 456.1024
Q91: Galletitas símil chocolinas 150gr. | R91: =SUMIFS($O$49:$O$59,$C$49:$C$59,Q91) -> 30.642707 | S91: =SUMIFS($O$65:$O$75,$C$65:$C$75,Q91) -> 268.6344
Q92: Bizcochos sabor queso 150gr. | R92: =SUMIFS($O$49:$O$59,$C$49:$C$59,Q92) -> 30.642707 | S92: =SUMIFS($O$65:$O$75,$C$65:$C$75,Q92) -> 263.52728
Q93: Polvorones free 150gr. | R93: =SUMIFS($O$49:$O$59,$C$49:$C$59,Q93) -> 22.729356 | S93: =SUMIFS($O$65:$O$75,$C$65:$C$75,Q93) -> 219.7171
Q94: Galletitas símil chocolinas free 150gr. | R94: =SUMIFS($O$49:$O$59,$C$49:$C$59,Q94) -> 13.132517 | S94: =SUMIFS($O$65:$O$75,$C$65:$C$75,Q94) -> 129.13641
Q95: Bizcochos sabor queso free 150gr. | R95: =SUMIFS($O$49:$O$59,$C$49:$C$59,Q95) -> 13.132517 | S95: =SUMIFS($O$65:$O$75,$C$65:$C$75,Q95) -> 112.93964

Sheet BOM
D2: Chocolate con chips picante - A01 | M2: Foto | R2: Calculo de receta promedio ponderada - kg de MP cada 100kg | AB2: 100 kg | AF2: 100 kg | AH2: =AL6 -> 426720.66 | AI2: =AL23 -> 343531.76 | AK2: Linea A - Galletitas | AU2: Linea A - Galletitas
D3: PT anual (kg) | E3: =SUMIFS('Plan de ventas'!$O$48:$O$60,'Plan de ventas'!$B$48:$B$60,D12)*1000 -> 101019.36 | R3: CÓDIGO | S3: DENOMINACIÓN | T3: A01 | U3: A02 | V3: A03 | W3: A04 | X3: A05 | Y3: A06 | Z3: A07 | AA3: A08 | AB3: A00 | AC3: B01 | AD3: B02 | AE3: B03 | AF3: B00 | AH3: A00 | AI3: B00 | AK3: NECESIDAD ANUAL MP | AU3: MAQUINAS
B4: Cajas / lote | E4: 1 | F4: ="Línea: Gourmet | Versión n°: 1"&CHAR(10)&CHAR(10)&"Lote = "&E4&" cajas × "&E5&" unid./caja = "&(E4*E5)&" unidades"&CHAR(10)&"Producto terminado = "&TEXT(E8,"#,##0.00")&" kg"&CHAR(10)&"Mezcla a preparar = "&TEXT(E9,"#,##0.00")&" kg (rendimiento "&TEXT(E7,"0%")&")" -> Línea: Gourmet | Versión n°: 1 Lote = 1 cajas × 20 unid./caja = 20 unidades Producto terminado = 3,00 kg Mezcla a preparar = 3,41 kg (rendimiento 88%) | S4: Volumen relativo (año 10) | T4: =SUMIFS('Plan de ventas'!$P$48:$P$60,'Plan de ventas'!$B$48:$B$60,T3) -> 0.28168974 | U4: =SUMIFS('Plan de ventas'!$P$48:$P$60,'Plan de ventas'!$B$48:$B$60,U3) -> 0.036619667 | V4: =SUMIFS('Plan de ventas'!$P$48:$P$60,'Plan de ventas'!$B$48:$B$60,V3) -> 0.085446359 | W4: =SUMIFS('Plan de ventas'!$P$48:$P$60,'Plan de ventas'!$B$48:$B$60,W3) -> 0.2629109 | X4: =SUMIFS('Plan de ventas'!$P$48:$P$60,'Plan de ventas'!$B$48:$B$60,X3) -> 0.036619667 | Y4: =SUMIFS('Plan de ventas'!$P$48:$P$60,'Plan de ventas'!$B$48:$B$60,Y3) -> 0.085446359 | Z4: =SUMIFS('Plan de ventas'!$P$48:$P$60,'Plan de ventas'!$B$48:$B$60,Z3) -> 0.063380192 | AA4: =SUMIFS('Plan de ventas'!$P$48:$P$60,'Plan de ventas'!$B$48:$B$60,AA3) -> 0.14788712 | AB4: =SUM(T4:AA4) -> 1 | AC4: =SUMIFS('Plan de ventas'!$P$48:$P$60,'Plan de ventas'!$B$48:$B$60,AC3) -> 0.36842094 | AD4: =SUMIFS('Plan de ventas'!$P$48:$P$60,'Plan de ventas'!$B$48:$B$60,AD3) -> 0.44210544 | AE4: =SUMIFS('Plan de ventas'!$P$48:$P$60,'Plan de ventas'!$B$48:$B$60,AE3) -> 0.18947362 | AF4: =SUM(AC4:AE4) -> 1 | AK4: Sección Operativa | AL4: Alimentación | AM4: Agregado | AN4: Desperdicios | AR4: Producción | AU4: Máquina | AV4: Modelo | AW4: Capacidad Teórica | AY4: Medidas | BA4: Peso | BC4: Consumo | BE4: Precio | BF4: Proveedor | BG4: Ubicación
B5: Unid. / caja | E5: 20 | R5: M001 | S5: FÉCULA DE MAÍZ | T5: =SUMIFS($L:$L,$C:$C,T$3,$D:$D,$R5)*100 -> 26.5 | U5: =SUMIFS($L:$L,$C:$C,U$3,$D:$D,$R5)*100 -> 24 | V5: =SUMIFS($L:$L,$C:$C,V$3,$D:$D,$R5)*100 -> 22 | W5: =SUMIFS($L:$L,$C:$C,W$3,$D:$D,$R5)*100 -> 23.32 | X5: =SUMIFS($L:$L,$C:$C,X$3,$D:$D,$R5)*100 -> 0 | Y5: =SUMIFS($L:$L,$C:$C,Y$3,$D:$D,$R5)*100 -> 0 | Z5: =SUMIFS($L:$L,$C:$C,Z$3,$D:$D,$R5)*100 -> 24 | AA5: =SUMIFS($L:$L,$C:$C,AA$3,$D:$D,$R5)*100 -> 28 | AB5: =SUMPRODUCT($T$4:$AA$4,T5:AA5) -> 22.016516 | AC5: =SUMIFS($L:$L,$C:$C,AC$3,$D:$D,$R5)*100 -> 0 | AD5: =SUMIFS($L:$L,$C:$C,AD$3,$D:$D,$R5)*100 -> 12 | AE5: =SUMIFS($L:$L,$C:$C,AE$3,$D:$D,$R5)*100 -> 11 | AF5: =SUMPRODUCT($AC$4:$AE$4,AC5:AE5) -> 7.3894751 | AH5: =AB5/100*$AL$6 -> 93949.022 | AI5: =AF5/100*$AL$23 -> 25385.194 | AN5: Recuperable | AP5: No recuperable | AU5: Amasadora | AW5: 130 | AX5: kg | AY5: 120x140x180 | AZ5: cm | BB5: kg | BC5: - | BD5: kw/h | BE5: 13000000
B6: Peso neto (g) | E6: 150 | R6: M006 | S6: SAL | T6: =SUMIFS($L:$L,$C:$C,T$3,$D:$D,$R6)*100 -> 0.5 | U6: =SUMIFS($L:$L,$C:$C,U$3,$D:$D,$R6)*100 -> 0.4 | V6: =SUMIFS($L:$L,$C:$C,V$3,$D:$D,$R6)*100 -> 0 | W6: =SUMIFS($L:$L,$C:$C,W$3,$D:$D,$R6)*100 -> 0 | X6: =SUMIFS($L:$L,$C:$C,X$3,$D:$D,$R6)*100 -> 1.5 | Y6: =SUMIFS($L:$L,$C:$C,Y$3,$D:$D,$R6)*100 -> 1.5 | Z6: =SUMIFS($L:$L,$C:$C,Z$3,$D:$D,$R6)*100 -> 0 | AA6: =SUMIFS($L:$L,$C:$C,AA$3,$D:$D,$R6)*100 -> 0.5 | AB6: =SUMPRODUCT($T$4:$AA$4,T6:AA6) -> 0.41253533 | AC6: =SUMIFS($L:$L,$C:$C,AC$3,$D:$D,$R6)*100 -> 1 | AD6: =SUMIFS($L:$L,$C:$C,AD$3,$D:$D,$R6)*100 -> 0.5 | AE6: =SUMIFS($L:$L,$C:$C,AE$3,$D:$D,$R6)*100 -> 0.3 | AF6: =SUMPRODUCT($AC$4:$AE$4,AC6:AE6) -> 0.64631574 | AH6: =AB6/100*$AL$6 -> 1760.3735 | AI6: =AF6/100*$AL$23 -> 2220.2998 | AK6: Amasado | AL6: =AR14*(1+AL16) -> 426720.66 | AM6: 0 | AO6: =AL6*AN6 -> 0 | AQ6: =AL6*AP6 -> 0 | AR6: =AL6+AM6-AO6-AQ6 -> 426720.66 | AS6: kg/año | AU6: Moldeadora | AV6: Ralem dulcera 600 | AX6: kg/h | AZ6: cm | BB6: kg | BC6: - | BD6: kw/h
B7: Rendim. (%) | E7: 0.88 | R7: M008 | S7: BICARBONATO DE AMONIO | T7: =SUMIFS($L:$L,$C:$C,T$3,$D:$D,$R7)*100 -> 0.5 | U7: =SUMIFS($L:$L,$C:$C,U$3,$D:$D,$R7)*100 -> 0 | V7: =SUMIFS($L:$L,$C:$C,V$3,$D:$D,$R7)*100 -> 0 | W7: =SUMIFS($L:$L,$C:$C,W$3,$D:$D,$R7)*100 -> 0 | X7: =SUMIFS($L:$L,$C:$C,X$3,$D:$D,$R7)*100 -> 0 | Y7: =SUMIFS($L:$L,$C:$C,Y$3,$D:$D,$R7)*100 -> 0 | Z7: =SUMIFS($L:$L,$C:$C,Z$3,$D:$D,$R7)*100 -> 1.5 | AA7: =SUMIFS($L:$L,$C:$C,AA$3,$D:$D,$R7)*100 -> 1 | AB7: =SUMPRODUCT($T$4:$AA$4,T7:AA7) -> 0.38380228 | AC7: =SUMIFS($L:$L,$C:$C,AC$3,$D:$D,$R7)*100 -> 0 | AD7: =SUMIFS($L:$L,$C:$C,AD$3,$D:$D,$R7)*100 -> 0 | AE7: =SUMIFS($L:$L,$C:$C,AE$3,$D:$D,$R7)*100 -> 0 | AF7: =SUMPRODUCT($AC$4:$AE$4,AC7:AE7) -> 0 | AH7: =AB7/100*$AL$6 -> 1637.7636 | AI7: =AF7/100*$AL$23 -> 0 | AK7: Moldeado | AL7: =AR6 -> 426720.66 | AM7: 0 | AN7: 0.03 | AO7: =AL7*AN7 -> 12801.62 | AP7: 0.02 | AQ7: =AL7*AP7 -> 8534.4132 | AR7: =AL7+AM7-AO7-AQ7 -> 405384.62 | AS7: kg/año | AU7: Horno tunel | AX7: kg/h | AZ7: cm | BB7: kg | BC7: - | BD7: kw/h
B8: PT (kg) | E8: =E4*E5*E6/1000 -> 3 | R8: M022 | S8: GOMA XÁNTICA | T8: =SUMIFS($L:$L,$C:$C,T$3,$D:$D,$R8)*100 -> 0.8 | U8: =SUMIFS($L:$L,$C:$C,U$3,$D:$D,$R8)*100 -> 1 | V8: =SUMIFS($L:$L,$C:$C,V$3,$D:$D,$R8)*100 -> 1 | W8: =SUMIFS($L:$L,$C:$C,W$3,$D:$D,$R8)*100 -> 0.432 | X8: =SUMIFS($L:$L,$C:$C,X$3,$D:$D,$R8)*100 -> 1 | Y8: =SUMIFS($L:$L,$C:$C,Y$3,$D:$D,$R8)*100 -> 1 | Z8: =SUMIFS($L:$L,$C:$C,Z$3,$D:$D,$R8)*100 -> 1 | AA8: =SUMIFS($L:$L,$C:$C,AA$3,$D:$D,$R8)*100 -> 1 | AB8: =SUMPRODUCT($T$4:$AA$4,T8:AA8) -> 0.79432866 | AC8: =SUMIFS($L:$L,$C:$C,AC$3,$D:$D,$R8)*100 -> 1.5 | AD8: =SUMIFS($L:$L,$C:$C,AD$3,$D:$D,$R8)*100 -> 1 | AE8: =SUMIFS($L:$L,$C:$C,AE$3,$D:$D,$R8)*100 -> 1 | AF8: =SUMPRODUCT($AC$4:$AE$4,AC8:AE8) -> 1.1842105 | AH8: =AB8/100*$AL$6 -> 3389.5645 | AI8: =AF8/100*$AL$23 -> 4068.139 | AK8: Horneado | AL8: =AR7 -> 405384.62 | AM8: 0 | AO8: =AL8*AN8 -> 0 | AP8: 0.04 | AQ8: =AL8*AP8 -> 16215.385 | AR8: =AL8+AM8-AO8-AQ8 -> 389169.24 | AS8: kg/año | AU8: Cinta de enfriamiento | AX8: kg/h | AZ8: cm | BB8: kg | BC8: - | BD8: kw/h
B9: Mezcla (kg) | E9: =E8/E7 -> 3.4090909 | R9: M028 | S9: PROPIONATO DE CALCIO | T9: =SUMIFS($L:$L,$C:$C,T$3,$D:$D,$R9)*100 -> 0 | U9: =SUMIFS($L:$L,$C:$C,U$3,$D:$D,$R9)*100 -> 0 | V9: =SUMIFS($L:$L,$C:$C,V$3,$D:$D,$R9)*100 -> 0 | W9: =SUMIFS($L:$L,$C:$C,W$3,$D:$D,$R9)*100 -> 0 | X9: =SUMIFS($L:$L,$C:$C,X$3,$D:$D,$R9)*100 -> 0 | Y9: =SUMIFS($L:$L,$C:$C,Y$3,$D:$D,$R9)*100 -> 0 | Z9: =SUMIFS($L:$L,$C:$C,Z$3,$D:$D,$R9)*100 -> 1 | AA9: =SUMIFS($L:$L,$C:$C,AA$3,$D:$D,$R9)*100 -> 1 | AB9: =SUMPRODUCT($T$4:$AA$4,T9:AA9) -> 0.21126731 | AC9: =SUMIFS($L:$L,$C:$C,AC$3,$D:$D,$R9)*100 -> 0 | AD9: =SUMIFS($L:$L,$C:$C,AD$3,$D:$D,$R9)*100 -> 1 | AE9: =SUMIFS($L:$L,$C:$C,AE$3,$D:$D,$R9)*100 -> 1 | AF9: =SUMPRODUCT($AC$4:$AE$4,AC9:AE9) -> 0.63157906 | AH9: =AB9/100*$AL$6 -> 901.52125 | AI9: =AF9/100*$AL$23 -> 2169.6746 | AK9: Enfriado | AL9: =AR8 -> 389169.24 | AM9: 0 | AN9: 0.03 | AO9: =AL9*AN9 -> 11675.077 | AP9: 0.02 | AQ9: =AL9*AP9 -> 7783.3848 | AR9: =AL9+AM9-AO9-AQ9 -> 369710.78 | AS9: kg/año | AU9: Envasadora vertical | AX9: kg/h | AZ9: cm | BB9: kg | BC9: - | BD9: kw/h
B10: ITEM | C10: PT | D10: MP | E10: DENOMINACION | F10: NIVEL | L10: % | M10: CANTIDAD | N10: UNIDAD | O10: OBSERVACIONES | R10: M030 | S10: HARINA DE ARROZ | T10: =SUMIFS($L:$L,$C:$C,T$3,$D:$D,$R10)*100 -> 18 | U10: =SUMIFS($L:$L,$C:$C,U$3,$D:$D,$R10)*100 -> 27 | V10: =SUMIFS($L:$L,$C:$C,V$3,$D:$D,$R10)*100 -> 27 | W10: =SUMIFS($L:$L,$C:$C,W$3,$D:$D,$R10)*100 -> 13.68 | X10: =SUMIFS($L:$L,$C:$C,X$3,$D:$D,$R10)*100 -> 25 | Y10: =SUMIFS($L:$L,$C:$C,Y$3,$D:$D,$R10)*100 -> 25 | Z10: =SUMIFS($L:$L,$C:$C,Z$3,$D:$D,$R10)*100 -> 22 | AA10: =SUMIFS($L:$L,$C:$C,AA$3,$D:$D,$R10)*100 -> 21 | AB10: =SUMPRODUCT($T$4:$AA$4,T10:AA10) -> 19.514463 | AC10: =SUMIFS($L:$L,$C:$C,AC$3,$D:$D,$R10)*100 -> 16 | AD10: =SUMIFS($L:$L,$C:$C,AD$3,$D:$D,$R10)*100 -> 14 | AE10: =SUMIFS($L:$L,$C:$C,AE$3,$D:$D,$R10)*100 -> 13 | AF10: =SUMPRODUCT($AC$4:$AE$4,AC10:AE10) -> 14.547368 | AH10: =AB10/100*$AL$6 -> 83272.247 | AI10: =AF10/100*$AL$23 -> 49974.83 | AK10: Fraccionado | AL10: =AR9 -> 369710.78 | AM10: 0 | AO10: =AL10*AN10 -> 0 | AQ10: =AL10*AP10 -> 0 | AR10: =AL10+AM10-AO10-AQ10 -> 369710.78 | AS10: kg/año | AU10: Envasadora | AX10: kg/h | AZ10: cm | BB10: kg | BC10: - | BD10: kw/h
F11: 0 | G11: 1 | H11: 2 | I11: 3 | J11: 4 | K11: 5 | R11: M031 | S11: JARABE DE GLUCOSA | T11: =SUMIFS($L:$L,$C:$C,T$3,$D:$D,$R11)*100 -> 6 | U11: =SUMIFS($L:$L,$C:$C,U$3,$D:$D,$R11)*100 -> 0 | V11: =SUMIFS($L:$L,$C:$C,V$3,$D:$D,$R11)*100 -> 0 | W11: =SUMIFS($L:$L,$C:$C,W$3,$D:$D,$R11)*100 -> 4.32 | X11: =SUMIFS($L:$L,$C:$C,X$3,$D:$D,$R11)*100 -> 0 | Y11: =SUMIFS($L:$L,$C:$C,Y$3,$D:$D,$R11)*100 -> 0 | Z11: =SUMIFS($L:$L,$C:$C,Z$3,$D:$D,$R11)*100 -> 0 | AA11: =SUMIFS($L:$L,$C:$C,AA$3,$D:$D,$R11)*100 -> 6 | AB11: =SUMPRODUCT($T$4:$AA$4,T11:AA11) -> 3.7132362 | AC11: =SUMIFS($L:$L,$C:$C,AC$3,$D:$D,$R11)*100 -> 0 | AD11: =SUMIFS($L:$L,$C:$C,AD$3,$D:$D,$R11)*100 -> 0 | AE11: =SUMIFS($L:$L,$C:$C,AE$3,$D:$D,$R11)*100 -> 0 | AF11: =SUMPRODUCT($AC$4:$AE$4,AC11:AE11) -> 0 | AH11: =AB11/100*$AL$6 -> 15845.146 | AI11: =AF11/100*$AL$23 -> 0 | AK11: Envasado primario | AL11: =AR10 -> 369710.78 | AM11: 0 | AO11: =AL11*AN11 -> 0 | AP11: 0.03 | AQ11: =AL11*AP11 -> 11091.323 | AR11: =AL11+AM11-AO11-AQ11 -> 358619.45 | AS11: kg/año | AX11: kg/h | AZ11: cm | BB11: kg | BC11: - | BD11: kw/h
B12: 1 | C12: A01 | D12: A01 | E12: Chocolate con chips picante (caja) | F12: X | L12: — | M12: =$E$4 -> 1 | N12: cajas | O12: Lote = 1 caja | R12: M036 | S12: ACEITE VEGETAL INTERESTERIFICADO | T12: =SUMIFS($L:$L,$C:$C,T$3,$D:$D,$R12)*100 -> 15 | U12: =SUMIFS($L:$L,$C:$C,U$3,$D:$D,$R12)*100 -> 14 | V12: =SUMIFS($L:$L,$C:$C,V$3,$D:$D,$R12)*100 -> 14 | W12: =SUMIFS($L:$L,$C:$C,W$3,$D:$D,$R12)*100 -> 11.16 | X12: =SUMIFS($L:$L,$C:$C,X$3,$D:$D,$R12)*100 -> 6 | Y12: =SUMIFS($L:$L,$C:$C,Y$3,$D:$D,$R12)*100 -> 0 | Z12: =SUMIFS($L:$L,$C:$C,Z$3,$D:$D,$R12)*100 -> 13 | AA12: =SUMIFS($L:$L,$C:$C,AA$3,$D:$D,$R12)*100 -> 15 | AB12: =SUMPRODUCT($T$4:$AA$4,T12:AA12) -> 12.130323 | AC12: =SUMIFS($L:$L,$C:$C,AC$3,$D:$D,$R12)*100 -> 0 | AD12: =SUMIFS($L:$L,$C:$C,AD$3,$D:$D,$R12)*100 -> 0 | AE12: =SUMIFS($L:$L,$C:$C,AE$3,$D:$D,$R12)*100 -> 0 | AF12: =SUMPRODUCT($AC$4:$AE$4,AC12:AE12) -> 0 | AH12: =AB12/100*$AL$6 -> 51762.596 | AI12: =AF12/100*$AL$23 -> 0 | AK12: Envasado secundario | AL12: =AR11 -> 358619.45 | AM12: 0 | AO12: =AL12*AN12 -> 0 | AQ12: =AL12*AP12 -> 0 | AR12: =AL12+AM12-AO12-AQ12 -> 358619.45 | AS12: kg/año | AX12: kg/h | AZ12: cm | BB12: kg | BC12: - | BD12: kw/h
B13: 2 | C13: A01 | D13: M001 | E13: FÉCULA DE MAÍZ | G13: X | L13: 0.265 | M13: =$E$9*L13 -> 0.90340909 | N13: Kg. | R13: M041 | S13: HUEVO EN POLVO DESHIDRATADO | T13: =SUMIFS($L:$L,$C:$C,T$3,$D:$D,$R13)*100 -> 2 | U13: =SUMIFS($L:$L,$C:$C,U$3,$D:$D,$R13)*100 -> 0 | V13: =SUMIFS($L:$L,$C:$C,V$3,$D:$D,$R13)*100 -> 4 | W13: =SUMIFS($L:$L,$C:$C,W$3,$D:$D,$R13)*100 -> 0 | X13: =SUMIFS($L:$L,$C:$C,X$3,$D:$D,$R13)*100 -> 0 | Y13: =SUMIFS($L:$L,$C:$C,Y$3,$D:$D,$R13)*100 -> 5 | Z13: =SUMIFS($L:$L,$C:$C,Z$3,$D:$D,$R13)*100 -> 0 | AA13: =SUMIFS($L:$L,$C:$C,AA$3,$D:$D,$R13)*100 -> 0 | AB13: =SUMPRODUCT($T$4:$AA$4,T13:AA13) -> 1.3323967 | AC13: =SUMIFS($L:$L,$C:$C,AC$3,$D:$D,$R13)*100 -> 0 | AD13: =SUMIFS($L:$L,$C:$C,AD$3,$D:$D,$R13)*100 -> 6 | AE13: =SUMIFS($L:$L,$C:$C,AE$3,$D:$D,$R13)*100 -> 6 | AF13: =SUMPRODUCT($AC$4:$AE$4,AC13:AE13) -> 3.7894744 | AH13: =AB13/100*$AL$6 -> 5685.612 | AI13: =AF13/100*$AL$23 -> 13018.048 | AK13: Paletizado | AL13: =AR12 -> 358619.45 | AM13: 0 | AO13: =AL13*AN13 -> 0 | AQ13: =AL13*AP13 -> 0 | AR13: =AL13+AM13-AO13-AQ13 -> 358619.45 | AS13: kg/año | AX13: kg/h | AZ13: cm | BB13: kg | BC13: - | BD13: kw/h
B14: 3 | C14: A01 | D14: M030 | E14: HARINA DE ARROZ | G14: X | L14: 0.18 | M14: =$E$9*L14 -> 0.61363636 | N14: Kg. | R14: M045 | S14: CACAO ALCALINO | T14: =SUMIFS($L:$L,$C:$C,T$3,$D:$D,$R14)*100 -> 4 | U14: =SUMIFS($L:$L,$C:$C,U$3,$D:$D,$R14)*100 -> 6 | V14: =SUMIFS($L:$L,$C:$C,V$3,$D:$D,$R14)*100 -> 6 | W14: =SUMIFS($L:$L,$C:$C,W$3,$D:$D,$R14)*100 -> 3.24 | X14: =SUMIFS($L:$L,$C:$C,X$3,$D:$D,$R14)*100 -> 0 | Y14: =SUMIFS($L:$L,$C:$C,Y$3,$D:$D,$R14)*100 -> 0 | Z14: =SUMIFS($L:$L,$C:$C,Z$3,$D:$D,$R14)*100 -> 6 | AA14: =SUMIFS($L:$L,$C:$C,AA$3,$D:$D,$R14)*100 -> 0 | AB14: =SUMPRODUCT($T$4:$AA$4,T14:AA14) -> 3.0912676 | AC14: =SUMIFS($L:$L,$C:$C,AC$3,$D:$D,$R14)*100 -> 0 | AD14: =SUMIFS($L:$L,$C:$C,AD$3,$D:$D,$R14)*100 -> 0 | AE14: =SUMIFS($L:$L,$C:$C,AE$3,$D:$D,$R14)*100 -> 0 | AF14: =SUMPRODUCT($AC$4:$AE$4,AC14:AE14) -> 0 | AH14: =AB14/100*$AL$6 -> 13191.077 | AI14: =AF14/100*$AL$23 -> 0 | AK14: TOTALES | AL14: =AL6 -> 426720.66 | AM14: =AM6 -> 0 | AO14: =AO6+AO7+AO8+AO9+AO11 -> 24476.697 | AQ14: =AQ6+AQ7+AQ8+AQ9+AQ11 -> 43624.506 | AR14: =SUMIFS('Plan de ventas'!$O48:$O60,'Plan de ventas'!$B$48:$B$60,"*A*")*1000 -> 358619.23 | AS14: kg/año | AX14: kg/h | AZ14: cm | BB14: kg | BC14: - | BD14: kw/h
B15: 4 | C15: A01 | D15: M036 | E15: ACEITE VEGETAL INTERESTERIFICADO | G15: X | L15: 0.15 | M15: =$E$9*L15 -> 0.51136364 | N15: Kg. | R15: M046 | S15: CHIPS DE CHOCOLATE | T15: =SUMIFS($L:$L,$C:$C,T$3,$D:$D,$R15)*100 -> 9 | U15: =SUMIFS($L:$L,$C:$C,U$3,$D:$D,$R15)*100 -> 0 | V15: =SUMIFS($L:$L,$C:$C,V$3,$D:$D,$R15)*100 -> 0 | W15: =SUMIFS($L:$L,$C:$C,W$3,$D:$D,$R15)*100 -> 0 | X15: =SUMIFS($L:$L,$C:$C,X$3,$D:$D,$R15)*100 -> 0 | Y15: =SUMIFS($L:$L,$C:$C,Y$3,$D:$D,$R15)*100 -> 0 | Z15: =SUMIFS($L:$L,$C:$C,Z$3,$D:$D,$R15)*100 -> 0 | AA15: =SUMIFS($L:$L,$C:$C,AA$3,$D:$D,$R15)*100 -> 0 | AB15: =SUMPRODUCT($T$4:$AA$4,T15:AA15) -> 2.5352077 | AC15: =SUMIFS($L:$L,$C:$C,AC$3,$D:$D,$R15)*100 -> 0 | AD15: =SUMIFS($L:$L,$C:$C,AD$3,$D:$D,$R15)*100 -> 0 | AE15: =SUMIFS($L:$L,$C:$C,AE$3,$D:$D,$R15)*100 -> 9 | AF15: =SUMPRODUCT($AC$4:$AE$4,AC15:AE15) -> 1.7052626 | AH15: =AB15/100*$AL$6 -> 10818.255 | AI15: =AF15/100*$AL$23 -> 5858.1186
B16: 5 | C16: A01 | D16: M052 | E16: AZÚCAR COMÚN | G16: X | L16: 0.14 | M16: =$E$9*L16 -> 0.47727273 | N16: Kg. | R16: M047 | S16: ESENCIA DE CHOCOLATE | T16: =SUMIFS($L:$L,$C:$C,T$3,$D:$D,$R16)*100 -> 0.3 | U16: =SUMIFS($L:$L,$C:$C,U$3,$D:$D,$R16)*100 -> 0.3 | V16: =SUMIFS($L:$L,$C:$C,V$3,$D:$D,$R16)*100 -> 0.4 | W16: =SUMIFS($L:$L,$C:$C,W$3,$D:$D,$R16)*100 -> 0 | X16: =SUMIFS($L:$L,$C:$C,X$3,$D:$D,$R16)*100 -> 0 | Y16: =SUMIFS($L:$L,$C:$C,Y$3,$D:$D,$R16)*100 -> 0 | Z16: =SUMIFS($L:$L,$C:$C,Z$3,$D:$D,$R16)*100 -> 0.5 | AA16: =SUMIFS($L:$L,$C:$C,AA$3,$D:$D,$R16)*100 -> 0 | AB16: =SUMPRODUCT($T$4:$AA$4,T16:AA16) -> 0.16136146 | AC16: =SUMIFS($L:$L,$C:$C,AC$3,$D:$D,$R16)*100 -> 0 | AD16: =SUMIFS($L:$L,$C:$C,AD$3,$D:$D,$R16)*100 -> 0 | AE16: =SUMIFS($L:$L,$C:$C,AE$3,$D:$D,$R16)*100 -> 0 | AF16: =SUMPRODUCT($AC$4:$AE$4,AC16:AE16) -> 0 | AH16: =AB16/100*$AL$6 -> 688.5627 | AI16: =AF16/100*$AL$23 -> 0 | AK16: Desperdicio total | AL16: 0.189899 | AQ16: Desvios | AR16: =AR13/AR14-1 -> 6.38792e-07
B17: 6 | C17: A01 | D17: M046 | E17: CHIPS DE CHOCOLATE | G17: X | L17: 0.09 | M17: =$E$9*L17 -> 0.30681818 | N17: Kg. | R17: M048 | S17: MIEL | T17: =SUMIFS($L:$L,$C:$C,T$3,$D:$D,$R17)*100 -> 2 | U17: =SUMIFS($L:$L,$C:$C,U$3,$D:$D,$R17)*100 -> 0 | V17: =SUMIFS($L:$L,$C:$C,V$3,$D:$D,$R17)*100 -> 0 | W17: =SUMIFS($L:$L,$C:$C,W$3,$D:$D,$R17)*100 -> 0 | X17: =SUMIFS($L:$L,$C:$C,X$3,$D:$D,$R17)*100 -> 0 | Y17: =SUMIFS($L:$L,$C:$C,Y$3,$D:$D,$R17)*100 -> 0 | Z17: =SUMIFS($L:$L,$C:$C,Z$3,$D:$D,$R17)*100 -> 0 | AA17: =SUMIFS($L:$L,$C:$C,AA$3,$D:$D,$R17)*100 -> 0 | AB17: =SUMPRODUCT($T$4:$AA$4,T17:AA17) -> 0.56337949 | AC17: =SUMIFS($L:$L,$C:$C,AC$3,$D:$D,$R17)*100 -> 0 | AD17: =SUMIFS($L:$L,$C:$C,AD$3,$D:$D,$R17)*100 -> 0 | AE17: =SUMIFS($L:$L,$C:$C,AE$3,$D:$D,$R17)*100 -> 0 | AF17: =SUMPRODUCT($AC$4:$AE$4,AC17:AE17) -> 0 | AH17: =AB17/100*$AL$6 -> 2404.0567 | AI17: =AF17/100*$AL$23 -> 0
B18: 7 | C18: A01 | D18: M031 | E18: JARABE DE GLUCOSA | G18: X | L18: 0.06 | M18: =$E$9*L18 -> 0.20454545 | N18: Kg. | R18: M049 | S18: JALAPEÑO DESHIDRATADO EN POLVO | T18: =SUMIFS($L:$L,$C:$C,T$3,$D:$D,$R18)*100 -> 0.2 | U18: =SUMIFS($L:$L,$C:$C,U$3,$D:$D,$R18)*100 -> 0 | V18: =SUMIFS($L:$L,$C:$C,V$3,$D:$D,$R18)*100 -> 0 | W18: =SUMIFS($L:$L,$C:$C,W$3,$D:$D,$R18)*100 -> 0 | X18: =SUMIFS($L:$L,$C:$C,X$3,$D:$D,$R18)*100 -> 0 | Y18: =SUMIFS($L:$L,$C:$C,Y$3,$D:$D,$R18)*100 -> 0 | Z18: =SUMIFS($L:$L,$C:$C,Z$3,$D:$D,$R18)*100 -> 0 | AA18: =SUMIFS($L:$L,$C:$C,AA$3,$D:$D,$R18)*100 -> 0 | AB18: =SUMPRODUCT($T$4:$AA$4,T18:AA18) -> 0.056337949 | AC18: =SUMIFS($L:$L,$C:$C,AC$3,$D:$D,$R18)*100 -> 0 | AD18: =SUMIFS($L:$L,$C:$C,AD$3,$D:$D,$R18)*100 -> 0 | AE18: =SUMIFS($L:$L,$C:$C,AE$3,$D:$D,$R18)*100 -> 0 | AF18: =SUMPRODUCT($AC$4:$AE$4,AC18:AE18) -> 0 | AH18: =AB18/100*$AL$6 -> 240.40567 | AI18: =AF18/100*$AL$23 -> 0
B19: 8 | C19: A01 | D19: M045 | E19: CACAO EN POLVO ALCALINO | G19: X | L19: 0.04 | M19: =$E$9*L19 -> 0.13636364 | N19: Kg. | R19: M052 | S19: AZÚCAR | T19: =SUMIFS($L:$L,$C:$C,T$3,$D:$D,$R19)*100 -> 14 | U19: =SUMIFS($L:$L,$C:$C,U$3,$D:$D,$R19)*100 -> 0 | V19: =SUMIFS($L:$L,$C:$C,V$3,$D:$D,$R19)*100 -> 18 | W19: =SUMIFS($L:$L,$C:$C,W$3,$D:$D,$R19)*100 -> 15.4 | X19: =SUMIFS($L:$L,$C:$C,X$3,$D:$D,$R19)*100 -> 0 | Y19: =SUMIFS($L:$L,$C:$C,Y$3,$D:$D,$R19)*100 -> 0 | Z19: =SUMIFS($L:$L,$C:$C,Z$3,$D:$D,$R19)*100 -> 0 | AA19: =SUMIFS($L:$L,$C:$C,AA$3,$D:$D,$R19)*100 -> 16 | AB19: =SUMPRODUCT($T$4:$AA$4,T19:AA19) -> 11.896713 | AC19: =SUMIFS($L:$L,$C:$C,AC$3,$D:$D,$R19)*100 -> 4 | AD19: =SUMIFS($L:$L,$C:$C,AD$3,$D:$D,$R19)*100 -> 22 | AE19: =SUMIFS($L:$L,$C:$C,AE$3,$D:$D,$R19)*100 -> 20 | AF19: =SUMPRODUCT($AC$4:$AE$4,AC19:AE19) -> 14.989476 | AH19: =AB19/100*$AL$6 -> 50765.73 | AI19: =AF19/100*$AL$23 -> 51493.61 | AK19: Linea B - Panificados | AU19: Linea B - Panificados
B20: 9 | C20: A01 | D20: M041 | E20: HUEVO EN POLVO DESHIDRATADO | G20: X | L20: 0.02 | M20: =$E$9*L20 -> 0.068181818 | N20: Kg. | R20: M056 | S20: BICARBONATO DE SODIO | T20: =SUMIFS($L:$L,$C:$C,T$3,$D:$D,$R20)*100 -> 0.5 | U20: =SUMIFS($L:$L,$C:$C,U$3,$D:$D,$R20)*100 -> 0.5 | V20: =SUMIFS($L:$L,$C:$C,V$3,$D:$D,$R20)*100 -> 0.8 | W20: =SUMIFS($L:$L,$C:$C,W$3,$D:$D,$R20)*100 -> 0 | X20: =SUMIFS($L:$L,$C:$C,X$3,$D:$D,$R20)*100 -> 0.5 | Y20: =SUMIFS($L:$L,$C:$C,Y$3,$D:$D,$R20)*100 -> 0.5 | Z20: =SUMIFS($L:$L,$C:$C,Z$3,$D:$D,$R20)*100 -> 0 | AA20: =SUMIFS($L:$L,$C:$C,AA$3,$D:$D,$R20)*100 -> 1 | AB20: =SUMPRODUCT($T$4:$AA$4,T20:AA20) -> 0.43643192 | AC20: =SUMIFS($L:$L,$C:$C,AC$3,$D:$D,$R20)*100 -> 0 | AD20: =SUMIFS($L:$L,$C:$C,AD$3,$D:$D,$R20)*100 -> 0 | AE20: =SUMIFS($L:$L,$C:$C,AE$3,$D:$D,$R20)*100 -> 0 | AF20: =SUMPRODUCT($AC$4:$AE$4,AC20:AE20) -> 0 | AH20: =AB20/100*$AL$6 -> 1862.3452 | AI20: =AF20/100*$AL$23 -> 0 | AK20: NECESIDAD ANUAL MP | AU20: MAQUINAS
B21: 10 | C21: A01 | D21: M048 | E21: MIEL | G21: X | L21: 0.02 | M21: =$E$9*L21 -> 0.068181818 | N21: Kg. | R21: M057 | S21: BICARBONATO DE CALCIO | T21: =SUMIFS($L:$L,$C:$C,T$3,$D:$D,$R21)*100 -> 0.3 | U21: =SUMIFS($L:$L,$C:$C,U$3,$D:$D,$R21)*100 -> 0.3 | V21: =SUMIFS($L:$L,$C:$C,V$3,$D:$D,$R21)*100 -> 0.8 | W21: =SUMIFS($L:$L,$C:$C,W$3,$D:$D,$R21)*100 -> 0 | X21: =SUMIFS($L:$L,$C:$C,X$3,$D:$D,$R21)*100 -> 0 | Y21: =SUMIFS($L:$L,$C:$C,Y$3,$D:$D,$R21)*100 -> 0 | Z21: =SUMIFS($L:$L,$C:$C,Z$3,$D:$D,$R21)*100 -> 0 | AA21: =SUMIFS($L:$L,$C:$C,AA$3,$D:$D,$R21)*100 -> 0 | AB21: =SUMPRODUCT($T$4:$AA$4,T21:AA21) -> 0.16384991 | AC21: =SUMIFS($L:$L,$C:$C,AC$3,$D:$D,$R21)*100 -> 0 | AD21: =SUMIFS($L:$L,$C:$C,AD$3,$D:$D,$R21)*100 -> 0 | AE21: =SUMIFS($L:$L,$C:$C,AE$3,$D:$D,$R21)*100 -> 0 | AF21: =SUMPRODUCT($AC$4:$AE$4,AC21:AE21) -> 0 | AH21: =AB21/100*$AL$6 -> 699.18141 | AI21: =AF21/100*$AL$23 -> 0 | AK21: Sección Operativa | AL21: Alimentación | AM21: Agregado | AN21: Desperdicios | AR21: Producción | AU21: Máquina | AV21: Modelo | AW21: Capacidad Teórica | AY21: Medidas | BA21: Peso | BC21: Consumo | BE21: Precio | BF21: Proveedor | BG21: Ubicación
B22: 11 | C22: A01 | D22: M022 | E22: GOMA XÁNTICA | G22: X | L22: 0.008 | M22: =$E$9*L22 -> 0.027272727 | N22: Kg. | R22: M089 | S22: ESENCIA DE VAINILLA | T22: =SUMIFS($L:$L,$C:$C,T$3,$D:$D,$R22)*100 -> 0.4 | U22: =SUMIFS($L:$L,$C:$C,U$3,$D:$D,$R22)*100 -> 0 | V22: =SUMIFS($L:$L,$C:$C,V$3,$D:$D,$R22)*100 -> 0 | W22: =SUMIFS($L:$L,$C:$C,W$3,$D:$D,$R22)*100 -> 0.14 | X22: =SUMIFS($L:$L,$C:$C,X$3,$D:$D,$R22)*100 -> 0 | Y22: =SUMIFS($L:$L,$C:$C,Y$3,$D:$D,$R22)*100 -> 0 | Z22: =SUMIFS($L:$L,$C:$C,Z$3,$D:$D,$R22)*100 -> 0 | AA22: =SUMIFS($L:$L,$C:$C,AA$3,$D:$D,$R22)*100 -> 0 | AB22: =SUMPRODUCT($T$4:$AA$4,T22:AA22) -> 0.14948342 | AC22: =SUMIFS($L:$L,$C:$C,AC$3,$D:$D,$R22)*100 -> 0 | AD22: =SUMIFS($L:$L,$C:$C,AD$3,$D:$D,$R22)*100 -> 0 | AE22: =SUMIFS($L:$L,$C:$C,AE$3,$D:$D,$R22)*100 -> 0.5 | AF22: =SUMPRODUCT($AC$4:$AE$4,AC22:AE22) -> 0.094736812 | AH22: =AB22/100*$AL$6 -> 637.87665 | AI22: =AF22/100*$AL$23 -> 325.45103 | AN22: Recuperable | AP22: No recuperable | AU22: Batidora | AX22: kg/h | AZ22: cm | BB22: kg | BC22: - | BD22: kw/h
B23: 12 | C23: A01 | D23: M006 | E23: SAL | G23: X | L23: 0.005 | M23: =$E$9*L23 -> 0.017045455 | N23: Kg. | R23: M104 | S23: PASTA DE PASAS DE UVA | T23: =SUMIFS($L:$L,$C:$C,T$3,$D:$D,$R23)*100 -> 0 | U23: =SUMIFS($L:$L,$C:$C,U$3,$D:$D,$R23)*100 -> 13 | V23: =SUMIFS($L:$L,$C:$C,V$3,$D:$D,$R23)*100 -> 0 | W23: =SUMIFS($L:$L,$C:$C,W$3,$D:$D,$R23)*100 -> 0 | X23: =SUMIFS($L:$L,$C:$C,X$3,$D:$D,$R23)*100 -> 0 | Y23: =SUMIFS($L:$L,$C:$C,Y$3,$D:$D,$R23)*100 -> 0 | Z23: =SUMIFS($L:$L,$C:$C,Z$3,$D:$D,$R23)*100 -> 16 | AA23: =SUMIFS($L:$L,$C:$C,AA$3,$D:$D,$R23)*100 -> 0 | AB23: =SUMPRODUCT($T$4:$AA$4,T23:AA23) -> 1.4901387 | AC23: =SUMIFS($L:$L,$C:$C,AC$3,$D:$D,$R23)*100 -> 0 | AD23: =SUMIFS($L:$L,$C:$C,AD$3,$D:$D,$R23)*100 -> 0 | AE23: =SUMIFS($L:$L,$C:$C,AE$3,$D:$D,$R23)*100 -> 0 | AF23: =SUMPRODUCT($AC$4:$AE$4,AC23:AE23) -> 0 | AH23: =AB23/100*$AL$6 -> 6358.7299 | AI23: =AF23/100*$AL$23 -> 0 | AK23: Batido | AL23: =AR32*(1+AL34) -> 343531.76 | AM23: 0 | AO23: =AL23*AN23 -> 0 | AQ23: =AL23*AP23 -> 0 | AR23: =AL23+AM23-AO23-AQ23 -> 343531.76 | AS23: kg/año | AU23: Dosificadora | AX23: kg/h | AZ23: cm | BB23: kg | BC23: - | BD23: kw/h
B24: 13 | C24: A01 | D24: M008 | E24: BICARBONATO DE AMONIO | G24: X | L24: 0.005 | M24: =$E$9*L24 -> 0.017045455 | N24: Kg. | R24: M105 | S24: ACEITE DE COCO | T24: =SUMIFS($L:$L,$C:$C,T$3,$D:$D,$R24)*100 -> 0 | U24: =SUMIFS($L:$L,$C:$C,U$3,$D:$D,$R24)*100 -> 5 | V24: =SUMIFS($L:$L,$C:$C,V$3,$D:$D,$R24)*100 -> 0 | W24: =SUMIFS($L:$L,$C:$C,W$3,$D:$D,$R24)*100 -> 0 | X24: =SUMIFS($L:$L,$C:$C,X$3,$D:$D,$R24)*100 -> 0 | Y24: =SUMIFS($L:$L,$C:$C,Y$3,$D:$D,$R24)*100 -> 0 | Z24: =SUMIFS($L:$L,$C:$C,Z$3,$D:$D,$R24)*100 -> 0 | AA24: =SUMIFS($L:$L,$C:$C,AA$3,$D:$D,$R24)*100 -> 0 | AB24: =SUMPRODUCT($T$4:$AA$4,T24:AA24) -> 0.18309833 | AC24: =SUMIFS($L:$L,$C:$C,AC$3,$D:$D,$R24)*100 -> 0 | AD24: =SUMIFS($L:$L,$C:$C,AD$3,$D:$D,$R24)*100 -> 0 | AE24: =SUMIFS($L:$L,$C:$C,AE$3,$D:$D,$R24)*100 -> 0 | AF24: =SUMPRODUCT($AC$4:$AE$4,AC24:AE24) -> 0 | AH24: =AB24/100*$AL$6 -> 781.31841 | AI24: =AF24/100*$AL$23 -> 0 | AK24: Dosificado | AL24: =AR23 -> 343531.76 | AM24: 0 | AO24: =AL24*AN24 -> 0 | AQ24: =AL24*AP24 -> 0 | AR24: =AL24+AM24-AO24-AQ24 -> 343531.76 | AS24: kg/año | AU24: Fermentadora | AX24: kg/h | AZ24: cm | BB24: kg | BC24: - | BD24: kw/h
B25: 14 | C25: A01 | D25: M056 | E25: BICARBONATO DE SODIO | G25: X | L25: 0.005 | M25: =$E$9*L25 -> 0.017045455 | N25: Kg. | R25: M106 | S25: FIBRA DE BAMBÚ | T25: =SUMIFS($L:$L,$C:$C,T$3,$D:$D,$R25)*100 -> 0 | U25: =SUMIFS($L:$L,$C:$C,U$3,$D:$D,$R25)*100 -> 4 | V25: =SUMIFS($L:$L,$C:$C,V$3,$D:$D,$R25)*100 -> 0 | W25: =SUMIFS($L:$L,$C:$C,W$3,$D:$D,$R25)*100 -> 0 | X25: =SUMIFS($L:$L,$C:$C,X$3,$D:$D,$R25)*100 -> 0 | Y25: =SUMIFS($L:$L,$C:$C,Y$3,$D:$D,$R25)*100 -> 0 | Z25: =SUMIFS($L:$L,$C:$C,Z$3,$D:$D,$R25)*100 -> 6 | AA25: =SUMIFS($L:$L,$C:$C,AA$3,$D:$D,$R25)*100 -> 0 | AB25: =SUMPRODUCT($T$4:$AA$4,T25:AA25) -> 0.52675982 | AC25: =SUMIFS($L:$L,$C:$C,AC$3,$D:$D,$R25)*100 -> 0 | AD25: =SUMIFS($L:$L,$C:$C,AD$3,$D:$D,$R25)*100 -> 0 | AE25: =SUMIFS($L:$L,$C:$C,AE$3,$D:$D,$R25)*100 -> 0 | AF25: =SUMPRODUCT($AC$4:$AE$4,AC25:AE25) -> 0 | AH25: =AB25/100*$AL$6 -> 2247.793 | AI25: =AF25/100*$AL$23 -> 0 | AK25: Fermentado | AL25: =AR24 -> 343531.76 | AM25: 0 | AO25: =AL25*AN25 -> 0 | AQ25: =AL25*AP25 -> 0 | AR25: =AL25+AM25-AO25-AQ25 -> 343531.76 | AS25: kg/año | AU25: Horno rotativo | AX25: kg/h | AZ25: cm | BB25: kg | BC25: - | BD25: kw/h
B26: 15 | C26: A01 | D26: M089 | E26: ESENCIA DE VAINILLA | G26: X | L26: 0.004 | M26: =$E$9*L26 -> 0.013636364 | N26: Kg. | R26: M107 | S26: PSYLLIUM | T26: =SUMIFS($L:$L,$C:$C,T$3,$D:$D,$R26)*100 -> 0 | U26: =SUMIFS($L:$L,$C:$C,U$3,$D:$D,$R26)*100 -> 3 | V26: =SUMIFS($L:$L,$C:$C,V$3,$D:$D,$R26)*100 -> 0 | W26: =SUMIFS($L:$L,$C:$C,W$3,$D:$D,$R26)*100 -> 0 | X26: =SUMIFS($L:$L,$C:$C,X$3,$D:$D,$R26)*100 -> 0 | Y26: =SUMIFS($L:$L,$C:$C,Y$3,$D:$D,$R26)*100 -> 0 | Z26: =SUMIFS($L:$L,$C:$C,Z$3,$D:$D,$R26)*100 -> 0 | AA26: =SUMIFS($L:$L,$C:$C,AA$3,$D:$D,$R26)*100 -> 0 | AB26: =SUMPRODUCT($T$4:$AA$4,T26:AA26) -> 0.109859 | AC26: =SUMIFS($L:$L,$C:$C,AC$3,$D:$D,$R26)*100 -> 3 | AD26: =SUMIFS($L:$L,$C:$C,AD$3,$D:$D,$R26)*100 -> 0 | AE26: =SUMIFS($L:$L,$C:$C,AE$3,$D:$D,$R26)*100 -> 0 | AF26: =SUMPRODUCT($AC$4:$AE$4,AC26:AE26) -> 1.1052628 | AH26: =AB26/100*$AL$6 -> 468.79105 | AI26: =AF26/100*$AL$23 -> 3796.9287 | AK26: Horneado | AL26: =AR25 -> 343531.76 | AM26: 0 | AO26: =AL26*AN26 -> 0 | AQ26: =AL26*AP26 -> 0 | AR26: =AL26+AM26-AO26-AQ26 -> 343531.76 | AS26: kg/año | AU26: Cinta de enfriamiento | AX26: kg/h | AZ26: cm | BB26: kg | BC26: - | BD26: kw/h
B27: 16 | C27: A01 | D27: M047 | E27: ESENCIA DE CHOCOLATE | G27: X | L27: 0.003 | M27: =$E$9*L27 -> 0.010227273 | N27: Kg. | R27: M108 | S27: EDULCORANTE | T27: =SUMIFS($L:$L,$C:$C,T$3,$D:$D,$R27)*100 -> 0 | U27: =SUMIFS($L:$L,$C:$C,U$3,$D:$D,$R27)*100 -> 1.5 | V27: =SUMIFS($L:$L,$C:$C,V$3,$D:$D,$R27)*100 -> 0 | W27: =SUMIFS($L:$L,$C:$C,W$3,$D:$D,$R27)*100 -> 0 | X27: =SUMIFS($L:$L,$C:$C,X$3,$D:$D,$R27)*100 -> 0 | Y27: =SUMIFS($L:$L,$C:$C,Y$3,$D:$D,$R27)*100 -> 0 | Z27: =SUMIFS($L:$L,$C:$C,Z$3,$D:$D,$R27)*100 -> 3 | AA27: =SUMIFS($L:$L,$C:$C,AA$3,$D:$D,$R27)*100 -> 0 | AB27: =SUMPRODUCT($T$4:$AA$4,T27:AA27) -> 0.24507008 | AC27: =SUMIFS($L:$L,$C:$C,AC$3,$D:$D,$R27)*100 -> 0 | AD27: =SUMIFS($L:$L,$C:$C,AD$3,$D:$D,$R27)*100 -> 0 | AE27: =SUMIFS($L:$L,$C:$C,AE$3,$D:$D,$R27)*100 -> 0 | AF27: =SUMPRODUCT($AC$4:$AE$4,AC27:AE27) -> 0 | AH27: =AB27/100*$AL$6 -> 1045.7646 | AI27: =AF27/100*$AL$23 -> 0 | AK27: Desmolde | AL27: =AR26 -> 343531.76 | AM27: 0 | AO27: =AL27*AN27 -> 0 | AQ27: =AL27*AP27 -> 0 | AR27: =AL27+AM27-AO27-AQ27 -> 343531.76 | AS27: kg/año | AU27: Envasadora | AX27: kg/h | AZ27: cm | BB27: kg | BC27: - | BD27: kw/h
B28: 17 | C28: A01 | D28: M057 | E28: BICARBONATO DE CALCIO | G28: X | L28: 0.003 | M28: =$E$9*L28 -> 0.010227273 | N28: Kg. | R28: M109 | S28: LECHE EN POLVO | T28: =SUMIFS($L:$L,$C:$C,T$3,$D:$D,$R28)*100 -> 0 | U28: =SUMIFS($L:$L,$C:$C,U$3,$D:$D,$R28)*100 -> 0 | V28: =SUMIFS($L:$L,$C:$C,V$3,$D:$D,$R28)*100 -> 6 | W28: =SUMIFS($L:$L,$C:$C,W$3,$D:$D,$R28)*100 -> 0 | X28: =SUMIFS($L:$L,$C:$C,X$3,$D:$D,$R28)*100 -> 0 | Y28: =SUMIFS($L:$L,$C:$C,Y$3,$D:$D,$R28)*100 -> 0 | Z28: =SUMIFS($L:$L,$C:$C,Z$3,$D:$D,$R28)*100 -> 0 | AA28: =SUMIFS($L:$L,$C:$C,AA$3,$D:$D,$R28)*100 -> 0 | AB28: =SUMPRODUCT($T$4:$AA$4,T28:AA28) -> 0.51267815 | AC28: =SUMIFS($L:$L,$C:$C,AC$3,$D:$D,$R28)*100 -> 4 | AD28: =SUMIFS($L:$L,$C:$C,AD$3,$D:$D,$R28)*100 -> 5 | AE28: =SUMIFS($L:$L,$C:$C,AE$3,$D:$D,$R28)*100 -> 4 | AF28: =SUMPRODUCT($AC$4:$AE$4,AC28:AE28) -> 4.4421054 | AH28: =AB28/100*$AL$6 -> 2187.7036 | AI28: =AF28/100*$AL$23 -> 15260.043 | AK28: Enfriado | AL28: =AR27 -> 343531.76 | AM28: 0 | AO28: =AL28*AN28 -> 0 | AP28: 0.04 | AQ28: =AL28*AP28 -> 13741.27 | AR28: =AL28+AM28-AO28-AQ28 -> 329790.49 | AS28: kg/año | AU28: Envasadora | AX28: kg/h | AZ28: cm | BB28: kg | BC28: - | BD28: kw/h
B29: 18 | C29: A01 | D29: M049 | E29: JALAPEÑO DESHIDRATADO EN POLVO | G29: X | L29: 0.002 | M29: =$E$9*L29 -> 0.0068181818 | N29: Kg. | R29: M110 | S29: JARABE DE MAÍZ ALTA FRUCTOSA | T29: =SUMIFS($L:$L,$C:$C,T$3,$D:$D,$R29)*100 -> 0 | U29: =SUMIFS($L:$L,$C:$C,U$3,$D:$D,$R29)*100 -> 0 | V29: =SUMIFS($L:$L,$C:$C,V$3,$D:$D,$R29)*100 -> 0 | W29: =SUMIFS($L:$L,$C:$C,W$3,$D:$D,$R29)*100 -> 7.92 | X29: =SUMIFS($L:$L,$C:$C,X$3,$D:$D,$R29)*100 -> 0 | Y29: =SUMIFS($L:$L,$C:$C,Y$3,$D:$D,$R29)*100 -> 0 | Z29: =SUMIFS($L:$L,$C:$C,Z$3,$D:$D,$R29)*100 -> 0 | AA29: =SUMIFS($L:$L,$C:$C,AA$3,$D:$D,$R29)*100 -> 0 | AB29: =SUMPRODUCT($T$4:$AA$4,T29:AA29) -> 2.0822543 | AC29: =SUMIFS($L:$L,$C:$C,AC$3,$D:$D,$R29)*100 -> 0 | AD29: =SUMIFS($L:$L,$C:$C,AD$3,$D:$D,$R29)*100 -> 0 | AE29: =SUMIFS($L:$L,$C:$C,AE$3,$D:$D,$R29)*100 -> 0 | AF29: =SUMPRODUCT($AC$4:$AE$4,AC29:AE29) -> 0 | AH29: =AB29/100*$AL$6 -> 8885.4093 | AI29: =AF29/100*$AL$23 -> 0 | AK29: Envasado primario | AL29: =AR28 -> 329790.49 | AM29: 0 | AO29: =AL29*AN29 -> 0 | AP29: 0.03 | AQ29: =AL29*AP29 -> 9893.7146 | AR29: =AL29+AM29-AO29-AQ29 -> 319896.77 | AS29: kg/año | AX29: kg/h | AZ29: cm | BB29: kg | BC29: - | BD29: kw/h
E30: AGUA
D31: TOTAL MEZCLA | L31: =L13+L14+L15+L16+L17+L18+L19+L20+L21+L22+L23+L24+L25+L26+L27+L28+L29 -> 1 | M31: =M13+M14+M15+M16+M17+M18+M19+M20+M21+M22+M23+M24+M25+M26+M27+M28+M29 -> 3.4090909 | N31: Kg. | R31: M111 | S31: LECITINA DE SOJA | T31: =SUMIFS($L:$L,$C:$C,T$3,$D:$D,$R31)*100 -> 0 | U31: =SUMIFS($L:$L,$C:$C,U$3,$D:$D,$R31)*100 -> 0 | V31: =SUMIFS($L:$L,$C:$C,V$3,$D:$D,$R31)*100 -> 0 | W31: =SUMIFS($L:$L,$C:$C,W$3,$D:$D,$R31)*100 -> 0.36 | X31: =SUMIFS($L:$L,$C:$C,X$3,$D:$D,$R31)*100 -> 0 | Y31: =SUMIFS($L:$L,$C:$C,Y$3,$D:$D,$R31)*100 -> 0 | Z31: =SUMIFS($L:$L,$C:$C,Z$3,$D:$D,$R31)*100 -> 0 | AA31: =SUMIFS($L:$L,$C:$C,AA$3,$D:$D,$R31)*100 -> 1 | AB31: =SUMPRODUCT($T$4:$AA$4,T31:AA31) -> 0.24253504 | AC31: =SUMIFS($L:$L,$C:$C,AC$3,$D:$D,$R31)*100 -> 0 | AD31: =SUMIFS($L:$L,$C:$C,AD$3,$D:$D,$R31)*100 -> 0 | AE31: =SUMIFS($L:$L,$C:$C,AE$3,$D:$D,$R31)*100 -> 0 | AF31: =SUMPRODUCT($AC$4:$AE$4,AC31:AE31) -> 0 | AH31: =AB31/100*$AL$6 -> 1034.9471 | AI31: =AF31/100*$AL$23 -> 0 | AK31: Envasado secundario | AL31: =AR29 -> 319896.77 | AM31: 0 | AO31: =AL31*AN31 -> 0 | AQ31: =AL31*AP31 -> 0 | AR31: =AL31+AM31-AO31-AQ31 -> 319896.77 | AS31: kg/año | AX31: kg/h | AZ31: cm | BB31: kg | BC31: - | BD31: kw/h
B32: EMBALAJE | R32: M112 | S32: ESENCIA DE LECHE CONDENSADA | T32: =SUMIFS($L:$L,$C:$C,T$3,$D:$D,$R32)*100 -> 0 | U32: =SUMIFS($L:$L,$C:$C,U$3,$D:$D,$R32)*100 -> 0 | V32: =SUMIFS($L:$L,$C:$C,V$3,$D:$D,$R32)*100 -> 0 | W32: =SUMIFS($L:$L,$C:$C,W$3,$D:$D,$R32)*100 -> 0.288 | X32: =SUMIFS($L:$L,$C:$C,X$3,$D:$D,$R32)*100 -> 0 | Y32: =SUMIFS($L:$L,$C:$C,Y$3,$D:$D,$R32)*100 -> 0 | Z32: =SUMIFS($L:$L,$C:$C,Z$3,$D:$D,$R32)*100 -> 0 | AA32: =SUMIFS($L:$L,$C:$C,AA$3,$D:$D,$R32)*100 -> 0 | AB32: =SUMPRODUCT($T$4:$AA$4,T32:AA32) -> 0.075718338 | AC32: =SUMIFS($L:$L,$C:$C,AC$3,$D:$D,$R32)*100 -> 0 | AD32: =SUMIFS($L:$L,$C:$C,AD$3,$D:$D,$R32)*100 -> 0 | AE32: =SUMIFS($L:$L,$C:$C,AE$3,$D:$D,$R32)*100 -> 0 | AF32: =SUMPRODUCT($AC$4:$AE$4,AC32:AE32) -> 0 | AH32: =AB32/100*$AL$6 -> 323.10579 | AI32: =AF32/100*$AL$23 -> 0 | AK32: TOTALES | AL32: =AL23 -> 343531.76 | AM32: =AM23 -> 0 | AO32: =AO23+AO24+AO25+AO26+AO28 -> 0 | AQ32: =AQ23+AQ24+AQ25+AQ26+AQ28 -> 13741.27 | AR32: =SUMIFS('Plan de ventas'!$O48:$O60,'Plan de ventas'!$B$48:$B$60,"*B*")*1000 -> 319894.73 | AS32: kg/año | AX32: kg/h | AZ32: cm | BB32: kg | BC32: - | BD32: kw/h
B33: 19 | C33: A01 | D33: M101 | E33: FILM FLOW-PACK (ENVOLTORIO PRIMARIO) | G33: X | L33: — | M33: =$E$4*$E$5 -> 20 | N33: uni. | O33: 1 por unidad | R33: M113 | S33: MERMELADA DE BATATA | T33: =SUMIFS($L:$L,$C:$C,T$3,$D:$D,$R33)*100 -> 0 | U33: =SUMIFS($L:$L,$C:$C,U$3,$D:$D,$R33)*100 -> 0 | V33: =SUMIFS($L:$L,$C:$C,V$3,$D:$D,$R33)*100 -> 0 | W33: =SUMIFS($L:$L,$C:$C,W$3,$D:$D,$R33)*100 -> 19.6 | X33: =SUMIFS($L:$L,$C:$C,X$3,$D:$D,$R33)*100 -> 0 | Y33: =SUMIFS($L:$L,$C:$C,Y$3,$D:$D,$R33)*100 -> 0 | Z33: =SUMIFS($L:$L,$C:$C,Z$3,$D:$D,$R33)*100 -> 0 | AA33: =SUMIFS($L:$L,$C:$C,AA$3,$D:$D,$R33)*100 -> 0 | AB33: =SUMPRODUCT($T$4:$AA$4,T33:AA33) -> 5.1530536 | AC33: =SUMIFS($L:$L,$C:$C,AC$3,$D:$D,$R33)*100 -> 0 | AD33: =SUMIFS($L:$L,$C:$C,AD$3,$D:$D,$R33)*100 -> 0 | AE33: =SUMIFS($L:$L,$C:$C,AE$3,$D:$D,$R33)*100 -> 0 | AF33: =SUMPRODUCT($AC$4:$AE$4,AC33:AE33) -> 0 | AH33: =AB33/100*$AL$6 -> 21989.144 | AI33: =AF33/100*$AL$23 -> 0
B34: 20 | C34: A01 | D34: M102 | E34: CAJA DE CARTÓN CORRUGADO | G34: X | L34: — | M34: =$E$4 -> 1 | N34: uni. | O34: 1 por caja | R34: M114 | S34: ÁCIDO CÍTRICO | T34: =SUMIFS($L:$L,$C:$C,T$3,$D:$D,$R34)*100 -> 0 | U34: =SUMIFS($L:$L,$C:$C,U$3,$D:$D,$R34)*100 -> 0 | V34: =SUMIFS($L:$L,$C:$C,V$3,$D:$D,$R34)*100 -> 0 | W34: =SUMIFS($L:$L,$C:$C,W$3,$D:$D,$R34)*100 -> 0.14 | X34: =SUMIFS($L:$L,$C:$C,X$3,$D:$D,$R34)*100 -> 0 | Y34: =SUMIFS($L:$L,$C:$C,Y$3,$D:$D,$R34)*100 -> 0 | Z34: =SUMIFS($L:$L,$C:$C,Z$3,$D:$D,$R34)*100 -> 0 | AA34: =SUMIFS($L:$L,$C:$C,AA$3,$D:$D,$R34)*100 -> 0 | AB34: =SUMPRODUCT($T$4:$AA$4,T34:AA34) -> 0.036807526 | AC34: =SUMIFS($L:$L,$C:$C,AC$3,$D:$D,$R34)*100 -> 0 | AD34: =SUMIFS($L:$L,$C:$C,AD$3,$D:$D,$R34)*100 -> 0 | AE34: =SUMIFS($L:$L,$C:$C,AE$3,$D:$D,$R34)*100 -> 0 | AF34: =SUMPRODUCT($AC$4:$AE$4,AC34:AE34) -> 0 | AH34: =AB34/100*$AL$6 -> 157.06532 | AI34: =AF34/100*$AL$23 -> 0 | AK34: Desperdicio total | AL34: 0.07389 | AQ34: Desvios | AR34: =AR31/AR32-1 -> 6.368e-06
B35: 21 | C35: A01 | D35: M103 | E35: CINTA DE CIERRE | G35: X | L35: — | M35: =$E$4 -> 1 | N35: uni. | O35: 1 por caja | R35: M115 | S35: ALMIDÓN DE MAÍZ | T35: =SUMIFS($L:$L,$C:$C,T$3,$D:$D,$R35)*100 -> 0 | U35: =SUMIFS($L:$L,$C:$C,U$3,$D:$D,$R35)*100 -> 0 | V35: =SUMIFS($L:$L,$C:$C,V$3,$D:$D,$R35)*100 -> 0 | W35: =SUMIFS($L:$L,$C:$C,W$3,$D:$D,$R35)*100 -> 0 | X35: =SUMIFS($L:$L,$C:$C,X$3,$D:$D,$R35)*100 -> 19 | Y35: =SUMIFS($L:$L,$C:$C,Y$3,$D:$D,$R35)*100 -> 19 | Z35: =SUMIFS($L:$L,$C:$C,Z$3,$D:$D,$R35)*100 -> 0 | AA35: =SUMIFS($L:$L,$C:$C,AA$3,$D:$D,$R35)*100 -> 0 | AB35: =SUMPRODUCT($T$4:$AA$4,T35:AA35) -> 2.3192545 | AC35: =SUMIFS($L:$L,$C:$C,AC$3,$D:$D,$R35)*100 -> 12 | AD35: =SUMIFS($L:$L,$C:$C,AD$3,$D:$D,$R35)*100 -> 0 | AE35: =SUMIFS($L:$L,$C:$C,AE$3,$D:$D,$R35)*100 -> 0 | AF35: =SUMPRODUCT($AC$4:$AE$4,AC35:AE35) -> 4.4210512 | AH35: =AB35/100*$AL$6 -> 9896.738 | AI35: =AF35/100*$AL$23 -> 15187.715
R36: M116 | S36: FÉCULA DE MANDIOCA | T36: =SUMIFS($L:$L,$C:$C,T$3,$D:$D,$R36)*100 -> 0 | U36: =SUMIFS($L:$L,$C:$C,U$3,$D:$D,$R36)*100 -> 0 | V36: =SUMIFS($L:$L,$C:$C,V$3,$D:$D,$R36)*100 -> 0 | W36: =SUMIFS($L:$L,$C:$C,W$3,$D:$D,$R36)*100 -> 0 | X36: =SUMIFS($L:$L,$C:$C,X$3,$D:$D,$R36)*100 -> 15 | Y36: =SUMIFS($L:$L,$C:$C,Y$3,$D:$D,$R36)*100 -> 14 | Z36: =SUMIFS($L:$L,$C:$C,Z$3,$D:$D,$R36)*100 -> 0 | AA36: =SUMIFS($L:$L,$C:$C,AA$3,$D:$D,$R36)*100 -> 0 | AB36: =SUMPRODUCT($T$4:$AA$4,T36:AA36) -> 1.745544 | AC36: =SUMIFS($L:$L,$C:$C,AC$3,$D:$D,$R36)*100 -> 10 | AD36: =SUMIFS($L:$L,$C:$C,AD$3,$D:$D,$R36)*100 -> 6 | AE36: =SUMIFS($L:$L,$C:$C,AE$3,$D:$D,$R36)*100 -> 5 | AF36: =SUMPRODUCT($AC$4:$AE$4,AC36:AE36) -> 7.2842101 | AH36: =AB36/100*$AL$6 -> 7448.5969 | AI36: =AF36/100*$AL$23 -> 25023.575
D37: Galletitas símil chocolinas free - A02 | M37: Foto | R37: M117 | S37: QUESO DESCREMADO EN POLVO | T37: =SUMIFS($L:$L,$C:$C,T$3,$D:$D,$R37)*100 -> 0 | U37: =SUMIFS($L:$L,$C:$C,U$3,$D:$D,$R37)*100 -> 0 | V37: =SUMIFS($L:$L,$C:$C,V$3,$D:$D,$R37)*100 -> 0 | W37: =SUMIFS($L:$L,$C:$C,W$3,$D:$D,$R37)*100 -> 0 | X37: =SUMIFS($L:$L,$C:$C,X$3,$D:$D,$R37)*100 -> 13 | Y37: =SUMIFS($L:$L,$C:$C,Y$3,$D:$D,$R37)*100 -> 0 | Z37: =SUMIFS($L:$L,$C:$C,Z$3,$D:$D,$R37)*100 -> 0 | AA37: =SUMIFS($L:$L,$C:$C,AA$3,$D:$D,$R37)*100 -> 0 | AB37: =SUMPRODUCT($T$4:$AA$4,T37:AA37) -> 0.47605567 | AC37: =SUMIFS($L:$L,$C:$C,AC$3,$D:$D,$R37)*100 -> 0 | AD37: =SUMIFS($L:$L,$C:$C,AD$3,$D:$D,$R37)*100 -> 0 | AE37: =SUMIFS($L:$L,$C:$C,AE$3,$D:$D,$R37)*100 -> 0 | AF37: =SUMPRODUCT($AC$4:$AE$4,AC37:AE37) -> 0 | AH37: =AB37/100*$AL$6 -> 2031.4279 | AI37: =AF37/100*$AL$23 -> 0
D38: PT anual (kg) | E38: =SUMIFS('Plan de ventas'!$O$48:$O$60,'Plan de ventas'!$B$48:$B$60,D47)*1000 -> 13132.517 | R38: M118 | S38: ACEITE DE GIRASOL ALTO OLEICO | T38: =SUMIFS($L:$L,$C:$C,T$3,$D:$D,$R38)*100 -> 0 | U38: =SUMIFS($L:$L,$C:$C,U$3,$D:$D,$R38)*100 -> 0 | V38: =SUMIFS($L:$L,$C:$C,V$3,$D:$D,$R38)*100 -> 0 | W38: =SUMIFS($L:$L,$C:$C,W$3,$D:$D,$R38)*100 -> 0 | X38: =SUMIFS($L:$L,$C:$C,X$3,$D:$D,$R38)*100 -> 8 | Y38: =SUMIFS($L:$L,$C:$C,Y$3,$D:$D,$R38)*100 -> 6 | Z38: =SUMIFS($L:$L,$C:$C,Z$3,$D:$D,$R38)*100 -> 0 | AA38: =SUMIFS($L:$L,$C:$C,AA$3,$D:$D,$R38)*100 -> 0 | AB38: =SUMPRODUCT($T$4:$AA$4,T38:AA38) -> 0.80563549 | AC38: =SUMIFS($L:$L,$C:$C,AC$3,$D:$D,$R38)*100 -> 0 | AD38: =SUMIFS($L:$L,$C:$C,AD$3,$D:$D,$R38)*100 -> 0 | AE38: =SUMIFS($L:$L,$C:$C,AE$3,$D:$D,$R38)*100 -> 0 | AF38: =SUMPRODUCT($AC$4:$AE$4,AC38:AE38) -> 0 | AH38: =AB38/100*$AL$6 -> 3437.813 | AI38: =AF38/100*$AL$23 -> 0
B39: Cajas / lote | E39: 1 | F39: ="Línea: Free | Versión n°: 1"&CHAR(10)&CHAR(10)&"Lote = "&E39&" cajas × "&E40&" unid./caja = "&(E39*E40)&" unidades"&CHAR(10)&"Producto terminado = "&TEXT(E43,"#,##0.00")&" kg"&CHAR(10)&"Mezcla a preparar = "&TEXT(E44,"#,##0.00")&" kg (rendimiento "&TEXT(E42,"0%")&")" -> Línea: Free | Versión n°: 1 Lote = 1 cajas × 20 unid./caja = 20 unidades Producto terminado = 3,00 kg Mezcla a preparar = 3,41 kg (rendimiento 88%) | R39: M119 | S39: CLARA DE HUEVO EN POLVO | T39: =SUMIFS($L:$L,$C:$C,T$3,$D:$D,$R39)*100 -> 0 | U39: =SUMIFS($L:$L,$C:$C,U$3,$D:$D,$R39)*100 -> 0 | V39: =SUMIFS($L:$L,$C:$C,V$3,$D:$D,$R39)*100 -> 0 | W39: =SUMIFS($L:$L,$C:$C,W$3,$D:$D,$R39)*100 -> 0 | X39: =SUMIFS($L:$L,$C:$C,X$3,$D:$D,$R39)*100 -> 5 | Y39: =SUMIFS($L:$L,$C:$C,Y$3,$D:$D,$R39)*100 -> 0 | Z39: =SUMIFS($L:$L,$C:$C,Z$3,$D:$D,$R39)*100 -> 0 | AA39: =SUMIFS($L:$L,$C:$C,AA$3,$D:$D,$R39)*100 -> 0 | AB39: =SUMPRODUCT($T$4:$AA$4,T39:AA39) -> 0.18309833 | AC39: =SUMIFS($L:$L,$C:$C,AC$3,$D:$D,$R39)*100 -> 0 | AD39: =SUMIFS($L:$L,$C:$C,AD$3,$D:$D,$R39)*100 -> 0 | AE39: =SUMIFS($L:$L,$C:$C,AE$3,$D:$D,$R39)*100 -> 0 | AF39: =SUMPRODUCT($AC$4:$AE$4,AC39:AE39) -> 0 | AH39: =AB39/100*$AL$6 -> 781.31841 | AI39: =AF39/100*$AL$23 -> 0
B40: Unid. / caja | E40: 20 | R40: M120 | S40: DEXTROSA | T40: =SUMIFS($L:$L,$C:$C,T$3,$D:$D,$R40)*100 -> 0 | U40: =SUMIFS($L:$L,$C:$C,U$3,$D:$D,$R40)*100 -> 0 | V40: =SUMIFS($L:$L,$C:$C,V$3,$D:$D,$R40)*100 -> 0 | W40: =SUMIFS($L:$L,$C:$C,W$3,$D:$D,$R40)*100 -> 0 | X40: =SUMIFS($L:$L,$C:$C,X$3,$D:$D,$R40)*100 -> 4 | Y40: =SUMIFS($L:$L,$C:$C,Y$3,$D:$D,$R40)*100 -> 4 | Z40: =SUMIFS($L:$L,$C:$C,Z$3,$D:$D,$R40)*100 -> 0 | AA40: =SUMIFS($L:$L,$C:$C,AA$3,$D:$D,$R40)*100 -> 0 | AB40: =SUMPRODUCT($T$4:$AA$4,T40:AA40) -> 0.4882641 | AC40: =SUMIFS($L:$L,$C:$C,AC$3,$D:$D,$R40)*100 -> 0 | AD40: =SUMIFS($L:$L,$C:$C,AD$3,$D:$D,$R40)*100 -> 0 | AE40: =SUMIFS($L:$L,$C:$C,AE$3,$D:$D,$R40)*100 -> 0 | AF40: =SUMPRODUCT($AC$4:$AE$4,AC40:AE40) -> 0 | AH40: =AB40/100*$AL$6 -> 2083.5238 | AI40: =AF40/100*$AL$23 -> 0
B41: Peso neto (g) | E41: 150 | R41: M121 | S41: ESENCIA DE QUESO | T41: =SUMIFS($L:$L,$C:$C,T$3,$D:$D,$R41)*100 -> 0 | U41: =SUMIFS($L:$L,$C:$C,U$3,$D:$D,$R41)*100 -> 0 | V41: =SUMIFS($L:$L,$C:$C,V$3,$D:$D,$R41)*100 -> 0 | W41: =SUMIFS($L:$L,$C:$C,W$3,$D:$D,$R41)*100 -> 0 | X41: =SUMIFS($L:$L,$C:$C,X$3,$D:$D,$R41)*100 -> 1 | Y41: =SUMIFS($L:$L,$C:$C,Y$3,$D:$D,$R41)*100 -> 1 | Z41: =SUMIFS($L:$L,$C:$C,Z$3,$D:$D,$R41)*100 -> 0 | AA41: =SUMIFS($L:$L,$C:$C,AA$3,$D:$D,$R41)*100 -> 0 | AB41: =SUMPRODUCT($T$4:$AA$4,T41:AA41) -> 0.12206603 | AC41: =SUMIFS($L:$L,$C:$C,AC$3,$D:$D,$R41)*100 -> 0 | AD41: =SUMIFS($L:$L,$C:$C,AD$3,$D:$D,$R41)*100 -> 0 | AE41: =SUMIFS($L:$L,$C:$C,AE$3,$D:$D,$R41)*100 -> 0 | AF41: =SUMPRODUCT($AC$4:$AE$4,AC41:AE41) -> 0 | AH41: =AB41/100*$AL$6 -> 520.88095 | AI41: =AF41/100*$AL$23 -> 0
B42: Rendim. (%) | E42: 0.88 | R42: M122 | S42: POLVO PARA HORNEAR | T42: =SUMIFS($L:$L,$C:$C,T$3,$D:$D,$R42)*100 -> 0 | U42: =SUMIFS($L:$L,$C:$C,U$3,$D:$D,$R42)*100 -> 0 | V42: =SUMIFS($L:$L,$C:$C,V$3,$D:$D,$R42)*100 -> 0 | W42: =SUMIFS($L:$L,$C:$C,W$3,$D:$D,$R42)*100 -> 0 | X42: =SUMIFS($L:$L,$C:$C,X$3,$D:$D,$R42)*100 -> 1 | Y42: =SUMIFS($L:$L,$C:$C,Y$3,$D:$D,$R42)*100 -> 1 | Z42: =SUMIFS($L:$L,$C:$C,Z$3,$D:$D,$R42)*100 -> 2 | AA42: =SUMIFS($L:$L,$C:$C,AA$3,$D:$D,$R42)*100 -> 2 | AB42: =SUMPRODUCT($T$4:$AA$4,T42:AA42) -> 0.54460064 | AC42: =SUMIFS($L:$L,$C:$C,AC$3,$D:$D,$R42)*100 -> 0 | AD42: =SUMIFS($L:$L,$C:$C,AD$3,$D:$D,$R42)*100 -> 2 | AE42: =SUMIFS($L:$L,$C:$C,AE$3,$D:$D,$R42)*100 -> 2 | AF42: =SUMPRODUCT($AC$4:$AE$4,AC42:AE42) -> 1.2631581 | AH42: =AB42/100*$AL$6 -> 2323.9234 | AI42: =AF42/100*$AL$23 -> 4339.3493
B43: PT (kg) | E43: =E39*E40*E41/1000 -> 3 | R43: M123 | S43: QUESO RALLADO | T43: =SUMIFS($L:$L,$C:$C,T$3,$D:$D,$R43)*100 -> 0 | U43: =SUMIFS($L:$L,$C:$C,U$3,$D:$D,$R43)*100 -> 0 | V43: =SUMIFS($L:$L,$C:$C,V$3,$D:$D,$R43)*100 -> 0 | W43: =SUMIFS($L:$L,$C:$C,W$3,$D:$D,$R43)*100 -> 0 | X43: =SUMIFS($L:$L,$C:$C,X$3,$D:$D,$R43)*100 -> 0 | Y43: =SUMIFS($L:$L,$C:$C,Y$3,$D:$D,$R43)*100 -> 12 | Z43: =SUMIFS($L:$L,$C:$C,Z$3,$D:$D,$R43)*100 -> 0 | AA43: =SUMIFS($L:$L,$C:$C,AA$3,$D:$D,$R43)*100 -> 0 | AB43: =SUMPRODUCT($T$4:$AA$4,T43:AA43) -> 1.0253563 | AC43: =SUMIFS($L:$L,$C:$C,AC$3,$D:$D,$R43)*100 -> 0 | AD43: =SUMIFS($L:$L,$C:$C,AD$3,$D:$D,$R43)*100 -> 0 | AE43: =SUMIFS($L:$L,$C:$C,AE$3,$D:$D,$R43)*100 -> 0 | AF43: =SUMPRODUCT($AC$4:$AE$4,AC43:AE43) -> 0 | AH43: =AB43/100*$AL$6 -> 4375.4072 | AI43: =AF43/100*$AL$23 -> 0
B44: Mezcla (kg) | E44: =E43/E42 -> 3.4090909 | R44: M124 | S44: GRASA VACUNA | T44: =SUMIFS($L:$L,$C:$C,T$3,$D:$D,$R44)*100 -> 0 | U44: =SUMIFS($L:$L,$C:$C,U$3,$D:$D,$R44)*100 -> 0 | V44: =SUMIFS($L:$L,$C:$C,V$3,$D:$D,$R44)*100 -> 0 | W44: =SUMIFS($L:$L,$C:$C,W$3,$D:$D,$R44)*100 -> 0 | X44: =SUMIFS($L:$L,$C:$C,X$3,$D:$D,$R44)*100 -> 0 | Y44: =SUMIFS($L:$L,$C:$C,Y$3,$D:$D,$R44)*100 -> 10 | Z44: =SUMIFS($L:$L,$C:$C,Z$3,$D:$D,$R44)*100 -> 0 | AA44: =SUMIFS($L:$L,$C:$C,AA$3,$D:$D,$R44)*100 -> 0 | AB44: =SUMPRODUCT($T$4:$AA$4,T44:AA44) -> 0.85446359 | AC44: =SUMIFS($L:$L,$C:$C,AC$3,$D:$D,$R44)*100 -> 0 | AD44: =SUMIFS($L:$L,$C:$C,AD$3,$D:$D,$R44)*100 -> 0 | AE44: =SUMIFS($L:$L,$C:$C,AE$3,$D:$D,$R44)*100 -> 0 | AF44: =SUMPRODUCT($AC$4:$AE$4,AC44:AE44) -> 0 | AH44: =AB44/100*$AL$6 -> 3646.1726 | AI44: =AF44/100*$AL$23 -> 0
B45: ITEM | D45: CODIGO | E45: DENOMINACION | F45: NIVEL | L45: % | M45: CANTIDAD | N45: UNIDAD | O45: OBSERVACIONES | R45: M125 | S45: PANACEA | T45: =SUMIFS($L:$L,$C:$C,T$3,$D:$D,$R45)*100 -> 0 | U45: =SUMIFS($L:$L,$C:$C,U$3,$D:$D,$R45)*100 -> 0 | V45: =SUMIFS($L:$L,$C:$C,V$3,$D:$D,$R45)*100 -> 0 | W45: =SUMIFS($L:$L,$C:$C,W$3,$D:$D,$R45)*100 -> 0 | X45: =SUMIFS($L:$L,$C:$C,X$3,$D:$D,$R45)*100 -> 0 | Y45: =SUMIFS($L:$L,$C:$C,Y$3,$D:$D,$R45)*100 -> 0 | Z45: =SUMIFS($L:$L,$C:$C,Z$3,$D:$D,$R45)*100 -> 4 | AA45: =SUMIFS($L:$L,$C:$C,AA$3,$D:$D,$R45)*100 -> 3 | AB45: =SUMPRODUCT($T$4:$AA$4,T45:AA45) -> 0.69718212 | AC45: =SUMIFS($L:$L,$C:$C,AC$3,$D:$D,$R45)*100 -> 0 | AD45: =SUMIFS($L:$L,$C:$C,AD$3,$D:$D,$R45)*100 -> 2 | AE45: =SUMIFS($L:$L,$C:$C,AE$3,$D:$D,$R45)*100 -> 2 | AF45: =SUMPRODUCT($AC$4:$AE$4,AC45:AE45) -> 1.2631581 | AH45: =AB45/100*$AL$6 -> 2975.0201 | AI45: =AF45/100*$AL$23 -> 4339.3493
F46: 0 | G46: 1 | H46: 2 | I46: 3 | J46: 4 | K46: 5 | R46: M126 | S46: ESENCIA DE VAINILLA / NARANJA / LIMÓN | T46: =SUMIFS($L:$L,$C:$C,T$3,$D:$D,$R46)*100 -> 0 | U46: =SUMIFS($L:$L,$C:$C,U$3,$D:$D,$R46)*100 -> 0 | V46: =SUMIFS($L:$L,$C:$C,V$3,$D:$D,$R46)*100 -> 0 | W46: =SUMIFS($L:$L,$C:$C,W$3,$D:$D,$R46)*100 -> 0 | X46: =SUMIFS($L:$L,$C:$C,X$3,$D:$D,$R46)*100 -> 0 | Y46: =SUMIFS($L:$L,$C:$C,Y$3,$D:$D,$R46)*100 -> 0 | Z46: =SUMIFS($L:$L,$C:$C,Z$3,$D:$D,$R46)*100 -> 0 | AA46: =SUMIFS($L:$L,$C:$C,AA$3,$D:$D,$R46)*100 -> 0.5 | AB46: =SUMPRODUCT($T$4:$AA$4,T46:AA46) -> 0.073943558 | AC46: =SUMIFS($L:$L,$C:$C,AC$3,$D:$D,$R46)*100 -> 0 | AD46: =SUMIFS($L:$L,$C:$C,AD$3,$D:$D,$R46)*100 -> 1.2 | AE46: =SUMIFS($L:$L,$C:$C,AE$3,$D:$D,$R46)*100 -> 0 | AF46: =SUMPRODUCT($AC$4:$AE$4,AC46:AE46) -> 0.53052653 | AH46: =AB46/100*$AL$6 -> 315.53244 | AI46: =AF46/100*$AL$23 -> 1822.5271
B47: 1 | D47: A02 | E47: Galletitas símil chocolinas free (caja) | F47: X | L47: — | M47: =$E$39 -> 1 | N47: cajas | O47: Lote = 1 caja | R47: M127 | S47: AGUA | T47: =SUMIFS($L:$L,$C:$C,T$3,$D:$D,$R47)*100 -> 0 | U47: =SUMIFS($L:$L,$C:$C,U$3,$D:$D,$R47)*100 -> 0 | V47: =SUMIFS($L:$L,$C:$C,V$3,$D:$D,$R47)*100 -> 0 | W47: =SUMIFS($L:$L,$C:$C,W$3,$D:$D,$R47)*100 -> 0 | X47: =SUMIFS($L:$L,$C:$C,X$3,$D:$D,$R47)*100 -> 0 | Y47: =SUMIFS($L:$L,$C:$C,Y$3,$D:$D,$R47)*100 -> 0 | Z47: =SUMIFS($L:$L,$C:$C,Z$3,$D:$D,$R47)*100 -> 0 | AA47: =SUMIFS($L:$L,$C:$C,AA$3,$D:$D,$R47)*100 -> 0 | AB47: =SUMPRODUCT($T$4:$AA$4,T47:AA47) -> 0 | AC47: =SUMIFS($L:$L,$C:$C,AC$3,$D:$D,$R47)*100 -> 38 | AD47: =SUMIFS($L:$L,$C:$C,AD$3,$D:$D,$R47)*100 -> 11 | AE47: =SUMIFS($L:$L,$C:$C,AE$3,$D:$D,$R47)*100 -> 10 | AF47: =SUMPRODUCT($AC$4:$AE$4,AC47:AE47) -> 20.757892 | AH47: =AB47/100*$AL$6 -> 0 | AI47: =AF47/100*$AL$23 -> 71309.95
B48: 2 | C48: A02 | D48: M030 | E48: HARINA DE ARROZ | G48: X | L48: 0.27 | M48: =$E$44*L48 -> 0.92045455 | N48: Kg. | R48: M128 | S48: ACEITE DE GIRASOL | T48: =SUMIFS($L:$L,$C:$C,T$3,$D:$D,$R48)*100 -> 0 | U48: =SUMIFS($L:$L,$C:$C,U$3,$D:$D,$R48)*100 -> 0 | V48: =SUMIFS($L:$L,$C:$C,V$3,$D:$D,$R48)*100 -> 0 | W48: =SUMIFS($L:$L,$C:$C,W$3,$D:$D,$R48)*100 -> 0 | X48: =SUMIFS($L:$L,$C:$C,X$3,$D:$D,$R48)*100 -> 0 | Y48: =SUMIFS($L:$L,$C:$C,Y$3,$D:$D,$R48)*100 -> 0 | Z48: =SUMIFS($L:$L,$C:$C,Z$3,$D:$D,$R48)*100 -> 0 | AA48: =SUMIFS($L:$L,$C:$C,AA$3,$D:$D,$R48)*100 -> 0 | AB48: =SUMPRODUCT($T$4:$AA$4,T48:AA48) -> 0 | AC48: =SUMIFS($L:$L,$C:$C,AC$3,$D:$D,$R48)*100 -> 6 | AD48: =SUMIFS($L:$L,$C:$C,AD$3,$D:$D,$R48)*100 -> 0 | AE48: =SUMIFS($L:$L,$C:$C,AE$3,$D:$D,$R48)*100 -> 0 | AF48: =SUMPRODUCT($AC$4:$AE$4,AC48:AE48) -> 2.2105256 | AH48: =AB48/100*$AL$6 -> 0 | AI48: =AF48/100*$AL$23 -> 7593.8575
B49: 3 | C49: A02 | D49: M001 | E49: FÉCULA DE MAÍZ | G49: X | L49: 0.24 | M49: =$E$44*L49 -> 0.81818182 | N49: Kg. | R49: M130 | S49: FIBRA C 200 | T49: =SUMIFS($L:$L,$C:$C,T$3,$D:$D,$R49)*100 -> 0 | U49: =SUMIFS($L:$L,$C:$C,U$3,$D:$D,$R49)*100 -> 0 | V49: =SUMIFS($L:$L,$C:$C,V$3,$D:$D,$R49)*100 -> 0 | W49: =SUMIFS($L:$L,$C:$C,W$3,$D:$D,$R49)*100 -> 0 | X49: =SUMIFS($L:$L,$C:$C,X$3,$D:$D,$R49)*100 -> 0 | Y49: =SUMIFS($L:$L,$C:$C,Y$3,$D:$D,$R49)*100 -> 0 | Z49: =SUMIFS($L:$L,$C:$C,Z$3,$D:$D,$R49)*100 -> 0 | AA49: =SUMIFS($L:$L,$C:$C,AA$3,$D:$D,$R49)*100 -> 0 | AB49: =SUMPRODUCT($T$4:$AA$4,T49:AA49) -> 0 | AC49: =SUMIFS($L:$L,$C:$C,AC$3,$D:$D,$R49)*100 -> 2.5 | AD49: =SUMIFS($L:$L,$C:$C,AD$3,$D:$D,$R49)*100 -> 0 | AE49: =SUMIFS($L:$L,$C:$C,AE$3,$D:$D,$R49)*100 -> 0 | AF49: =SUMPRODUCT($AC$4:$AE$4,AC49:AE49) -> 0.92105234 | AH49: =AB49/100*$AL$6 -> 0 | AI49: =AF49/100*$AL$23 -> 3164.1073
B50: 4 | C50: A02 | D50: M036 | E50: ACEITE VEGETAL INTERESTERIFICADO | G50: X | L50: 0.14 | M50: =$E$44*L50 -> 0.47727273 | N50: Kg. | R50: M131 | S50: LEVADURA | T50: =SUMIFS($L:$L,$C:$C,T$3,$D:$D,$R50)*100 -> 0 | U50: =SUMIFS($L:$L,$C:$C,U$3,$D:$D,$R50)*100 -> 0 | V50: =SUMIFS($L:$L,$C:$C,V$3,$D:$D,$R50)*100 -> 0 | W50: =SUMIFS($L:$L,$C:$C,W$3,$D:$D,$R50)*100 -> 0 | X50: =SUMIFS($L:$L,$C:$C,X$3,$D:$D,$R50)*100 -> 0 | Y50: =SUMIFS($L:$L,$C:$C,Y$3,$D:$D,$R50)*100 -> 0 | Z50: =SUMIFS($L:$L,$C:$C,Z$3,$D:$D,$R50)*100 -> 0 | AA50: =SUMIFS($L:$L,$C:$C,AA$3,$D:$D,$R50)*100 -> 0 | AB50: =SUMPRODUCT($T$4:$AA$4,T50:AA50) -> 0 | AC50: =SUMIFS($L:$L,$C:$C,AC$3,$D:$D,$R50)*100 -> 2 | AD50: =SUMIFS($L:$L,$C:$C,AD$3,$D:$D,$R50)*100 -> 0 | AE50: =SUMIFS($L:$L,$C:$C,AE$3,$D:$D,$R50)*100 -> 0 | AF50: =SUMPRODUCT($AC$4:$AE$4,AC50:AE50) -> 0.73684187 | AH50: =AB50/100*$AL$6 -> 0 | AI50: =AF50/100*$AL$23 -> 2531.2858
B51: 5 | C51: A02 | D51: M104 | E51: PASTA DE PASAS DE UVA | G51: X | L51: 0.13 | M51: =$E$44*L51 -> 0.44318182 | N51: Kg. | R51: M134 | S51: MARGARINA | T51: =SUMIFS($L:$L,$C:$C,T$3,$D:$D,$R51)*100 -> 0 | U51: =SUMIFS($L:$L,$C:$C,U$3,$D:$D,$R51)*100 -> 0 | V51: =SUMIFS($L:$L,$C:$C,V$3,$D:$D,$R51)*100 -> 0 | W51: =SUMIFS($L:$L,$C:$C,W$3,$D:$D,$R51)*100 -> 0 | X51: =SUMIFS($L:$L,$C:$C,X$3,$D:$D,$R51)*100 -> 0 | Y51: =SUMIFS($L:$L,$C:$C,Y$3,$D:$D,$R51)*100 -> 0 | Z51: =SUMIFS($L:$L,$C:$C,Z$3,$D:$D,$R51)*100 -> 0 | AA51: =SUMIFS($L:$L,$C:$C,AA$3,$D:$D,$R51)*100 -> 0 | AB51: =SUMPRODUCT($T$4:$AA$4,T51:AA51) -> 0 | AC51: =SUMIFS($L:$L,$C:$C,AC$3,$D:$D,$R51)*100 -> 0 | AD51: =SUMIFS($L:$L,$C:$C,AD$3,$D:$D,$R51)*100 -> 16 | AE51: =SUMIFS($L:$L,$C:$C,AE$3,$D:$D,$R51)*100 -> 15 | AF51: =SUMPRODUCT($AC$4:$AE$4,AC51:AE51) -> 9.9157914 | AH51: =AB51/100*$AL$6 -> 0 | AI51: =AF51/100*$AL$23 -> 34063.892
B52: 6 | C52: A02 | D52: M045 | E52: CACAO ALCALINO | G52: X | L52: 0.06 | M52: =$E$44*L52 -> 0.20454545 | N52: Kg. | R52: M137 | S52: SORBATO DE POTASIO | T52: =SUMIFS($L:$L,$C:$C,T$3,$D:$D,$R52)*100 -> 0 | U52: =SUMIFS($L:$L,$C:$C,U$3,$D:$D,$R52)*100 -> 0 | V52: =SUMIFS($L:$L,$C:$C,V$3,$D:$D,$R52)*100 -> 0 | W52: =SUMIFS($L:$L,$C:$C,W$3,$D:$D,$R52)*100 -> 0 | X52: =SUMIFS($L:$L,$C:$C,X$3,$D:$D,$R52)*100 -> 0 | Y52: =SUMIFS($L:$L,$C:$C,Y$3,$D:$D,$R52)*100 -> 0 | Z52: =SUMIFS($L:$L,$C:$C,Z$3,$D:$D,$R52)*100 -> 0 | AA52: =SUMIFS($L:$L,$C:$C,AA$3,$D:$D,$R52)*100 -> 0 | AB52: =SUMPRODUCT($T$4:$AA$4,T52:AA52) -> 0 | AC52: =SUMIFS($L:$L,$C:$C,AC$3,$D:$D,$R52)*100 -> 0 | AD52: =SUMIFS($L:$L,$C:$C,AD$3,$D:$D,$R52)*100 -> 0.3 | AE52: =SUMIFS($L:$L,$C:$C,AE$3,$D:$D,$R52)*100 -> 0.2 | AF52: =SUMPRODUCT($AC$4:$AE$4,AC52:AE52) -> 0.17052636 | AH52: =AB52/100*$AL$6 -> 0 | AI52: =AF52/100*$AL$23 -> 585.81219
B53: 7 | C53: A02 | D53: M105 | E53: ACEITE DE COCO | G53: X | L53: 0.05 | M53: =$E$44*L53 -> 0.17045455 | N53: Kg. | R53: M164 | S53: EDULZUGAR | T53: =SUMIFS($L:$L,$C:$C,T$3,$D:$D,$R53)*100 -> 0 | U53: =SUMIFS($L:$L,$C:$C,U$3,$D:$D,$R53)*100 -> 0 | V53: =SUMIFS($L:$L,$C:$C,V$3,$D:$D,$R53)*100 -> 0 | W53: =SUMIFS($L:$L,$C:$C,W$3,$D:$D,$R53)*100 -> 0 | X53: =SUMIFS($L:$L,$C:$C,X$3,$D:$D,$R53)*100 -> 0 | Y53: =SUMIFS($L:$L,$C:$C,Y$3,$D:$D,$R53)*100 -> 0 | Z53: =SUMIFS($L:$L,$C:$C,Z$3,$D:$D,$R53)*100 -> 0 | AA53: =SUMIFS($L:$L,$C:$C,AA$3,$D:$D,$R53)*100 -> 3 | AB53: =SUMPRODUCT($T$4:$AA$4,T53:AA53) -> 0.44366135 | AC53: =SUMIFS($L:$L,$C:$C,AC$3,$D:$D,$R53)*100 -> 0 | AD53: =SUMIFS($L:$L,$C:$C,AD$3,$D:$D,$R53)*100 -> 0 | AE53: =SUMIFS($L:$L,$C:$C,AE$3,$D:$D,$R53)*100 -> 0 | AF53: =SUMPRODUCT($AC$4:$AE$4,AC53:AE53) -> 0 | AH53: =AB53/100*$AL$6 -> 1893.1946 | AI53: =AF53/100*$AL$23 -> 0
B54: 8 | C54: A02 | D54: M106 | E54: FIBRA DE BAMBÚ | G54: X | L54: 0.04 | M54: =$E$44*L54 -> 0.13636364 | N54: Kg. | T54: =SUM(T5:T53) -> 100 | U54: =SUM(U5:U53) -> 100 | V54: =SUM(V5:V53) -> 100 | W54: =SUM(W5:W53) -> 100 | X54: =SUM(X5:X53) -> 100 | Y54: =SUM(Y5:Y53) -> 100 | Z54: =SUM(Z5:Z53) -> 100 | AA54: =SUM(AA5:AA53) -> 100 | ... AF54: =SUM(AF5:AF53) -> 100 | AH54: =SUM(AH5:AH53) -> 426720.66 | AI54: =SUM(AI5:AI53) -> 343531.76
B55: 9 | C55: A02 | D55: M107 | E55: PSYLLIUM | G55: X | L55: 0.03 | M55: =$E$44*L55 -> 0.10227273 | N55: Kg.
B56: 10 | C56: A02 | D56: M108 | E56: EDULCORANTE | G56: X | L56: 0.015 | M56: =$E$44*L56 -> 0.051136364 | N56: Kg.
B57: 11 | C57: A02 | D57: M022 | E57: GOMA XÁNTICA | G57: X | L57: 0.01 | M57: =$E$44*L57 -> 0.034090909 | N57: Kg.
B58: 12 | C58: A02 | D58: M056 | E58: BICARBONATO DE SODIO | G58: X | L58: 0.005 | M58: =$E$44*L58 -> 0.017045455 | N58: Kg.
B59: 13 | C59: A02 | D59: M006 | E59: SAL | G59: X | L59: 0.004 | M59: =$E$44*L59 -> 0.013636364 | N59: Kg.
B60: 14 | C60: A02 | D60: M047 | E60: ESENCIA DE CHOCOLATE | G60: X | L60: 0.003 | M60: =$E$44*L60 -> 0.010227273 | N60: Kg.
B61: 15 | C61: A02 | D61: M057 | E61: BICARBONATO DE CALCIO | G61: X | L61: 0.003 | M61: =$E$44*L61 -> 0.010227273 | N61: Kg.
D62: TOTAL MEZCLA | L62: =L48+L49+L50+L51+L52+L53+L54+L55+L56+L57+L58+L59+L60+L61 -> 1 | M62: =M48+M49+M50+M51+M52+M53+M54+M55+M56+M57+M58+M59+M60+M61 -> 3.4090909 | N62: Kg.
B63: EMBALAJE
B64: 16 | C64: A02 | D64: M101 | E64: FILM FLOW-PACK (ENVOLTORIO PRIMARIO) | G64: X | L64: — | M64: =$E$39*$E$40 -> 20 | N64: uni. | O64: 1 por unidad
B65: 17 | C65: A02 | D65: M102 | E65: CAJA DE CARTÓN CORRUGADO | G65: X | L65: — | M65: =$E$39 -> 1 | N65: uni. | O65: 1 por caja
B66: 18 | C66: A02 | D66: M103 | E66: CINTA DE CIERRE | G66: X | L66: — | M66: =$E$39 -> 1 | N66: uni. | O66: 1 por caja
D68: Galletitas símil chocolinas - A03 | M68: Foto
D69: PT anual (kg) | E69: =SUMIFS('Plan de ventas'!$O$48:$O$60,'Plan de ventas'!$B$48:$B$60,D78)*1000 -> 30642.707
B70: Cajas / lote | E70: 1 | F70: ="Línea: Clásicas | Versión n°: 1"&CHAR(10)&CHAR(10)&"Lote = "&E70&" cajas × "&E71&" unid./caja = "&(E70*E71)&" unidades"&CHAR(10)&"Producto terminado = "&TEXT(E74,"#,##0.00")&" kg"&CHAR(10)&"Mezcla a preparar = "&TEXT(E75,"#,##0.00")&" kg (rendimiento "&TEXT(E73,"0%")&")" -> Línea: Clásicas | Versión n°: 1 Lote = 1 cajas × 20 unid./caja = 20 unidades Producto terminado = 3,00 kg Mezcla a preparar = 3,41 kg (rendimiento 88%)
B71: Unid. / caja | E71: 20
B72: Peso neto (g) | E72: 150
B73: Rendim. (%) | E73: 0.88
B74: PT (kg) | E74: =E70*E71*E72/1000 -> 3
B75: Mezcla (kg) | E75: =E74/E73 -> 3.4090909
B76: ITEM | D76: CODIGO | E76: DENOMINACION | F76: NIVEL | L76: % | M76: CANTIDAD | N76: UNIDAD | O76: OBSERVACIONES
F77: 0 | G77: 1 | H77: 2 | I77: 3 | J77: 4 | K77: 5
B78: 1 | D78: A03 | E78: Galletitas símil chocolinas (caja) | F78: X | L78: — | M78: =$E$70 -> 1 | N78: cajas | O78: Lote = 1 caja
B79: 2 | C79: A03 | D79: M030 | E79: HARINA DE ARROZ | G79: X | L79: 0.27 | M79: =$E$75*L79 -> 0.92045455 | N79: Kg.
B80: 3 | C80: A03 | D80: M001 | E80: FÉCULA DE MAÍZ | G80: X | L80: 0.22 | M80: =$E$75*L80 -> 0.75 | N80: Kg.
B81: 4 | C81: A03 | D81: M052 | E81: AZÚCAR COMÚN | G81: X | L81: 0.18 | M81: =$E$75*L81 -> 0.61363636 | N81: Kg.
B82: 5 | C82: A03 | D82: M036 | E82: ACEITE VEGETAL INTERESTERIFICADO | G82: X | L82: 0.14 | M82: =$E$75*L82 -> 0.47727273 | N82: Kg.
B83: 6 | C83: A03 | D83: M045 | E83: CACAO ALCALINO | G83: X | L83: 0.06 | M83: =$E$75*L83 -> 0.20454545 | N83: Kg.
B84: 7 | C84: A03 | D84: M109 | E84: LECHE EN POLVO | G84: X | L84: 0.06 | M84: =$E$75*L84 -> 0.20454545 | N84: Kg.
B85: 8 | C85: A03 | D85: M041 | E85: HUEVO EN POLVO DESHIDRATADO | G85: X | L85: 0.04 | M85: =$E$75*L85 -> 0.13636364 | N85: Kg.
B86: 9 | C86: A03 | D86: M022 | E86: GOMA XÁNTICA | G86: X | L86: 0.01 | M86: =$E$75*L86 -> 0.034090909 | N86: Kg.
B87: 10 | C87: A03 | D87: M056 | E87: BICARBONATO DE SODIO | G87: X | L87: 0.008 | M87: =$E$75*L87 -> 0.027272727 | N87: Kg.
B88: 11 | C88: A03 | D88: M057 | E88: BICARBONATO DE CALCIO | G88: X | L88: 0.008 | M88: =$E$75*L88 -> 0.027272727 | N88: Kg.
B89: 12 | C89: A03 | D89: M047 | E89: ESENCIA DE CHOCOLATE | G89: X | L89: 0.004 | M89: =$E$75*L89 -> 0.013636364 | N89: Kg.
D90: TOTAL MEZCLA | L90: =L79+L80+L81+L82+L83+L84+L85+L86+L87+L88+L89 -> 1 | M90: =M79+M80+M81+M82+M83+M84+M85+M86+M87+M88+M89 -> 3.4090909 | N90: Kg.
B91: EMBALAJE
B92: 13 | C92: A03 | D92: M101 | E92: FILM FLOW-PACK (ENVOLTORIO PRIMARIO) | G92: X | L92: — | M92: =$E$70*$E$71 -> 20 | N92: uni. | O92: 1 por unidad
B93: 14 | C93: A03 | D93: M102 | E93: CAJA DE CARTÓN CORRUGADO | G93: X | L93: — | M93: =$E$70 -> 1 | N93: uni. | O93: 1 por caja
B94: 15 | C94: A03 | D94: M103 | E94: CINTA DE CIERRE | G94: X | L94: — | M94: =$E$70 -> 1 | N94: uni. | O94: 1 por caja
D96: Pepa rellena de batata - A04
D97: PT anual (kg) | E97: =SUMIFS('Plan de ventas'!$O$48:$O$60,'Plan de ventas'!$B$48:$B$60,D106)*1000 -> 94284.902
B98: Cajas | E98: 1 | F98: ="Línea: Clásicas | Versión n°: 1"&CHAR(10)&CHAR(10)&"Lote = "&E98&" cajas × "&E99&" unid./caja = "&(E98*E99)&" unidades"&CHAR(10)&"Producto terminado = "&TEXT(E102,"#,##0.00")&" kg"&CHAR(10)&"Mezcla a preparar = "&TEXT(E103,"#,##0.00")&" kg (rendimiento "&TEXT(E101,"0%")&")" -> Línea: Clásicas | Versión n°: 1 Lote = 1 cajas × 20 unid./caja = 20 unidades Producto terminado = 3,00 kg Mezcla a preparar = 3,53 kg (rendimiento 85%)
B99: Unid. / caja | E99: 20
B100: Peso neto (g) | E100: 150
B101: Rendim. (%) | E101: 0.85
B102: PT (kg) | E102: =E98*E99*E100/1000 -> 3
B103: Mezcla (kg) | E103: =E102/E101 -> 3.5294118
...

Sheet BOM y balanceo
D2: Chocolate con chips picante - A01 | M2: Foto | R2: Calculo de receta promedio ponderada - kg de MP cada 100kg | AB2: 100 kg | AF2: 100 kg | AH2: =AL6 -> 431449.24 | AI2: =AL23 -> 395371.07 | AK2: Linea A - Galletitas | AU2: Linea A - Galletitas
D3: PT anual (kg) | E3: =SUMIFS('Plan de ventas'!$O$48:$O$60,'Plan de ventas'!$B$48:$B$60,D12)*1000 -> 101019.36 | R3: CÓDIGO | S3: DENOMINACIÓN | T3: A01 | U3: A02 | V3: A03 | W3: A04 | X3: A05 | Y3: A06 | Z3: A07 | AA3: A08 | AB3: A00 | AC3: B01 | AD3: B02 | AE3: B03 | AF3: B00 | AH3: A00 | AI3: B00 | AK3: NECESIDAD ANUAL MP | AU3: MAQUINAS
B4: Cajas / lote | E4: 1 | F4: ="Línea: Gourmet | Versión n°: 1"&CHAR(10)&CHAR(10)&"Lote = "&E4&" cajas × "&E5&" unid./caja = "&(E4*E5)&" unidades"&CHAR(10)&"Producto terminado = "&TEXT(E8,"#,##0.00")&" kg"&CHAR(10)&"Mezcla a preparar = "&TEXT(E9,"#,##0.00")&" kg (rendimiento "&TEXT(E7,"0%")&")" -> Línea: Gourmet | Versión n°: 1 Lote = 1 cajas × 20 unid./caja = 20 unidades Producto terminado = 3,00 kg Mezcla a preparar = 3,41 kg (rendimiento 88%) | S4: Volumen relativo (año 10) | T4: =SUMIFS('Plan de ventas'!$P$48:$P$60,'Plan de ventas'!$B$48:$B$60,T3) -> 0.28168974 | U4: =SUMIFS('Plan de ventas'!$P$48:$P$60,'Plan de ventas'!$B$48:$B$60,U3) -> 0.036619667 | V4: =SUMIFS('Plan de ventas'!$P$48:$P$60,'Plan de ventas'!$B$48:$B$60,V3) -> 0.085446359 | W4: =SUMIFS('Plan de ventas'!$P$48:$P$60,'Plan de ventas'!$B$48:$B$60,W3) -> 0.2629109 | X4: =SUMIFS('Plan de ventas'!$P$48:$P$60,'Plan de ventas'!$B$48:$B$60,X3) -> 0.036619667 | Y4: =SUMIFS('Plan de ventas'!$P$48:$P$60,'Plan de ventas'!$B$48:$B$60,Y3) -> 0.085446359 | Z4: =SUMIFS('Plan de ventas'!$P$48:$P$60,'Plan de ventas'!$B$48:$B$60,Z3) -> 0.063380192 | AA4: =SUMIFS('Plan de ventas'!$P$48:$P$60,'Plan de ventas'!$B$48:$B$60,AA3) -> 0.14788712 | AB4: =SUM(T4:AA4) -> 1 | AC4: =SUMIFS('Plan de ventas'!$P$48:$P$60,'Plan de ventas'!$B$48:$B$60,AC3) -> 0.36842094 | AD4: =SUMIFS('Plan de ventas'!$P$48:$P$60,'Plan de ventas'!$B$48:$B$60,AD3) -> 0.44210544 | AE4: =SUMIFS('Plan de ventas'!$P$48:$P$60,'Plan de ventas'!$B$48:$B$60,AE3) -> 0.18947362 | AF4: =SUM(AC4:AE4) -> 1 | AK4: Sección Operativa | AL4: Alimentación | AM4: Agregado | AN4: Desperdicios | AR4: Producción | AU4: Máquina | AV4: Modelo | AW4: Capacidad Teórica | AY4: Medidas | BA4: Peso | BC4: Consumo | BE4: Precio | BF4: Proveedor | BG4: Ubicación
B5: Unid. / caja | E5: 20 | R5: M001 | S5: FÉCULA DE MAÍZ | T5: =SUMIFS($L:$L,$C:$C,T$3,$D:$D,$R5)*100 -> 24.645 | U5: =SUMIFS($L:$L,$C:$C,U$3,$D:$D,$R5)*100 -> 22.32 | V5: =SUMIFS($L:$L,$C:$C,V$3,$D:$D,$R5)*100 -> 20.46 | W5: =SUMIFS($L:$L,$C:$C,W$3,$D:$D,$R5)*100 -> 21.6876 | X5: =SUMIFS($L:$L,$C:$C,X$3,$D:$D,$R5)*100 -> 0 | Y5: =SUMIFS($L:$L,$C:$C,Y$3,$D:$D,$R5)*100 -> 0 | Z5: =SUMIFS($L:$L,$C:$C,Z$3,$D:$D,$R5)*100 -> 22.32 | AA5: =SUMIFS($L:$L,$C:$C,AA$3,$D:$D,$R5)*100 -> 26.04 | AB5: =SUMPRODUCT($T$4:$AA$4,T5:AA5) -> 20.47536 | AC5: =SUMIFS($L:$L,$C:$C,AC$3,$D:$D,$R5)*100 -> 0 | AD5: =SUMIFS($L:$L,$C:$C,AD$3,$D:$D,$R5)*100 -> 10.68 | AE5: =SUMIFS($L:$L,$C:$C,AE$3,$D:$D,$R5)*100 -> 9.79 | AF5: =SUMPRODUCT($AC$4:$AE$4,AC5:AE5) -> 6.5766329 | AH5: =AB5/100*$AL$6 -> 88340.784 | AI5: =AF5/100*$AL$23 -> 26002.104 | AN5: Recuperable | AP5: No recuperable | AU5: Amasadora | AW5: 130 | AX5: kg | AY5: 120x140x180 | AZ5: cm | BB5: kg | BC5: - | BD5: kw/h | BE5: 13000000
B6: Peso neto (g) | E6: 150 | R6: M006 | S6: SAL | T6: =SUMIFS($L:$L,$C:$C,T$3,$D:$D,$R6)*100 -> 0.465 | U6: =SUMIFS($L:$L,$C:$C,U$3,$D:$D,$R6)*100 -> 0.372 | V6: =SUMIFS($L:$L,$C:$C,V$3,$D:$D,$R6)*100 -> 0 | W6: =SUMIFS($L:$L,$C:$C,W$3,$D:$D,$R6)*100 -> 0 | X6: =SUMIFS($L:$L,$C:$C,X$3,$D:$D,$R6)*100 -> 1.395 | Y6: =SUMIFS($L:$L,$C:$C,Y$3,$D:$D,$R6)*100 -> 1.395 | Z6: =SUMIFS($L:$L,$C:$C,Z$3,$D:$D,$R6)*100 -> 0 | AA6: =SUMIFS($L:$L,$C:$C,AA$3,$D:$D,$R6)*100 -> 0.465 | AB6: =SUMPRODUCT($T$4:$AA$4,T6:AA6) -> 0.38365786 | AC6: =SUMIFS($L:$L,$C:$C,AC$3,$D:$D,$R6)*100 -> 0.85 | AD6: =SUMIFS($L:$L,$C:$C,AD$3,$D:$D,$R6)*100 -> 0.445 | AE6: =SUMIFS($L:$L,$C:$C,AE$3,$D:$D,$R6)*100 -> 0.267 | AF6: =SUMPRODUCT($AC$4:$AE$4,AC6:AE6) -> 0.56048417 | AH6: =AB6/100*$AL$6 -> 1655.2889 | AI6: =AF6/100*$AL$23 -> 2215.9923 | AK6: Amasado | AL6: =+AR6/(1-AN6-AP6) -> 431449.24 | AM6: 0 | AR6: =+AL7 -> 431449.24 | AS6: kg/año | AT6: =+AL6-AO6-AQ6 -> 431449.24 | AU6: Moldeadora | AX6: kg/h | AZ6: cm | BB6: kg | BC6: - | BD6: kw/h
B7: Rendim. (%) | E7: 0.88 | R7: M008 | S7: BICARBONATO DE AMONIO | T7: =SUMIFS($L:$L,$C:$C,T$3,$D:$D,$R7)*100 -> 0.465 | U7: =SUMIFS($L:$L,$C:$C,U$3,$D:$D,$R7)*100 -> 0 | V7: =SUMIFS($L:$L,$C:$C,V$3,$D:$D,$R7)*100 -> 0 | W7: =SUMIFS($L:$L,$C:$C,W$3,$D:$D,$R7)*100 -> 0 | X7: =SUMIFS($L:$L,$C:$C,X$3,$D:$D,$R7)*100 -> 0 | Y7: =SUMIFS($L:$L,$C:$C,Y$3,$D:$D,$R7)*100 -> 0 | Z7: =SUMIFS($L:$L,$C:$C,Z$3,$D:$D,$R7)*100 -> 1.395 | AA7: =SUMIFS($L:$L,$C:$C,AA$3,$D:$D,$R7)*100 -> 0.93 | AB7: =SUMPRODUCT($T$4:$AA$4,T7:AA7) -> 0.35693612 | AC7: =SUMIFS($L:$L,$C:$C,AC$3,$D:$D,$R7)*100 -> 0 | AD7: =SUMIFS($L:$L,$C:$C,AD$3,$D:$D,$R7)*100 -> 0 | AE7: =SUMIFS($L:$L,$C:$C,AE$3,$D:$D,$R7)*100 -> 0 | AF7: =SUMPRODUCT($AC$4:$AE$4,AC7:AE7) -> 0 | AH7: =AB7/100*$AL$6 -> 1539.9982 | AI7: =AF7/100*$AL$23 -> 0 | AK7: Moldeado | AL7: =+AR7/(1-AN7-AP7) -> 431449.24 | AM7: 0 | AN7: 0.01 | AO7: =+AN7*AL7 -> 4314.4924 | AP7: 0.01 | AQ7: =+AP7*AL7 -> 4314.4924 | AR7: =+AL8 -> 422820.25 | AS7: kg/año | AT7: =+AL7-AO7-AQ7 -> 422820.25 | AU7: Horno tunel | AX7: kg/h | AZ7: cm | BB7: kg | BC7: - | BD7: kw/h
B8: PT (kg) | E8: =E4*E5*E6/1000 -> 3 | R8: M022 | S8: GOMA XÁNTICA | T8: =SUMIFS($L:$L,$C:$C,T$3,$D:$D,$R8)*100 -> 0.744 | U8: =SUMIFS($L:$L,$C:$C,U$3,$D:$D,$R8)*100 -> 0.93 | V8: =SUMIFS($L:$L,$C:$C,V$3,$D:$D,$R8)*100 -> 0.93 | W8: =SUMIFS($L:$L,$C:$C,W$3,$D:$D,$R8)*100 -> 0.40176 | X8: =SUMIFS($L:$L,$C:$C,X$3,$D:$D,$R8)*100 -> 0.93 | Y8: =SUMIFS($L:$L,$C:$C,Y$3,$D:$D,$R8)*100 -> 0.93 | Z8: =SUMIFS($L:$L,$C:$C,Z$3,$D:$D,$R8)*100 -> 0.93 | AA8: =SUMIFS($L:$L,$C:$C,AA$3,$D:$D,$R8)*100 -> 0.93 | AB8: =SUMPRODUCT($T$4:$AA$4,T8:AA8) -> 0.73872566 | AC8: =SUMIFS($L:$L,$C:$C,AC$3,$D:$D,$R8)*100 -> 1.275 | AD8: =SUMIFS($L:$L,$C:$C,AD$3,$D:$D,$R8)*100 -> 0.89 | AE8: =SUMIFS($L:$L,$C:$C,AE$3,$D:$D,$R8)*100 -> 0.89 | AF8: =SUMPRODUCT($AC$4:$AE$4,AC8:AE8) -> 1.0318421 | AH8: =AB8/100*$AL$6 -> 3187.2262 | AI8: =AF8/100*$AL$23 -> 4079.605 | AK8: Horneado | AL8: =+AR8/(1-AN8-AP8) -> 422820.25 | AM8: 0 | AP8: 0.07 | AQ8: =+AP8*AL8 -> 29597.418 | AR8: =+AL9 -> 393222.84 | AS8: kg/año | AT8: =+AL8-AO8-AQ8 -> 393222.84 | AU8: Cinta de enfriamiento | AX8: kg/h | AZ8: cm | BB8: kg | BC8: - | BD8: kw/h
B9: Mezcla (kg) | E9: =E8/E7 -> 3.4090909 | R9: M028 | S9: PROPIONATO DE CALCIO | T9: =SUMIFS($L:$L,$C:$C,T$3,$D:$D,$R9)*100 -> 0 | U9: =SUMIFS($L:$L,$C:$C,U$3,$D:$D,$R9)*100 -> 0 | V9: =SUMIFS($L:$L,$C:$C,V$3,$D:$D,$R9)*100 -> 0 | W9: =SUMIFS($L:$L,$C:$C,W$3,$D:$D,$R9)*100 -> 0 | X9: =SUMIFS($L:$L,$C:$C,X$3,$D:$D,$R9)*100 -> 0 | Y9: =SUMIFS($L:$L,$C:$C,Y$3,$D:$D,$R9)*100 -> 0 | Z9: =SUMIFS($L:$L,$C:$C,Z$3,$D:$D,$R9)*100 -> 0.93 | AA9: =SUMIFS($L:$L,$C:$C,AA$3,$D:$D,$R9)*100 -> 0.93 | AB9: =SUMPRODUCT($T$4:$AA$4,T9:AA9) -> 0.1964786 | AC9: =SUMIFS($L:$L,$C:$C,AC$3,$D:$D,$R9)*100 -> 0 | AD9: =SUMIFS($L:$L,$C:$C,AD$3,$D:$D,$R9)*100 -> 0.89 | AE9: =SUMIFS($L:$L,$C:$C,AE$3,$D:$D,$R9)*100 -> 0.89 | AF9: =SUMPRODUCT($AC$4:$AE$4,AC9:AE9) -> 0.56210537 | AH9: =AB9/100*$AL$6 -> 847.70541 | AI9: =AF9/100*$AL$23 -> 2222.402 | AK9: Enfriado | AL9: =+AR9/(1-AN9-AP9) -> 393222.84 | AM9: 0 | AN9: 0.04 | AO9: =+AN9*AL9 -> 15728.913 | AP9: 0.01 | AQ9: =+AP9*AL9 -> 3932.2283 | AR9: =+AL10 -> 373561.69 | AS9: kg/año | AT9: =+AL9-AO9-AQ9 -> 373561.69 | AU9: Envasadora vertical | AX9: kg/h | AZ9: cm | BB9: kg | BC9: - | BD9: kw/h
B10: ITEM | C10: PT | D10: MP | E10: DENOMINACION | F10: NIVEL | L10: % | M10: CANTIDAD | N10: UNIDAD | O10: OBSERVACIONES | R10: M030 | S10: HARINA DE ARROZ | T10: =SUMIFS($L:$L,$C:$C,T$3,$D:$D,$R10)*100 -> 16.74 | U10: =SUMIFS($L:$L,$C:$C,U$3,$D:$D,$R10)*100 -> 25.11 | V10: =SUMIFS($L:$L,$C:$C,V$3,$D:$D,$R10)*100 -> 25.11 | W10: =SUMIFS($L:$L,$C:$C,W$3,$D:$D,$R10)*100 -> 12.7224 | X10: =SUMIFS($L:$L,$C:$C,X$3,$D:$D,$R10)*100 -> 23.25 | Y10: =SUMIFS($L:$L,$C:$C,Y$3,$D:$D,$R10)*100 -> 23.25 | Z10: =SUMIFS($L:$L,$C:$C,Z$3,$D:$D,$R10)*100 -> 20.46 | AA10: =SUMIFS($L:$L,$C:$C,AA$3,$D:$D,$R10)*100 -> 19.53 | AB10: =SUMPRODUCT($T$4:$AA$4,T10:AA10) -> 18.148451 | AC10: =SUMIFS($L:$L,$C:$C,AC$3,$D:$D,$R10)*100 -> 13.6 | AD10: =SUMIFS($L:$L,$C:$C,AD$3,$D:$D,$R10)*100 -> 12.46 | AE10: =SUMIFS($L:$L,$C:$C,AE$3,$D:$D,$R10)*100 -> 11.57 | AF10: =SUMPRODUCT($AC$4:$AE$4,AC10:AE10) -> 12.711368 | AH10: =AB10/100*$AL$6 -> 78301.353 | AI10: =AF10/100*$AL$23 -> 50257.073 | AK10: Fraccionado | AL10: =+AR10/(1-AN10-AP10) -> 373561.69 | AM10: 0 | AR10: =+AL11 -> 373561.69 | AS10: kg/año | AT10: =+AL10-AO10-AQ10 -> 373561.69 | AU10: Envasadora | AX10: kg/h | AZ10: cm | BB10: kg | BC10: - | BD10: kw/h
F11: 0 | G11: 1 | H11: 2 | I11: 3 | J11: 4 | K11: 5 | R11: M031 | S11: JARABE DE GLUCOSA | T11: =SUMIFS($L:$L,$C:$C,T$3,$D:$D,$R11)*100 -> 5.58 | U11: =SUMIFS($L:$L,$C:$C,U$3,$D:$D,$R11)*100 -> 0 | V11: =SUMIFS($L:$L,$C:$C,V$3,$D:$D,$R11)*100 -> 0 | W11: =SUMIFS($L:$L,$C:$C,W$3,$D:$D,$R11)*100 -> 4.0176 | X11: =SUMIFS($L:$L,$C:$C,X$3,$D:$D,$R11)*100 -> 0 | Y11: =SUMIFS($L:$L,$C:$C,Y$3,$D:$D,$R11)*100 -> 0 | Z11: =SUMIFS($L:$L,$C:$C,Z$3,$D:$D,$R11)*100 -> 0 | AA11: =SUMIFS($L:$L,$C:$C,AA$3,$D:$D,$R11)*100 -> 5.58 | AB11: =SUMPRODUCT($T$4:$AA$4,T11:AA11) -> 3.4533097 | AC11: =SUMIFS($L:$L,$C:$C,AC$3,$D:$D,$R11)*100 -> 0 | AD11: =SUMIFS($L:$L,$C:$C,AD$3,$D:$D,$R11)*100 -> 0 | AE11: =SUMIFS($L:$L,$C:$C,AE$3,$D:$D,$R11)*100 -> 0 | AF11: =SUMPRODUCT($AC$4:$AE$4,AC11:AE11) -> 0 | AH11: =AB11/100*$AL$6 -> 14899.278 | AI11: =AF11/100*$AL$23 -> 0 | AK11: Envasado primario | AL11: =+AR11/(1-AN11-AP11) -> 373561.69 | AM11: 0 | AN11: 0.04 | AO11: =+AN11*AL11 -> 14942.468 | AR11: =+AR12 -> 358619.23 | AS11: kg/año | AT11: =+AL11-AO11-AQ11 -> 358619.23 | AX11: kg/h | AZ11: cm | BB11: kg | BC11: - | BD11: kw/h
B12: 1 | C12: A01 | D12: A01 | E12: Chocolate con chips picante (caja) | F12: X | L12: — | M12: =$E$4 -> 1 | N12: cajas | O12: Lote = 1 caja | R12: M036 | S12: ACEITE VEGETAL INTERESTERIFICADO | T12: =SUMIFS($L:$L,$C:$C,T$3,$D:$D,$R12)*100 -> 13.95 | U12: =SUMIFS($L:$L,$C:$C,U$3,$D:$D,$R12)*100 -> 13.02 | V12: =SUMIFS($L:$L,$C:$C,V$3,$D:$D,$R12)*100 -> 13.02 | W12: =SUMIFS($L:$L,$C:$C,W$3,$D:$D,$R12)*100 -> 10.3788 | X12: =SUMIFS($L:$L,$C:$C,X$3,$D:$D,$R12)*100 -> 5.58 | Y12: =SUMIFS($L:$L,$C:$C,Y$3,$D:$D,$R12)*100 -> 0 | Z12: =SUMIFS($L:$L,$C:$C,Z$3,$D:$D,$R12)*100 -> 12.09 | AA12: =SUMIFS($L:$L,$C:$C,AA$3,$D:$D,$R12)*100 -> 13.95 | AB12: =SUMPRODUCT($T$4:$AA$4,T12:AA12) -> 11.281201 | AC12: =SUMIFS($L:$L,$C:$C,AC$3,$D:$D,$R12)*100 -> 0 | AD12: =SUMIFS($L:$L,$C:$C,AD$3,$D:$D,$R12)*100 -> 0 | AE12: =SUMIFS($L:$L,$C:$C,AE$3,$D:$D,$R12)*100 -> 0 | AF12: =SUMPRODUCT($AC$4:$AE$4,AC12:AE12) -> 0 | AH12: =AB12/100*$AL$6 -> 48672.655 | AI12: =AF12/100*$AL$23 -> 0 | AK12: Envasado secundario | AL12: =+AR12/(1-AN12-AP12) -> 358619.23 | AM12: 0 | AR12: =+AL13 -> 358619.23 | AS12: kg/año | AT12: =+AL12-AO12-AQ12 -> 358619.23 | AX12: kg/h | AZ12: cm | BB12: kg | BC12: - | BD12: kw/h
B13: 2 | C13: A01 | D13: M001 | E13: FÉCULA DE MAÍZ | G13: X | L13: =+M13/$M$31 -> 0.24645 | M13: 0.90340909 | N13: Kg. | R13: M041 | S13: HUEVO EN POLVO DESHIDRATADO | T13: =SUMIFS($L:$L,$C:$C,T$3,$D:$D,$R13)*100 -> 1.86 | U13: =SUMIFS($L:$L,$C:$C,U$3,$D:$D,$R13)*100 -> 0 | V13: =SUMIFS($L:$L,$C:$C,V$3,$D:$D,$R13)*100 -> 3.72 | W13: =SUMIFS($L:$L,$C:$C,W$3,$D:$D,$R13)*100 -> 0 | X13: =SUMIFS($L:$L,$C:$C,X$3,$D:$D,$R13)*100 -> 0 | Y13: =SUMIFS($L:$L,$C:$C,Y$3,$D:$D,$R13)*100 -> 4.65 | Z13: =SUMIFS($L:$L,$C:$C,Z$3,$D:$D,$R13)*100 -> 0 | AA13: =SUMIFS($L:$L,$C:$C,AA$3,$D:$D,$R13)*100 -> 0 | AB13: =SUMPRODUCT($T$4:$AA$4,T13:AA13) -> 1.2391289 | AC13: =SUMIFS($L:$L,$C:$C,AC$3,$D:$D,$R13)*100 -> 0 | AD13: =SUMIFS($L:$L,$C:$C,AD$3,$D:$D,$R13)*100 -> 5.34 | AE13: =SUMIFS($L:$L,$C:$C,AE$3,$D:$D,$R13)*100 -> 5.34 | AF13: =SUMPRODUCT($AC$4:$AE$4,AC13:AE13) -> 3.3726322 | AH13: =AB13/100*$AL$6 -> 5346.2124 | AI13: =AF13/100*$AL$23 -> 13334.412 | AK13: Paletizado | AL13: =+AR13/(1-AN13-AP13) -> 358619.23 | AM13: 0 | AR13: =+AR14 -> 358619.23 | AS13: kg/año | AX13: kg/h | AZ13: cm | BB13: kg | BC13: - | BD13: kw/h
B14: 3 | C14: A01 | D14: M030 | E14: HARINA DE ARROZ | G14: X | L14: =+M14/$M$31 -> 0.1674 | M14: 0.61363636 | N14: Kg. | R14: M045 | S14: CACAO ALCALINO | T14: =SUMIFS($L:$L,$C:$C,T$3,$D:$D,$R14)*100 -> 3.72 | U14: =SUMIFS($L:$L,$C:$C,U$3,$D:$D,$R14)*100 -> 5.58 | V14: =SUMIFS($L:$L,$C:$C,V$3,$D:$D,$R14)*100 -> 5.58 | W14: =SUMIFS($L:$L,$C:$C,W$3,$D:$D,$R14)*100 -> 3.0132 | X14: =SUMIFS($L:$L,$C:$C,X$3,$D:$D,$R14)*100 -> 0 | Y14: =SUMIFS($L:$L,$C:$C,Y$3,$D:$D,$R14)*100 -> 0 | Z14: =SUMIFS($L:$L,$C:$C,Z$3,$D:$D,$R14)*100 -> 5.58 | AA14: =SUMIFS($L:$L,$C:$C,AA$3,$D:$D,$R14)*100 -> 0 | AB14: =SUMPRODUCT($T$4:$AA$4,T14:AA14) -> 2.8748789 | AC14: =SUMIFS($L:$L,$C:$C,AC$3,$D:$D,$R14)*100 -> 0 | AD14: =SUMIFS($L:$L,$C:$C,AD$3,$D:$D,$R14)*100 -> 0 | AE14: =SUMIFS($L:$L,$C:$C,AE$3,$D:$D,$R14)*100 -> 0 | AF14: =SUMPRODUCT($AC$4:$AE$4,AC14:AE14) -> 0 | AH14: =AB14/100*$AL$6 -> 12403.643 | AI14: =AF14/100*$AL$23 -> 0 | AK14: TOTALES | AL14: =+AR14+AO14+AQ14 -> 431449.24 | AM14: =AM6 -> 0 | AO14: =AO6+AO7+AO8+AO9+AO11 -> 34985.874 | AQ14: =AQ6+AQ7+AQ8+AQ9+AQ11 -> 37844.138 | AR14: =SUMIFS('Plan de ventas'!$O48:$O60,'Plan de ventas'!$B$48:$B$60,"*A*")*1000 -> 358619.23 | AS14: kg/año | AX14: kg/h | AZ14: cm | BB14: kg | BC14: - | BD14: kw/h
B15: 4 | C15: A01 | D15: M036 | E15: ACEITE VEGETAL INTERESTERIFICADO | G15: X | L15: =+M15/$M$31 -> 0.1395 | M15: 0.51136364 | N15: Kg. | R15: M046 | S15: CHIPS DE CHOCOLATE | T15: =SUMIFS($L:$L,$C:$C,T$3,$D:$D,$R15)*100 -> 8.37 | U15: =SUMIFS($L:$L,$C:$C,U$3,$D:$D,$R15)*100 -> 0 | V15: =SUMIFS($L:$L,$C:$C,V$3,$D:$D,$R15)*100 -> 0 | W15: =SUMIFS($L:$L,$C:$C,W$3,$D:$D,$R15)*100 -> 0 | X15: =SUMIFS($L:$L,$C:$C,X$3,$D:$D,$R15)*100 -> 0 | Y15: =SUMIFS($L:$L,$C:$C,Y$3,$D:$D,$R15)*100 -> 0 | Z15: =SUMIFS($L:$L,$C:$C,Z$3,$D:$D,$R15)*100 -> 0 | AA15: =SUMIFS($L:$L,$C:$C,AA$3,$D:$D,$R15)*100 -> 0 | AB15: =SUMPRODUCT($T$4:$AA$4,T15:AA15) -> 2.3577432 | AC15: =SUMIFS($L:$L,$C:$C,AC$3,$D:$D,$R15)*100 -> 0 | AD15: =SUMIFS($L:$L,$C:$C,AD$3,$D:$D,$R15)*100 -> 0 | AE15: =SUMIFS($L:$L,$C:$C,AE$3,$D:$D,$R15)*100 -> 8.01 | AF15: =SUMPRODUCT($AC$4:$AE$4,AC15:AE15) -> 1.5176837 | AH15: =AB15/100*$AL$6 -> 10172.465 | AI15: =AF15/100*$AL$23 -> 6000.4824
B16: 5 | C16: A01 | D16: M052 | E16: AZÚCAR COMÚN | G16: X | L16: =+M16/$M$31 -> 0.1302 | M16: 0.47727273 | N16: Kg. | R16: M047 | S16: ESENCIA DE CHOCOLATE | T16: =SUMIFS($L:$L,$C:$C,T$3,$D:$D,$R16)*100 -> 0.279 | U16: =SUMIFS($L:$L,$C:$C,U$3,$D:$D,$R16)*100 -> 0.279 | V16: =SUMIFS($L:$L,$C:$C,V$3,$D:$D,$R16)*100 -> 0.372 | W16: =SUMIFS($L:$L,$C:$C,W$3,$D:$D,$R16)*100 -> 0 | X16: =SUMIFS($L:$L,$C:$C,X$3,$D:$D,$R16)*100 -> 0 | Y16: =SUMIFS($L:$L,$C:$C,Y$3,$D:$D,$R16)*100 -> 0 | Z16: =SUMIFS($L:$L,$C:$C,Z$3,$D:$D,$R16)*100 -> 0.465 | AA16: =SUMIFS($L:$L,$C:$C,AA$3,$D:$D,$R16)*100 -> 0 | AB16: =SUMPRODUCT($T$4:$AA$4,T16:AA16) -> 0.15006616 | AC16: =SUMIFS($L:$L,$C:$C,AC$3,$D:$D,$R16)*100 -> 0 | AD16: =SUMIFS($L:$L,$C:$C,AD$3,$D:$D,$R16)*100 -> 0 | AE16: =SUMIFS($L:$L,$C:$C,AE$3,$D:$D,$R16)*100 -> 0 | AF16: =SUMPRODUCT($AC$4:$AE$4,AC16:AE16) -> 0 | AH16: =AB16/100*$AL$6 -> 647.4593 | AI16: =AF16/100*$AL$23 -> 0 | AK16: Desperdicio total | AL16: 0.18 | AQ16: Desvios | AR16: =AR13/AR14-1 -> 0
B17: 6 | C17: A01 | D17: M046 | E17: CHIPS DE CHOCOLATE | G17: X | L17: =+M17/$M$31 -> 0.0837 | M17: 0.30681818 | N17: Kg. | R17: M048 | S17: MIEL | T17: =SUMIFS($L:$L,$C:$C,T$3,$D:$D,$R17)*100 -> 1.86 | U17: =SUMIFS($L:$L,$C:$C,U$3,$D:$D,$R17)*100 -> 0 | V17: =SUMIFS($L:$L,$C:$C,V$3,$D:$D,$R17)*100 -> 0 | W17: =SUMIFS($L:$L,$C:$C,W$3,$D:$D,$R17)*100 -> 0 | X17: =SUMIFS($L:$L,$C:$C,X$3,$D:$D,$R17)*100 -> 0 | Y17: =SUMIFS($L:$L,$C:$C,Y$3,$D:$D,$R17)*100 -> 0 | Z17: =SUMIFS($L:$L,$C:$C,Z$3,$D:$D,$R17)*100 -> 0 | AA17: =SUMIFS($L:$L,$C:$C,AA$3,$D:$D,$R17)*100 -> 0 | AB17: =SUMPRODUCT($T$4:$AA$4,T17:AA17) -> 0.52394292 | AC17: =SUMIFS($L:$L,$C:$C,AC$3,$D:$D,$R17)*100 -> 0 | AD17: =SUMIFS($L:$L,$C:$C,AD$3,$D:$D,$R17)*100 -> 0 | AE17: =SUMIFS($L:$L,$C:$C,AE$3,$D:$D,$R17)*100 -> 0 | AF17: =SUMPRODUCT($AC$4:$AE$4,AC17:AE17) -> 0 | AH17: =AB17/100*$AL$6 -> 2260.5478 | AI17: =AF17/100*$AL$23 -> 0
B18: 7 | C18: A01 | D18: M031 | E18: JARABE DE GLUCOSA | G18: X | L18: =+M18/$M$31 -> 0.0558 | M18: 0.20454545 | N18: Kg. | R18: M049 | S18: JALAPEÑO DESHIDRATADO EN POLVO | T18: =SUMIFS($L:$L,$C:$C,T$3,$D:$D,$R18)*100 -> 0.186 | U18: =SUMIFS($L:$L,$C:$C,U$3,$D:$D,$R18)*100 -> 0 | V18: =SUMIFS($L:$L,$C:$C,V$3,$D:$D,$R18)*100 -> 0 | W18: =SUMIFS($L:$L,$C:$C,W$3,$D:$D,$R18)*100 -> 0 | X18: =SUMIFS($L:$L,$C:$C,X$3,$D:$D,$R18)*100 -> 0 | Y18: =SUMIFS($L:$L,$C:$C,Y$3,$D:$D,$R18)*100 -> 0 | Z18: =SUMIFS($L:$L,$C:$C,Z$3,$D:$D,$R18)*100 -> 0 | AA18: =SUMIFS($L:$L,$C:$C,AA$3,$D:$D,$R18)*100 -> 0 | AB18: =SUMPRODUCT($T$4:$AA$4,T18:AA18) -> 0.052394292 | AC18: =SUMIFS($L:$L,$C:$C,AC$3,$D:$D,$R18)*100 -> 0 | AD18: =SUMIFS($L:$L,$C:$C,AD$3,$D:$D,$R18)*100 -> 0 | AE18: =SUMIFS($L:$L,$C:$C,AE$3,$D:$D,$R18)*100 -> 0 | AF18: =SUMPRODUCT($AC$4:$AE$4,AC18:AE18) -> 0 | AH18: =AB18/100*$AL$6 -> 226.05478 | AI18: =AF18/100*$AL$23 -> 0 | AL18: 0.09
B19: 8 | C19: A01 | D19: M045 | E19: CACAO EN POLVO ALCALINO | G19: X | L19: =+M19/$M$31 -> 0.0372 | M19: 0.13636364 | N19: Kg. | R19: M052 | S19: AZÚCAR | T19: =SUMIFS($L:$L,$C:$C,T$3,$D:$D,$R19)*100 -> 13.02 | U19: =SUMIFS($L:$L,$C:$C,U$3,$D:$D,$R19)*100 -> 0 | V19: =SUMIFS($L:$L,$C:$C,V$3,$D:$D,$R19)*100 -> 16.74 | W19: =SUMIFS($L:$L,$C:$C,W$3,$D:$D,$R19)*100 -> 14.322 | X19: =SUMIFS($L:$L,$C:$C,X$3,$D:$D,$R19)*100 -> 0 | Y19: =SUMIFS($L:$L,$C:$C,Y$3,$D:$D,$R19)*100 -> 0 | Z19: =SUMIFS($L:$L,$C:$C,Z$3,$D:$D,$R19)*100 -> 0 | AA19: =SUMIFS($L:$L,$C:$C,AA$3,$D:$D,$R19)*100 -> 14.88 | AB19: =SUMPRODUCT($T$4:$AA$4,T19:AA19) -> 11.063943 | AC19: =SUMIFS($L:$L,$C:$C,AC$3,$D:$D,$R19)*100 -> 3.4 | AD19: =SUMIFS($L:$L,$C:$C,AD$3,$D:$D,$R19)*100 -> 19.58 | AE19: =SUMIFS($L:$L,$C:$C,AE$3,$D:$D,$R19)*100 -> 17.8 | AF19: =SUMPRODUCT($AC$4:$AE$4,AC19:AE19) -> 13.281686 | AH19: =AB19/100*$AL$6 -> 47735.296 | AI19: =AF19/100*$AL$23 -> 52511.945 | AK19: Linea B - Panificados | AU19: Linea B - Panificados
B20: 9 | C20: A01 | D20: M041 | E20: HUEVO EN POLVO DESHIDRATADO | G20: X | L20: =+M20/$M$31 -> 0.0186 | M20: 0.068181818 | N20: Kg. | R20: M056 | S20: BICARBONATO DE SODIO | T20: =SUMIFS($L:$L,$C:$C,T$3,$D:$D,$R20)*100 -> 0.465 | U20: =SUMIFS($L:$L,$C:$C,U$3,$D:$D,$R20)*100 -> 0.465 | V20: =SUMIFS($L:$L,$C:$C,V$3,$D:$D,$R20)*100 -> 0.744 | W20: =SUMIFS($L:$L,$C:$C,W$3,$D:$D,$R20)*100 -> 0 | X20: =SUMIFS($L:$L,$C:$C,X$3,$D:$D,$R20)*100 -> 0.465 | Y20: =SUMIFS($L:$L,$C:$C,Y$3,$D:$D,$R20)*100 -> 0.465 | Z20: =SUMIFS($L:$L,$C:$C,Z$3,$D:$D,$R20)*100 -> 0 | AA20: =SUMIFS($L:$L,$C:$C,AA$3,$D:$D,$R20)*100 -> 0.93 | AB20: =SUMPRODUCT($T$4:$AA$4,T20:AA20) -> 0.40588169 | AC20: =SUMIFS($L:$L,$C:$C,AC$3,$D:$D,$R20)*100 -> 0 | AD20: =SUMIFS($L:$L,$C:$C,AD$3,$D:$D,$R20)*100 -> 0 | AE20: =SUMIFS($L:$L,$C:$C,AE$3,$D:$D,$R20)*100 -> 0 | AF20: =SUMPRODUCT($AC$4:$AE$4,AC20:AE20) -> 0 | AH20: =AB20/100*$AL$6 -> 1751.1734 | AI20: =AF20/100*$AL$23 -> 0 | AK20: NECESIDAD ANUAL MP | AU20: MAQUINAS
B21: 10 | C21: A01 | D21: M048 | E21: MIEL | G21: X | L21: =+M21/$M$31 -> 0.0186 | M21: 0.068181818 | N21: Kg. | R21: M057 | S21: BICARBONATO DE CALCIO | T21: =SUMIFS($L:$L,$C:$C,T$3,$D:$D,$R21)*100 -> 0.279 | U21: =SUMIFS($L:$L,$C:$C,U$3,$D:$D,$R21)*100 -> 0.279 | V21: =SUMIFS($L:$L,$C:$C,V$3,$D:$D,$R21)*100 -> 0.744 | W21: =SUMIFS($L:$L,$C:$C,W$3,$D:$D,$R21)*100 -> 0 | X21: =SUMIFS($L:$L,$C:$C,X$3,$D:$D,$R21)*100 -> 0 | Y21: =SUMIFS($L:$L,$C:$C,Y$3,$D:$D,$R21)*100 -> 0 | Z21: =SUMIFS($L:$L,$C:$C,Z$3,$D:$D,$R21)*100 -> 0 | AA21: =SUMIFS($L:$L,$C:$C,AA$3,$D:$D,$R21)*100 -> 0 | AB21: =SUMPRODUCT($T$4:$AA$4,T21:AA21) -> 0.15238042 | AC21: =SUMIFS($L:$L,$C:$C,AC$3,$D:$D,$R21)*100 -> 0 | AD21: =SUMIFS($L:$L,$C:$C,AD$3,$D:$D,$R21)*100 -> 0 | AE21: =SUMIFS($L:$L,$C:$C,AE$3,$D:$D,$R21)*100 -> 0 | AF21: =SUMPRODUCT($AC$4:$AE$4,AC21:AE21) -> 0 | AH21: =AB21/100*$AL$6 -> 657.44414 | AI21: =AF21/100*$AL$23 -> 0 | AK21: Sección Operativa | AL21: Alimentación | AM21: Agregado | AN21: Desperdicios | AR21: Producción | AU21: Máquina | AV21: Modelo | AW21: Capacidad Teórica | AY21: Medidas | BA21: Peso | BC21: Consumo | BE21: Precio | BF21: Proveedor | BG21: Ubicación
B22: 11 | C22: A01 | D22: M022 | E22: GOMA XÁNTICA | G22: X | L22: =+M22/$M$31 -> 0.00744 | M22: 0.027272727 | N22: Kg. | R22: M089 | S22: ESENCIA DE VAINILLA | T22: =SUMIFS($L:$L,$C:$C,T$3,$D:$D,$R22)*100 -> 0.372 | U22: =SUMIFS($L:$L,$C:$C,U$3,$D:$D,$R22)*100 -> 0 | V22: =SUMIFS($L:$L,$C:$C,V$3,$D:$D,$R22)*100 -> 0 | W22: =SUMIFS($L:$L,$C:$C,W$3,$D:$D,$R22)*100 -> 0.1302 | X22: =SUMIFS($L:$L,$C:$C,X$3,$D:$D,$R22)*100 -> 0 | Y22: =SUMIFS($L:$L,$C:$C,Y$3,$D:$D,$R22)*100 -> 0 | Z22: =SUMIFS($L:$L,$C:$C,Z$3,$D:$D,$R22)*100 -> 0 | AA22: =SUMIFS($L:$L,$C:$C,AA$3,$D:$D,$R22)*100 -> 0 | AB22: =SUMPRODUCT($T$4:$AA$4,T22:AA22) -> 0.13901958 | AC22: =SUMIFS($L:$L,$C:$C,AC$3,$D:$D,$R22)*100 -> 0 | AD22: =SUMIFS($L:$L,$C:$C,AD$3,$D:$D,$R22)*100 -> 0 | AE22: =SUMIFS($L:$L,$C:$C,AE$3,$D:$D,$R22)*100 -> 0.445 | AF22: =SUMPRODUCT($AC$4:$AE$4,AC22:AE22) -> 0.084315763 | AH22: =AB22/100*$AL$6 -> 599.79893 | AI22: =AF22/100*$AL$23 -> 333.36014 | AN22: Recuperable | AP22: No recuperable | AU22: Batidora | AX22: kg/h | AZ22: cm | BB22: kg | BC22: - | BD22: kw/h
B23: 12 | C23: A01 | D23: M006 | E23: SAL | G23: X | L23: =+M23/$M$31 -> 0.00465 | M23: 0.017045455 | N23: Kg. | R23: M104 | S23: PASTA DE PASAS DE UVA | T23: =SUMIFS($L:$L,$C:$C,T$3,$D:$D,$R23)*100 -> 0 | U23: =SUMIFS($L:$L,$C:$C,U$3,$D:$D,$R23)*100 -> 12.09 | V23: =SUMIFS($L:$L,$C:$C,V$3,$D:$D,$R23)*100 -> 0 | W23: =SUMIFS($L:$L,$C:$C,W$3,$D:$D,$R23)*100 -> 0 | X23: =SUMIFS($L:$L,$C:$C,X$3,$D:$D,$R23)*100 -> 0 | Y23: =SUMIFS($L:$L,$C:$C,Y$3,$D:$D,$R23)*100 -> 0 | Z23: =SUMIFS($L:$L,$C:$C,Z$3,$D:$D,$R23)*100 -> 14.88 | AA23: =SUMIFS($L:$L,$C:$C,AA$3,$D:$D,$R23)*100 -> 0 | AB23: =SUMPRODUCT($T$4:$AA$4,T23:AA23) -> 1.385829 | AC23: =SUMIFS($L:$L,$C:$C,AC$3,$D:$D,$R23)*100 -> 0 | AD23: =SUMIFS($L:$L,$C:$C,AD$3,$D:$D,$R23)*100 -> 0 | AE23: =SUMIFS($L:$L,$C:$C,AE$3,$D:$D,$R23)*100 -> 0 | AF23: =SUMPRODUCT($AC$4:$AE$4,AC23:AE23) -> 0 | AH23: =AB23/100*$AL$6 -> 5979.1488 | AI23: =AF23/100*$AL$23 -> 0 | AK23: Batido | AL23: =+AR23/(1-AN23-AP23) -> 395371.07 | AM23: 0 | AO23: =AL23*AN23 -> 0 | AQ23: =AL23*AP23 -> 0 | AR23: =+AL24 -> 395371.07 | AS23: kg/año | AU23: Dosificadora | AX23: kg/h | AZ23: cm | BB23: kg | BC23: - | BD23: kw/h
B24: 13 | C24: A01 | D24: M008 | E24: BICARBONATO DE AMONIO | G24: X | L24: =+M24/$M$31 -> 0.00465 | M24: 0.017045455 | N24: Kg. | R24: M105 | S24: ACEITE DE COCO | T24: =SUMIFS($L:$L,$C:$C,T$3,$D:$D,$R24)*100 -> 0 | U24: =SUMIFS($L:$L,$C:$C,U$3,$D:$D,$R24)*100 -> 4.65 | V24: =SUMIFS($L:$L,$C:$C,V$3,$D:$D,$R24)*100 -> 0 | W24: =SUMIFS($L:$L,$C:$C,W$3,$D:$D,$R24)*100 -> 0 | X24: =SUMIFS($L:$L,$C:$C,X$3,$D:$D,$R24)*100 -> 0 | Y24: =SUMIFS($L:$L,$C:$C,Y$3,$D:$D,$R24)*100 -> 0 | Z24: =SUMIFS($L:$L,$C:$C,Z$3,$D:$D,$R24)*100 -> 0 | AA24: =SUMIFS($L:$L,$C:$C,AA$3,$D:$D,$R24)*100 -> 0 | AB24: =SUMPRODUCT($T$4:$AA$4,T24:AA24) -> 0.17028145 | AC24: =SUMIFS($L:$L,$C:$C,AC$3,$D:$D,$R24)*100 -> 0 | AD24: =SUMIFS($L:$L,$C:$C,AD$3,$D:$D,$R24)*100 -> 0 | AE24: =SUMIFS($L:$L,$C:$C,AE$3,$D:$D,$R24)*100 -> 0 | AF24: =SUMPRODUCT($AC$4:$AE$4,AC24:AE24) -> 0 | AH24: =AB24/100*$AL$6 -> 734.67802 | AI24: =AF24/100*$AL$23 -> 0 | AK24: Dosificado | AL24: =+AR24/(1-AN24-AP24) -> 395371.07 | AM24: 0 | AO24: =AL24*AN24 -> 0 | AQ24: =AL24*AP24 -> 0 | AR24: =+AL25 -> 395371.07 | AS24: kg/año | AU24: Fermentadora | AX24: kg/h | AZ24: cm | BB24: kg | BC24: - | BD24: kw/h
B25: 14 | C25: A01 | D25: M056 | E25: BICARBONATO DE SODIO | G25: X | L25: =+M25/$M$31 -> 0.00465 | M25: 0.017045455 | N25: Kg. | R25: M106 | S25: FIBRA DE BAMBÚ | T25: =SUMIFS($L:$L,$C:$C,T$3,$D:$D,$R25)*100 -> 0 | U25: =SUMIFS($L:$L,$C:$C,U$3,$D:$D,$R25)*100 -> 3.72 | V25: =SUMIFS($L:$L,$C:$C,V$3,$D:$D,$R25)*100 -> 0 | W25: =SUMIFS($L:$L,$C:$C,W$3,$D:$D,$R25)*100 -> 0 | X25: =SUMIFS($L:$L,$C:$C,X$3,$D:$D,$R25)*100 -> 0 | Y25: =SUMIFS($L:$L,$C:$C,Y$3,$D:$D,$R25)*100 -> 0 | Z25: =SUMIFS($L:$L,$C:$C,Z$3,$D:$D,$R25)*100 -> 5.58 | AA25: =SUMIFS($L:$L,$C:$C,AA$3,$D:$D,$R25)*100 -> 0 | AB25: =SUMPRODUCT($T$4:$AA$4,T25:AA25) -> 0.48988663 | AC25: =SUMIFS($L:$L,$C:$C,AC$3,$D:$D,$R25)*100 -> 0 | AD25: =SUMIFS($L:$L,$C:$C,AD$3,$D:$D,$R25)*100 -> 0 | AE25: =SUMIFS($L:$L,$C:$C,AE$3,$D:$D,$R25)*100 -> 0 | AF25: =SUMPRODUCT($AC$4:$AE$4,AC25:AE25) -> 0 | AH25: =AB25/100*$AL$6 -> 2113.6121 | AI25: =AF25/100*$AL$23 -> 0 | AK25: Fermentado | AL25: =+AR25/(1-AN25-AP25) -> 395371.07 | AM25: 0 | AO25: =AL25*AN25 -> 0 | AQ25: =AL25*AP25 -> 0 | AR25: =+AL26 -> 395371.07 | AS25: kg/año | AU25: Horno rotativo | AX25: kg/h | AZ25: cm | BB25: kg | BC25: - | BD25: kw/h
B26: 15 | C26: A01 | D26: M089 | E26: ESENCIA DE VAINILLA | G26: X | L26: =+M26/$M$31 -> 0.00372 | M26: 0.013636364 | N26: Kg. | R26: M107 | S26: PSYLLIUM | T26: =SUMIFS($L:$L,$C:$C,T$3,$D:$D,$R26)*100 -> 0 | U26: =SUMIFS($L:$L,$C:$C,U$3,$D:$D,$R26)*100 -> 2.79 | V26: =SUMIFS($L:$L,$C:$C,V$3,$D:$D,$R26)*100 -> 0 | W26: =SUMIFS($L:$L,$C:$C,W$3,$D:$D,$R26)*100 -> 0 | X26: =SUMIFS($L:$L,$C:$C,X$3,$D:$D,$R26)*100 -> 0 | Y26: =SUMIFS($L:$L,$C:$C,Y$3,$D:$D,$R26)*100 -> 0 | Z26: =SUMIFS($L:$L,$C:$C,Z$3,$D:$D,$R26)*100 -> 0 | AA26: =SUMIFS($L:$L,$C:$C,AA$3,$D:$D,$R26)*100 -> 0 | AB26: =SUMPRODUCT($T$4:$AA$4,T26:AA26) -> 0.10216887 | AC26: =SUMIFS($L:$L,$C:$C,AC$3,$D:$D,$R26)*100 -> 2.55 | AD26: =SUMIFS($L:$L,$C:$C,AD$3,$D:$D,$R26)*100 -> 0 | AE26: =SUMIFS($L:$L,$C:$C,AE$3,$D:$D,$R26)*100 -> 0 | AF26: =SUMPRODUCT($AC$4:$AE$4,AC26:AE26) -> 0.93947339 | AH26: =AB26/100*$AL$6 -> 440.80681 | AI26: =AF26/100*$AL$23 -> 3714.406 | AK26: Horneado | AL26: =+AR26/(1-AN26-AP26) -> 395371.07 | AM26: 0 | AO26: =AL26*AN26 -> 0 | AP26: 0.13 | AQ26: =AL26*AP26 -> 51398.239 | AR26: =+AL27 -> 343972.83 | AS26: kg/año | AU26: Cinta de enfriamiento | AX26: kg/h | AZ26: cm | BB26: kg | BC26: - | BD26: kw/h
B27: 16 | C27: A01 | D27: M047 | E27: ESENCIA DE CHOCOLATE | G27: X | L27: =+M27/$M$31 -> 0.00279 | M27: 0.010227273 | N27: Kg. | R27: M108 | S27: EDULCORANTE | T27: =SUMIFS($L:$L,$C:$C,T$3,$D:$D,$R27)*100 -> 0 | U27: =SUMIFS($L:$L,$C:$C,U$3,$D:$D,$R27)*100 -> 1.395 | V27: =SUMIFS($L:$L,$C:$C,V$3,$D:$D,$R27)*100 -> 0 | W27: =SUMIFS($L:$L,$C:$C,W$3,$D:$D,$R27)*100 -> 0 | X27: =SUMIFS($L:$L,$C:$C,X$3,$D:$D,$R27)*100 -> 0 | Y27: =SUMIFS($L:$L,$C:$C,Y$3,$D:$D,$R27)*100 -> 0 | Z27: =SUMIFS($L:$L,$C:$C,Z$3,$D:$D,$R27)*100 -> 2.79 | AA27: =SUMIFS($L:$L,$C:$C,AA$3,$D:$D,$R27)*100 -> 0 | AB27: =SUMPRODUCT($T$4:$AA$4,T27:AA27) -> 0.22791517 | AC27: =SUMIFS($L:$L,$C:$C,AC$3,$D:$D,$R27)*100 -> 0 | AD27: =SUMIFS($L:$L,$C:$C,AD$3,$D:$D,$R27)*100 -> 0 | AE27: =SUMIFS($L:$L,$C:$C,AE$3,$D:$D,$R27)*100 -> 0 | AF27: =SUMPRODUCT($AC$4:$AE$4,AC27:AE27) -> 0 | AH27: =AB27/100*$AL$6 -> 983.33827 | AI27: =AF27/100*$AL$23 -> 0 | AK27: Desmolde | AL27: =+AR27/(1-AN27-AP27) -> 343972.83 | AM27: 0 | AO27: =AL27*AN27 -> 0 | AQ27: =AL27*AP27 -> 0 | AR27: =+AL28 -> 343972.83 | AS27: kg/año | AU27: Envasadora | AX27: kg/h | AZ27: cm | BB27: kg | BC27: - | BD27: kw/h
B28: 17 | C28: A01 | D28: M057 | E28: BICARBONATO DE CALCIO | G28: X | L28: =+M28/$M$31 -> 0.00279 | M28: 0.010227273 | N28: Kg. | R28: M109 | S28: LECHE EN POLVO | T28: =SUMIFS($L:$L,$C:$C,T$3,$D:$D,$R28)*100 -> 0 | U28: =SUMIFS($L:$L,$C:$C,U$3,$D:$D,$R28)*100 -> 0 | V28: =SUMIFS($L:$L,$C:$C,V$3,$D:$D,$R28)*100 -> 5.58 | W28: =SUMIFS($L:$L,$C:$C,W$3,$D:$D,$R28)*100 -> 0 | X28: =SUMIFS($L:$L,$C:$C,X$3,$D:$D,$R28)*100 -> 0 | Y28: =SUMIFS($L:$L,$C:$C,Y$3,$D:$D,$R28)*100 -> 0 | Z28: =SUMIFS($L:$L,$C:$C,Z$3,$D:$D,$R28)*100 -> 0 | AA28: =SUMIFS($L:$L,$C:$C,AA$3,$D:$D,$R28)*100 -> 0 | AB28: =SUMPRODUCT($T$4:$AA$4,T28:AA28) -> 0.47679068 | AC28: =SUMIFS($L:$L,$C:$C,AC$3,$D:$D,$R28)*100 -> 3.4 | AD28: =SUMIFS($L:$L,$C:$C,AD$3,$D:$D,$R28)*100 -> 4.45 | AE28: =SUMIFS($L:$L,$C:$C,AE$3,$D:$D,$R28)*100 -> 3.56 | AF28: =SUMPRODUCT($AC$4:$AE$4,AC28:AE28) -> 3.8945265 | AH28: =AB28/100*$AL$6 -> 2057.1098 | AI28: =AF28/100*$AL$23 -> 15397.831 | AK28: Enfriado | AL28: =+AR28/(1-AN28-AP28) -> 343972.83 | AM28: 0 | AO28: =AL28*AN28 -> 0 | AP28: 0.07 | AQ28: =AL28*AP28 -> 24078.098 | AR28: =+AL29 -> 319894.73 | AS28: kg/año | AU28: Envasadora | AX28: kg/h | AZ28: cm | BB28: kg | BC28: - | BD28: kw/h
B29: 18 | C29: A01 | D29: M049 | E29: JALAPEÑO DESHIDRATADO EN POLVO | G29: X | L29: =+M29/$M$31 -> 0.00186 | M29: 0.0068181818 | N29: Kg. | P29: =3.41*1.07-3.41 -> 0.2387 | R29: M110 | S29: JARABE DE MAÍZ ALTA FRUCTOSA | T29: =SUMIFS($L:$L,$C:$C,T$3,$D:$D,$R29)*100 -> 0 | U29: =SUMIFS($L:$L,$C:$C,U$3,$D:$D,$R29)*100 -> 0 | V29: =SUMIFS($L:$L,$C:$C,V$3,$D:$D,$R29)*100 -> 0 | W29: =SUMIFS($L:$L,$C:$C,W$3,$D:$D,$R29)*100 -> 7.3656 | X29: =SUMIFS($L:$L,$C:$C,X$3,$D:$D,$R29)*100 -> 0 | Y29: =SUMIFS($L:$L,$C:$C,Y$3,$D:$D,$R29)*100 -> 0 | Z29: =SUMIFS($L:$L,$C:$C,Z$3,$D:$D,$R29)*100 -> 0 | AA29: =SUMIFS($L:$L,$C:$C,AA$3,$D:$D,$R29)*100 -> 0 | AB29: =SUMPRODUCT($T$4:$AA$4,T29:AA29) -> 1.9364965 | AC29: =SUMIFS($L:$L,$C:$C,AC$3,$D:$D,$R29)*100 -> 0 | AD29: =SUMIFS($L:$L,$C:$C,AD$3,$D:$D,$R29)*100 -> 0 | AE29: =SUMIFS($L:$L,$C:$C,AE$3,$D:$D,$R29)*100 -> 0 | AF29: =SUMPRODUCT($AC$4:$AE$4,AC29:AE29) -> 0 | AH29: =AB29/100*$AL$6 -> 8354.9994 | AI29: =AF29/100*$AL$23 -> 0 | AK29: Envasado primario | AL29: =+AR29/(1-AN29-AP29) -> 319894.73 | AM29: 0 | AO29: =AL29*AN29 -> 0 | AQ29: =AL29*AP29 -> 0 | AR29: =+AL30 -> 319894.73 | AS29: kg/año | AX29: kg/h | AZ29: cm | BB29: kg | BC29: - | BD29: kw/h
E30: AGUA | L30: =+M30/M31 -> 0.07 | M30: =+M31*0.07 -> 0.25659824 | R30: M111 | S30: LECITINA DE SOJA | T30: =SUMIFS($L:$L,$C:$C,T$3,$D:$D,$R30)*100 -> 0 | U30: =SUMIFS($L:$L,$C:$C,U$3,$D:$D,$R30)*100 -> 0 | V30: =SUMIFS($L:$L,$C:$C,V$3,$D:$D,$R30)*100 -> 0 | W30: =SUMIFS($L:$L,$C:$C,W$3,$D:$D,$R30)*100 -> 0.3348 | X30: =SUMIFS($L:$L,$C:$C,X$3,$D:$D,$R30)*100 -> 0 | Y30: =SUMIFS($L:$L,$C:$C,Y$3,$D:$D,$R30)*100 -> 0 | Z30: =SUMIFS($L:$L,$C:$C,Z$3,$D:$D,$R30)*100 -> 0 | AA30: =SUMIFS($L:$L,$C:$C,AA$3,$D:$D,$R30)*100 -> 0.93 | AB30: =SUMPRODUCT($T$4:$AA$4,T30:AA30) -> 0.22555759 | AC30: =SUMIFS($L:$L,$C:$C,AC$3,$D:$D,$R30)*100 -> 0 | AD30: =SUMIFS($L:$L,$C:$C,AD$3,$D:$D,$R30)*100 -> 0 | AE30: =SUMIFS($L:$L,$C:$C,AE$3,$D:$D,$R30)*100 -> 0 | AF30: =SUMPRODUCT($AC$4:$AE$4,AC30:AE30) -> 0 | AH30: =AB30/100*$AL$6 -> 973.16648 | AI30: =AF30/100*$AL$23 -> 0 | AK30: Envasado secundario | AL30: =+AR30/(1-AN30-AP30) -> 319894.73 | AM30: 0 | AO30: =AL30*AN30 -> 0 | AQ30: =AL30*AP30 -> 0 | AR30: =+AR31 -> 319894.73 | AS30: kg/año | AX30: kg/h | AZ30: cm | BB30: kg | BC30: - | BD30: kw/h
D31: TOTAL MEZCLA | L31: =+SUM(L13:L30) -> 1 | M31: =+SUM(M13:M29)/0.93 -> 3.6656891 | N31: Kg. | R31: M112 | S31: ESENCIA DE LECHE CONDENSADA | T31: =SUMIFS($L:$L,$C:$C,T$3,$D:$D,$R31)*100 -> 0 | U31: =SUMIFS($L:$L,$C:$C,U$3,$D:$D,$R31)*100 -> 0 | V31: =SUMIFS($L:$L,$C:$C,V$3,$D:$D,$R31)*100 -> 0 | W31: =SUMIFS($L:$L,$C:$C,W$3,$D:$D,$R31)*100 -> 0.26784 | X31: =SUMIFS($L:$L,$C:$C,X$3,$D:$D,$R31)*100 -> 0 | Y31: =SUMIFS($L:$L,$C:$C,Y$3,$D:$D,$R31)*100 -> 0 | Z31: =SUMIFS($L:$L,$C:$C,Z$3,$D:$D,$R31)*100 -> 0 | AA31: =SUMIFS($L:$L,$C:$C,AA$3,$D:$D,$R31)*100 -> 0 | AB31: =SUMPRODUCT($T$4:$AA$4,T31:AA31) -> 0.070418055 | AC31: =SUMIFS($L:$L,$C:$C,AC$3,$D:$D,$R31)*100 -> 0 | AD31: =SUMIFS($L:$L,$C:$C,AD$3,$D:$D,$R31)*100 -> 0 | AE31: =SUMIFS($L:$L,$C:$C,AE$3,$D:$D,$R31)*100 -> 0 | AF31: =SUMPRODUCT($AC$4:$AE$4,AC31:AE31) -> 0 | AH31: =AB31/100*$AL$6 -> 303.81816 | AI31: =AF31/100*$AL$23 -> 0 | AK31: TOTALES | AL31: =+AQ31+AR31 -> 395371.07 | AM31: =AM23 -> 0 | AO31: =AO23+AO24+AO25+AO26+AO28 -> 0 | AQ31: =AQ23+AQ24+AQ25+AQ26+AQ28 -> 75476.338 | AR31: =SUMIFS('Plan de ventas'!$O48:$O60,'Plan de ventas'!$B$48:$B$60,"*B*")*1000 -> 319894.73 | AS31: kg/año | AX31: kg/h | AZ31: cm | BB31: kg | BC31: - | BD31: kw/h
B32: EMBALAJE | R32: M113 | S32: MERMELADA DE BATATA | T32: =SUMIFS($L:$L,$C:$C,T$3,$D:$D,$R32)*100 -> 0 | U32: =SUMIFS($L:$L,$C:$C,U$3,$D:$D,$R32)*100 -> 0 | V32: =SUMIFS($L:$L,$C:$C,V$3,$D:$D,$R32)*100 -> 0 | W32: =SUMIFS($L:$L,$C:$C,W$3,$D:$D,$R32)*100 -> 18.228 | X32: =SUMIFS($L:$L,$C:$C,X$3,$D:$D,$R32)*100 -> 0 | Y32: =SUMIFS($L:$L,$C:$C,Y$3,$D:$D,$R32)*100 -> 0 | Z32: =SUMIFS($L:$L,$C:$C,Z$3,$D:$D,$R32)*100 -> 0 | AA32: =SUMIFS($L:$L,$C:$C,AA$3,$D:$D,$R32)*100 -> 0 | AB32: =SUMPRODUCT($T$4:$AA$4,T32:AA32) -> 4.7923398 | AC32: =SUMIFS($L:$L,$C:$C,AC$3,$D:$D,$R32)*100 -> 0 | AD32: =SUMIFS($L:$L,$C:$C,AD$3,$D:$D,$R32)*100 -> 0 | AE32: =SUMIFS($L:$L,$C:$C,AE$3,$D:$D,$R32)*100 -> 0 | AF32: =SUMPRODUCT($AC$4:$AE$4,AC32:AE32) -> 0 | AH32: =AB32/100*$AL$6 -> 20676.514 | AI32: =AF32/100*$AL$23 -> 0
B33: 19 | C33: A01 | D33: M101 | E33: FILM FLOW-PACK (ENVOLTORIO PRIMARIO) | G33: X | L33: — | M33: =$E$4*$E$5 -> 20 | N33: uni. | O33: 1 por unidad | R33: M114 | S33: ÁCIDO CÍTRICO | T33: =SUMIFS($L:$L,$C:$C,T$3,$D:$D,$R33)*100 -> 0 | U33: =SUMIFS($L:$L,$C:$C,U$3,$D:$D,$R33)*100 -> 0 | V33: =SUMIFS($L:$L,$C:$C,V$3,$D:$D,$R33)*100 -> 0 | W33: =SUMIFS($L:$L,$C:$C,W$3,$D:$D,$R33)*100 -> 0.1302 | X33: =SUMIFS($L:$L,$C:$C,X$3,$D:$D,$R33)*100 -> 0 | Y33: =SUMIFS($L:$L,$C:$C,Y$3,$D:$D,$R33)*100 -> 0 | Z33: =SUMIFS($L:$L,$C:$C,Z$3,$D:$D,$R33)*100 -> 0 | AA33: =SUMIFS($L:$L,$C:$C,AA$3,$D:$D,$R33)*100 -> 0 | AB33: =SUMPRODUCT($T$4:$AA$4,T33:AA33) -> 0.034230999 | AC33: =SUMIFS($L:$L,$C:$C,AC$3,$D:$D,$R33)*100 -> 0 | AD33: =SUMIFS($L:$L,$C:$C,AD$3,$D:$D,$R33)*100 -> 0 | AE33: =SUMIFS($L:$L,$C:$C,AE$3,$D:$D,$R33)*100 -> 0 | AF33: =SUMPRODUCT($AC$4:$AE$4,AC33:AE33) -> 0 | AH33: =AB33/100*$AL$6 -> 147.68938 | AI33: =AF33/100*$AL$23 -> 0 | AK33: Desperdicio total | AL33: 0.07389 | AQ33: Desvios | AR33: =AR30/AR31-1 -> 0
B34: 20 | C34: A01 | D34: M102 | E34: CAJA DE CARTÓN CORRUGADO | G34: X | L34: — | M34: =$E$4 -> 1 | N34: uni. | O34: 1 por caja | R34: M115 | S34: ALMIDÓN DE MAÍZ | T34: =SUMIFS($L:$L,$C:$C,T$3,$D:$D,$R34)*100 -> 0 | U34: =SUMIFS($L:$L,$C:$C,U$3,$D:$D,$R34)*100 -> 0 | V34: =SUMIFS($L:$L,$C:$C,V$3,$D:$D,$R34)*100 -> 0 | W34: =SUMIFS($L:$L,$C:$C,W$3,$D:$D,$R34)*100 -> 0 | X34: =SUMIFS($L:$L,$C:$C,X$3,$D:$D,$R34)*100 -> 17.67 | Y34: =SUMIFS($L:$L,$C:$C,Y$3,$D:$D,$R34)*100 -> 17.67 | Z34: =SUMIFS($L:$L,$C:$C,Z$3,$D:$D,$R34)*100 -> 0 | AA34: =SUMIFS($L:$L,$C:$C,AA$3,$D:$D,$R34)*100 -> 0 | AB34: =SUMPRODUCT($T$4:$AA$4,T34:AA34) -> 2.1569067 | AC34: =SUMIFS($L:$L,$C:$C,AC$3,$D:$D,$R34)*100 -> 10.2 | AD34: =SUMIFS($L:$L,$C:$C,AD$3,$D:$D,$R34)*100 -> 0 | AE34: =SUMIFS($L:$L,$C:$C,AE$3,$D:$D,$R34)*100 -> 0 | AF34: =SUMPRODUCT($AC$4:$AE$4,AC34:AE34) -> 3.7578935 | AH34: =AB34/100*$AL$6 -> 9305.9574 | AI34: =AF34/100*$AL$23 -> 14857.624
B35: 21 | C35: A01 | D35: M103 | E35: CINTA DE CIERRE | G35: X | L35: — | M35: =$E$4 -> 1 | N35: uni. | O35: 1 por caja | R35: M116 | S35: FÉCULA DE MANDIOCA | T35: =SUMIFS($L:$L,$C:$C,T$3,$D:$D,$R35)*100 -> 0 | U35: =SUMIFS($L:$L,$C:$C,U$3,$D:$D,$R35)*100 -> 0 | V35: =SUMIFS($L:$L,$C:$C,V$3,$D:$D,$R35)*100 -> 0 | W35: =SUMIFS($L:$L,$C:$C,W$3,$D:$D,$R35)*100 -> 0 | X35: =SUMIFS($L:$L,$C:$C,X$3,$D:$D,$R35)*100 -> 13.95 | Y35: =SUMIFS($L:$L,$C:$C,Y$3,$D:$D,$R35)*100 -> 13.02 | Z35: =SUMIFS($L:$L,$C:$C,Z$3,$D:$D,$R35)*100 -> 0 | AA35: =SUMIFS($L:$L,$C:$C,AA$3,$D:$D,$R35)*100 -> 0 | AB35: =SUMPRODUCT($T$4:$AA$4,T35:AA35) -> 1.6233559 | AC35: =SUMIFS($L:$L,$C:$C,AC$3,$D:$D,$R35)*100 -> 8.5 | AD35: =SUMIFS($L:$L,$C:$C,AD$3,$D:$D,$R35)*100 -> 5.34 | AE35: =SUMIFS($L:$L,$C:$C,AE$3,$D:$D,$R35)*100 -> 4.45 | AF35: =SUMPRODUCT($AC$4:$AE$4,AC35:AE35) -> 6.3355786 | AH35: =AB35/100*$AL$6 -> 7003.9568 | AI35: =AF35/100*$AL$23 -> 25049.045 | AL35: 0.07
R36: M117 | S36: QUESO DESCREMADO EN POLVO | T36: =SUMIFS($L:$L,$C:$C,T$3,$D:$D,$R36)*100 -> 0 | U36: =SUMIFS($L:$L,$C:$C,U$3,$D:$D,$R36)*100 -> 0 | V36: =SUMIFS($L:$L,$C:$C,V$3,$D:$D,$R36)*100 -> 0 | W36: =SUMIFS($L:$L,$C:$C,W$3,$D:$D,$R36)*100 -> 0 | X36: =SUMIFS($L:$L,$C:$C,X$3,$D:$D,$R36)*100 -> 12.09 | Y36: =SUMIFS($L:$L,$C:$C,Y$3,$D:$D,$R36)*100 -> 0 | Z36: =SUMIFS($L:$L,$C:$C,Z$3,$D:$D,$R36)*100 -> 0 | AA36: =SUMIFS($L:$L,$C:$C,AA$3,$D:$D,$R36)*100 -> 0 | AB36: =SUMPRODUCT($T$4:$AA$4,T36:AA36) -> 0.44273177 | AC36: =SUMIFS($L:$L,$C:$C,AC$3,$D:$D,$R36)*100 -> 0 | AD36: =SUMIFS($L:$L,$C:$C,AD$3,$D:$D,$R36)*100 -> 0 | AE36: =SUMIFS($L:$L,$C:$C,AE$3,$D:$D,$R36)*100 -> 0 | AF36: =SUMPRODUCT($AC$4:$AE$4,AC36:AE36) -> 0 | AH36: =AB36/100*$AL$6 -> 1910.1628 | AI36: =AF36/100*$AL$23 -> 0
D37: Galletitas símil chocolinas free - A02 | M37: Foto | R37: M118 | S37: ACEITE DE GIRASOL ALTO OLEICO | T37: =SUMIFS($L:$L,$C:$C,T$3,$D:$D,$R37)*100 -> 0 | U37: =SUMIFS($L:$L,$C:$C,U$3,$D:$D,$R37)*100 -> 0 | V37: =SUMIFS($L:$L,$C:$C,V$3,$D:$D,$R37)*100 -> 0 | W37: =SUMIFS($L:$L,$C:$C,W$3,$D:$D,$R37)*100 -> 0 | X37: =SUMIFS($L:$L,$C:$C,X$3,$D:$D,$R37)*100 -> 7.44 | Y37: =SUMIFS($L:$L,$C:$C,Y$3,$D:$D,$R37)*100 -> 5.58 | Z37: =SUMIFS($L:$L,$C:$C,Z$3,$D:$D,$R37)*100 -> 0 | AA37: =SUMIFS($L:$L,$C:$C,AA$3,$D:$D,$R37)*100 -> 0 | AB37: =SUMPRODUCT($T$4:$AA$4,T37:AA37) -> 0.749241 | AC37: =SUMIFS($L:$L,$C:$C,AC$3,$D:$D,$R37)*100 -> 0 | AD37: =SUMIFS($L:$L,$C:$C,AD$3,$D:$D,$R37)*100 -> 0 | AE37: =SUMIFS($L:$L,$C:$C,AE$3,$D:$D,$R37)*100 -> 0 | AF37: =SUMPRODUCT($AC$4:$AE$4,AC37:AE37) -> 0 | AH37: =AB37/100*$AL$6 -> 3232.5946 | AI37: =AF37/100*$AL$23 -> 0
D38: PT anual (kg) | E38: =SUMIFS('Plan de ventas'!$O$48:$O$60,'Plan de ventas'!$B$48:$B$60,D47)*1000 -> 13132.517 | R38: M119 | S38: CLARA DE HUEVO EN POLVO | T38: =SUMIFS($L:$L,$C:$C,T$3,$D:$D,$R38)*100 -> 0 | U38: =SUMIFS($L:$L,$C:$C,U$3,$D:$D,$R38)*100 -> 0 | V38: =SUMIFS($L:$L,$C:$C,V$3,$D:$D,$R38)*100 -> 0 | W38: =SUMIFS($L:$L,$C:$C,W$3,$D:$D,$R38)*100 -> 0 | X38: =SUMIFS($L:$L,$C:$C,X$3,$D:$D,$R38)*100 -> 4.65 | Y38: =SUMIFS($L:$L,$C:$C,Y$3,$D:$D,$R38)*100 -> 0 | Z38: =SUMIFS($L:$L,$C:$C,Z$3,$D:$D,$R38)*100 -> 0 | AA38: =SUMIFS($L:$L,$C:$C,AA$3,$D:$D,$R38)*100 -> 0 | AB38: =SUMPRODUCT($T$4:$AA$4,T38:AA38) -> 0.17028145 | AC38: =SUMIFS($L:$L,$C:$C,AC$3,$D:$D,$R38)*100 -> 0 | AD38: =SUMIFS($L:$L,$C:$C,AD$3,$D:$D,$R38)*100 -> 0 | AE38: =SUMIFS($L:$L,$C:$C,AE$3,$D:$D,$R38)*100 -> 0 | AF38: =SUMPRODUCT($AC$4:$AE$4,AC38:AE38) -> 0 | AH38: =AB38/100*$AL$6 -> 734.67802 | AI38: =AF38/100*$AL$23 -> 0
B39: Cajas / lote | E39: 1 | F39: ="Línea: Free | Versión n°: 1"&CHAR(10)&CHAR(10)&"Lote = "&E39&" cajas × "&E40&" unid./caja = "&(E39*E40)&" unidades"&CHAR(10)&"Producto terminado = "&TEXT(E43,"#,##0.00")&" kg"&CHAR(10)&"Mezcla a preparar = "&TEXT(E44,"#,##0.00")&" kg (rendimiento "&TEXT(E42,"0%")&")" -> Línea: Free | Versión n°: 1 Lote = 1 cajas × 20 unid./caja = 20 unidades Producto terminado = 3,00 kg Mezcla a preparar = 3,41 kg (rendimiento 88%) | R39: M120 | S39: DEXTROSA | T39: =SUMIFS($L:$L,$C:$C,T$3,$D:$D,$R39)*100 -> 0 | U39: =SUMIFS($L:$L,$C:$C,U$3,$D:$D,$R39)*100 -> 0 | V39: =SUMIFS($L:$L,$C:$C,V$3,$D:$D,$R39)*100 -> 0 | W39: =SUMIFS($L:$L,$C:$C,W$3,$D:$D,$R39)*100 -> 0 | X39: =SUMIFS($L:$L,$C:$C,X$3,$D:$D,$R39)*100 -> 3.72 | Y39: =SUMIFS($L:$L,$C:$C,Y$3,$D:$D,$R39)*100 -> 3.72 | Z39: =SUMIFS($L:$L,$C:$C,Z$3,$D:$D,$R39)*100 -> 0 | AA39: =SUMIFS($L:$L,$C:$C,AA$3,$D:$D,$R39)*100 -> 0 | AB39: =SUMPRODUCT($T$4:$AA$4,T39:AA39) -> 0.45408561 | AC39: =SUMIFS($L:$L,$C:$C,AC$3,$D:$D,$R39)*100 -> 0 | AD39: =SUMIFS($L:$L,$C:$C,AD$3,$D:$D,$R39)*100 -> 0 | AE39: =SUMIFS($L:$L,$C:$C,AE$3,$D:$D,$R39)*100 -> 0 | AF39: =SUMPRODUCT($AC$4:$AE$4,AC39:AE39) -> 0 | AH39: =AB39/100*$AL$6 -> 1959.1489 | AI39: =AF39/100*$AL$23 -> 0
B40: Unid. / caja | E40: 20 | R40: M121 | S40: ESENCIA DE QUESO | T40: =SUMIFS($L:$L,$C:$C,T$3,$D:$D,$R40)*100 -> 0 | U40: =SUMIFS($L:$L,$C:$C,U$3,$D:$D,$R40)*100 -> 0 | V40: =SUMIFS($L:$L,$C:$C,V$3,$D:$D,$R40)*100 -> 0 | W40: =SUMIFS($L:$L,$C:$C,W$3,$D:$D,$R40)*100 -> 0 | X40: =SUMIFS($L:$L,$C:$C,X$3,$D:$D,$R40)*100 -> 0.93 | Y40: =SUMIFS($L:$L,$C:$C,Y$3,$D:$D,$R40)*100 -> 0.93 | Z40: =SUMIFS($L:$L,$C:$C,Z$3,$D:$D,$R40)*100 -> 0 | AA40: =SUMIFS($L:$L,$C:$C,AA$3,$D:$D,$R40)*100 -> 0 | AB40: =SUMPRODUCT($T$4:$AA$4,T40:AA40) -> 0.1135214 | AC40: =SUMIFS($L:$L,$C:$C,AC$3,$D:$D,$R40)*100 -> 0 | AD40: =SUMIFS($L:$L,$C:$C,AD$3,$D:$D,$R40)*100 -> 0 | AE40: =SUMIFS($L:$L,$C:$C,AE$3,$D:$D,$R40)*100 -> 0 | AF40: =SUMPRODUCT($AC$4:$AE$4,AC40:AE40) -> 0 | AH40: =AB40/100*$AL$6 -> 489.78723 | AI40: =AF40/100*$AL$23 -> 0
B41: Peso neto (g) | E41: 150 | R41: M122 | S41: POLVO PARA HORNEAR | T41: =SUMIFS($L:$L,$C:$C,T$3,$D:$D,$R41)*100 -> 0 | U41: =SUMIFS($L:$L,$C:$C,U$3,$D:$D,$R41)*100 -> 0 | V41: =SUMIFS($L:$L,$C:$C,V$3,$D:$D,$R41)*100 -> 0 | W41: =SUMIFS($L:$L,$C:$C,W$3,$D:$D,$R41)*100 -> 0 | X41: =SUMIFS($L:$L,$C:$C,X$3,$D:$D,$R41)*100 -> 0.93 | Y41: =SUMIFS($L:$L,$C:$C,Y$3,$D:$D,$R41)*100 -> 0.93 | Z41: =SUMIFS($L:$L,$C:$C,Z$3,$D:$D,$R41)*100 -> 1.86 | AA41: =SUMIFS($L:$L,$C:$C,AA$3,$D:$D,$R41)*100 -> 1.86 | AB41: =SUMPRODUCT($T$4:$AA$4,T41:AA41) -> 0.5064786 | AC41: =SUMIFS($L:$L,$C:$C,AC$3,$D:$D,$R41)*100 -> 0 | AD41: =SUMIFS($L:$L,$C:$C,AD$3,$D:$D,$R41)*100 -> 1.78 | AE41: =SUMIFS($L:$L,$C:$C,AE$3,$D:$D,$R41)*100 -> 1.78 | AF41: =SUMPRODUCT($AC$4:$AE$4,AC41:AE41) -> 1.1242107 | AH41: =AB41/100*$AL$6 -> 2185.198 | AI41: =AF41/100*$AL$23 -> 4444.804
B42: Rendim. (%) | E42: 0.88 | R42: M123 | S42: QUESO RALLADO | T42: =SUMIFS($L:$L,$C:$C,T$3,$D:$D,$R42)*100 -> 0 | U42: =SUMIFS($L:$L,$C:$C,U$3,$D:$D,$R42)*100 -> 0 | V42: =SUMIFS($L:$L,$C:$C,V$3,$D:$D,$R42)*100 -> 0 | W42: =SUMIFS($L:$L,$C:$C,W$3,$D:$D,$R42)*100 -> 0 | X42: =SUMIFS($L:$L,$C:$C,X$3,$D:$D,$R42)*100 -> 0 | Y42: =SUMIFS($L:$L,$C:$C,Y$3,$D:$D,$R42)*100 -> 11.16 | Z42: =SUMIFS($L:$L,$C:$C,Z$3,$D:$D,$R42)*100 -> 0 | AA42: =SUMIFS($L:$L,$C:$C,AA$3,$D:$D,$R42)*100 -> 0 | AB42: =SUMPRODUCT($T$4:$AA$4,T42:AA42) -> 0.95358136 | AC42: =SUMIFS($L:$L,$C:$C,AC$3,$D:$D,$R42)*100 -> 0 | AD42: =SUMIFS($L:$L,$C:$C,AD$3,$D:$D,$R42)*100 -> 0 | AE42: =SUMIFS($L:$L,$C:$C,AE$3,$D:$D,$R42)*100 -> 0 | AF42: =SUMPRODUCT($AC$4:$AE$4,AC42:AE42) -> 0 | AH42: =AB42/100*$AL$6 -> 4114.2195 | AI42: =AF42/100*$AL$23 -> 0
B43: PT (kg) | E43: =E39*E40*E41/1000 -> 3 | R43: M124 | S43: GRASA VACUNA | T43: =SUMIFS($L:$L,$C:$C,T$3,$D:$D,$R43)*100 -> 0 | U43: =SUMIFS($L:$L,$C:$C,U$3,$D:$D,$R43)*100 -> 0 | V43: =SUMIFS($L:$L,$C:$C,V$3,$D:$D,$R43)*100 -> 0 | W43: =SUMIFS($L:$L,$C:$C,W$3,$D:$D,$R43)*100 -> 0 | X43: =SUMIFS($L:$L,$C:$C,X$3,$D:$D,$R43)*100 -> 0 | Y43: =SUMIFS($L:$L,$C:$C,Y$3,$D:$D,$R43)*100 -> 9.3 | Z43: =SUMIFS($L:$L,$C:$C,Z$3,$D:$D,$R43)*100 -> 0 | AA43: =SUMIFS($L:$L,$C:$C,AA$3,$D:$D,$R43)*100 -> 0 | AB43: =SUMPRODUCT($T$4:$AA$4,T43:AA43) -> 0.79465113 | AC43: =SUMIFS($L:$L,$C:$C,AC$3,$D:$D,$R43)*100 -> 0 | AD43: =SUMIFS($L:$L,$C:$C,AD$3,$D:$D,$R43)*100 -> 0 | AE43: =SUMIFS($L:$L,$C:$C,AE$3,$D:$D,$R43)*100 -> 0 | AF43: =SUMPRODUCT($AC$4:$AE$4,AC43:AE43) -> 0 | AH43: =AB43/100*$AL$6 -> 3428.5163 | AI43: =AF43/100*$AL$23 -> 0
B44: Mezcla (kg) | E44: =E43/E42 -> 3.4090909 | R44: M125 | S44: PANACEA | T44: =SUMIFS($L:$L,$C:$C,T$3,$D:$D,$R44)*100 -> 0 | U44: =SUMIFS($L:$L,$C:$C,U$3,$D:$D,$R44)*100 -> 0 | V44: =SUMIFS($L:$L,$C:$C,V$3,$D:$D,$R44)*100 -> 0 | W44: =SUMIFS($L:$L,$C:$C,W$3,$D:$D,$R44)*100 -> 0 | X44: =SUMIFS($L:$L,$C:$C,X$3,$D:$D,$R44)*100 -> 0 | Y44: =SUMIFS($L:$L,$C:$C,Y$3,$D:$D,$R44)*100 -> 0 | Z44: =SUMIFS($L:$L,$C:$C,Z$3,$D:$D,$R44)*100 -> 3.72 | AA44: =SUMIFS($L:$L,$C:$C,AA$3,$D:$D,$R44)*100 -> 2.79 | AB44: =SUMPRODUCT($T$4:$AA$4,T44:AA44) -> 0.64837937 | AC44: =SUMIFS($L:$L,$C:$C,AC$3,$D:$D,$R44)*100 -> 0 | AD44: =SUMIFS($L:$L,$C:$C,AD$3,$D:$D,$R44)*100 -> 1.78 | AE44: =SUMIFS($L:$L,$C:$C,AE$3,$D:$D,$R44)*100 -> 1.78 | AF44: =SUMPRODUCT($AC$4:$AE$4,AC44:AE44) -> 1.1242107 | AH44: =AB44/100*$AL$6 -> 2797.4278 | AI44: =AF44/100*$AL$23 -> 4444.804
B45: ITEM | D45: CODIGO | E45: DENOMINACION | F45: NIVEL | L45: % | M45: CANTIDAD | N45: UNIDAD | O45: OBSERVACIONES | R45: M126 | S45: ESENCIA DE VAINILLA / NARANJA / LIMÓN | T45: =SUMIFS($L:$L,$C:$C,T$3,$D:$D,$R45)*100 -> 0 | U45: =SUMIFS($L:$L,$C:$C,U$3,$D:$D,$R45)*100 -> 0 | V45: =SUMIFS($L:$L,$C:$C,V$3,$D:$D,$R45)*100 -> 0 | W45: =SUMIFS($L:$L,$C:$C,W$3,$D:$D,$R45)*100 -> 0 | X45: =SUMIFS($L:$L,$C:$C,X$3,$D:$D,$R45)*100 -> 0 | Y45: =SUMIFS($L:$L,$C:$C,Y$3,$D:$D,$R45)*100 -> 0 | Z45: =SUMIFS($L:$L,$C:$C,Z$3,$D:$D,$R45)*100 -> 0 | AA45: =SUMIFS($L:$L,$C:$C,AA$3,$D:$D,$R45)*100 -> 0.465 | AB45: =SUMPRODUCT($T$4:$AA$4,T45:AA45) -> 0.068767509 | AC45: =SUMIFS($L:$L,$C:$C,AC$3,$D:$D,$R45)*100 -> 0 | AD45: =SUMIFS($L:$L,$C:$C,AD$3,$D:$D,$R45)*100 -> 1.068 | AE45: =SUMIFS($L:$L,$C:$C,AE$3,$D:$D,$R45)*100 -> 0 | AF45: =SUMPRODUCT($AC$4:$AE$4,AC45:AE45) -> 0.47216861 | AH45: =AB45/100*$AL$6 -> 296.69689 | AI45: =AF45/100*$AL$23 -> 1866.8181
F46: 0 | G46: 1 | H46: 2 | I46: 3 | J46: 4 | K46: 5 | R46: M127 | S46: AGUA | T46: =SUMIFS($L:$L,$C:$C,T$3,$D:$D,$R46)*100 -> 0 | U46: =SUMIFS($L:$L,$C:$C,U$3,$D:$D,$R46)*100 -> 0 | V46: =SUMIFS($L:$L,$C:$C,V$3,$D:$D,$R46)*100 -> 0 | W46: =SUMIFS($L:$L,$C:$C,W$3,$D:$D,$R46)*100 -> 0 | X46: =SUMIFS($L:$L,$C:$C,X$3,$D:$D,$R46)*100 -> 0 | Y46: =SUMIFS($L:$L,$C:$C,Y$3,$D:$D,$R46)*100 -> 0 | Z46: =SUMIFS($L:$L,$C:$C,Z$3,$D:$D,$R46)*100 -> 0 | AA46: =SUMIFS($L:$L,$C:$C,AA$3,$D:$D,$R46)*100 -> 0 | AB46: =SUMPRODUCT($T$4:$AA$4,T46:AA46) -> 0 | AC46: =SUMIFS($L:$L,$C:$C,AC$3,$D:$D,$R46)*100 -> 32.3 | AD46: =SUMIFS($L:$L,$C:$C,AD$3,$D:$D,$R46)*100 -> 9.79 | AE46: =SUMIFS($L:$L,$C:$C,AE$3,$D:$D,$R46)*100 -> 8.9 | AF46: =SUMPRODUCT($AC$4:$AE$4,AC46:AE46) -> 17.914524 | AH46: =AB46/100*$AL$6 -> 0 | AI46: =AF46/100*$AL$23 -> 70828.845
B47: 1 | D47: A02 | E47: Galletitas símil chocolinas free (caja) | F47: X | L47: — | M47: =$E$39 -> 1 | N47: cajas | O47: Lote = 1 caja | R47: M128 | S47: ACEITE DE GIRASOL | T47: =SUMIFS($L:$L,$C:$C,T$3,$D:$D,$R47)*100 -> 0 | U47: =SUMIFS($L:$L,$C:$C,U$3,$D:$D,$R47)*100 -> 0 | V47: =SUMIFS($L:$L,$C:$C,V$3,$D:$D,$R47)*100 -> 0 | W47: =SUMIFS($L:$L,$C:$C,W$3,$D:$D,$R47)*100 -> 0 | X47: =SUMIFS($L:$L,$C:$C,X$3,$D:$D,$R47)*100 -> 0 | Y47: =SUMIFS($L:$L,$C:$C,Y$3,$D:$D,$R47)*100 -> 0 | Z47: =SUMIFS($L:$L,$C:$C,Z$3,$D:$D,$R47)*100 -> 0 | AA47: =SUMIFS($L:$L,$C:$C,AA$3,$D:$D,$R47)*100 -> 0 | AB47: =SUMPRODUCT($T$4:$AA$4,T47:AA47) -> 0 | AC47: =SUMIFS($L:$L,$C:$C,AC$3,$D:$D,$R47)*100 -> 5.1 | AD47: =SUMIFS($L:$L,$C:$C,AD$3,$D:$D,$R47)*100 -> 0 | AE47: =SUMIFS($L:$L,$C:$C,AE$3,$D:$D,$R47)*100 -> 0 | AF47: =SUMPRODUCT($AC$4:$AE$4,AC47:AE47) -> 1.8789468 | AH47: =AB47/100*$AL$6 -> 0 | AI47: =AF47/100*$AL$23 -> 7428.812
B48: 2 | C48: A02 | D48: M030 | E48: HARINA DE ARROZ | G48: X | L48: =+M48/$M$63 -> 0.2511 | M48: 0.92045455 | N48: Kg. | R48: M130 | S48: FIBRA C 200 | T48: =SUMIFS($L:$L,$C:$C,T$3,$D:$D,$R48)*100 -> 0 | U48: =SUMIFS($L:$L,$C:$C,U$3,$D:$D,$R48)*100 -> 0 | V48: =SUMIFS($L:$L,$C:$C,V$3,$D:$D,$R48)*100 -> 0 | W48: =SUMIFS($L:$L,$C:$C,W$3,$D:$D,$R48)*100 -> 0 | X48: =SUMIFS($L:$L,$C:$C,X$3,$D:$D,$R48)*100 -> 0 | Y48: =SUMIFS($L:$L,$C:$C,Y$3,$D:$D,$R48)*100 -> 0 | Z48: =SUMIFS($L:$L,$C:$C,Z$3,$D:$D,$R48)*100 -> 0 | AA48: =SUMIFS($L:$L,$C:$C,AA$3,$D:$D,$R48)*100 -> 0 | AB48: =SUMPRODUCT($T$4:$AA$4,T48:AA48) -> 0 | AC48: =SUMIFS($L:$L,$C:$C,AC$3,$D:$D,$R48)*100 -> 2.125 | AD48: =SUMIFS($L:$L,$C:$C,AD$3,$D:$D,$R48)*100 -> 0 | AE48: =SUMIFS($L:$L,$C:$C,AE$3,$D:$D,$R48)*100 -> 0 | AF48: =SUMPRODUCT($AC$4:$AE$4,AC48:AE48) -> 0.78289449 | AH48: =AB48/100*$AL$6 -> 0 | AI48: =AF48/100*$AL$23 -> 3095.3383
B49: 3 | C49: A02 | D49: M001 | E49: FÉCULA DE MAÍZ | G49: X | L49: =+M49/$M$63 -> 0.2232 | M49: 0.81818182 | N49: Kg. | R49: M131 | S49: LEVADURA | T49: =SUMIFS($L:$L,$C:$C,T$3,$D:$D,$R49)*100 -> 0 | U49: =SUMIFS($L:$L,$C:$C,U$3,$D:$D,$R49)*100 -> 0 | V49: =SUMIFS($L:$L,$C:$C,V$3,$D:$D,$R49)*100 -> 0 | W49: =SUMIFS($L:$L,$C:$C,W$3,$D:$D,$R49)*100 -> 0 | X49: =SUMIFS($L:$L,$C:$C,X$3,$D:$D,$R49)*100 -> 0 | Y49: =SUMIFS($L:$L,$C:$C,Y$3,$D:$D,$R49)*100 -> 0 | Z49: =SUMIFS($L:$L,$C:$C,Z$3,$D:$D,$R49)*100 -> 0 | AA49: =SUMIFS($L:$L,$C:$C,AA$3,$D:$D,$R49)*100 -> 0 | AB49: =SUMPRODUCT($T$4:$AA$4,T49:AA49) -> 0 | AC49: =SUMIFS($L:$L,$C:$C,AC$3,$D:$D,$R49)*100 -> 1.7 | AD49: =SUMIFS($L:$L,$C:$C,AD$3,$D:$D,$R49)*100 -> 0 | AE49: =SUMIFS($L:$L,$C:$C,AE$3,$D:$D,$R49)*100 -> 0 | AF49: =SUMPRODUCT($AC$4:$AE$4,AC49:AE49) -> 0.62631559 | AH49: =AB49/100*$AL$6 -> 0 | AI49: =AF49/100*$AL$23 -> 2476.2707
B50: 4 | C50: A02 | D50: M036 | E50: ACEITE VEGETAL INTERESTERIFICADO | G50: X | L50: =+M50/$M$63 -> 0.1302 | M50: 0.47727273 | N50: Kg. | R50: M134 | S50: MARGARINA | T50: =SUMIFS($L:$L,$C:$C,T$3,$D:$D,$R50)*100 -> 0 | U50: =SUMIFS($L:$L,$C:$C,U$3,$D:$D,$R50)*100 -> 0 | V50: =SUMIFS($L:$L,$C:$C,V$3,$D:$D,$R50)*100 -> 0 | W50: =SUMIFS($L:$L,$C:$C,W$3,$D:$D,$R50)*100 -> 0 | X50: =SUMIFS($L:$L,$C:$C,X$3,$D:$D,$R50)*100 -> 0 | Y50: =SUMIFS($L:$L,$C:$C,Y$3,$D:$D,$R50)*100 -> 0 | Z50: =SUMIFS($L:$L,$C:$C,Z$3,$D:$D,$R50)*100 -> 0 | AA50: =SUMIFS($L:$L,$C:$C,AA$3,$D:$D,$R50)*100 -> 0 | AB50: =SUMPRODUCT($T$4:$AA$4,T50:AA50) -> 0 | AC50: =SUMIFS($L:$L,$C:$C,AC$3,$D:$D,$R50)*100 -> 0 | AD50: =SUMIFS($L:$L,$C:$C,AD$3,$D:$D,$R50)*100 -> 14.24 | AE50: =SUMIFS($L:$L,$C:$C,AE$3,$D:$D,$R50)*100 -> 13.35 | AF50: =SUMPRODUCT($AC$4:$AE$4,AC50:AE50) -> 8.8250543 | AH50: =AB50/100*$AL$6 -> 0 | AI50: =AF50/100*$AL$23 -> 34891.712
B51: 5 | C51: A02 | D51: M104 | E51: PASTA DE PASAS DE UVA | G51: X | L51: =+M51/$M$63 -> 0.1209 | M51: 0.44318182 | N51: Kg. | R51: M137 | S51: SORBATO DE POTASIO | T51: =SUMIFS($L:$L,$C:$C,T$3,$D:$D,$R51)*100 -> 0 | U51: =SUMIFS($L:$L,$C:$C,U$3,$D:$D,$R51)*100 -> 0 | V51: =SUMIFS($L:$L,$C:$C,V$3,$D:$D,$R51)*100 -> 0 | W51: =SUMIFS($L:$L,$C:$C,W$3,$D:$D,$R51)*100 -> 0 | X51: =SUMIFS($L:$L,$C:$C,X$3,$D:$D,$R51)*100 -> 0 | Y51: =SUMIFS($L:$L,$C:$C,Y$3,$D:$D,$R51)*100 -> 0 | Z51: =SUMIFS($L:$L,$C:$C,Z$3,$D:$D,$R51)*100 -> 0 | AA51: =SUMIFS($L:$L,$C:$C,AA$3,$D:$D,$R51)*100 -> 0 | AB51: =SUMPRODUCT($T$4:$AA$4,T51:AA51) -> 0 | AC51: =SUMIFS($L:$L,$C:$C,AC$3,$D:$D,$R51)*100 -> 0 | AD51: =SUMIFS($L:$L,$C:$C,AD$3,$D:$D,$R51)*100 -> 0.267 | AE51: =SUMIFS($L:$L,$C:$C,AE$3,$D:$D,$R51)*100 -> 0.178 | AF51: =SUMPRODUCT($AC$4:$AE$4,AC51:AE51) -> 0.15176846 | AH51: =AB51/100*$AL$6 -> 0 | AI51: =AF51/100*$AL$23 -> 600.04858
B52: 6 | C52: A02 | D52: M045 | E52: CACAO ALCALINO | G52: X | L52: =+M52/$M$63 -> 0.0558 | M52: 0.20454545 | N52: Kg. | R52: M164 | S52: EDULZUGAR | T52: =SUMIFS($L:$L,$C:$C,T$3,$D:$D,$R52)*100 -> 0 | U52: =SUMIFS($L:$L,$C:$C,U$3,$D:$D,$R52)*100 -> 0 | V52: =SUMIFS($L:$L,$C:$C,V$3,$D:$D,$R52)*100 -> 0 | W52: =SUMIFS($L:$L,$C:$C,W$3,$D:$D,$R52)*100 -> 0 | X52: =SUMIFS($L:$L,$C:$C,X$3,$D:$D,$R52)*100 -> 0 | Y52: =SUMIFS($L:$L,$C:$C,Y$3,$D:$D,$R52)*100 -> 0 | Z52: =SUMIFS($L:$L,$C:$C,Z$3,$D:$D,$R52)*100 -> 0 | AA52: =SUMIFS($L:$L,$C:$C,AA$3,$D:$D,$R52)*100 -> 2.79 | AB52: =SUMPRODUCT($T$4:$AA$4,T52:AA52) -> 0.41260505 | AC52: =SUMIFS($L:$L,$C:$C,AC$3,$D:$D,$R52)*100 -> 0 | AD52: =SUMIFS($L:$L,$C:$C,AD$3,$D:$D,$R52)*100 -> 0 | AE52: =SUMIFS($L:$L,$C:$C,AE$3,$D:$D,$R52)*100 -> 0 | AF52: =SUMPRODUCT($AC$4:$AE$4,AC52:AE52) -> 0 | AH52: =AB52/100*$AL$6 -> 1780.1814 | AI52: =AF52/100*$AL$23 -> 0
B53: 7 | C53: A02 | D53: M105 | E53: ACEITE DE COCO | G53: X | L53: =+M53/$M$63 -> 0.0465 | M53: 0.17045455 | N53: Kg. | S53: AGUA | T53: 7 | U53: 7 | V53: 7 | W53: 7 | X53: 7 | Y53: 7 | Z53: 7 | AA53: 7 | AB53: =SUMPRODUCT($T$4:$AA$4,T53:AA53) -> 7 | AC53: 15 | AD53: 11 | AE53: 11 | AF53: =SUMPRODUCT($AC$4:$AE$4,AC53:AE53) -> 12.473684 | AH53: =AB53/100*$AL$6 -> 30201.447 | AI53: =AF53/100*$AL$23 -> 49317.337
B54: 8 | C54: A02 | D54: M106 | E54: FIBRA DE BAMBÚ | G54: X | L54: =+M54/$M$63 -> 0.0372 | M54: 0.13636364 | N54: Kg. | T54: =+SUM(T5:T53) -> 100 | U54: =+SUM(U5:U53) -> 100 | V54: =+SUM(V5:V53) -> 100 | W54: =+SUM(W5:W53) -> 100 | X54: =+SUM(X5:X53) -> 100 | Y54: =+SUM(Y5:Y53) -> 100 | Z54: =+SUM(Z5:Z53) -> 100 | AA54: =+SUM(AA5:AA53) -> 100 | ... AF54: =+SUM(AF5:AF53) -> 100 | AH54: =SUM(AH5:AH53) -> 431449.24 | AI54: =SUM(AI5:AI53) -> 395371.07
B55: 9 | C55: A02 | D55: M107 | E55: PSYLLIUM | G55: X | L55: =+M55/$M$63 -> 0.0279 | M55: 0.10227273 | N55: Kg.
B56: 10 | C56: A02 | D56: M108 | E56: EDULCORANTE | G56: X | L56: =+M56/$M$63 -> 0.01395 | M56: 0.051136364 | N56: Kg.
B57: 11 | C57: A02 | D57: M022 | E57: GOMA XÁNTICA | G57: X | L57: =+M57/$M$63 -> 0.0093 | M57: 0.034090909 | N57: Kg.
B58: 12 | C58: A02 | D58: M056 | E58: BICARBONATO DE SODIO | G58: X | L58: =+M58/$M$63 -> 0.00465 | M58: 0.017045455 | N58: Kg.
B59: 13 | C59: A02 | D59: M006 | E59: SAL | G59: X | L59: =+M59/$M$63 -> 0.00372 | M59: 0.013636364 | N59: Kg.
B60: 14 | C60: A02 | D60: M047 | E60: ESENCIA DE CHOCOLATE | G60: X | L60: =+M60/$M$63 -> 0.00279 | M60: 0.010227273 | N60: Kg.
B61: 15 | C61: A02 | D61: M057 | E61: BICARBONATO DE CALCIO | G61: X | L61: =+M61/$M$63 -> 0.00279 | M61: 0.010227273 | N61: Kg.
E62: AGUA | L62: 0.07 | M62: =+M63*0.07 -> 0.25659824
D63: TOTAL MEZCLA | L63: =+SUM(L48:L62) -> 1 | M63: =+SUM(M48:M61)/0.93 -> 3.6656891 | N63: Kg.
B64: EMBALAJE
B65: 16 | C65: A02 | D65: M101 | E65: FILM FLOW-PACK (ENVOLTORIO PRIMARIO) | G65: X | L65: — | M65: =$E$39*$E$40 -> 20 | N65: uni. | O65: 1 por unidad
B66: 17 | C66: A02 | D66: M102 | E66: CAJA DE CARTÓN CORRUGADO | G66: X | L66: — | M66: =$E$39 -> 1 | N66: uni. | O66: 1 por caja
B67: 18 | C67: A02 | D67: M103 | E67: CINTA DE CIERRE | G67: X | L67: — | M67: =$E$39 -> 1 | N67: uni. | O67: 1 por caja
D69: Galletitas símil chocolinas - A03 | M69: Foto
D70: PT anual (kg) | E70: =SUMIFS('Plan de ventas'!$O$48:$O$60,'Plan de ventas'!$B$48:$B$60,D79)*1000 -> 30642.707
B71: Cajas / lote | E71: 1 | F71: ="Línea: Clásicas | Versión n°: 1"&CHAR(10)&CHAR(10)&"Lote = "&E71&" cajas × "&E72&" unid./caja = "&(E71*E72)&" unidades"&CHAR(10)&"Producto terminado = "&TEXT(E75,"#,##0.00")&" kg"&CHAR(10)&"Mezcla a preparar = "&TEXT(E76,"#,##0.00")&" kg (rendimiento "&TEXT(E74,"0%")&")" -> Línea: Clásicas | Versión n°: 1 Lote = 1 cajas × 20 unid./caja = 20 unidades Producto terminado = 3,00 kg Mezcla a preparar = 3,41 kg (rendimiento 88%)
B72: Unid. / caja | E72: 20
B73: Peso neto (g) | E73: 150
B74: Rendim. (%) | E74: 0.88
B75: PT (kg) | E75: =E71*E72*E73/1000 -> 3
B76: Mezcla (kg) | E76: =E75/E74 -> 3.4090909
B77: ITEM | D77: CODIGO | E77: DENOMINACION | F77: NIVEL | L77: % | M77: CANTIDAD | N77: UNIDAD | O77: OBSERVACIONES
F78: 0 | G78: 1 | H78: 2 | I78: 3 | J78: 4 | K78: 5
B79: 1 | D79: A03 | E79: Galletitas símil chocolinas (caja) | F79: X | L79: — | M79: =$E$71 -> 1 | N79: cajas | O79: Lote = 1 caja
B80: 2 | C80: A03 | D80: M030 | E80: HARINA DE ARROZ | G80: X | L80: =+M80/$M$92 -> 0.2511 | M80: 0.92045455 | N80: Kg.
B81: 3 | C81: A03 | D81: M001 | E81: FÉCULA DE MAÍZ | G81: X | L81: =+M81/$M$92 -> 0.2046 | M81: 0.75 | N81: Kg.
B82: 4 | C82: A03 | D82: M052 | E82: AZÚCAR COMÚN | G82: X | L82: =+M82/$M$92 -> 0.1674 | M82: 0.61363636 | N82: Kg.
B83: 5 | C83: A03 | D83: M036 | E83: ACEITE VEGETAL INTERESTERIFICADO | G83: X | L83: =+M83/$M$92 -> 0.1302 | M83: 0.47727273 | N83: Kg.
B84: 6 | C84: A03 | D84: M045 | E84: CACAO ALCALINO | G84: X | L84: =+M84/$M$92 -> 0.0558 | M84: 0.20454545 | N84: Kg.
B85: 7 | C85: A03 | D85: M109 | E85: LECHE EN POLVO | G85: X | L85: =+M85/$M$92 -> 0.0558 | M85: 0.20454545 | N85: Kg.
B86: 8 | C86: A03 | D86: M041 | E86: HUEVO EN POLVO DESHIDRATADO | G86: X | L86: =+M86/$M$92 -> 0.0372 | M86: 0.13636364 | N86: Kg.
B87: 9 | C87: A03 | D87: M022 | E87: GOMA XÁNTICA | G87: X | L87: =+M87/$M$92 -> 0.0093 | M87: 0.034090909 | N87: Kg.
B88: 10 | C88: A03 | D88: M056 | E88: BICARBONATO DE SODIO | G88: X | L88: =+M88/$M$92 -> 0.00744 | M88: 0.027272727 | N88: Kg.
B89: 11 | C89: A03 | D89: M057 | E89: BICARBONATO DE CALCIO | G89: X | L89: =+M89/$M$92 -> 0.00744 | M89: 0.027272727 | N89: Kg.
B90: 12 | C90: A03 | D90: M047 | E90: ESENCIA DE CHOCOLATE | G90: X | L90: =+M90/$M$92 -> 0.00372 | M90: 0.013636364 | N90: Kg.
E91: AGUA | L91: =+M91/$M$92 -> 0.07 | M91: =+M92*0.07 -> 0.25659824
D92: TOTAL MEZCLA | L92: =+SUM(L80:L91) -> 1 | M92: =+SUM(M80:M90)/0.93 -> 3.6656891 | N92: Kg.
B93: EMBALAJE
B94: 13 | C94: A03 | D94: M101 | E94: FILM FLOW-PACK (ENVOLTORIO PRIMARIO) | G94: X | L94: — | M94: =$E$71*$E$72 -> 20 | N94: uni. | O94: 1 por unidad
B95: 14 | C95: A03 | D95: M102 | E95: CAJA DE CARTÓN CORRUGADO | G95: X | L95: — | M95: =$E$71 -> 1 | N95: uni. | O95: 1 por caja
B96: 15 | C96: A03 | D96: M103 | E96: CINTA DE CIERRE | G96: X | L96: — | M96: =$E$71 -> 1 | N96: uni. | O96: 1 por caja
D98: Pepa rellena de batata - A04
D99: PT anual (kg) | E99: =SUMIFS('Plan de ventas'!$O$48:$O$60,'Plan de ventas'!$B$48:$B$60,D108)*1000 -> 94284.902
B100: Cajas | E100: 1 | F100: ="Línea: Clásicas | Versión n°: 1"&CHAR(10)&CHAR(10)&"Lote = "&E100&" cajas × "&E101&" unid./caja = "&(E100*E101)&" unidades"&CHAR(10)&"Producto terminado = "&TEXT(E104,"#,##0.00")&" kg"&CHAR(10)&"Mezcla a preparar = "&TEXT(E105,"#,##0.00")&" kg (rendimiento "&TEXT(E103,"0%")&")" -> Línea: Clásicas | Versión n°: 1 Lote = 1 cajas × 20 unid./caja = 20 unidades Producto terminado = 3,00 kg Mezcla a preparar = 3,53 kg (rendimiento 85%)
B101: Unid. / caja | E101: 20
B102: Peso neto (g) | E102: 150
B103: Rendim. (%) | E103: 0.85
...

Sheet Ritmo y capacidad
A1: Linea A - Galletitas | R1: Días activos/año | S1: =52*5-11-10 -> 239 | T1: Turnos | U1: 2
A2: NECESIDAD ANUAL MP | L2: Linea A - Galletitas | R2: Horas activas/año | S2: =+U2*U1*S1 -> 3824 | T2: Hs/turno | U2: 8
A3: Sección Operativa | B3: Alimentación | C3: Agregado | D3: Desperdicios | H3: Producción | L3: Sección Operativa | M3: Producción (kg/año) | N3: Hs activas/año | O3: Producción (kg/h) | P3: Semielaborado
D4: Recuperable | F4: No recuperable
A5: Amasado | B5: 431449.24 | C5: 0 | H5: 431449.24 | I5: kg/año | L5: Amasado | M5: 431449.24 | N5: =+$S$2 -> 3824 | O5: =+M5/N5 -> 112.82668 | P5: Amasijo
A6: Moldeado | B6: 431449.24 | C6: 0 | D6: 0.01 | E6: 4314.4924 | F6: 0.01 | G6: 4314.4924 | H6: 422820.25 | I6: kg/año | L6: Moldeado | M6: 422820.25 | N6: =+$S$2 -> 3824 | O6: =+M6/N6 -> 110.57015 | P6: Galletitas crudas formadas
A7: Horneado | B7: 422820.25 | C7: 0 | F7: 0.07 | G7: 29597.418 | H7: 393222.84 | I7: kg/año | L7: Horneado | M7: 393222.84 | N7: =+$S$2 -> 3824 | O7: =+M7/N7 -> 102.83024 | P7: Galletitas cocidas
A8: Enfriado | B8: 393222.84 | C8: 0 | D8: 0.04 | E8: 15728.913 | F8: 0.01 | G8: 3932.2284 | H8: 373561.69 | I8: kg/año | L8: Enfriado | M8: 373561.69 | N8: =+$S$2 -> 3824 | O8: =+M8/N8 -> 97.688727 | P8: Galletitas cocidas
A9: Envasado | B9: 373561.69 | C9: 0 | D9: 0.04 | E9: 14942.468 | H9: 358619.23 | I9: kg/año | L9: Envasado | M9: 358619.23 | N9: =+$S$2 -> 3824 | O9: =+M9/N9 -> 93.781178 | P9: Empaque (cajas)
A10: Paletizado | B10: 358619.23 | C10: 0 | H10: 358619.23 | I10: kg/año
A11: TOTALES | B11: 431449.24 | C11: 0 | E11: 34985.874 | G11: 37844.138 | H11: 358619.23 | I11: kg/año
X13: Linea B - Panificados
X14: Sección Operativa | Y14: Producción (kg/año) | Z14: Capacidad de la maquina (kg/h) | AA14: Hs activas/año | AB14: Capacidad de la maquina (kg/año | AC14: Cantidad de maquinas
X16: Batido | Y16: =M22 -> 395371.07 | Z16: 136.2 | AA16: =+$S$2 -> 3824 | AB16: =AA16*Z16 -> 520828.8 | AC16: =ROUNDUP(Y16/AB16,0) -> 1 | AD16: =Y16/(AB16*AC16) -> 0.75911907
X17: Dosificado | Y17: =M23 -> 395371.07 | Z17: 108 | AA17: =+$S$2 -> 3824 | AB17: =AA17*Z17 -> 412992 | AC17: =ROUNDUP(Y17/AB17,0) -> 1 | AD17: =Y17/(AB17*AC17) -> 0.95733349
A18: Linea B - Panificados | X18: Fermentado | Y18: =M24 -> 395371.07 | Z18: 38 | AA18: =+$S$2 -> 3824 | AB18: =AA18*Z18 -> 145312 | AC18: =ROUNDUP(Y18/AB18,0) -> 3 | AD18: =Y18/(AB18*AC18) -> 0.90694752
A19: NECESIDAD ANUAL MP | L19: Linea B - Panificados | X19: Horneado | Y19: =M25 -> 343972.83 | Z19: 45 | AA19: =+$S$2 -> 3824 | AB19: =AA19*Z19 -> 172080 | AC19: =ROUNDUP(Y19/AB19,0) -> 2 | AD19: =Y19/(AB19*AC19) -> 0.99945616
A20: Sección Operativa | B20: Alimentación | C20: Agregado | D20: Desperdicios | H20: Producción | L20: Sección Operativa | M20: Producción (kg/año) | N20: Hs activas/año | O20: Producción (kg/h) | P20: Semielaborado | X20: Envasado | Y20: =M27 -> 319894.73 | Z20: 240 | AA20: =+$S$2 -> 3824 | AB20: =AA20*Z20 -> 917760 | AC20: =ROUNDUP(Y20/AB20,0) -> 1 | AD20: =Y20/(AB20*AC20) -> 0.34856034
D21: Recuperable | F21: No recuperable
A22: Batido | B22: 395371.07 | C22: 0 | E22: 0 | G22: 0 | H22: 395371.07 | I22: kg/año | L22: Batido | M22: 395371.07 | N22: =+$S$2 -> 3824 | O22: =+M22/N22 -> 103.39202 | P22: Batido (masa) | X22: Linea A - Galletitas
A23: Dosificado | B23: 395371.07 | C23: 0 | E23: 0 | G23: 0 | H23: 395371.07 | I23: kg/año | L23: Dosificado | M23: 395371.07 | N23: =+$S$2 -> 3824 | O23: =+M23/N23 -> 103.39202 | P23: Masa | X23: Sección Operativa | Y23: Producción (kg/año) | Z23: Capacidad de la maquina (kg/h) | AA23: Hs activas/año | AB23: Capacidad de la maquina (kg/año) | AC23: Cantidad de maquinas
A24: Fermentado | B24: 395371.07 | C24: 0 | E24: 0 | G24: 0 | H24: 395371.07 | I24: kg/año | L24: Fermentado | M24: 395371.07 | N24: =+$S$2 -> 3824 | O24: =+M24/N24 -> 103.39202 | P24: Panificado en molde
A25: Horneado | B25: 395371.07 | C25: 0 | E25: 0 | F25: 0.13 | G25: 51398.239 | H25: 343972.83 | I25: kg/año | L25: Horneado | M25: 343972.83 | N25: =+$S$2 -> 3824 | O25: =+M25/N25 -> 89.951055 | P25: Panificado en molde | X25: Amasado | Y25: =M5 -> 431449.24 | Z25: 150 | AA25: =+$S$2 -> 3824 | AB25: =AA25*Z25 -> 573600 | AC25: =ROUNDUP(Y25/AB25,0) -> 1 | AD25: =Y25/(AB25*AC25) -> 0.75217789
A26: Enfriado | B26: 343972.83 | C26: 0 | E26: 0 | F26: 0.07 | G26: 24078.098 | H26: 319894.73 | I26: kg/año | L26: Enfriado | M26: 319894.73 | N26: =+$S$2 -> 3824 | O26: =+M26/N26 -> 83.654481 | P26: Panificado en molde | X26: Moldeado | Y26: =M6 -> 422820.25 | Z26: 111 | AA26: =+$S$2 -> 3824 | AB26: =AA26*Z26 -> 424464 | AC26: =ROUNDUP(Y26/AB26,0) -> 1 | AD26: =Y26/(AB26*AC26) -> 0.99612748
A27: Envasado primario | B27: 319894.73 | C27: 0 | E27: 0 | G27: 0 | H27: 319894.73 | I27: kg/año | L27: Envasado | M27: 319894.73 | N27: =+$S$2 -> 3824 | O27: =+M27/N27 -> 83.654481 | P27: Empaque (Cajas) | X27: Horneado | Y27: =M7 -> 393222.84 | Z27: 103 | AA27: =+$S$2 -> 3824 | AB27: =AA27*Z27 -> 393872 | AC27: =ROUNDUP(Y27/AB27,0) -> 1 | AD27: =Y27/(AB27*AC27) -> 0.99835184
A28: TOTALES | B28: 395371.07 | C28: 0 | E28: 0 | G28: 75476.338 | H28: 319894.73 | I28: kg/año | X28: Enfriado | Y28: =M8 -> 373561.69 | Z28: 98 | AA28: =+$S$2 -> 3824 | AB28: =AA28*Z28 -> 374752 | AC28: =ROUNDUP(Y28/AB28,0) -> 1 | AD28: =Y28/(AB28*AC28) -> 0.99682375
X29: Envasado | Y29: =M9 -> 358619.23 | Z29: 270 | AA29: =+$S$2 -> 3824 | AB29: =AA29*Z29 -> 1032480 | AC29: =ROUNDUP(Y29/AB29,0) -> 1 | AD29: =Y29/(AB29*AC29) -> 0.3473377
N31: Budin | O31: =84*0.6 -> 50.4
N32: Pan | O32: =O26-O31 -> 33.254481

Sheet Relaciones - Superficies
A1: DIAGRAMA DE RELACIÓN - SUPERFICIES Y DIMENSIONAMIENTO
A3: Parámetros / supuestos editables
A4: Huella pallet (m²) | B4: 1.2
A5: Factor pasillos almacén | B5: 1.6
A6: Tiempo enfriado galletitas (min) | B6: 4
A7: Carga superficial galletitas (kg/m²) | B7: 3
A8: Tiempo enfriado pan/budín (min) | B8: 60
A9: Carga superficial pan/budín (kg/m²) | B9: 12
A10: Holgura lateral por lado (m) | B10: 0.5
A11: Holgura en extremos por lado (m) | B11: 1
A12: Margen operativo enfriado | B12: 1.2
A13: Participación Pan en P/B | B13: =(Produccion!$E$22*0.4)/((Produccion!$E$22*0.4)+((Produccion!$E$23+Produccion!$E$24)*0.18)) -> 0.56451613
A14: Participación Budín en P/B | B14: =1-B13 -> 0.43548387
A17: Nodo | B17: Sección / área | C17: Línea | D17: Capacidad requerida (kg/h) | E17: Equipo | F17: Cantidad | G17: Ancho base (m) | H17: Largo base (m) | I17: Superficie maquinaria | J17: Lados de operación | K17: Superficie operación | L17: Superficie sección (m²)
A18: 2 | B18: Sección pesado | C18: Común | D18: ='Ritmo y capacidad'!$O$5+'Ritmo y capacidad'!$O$22 -> 216.2187 | E18: Balanza de piso + puesto de micropesado | F18: 1 | G18: 0.43 | H18: 0.51 | I18: =+H18*G18*F18 -> 0.2193 | J18: 3 | K18: =+J18*1 -> 3 | L18: =+K18+I18 -> 3.2193
A19: 3 | B19: Amasado | C19: Común | D19: =+'Ritmo y capacidad'!O5 -> 112.82668 | E19: Amasadora doble Z | F19: 1 | G19: 1.2 | H19: 1.4 | I19: =+H19*G19*F19 -> 1.68 | J19: 3 | K19: =+J19*1 -> 3 | L19: =+K19+I19 -> 4.68
A20: 3 | B20: Batido | C20: Común | D20: =+'Ritmo y capacidad'!O22 -> 103.39202 | E20: Batidora 100 L | F20: 1 | G20: 0.75 | H20: 0.8 | I20: =+H20*G20*F20 -> 0.6 | J20: 3 | K20: =+J20*1 -> 3 | L20: =+K20+I20 -> 3.6
A21: 4 | B21: Formado G | C21: Galletitas | D21: ='Ritmo y capacidad'!$O$6 -> 110.57015 | E21: Máquina rotativa RALEM 600 | F21: 1 | I21: =+H21*G21*F21 -> 0 | J21: 1 | K21: =+J21*1 -> 1 | L21: =+K21+I21 -> 1
A22: 5 | B22: Horno túnel G | C22: Galletitas | D22: ='Ritmo y capacidad'!$O$7 -> 102.83024 | E22: Horno túnel GD-BTOM10 | F22: 1 | G22: 0.6 | H22: 16 | I22: =+H22*G22*F22 -> 9.6 | J22: 2 | K22: =+J22*1 -> 2 | L22: =+K22+I22 -> 11.6
A23: 6 | B23: Enfriado G | C23: Galletitas | D23: ='Ritmo y capacidad'!$O$8 -> 97.688727 | E23: Cinta continua dimensionada por caudal y residencia | F23: 1 | G23: 1 | H23: 40 | I23: =+H23*G23*F23 -> 40 | J23: 3 | K23: =+J23*1 -> 3 | L23: =+K23+I23 -> 43
A24: 7 | B24: Envasado 1° G | C24: Galletitas | D24: ='Ritmo y capacidad'!$O$9 -> 93.781178 | E24: Envasadora vertical + detector de metales | F24: 1 | G24: 0.97 | H24: 3.33 | I24: =+H24*G24*F24 -> 3.2301 | J24: 3 | K24: =+J24*1 -> 3 | L24: =+K24+I24 -> 6.2301
A25: 8 | B25: Envasado 2° G | C25: Galletitas | D25: ='Ritmo y capacidad'!$O$11 | E25: Puesto manual de envasado | F25: 1 | G25: 1.5 | H25: 1 | I25: =+H25*G25*F25 -> 1.5 | J25: - | K25: - | L25: -
A26: 9 | B26: Dosificado | C26: Panificados | D26: =+'Ritmo y capacidad'!O23 -> 103.39202 | E26: Dosificado | F26: 1 | G26: 1.33 | H26: 1 | I26: =+H26*G26*F26 -> 1.33 | J26: 3 | K26: =+J26*1 -> 3 | L26: =+K26+I26 -> 4.33
A27: 10 | B27: Fermentado P/B | C27: Panificados | D27: ='Ritmo y capacidad'!$O$24 -> 103.39202 | E27: Fermentador NKF-36RS | F27: 1 | G27: 0.58 | H27: 0.98 | I27: =+H27*G27*F27 -> 0.5684 | J27: 3 | K27: =+J27*1 -> 3 | L27: =+K27+I27 -> 3.5684
A28: 11 | B28: Horneado P/B | C28: Panificados | D28: ='Ritmo y capacidad'!$O$25 -> 89.951055 | E28: Horno rotativo SIGMA B-7090 | F28: 1 | G28: 1.6 | H28: 1.95 | I28: =+H28*G28*F28 -> 3.12 | J28: 2 | K28: =+J28*1 -> 2 | L28: =+K28+I28 -> 5.12
A29: 12 | B29: Enfriado P/B | C29: Panificados | D29: ='Ritmo y capacidad'!$O$26 -> 83.654481 | E29: Carros de enfriamiento | F29: 2 | G29: 0.4 | H29: 0.6 | I29: =+H29*G29*F29 -> 0.48 | J29: 4 | K29: =+J29*1 -> 4 | L29: =+K29+I29 -> 4.48
A30: 13 | B30: Envasado 1° Pan | C30: Panificados | D30: ='Ritmo y capacidad'!$O$27*$B$13 -> 47.224304 | E30: Envasadora KL-250SZ | F30: 1 | G30: 0.37 | H30: 3.92 | I30: =+H30*G30*F30 -> 1.4504 | J30: 4 | K30: =+J30*1 -> 4 | L30: =+K30+I30 -> 5.4504
A31: 14 | B31: Envasado 1° Budín | C31: Panificados | D31: ='Ritmo y capacidad'!$O$27*$B$14 -> 36.430177 | E31: Envasadora KL-250SZ | F31: 1 | G31: 0.37 | H31: 3.92 | I31: =+H31*G31*F31 -> 1.4504 | J31: 4 | K31: =+J31*1 -> 4 | L31: =+K31+I31 -> 5.4504
A32: 15 | B32: Envasado 2° Pan | C32: Panificados | D32: =#REF!*$B$13 -> #REF! | E32: Puesto manual de encajado | F32: 1 | G32: 1.5 | H32: 1 | I32: =+H32*G32*F32 -> 1.5 | J32: 0 | K32: =+J32*1 -> 0 | L32: =+K32+I32 -> 1.5
A33: Superficie neta requerida | L33: =+#REF!+#REF! -> #REF!
L34: =+SUM(L18:L33) -> #REF!
A35: 15% plus pasillos | L35: =+L34*0.15 -> #REF!
A36: Área total requerida | L36: =+L34+L35 -> #REF!

Sheet Produccion
B1: Año 1/2
D2: Produccion | H2: Personal | J2: Producción por turno y eficiencia | O2: Escala de producción
D3: Producto | E3: Linea | F3: Turnos | G3: Horario | H3: RH/turno | I3: RH | J3: Cajas/turno | K3: kg/caja | M3: kg/turno | N3: kg/h | O3: kg/dia | P3: kg/año | Q3: Tn/año | R3: $/kg | S3: FC ($M)
D4: Pepas | E4: A | F4: 2 | G4: M, T | H4: 9 | I4: =F4*H4 -> 18 | J4: 900 | K4: 2.7 | M4: =J4*K4 -> 2430 | N4: =M4/8 -> 303.75 | O4: =M4*F4 -> 4860 | P4: =O4*24*12 -> 1399680 | Q4: =P4/1000 -> 1399.68 | R4: 10000 | S4: =P4*R4/1000000 -> 13996.8
D5: Polvorones | E5: A | F5: 1 | G5: N | H5: 6 | I5: =F5*H5 -> 6 | J5: 500 | K5: 2.7 | M5: =J5*K5 -> 1350 | N5: =M5/8 -> 168.75 | O5: =M5*F5 -> 1350 | P5: =O5*24*12 -> 388800 | Q5: =P5/1000 -> 388.8 | R5: 10000 | S5: =P5*R5/1000000 -> 3888
D6: Budines | E6: B | F6: 1 | G6: M, T | H6: 8 | I6: =F6*H6 -> 8 | J6: 350 | K6: 3 | M6: =J6*K6 -> 1050 | N6: =M6/8 -> 131.25 | O6: =M6*F6 -> 1050 | P6: =O6*24*12 -> 302400 | Q6: =P6/1000 -> 302.4 | R6: 15000 | S6: =P6*R6/1000000 -> 4536
D7: Total | F7: =AVERAGE(F4:F6) -> 1.3333333 | H7: =SUM(H4:H6) -> 23 | I7: =SUM(I4:I6) -> 32 | J7: =SUM(J4:J6) -> 1750 | K7: =AVERAGE(K4:K6) -> 2.8 | M7: =SUM(M4:M6) -> 4830 | N7: =SUM(N4:N6) -> 603.75 | O7: =SUM(O4:O6) -> 7260 | P7: =SUM(P4:P6) -> 2090880 | Q7: =SUM(Q4:Q6) -> 2090.88 | R7: =SUM(R4:R6) -> 35000 | S7: =SUM(S4:S6) -> 22420.8
D9: Linea A
D10: Linea B | H10: =16+18 -> 34
K11: 2 turnos | L11: 3 turnos
B13: | | C13: COD | D13: Producto | E13: kg/año | F13: Tn/año | G13: $/kg | H13: FC [$MM] | I13: kg/mes | J13: kg/dia | K13: kg/h (2T) | L13: kg/h (3T) | N13: Ventas smams | P13: Factor | R13: % saludable | S13: % no saludable
B14: A | C14: A01 | D14: Chocolate con chips picante 150gr. | E14: 60000 | F14: =E14/1000 -> 60 | G14: 9590 | H14: =E14*G14/1000000 -> 575.4 | I14: =E14/12 -> 5000 | J14: =I14/20 -> 250 | K14: =J14/(8*2) -> 15.625 | L14: =J14/(8*3) -> 10.416667 | N14: 80000 | P14: 0.6 | R14: 0.3 | S14: 0.7
B15: A | C15: A02 | D15: Galletitas símil chocolinas free 150gr. | E15: =P16*R14 -> 7800 | F15: =E15/1000 -> 7.8 | G15: 9102 | H15: =E15*G15/1000000 -> 70.9956 | I15: =E15/12 -> 650 | J15: =I15/20 -> 32.5 | K15: =J15/(8*2) -> 2.03125 | L15: =J15/(8*3) -> 1.3541667 | N15: 46250
B16: A | C16: A03 | D16: Galletitas símil chocolinas 150gr. | E16: =P16*S14 -> 18200 | F16: =E16/1000 -> 18.2 | G16: 8127 | H16: =E16*G16/1000000 -> 147.9114 | I16: =E16/12 -> 1516.6667 | J16: =I16/20 -> 75.833333 | K16: =J16/(8*2) -> 4.7395833 | L16: =J16/(8*3) -> 3.1597222 | N16: 46250 | P16: =26000 -> 26000
B17: A | C17: A04 | D17: Pepas chocolate y batata 150gr. | E17: =56000 -> 56000 | F17: =E17/1000 -> 56 | G17: 7935 | H17: =E17*G17/1000000 -> 444.36 | I17: =E17/12 -> 4666.6667 | J17: =I17/20 -> 233.33333 | K17: =J17/(8*2) -> 14.583333 | L17: =J17/(8*3) -> 9.7222222 | N17: 130000
B18: A | C18: A05 | D18: Bizcochos sabor queso free 150gr. | E18: =P19*R14 -> 7800 | F18: =E18/1000 -> 7.8 | G18: 7989 | H18: =E18*G18/1000000 -> 62.3142 | I18: =E18/12 -> 650 | J18: =I18/20 -> 32.5 | K18: =J18/(8*2) -> 2.03125 | L18: =J18/(8*3) -> 1.3541667 | N18: 26000
B19: A | C19: A06 | D19: Bizcochos sabor queso 150gr. | E19: =P19*S14 -> 18200 | F19: =E19/1000 -> 18.2 | G19: 7989 | H19: =E19*G19/1000000 -> 145.3998 | I19: =E19/12 -> 1516.6667 | J19: =I19/20 -> 75.833333 | K19: =J19/(8*2) -> 4.7395833 | L19: =J19/(8*3) -> 3.1597222 | N19: 26000 | P19: =26000 -> 26000
B20: A | C20: A07 | D20: Polvorones sin azucar150gr. | E20: =P21*R14 -> 13500 | F20: =E20/1000 -> 13.5 | G20: 8948 | H20: =E20*G20/1000000 -> 120.798 | I20: =E20/12 -> 1125 | J20: =I20/20 -> 56.25 | K20: =J20/(8*2) -> 3.515625 | L20: =J20/(8*3) -> 2.34375 | N20: 88000
B21: A | C21: A08 | D21: Polvorones 150gr. | E21: =P21*S14 -> 31500 | F21: =E21/1000 -> 31.5 | G21: 7989 | H21: =E21*G21/1000000 -> 251.6535 | I21: =E21/12 -> 2625 | J21: =I21/20 -> 131.25 | K21: =J21/(8*2) -> 8.203125 | L21: =J21/(8*3) -> 5.46875 | N21: 88000 | P21: =45000 -> 45000
B22: B | C22: B01 | D22: Pan de molde 400gr. | E22: 70000 | F22: =E22/1000 -> 70 | G22: 9000 | H22: =E22*G22/1000000 -> 630 | I22: =E22/12 -> 5833.3333 | J22: =I22/20 -> 291.66667 | K22: =J22/(8*2) -> 18.229167 | L22: =J22/(8*3) -> 12.152778 | N22: 125000
B23: B | C23: B02 | D23: Budines 180gr. | E23: =P23*S14 -> 84000 | F23: =E23/1000 -> 84 | G23: 11296 | H23: =E23*G23/1000000 -> 948.864 | I23: =E23/12 -> 7000 | J23: =I23/20 -> 350 | K23: =J23/(8*2) -> 21.875 | L23: =J23/(8*3) -> 14.583333 | N23: 118000 | P23: =120000 -> 120000
B24: B | C24: B03 | D24: Budines free 180gr. | E24: =P23*R14 -> 36000 | F24: =E24/1000 -> 36 | G24: 11296 | H24: =E24*G24/1000000 -> 406.656 | I24: =E24/12 -> 3000 | J24: =I24/20 -> 150 | K24: =J24/(8*2) -> 9.375 | L24: =J24/(8*3) -> 6.25 | N24: 30000
B25: Total | D25: Total | E25: =SUM(E14:E24) -> 403000 | F25: =SUM(F14:F23) -> 367 | G25: =AVERAGE(G14:G23) -> 8796.5 | H25: =SUM(H14:H23) -> 3397.6965 | I25: =SUM(I14:I23) -> 30583.333 | J25: =AVERAGE(J14:J23) -> 152.91667 | K25: =AVERAGE(K14:K23) -> 9.5572917 | L25: =AVERAGE(L14:L23) -> 6.3715278
E27: 2T | F27: 3T
B28: LINEA A | D28: Capacidad esperada (kg/h) | E28: =SUM(K14:K21) -> 55.46875 | F28: =SUM(L14:L21) -> 36.979167
D29: Capacidad real (kg/h) | E29: =100 -> 100 | F29: =100 -> 100
D30: Aprovechamiento | E30: =E28/E29 -> 0.5546875 | F30: =F28/F29 -> 0.36979167
B32: LINEA B | D32: Capacidad esperada (kg/h) | E32: =SUM(K22:K24) -> 49.479167 | F32: =SUM(L22:L24) -> 32.986111
D33: Capacidad real (kg/h) | E33: 50 | F33: 50
D34: Aprovechamiento | E34: =E32/E33 -> 0.98958333 | F34: =F32/F33 -> 0.65972222
B36: El aprovechamiento debe estar entre 60/90%. Esto se mejora bajando la capacidad de la maquina o aumentando la producción, sin agregar máquinas
B39: Año 10
K40: 2 turnos | L40: 3 turnos
B41: | | C41: COD | D41: Producto | E41: kg/año | F41: Tn/año | G41: $/kg | H41: FC [$MM] | I41: kg/mes | J41: kg/dia | K41: kg/h (2T) | L41: kg/h (3T)
B42: A | C42: A001 | D42: Chocolate con chips picante 150gr. | E42: ='Plan de ventas'!O49*1000 -> 101019.36 | F42: =E42/1000 -> 101.01936 | G42: 9590 | H42: =E42*G42/1000000 -> 968.77564 | I42: =E42/12 -> 8418.2798 | J42: =I42/20 -> 420.91399 | K42: =J42/(8*2) -> 26.307124 | L42: =J42/(8*3) -> 17.538083
B43: A | C43: A002 | D43: Galletitas símil chocolinas free 150gr. | E43: ='Plan de ventas'!O50*1000 -> 13132.517 | F43: =E43/1000 -> 13.132517 | G43: 9102 | H43: =E43*G43/1000000 -> 119.53217 | I43: =E43/12 -> 1094.3764 | J43: =I43/20 -> 54.718819 | K43: =J43/(8*2) -> 3.4199262 | L43: =J43/(8*3) -> 2.2799508
B44: A | C44: A003 | D44: Galletitas símil chocolinas 150gr. | E44: ='Plan de ventas'!O51*1000 -> 30642.707 | F44: =E44/1000 -> 30.642707 | G44: 8127 | H44: =E44*G44/1000000 -> 249.03328 | I44: =E44/12 -> 2553.5589 | J44: =I44/20 -> 127.67795 | K44: =J44/(8*2) -> 7.9798716 | L44: =J44/(8*3) -> 5.3199144
B45: A | C45: A004 | D45: Pepas chocolate y batata 150gr. | E45: ='Plan de ventas'!O52*1000 -> 94284.902 | F45: =E45/1000 -> 94.284902 | G45: 7935 | H45: =E45*G45/1000000 -> 748.1507 | I45: =E45/12 -> 7857.0752 | J45: =I45/20 -> 392.85376 | K45: =J45/(8*2) -> 24.55336 | L45: =J45/(8*3) -> 16.368907
B46: A | C46: A005 | D46: Bizcochos sabor queso free 150gr. | E46: ='Plan de ventas'!O53*1000 -> 13132.517 | F46: =E46/1000 -> 13.132517 | G46: 7989 | H46: =E46*G46/1000000 -> 104.91567 | I46: =E46/12 -> 1094.3764 | J46: =I46/20 -> 54.718819 | K46: =J46/(8*2) -> 3.4199262 | L46: =J46/(8*3) -> 2.2799508
B47: A | C47: A006 | D47: Bizcochos sabor queso 150gr. | E47: ='Plan de ventas'!O54*1000 -> 30642.707 | F47: =E47/1000 -> 30.642707 | G47: 7989 | H47: =E47*G47/1000000 -> 244.80459 | I47: =E47/12 -> 2553.5589 | J47: =I47/20 -> 127.67795 | K47: =J47/(8*2) -> 7.9798716 | L47: =J47/(8*3) -> 5.3199144
B48: A | C48: A007 | D48: Polvorones free 150gr. | E48: ='Plan de ventas'!O55*1000 -> 22729.356 | F48: =E48/1000 -> 22.729356 | G48: 8948 | H48: =E48*G48/1000000 -> 203.38227 | I48: =E48/12 -> 1894.113 | J48: =I48/20 -> 94.705648 | K48: =J48/(8*2) -> 5.919103 | L48: =J48/(8*3) -> 3.9460687
B49: A | C49: A008 | D49: Polvorones 150gr. | E49: ='Plan de ventas'!O56*1000 -> 53035.163 | F49: =E49/1000 -> 53.035163 | G49: 7989 | H49: =E49*G49/1000000 -> 423.69792 | I49: =E49/12 -> 4419.5969 | J49: =I49/20 -> 220.97985 | K49: =J49/(8*2) -> 13.81124 | L49: =J49/(8*3) -> 9.2074936
B50: B | C50: B001 | D50: Pan de molde 400gr. | E50: ='Plan de ventas'!O57*1000 -> 117855.92 | F50: =E50/1000 -> 117.85592 | G50: 9000 | H50: =E50*G50/1000000 -> 1060.7033 | I50: =E50/12 -> 9821.3265 | J50: =I50/20 -> 491.06632 | K50: =J50/(8*2) -> 30.691645 | L50: =J50/(8*3) -> 20.461097
B51: B | C51: B002 | D51: Budines 180gr. | E51: ='Plan de ventas'!O58*1000 -> 141427.2 | F51: =E51/1000 -> 141.4272 | G51: 11296 | H51: =E51*G51/1000000 -> 1597.5617 | I51: =E51/12 -> 11785.6 | J51: =I51/20 -> 589.28001 | K51: =J51/(8*2) -> 36.830001 | L51: =J51/(8*3) -> 24.553334
B52: B | C52: B003 | D52: Budines free 180gr. | E52: ='Plan de ventas'!O59*1000 -> 60611.615 | F52: =E52/1000 -> 60.611615 | G52: 11296 | H52: =E52*G52/1000000 -> 684.6688 | I52: =E52/12 -> 5050.9679 | J52: =I52/20 -> 252.54839 | K52: =J52/(8*2) -> 15.784275 | L52: =J52/(8*3) -> 10.52285
B53: Total | E53: =SUM(E42:E52) -> 678513.96 | F53: =SUM(F42:F51) -> 617.90235 | G53: =AVERAGE(G42:G51) -> 8796.5 | H53: =SUM(H42:H51) -> 5720.5572 | I53: =AVERAGE(I42:I51) -> 5149.1862 | J53: =AVERAGE(J42:J51) -> 257.45931 | K53: =AVERAGE(K42:K51) -> 16.091207 | L53: =AVERAGE(L42:L51) -> 10.727471
E55: 2T | F55: 3T
B56: LINEA A | D56: Capacidad esperada (kg/h) | E56: =SUM(K42:K49) -> 93.390423 | F56: =SUM(L42:L49) -> 62.260282
D57: Capacidad real (kg/h) | E57: =100 -> 100 | F57: =100 -> 100
D58: Aprovechamiento | E58: =E56/E57 -> 0.93390423 | F58: =F56/F57 -> 0.62260282
B60: LINEA B | D60: Capacidad esperada (kg/h) | E60: =SUM(K50:K52) -> 83.30592 | F60: =SUM(L50:L52) -> 55.53728
D61: Capacidad real (kg/h) | E61: 50 | F61: 50
D62: Aprovechamiento | E62: =E60/E61 -> 1.6661184 | F62: =F60/F61 -> 1.1107456

Sheet Inversiones
B2: Activo fijo | Q2: Planta | T2: Activo trabajo
B3: Concepto | C3: ARS [MM] | D3: % | G3: Categoría | H3: Equipo | I3: Cantidad | J3: Precio USD | K3: Precio $ | L3: Total $ | N3: TC | O3: 1360 | Q3: Area | R3: m2 | T3: Concepto | U3: ARS MM | V3: Plazo | W3: AT
B4: Nave industrial | C4: =900000*O3/1000000 -> 1224 | D4: =C4/$C$9 -> 0.68804941 | F4: Rodados y equipos aux | G4: Uso general | H4: Autoelevador | I4: 1 | J4: 15000 | L4: =IF(J4="",I4*K4,I4*J4*$O$3) -> 20400000 | Q4: Producción y oficinas | R4: 680 | T4: Compras MP | U4: =Costos!C5 -> 1067.6694 | V4: 30 | W4: =U4/365*V4 -> 87.753649
B5: Obras complementarias | C5: =R7*0.7*R9/1000000 -> 186.2 | D5: =C5/$C$9 -> 0.10466895 | H5: Zorra | I5: 2 | K5: 450000 | L5: =IF(J5="",I5*K5,I5*J5*$O$3) -> 900000 | Q5: Deposito producto terminado | R5: 450 | T5: Ventas PT | U5: ='Plan de ventas'!F76 -> 3585.9637 | V5: 45 | W5: =U5/365*V5 -> 442.10512
B6: Máquinas operativas | C6: =L35/1000000 -> 336.792 | D6: =C6/$C$9 -> 0.18932152 | H6: Balanza micro pesado | I6: 1 | K6: 200000 | L6: =IF(J6="",I6*K6,I6*J6*$O$3) -> 200000 | Q6: Deposito mp | R6: 200
B7: Rodados y equipos auxiliares | C7: =L8/1000000 -> 22.2 | D7: =C7/$C$9 -> 0.012479328 | H7: Balanza macro pesado | I7: 1 | K7: 700000 | L7: =IF(J7="",I7*K7,I7*J7*$O$3) -> 700000 | Q7: Total | R7: =SUM(R4:R6) -> 1330 | W7: Inversion AT
B8: Muebles y útiles | C8: =L18/1000000 -> 9.75 | D8: =C8/$C$9 -> 0.0054807858 | G8: Total | L8: =SUM(L4:L7) -> 22200000 | W8: =W5-W4 -> 354.35147
B9: Total | C9: =SUM(C4:C8) -> 1778.942 | D9: =SUM(D4:D8) -> 1 | Q9: Costo construcción m2 | R9: =200000 -> 200000
F10: Muebles y utiles | H10: Impresora Injket | I10: 1 | K10: 200000 | L10: =IF(J10="",I10*K10,I10*J10*$O$3) -> 200000
H11: Computadoras | I11: 8 | K11: 500000 | L11: =IF(J11="",I11*K11,I11*J11*$O$3) -> 4000000
H12: Sillas | I12: 15 | K12: 150000 | L12: =IF(J12="",I12*K12,I12*J12*$O$3) -> 2250000
H13: Mesas | I13: 3 | K13: 200000 | L13: =IF(J13="",I13*K13,I13*J13*$O$3) -> 600000
H14: Sanitario (inodoro + lavamano) | I14: 6 | K14: 450000 | L14: =IF(J14="",I14*K14,I14*J14*$O$3) -> 2700000
G18: Total | L18: =SUM(L10:L17) -> 9750000
F20: Maquinas | G20: Línea de Galletitas | H20: Amasadora Industrial | I20: 1 | J20: 13500 | L20: =IF(J20="",I20*K20,I20*J20*$O$3) -> 18360000
H21: Rotativa con dulcera | I21: 1 | J21: 15000 | L21: =IF(J21="",I21*K21,I21*J21*$O$3) -> 20400000
H22: Moldes formadores | I22: 4 | J22: 5000 | L22: =IF(J22="",I22*K22,I22*J22*$O$3) -> 27200000
H23: Horno de Túnel (Continuo) | I23: 1 | J23: 100000 | L23: =IF(J23="",I23*K23,I23*J23*$O$3) -> 136000000
H24: Cinta de Enfriamiento | I24: 1 | J24: 12000 | L24: =IF(J24="",I24*K24,I24*J24*$O$3) -> 16320000
H25: Envasadora | I25: 1 | J25: 4000 | L25: =IF(J25="",I25*K25,I25*J25*$O$3) -> 5440000
G26: Línea de panificados | H26: Batidora Industrial | I26: 1 | K26: 2500000 | L26: =IF(J26="",I26*K26,I26*J26*$O$3) -> 2500000
H27: Dosificadora Volumétrica de Pistones | I27: 1 | K27: 2000000 | L27: =IF(J27="",I27*K27,I27*J27*$O$3) -> 2000000
H28: Carros para horno | I28: 4 | K28: 510000 | L28: =IF(J28="",I28*K28,I28*J28*$O$3) -> 2040000
H29: Horno Rotativo | I29: 2 | K29: 15000000 | L29: =IF(J29="",I29*K29,I29*J29*$O$3) -> 30000000
H30: Fermentadora de pan | I30: 1 | K30: 1900000 | L30: =IF(J30="",I30*K30,I30*J30*$O$3) -> 1900000
H31: Cortadora de pan | I31: 1 | J31: 500 | L31: =IF(J31="",I31*K31,I31*J31*$O$3) -> 680000
H32: Carros de enfriamiento | I32: 4 | K32: 400000 | L32: =IF(J32="",I32*K32,I32*J32*$O$3) -> 1600000
H33: Detector de metales | I33: 1 | J33: 3200 | L33: =IF(J33="",I33*K33,I33*J33*$O$3) -> 4352000
H34: Envasadora | I34: 1 | J34: 50000 | L34: =IF(J34="",I34*K34,I34*J34*$O$3) -> 68000000
G35: Total | L35: =SUM(L20:L34) -> 336792000

Sheet Costos
B2: Resumen costos anuales | F2: Mano de obra | M2: Materia prima
B3: Concepto | C3: ARS [MM] | D3: % | F3: Sector | G3: Posición | H3: Tipo | I3: Cantidad | J3: Sueldo basico [ARS] | K3: Total anual [ARS] | M3: COD | N3: Producto | O3: Costo MP / Kg ($) | P3: Q anual (kg) | Q3: Costo anual ($) | S3: $/kg | T3: Costo/precio
B4: Mano de obra | C4: =$K$14/1000000 -> 1356.5203 | D4: =C4/$C$7 -> 0.39170376 | F4: Producción | G4: Operario | H4: Directo | I4: 37 | J4: 1072000 | K4: =I4*J4*12*1.24 -> 590200320 | M4: A01 | N4: Chocolate con chips picante 150gr. | O4: 1775.67 | P4: =VLOOKUP(M4,Produccion!C:E,3,0) -> 60000 | Q4: =O4*P4 -> 106540200 | S4: =VLOOKUP(M4,Produccion!C:G,5,0) -> 9590 | T4: =O4/S4 -> 0.1851585 | W4: A001 | X4: Chocolate con chips picante | Y4: 1775.67
B5: Materia prima | C5: =Q15/1000000 -> 1067.6694 | D5: =C5/$C$7 -> 0.30829624 | F5: Calidad | G5: Analistas | H5: Indirecto | I5: 3 | J5: 2200000 | K5: =I5*J5*12*1.24 -> 98208000 | M5: A02 | N5: Galletitas símil chocolinas free 150gr. | O5: =1723 -> 1723 | P5: =VLOOKUP(M5,Produccion!C:E,3,0) -> 7800 | Q5: =O5*P5 -> 13439400 | S5: =VLOOKUP(M5,Produccion!C:G,5,0) -> 9102 | T5: =O5/S5 -> 0.18929906 | W5: A002 | X5: Galletitas simil chocolinas | Y5: 1498.67
B6: Otros costos | C6: =SUM(C4:C5)/0.7*0.3 -> 1038.9384 | D6: =C6/$C$7 -> 0.3 | F6: Admin y Finanzas | G6: Analistas | H6: Indirecto | I6: 4 | J6: 2200000 | K6: =I6*J6*12*1.24 -> 130944000 | M6: A03 | N6: Galletitas símil chocolinas 150gr. | O6: 1498.67 | P6: =VLOOKUP(M6,Produccion!C:E,3,0) -> 18200 | Q6: =O6*P6 -> 27275794 | S6: =VLOOKUP(M6,Produccion!C:G,5,0) -> 8127 | T6: =O6/S6 -> 0.1844063 | W6: A003 | X6: Pepas chocolate y batata | Y6: 2404.98
B7: Total | C7: =SUM(C4:C6) -> 3463.1282 | D7: =SUM(D4:D6) -> 1 | F7: Producción | G7: Supervisores | H7: Directo | I7: 2 | J7: 2000000 | K7: =I7*J7*12*1.24 -> 59520000 | M7: A04 | N7: Pepas chocolate y batata 150gr. | O7: 2405 | P7: =VLOOKUP(M7,Produccion!C:E,3,0) -> 56000 | Q7: =O7*P7 -> 134680000 | S7: =VLOOKUP(M7,Produccion!C:G,5,0) -> 7935 | T7: =O7/S7 -> 0.30308759 | W7: A004 | X7: Bizcochos salados | Y7: 974.85
F8: Producción | G8: Jefes | H8: Directo | I8: 4 | J8: 2500000 | K8: =I8*J8*12*1.24 -> 148800000 | M8: A05 | N8: Bizcochos sabor queso free 150gr. | O8: 975 | P8: =VLOOKUP(M8,Produccion!C:E,3,0) -> 7800 | Q8: =O8*P8 -> 7605000 | S8: =VLOOKUP(M8,Produccion!C:G,5,0) -> 7989 | T8: =O8/S8 -> 0.12204281 | W8: A005 | X8: Polvorones | Y8: 1958.97
F9: Admin y Finanzas | G9: Gerente | H9: Indirecto | I9: 1 | J9: 3400000 | K9: =I9*J9*12*1.24 -> 50592000 | M9: A06 | N9: Bizcochos sabor queso 150gr. | O9: 975 | P9: =VLOOKUP(M9,Produccion!C:E,3,0) -> 18200 | Q9: =O9*P9 -> 17745000 | S9: =VLOOKUP(M9,Produccion!C:G,5,0) -> 7989 | T9: =O9/S9 -> 0.12204281 | W9: B001 | X9: Pan de molde | Y9: 3034.2
F10: Calidad | G10: Gerente | H10: Indirecto | I10: 1 | J10: 3400000 | K10: =I10*J10*12*1.24 -> 50592000 | M10: A07 | N10: Polvorones free 150gr. | O10: 2253 | P10: =VLOOKUP(M10,Produccion!C:E,3,0) -> 13500 | Q10: =O10*P10 -> 30415500 | S10: =VLOOKUP(M10,Produccion!C:G,5,0) -> 8948 | T10: =O10/S10 -> 0.25178811 | W10: B002 | X10: Budines | Y10: 3798.74
F11: Producción | G11: Gerente | H11: Directo | I11: 1 | J11: 3400000 | K11: =I11*J11*12*1.24 -> 50592000 | M11: A08 | N11: Polvorones 150gr. | O11: 1959 | P11: =VLOOKUP(M11,Produccion!C:E,3,0) -> 31500 | Q11: =O11*P11 -> 61708500 | S11: =VLOOKUP(M11,Produccion!C:G,5,0) -> 7989 | T11: =O11/S11 -> 0.24521217 | W11: B003 | X11: Budines | Y11: 3798.74
F12: Ventas | G12: Gerente | H12: Indirecto | I12: 1 | J12: 3400000 | K12: =I12*J12*12*1.24 -> 50592000 | M12: B01 | N12: Pan de molde 400gr. | O12: 3034 | P12: =VLOOKUP(M12,Produccion!C:E,3,0) -> 70000 | Q12: =O12*P12 -> 212380000 | S12: =VLOOKUP(M12,Produccion!C:G,5,0) -> 9000 | T12: =O12/S12 -> 0.33711111
F13: Gerencia | G13: CEO | H13: Indirecto | I13: 1 | J13: 8500000 | K13: =I13*J13*12*1.24 -> 126480000 | M13: B02 | N13: Budines 180gr. | O13: 3799 | P13: =VLOOKUP(M13,Produccion!C:E,3,0) -> 84000 | Q13: =O13*P13 -> 319116000 | S13: =VLOOKUP(M13,Produccion!C:G,5,0) -> 11296 | T13: =O13/S13 -> 0.33631374
F14: Total | I14: =SUM(I4:I13) -> 55 | J14: =SUM(J4:J13) -> 32072000 | K14: =SUM(K4:K13) -> 1356520320 | M14: B03 | N14: Budines free 180gr. | O14: 3799 | P14: =VLOOKUP(M14,Produccion!C:E,3,0) -> 36000 | Q14: =O14*P14 -> 136764000 | S14: =VLOOKUP(M14,Produccion!C:G,5,0) -> 11296 | T14: =O14/S14 -> 0.33631374
M15: Total | Q15: =SUM(Q4:Q14) -> 1067669394
F17: Apertura mano de obra
F18: Concepto | G18: ARS [MM] | H18: %
F19: Mano de obra directa | G19: =SUMIF(H4:H13,"Directo",J4:J13) -> 8972000 | H19: =G19/$G$21 -> 0.27974557
F20: Mano de obra indirecta | G20: =SUMIF(H4:H13,"Indirecto",J4:J13) -> 23100000 | H20: =G20/$G$21 -> 0.72025443
F21: Total | G21: =SUM(G19:G20) -> 32072000 | H21: =SUM(H19:H20) -> 1

Sheet Flujo
D1: =IF(E2="x","y","") | E1: =IF(F2="x","y","") | F1: =IF(G2="x","y","") | G1: =IF(H2="x","y","") -> y | H1: =IF(I2="x","y","") | I1: =IF(J2="x","y","") | J1: =IF(K2="x","y","") | K1: =IF(L2="x","y","") | ... M1: =IF(N2="x","y","")
B2: Flujo de fondos [ARS MM] | D2: =IF(AND(D10>0,C10<0),"x","") | E2: =IF(AND(E10>0,D10<0),"x","") | F2: =IF(AND(F10>0,E10<0),"x","") | G2: =IF(AND(G10>0,F10<0),"x","") | H2: =IF(AND(H10>0,G10<0),"x","") -> x | I2: =IF(AND(I10>0,H10<0),"x","") | J2: =IF(AND(J10>0,I10<0),"x","") | K2: =IF(AND(K10>0,J10<0),"x","") | ... M2: =IF(AND(M10>0,L10<0),"x","")
B3: Concepto/Año | C3: 0 | D3: 1 | E3: 2 | F3: 3 | G3: 4 | H3: 5 | I3: 6 | J3: 7 | K3: 8 | L3: 9 | M3: 10 | N3: Total
B4: Ingresos | C4: 0 | D4: ='Plan de ventas'!F76 -> 3585.9637 | E4: ='Plan de ventas'!G76 -> 4098.24 | F4: ='Plan de ventas'!H76 -> 4347.413 | G4: ='Plan de ventas'!I76 -> 4611.7357 | H4: ='Plan de ventas'!J76 -> 4892.1292 | I4: ='Plan de ventas'!K76 -> 5240.4488 | J4: ='Plan de ventas'!L76 -> 5613.5688 | K4: ='Plan de ventas'!M76 -> 6013.2549 | ... M4: ='Plan de ventas'!O76 -> 6900.0262 | N4: =SUM(C4:M4) -> 51744.179
B5: Egresos | C5: =Inversiones!C9 -> 1778.942 | D5: =Costos!$C$7+Inversiones!W8 -> 3817.4796 | E5: =Costos!$C$7 -> 3463.1282 | F5: =Costos!$C$7 -> 3463.1282 | G5: =Costos!$C$7 -> 3463.1282 | H5: =Costos!$C$7 -> 3463.1282 | I5: =Costos!$C$7 -> 3463.1282 | J5: =Costos!$C$7 -> 3463.1282 | K5: =Costos!$C$7 -> 3463.1282 | L5: =Costos!$C$7 -> 3463.1282 | M5: =Costos!$C$7-Inversiones!W8 -> 3108.7767 | N5: =SUM(C5:M5) -> 36410.224
B6: Utilidad | C6: =C4-C5 -> -1778.942 | D6: =D4-D5 -> -231.5159 | E6: =E4-E5 -> 635.11183 | F6: =F4-F5 -> 884.28482 | G6: =G4-G5 -> 1148.6075 | H6: =H4-H5 -> 1429.0011 | I6: =I4-I5 -> 1777.3207 | J6: =J4-J5 -> 2150.4406 | ... M6: =M4-M5 -> 3791.2495 | N6: =SUM(C6:M6) -> 15333.955
B7: Honorarios directorio (5%) | C7: 0 | D7: =D6*5% -> -11.575795 | E7: =E6*5% -> 31.755591 | F7: =F6*5% -> 44.214241 | G7: =G6*5% -> 57.430376 | H7: =H6*5% -> 71.450053 | I7: =I6*5% -> 88.866033 | J7: =J6*5% -> 107.52203 | K7: =K6*5% -> 127.50634 | ... M7: =M6*5% -> 189.56248 | N7: =SUM(C7:M7) -> 855.64486
B8: IIGG (35%) | C8: 0 | D8: =D6*35% -> -81.030565 | E8: =E6*35% -> 222.28914 | F8: =F6*35% -> 309.49969 | G8: =G6*35% -> 402.01263 | H8: =H6*35% -> 500.15037 | I8: =I6*35% -> 622.06223 | J8: =J6*35% -> 752.65422 | K8: =K6*35% -> 892.54435 | ... M8: =M6*35% -> 1326.9373 | N8: =SUM(C8:M8) -> 5989.514
B9: Saldo | C9: =C6-C7-C8 -> -1778.942 | D9: =D6-D7-D8 -> -138.90954 | E9: =E6-E7-E8 -> 381.0671 | F9: =F6-F7-F8 -> 530.57089 | G9: =G6-G7-G8 -> 689.16452 | H9: =H6-H7-H8 -> 857.40063 | I9: =I6-I7-I8 -> 1066.3924 | J9: =J6-J7-J8 -> 1290.2644 | ... M9: =M6-M7-M8 -> 2274.7497 | N9: =SUM(C9:M9) -> 8488.7964
B10: Saldo Acumulado | C10: =C9 -> -1778.942 | D10: =C10+D9 -> -1917.8515 | E10: =D10+E9 -> -1536.7844 | F10: =E10+F9 -> -1006.2136 | G10: =F10+G9 -> -317.04904 | H10: =G10+H9 -> 540.3516 | I10: =H10+I9 -> 1606.744 | J10: =I10+J9 -> 2897.0084 | K10: =J10+K9 -> 4427.0844 | ... N10: =M10+N9 -> 16977.593
B12: Beneficio neto [ARS MM] | C12: =N6-N7-N8 -> 8488.7964
B13: Recupero inversión | C13: =HLOOKUP("x",$D$2:$M$3,2,0) & " años y " & ROUNDUP(-(HLOOKUP("y",$D$1:$M$10,10,0))*365/HLOOKUP("x",$D$2:$M$9,8,0),0) & " días" -> 5 años y 135 días | G13: =HLOOKUP("x",$D$2:$M$3,2,0)+(-(HLOOKUP("y",$D$1:$M$10,10,0))*365/HLOOKUP("x",$D$2:$M$9,8,0))/365 -> 5.3697793
B14: TIR [%] | C14: =IRR(C9:M9) -> 0.30012826
B15: VAN [ARS MM] | C15: {=NPV(F15,C9:M9)} -> 1803.5673 | E15: wacc | F15: 0.15
