Workbook

Sheet Balance Inicial
A1: Balance al 31-07-2017
B2: $
A3: Disponibilidades en M/N | B3: 1200000
A4: Inversiones Transitorias | B4: =+B40 -> 133000 | C4: a
A5: Cuentas por Cobrar | B5: 350000
A6: Intereses a Devengar | B6: =+B103 -> 78000 | C6: d
A7: Cargos Diferidos | B7: =+D55 -> 575000 | C7: b
A8: Terrenos | B8: 800000
A9: Edificios | B9: 1400000
A10: Instalaciones | B10: 1000000
A11: Vehículos y Muebles | B11: 950000
A12: Amortizaciones Acumuladas | B12: =-H118 -> -481175 | C12: e
A13: IVA Crédito Fiscal | B13: 180000
A14: ACTIVO TOTAL | B14: =+SUM(B3:B13) -> 6184825 | C14: =SUM(B3:B13) -> 6184825
A15: Cuentas por Pagar | B15: 670000
A16: Provisiones | B16: =+C65 -> 190000 | C16: c
A17: Préstamos | B17: =+B101 -> 360000 | C17: d
A18: Intereses Documentados | B18: =+B102 -> 94380 | C18: d
A19: Previsión Despidos | B19: 210000
A20: Remuneraciones a Pagar | B20: 700000
A21: Cargas Sociales a Pagar | B21: 390000
A22: Provisión Impuesto a las Ganancias | B22: 70000
A23: IVA Débito Fiscal | B23: 400445
A24: Pasivo Exigible | B24: =+SUM(B15:B23) -> 3084825
A25: Capital Social | B25: 2500000
A26: Reservas | B26: 250000
A27: Utilidades | B27: =+B14-B24-B25-B26 -> 350000 | C27: f
A28: Patrimonio Neto | B28: =+SUM(B25:B27) -> 3100000
A29: PASIVO TOTAL | B29: =+B28+B24 -> 6184825
A33: El 10/7 hizo
A34: =1000*140 -> 140000
A37: =1000*(140-133) -> 7000
A38: El 31/7 hizo | B38: DC
B39: Por lo tanto el saldo de Inversiones Transitorias al 31 de Julio será
B40: =+A34-A37 -> 133000 | C40: o directamente 1.000 x 133
A44: =+A45*1.21 -> 1669800
A45: 1380000
A47: =+A45*0.21 -> 289800
A52: Y cada fin de mes
A53: =+A45/12 -> 115000 | B53: Seguros
A55: Asi hasta Julio (7 meses) | B55: Saldo cargos Diferidos al 31/7 | D55: =+A45-A53*7 -> 575000
A59: En Junio y Julio se hizo
B60: Asesoría Contable
A61: =190000/2 -> 95000
A65: Por lo que el saldo de la cuenta Provisiones es al 31/7 de | C65: =+A61*2 -> 190000
A71: Al tomar el préstamo el 31-1-17 hicimos:
A74: 900000
A77: (900000x0,25/12x10)
A78: =+A74*0.26/12*10 -> 195000
A80: =+A78+A81 -> 235950
A81: =+A78*0.21 -> 40950
A86: Desde el 28-2-2012 se devengan los intereses y se pagan capital e intereses:
A88: =+A78/10 -> 19500 | B88: Intereses Perdidos
A91: =+A74/10 -> 90000
A96: =+A80/10 -> 23595
A100: Como al 31-7 transcurrieron 6 meses de cancelación del crédito y devengamiento de intereses:
A101: Saldo de Préstamos | B101: =+A74-6*A91 -> 360000
A102: Saldo de Intereses Documentados | B102: =+A80-A96*6 -> 94380
A103: Saldo de Intereses a Devengar | B103: =+A78-6*A88 -> 78000
A113: BIEN DE USO | B113: VO | C113: VU | D113: VR | E113: AA 31-12-16 | F113: AM.MES | G113: AM.MESx7 | H113: AA 31-07-17
A114: TERRENOS | B114: =+B8 -> 800000 | C114: - | D114: - | E114: - | F114: - | G114: - | H114: -
A115: EDIFICIOS | B115: =+B9 -> 1400000 | C115: 25 | D115: 530000 | E115: 81000 | F115: =+(B115-D115)/(C115*12) -> 2900 | G115: =+F115*7 -> 20300 | H115: =+E115+G115 -> 101300
A116: INSTALACIONES | B116: =+B10 -> 1000000 | C116: 20 | D116: 610000 | E116: 135000 | F116: =+(B116-D116)/(C116*12) -> 1625 | G116: =+F116*7 -> 11375 | H116: =+E116+G116 -> 146375
A117: VEHICULOS Y MUEBLES | B117: 990000 | C117: 5 | E117: 118000 | F117: =+(B117-D117)/(C117*12) -> 16500 | G117: =+F117*7 -> 115500 | H117: =+E117+G117 -> 233500
B118: =SUM(B114:B117) -> 4190000 | E118: =SUM(E115:E117) -> 334000 | F118: =SUM(F115:F117) -> 21025 | H118: =SUM(H115:H117) -> 481175

Sheet Libro Diario
E1: LIBRO DIARIO
A2: Movimientos | E2: Asientos
I3: DEBE | J3: HABER
C7: =+'Balance Inicial'!B20 -> 700000 | E7: Rem a Pagar (P) | I7: =+C7 -> 700000
E8: CS a Pagar (P) | I8: =+C11 -> 390000
F9: a Disponibilidades (A) | J9: =+I7+I8 -> 1090000
C11: =+'Balance Inicial'!B21 -> 390000
E21: Cuenta por Cobrar (A) | I21: =+C23 -> 1028500
B22: =+B27*0.5*0.9*1.21 -> 925650 | E22: Disponibilidades (A) | I22: =+B22 -> 925650
C23: =+B27*0.5*1.21 -> 1028500 | E23: Descuento Pronto pago (R-) | I23: =+B24 -> 85000
B24: =+B27*0.5*0.1 -> 85000 | E24: IVA Crédito Fiscal (A) | I24: =+C26 -> 17850
C25: =+B27*0.21 -> 357000 | F25: a Ventas (R+) | J25: =+B27 -> 1700000
A26: Dto.P.Pago | C26: =+B24*0.21 -> 17850 | F26: IVA Débito Fiscal (P) | J26: =+C25 -> 357000
B27: 1700000 | I27: =SUM(I21:I26) -> 2057000 | J27: =SUM(J21:J26) -> 2057000
B30: Ventas
A31: A fin de mes devengar 1700000x0,5x0,12/12/30x(31-10) | E31: =+B27/2*(0.12/12)/30*(31-10) -> 5950
B35: 130000 | E35: Plazo Fijo (A) | I35: =+B35 -> 130000
F36: a Disponibilidades (A) | J36: =+I35 -> 130000
E38: Intereses P.Fijo (A) | I38: =+B39 -> 1950
B39: =+B35*0.18/12 -> 1950 | F39: a Int.a Devengar (P) | J39: =+I38 -> 1950
A45: Son 1.000 acciones a 147 que estaban en stock a 133, o sea:
E47: Disponibilidades en M/N (A) | I47: =+C51 -> 147000
B48: =+'Balance Inicial'!B40 -> 133000 | F48: a Inversiones Transitorias (A) | J48: =+B48 -> 133000
F49: Rendimiento Acciones (R+) | J49: =+C53 -> 14000
I50: =+SUM(I47:I49) -> 147000 | J50: =+SUM(J47:J49) -> 147000
C51: =+B48+C53 -> 147000
C53: =+(147-133)*1000 -> 14000
C55: Rendimiento Acciones
A60: Aj.Ej.Ant
B61: =+B65-184000 -> 6000 | E61: Provisiones (P) | I61: =+B65 -> 190000
E62: IVA CF (A) | I62: =+C63 -> 38640
C63: =184000*0.21 -> 38640 | F63: a Disponibilidades (A) | J63: =+C66 -> 222640
F64: Ajuste Ej.Anteriores (R+) | J64: =+B61 -> 6000
B65: =+'Balance Inicial'!B16 -> 190000 | I65: =SUM(I61:I64) -> 228640 | J65: =SUM(J61:J64) -> 228640
C66: =184000*1.21 -> 222640
B74: 70000 | E74: Préstamos al Personal (A) | I74: =+B74 -> 70000
F75: a Disponibilidades (A) | J75: =+B74 -> 70000
E83: Disponibilidades (A) | I83: =+C84 -> 72600
B84: =240000/5*4 -> 192000 | C84: =60000*1.21 -> 72600 | E84: Amortizaciones Acumuladas (P) | I84: =+B84 -> 192000
F85: a Bienes de Uso (A) | J85: =+B89 -> 240000
C86: =60000-(240000-192000) -> 12000 | D86: Resultado | F86: IVA DF (P) | J86: =+C91 -> 12600
D87: Seguro s/Siniestro | F87: Resultado seguro s/Siniestro (R+) | J87: =+C86 -> 12000
I88: =SUM(I83:I87) -> 264600 | J88: =SUM(J83:J87) -> 264600
B89: 240000
C91: =60000*0.21 -> 12600
C100: =+B74/5 -> 14000
B101: =-C100+C102-B104 -> 680200 | E101: Sueldos (R-) | I101: =+C102 -> 780000
C102: 780000 | D102: Sueldos | E102: C.Sociales (R-) | I102: =+C106 -> 468000
F103: a Préstamos al Personal (A) | J103: =+C100 -> 14000
B104: =+(C102)*0.11 -> 85800 | F104: Remuneraciones a Pagar (P) | J104: =+B101 -> 680200
F105: C.Sociales a Pagar (P) | J105: =+B106 -> 553800
B106: =+B104+C106 -> 553800 | C106: =+C102*0.6 -> 468000 | D106: C.Sociales | I106: =SUM(I101:I105) -> 1248000 | J106: =SUM(J100:J105) -> 1248000
C111: =+'Balance Inicial'!$A$53 -> 115000 | E111: Seguros (R-) | I111: =+C111 -> 115000
D112: Seguros | F112: a Cargos Diferidos (A) | J112: =+I111 -> 115000
E117: Préstamo (P) | I117: =+B118 -> 90000
B118: =+'Balance Inicial'!$A$91 -> 90000 | E118: Inereses Documentados (P) | I118: =+B121 -> 23595
F119: a Dsponibilidades (A) | J119: =+I118+I117 -> 113595
B121: =+'Balance Inicial'!$A$96 -> 23595
B126: =+'Balance Inicial'!$A$88 -> 19500 | E126: I.Perdidos (R-) | I126: =+B126 -> 19500
D127: IP | F127: a Intereses a Devengar (A) | J127: =+I126 -> 19500
E131: Intereses por Cobrar (A) | I131: =+C133 -> 7199.5
F132: a Intereses Ganados (R+) | J132: =+B133 -> 5950
A133: IG | B133: =+E31 -> 5950 | C133: =+E31*1.21 -> 7199.5 | F133: IVA DF (P) | J133: =+B136 -> 1249.5
I134: =SUM(I131:I133) -> 7199.5 | J134: =SUM(J131:J133) -> 7199.5
B136: =+B133*0.21 -> 1249.5
E141: Intereses a Devengar (P) | I141: =+B143 -> 910
F142: a Intereses Ganados (R+) | J142: =+I141 -> 910
A143: IG | B143: =+B39/30*(31-17) -> 910
E148: Amort.Ejercicio B.Uso (R-) | I148: =+B149 -> 17025
B149: =+'Balance Inicial'!F118-'Libro Diario'!B89/(5*12) -> 17025 | C149: Am.Ej. | F149: a Am.Acum.B.Uso (P) | J149: =+B149 -> 17025
A153: R+ | B153: =+B143+B133+C86+B61+C53+B27 -> 1738860
A154: R- | B154: =+B149+B126+C111+C106+C102+B24 -> 1484525
C155: =+(B153-B154)*0.3 -> 76300.5
B157: IIGG
A158: CIERRE DEL EJERCICIO
A159: CUENTAS DE EGRESO
A160: Dto.PP | F160: =+B24 -> 85000 | G160: Ganancias y Pérdidas | K160: =+SUM(L161:L167) -> 1560825.5
H161: a Dto.PP (R-) | L161: =+F160 -> 85000
H162: Sueldos (R-) | L162: =+F164 -> 780000
H163: Cs.Soc. (R-) | L163: =+F166 -> 468000
A164: Sueldos | F164: =+C102 -> 780000 | H164: Seguros (R-) | L164: =+F168 -> 115000
H165: Int.Perdidos (R-) | L165: =+F170 -> 19500
A166: CS Soc | F166: =+C106 -> 468000 | H166: Amort.Ej (R-) | L166: =+F172 -> 17025
E167: GyP | H167: IIGG (R-) | L167: =+F174 -> 76300.5
A168: Seguros | F168: =+C111 -> 115000
A170: Int.Perd. | F170: =+B126 -> 19500
A172: Am.Ej | F172: =+B149 -> 17025
A174: IIGG | F174: =+C155 -> 76300.5
A175: CUENTAS DE INGRESO
A176: Ventas | F176: =+B27 -> 1700000 | G176: Ventas (R+) | K176: =+F176 -> 1700000
G177: Rendimiento Acciones (R+) | K177: =+F178 -> 14000
A178: Rend.Acc. | F178: =+C53 -> 14000 | G178: Ajuste de Ejercicios Anteriores (R+) | K178: =+F180 -> 6000
G179: Resultado Seguro s/Siniestros (R+) | K179: =+F182 -> 12000
A180: Aj.Ej.Ant. | E180: GyP | F180: =+B61 -> 6000 | G180: Intereses Ganados (R+) | K180: =+F184 -> 6860
H181: a Ganancias y Pérdidas | L181: =+SUM(K176:K180) -> 1738860
F182: =+C86 -> 12000
A183: Result.Seguro s/Siniestro
F184: =+B133+B143 -> 6860
C185: Int.Ganados
G187: Ganancias y Pérdidas | K187: =+C188 -> 178034.5
...

Sheet Hoja1
A1: Balance al 31-07-2017
B2: $
A3: Disponibilidades en M/N | B3: 1200000
A4: Inversiones Transitorias | B4: =1000*133 -> 133000 | E4: BIEN DE USO | F4: VO | G4: VU | H4: VR | I4: AA 31-12-16 | J4: Am Mens | K4: AA 31-07-17
A5: Cuentas por Cobrar | B5: 350000 | E5: TERRENOS | F5: 800000 | G5: - | H5: - | I5: -
A6: Intereses a Devengar | B6: =900000*0.26/12*4 -> 78000 | E6: EDIFICIOS | F6: 1400000 | G6: 25 | H6: 530000 | I6: 81000 | J6: =(F6-H6)/(G6*12) -> 2900 | K6: =I6+J6*7 -> 101300
A7: Cargos Diferidos | B7: =1380000/12*5 -> 575000 | E7: INSTALACIONES | F7: 1000000 | G7: 20 | H7: 610000 | I7: 135000 | J7: =(F7-H7)/(G7*12) -> 1625 | K7: =I7+J7*7 -> 146375
A8: Terrenos | B8: 800000 | E8: VEHICULOS Y MUEBLES | F8: 990000 | G8: 5 | I8: 118000 | J8: =(F8-H8)/(G8*12) -> 16500 | K8: =I8+J8*7 -> 233500
A9: Edificios | B9: 1400000 | F9: 4190000 | I9: 334000 | J9: =SUM(J6:J8) -> 21025 | K9: =SUM(K6:K8) -> 481175
A10: Instalaciones | B10: 1000000
A11: Vehículos y Muebles | B11: 950000
A12: Amortizaciones Acumuladas | B12: =-K9 -> -481175
A13: IVA Crédito Fiscal | B13: 180000
A14: ACTIVO TOTAL | B14: =+SUM(B3:B13) -> 6184825
A15: Cuentas por Pagar | B15: 670000
A16: Provisiones | B16: =190000 -> 190000
A17: Préstamos | B17: =900000/10*4 -> 360000
A18: Intereses Documentados | B18: =900000*0.26/12*4*1.21 -> 94380
A19: Previsión Despidos | B19: 210000
A20: Remuneraciones a Pagar | B20: 700000
A21: Cargas Sociales a Pagar | B21: 390000
A22: Provisión Impuesto a las Ganancias | B22: 70000
A23: IVA Débito Fiscal | B23: 400445
A24: Pasivo Exigible | B24: =+SUM(B15:B23) -> 3084825
A25: Capital Social | B25: 2500000
A26: Reservas | B26: 250000
A27: Utilidades | B27: =+B14-B24-B25-B26 -> 350000
A28: Patrimonio Neto | B28: =+SUM(B25:B27) -> 3100000
A29: PASIVO TOTAL | B29: =+B28+B24 -> 6184825
A32: =+A20 -> Remuneraciones a Pagar | B32: =+B20 -> 700000
A33: =+A21 -> Cargas Sociales a Pagar | B33: =+B21 -> 390000
A34: Disp | C34: =+B32+B33 -> 1090000
A37: CxC | B37: =C41*0.5*1.21 -> 1028500
A38: Disp | B38: =C41*0.5*0.9*1.21 -> 925650
A39: Dto PP R- | B39: =C41*0.5*0.1 -> 85000
A40: IVA CF | B40: =+B39*0.21 -> 17850
A41: Ventas R+ | C41: 1700000
A42: IVA DF | C42: =C41*0.21 -> 357000
A44: PF | B44: 130000
A45: Disp | C45: =+B44 -> 130000
A47: IxC | B47: =+B44*0.18/12 -> 1950
A48: Int a Dev | C48: =+B47 -> 1950
A50: Disp | B50: =147*1000 -> 147000
A51: =+A4 -> Inversiones Transitorias | C51: =+B4 -> 133000
A52: Ganancia Acciones R+ | C52: =+B50-C51 -> 14000
A54: Provisiones | B54: 190000
A55: Iva CF | B55: =184000*0.21 -> 38640
A56: Aj Ej Ant R+ | C56: 6000
A57: Disp | C57: =184000*1.21 -> 222640
A59: Prest Pers | B59: 70000
A60: Disp | C60: =+B59 -> 70000
A62: Disp | B62: =F64*1.21 -> 72600 | E62: VO | F62: 240000
A63: AA | B63: =F62/5*4 -> 192000 | E63: AA | F63: =+B63 -> 192000 | G63: =+F62-F63 -> 48000
A64: Ut x Vta BU R+ | C64: =-(C65-B63-F64) -> 12000 | E64: Venta | F64: 60000
A65: BU | C65: =+F62 -> 240000
A66: IVA DF | C66: =+F64*0.21 -> 12600
A68: S R- | B68: 780000
A69: CS R- | B69: =+B68*0.6 -> 468000
A70: CSAP | C70: =+B68*0.71 -> 553800
A71: =+A59 -> Prest Pers | C71: =+B59/5 -> 14000
A72: RAP | C72: =+B68*0.89-C71 -> 680200
A74: Seguro Inc R- | B74: =+B7/5 -> 115000
A75: CD | C75: =+B74 -> 115000
A77: =+A17 -> Préstamos | B77: =+B17/4 -> 90000
A78: =+A18 -> Intereses Documentados | B78: =+B18/4 -> 23595
A79: Disp | C79: =+B77+B78 -> 113595
A81: Int Perd R- | B81: =+C82 -> 19500
A82: =+A6 -> Intereses a Devengar | C82: =+B6/4 -> 19500
A84: IxC | B84: =+C85*1.21 -> 7199.5
A85: Int Gan R+ | C85: =1700000*0.5*0.01/30*21 -> 5950
A86: IVA DF | C86: =+C85*0.21 -> 1249.5
A88: =+A48 -> Int a Dev | B88: =+B47/30*14 -> 910
A89: Int Gan R+ | C89: =+B88 -> 910
A91: Amort R- | B91: =+J9-240000/60 -> 17025
A92: AA | C92: =+B91 -> 17025
A94: IIGG R- | B94: =+F97 -> 76300.5 | E94: R+ | F94: =+C41+C52+C56+C64+C85+C89 -> 1738860
A95: Prov IIGG | C95: =+B94 -> 76300.5 | E95: R- | F95: =+B39+B68+B69+B74+B81+B91 -> 1484525
F96: =+F94-F95 -> 254335
E97: IIGG | F97: =+F96*0.3 -> 76300.5
A98: Cieres
A99: GYP | B99: =SUM(C100:C106) -> 1560825.5
A100: =+A39 -> Dto PP R- | C100: =+B39 -> 85000
A101: =+A68 -> S R- | C101: =+B68 -> 780000
A102: =+A69 -> CS R- | C102: =+B69 -> 468000
A103: =+A74 -> Seguro Inc R- | C103: =+B74 -> 115000
A104: =+A81 -> Int Perd R- | C104: =+B81 -> 19500
A105: =+A91 -> Amort R- | C105: =+B91 -> 17025
A106: =+A94 -> IIGG R- | C106: =+B94 -> 76300.5
A108: =+A41 -> Ventas R+ | B108: =+C41 -> 1700000
A109: =+A52 -> Ganancia Acciones R+ | B109: =+C52 -> 14000
A110: =+A56 -> Aj Ej Ant R+ | B110: =+C56 -> 6000
A111: =+A64 -> Ut x Vta BU R+ | B111: =+C64 -> 12000
A112: =+A85 -> Int Gan R+ | B112: =+C85 -> 5950
A113: =+A89 -> Int Gan R+ | B113: =+C89 -> 910
A114: GyP | C114: =SUM(B108:B113) -> 1738860
A116: GYP | B116: =+C117 -> 178034.5
A117: Ut | C117: =+C114-B99 -> 178034.5
